Workbook

Sheet 0. Database
A1: Centralized Database (USD mm except EPS/shares) — Blue = input
A3: Ticker | B3: Metric | C3: 2013A | D3: 2014A | E3: 2015A | F3: 2016A | G3: 2017A | H3: 2018A | I3: 2019A | J3: 2020A | K3: 2021A | L3: 2022A | M3: 2023A | N3: 2024A | O3: 2025E | P3: 2026E | Q3: 2027E | R3: 2028E | S3: 2029E | T3: 2030E
A4: MSFT (FY(Jun))
A5: MSFT | B5: Revenue | C5: 77849 | D5: 86833 | E5: 93580 | F5: 85320 | G5: 96571 | H5: 110360 | I5: 125843 | J5: 143015 | K5: 168088 | L5: 198270 | M5: 211915 | N5: 245122 | O5: 281724 | P5: 329440.24 | Q5: 387103.71 | R5: 463474.17 | S5: 553714.52 | T5: 652772.62
A6: MSFT | B6: Operating Income | C6: 26764 | D6: 27759 | E6: 18161 | F6: 20182 | G6: 29025 | H6: 35058 | I6: 42959 | J6: 52959 | K6: 69916 | L6: 83383 | M6: 88523 | N6: 109433 | O6: 128528 | P6: 153454.1 | Q6: 179274.53 | R6: 217551.82 | S6: 266239.28 | T6: 318436.19
A7: MSFT | B7: Net Income | C7: 21863 | D7: 22074 | E7: 12193 | F7: 16798 | G7: 25489 | H7: 16571 | I7: 39240 | J7: 44281 | K7: 61271 | L7: 72738 | M7: 72361 | N7: 88136 | O7: 101832 | P7: 129372.86 | Q7: 144971.56 | R7: 175683.92 | S7: 215472.22 | T7: 258948.36
A8: MSFT | B8: EPS | C8: 2.63 | D8: 2.66 | E8: 2.59 | F8: 2.79 | G8: 3.29 | H8: 3.88 | I8: 4.75 | J8: 5.76 | K8: 7.97 | L8: 9.21 | M8: 9.81 | N8: 11.8 | O8: 13.91 | P8: 16.75 | Q8: 19.47 | R8: 23.61 | S8: 28.97 | T8: 34.82
A9: MSFT | B9: Diluted Shares (mm) | C9: 8452.25 | D9: 8385.25 | E9: 8254 | F9: 8012.25 | G9: 7831.25 | H9: 7792.25 | I9: 7752 | J9: 7681.5 | K9: 7607.75 | L9: 7540.5 | M9: 7472.25 | N9: 7468.5 | O9: 7467.75 | P9: 7453.97 | Q9: 7446.49 | R9: 7440.67 | S9: 7436.61 | T9: 7436.22
A10: MSFT | B10: SBC | C10: 2406 | D10: 2446 | E10: 2574 | F10: 2668 | G10: 3266 | H10: 3940 | I10: 4652 | J10: 5289 | K10: 6118 | L10: 7502 | M10: 9611 | N10: 10734 | O10: 11974 | P10: 12189 | Q10: 10478.4 | R10: 11434.24 | S10: 12826.56 | T10: 14871.62
A11: MSFT | B11: D&A | C11: 3339 | D11: 4245 | E11: 5400 | F11: 5878 | G11: 7800 | H11: 9900 | I11: 11600 | J11: 12300 | K11: 10900 | L11: 14600 | M11: 13500 | N11: 20000 | O11: 28000 | P11: 39638.96 | Q11: 62441.96 | R11: 94995.43 | S11: 131504.45 | T11: 167239.58
A12: MSFT | B12: Capex | C12: 4257 | D12: 5485 | E12: 5944 | F12: 8932 | G12: 10200 | H12: 13600 | I12: 16900 | J12: 19000 | K12: 24200 | L12: 29200 | M12: 31900 | N12: 55700 | O12: 88200 | P12: 145871.3 | Q12: 245263.45 | R12: 286760.35 | S12: 300210.91 | T12: 304616.04
A13: MSFT | B13: CFO | C13: 28833 | D13: 32231 | E13: 29080 | F13: 33325 | G13: 39507 | H13: 43884 | I13: 52185 | J13: 60675 | K13: 76740 | L13: 89035 | M13: 87582 | N13: 118548 | O13: 136162 | P13: 174558.18 | Q13: 232097.78 | R13: 294570.35 | S13: 359672.36 | T13: 438548.9
A14: MSFT | B14: FCF | C14: 24576 | D14: 26746 | E14: 23136 | F14: 24393 | G14: 29307 | H14: 30284 | I14: 35285 | J14: 41675 | K14: 52540 | L14: 59835 | M14: 55682 | N14: 62848 | O14: 47962 | P14: 28686.88 | Q14: -13165.67 | R14: 7810 | S14: 59461.45 | T14: 133932.86
A15: MSFT | B15: Buybacks | C15: 5360 | D15: 7316 | E15: 14443 | F15: 15969 | G15: 11788 | H15: 10721 | I15: 19543 | J15: 22968 | K15: 27385 | L15: 32696 | M15: 22245 | N15: 17254 | O15: 18420 | P15: 22499.7 | Q15: 19070.28 | R15: 19500.41 | S15: 20126.95 | T15: 21047.23
A16: MSFT | B16: Intell Cloud | C16: 0 | D16: 0 | E16: 0 | F16: 0 | G16: 0 | H16: 0 | I16: 0 | J16: 0 | K16: 0 | L16: 0 | M16: 72314 | N16: 87464 | O16: 106265 | P16: 136688.31 | Q16: 180358.14 | R16: 235873.55 | S16: 304531.45 | T16: 384276.13
... A18: MSFT | B18: Useful Life(yr) | C18: 3.16 | D18: 2.69 | E18: 2.81 | F18: 2.83 | G18: 2.71 | H18: 2.73 | I18: 2.74 | J18: 3.08 | K18: 4.33 | L18: 4.12 | M18: 6.1 | N18: 5.59 | O18: 5.26 | P18: 4.89 | Q18: 4.36 | R18: 4.38 | S18: 4.6 | T18: 4.7
A20: AMZN (CY)
A21: AMZN | B21: Revenue | C21: 74453 | D21: 88988.4 | E21: 107006.6 | F21: 135987 | G21: 177866 | H21: 232887 | I21: 280522 | J21: 386064 | K21: 469822 | L21: 513983 | M21: 574785 | N21: 637959 | O21: 716924 | P21: 827599.51 | Q21: 946630.91 | R21: 1063340.6 | S21: 1183117.7 | T21: 1305415.5
A22: AMZN | B22: Operating Income | C22: 745 | D22: 178.4 | E22: 2232.6 | F22: 4186 | G22: 4107 | H22: 12420 | I22: 14540 | J22: 22899 | K22: 24879 | L22: 12248 | M22: 36852 | N22: 68593 | O22: 79975 | P22: 109001.86 | Q22: 146127.4 | R22: 183469.22 | S22: 223208.87 | T22: 264582.39
A23: AMZN | B23: Net Income | C23: 273 | D23: -240.6 | E23: 596.1 | F23: 2371 | G23: 3033 | H23: 10073 | I23: 11588 | J23: 21331 | K23: 33364 | L23: -2722 | M23: 30425 | N23: 59248 | O23: 77670 | P23: 98333.72 | Q23: 116218.4 | R23: 145016.4 | S23: 177176.2 | T23: 211925.99
A24: AMZN | B24: EPS | C24: 0.03 | D24: -0.03 | E24: 0.06 | F24: 0.24 | G24: 0.31 | H24: 1.01 | I24: 1.15 | J24: 2.08 | K24: 3.25 | L24: -0.26 | M24: 2.88 | N24: 5.53 | O24: 7.17 | P24: 9.02 | Q24: 10.58 | R24: 13.11 | S24: 15.92 | T24: 18.92
A25: AMZN | B25: Diluted Shares (mm) | C25: 9340 | D25: 9440 | E25: 9620 | F25: 9720 | G25: 9910 | H25: 10020 | I25: 10100 | J25: 10254 | K25: 10274.5 | L25: 10296.5 | M25: 10568.69 | N25: 10721 | O25: 10827 | P25: 10907.55 | Q25: 10986.16 | R25: 11059.39 | S25: 11131.13 | T25: 11201.4
A26: AMZN | B26: SBC | C26: -1134 | D26: -1497 | E26: -2120 | F26: -2975 | G26: -4214 | H26: -5418 | I26: -6864 | J26: -9208 | K26: -12757 | L26: -19621 | M26: -24023 | N26: -22077.4 | O26: -19467 | P26: -18863.32 | Q26: -17920.15 | R26: -18816.16 | S26: -19756.97 | T26: -20744.82
A27: AMZN | B27: D&A | C27: 3253 | D27: 4745 | E27: 6281 | F27: 8117 | G27: 11478 | H27: 15341 | I27: 21789 | J27: 25251 | K27: 34296 | L27: 41461 | M27: 48663 | N27: 52795 | O27: 65756 | P27: 81175.82 | Q27: 90716.93 | R27: 120533.23 | S27: 150703.05 | T27: 175451.44
A28: AMZN | B28: Capex | C28: 3443 | D28: 4892 | E28: 4588 | F28: 6736 | G28: 10057 | H28: 11322 | I28: 12690 | J28: 35046 | K28: 55396 | L28: 58321 | M28: 48133 | N28: 77658 | O28: 128320 | P28: 200104.98 | Q28: 270141.72 | R28: 283648.81 | S28: 297831.25 | T28: 312722.81
A29: AMZN | B29: CFO | C29: 5474 | D29: 6841.4 | E29: 11920.1 | F29: 17271 | G29: 18434 | H29: 30724 | I29: 38515 | J29: 66064 | K29: 46327 | L29: 46752 | M29: 84946 | N29: 115877 | O29: 139514 | P29: 181004.31 | Q29: 224443.7 | R29: 281471.71 | S29: 342814.42 | T29: 401080.41
A30: AMZN | B30: FCF | C30: 2031 | D30: 1949.4 | E30: 7332.1 | F30: 10535 | G30: 8377 | H30: 19402 | I30: 25825 | J30: 31018 | K30: -9069 | L30: -11569 | M30: 36813 | N30: 38219 | O30: 11194 | P30: -19100.67 | Q30: -45698.02 | R30: -2177.1 | S30: 44983.17 | T30: 88357.6
A31: AMZN | B31: Buybacks | C31: 0 | D31: 0 | E31: 0 | F31: 0 | G31: 0 | H31: 0 | I31: 0 | J31: 0 | K31: 0 | L31: 6000 | M31: 0 | N31: 0 | O31: 0 | P31: 0 | Q31: 0 | R31: 0 | S31: 0 | T31: 0
A32: AMZN | B32: AWS Rev | C32: 3107.57 | D32: 4644 | E32: 7880 | F32: 12219 | G32: 17458 | H32: 25656 | I32: 35026 | J32: 45370 | K32: 62202 | L32: 80096 | M32: 90757 | N32: 107556 | O32: 128725 | P32: 171284.9 | Q32: 225587.94 | R32: 274421.67 | S32: 323817.58 | T32: 374009.3
A33: AMZN | B33: AWS OI | D33: 458 | E33: 1508 | F33: 3109 | G33: 4331 | H33: 7296 | I33: 9201 | J33: 13531 | K33: 18532 | L33: 22841 | M33: 24631 | N33: 39834 | O33: 45606 | P33: 61254.41 | Q33: 81248.3 | R33: 100888.47 | S33: 121477.03 | T33: 143111.04
A35: GOOGL (CY)
A36: GOOGL | B36: Revenue | C36: 55519 | D36: 66001 | E36: 74989 | F36: 90272 | G36: 110855 | H36: 136819 | I36: 161857 | J36: 182527 | K36: 257637 | L36: 282836 | M36: 307394 | N36: 350018 | O36: 402836 | P36: 488278.6 | Q36: 591935.74 | R36: 701414.49 | S36: 815276.88 | T36: 921874.95
A37: GOOGL | B37: Operating Income | C37: 15403 | D37: 16496 | E37: 19360 | F37: 23716 | G37: 26146 | H37: 26953 | I37: 34231 | J37: 41224 | K37: 78714 | L37: 74842 | M37: 84293 | N37: 112390 | O37: 129039 | P37: 167318.21 | Q37: 210287.33 | R37: 253779.42 | S37: 298519.7 | T37: 338347.07
A38: GOOGL | B38: Net Income | C38: 12720 | D38: 14136 | E38: 16348 | F38: 19478 | G38: 12662 | H38: 30736 | I38: 34343 | J38: 40269 | K38: 76033 | L38: 59972 | M38: 73795 | N38: 100118 | O38: 132170 | P38: 168543.28 | Q38: 174626.97 | R38: 210753.44 | S38: 249488.6 | T38: 285975.76
A39: GOOGL | B39: EPS | C39: 0.94 | D39: 1.03 | E39: 1.18 | F39: 1.39 | G39: 0.9 | H39: 2.19 | I39: 2.46 | J39: 2.93 | K39: 5.61 | L39: 4.56 | M39: 5.8 | N39: 8.04 | O39: 10.81 | P39: 13.73 | Q39: 14.16 | R39: 17.04 | S39: 20.12 | T39: 22.99
A40: GOOGL | B40: Diluted Shares (mm) | C40: 13552.38 | D40: 13741.41 | E40: 13858.6 | F40: 13974.09 | G40: 14071.67 | H40: 14065.69 | I40: 13971.13 | J40: 13740.56 | K40: 13553 | L40: 13159 | M40: 12722 | N40: 12447 | O40: 12230 | P40: 12275.96 | Q40: 12335.53 | R40: 12366.42 | S40: 12399.99 | T40: 12436.85
A41: GOOGL | B41: SBC | C41: -3268 | D41: -4175 | E41: -4903 | F41: -6703 | G41: -7679 | H41: -9353 | I41: -10794 | J41: -12991 | K41: -15376 | L41: -19362 | M41: -22460 | N41: -22785 | O41: -24953 | P41: -27937.33 | Q41: -30032.63 | R41: -31979.73 | S41: -33657.1 | T41: -35339.95
A42: GOOGL | B42: D&A | C42: 2781 | D42: 3523 | E42: 4132 | F42: 5267 | G42: 6103 | H42: 8164 | I42: 10856 | J42: 12905 | K42: 11555 | L42: 15287 | M42: 13326 | N42: 15311 | O42: 21136 | P42: 42874.7 | Q42: 69582.72 | R42: 98340.16 | S42: 127674.93 | T42: 156155.17
A43: GOOGL | B43: Capex | C43: 7358 | D43: 10959 | E43: 9915 | F43: 10183 | G43: 13184 | H43: 25139 | I43: 23548 | J43: 22281 | K43: 24640 | L43: 31485 | M43: 32251 | N43: 52535 | O43: 91447 | P43: 185234.28 | Q43: 259327.99 | R43: 285260.79 | S43: 299523.83 | T43: 314500.02
A44: GOOGL | B44: CFO | C44: 18584 | D44: 22272 | E44: 25829 | F44: 36036 | G44: 37091 | H44: 47971 | I44: 54520 | J44: 65124 | K44: 91652 | L44: 91495 | M44: 101746 | N44: 125299 | O44: 164713 | P44: 211985.47 | Q44: 282346.21 | R44: 352943.8 | S44: 424226.82 | T44: 490867.35
A45: GOOGL | B45: FCF | C45: 11226 | D45: 11313 | E45: 15914 | F45: 25853 | G45: 23907 | H45: 22832 | I45: 30972 | J45: 42843 | K45: 67012 | L45: 60010 | M45: 69495 | N45: 72764 | O45: 73266 | P45: 26751.19 | Q45: 23018.22 | R45: 67683.01 | S45: 124702.99 | T45: 176367.33
A46: GOOGL | B46: Buybacks | C46: 0 | D46: 0 | E46: 1827 | F46: 3693 | G46: 4846 | H46: 9075 | I46: 18396 | J46: 31149 | K46: 50274 | L46: 59296 | M46: 61504 | N46: 62222 | O46: 45709 | P46: 0 | Q46: 20000 | R46: 20000 | S46: 20000 | T46: 15000
A47: GOOGL | B47: Cloud Rev | G47: 4056 | H47: 5838 | I47: 8918 | J47: 13059 | K47: 19206 | L47: 26280 | M47: 33088 | N47: 43229 | O47: 58705 | P47: 99085.93 | Q47: 157303.91 | R47: 220225.47 | S47: 286293.12 | T47: 343551.74
A48: GOOGL | B48: Search Rev | G48: 69811 | H48: 85296 | I48: 98115 | J48: 104062 | K48: 148951 | L48: 162450 | M48: 175033 | N48: 198084 | O48: 224532 | P48: 258723.55 | Q48: 291360.5 | R48: 324483.39 | S48: 358139.29 | T48: 392613.71
A49: GOOGL | B49: YouTube Rev | G49: 8150 | H49: 11115 | I49: 15149 | J49: 19772 | K49: 28845 | L49: 29243 | M49: 31510 | N49: 36147 | O49: 40367 | P49: 43997.73 | Q49: 49277.45 | R49: 54574.78 | S49: 59759.38 | T49: 64838.93
A50: GOOGL | B50: GCloud OI | H50: -4348 | I50: -4645 | J50: -5607 | K50: -2282 | L50: -1922 | M50: 1716 | N50: 6112 | O50: 13910 | P50: 32420.97 | Q50: 57771.82 | R50: 85285.05 | S50: 113733.5 | T50: 138713.29
A52: META (CY)
A53: META | B53: Revenue | C53: 7872 | D53: 12466 | E53: 17927 | F53: 27638 | G53: 40653 | H53: 55838 | I53: 70696.5 | J53: 85966 | K53: 117929 | L53: 116609 | M53: 134901 | N53: 164500 | O53: 200965 | P53: 255175.56 | Q53: 306410.52 | R53: 357336.07 | S53: 407351.97 | T53: 456192.68
A54: META | B54: Operating Income | C54: 2804 | D54: 4994.8 | E54: 6225 | F54: 12427 | G54: 20202 | H54: 24913 | I54: 23985.5 | J54: 32671 | K54: 46753 | L54: 28945 | M54: 46751 | N54: 69380 | O54: 83276 | P54: 90489.79 | Q54: 104437.61 | R54: 118413.08 | S54: 131523.75 | T54: 142814.67
A55: META | B55: Net Income | C55: 1491 | D55: 2924.8 | E55: 3669 | F55: 10187.2 | G55: 15919 | H55: 22112 | I55: 18484.5 | J55: 29145 | K55: 39370 | L55: 23199 | M55: 39097 | N55: 62360 | O55: 60458 | P55: 85782.86 | Q55: 91160.94 | R55: 103452.71 | S55: 115846.5 | T55: 127804.37
A56: META | B56: EPS | C56: 0.59 | D56: 1.1 | E56: 1.28 | F56: 3.48 | G56: 5.39 | H56: 7.66 | I56: 6.44 | J56: 10.08 | K56: 14.07 | L56: 8.79 | M56: 14.87 | N56: 23.99 | O56: 23.49 | P56: 33.28 | Q56: 34.94 | R56: 39.24 | S56: 43.51 | T56: 47.52
A57: META | B57: Diluted Shares (mm) | C57: 2521.75 | D57: 2671 | E57: 2856.75 | F57: 2923.75 | G57: 2954 | H57: 2886 | I57: 2871 | J57: 2890 | K57: 2799 | L57: 2640 | M57: 2630 | N57: 2599 | O57: 2574 | P57: 2577.79 | Q57: 2609.3 | R57: 2636.12 | S57: 2662.83 | T57: 2689.4
A58: META | B58: SBC | C58: -906 | D58: -1837 | E58: -2969 | F58: -3202 | G58: -3723 | H58: -4152 | I58: -4835 | J58: -6536 | K58: -9163 | L58: -11991 | M58: -14027 | N58: -16690 | O58: -20426 | P58: -23722.2 | Q58: -24908.31 | R58: -26153.73 | S58: -27461.41 | T58: -28834.48
A59: META | B59: D&A | C59: 1011 | D59: 1243 | E59: 1945 | F59: 2342 | G59: 3025 | H59: 4315 | I59: 5741 | J59: 6862 | K59: 7966 | L59: 8686 | M59: 11177 | N59: 15498 | O59: 18616 | P59: 35955.99 | Q59: 56602.9 | R59: 78641.85 | S59: 100070.74 | T59: 120937.09
A60: META | B60: Capex | C60: 1362 | D60: 1831 | E60: 2523 | F60: 4491 | G60: 6732 | H60: 13980 | I60: 15102 | J60: 15115 | K60: 18567 | L60: 31186 | M60: 27045 | N60: 37256 | O60: 69691 | P60: 135583.71 | Q60: 165714.44 | R60: 185600.17 | S60: 196736.18 | T60: 208540.35
A61: META | B61: CFO | C61: 4222 | D61: 5507.8 | E61: 8607 | F61: 16061 | G61: 24216 | H61: 29339 | I61: 36312.5 | J61: 38747 | K61: 57683 | L61: 50475 | M61: 71113 | N61: 91328 | O61: 115800 | P61: 180250.64 | Q61: 206102.96 | R61: 243250.01 | S61: 279015.98 | T61: 314478.51
A62: META | B62: FCF | C62: 2860 | D62: 3676.8 | E62: 6084 | F62: 11570 | G62: 17484 | H62: 15359 | I62: 21210.5 | J62: 23632 | K62: 39116 | L62: 19289 | M62: 44068 | N62: 54072 | O62: 46109 | P62: 44666.93 | Q62: 40388.52 | R62: 57649.84 | S62: 82279.8 | T62: 105938.16
A63: META | B63: Buybacks | C63: 0 | D63: 0 | E63: 0 | F63: 0 | G63: 1976 | H63: 12879 | I63: 4201 | J63: 6272 | K63: 44538 | L63: 27956 | M63: 19775 | N63: 30125 | O63: 26248 | P63: 0 | Q63: 6000 | R63: 6000 | S63: 6000 | T63: 6000
A64: META | B64: Ad Rev(META) | C64: 6986 | D64: 11492 | E64: 17080 | F64: 26885 | G64: 39942 | H64: 55012 | I64: 69654.5 | J64: 84169 | K64: 114934 | L64: 113641 | M64: 131948 | N64: 160632 | O64: 196174 | P64: 248664.66 | Q64: 298597.44 | R64: 348271.65 | S64: 397194.59 | T64: 444912.31
A65: META | B65: FOA Rev | I65: 70196 | J65: 84826 | K65: 115655 | L65: 114450 | M65: 133005 | N65: 162354 | O65: 198758 | P65: 252529.81 | Q65: 303235.62 | R65: 353605.56 | S65: 403061.89 | T65: 451366.33
A66: META | B66: FOA OI | I66: 28489 | J66: 39294 | K66: 56947 | L66: 42662 | M66: 62870 | N66: 87109 | O66: 102469 | P66: 109500.79 | Q66: 122498.06 | R66: 135570.51 | S66: 147823.31 | T66: 158299.25
A67: META | B67: RL Rev | I67: 501 | J67: 1139 | K67: 2274 | L67: 2159 | M67: 1896 | N67: 2146 | O67: 2207 | P67: 2645.75 | Q67: 3174.9 | R67: 3730.51 | S67: 4290.08 | T67: 4826.34
A68: META | B68: RL OI | I68: -4503 | J68: -6623 | K68: -10194 | L68: -13717 | M68: -16119 | N68: -17729 | O68: -19193 | P68: -19011 | Q68: -18060.45 | R68: -17157.43 | S68: -16299.56 | T68: -15484.58
A70: ORCL (FY(May))
A71: ORCL | B71: Revenue | C71: 37253 | D71: 38305 | E71: 38253 | F71: 37057 | G71: 37899 | H71: 39431 | I71: 39525 | J71: 39073 | K71: 40481 | L71: 42441 | M71: 49955 | N71: 52961 | O71: 57399 | P71: 67286.75 | Q71: 88782.02 | R71: 125445.05 | S71: 165192.96 | T71: 185555.08
A72: ORCL | B72: Operating Income | C72: 14684 | D72: 14758 | E72: 13870 | F72: 12604 | G72: 12710 | H72: 13264 | I72: 13535 | J72: 13897 | K72: 15214 | L72: 10927 | M72: 13094 | N72: 15354 | O72: 17678 | P72: 19462.44 | Q72: 21128.19 | R72: 36930.86 | S72: 53057.71 | T72: 57952.82
A73: ORCL | B73: Net Income | C73: 10926 | D73: 10955 | E73: 9938 | F73: 8900 | G73: 9334 | H73: 3587 | I73: 11083 | J73: 10135 | K73: 13747 | L73: 6718 | M73: 8504 | N73: 10467 | O73: 12443 | P73: 15820.55 | Q73: 13363.1 | R73: 26776.66 | S73: 39834.82 | T73: 44104.48
A74: ORCL | B74: EPS | C74: 2.26 | D74: 2.38 | E74: 2.21 | F74: 2.07 | G74: 2.21 | H74: 0.85 | I74: 2.97 | J74: 3.08 | K74: 4.55 | L74: 2.41 | M74: 3.07 | N74: 3.71 | O74: 4.34 | P74: 5.43 | Q74: 4.54 | R74: 8.98 | S74: 13.15 | T74: 14.32
A75: ORCL | B75: Diluted Shares (mm) | C75: 4843.75 | D75: 4604.5 | E75: 4502.5 | F75: 4305.5 | G75: 4217 | H75: 4238 | I75: 3732 | J75: 3293.5 | K75: 3022.5 | L75: 2785.5 | M75: 2766.25 | N75: 2823.25 | O75: 2866.25 | P75: 2915.76 | Q75: 2940.66 | R75: 2980.3 | S75: 3028.26 | T75: 3079.57
A76: ORCL | B76: SBC | C76: 755 | D76: 805 | E76: 933 | F76: 1037 | G76: 1350 | H76: 1607 | I76: 1653 | J76: 1590 | K76: 1837 | L76: 2613 | M76: 3547 | N76: 3974 | O76: 4674 | P76: 5069.6 | Q76: 6473.15 | R76: 8609.75 | S76: 10649.61 | T76: 11212.32
A77: ORCL | B77: D&A | C77: 546 | D77: 608 | E77: 712 | F77: 871 | G77: 1000 | H77: 1165 | I77: 1230 | J77: 1382 | K77: 1537 | L77: 1972 | M77: 2526 | N77: 3129 | O77: 3867 | P77: 7501.53 | Q77: 16868.58 | R77: 27597.91 | S77: 39646.31 | T77: 48244.32
A78: ORCL | B78: Capex | C78: 650 | D78: 580 | E78: 1391 | F78: 1189 | G78: 2021 | H78: 1736 | I78: 1660 | J78: 1564 | K78: 2135 | L78: 4511 | M78: 8695 | N78: 6866 | O78: 21215 | P78: 51882 | Q78: 52141.41 | R78: 69869.49 | S78: 81048.61 | T78: 66459.86
A79: ORCL | B79: CFO | C79: 14225 | D79: 14921 | E79: 14336 | F79: 13560 | G79: 14125 | H79: 15386 | I79: 14551 | J79: 13139 | K79: 15888 | L79: 9540 | M79: 17166 | N79: 18673 | O79: 20821 | P79: 25457.17 | Q79: 33694.38 | R79: 50132.95 | S79: 66529.01 | T79: 84964.12
A80: ORCL | B80: FCF | C80: 13575 | D80: 14341 | E80: 12945 | F80: 12371 | G80: 12104 | H80: 13650 | I80: 12891 | J80: 11575 | K80: 13753 | L80: 5029 | M80: 8471 | N80: 11807 | O80: -394 | P80: -26424.83 | Q80: -18447.03 | R80: -19736.54 | S80: -14519.6 | T80: 18504.26
A81: ORCL | B81: Buybacks | C81: 11021 | D81: 9813 | E81: 8087 | F81: 10440 | G81: 3561 | H81: 11347 | I81: 36140 | J81: 19240 | K81: 20934 | L81: 16248 | M81: 1300 | N81: 1202 | O81: 600 | P81: 95 | Q81: 0 | R81: 0 | S81: 0 | T81: 0
A82: ORCL | B82: Cloud Total(ORCL) | C82: 1365 | D82: 1577 | E82: 2094 | F82: 2854 | G82: 4572 | H82: 6189.17 | I82: 6918.19 | J82: 7811.32 | K82: 8945 | L82: 10809 | M82: 15882 | N82: 19775 | O82: 24507 | P82: 34020.24 | Q82: 55591.76 | R82: 92351.27 | S82: 132214.36 | T82: 152708.94
A83: ORCL | B83: IaaS Rev | L83: 2760.74 | M83: 4500 | N83: 6800 | O83: 10234 | P83: 18064.4 | Q83: 37935.24 | R83: 72977.07 | S83: 111105.3 | T83: 129847.66
A84: ORCL | B84: SaaS Rev | L84: 7999.33 | M84: 11400 | N84: 12949 | O84: 14272 | P84: 15955.84 | Q84: 17656.52 | R84: 19374.2 | S84: 21109.07 | T84: 22861.28
A85: ORCL | B85: RPO | I85: 36200 | J85: 37000 | K85: 41300 | L85: 46600 | M85: 67900 | N85: 98000 | O85: 138000
A86: ORCL | B86: OpInc(Adj) | C86: 17612 | D86: 18108 | E86: 17396 | F86: 15785 | G86: 16168 | H86: 17155 | I86: 17384 | J86: 17383 | K86: 19000 | L86: 19592 | M86: 20904 | N86: 23054 | O86: 25034 | P86: 28113.04 | Q86: 28489.16 | R86: 46280.73 | S86: 64368.1 | T86: 69758.92
A87: ORCL | B87: EPS(Adj) | C87: 2.68 | D87: 2.87 | E87: 2.77 | F87: 2.61 | G87: 2.74 | H87: 3.05 | I87: 3.52 | J87: 3.85 | K87: 4.67 | L87: 4.9 | M87: 5.12 | N87: 5.56 | O87: 6.03 | P87: 7.32 | Q87: 6.09 | R87: 10.59 | S87: 14.81 | T87: 15.94

Sheet 1. Summary
B2: AI Capex Cycle: Hyperscaler Deep-Dive (2013-2030)
B3: MSFT | AMZN | GOOGL | META | ORCL + S&P 500 AI EPS Decomposition
B5: SHEETS
B6: 0. Database — 2013-2030 centralized data. Blue=input. All other sheets reference this.
B7: 1. Summary — This page
B8: 2. Revenue — Total rev, YoY%, Cloud/AI proxy. Derived metrics reference SAME sheet cells (black font).
B9: 3. Capex & D&A — Capex, Capex/Rev, D&A, D&A/Rev. Local formulas reference raw data on same sheet.
B10: 4. FCF & Cash — CFO, FCF margin, FCF/NI, Capex/CFO. All ratios use same-sheet references.
B11: 5. EPS & Margins — OpMargin, Net Margin, EPS YoY. Same-sheet referencing pattern.
B12: 6. Burry Sensitivity — GPU life compression on 2026E EPS. Editable tax rate assumptions.
B13: 7. S&P 500 AI EPS Split — AI vs Non-AI EPS decomposition + dual P/E valuation + 4 stress scenarios.
B14: 8. Charts — 6 visualizations (Capex/Rev, FCF Margin, Capex absolute, Rev YoY, OpMargin, D&A/Rev).

Sheet 2. Revenue
A1: Revenue & AI/Cloud Detail (2013-2030E)
A3: A. Total Revenue ($mm)
A4: Company | B4: 2013A | C4: 2014A | D4: 2015A | E4: 2016A | F4: 2017A | G4: 2018A | H4: 2019A | I4: 2020A | J4: 2021A | K4: 2022A | L4: 2023A | M4: 2024A | N4: 2025E | O4: 2026E | P4: 2027E | Q4: 2028E | R4: 2029E | S4: 2030E
A5: MSFT | B5: ='0. Database'!C5 -> 77849 | C5: ='0. Database'!D5 -> 86833 | D5: ='0. Database'!E5 -> 93580 | E5: ='0. Database'!F5 -> 85320 | F5: ='0. Database'!G5 -> 96571 | G5: ='0. Database'!H5 -> 110360 | H5: ='0. Database'!I5 -> 125843 | I5: ='0. Database'!J5 -> 143015 | ... S5: ='0. Database'!T5 -> 652772.62
A6: AMZN | B6: ='0. Database'!C21 -> 74453 | C6: ='0. Database'!D21 -> 88988.4 | D6: ='0. Database'!E21 -> 107006.6 | E6: ='0. Database'!F21 -> 135987 | F6: ='0. Database'!G21 -> 177866 | G6: ='0. Database'!H21 -> 232887 | H6: ='0. Database'!I21 -> 280522 | I6: ='0. Database'!J21 -> 386064 | ... S6: ='0. Database'!T21 -> 1305415.5
A7: GOOGL | B7: ='0. Database'!C36 -> 55519 | C7: ='0. Database'!D36 -> 66001 | D7: ='0. Database'!E36 -> 74989 | E7: ='0. Database'!F36 -> 90272 | F7: ='0. Database'!G36 -> 110855 | G7: ='0. Database'!H36 -> 136819 | H7: ='0. Database'!I36 -> 161857 | I7: ='0. Database'!J36 -> 182527 | ... S7: ='0. Database'!T36 -> 921874.95
A8: META | B8: ='0. Database'!C53 -> 7872 | C8: ='0. Database'!D53 -> 12466 | D8: ='0. Database'!E53 -> 17927 | E8: ='0. Database'!F53 -> 27638 | F8: ='0. Database'!G53 -> 40653 | G8: ='0. Database'!H53 -> 55838 | H8: ='0. Database'!I53 -> 70696.5 | I8: ='0. Database'!J53 -> 85966 | ... S8: ='0. Database'!T53 -> 456192.68
A9: ORCL | B9: ='0. Database'!C71 -> 37253 | C9: ='0. Database'!D71 -> 38305 | D9: ='0. Database'!E71 -> 38253 | E9: ='0. Database'!F71 -> 37057 | F9: ='0. Database'!G71 -> 37899 | G9: ='0. Database'!H71 -> 39431 | H9: ='0. Database'!I71 -> 39525 | I9: ='0. Database'!J71 -> 39073 | ... S9: ='0. Database'!T71 -> 185555.08
A11: C. Cloud / AI Proxy Revenue ($mm)
A12: Company | B12: 2013A | C12: 2014A | D12: 2015A | E12: 2016A | F12: 2017A | G12: 2018A | H12: 2019A | I12: 2020A | J12: 2021A | K12: 2022A | L12: 2023A | M12: 2024A | N12: 2025E | O12: 2026E | P12: 2027E | Q12: 2028E | R12: 2029E | S12: 2030E
A13: MSFT — Azure
A14: AMZN — AWS | B14: ='0. Database'!C32 -> 3107.57 | C14: ='0. Database'!D32 -> 4644 | D14: ='0. Database'!E32 -> 7880 | E14: ='0. Database'!F32 -> 12219 | F14: ='0. Database'!G32 -> 17458 | G14: ='0. Database'!H32 -> 25656 | H14: ='0. Database'!I32 -> 35026 | I14: ='0. Database'!J32 -> 45370 | ... S14: ='0. Database'!T32 -> 374009.3
A15: GOOGL — Cloud | B15: ='0. Database'!C47 -> 0 | C15: ='0. Database'!D47 -> 0 | D15: ='0. Database'!E47 -> 0 | E15: ='0. Database'!F47 -> 0 | F15: ='0. Database'!G47 -> 4056 | G15: ='0. Database'!H47 -> 5838 | H15: ='0. Database'!I47 -> 8918 | I15: ='0. Database'!J47 -> 13059 | ... S15: ='0. Database'!T47 -> 343551.74
A16: META — Advertising | B16: ='0. Database'!C64 -> 6986 | C16: ='0. Database'!D64 -> 11492 | D16: ='0. Database'!E64 -> 17080 | E16: ='0. Database'!F64 -> 26885 | F16: ='0. Database'!G64 -> 39942 | G16: ='0. Database'!H64 -> 55012 | H16: ='0. Database'!I64 -> 69654.5 | I16: ='0. Database'!J64 -> 84169 | ... S16: ='0. Database'!T64 -> 444912.31
A17: ORCL — Cloud Total | B17: ='0. Database'!C82 -> 1365 | C17: ='0. Database'!D82 -> 1577 | D17: ='0. Database'!E82 -> 2094 | E17: ='0. Database'!F82 -> 2854 | F17: ='0. Database'!G82 -> 4572 | G17: ='0. Database'!H82 -> 6189.17 | H17: ='0. Database'!I82 -> 6918.19 | I17: ='0. Database'!J82 -> 7811.32 | ... S17: ='0. Database'!T82 -> 152708.94
A19: B. Revenue YoY %
A20: Company | B20: 2013A | C20: 2014A | D20: 2015A | E20: 2016A | F20: 2017A | G20: 2018A | H20: 2019A | I20: 2020A | J20: 2021A | K20: 2022A | L20: 2023A | M20: 2024A | N20: 2025E | O20: 2026E | P20: 2027E | Q20: 2028E | R20: 2029E | S20: 2030E
A21: MSFT | C21: =IFERROR(C5/B5-1,"") -> 0.1154029 | D21: =IFERROR(D5/C5-1,"") -> 0.077700874 | E21: =IFERROR(E5/D5-1,"") -> -0.088266724 | F21: =IFERROR(F5/E5-1,"") -> 0.13186826 | G21: =IFERROR(G5/F5-1,"") -> 0.14278614 | H21: =IFERROR(H5/G5-1,"") -> 0.1402954 | I21: =IFERROR(I5/H5-1,"") -> 0.13645574 | J21: =IFERROR(J5/I5-1,"") -> 0.17531727 | ... S21: =IFERROR(S5/R5-1,"") -> 0.17889742
A22: AMZN | C22: =IFERROR(C6/B6-1,"") -> 0.19522921 | D22: =IFERROR(D6/C6-1,"") -> 0.20247808 | E22: =IFERROR(E6/D6-1,"") -> 0.27082815 | F22: =IFERROR(F6/E6-1,"") -> 0.30796326 | G22: =IFERROR(G6/F6-1,"") -> 0.30933962 | H22: =IFERROR(H6/G6-1,"") -> 0.20454126 | I22: =IFERROR(I6/H6-1,"") -> 0.37623431 | J22: =IFERROR(J6/I6-1,"") -> 0.21695367 | ... S22: =IFERROR(S6/R6-1,"") -> 0.10336905
A23: GOOGL | C23: =IFERROR(C7/B7-1,"") -> 0.18880023 | D23: =IFERROR(D7/C7-1,"") -> 0.13617975 | E23: =IFERROR(E7/D7-1,"") -> 0.20380322 | F23: =IFERROR(F7/E7-1,"") -> 0.2280109 | G23: =IFERROR(G7/F7-1,"") -> 0.23421587 | H23: =IFERROR(H7/G7-1,"") -> 0.1830009 | I23: =IFERROR(I7/H7-1,"") -> 0.12770532 | J23: =IFERROR(J7/I7-1,"") -> 0.41150076 | ... S23: =IFERROR(S7/R7-1,"") -> 0.13075076
A24: META | C24: =IFERROR(C8/B8-1,"") -> 0.5835874 | D24: =IFERROR(D8/C8-1,"") -> 0.43807155 | E24: =IFERROR(E8/D8-1,"") -> 0.54169688 | F24: =IFERROR(F8/E8-1,"") -> 0.47090962 | G24: =IFERROR(G8/F8-1,"") -> 0.37352717 | H24: =IFERROR(H8/G8-1,"") -> 0.26610015 | I24: =IFERROR(I8/H8-1,"") -> 0.21598665 | J24: =IFERROR(J8/I8-1,"") -> 0.37180979 | ... S24: =IFERROR(S8/R8-1,"") -> 0.11989806
A25: ORCL | C25: =IFERROR(C9/B9-1,"") -> 0.028239336 | D25: =IFERROR(D9/C9-1,"") -> -0.0013575251 | E25: =IFERROR(E9/D9-1,"") -> -0.031265522 | F25: =IFERROR(F9/E9-1,"") -> 0.022721753 | G25: =IFERROR(G9/F9-1,"") -> 0.04042323 | H25: =IFERROR(H9/G9-1,"") -> 0.0023839111 | I25: =IFERROR(I9/H9-1,"") -> -0.0114358 | J25: =IFERROR(J9/I9-1,"") -> 0.036035114 | ... S25: =IFERROR(S9/R9-1,"") -> 0.12326264

Sheet 3. Capex & D&A
A1: Capex & Depreciation (2013-2030E)
A3: A. Capex ($mm)
A4: Company | B4: 2013A | C4: 2014A | D4: 2015A | E4: 2016A | F4: 2017A | G4: 2018A | H4: 2019A | I4: 2020A | J4: 2021A | K4: 2022A | L4: 2023A | M4: 2024A | N4: 2025E | O4: 2026E | P4: 2027E | Q4: 2028E | R4: 2029E | S4: 2030E
A5: MSFT | B5: ='0. Database'!C12 -> 4257 | C5: ='0. Database'!D12 -> 5485 | D5: ='0. Database'!E12 -> 5944 | E5: ='0. Database'!F12 -> 8932 | F5: ='0. Database'!G12 -> 10200 | G5: ='0. Database'!H12 -> 13600 | H5: ='0. Database'!I12 -> 16900 | I5: ='0. Database'!J12 -> 19000 | ... S5: ='0. Database'!T12 -> 304616.04
A6: AMZN | B6: ='0. Database'!C28 -> 3443 | C6: ='0. Database'!D28 -> 4892 | D6: ='0. Database'!E28 -> 4588 | E6: ='0. Database'!F28 -> 6736 | F6: ='0. Database'!G28 -> 10057 | G6: ='0. Database'!H28 -> 11322 | H6: ='0. Database'!I28 -> 12690 | I6: ='0. Database'!J28 -> 35046 | ... S6: ='0. Database'!T28 -> 312722.81
A7: GOOGL | B7: ='0. Database'!C43 -> 7358 | C7: ='0. Database'!D43 -> 10959 | D7: ='0. Database'!E43 -> 9915 | E7: ='0. Database'!F43 -> 10183 | F7: ='0. Database'!G43 -> 13184 | G7: ='0. Database'!H43 -> 25139 | H7: ='0. Database'!I43 -> 23548 | I7: ='0. Database'!J43 -> 22281 | ... S7: ='0. Database'!T43 -> 314500.02
A8: META | B8: ='0. Database'!C60 -> 1362 | C8: ='0. Database'!D60 -> 1831 | D8: ='0. Database'!E60 -> 2523 | E8: ='0. Database'!F60 -> 4491 | F8: ='0. Database'!G60 -> 6732 | G8: ='0. Database'!H60 -> 13980 | H8: ='0. Database'!I60 -> 15102 | I8: ='0. Database'!J60 -> 15115 | ... S8: ='0. Database'!T60 -> 208540.35
A9: ORCL | B9: ='0. Database'!C78 -> 650 | C9: ='0. Database'!D78 -> 580 | D9: ='0. Database'!E78 -> 1391 | E9: ='0. Database'!F78 -> 1189 | F9: ='0. Database'!G78 -> 2021 | G9: ='0. Database'!H78 -> 1736 | H9: ='0. Database'!I78 -> 1660 | I9: ='0. Database'!J78 -> 1564 | ... S9: ='0. Database'!T78 -> 66459.86
A11: D. D&A ($mm)
A12: Company | B12: 2013A | C12: 2014A | D12: 2015A | E12: 2016A | F12: 2017A | G12: 2018A | H12: 2019A | I12: 2020A | J12: 2021A | K12: 2022A | L12: 2023A | M12: 2024A | N12: 2025E | O12: 2026E | P12: 2027E | Q12: 2028E | R12: 2029E | S12: 2030E
A13: MSFT | B13: ='0. Database'!C11 -> 3339 | C13: ='0. Database'!D11 -> 4245 | D13: ='0. Database'!E11 -> 5400 | E13: ='0. Database'!F11 -> 5878 | F13: ='0. Database'!G11 -> 7800 | G13: ='0. Database'!H11 -> 9900 | H13: ='0. Database'!I11 -> 11600 | I13: ='0. Database'!J11 -> 12300 | ... S13: ='0. Database'!T11 -> 167239.58
A14: AMZN | B14: ='0. Database'!C27 -> 3253 | C14: ='0. Database'!D27 -> 4745 | D14: ='0. Database'!E27 -> 6281 | E14: ='0. Database'!F27 -> 8117 | F14: ='0. Database'!G27 -> 11478 | G14: ='0. Database'!H27 -> 15341 | H14: ='0. Database'!I27 -> 21789 | I14: ='0. Database'!J27 -> 25251 | ... S14: ='0. Database'!T27 -> 175451.44
A15: GOOGL | B15: ='0. Database'!C42 -> 2781 | C15: ='0. Database'!D42 -> 3523 | D15: ='0. Database'!E42 -> 4132 | E15: ='0. Database'!F42 -> 5267 | F15: ='0. Database'!G42 -> 6103 | G15: ='0. Database'!H42 -> 8164 | H15: ='0. Database'!I42 -> 10856 | I15: ='0. Database'!J42 -> 12905 | ... S15: ='0. Database'!T42 -> 156155.17
A16: META | B16: ='0. Database'!C59 -> 1011 | C16: ='0. Database'!D59 -> 1243 | D16: ='0. Database'!E59 -> 1945 | E16: ='0. Database'!F59 -> 2342 | F16: ='0. Database'!G59 -> 3025 | G16: ='0. Database'!H59 -> 4315 | H16: ='0. Database'!I59 -> 5741 | I16: ='0. Database'!J59 -> 6862 | ... S16: ='0. Database'!T59 -> 120937.09
A17: ORCL | B17: ='0. Database'!C77 -> 546 | C17: ='0. Database'!D77 -> 608 | D17: ='0. Database'!E77 -> 712 | E17: ='0. Database'!F77 -> 871 | F17: ='0. Database'!G77 -> 1000 | G17: ='0. Database'!H77 -> 1165 | H17: ='0. Database'!I77 -> 1230 | I17: ='0. Database'!J77 -> 1382 | ... S17: ='0. Database'!T77 -> 48244.32
A19: (Revenue — for ratios)
A20: Company | B20: 2013A | C20: 2014A | D20: 2015A | E20: 2016A | F20: 2017A | G20: 2018A | H20: 2019A | I20: 2020A | J20: 2021A | K20: 2022A | L20: 2023A | M20: 2024A | N20: 2025E | O20: 2026E | P20: 2027E | Q20: 2028E | R20: 2029E | S20: 2030E
A21: MSFT | B21: ='0. Database'!C5 -> 77849 | C21: ='0. Database'!D5 -> 86833 | D21: ='0. Database'!E5 -> 93580 | E21: ='0. Database'!F5 -> 85320 | F21: ='0. Database'!G5 -> 96571 | G21: ='0. Database'!H5 -> 110360 | H21: ='0. Database'!I5 -> 125843 | I21: ='0. Database'!J5 -> 143015 | ... S21: ='0. Database'!T5 -> 652772.62
A22: AMZN | B22: ='0. Database'!C21 -> 74453 | C22: ='0. Database'!D21 -> 88988.4 | D22: ='0. Database'!E21 -> 107006.6 | E22: ='0. Database'!F21 -> 135987 | F22: ='0. Database'!G21 -> 177866 | G22: ='0. Database'!H21 -> 232887 | H22: ='0. Database'!I21 -> 280522 | I22: ='0. Database'!J21 -> 386064 | ... S22: ='0. Database'!T21 -> 1305415.5
A23: GOOGL | B23: ='0. Database'!C36 -> 55519 | C23: ='0. Database'!D36 -> 66001 | D23: ='0. Database'!E36 -> 74989 | E23: ='0. Database'!F36 -> 90272 | F23: ='0. Database'!G36 -> 110855 | G23: ='0. Database'!H36 -> 136819 | H23: ='0. Database'!I36 -> 161857 | I23: ='0. Database'!J36 -> 182527 | ... S23: ='0. Database'!T36 -> 921874.95
A24: META | B24: ='0. Database'!C53 -> 7872 | C24: ='0. Database'!D53 -> 12466 | D24: ='0. Database'!E53 -> 17927 | E24: ='0. Database'!F53 -> 27638 | F24: ='0. Database'!G53 -> 40653 | G24: ='0. Database'!H53 -> 55838 | H24: ='0. Database'!I53 -> 70696.5 | I24: ='0. Database'!J53 -> 85966 | ... S24: ='0. Database'!T53 -> 456192.68
A25: ORCL | B25: ='0. Database'!C71 -> 37253 | C25: ='0. Database'!D71 -> 38305 | D25: ='0. Database'!E71 -> 38253 | E25: ='0. Database'!F71 -> 37057 | F25: ='0. Database'!G71 -> 37899 | G25: ='0. Database'!H71 -> 39431 | H25: ='0. Database'!I71 -> 39525 | I25: ='0. Database'!J71 -> 39073 | ... S25: ='0. Database'!T71 -> 185555.08
A27: B. Capex YoY %
A28: Company | B28: 2013A | C28: 2014A | D28: 2015A | E28: 2016A | F28: 2017A | G28: 2018A | H28: 2019A | I28: 2020A | J28: 2021A | K28: 2022A | L28: 2023A | M28: 2024A | N28: 2025E | O28: 2026E | P28: 2027E | Q28: 2028E | R28: 2029E | S28: 2030E
A29: MSFT | C29: =IFERROR(C5/B5-1,"") -> 0.28846606 | D29: =IFERROR(D5/C5-1,"") -> 0.083682771 | E29: =IFERROR(E5/D5-1,"") -> 0.50269179 | F29: =IFERROR(F5/E5-1,"") -> 0.14196149 | G29: =IFERROR(G5/F5-1,"") -> 0.33333333 | H29: =IFERROR(H5/G5-1,"") -> 0.24264706 | I29: =IFERROR(I5/H5-1,"") -> 0.12426036 | J29: =IFERROR(J5/I5-1,"") -> 0.27368421 | ... S29: =IFERROR(S5/R5-1,"") -> 0.014673451
A30: AMZN | C30: =IFERROR(C6/B6-1,"") -> 0.42085391 | D30: =IFERROR(D6/C6-1,"") -> -0.062142273 | E30: =IFERROR(E6/D6-1,"") -> 0.46817786 | F30: =IFERROR(F6/E6-1,"") -> 0.49302257 | G30: =IFERROR(G6/F6-1,"") -> 0.12578304 | H30: =IFERROR(H6/G6-1,"") -> 0.12082671 | I30: =IFERROR(I6/H6-1,"") -> 1.7617021 | J30: =IFERROR(J6/I6-1,"") -> 0.58066541 | ... S30: =IFERROR(S6/R6-1,"") -> 0.049999992
A31: GOOGL | C31: =IFERROR(C7/B7-1,"") -> 0.48939929 | D31: =IFERROR(D7/C7-1,"") -> -0.095264166 | E31: =IFERROR(E7/D7-1,"") -> 0.027029753 | F31: =IFERROR(F7/E7-1,"") -> 0.29470686 | G31: =IFERROR(G7/F7-1,"") -> 0.90678095 | H31: =IFERROR(H7/G7-1,"") -> -0.063288118 | I31: =IFERROR(I7/H7-1,"") -> -0.053804994 | J31: =IFERROR(J7/I7-1,"") -> 0.10587496 | ... S31: =IFERROR(S7/R7-1,"") -> 0.049999995
A32: META | C32: =IFERROR(C8/B8-1,"") -> 0.34434655 | D32: =IFERROR(D8/C8-1,"") -> 0.37793555 | E32: =IFERROR(E8/D8-1,"") -> 0.78002378 | F32: =IFERROR(F8/E8-1,"") -> 0.498998 | G32: =IFERROR(G8/F8-1,"") -> 1.0766488 | H32: =IFERROR(H8/G8-1,"") -> 0.080257511 | I32: =IFERROR(I8/H8-1,"") -> 0.00086081314 | J32: =IFERROR(J8/I8-1,"") -> 0.2283824 | ... S32: =IFERROR(S8/R8-1,"") -> 0.059999996
A33: ORCL | C33: =IFERROR(C9/B9-1,"") -> -0.10769231 | D33: =IFERROR(D9/C9-1,"") -> 1.3982759 | E33: =IFERROR(E9/D9-1,"") -> -0.14521927 | F33: =IFERROR(F9/E9-1,"") -> 0.69974769 | G33: =IFERROR(G9/F9-1,"") -> -0.1410193 | H33: =IFERROR(H9/G9-1,"") -> -0.043778802 | I33: =IFERROR(I9/H9-1,"") -> -0.057831325 | J33: =IFERROR(J9/I9-1,"") -> 0.36508951 | ... S33: =IFERROR(S9/R9-1,"") -> -0.18
A35: C. Capex / Revenue %
A36: Company | B36: 2013A | C36: 2014A | D36: 2015A | E36: 2016A | F36: 2017A | G36: 2018A | H36: 2019A | I36: 2020A | J36: 2021A | K36: 2022A | L36: 2023A | M36: 2024A | N36: 2025E | O36: 2026E | P36: 2027E | Q36: 2028E | R36: 2029E | S36: 2030E
A37: MSFT | B37: =IFERROR(B5/B21,"") -> 0.054682783 | C37: =IFERROR(C5/C21,"") -> 0.063167229 | D37: =IFERROR(D5/D21,"") -> 0.063517846 | E37: =IFERROR(E5/E21,"") -> 0.10468823 | F37: =IFERROR(F5/F21,"") -> 0.10562177 | G37: =IFERROR(G5/G21,"") -> 0.12323306 | H37: =IFERROR(H5/H21,"") -> 0.13429432 | I37: =IFERROR(I5/I21,"") -> 0.1328532 | ... S37: =IFERROR(S5/S21,"") -> 0.46664954
A38: AMZN | B38: =IFERROR(B6/B22,"") -> 0.046243939 | C38: =IFERROR(C6/C22,"") -> 0.054973457 | D38: =IFERROR(D6/D22,"") -> 0.04287586 | E38: =IFERROR(E6/E22,"") -> 0.049534147 | F38: =IFERROR(F6/F22,"") -> 0.056542566 | G38: =IFERROR(G6/G22,"") -> 0.048615852 | H38: =IFERROR(H6/H22,"") -> 0.045237094 | I38: =IFERROR(I6/I22,"") -> 0.090777695 | ... S38: =IFERROR(S6/S22,"") -> 0.23955807
A39: GOOGL | B39: =IFERROR(B7/B23,"") -> 0.13253121 | C39: =IFERROR(C7/C23,"") -> 0.16604294 | D39: =IFERROR(D7/D23,"") -> 0.13221939 | E39: =IFERROR(E7/E23,"") -> 0.11280353 | F39: =IFERROR(F7/F23,"") -> 0.11893013 | G39: =IFERROR(G7/G23,"") -> 0.1837391 | H39: =IFERROR(H7/H23,"") -> 0.14548645 | I39: =IFERROR(I7/I23,"") -> 0.12206961 | ... S39: =IFERROR(S7/S23,"") -> 0.34115258
A40: META | B40: =IFERROR(B8/B24,"") -> 0.17301829 | C40: =IFERROR(C8/C24,"") -> 0.14687951 | D40: =IFERROR(D8/D24,"") -> 0.14073744 | E40: =IFERROR(E8/E24,"") -> 0.16249367 | F40: =IFERROR(F8/F24,"") -> 0.16559663 | G40: =IFERROR(G8/G24,"") -> 0.25036713 | H40: =IFERROR(H8/H24,"") -> 0.21361736 | I40: =IFERROR(I8/I24,"") -> 0.17582533 | ... S40: =IFERROR(S8/S24,"") -> 0.45713217
A41: ORCL | B41: =IFERROR(B9/B25,"") -> 0.017448259 | C41: =IFERROR(C9/C25,"") -> 0.015141626 | D41: =IFERROR(D9/D25,"") -> 0.036363161 | E41: =IFERROR(E9/E25,"") -> 0.032085706 | F41: =IFERROR(F9/F25,"") -> 0.053325945 | G41: =IFERROR(G9/G25,"") -> 0.044026274 | H41: =IFERROR(H9/H25,"") -> 0.041998735 | I41: =IFERROR(I9/I25,"") -> 0.040027641 | ... S41: =IFERROR(S9/S25,"") -> 0.35816783
A43: E. D&A / Revenue %
A44: Company | B44: 2013A | C44: 2014A | D44: 2015A | E44: 2016A | F44: 2017A | G44: 2018A | H44: 2019A | I44: 2020A | J44: 2021A | K44: 2022A | L44: 2023A | M44: 2024A | N44: 2025E | O44: 2026E | P44: 2027E | Q44: 2028E | R44: 2029E | S44: 2030E
A45: MSFT | B45: =IFERROR(B13/B21,"") -> 0.042890724 | C45: =IFERROR(C13/C21,"") -> 0.048886944 | D45: =IFERROR(D13/D21,"") -> 0.057704638 | E45: =IFERROR(E13/E21,"") -> 0.068893577 | F45: =IFERROR(F13/F21,"") -> 0.080769589 | G45: =IFERROR(G13/G21,"") -> 0.089706415 | H45: =IFERROR(H13/H21,"") -> 0.092178349 | I45: =IFERROR(I13/I21,"") -> 0.086004965 | ... S45: =IFERROR(S13/S21,"") -> 0.25619883
A46: AMZN | B46: =IFERROR(B14/B22,"") -> 0.043691994 | C46: =IFERROR(C14/C22,"") -> 0.053321557 | D46: =IFERROR(D14/D22,"") -> 0.058697314 | E46: =IFERROR(E14/E22,"") -> 0.059689529 | F46: =IFERROR(F14/F22,"") -> 0.064531726 | G46: =IFERROR(G14/G22,"") -> 0.065873149 | H46: =IFERROR(H14/H22,"") -> 0.077673052 | I46: =IFERROR(I14/I22,"") -> 0.065406254 | ... S46: =IFERROR(S14/S22,"") -> 0.13440276
A47: GOOGL | B47: =IFERROR(B15/B23,"") -> 0.05009096 | C47: =IFERROR(C15/C23,"") -> 0.053377979 | D47: =IFERROR(D15/D23,"") -> 0.055101415 | E47: =IFERROR(E15/E23,"") -> 0.058345888 | F47: =IFERROR(F15/F23,"") -> 0.055053899 | G47: =IFERROR(G15/G23,"") -> 0.059670075 | H47: =IFERROR(H15/H23,"") -> 0.067071551 | I47: =IFERROR(I15/I23,"") -> 0.070701869 | ... S47: =IFERROR(S15/S23,"") -> 0.16938867
A48: META | B48: =IFERROR(B16/B24,"") -> 0.12842988 | C48: =IFERROR(C16/C24,"") -> 0.099711215 | D48: =IFERROR(D16/D24,"") -> 0.10849557 | E48: =IFERROR(E16/E24,"") -> 0.084738404 | F48: =IFERROR(F16/F24,"") -> 0.074410253 | G48: =IFERROR(G16/G24,"") -> 0.077277123 | H48: =IFERROR(H16/H24,"") -> 0.081206283 | I48: =IFERROR(I16/I24,"") -> 0.079822255 | ... S48: =IFERROR(S16/S24,"") -> 0.2651009
A49: ORCL | B49: =IFERROR(B17/B25,"") -> 0.014656538 | C49: =IFERROR(C17/C25,"") -> 0.015872601 | D49: =IFERROR(D17/D25,"") -> 0.018612919 | E49: =IFERROR(E17/E25,"") -> 0.023504331 | F49: =IFERROR(F17/F25,"") -> 0.02638592 | G49: =IFERROR(G17/G25,"") -> 0.029545282 | H49: =IFERROR(H17/H25,"") -> 0.031119545 | I49: =IFERROR(I17/I25,"") -> 0.035369693 | ... S49: =IFERROR(S17/S25,"") -> 0.26
A51: F. D&A YoY %
A52: Company | B52: 2013A | C52: 2014A | D52: 2015A | E52: 2016A | F52: 2017A | G52: 2018A | H52: 2019A | I52: 2020A | J52: 2021A | K52: 2022A | L52: 2023A | M52: 2024A | N52: 2025E | O52: 2026E | P52: 2027E | Q52: 2028E | R52: 2029E | S52: 2030E
A53: MSFT | C53: =IFERROR(C13/B13-1,"") -> 0.27133872 | D53: =IFERROR(D13/C13-1,"") -> 0.27208481 | E53: =IFERROR(E13/D13-1,"") -> 0.088518519 | F53: =IFERROR(F13/E13-1,"") -> 0.32698197 | G53: =IFERROR(G13/F13-1,"") -> 0.26923077 | H53: =IFERROR(H13/G13-1,"") -> 0.17171717 | I53: =IFERROR(I13/H13-1,"") -> 0.060344828 | J53: =IFERROR(J13/I13-1,"") -> -0.11382114 | ... S53: =IFERROR(S13/R13-1,"") -> 0.27174084
A54: AMZN | C54: =IFERROR(C14/B14-1,"") -> 0.45865355 | D54: =IFERROR(D14/C14-1,"") -> 0.32370917 | E54: =IFERROR(E14/D14-1,"") -> 0.29231014 | F54: =IFERROR(F14/E14-1,"") -> 0.41406924 | G54: =IFERROR(G14/F14-1,"") -> 0.33655689 | H54: =IFERROR(H14/G14-1,"") -> 0.42031158 | I54: =IFERROR(I14/H14-1,"") -> 0.15888751 | J54: =IFERROR(J14/I14-1,"") -> 0.35820364 | ... S54: =IFERROR(S14/R14-1,"") -> 0.16421957
A55: GOOGL | C55: =IFERROR(C15/B15-1,"") -> 0.2668105 | D55: =IFERROR(D15/C15-1,"") -> 0.17286404 | E55: =IFERROR(E15/D15-1,"") -> 0.27468538 | F55: =IFERROR(F15/E15-1,"") -> 0.15872413 | G55: =IFERROR(G15/F15-1,"") -> 0.33770277 | H55: =IFERROR(H15/G15-1,"") -> 0.32974032 | I55: =IFERROR(I15/H15-1,"") -> 0.18874355 | J55: =IFERROR(J15/I15-1,"") -> -0.10461062 | ... S55: =IFERROR(S15/R15-1,"") -> 0.22306838
A56: META | C56: =IFERROR(C16/B16-1,"") -> 0.22947577 | D56: =IFERROR(D16/C16-1,"") -> 0.56476267 | E56: =IFERROR(E16/D16-1,"") -> 0.20411311 | F56: =IFERROR(F16/E16-1,"") -> 0.29163108 | G56: =IFERROR(G16/F16-1,"") -> 0.42644628 | H56: =IFERROR(H16/G16-1,"") -> 0.33047509 | I56: =IFERROR(I16/H16-1,"") -> 0.19526215 | J56: =IFERROR(J16/I16-1,"") -> 0.16088604 | ... S56: =IFERROR(S16/R16-1,"") -> 0.208516
A57: ORCL | C57: =IFERROR(C17/B17-1,"") -> 0.11355311 | D57: =IFERROR(D17/C17-1,"") -> 0.17105263 | E57: =IFERROR(E17/D17-1,"") -> 0.22331461 | F57: =IFERROR(F17/E17-1,"") -> 0.14810563 | G57: =IFERROR(G17/F17-1,"") -> 0.165 | H57: =IFERROR(H17/G17-1,"") -> 0.055793991 | I57: =IFERROR(I17/H17-1,"") -> 0.12357724 | J57: =IFERROR(J17/I17-1,"") -> 0.1121563 | ... S57: =IFERROR(S17/R17-1,"") -> 0.21686785

Sheet 4. FCF & Cash
A1: FCF & Cash Quality (2013-2030E)
A3: A. CFO ($mm)
A4: Company | B4: 2013A | C4: 2014A | D4: 2015A | E4: 2016A | F4: 2017A | G4: 2018A | H4: 2019A | I4: 2020A | J4: 2021A | K4: 2022A | L4: 2023A | M4: 2024A | N4: 2025E | O4: 2026E | P4: 2027E | Q4: 2028E | R4: 2029E | S4: 2030E
A5: MSFT | B5: ='0. Database'!C13 -> 28833 | C5: ='0. Database'!D13 -> 32231 | D5: ='0. Database'!E13 -> 29080 | E5: ='0. Database'!F13 -> 33325 | F5: ='0. Database'!G13 -> 39507 | G5: ='0. Database'!H13 -> 43884 | H5: ='0. Database'!I13 -> 52185 | I5: ='0. Database'!J13 -> 60675 | ... S5: ='0. Database'!T13 -> 438548.9
A6: AMZN | B6: ='0. Database'!C29 -> 5474 | C6: ='0. Database'!D29 -> 6841.4 | D6: ='0. Database'!E29 -> 11920.1 | E6: ='0. Database'!F29 -> 17271 | F6: ='0. Database'!G29 -> 18434 | G6: ='0. Database'!H29 -> 30724 | H6: ='0. Database'!I29 -> 38515 | I6: ='0. Database'!J29 -> 66064 | ... S6: ='0. Database'!T29 -> 401080.41
A7: GOOGL | B7: ='0. Database'!C44 -> 18584 | C7: ='0. Database'!D44 -> 22272 | D7: ='0. Database'!E44 -> 25829 | E7: ='0. Database'!F44 -> 36036 | F7: ='0. Database'!G44 -> 37091 | G7: ='0. Database'!H44 -> 47971 | H7: ='0. Database'!I44 -> 54520 | I7: ='0. Database'!J44 -> 65124 | ... S7: ='0. Database'!T44 -> 490867.35
A8: META | B8: ='0. Database'!C61 -> 4222 | C8: ='0. Database'!D61 -> 5507.8 | D8: ='0. Database'!E61 -> 8607 | E8: ='0. Database'!F61 -> 16061 | F8: ='0. Database'!G61 -> 24216 | G8: ='0. Database'!H61 -> 29339 | H8: ='0. Database'!I61 -> 36312.5 | I8: ='0. Database'!J61 -> 38747 | ... S8: ='0. Database'!T61 -> 314478.51
A9: ORCL | B9: ='0. Database'!C79 -> 14225 | C9: ='0. Database'!D79 -> 14921 | D9: ='0. Database'!E79 -> 14336 | E9: ='0. Database'!F79 -> 13560 | F9: ='0. Database'!G79 -> 14125 | G9: ='0. Database'!H79 -> 15386 | H9: ='0. Database'!I79 -> 14551 | I9: ='0. Database'!J79 -> 13139 | ... S9: ='0. Database'!T79 -> 84964.12
A11: B. FCF ($mm)
A12: Company | B12: 2013A | C12: 2014A | D12: 2015A | E12: 2016A | F12: 2017A | G12: 2018A | H12: 2019A | I12: 2020A | J12: 2021A | K12: 2022A | L12: 2023A | M12: 2024A | N12: 2025E | O12: 2026E | P12: 2027E | Q12: 2028E | R12: 2029E | S12: 2030E
A13: MSFT | B13: ='0. Database'!C14 -> 24576 | C13: ='0. Database'!D14 -> 26746 | D13: ='0. Database'!E14 -> 23136 | E13: ='0. Database'!F14 -> 24393 | F13: ='0. Database'!G14 -> 29307 | G13: ='0. Database'!H14 -> 30284 | H13: ='0. Database'!I14 -> 35285 | I13: ='0. Database'!J14 -> 41675 | ... S13: ='0. Database'!T14 -> 133932.86
A14: AMZN | B14: ='0. Database'!C30 -> 2031 | C14: ='0. Database'!D30 -> 1949.4 | D14: ='0. Database'!E30 -> 7332.1 | E14: ='0. Database'!F30 -> 10535 | F14: ='0. Database'!G30 -> 8377 | G14: ='0. Database'!H30 -> 19402 | H14: ='0. Database'!I30 -> 25825 | I14: ='0. Database'!J30 -> 31018 | ... S14: ='0. Database'!T30 -> 88357.6
A15: GOOGL | B15: ='0. Database'!C45 -> 11226 | C15: ='0. Database'!D45 -> 11313 | D15: ='0. Database'!E45 -> 15914 | E15: ='0. Database'!F45 -> 25853 | F15: ='0. Database'!G45 -> 23907 | G15: ='0. Database'!H45 -> 22832 | H15: ='0. Database'!I45 -> 30972 | I15: ='0. Database'!J45 -> 42843 | ... S15: ='0. Database'!T45 -> 176367.33
A16: META | B16: ='0. Database'!C62 -> 2860 | C16: ='0. Database'!D62 -> 3676.8 | D16: ='0. Database'!E62 -> 6084 | E16: ='0. Database'!F62 -> 11570 | F16: ='0. Database'!G62 -> 17484 | G16: ='0. Database'!H62 -> 15359 | H16: ='0. Database'!I62 -> 21210.5 | I16: ='0. Database'!J62 -> 23632 | ... S16: ='0. Database'!T62 -> 105938.16
A17: ORCL | B17: ='0. Database'!C80 -> 13575 | C17: ='0. Database'!D80 -> 14341 | D17: ='0. Database'!E80 -> 12945 | E17: ='0. Database'!F80 -> 12371 | F17: ='0. Database'!G80 -> 12104 | G17: ='0. Database'!H80 -> 13650 | H17: ='0. Database'!I80 -> 12891 | I17: ='0. Database'!J80 -> 11575 | ... S17: ='0. Database'!T80 -> 18504.26
A19: E. Buybacks ($mm)
A20: Company | B20: 2013A | C20: 2014A | D20: 2015A | E20: 2016A | F20: 2017A | G20: 2018A | H20: 2019A | I20: 2020A | J20: 2021A | K20: 2022A | L20: 2023A | M20: 2024A | N20: 2025E | O20: 2026E | P20: 2027E | Q20: 2028E | R20: 2029E | S20: 2030E
A21: MSFT | B21: ='0. Database'!C15 -> 5360 | C21: ='0. Database'!D15 -> 7316 | D21: ='0. Database'!E15 -> 14443 | E21: ='0. Database'!F15 -> 15969 | F21: ='0. Database'!G15 -> 11788 | G21: ='0. Database'!H15 -> 10721 | H21: ='0. Database'!I15 -> 19543 | I21: ='0. Database'!J15 -> 22968 | ... S21: ='0. Database'!T15 -> 21047.23
A22: AMZN | B22: ='0. Database'!C31 -> 0 | C22: ='0. Database'!D31 -> 0 | D22: ='0. Database'!E31 -> 0 | E22: ='0. Database'!F31 -> 0 | F22: ='0. Database'!G31 -> 0 | G22: ='0. Database'!H31 -> 0 | H22: ='0. Database'!I31 -> 0 | I22: ='0. Database'!J31 -> 0 | ... S22: ='0. Database'!T31 -> 0
A23: GOOGL | B23: ='0. Database'!C46 -> 0 | C23: ='0. Database'!D46 -> 0 | D23: ='0. Database'!E46 -> 1827 | E23: ='0. Database'!F46 -> 3693 | F23: ='0. Database'!G46 -> 4846 | G23: ='0. Database'!H46 -> 9075 | H23: ='0. Database'!I46 -> 18396 | I23: ='0. Database'!J46 -> 31149 | ... S23: ='0. Database'!T46 -> 15000
A24: META | B24: ='0. Database'!C63 -> 0 | C24: ='0. Database'!D63 -> 0 | D24: ='0. Database'!E63 -> 0 | E24: ='0. Database'!F63 -> 0 | F24: ='0. Database'!G63 -> 1976 | G24: ='0. Database'!H63 -> 12879 | H24: ='0. Database'!I63 -> 4201 | I24: ='0. Database'!J63 -> 6272 | ... S24: ='0. Database'!T63 -> 6000
A25: ORCL | B25: ='0. Database'!C81 -> 11021 | C25: ='0. Database'!D81 -> 9813 | D25: ='0. Database'!E81 -> 8087 | E25: ='0. Database'!F81 -> 10440 | F25: ='0. Database'!G81 -> 3561 | G25: ='0. Database'!H81 -> 11347 | H25: ='0. Database'!I81 -> 36140 | I25: ='0. Database'!J81 -> 19240 | ... S25: ='0. Database'!T81 -> 0
A27: (Revenue)
A28: Company | B28: 2013A | C28: 2014A | D28: 2015A | E28: 2016A | F28: 2017A | G28: 2018A | H28: 2019A | I28: 2020A | J28: 2021A | K28: 2022A | L28: 2023A | M28: 2024A | N28: 2025E | O28: 2026E | P28: 2027E | Q28: 2028E | R28: 2029E | S28: 2030E
A29: MSFT | B29: ='0. Database'!C5 -> 77849 | C29: ='0. Database'!D5 -> 86833 | D29: ='0. Database'!E5 -> 93580 | E29: ='0. Database'!F5 -> 85320 | F29: ='0. Database'!G5 -> 96571 | G29: ='0. Database'!H5 -> 110360 | H29: ='0. Database'!I5 -> 125843 | I29: ='0. Database'!J5 -> 143015 | ... S29: ='0. Database'!T5 -> 652772.62
A30: AMZN | B30: ='0. Database'!C21 -> 74453 | C30: ='0. Database'!D21 -> 88988.4 | D30: ='0. Database'!E21 -> 107006.6 | E30: ='0. Database'!F21 -> 135987 | F30: ='0. Database'!G21 -> 177866 | G30: ='0. Database'!H21 -> 232887 | H30: ='0. Database'!I21 -> 280522 | I30: ='0. Database'!J21 -> 386064 | ... S30: ='0. Database'!T21 -> 1305415.5
A31: GOOGL | B31: ='0. Database'!C36 -> 55519 | C31: ='0. Database'!D36 -> 66001 | D31: ='0. Database'!E36 -> 74989 | E31: ='0. Database'!F36 -> 90272 | F31: ='0. Database'!G36 -> 110855 | G31: ='0. Database'!H36 -> 136819 | H31: ='0. Database'!I36 -> 161857 | I31: ='0. Database'!J36 -> 182527 | ... S31: ='0. Database'!T36 -> 921874.95
A32: META | B32: ='0. Database'!C53 -> 7872 | C32: ='0. Database'!D53 -> 12466 | D32: ='0. Database'!E53 -> 17927 | E32: ='0. Database'!F53 -> 27638 | F32: ='0. Database'!G53 -> 40653 | G32: ='0. Database'!H53 -> 55838 | H32: ='0. Database'!I53 -> 70696.5 | I32: ='0. Database'!J53 -> 85966 | ... S32: ='0. Database'!T53 -> 456192.68
A33: ORCL | B33: ='0. Database'!C71 -> 37253 | C33: ='0. Database'!D71 -> 38305 | D33: ='0. Database'!E71 -> 38253 | E33: ='0. Database'!F71 -> 37057 | F33: ='0. Database'!G71 -> 37899 | G33: ='0. Database'!H71 -> 39431 | H33: ='0. Database'!I71 -> 39525 | I33: ='0. Database'!J71 -> 39073 | ... S33: ='0. Database'!T71 -> 185555.08
A35: (NI)
A36: Company | B36: 2013A | C36: 2014A | D36: 2015A | E36: 2016A | F36: 2017A | G36: 2018A | H36: 2019A | I36: 2020A | J36: 2021A | K36: 2022A | L36: 2023A | M36: 2024A | N36: 2025E | O36: 2026E | P36: 2027E | Q36: 2028E | R36: 2029E | S36: 2030E
A37: MSFT | B37: ='0. Database'!C7 -> 21863 | C37: ='0. Database'!D7 -> 22074 | D37: ='0. Database'!E7 -> 12193 | E37: ='0. Database'!F7 -> 16798 | F37: ='0. Database'!G7 -> 25489 | G37: ='0. Database'!H7 -> 16571 | H37: ='0. Database'!I7 -> 39240 | I37: ='0. Database'!J7 -> 44281 | ... S37: ='0. Database'!T7 -> 258948.36
A38: AMZN | B38: ='0. Database'!C23 -> 273 | C38: ='0. Database'!D23 -> -240.6 | D38: ='0. Database'!E23 -> 596.1 | E38: ='0. Database'!F23 -> 2371 | F38: ='0. Database'!G23 -> 3033 | G38: ='0. Database'!H23 -> 10073 | H38: ='0. Database'!I23 -> 11588 | I38: ='0. Database'!J23 -> 21331 | ... S38: ='0. Database'!T23 -> 211925.99
A39: GOOGL | B39: ='0. Database'!C38 -> 12720 | C39: ='0. Database'!D38 -> 14136 | D39: ='0. Database'!E38 -> 16348 | E39: ='0. Database'!F38 -> 19478 | F39: ='0. Database'!G38 -> 12662 | G39: ='0. Database'!H38 -> 30736 | H39: ='0. Database'!I38 -> 34343 | I39: ='0. Database'!J38 -> 40269 | ... S39: ='0. Database'!T38 -> 285975.76
A40: META | B40: ='0. Database'!C55 -> 1491 | C40: ='0. Database'!D55 -> 2924.8 | D40: ='0. Database'!E55 -> 3669 | E40: ='0. Database'!F55 -> 10187.2 | F40: ='0. Database'!G55 -> 15919 | G40: ='0. Database'!H55 -> 22112 | H40: ='0. Database'!I55 -> 18484.5 | I40: ='0. Database'!J55 -> 29145 | ... S40: ='0. Database'!T55 -> 127804.37
A41: ORCL | B41: ='0. Database'!C73 -> 10926 | C41: ='0. Database'!D73 -> 10955 | D41: ='0. Database'!E73 -> 9938 | E41: ='0. Database'!F73 -> 8900 | F41: ='0. Database'!G73 -> 9334 | G41: ='0. Database'!H73 -> 3587 | H41: ='0. Database'!I73 -> 11083 | I41: ='0. Database'!J73 -> 10135 | ... S41: ='0. Database'!T73 -> 44104.48
A43: (Capex)
A44: Company | B44: 2013A | C44: 2014A | D44: 2015A | E44: 2016A | F44: 2017A | G44: 2018A | H44: 2019A | I44: 2020A | J44: 2021A | K44: 2022A | L44: 2023A | M44: 2024A | N44: 2025E | O44: 2026E | P44: 2027E | Q44: 2028E | R44: 2029E | S44: 2030E
A45: MSFT | B45: ='0. Database'!C12 -> 4257 | C45: ='0. Database'!D12 -> 5485 | D45: ='0. Database'!E12 -> 5944 | E45: ='0. Database'!F12 -> 8932 | F45: ='0. Database'!G12 -> 10200 | G45: ='0. Database'!H12 -> 13600 | H45: ='0. Database'!I12 -> 16900 | I45: ='0. Database'!J12 -> 19000 | ... S45: ='0. Database'!T12 -> 304616.04
A46: AMZN | B46: ='0. Database'!C28 -> 3443 | C46: ='0. Database'!D28 -> 4892 | D46: ='0. Database'!E28 -> 4588 | E46: ='0. Database'!F28 -> 6736 | F46: ='0. Database'!G28 -> 10057 | G46: ='0. Database'!H28 -> 11322 | H46: ='0. Database'!I28 -> 12690 | I46: ='0. Database'!J28 -> 35046 | ... S46: ='0. Database'!T28 -> 312722.81
A47: GOOGL | B47: ='0. Database'!C43 -> 7358 | C47: ='0. Database'!D43 -> 10959 | D47: ='0. Database'!E43 -> 9915 | E47: ='0. Database'!F43 -> 10183 | F47: ='0. Database'!G43 -> 13184 | G47: ='0. Database'!H43 -> 25139 | H47: ='0. Database'!I43 -> 23548 | I47: ='0. Database'!J43 -> 22281 | ... S47: ='0. Database'!T43 -> 314500.02
A48: META | B48: ='0. Database'!C60 -> 1362 | C48: ='0. Database'!D60 -> 1831 | D48: ='0. Database'!E60 -> 2523 | E48: ='0. Database'!F60 -> 4491 | F48: ='0. Database'!G60 -> 6732 | G48: ='0. Database'!H60 -> 13980 | H48: ='0. Database'!I60 -> 15102 | I48: ='0. Database'!J60 -> 15115 | ... S48: ='0. Database'!T60 -> 208540.35
A49: ORCL | B49: ='0. Database'!C78 -> 650 | C49: ='0. Database'!D78 -> 580 | D49: ='0. Database'!E78 -> 1391 | E49: ='0. Database'!F78 -> 1189 | F49: ='0. Database'!G78 -> 2021 | G49: ='0. Database'!H78 -> 1736 | H49: ='0. Database'!I78 -> 1660 | I49: ='0. Database'!J78 -> 1564 | ... S49: ='0. Database'!T78 -> 66459.86
A51: C. FCF Margin %
A52: Company | B52: 2013A | C52: 2014A | D52: 2015A | E52: 2016A | F52: 2017A | G52: 2018A | H52: 2019A | I52: 2020A | J52: 2021A | K52: 2022A | L52: 2023A | M52: 2024A | N52: 2025E | O52: 2026E | P52: 2027E | Q52: 2028E | R52: 2029E | S52: 2030E
A53: MSFT | B53: =IFERROR(B13/B29,"") -> 0.31568806 | C53: =IFERROR(C13/C29,"") -> 0.30801654 | D53: =IFERROR(D13/D29,"") -> 0.24723231 | E53: =IFERROR(E13/E29,"") -> 0.28590014 | F53: =IFERROR(F13/F29,"") -> 0.3034762 | G53: =IFERROR(G13/G29,"") -> 0.27441102 | H53: =IFERROR(H13/H29,"") -> 0.28038906 | I53: =IFERROR(I13/I29,"") -> 0.291403 | ... S53: =IFERROR(S13/S29,"") -> 0.20517536
A54: AMZN | B54: =IFERROR(B14/B30,"") -> 0.027278955 | C54: =IFERROR(C14/C30,"") -> 0.021906226 | D54: =IFERROR(D14/D30,"") -> 0.068520073 | E54: =IFERROR(E14/E30,"") -> 0.077470641 | F54: =IFERROR(F14/F30,"") -> 0.047097253 | G54: =IFERROR(G14/G30,"") -> 0.08331079 | H54: =IFERROR(H14/H30,"") -> 0.092060516 | I54: =IFERROR(I14/I30,"") -> 0.080344192 | ... S54: =IFERROR(S14/S30,"") -> 0.067685424
A55: GOOGL | B55: =IFERROR(B15/B31,"") -> 0.20220105 | C55: =IFERROR(C15/C31,"") -> 0.17140649 | D55: =IFERROR(D15/D31,"") -> 0.21221779 | E55: =IFERROR(E15/E31,"") -> 0.28639002 | F55: =IFERROR(F15/F31,"") -> 0.2156601 | G55: =IFERROR(G15/G31,"") -> 0.16687741 | H55: =IFERROR(H15/H31,"") -> 0.1913541 | I55: =IFERROR(I15/I31,"") -> 0.23472144 | ... S55: =IFERROR(S15/S31,"") -> 0.19131372
A56: META | B56: =IFERROR(B16/B32,"") -> 0.36331301 | C56: =IFERROR(C16/C32,"") -> 0.29494625 | D56: =IFERROR(D16/D32,"") -> 0.33937636 | E56: =IFERROR(E16/E32,"") -> 0.41862653 | F56: =IFERROR(F16/F32,"") -> 0.43007896 | G56: =IFERROR(G16/G32,"") -> 0.27506358 | H56: =IFERROR(H16/H32,"") -> 0.30002192 | I56: =IFERROR(I16/I32,"") -> 0.27489938 | ... S56: =IFERROR(S16/S32,"") -> 0.2322224
A57: ORCL | B57: =IFERROR(B17/B33,"") -> 0.36440018 | C57: =IFERROR(C17/C33,"") -> 0.37438977 | D57: =IFERROR(D17/D33,"") -> 0.33840483 | E57: =IFERROR(E17/E33,"") -> 0.33383706 | F57: =IFERROR(F17/F33,"") -> 0.31937518 | G57: =IFERROR(G17/G33,"") -> 0.34617433 | H57: =IFERROR(H17/H33,"") -> 0.32614801 | I57: =IFERROR(I17/I33,"") -> 0.29624037 | ... S57: =IFERROR(S17/S33,"") -> 0.099723812
A59: D. FCF / Net Income %
A60: Company | B60: 2013A | C60: 2014A | D60: 2015A | E60: 2016A | F60: 2017A | G60: 2018A | H60: 2019A | I60: 2020A | J60: 2021A | K60: 2022A | L60: 2023A | M60: 2024A | N60: 2025E | O60: 2026E | P60: 2027E | Q60: 2028E | R60: 2029E | S60: 2030E
A61: MSFT | B61: =IFERROR(B13/B37,"") -> 1.1240909 | C61: =IFERROR(C13/C37,"") -> 1.2116517 | D61: =IFERROR(D13/D37,"") -> 1.8974822 | E61: =IFERROR(E13/E37,"") -> 1.4521372 | F61: =IFERROR(F13/F37,"") -> 1.1497901 | G61: =IFERROR(G13/G37,"") -> 1.82753 | H61: =IFERROR(H13/H37,"") -> 0.89920999 | I61: =IFERROR(I13/I37,"") -> 0.94114857 | ... S61: =IFERROR(S13/S37,"") -> 0.51721841
A62: AMZN | B62: =IFERROR(B14/B38,"") -> 7.4395604 | C62: =IFERROR(C14/C38,"") -> -8.1022444 | D62: =IFERROR(D14/D38,"") -> 12.300117 | E62: =IFERROR(E14/E38,"") -> 4.4432729 | F62: =IFERROR(F14/F38,"") -> 2.7619519 | G62: =IFERROR(G14/G38,"") -> 1.9261392 | H62: =IFERROR(H14/H38,"") -> 2.2285986 | I62: =IFERROR(I14/I38,"") -> 1.4541278 | ... S62: =IFERROR(S14/S38,"") -> 0.41692668
A63: GOOGL | B63: =IFERROR(B15/B39,"") -> 0.88254717 | C63: =IFERROR(C15/C39,"") -> 0.80029711 | D63: =IFERROR(D15/D39,"") -> 0.97345241 | E63: =IFERROR(E15/E39,"") -> 1.3272923 | F63: =IFERROR(F15/F39,"") -> 1.8880903 | G63: =IFERROR(G15/G39,"") -> 0.74284227 | H63: =IFERROR(H15/H39,"") -> 0.90184317 | I63: =IFERROR(I15/I39,"") -> 1.0639201 | ... S63: =IFERROR(S15/S39,"") -> 0.61672126
A64: META | B64: =IFERROR(B16/B40,"") -> 1.9181757 | C64: =IFERROR(C16/C40,"") -> 1.2571116 | D64: =IFERROR(D16/D40,"") -> 1.6582175 | E64: =IFERROR(E16/E40,"") -> 1.135739 | F64: =IFERROR(F16/F40,"") -> 1.0983102 | G64: =IFERROR(G16/G40,"") -> 0.69460022 | H64: =IFERROR(H16/H40,"") -> 1.1474749 | I64: =IFERROR(I16/I40,"") -> 0.81084234 | ... S64: =IFERROR(S16/S40,"") -> 0.82890875
A65: ORCL | B65: =IFERROR(B17/B41,"") -> 1.2424492 | C65: =IFERROR(C17/C41,"") -> 1.3090826 | D65: =IFERROR(D17/D41,"") -> 1.302576 | E65: =IFERROR(E17/E41,"") -> 1.39 | F65: =IFERROR(F17/F41,"") -> 1.2967645 | G65: =IFERROR(G17/G41,"") -> 3.8054084 | H65: =IFERROR(H17/H41,"") -> 1.1631327 | I65: =IFERROR(I17/I41,"") -> 1.1420819 | ... S65: =IFERROR(S17/S41,"") -> 0.41955511
A67: F. Capex / CFO %
A68: Company | B68: 2013A | C68: 2014A | D68: 2015A | E68: 2016A | F68: 2017A | G68: 2018A | H68: 2019A | I68: 2020A | J68: 2021A | K68: 2022A | L68: 2023A | M68: 2024A | N68: 2025E | O68: 2026E | P68: 2027E | Q68: 2028E | R68: 2029E | S68: 2030E
A69: MSFT | B69: =IFERROR(B45/B5,"") -> 0.14764333 | C69: =IFERROR(C45/C5,"") -> 0.17017778 | D69: =IFERROR(D45/D5,"") -> 0.20440165 | E69: =IFERROR(E45/E5,"") -> 0.26802701 | F69: =IFERROR(F45/F5,"") -> 0.25818209 | G69: =IFERROR(G45/G5,"") -> 0.30990794 | H69: =IFERROR(H45/H5,"") -> 0.32384785 | I69: =IFERROR(I45/I5,"") -> 0.3131438 | ... S69: =IFERROR(S45/S5,"") -> 0.69459994
A70: AMZN | B70: =IFERROR(B46/B6,"") -> 0.62897333 | C70: =IFERROR(C46/C6,"") -> 0.71505832 | D70: =IFERROR(D46/D6,"") -> 0.3848961 | E70: =IFERROR(E46/E6,"") -> 0.39001795 | F70: =IFERROR(F46/F6,"") -> 0.54556797 | G70: =IFERROR(G46/G6,"") -> 0.3685067 | H70: =IFERROR(H46/H6,"") -> 0.32948202 | I70: =IFERROR(I46/I6,"") -> 0.53048559 | ... S70: =IFERROR(S46/S6,"") -> 0.77970103
A71: GOOGL | B71: =IFERROR(B47/B7,"") -> 0.39593198 | C71: =IFERROR(C47/C7,"") -> 0.4920528 | D71: =IFERROR(D47/D7,"") -> 0.38387084 | E71: =IFERROR(E47/E7,"") -> 0.28257853 | F71: =IFERROR(F47/F7,"") -> 0.35545011 | G71: =IFERROR(G47/G7,"") -> 0.52404578 | H71: =IFERROR(H47/H7,"") -> 0.43191489 | I71: =IFERROR(I47/I7,"") -> 0.34213193 | ... S71: =IFERROR(S47/S7,"") -> 0.64070267
A72: META | B72: =IFERROR(B48/B8,"") -> 0.32259593 | C72: =IFERROR(C48/C8,"") -> 0.33243763 | D72: =IFERROR(D48/D8,"") -> 0.2931335 | E72: =IFERROR(E48/E8,"") -> 0.27962144 | F72: =IFERROR(F48/F8,"") -> 0.27799802 | G72: =IFERROR(G48/G8,"") -> 0.47649886 | H72: =IFERROR(H48/H8,"") -> 0.41588985 | I72: =IFERROR(I48/I8,"") -> 0.39009472 | ... S72: =IFERROR(S48/S8,"") -> 0.66313069
A73: ORCL | B73: =IFERROR(B49/B9,"") -> 0.0456942 | C73: =IFERROR(C49/C9,"") -> 0.038871389 | D73: =IFERROR(D49/D9,"") -> 0.09702846 | E73: =IFERROR(E49/E9,"") -> 0.087684366 | F73: =IFERROR(F49/F9,"") -> 0.14307965 | G73: =IFERROR(G49/G9,"") -> 0.11282985 | H73: =IFERROR(H49/H9,"") -> 0.11408151 | I73: =IFERROR(I49/I9,"") -> 0.11903493 | ... S73: =IFERROR(S49/S9,"") -> 0.78221089

Sheet 5. EPS & Margins
A1: EPS, OpMargin & Profitability (2013-2030E)
A3: A. Operating Income ($mm)
A4: Company | B4: 2013A | C4: 2014A | D4: 2015A | E4: 2016A | F4: 2017A | G4: 2018A | H4: 2019A | I4: 2020A | J4: 2021A | K4: 2022A | L4: 2023A | M4: 2024A | N4: 2025E | O4: 2026E | P4: 2027E | Q4: 2028E | R4: 2029E | S4: 2030E
A5: MSFT | B5: ='0. Database'!C6 -> 26764 | C5: ='0. Database'!D6 -> 27759 | D5: ='0. Database'!E6 -> 18161 | E5: ='0. Database'!F6 -> 20182 | F5: ='0. Database'!G6 -> 29025 | G5: ='0. Database'!H6 -> 35058 | H5: ='0. Database'!I6 -> 42959 | I5: ='0. Database'!J6 -> 52959 | ... S5: ='0. Database'!T6 -> 318436.19
A6: AMZN | B6: ='0. Database'!C22 -> 745 | C6: ='0. Database'!D22 -> 178.4 | D6: ='0. Database'!E22 -> 2232.6 | E6: ='0. Database'!F22 -> 4186 | F6: ='0. Database'!G22 -> 4107 | G6: ='0. Database'!H22 -> 12420 | H6: ='0. Database'!I22 -> 14540 | I6: ='0. Database'!J22 -> 22899 | ... S6: ='0. Database'!T22 -> 264582.39
A7: GOOGL | B7: ='0. Database'!C37 -> 15403 | C7: ='0. Database'!D37 -> 16496 | D7: ='0. Database'!E37 -> 19360 | E7: ='0. Database'!F37 -> 23716 | F7: ='0. Database'!G37 -> 26146 | G7: ='0. Database'!H37 -> 26953 | H7: ='0. Database'!I37 -> 34231 | I7: ='0. Database'!J37 -> 41224 | ... S7: ='0. Database'!T37 -> 338347.07
A8: META | B8: ='0. Database'!C54 -> 2804 | C8: ='0. Database'!D54 -> 4994.8 | D8: ='0. Database'!E54 -> 6225 | E8: ='0. Database'!F54 -> 12427 | F8: ='0. Database'!G54 -> 20202 | G8: ='0. Database'!H54 -> 24913 | H8: ='0. Database'!I54 -> 23985.5 | I8: ='0. Database'!J54 -> 32671 | ... S8: ='0. Database'!T54 -> 142814.67
A9: ORCL | B9: ='0. Database'!C72 -> 14684 | C9: ='0. Database'!D72 -> 14758 | D9: ='0. Database'!E72 -> 13870 | E9: ='0. Database'!F72 -> 12604 | F9: ='0. Database'!G72 -> 12710 | G9: ='0. Database'!H72 -> 13264 | H9: ='0. Database'!I72 -> 13535 | I9: ='0. Database'!J72 -> 13897 | ... S9: ='0. Database'!T72 -> 57952.82
A11: C. Net Income ($mm)
A12: Company | B12: 2013A | C12: 2014A | D12: 2015A | E12: 2016A | F12: 2017A | G12: 2018A | H12: 2019A | I12: 2020A | J12: 2021A | K12: 2022A | L12: 2023A | M12: 2024A | N12: 2025E | O12: 2026E | P12: 2027E | Q12: 2028E | R12: 2029E | S12: 2030E
A13: MSFT | B13: ='0. Database'!C7 -> 21863 | C13: ='0. Database'!D7 -> 22074 | D13: ='0. Database'!E7 -> 12193 | E13: ='0. Database'!F7 -> 16798 | F13: ='0. Database'!G7 -> 25489 | G13: ='0. Database'!H7 -> 16571 | H13: ='0. Database'!I7 -> 39240 | I13: ='0. Database'!J7 -> 44281 | ... S13: ='0. Database'!T7 -> 258948.36
A14: AMZN | B14: ='0. Database'!C23 -> 273 | C14: ='0. Database'!D23 -> -240.6 | D14: ='0. Database'!E23 -> 596.1 | E14: ='0. Database'!F23 -> 2371 | F14: ='0. Database'!G23 -> 3033 | G14: ='0. Database'!H23 -> 10073 | H14: ='0. Database'!I23 -> 11588 | I14: ='0. Database'!J23 -> 21331 | ... S14: ='0. Database'!T23 -> 211925.99
A15: GOOGL | B15: ='0. Database'!C38 -> 12720 | C15: ='0. Database'!D38 -> 14136 | D15: ='0. Database'!E38 -> 16348 | E15: ='0. Database'!F38 -> 19478 | F15: ='0. Database'!G38 -> 12662 | G15: ='0. Database'!H38 -> 30736 | H15: ='0. Database'!I38 -> 34343 | I15: ='0. Database'!J38 -> 40269 | ... S15: ='0. Database'!T38 -> 285975.76
A16: META | B16: ='0. Database'!C55 -> 1491 | C16: ='0. Database'!D55 -> 2924.8 | D16: ='0. Database'!E55 -> 3669 | E16: ='0. Database'!F55 -> 10187.2 | F16: ='0. Database'!G55 -> 15919 | G16: ='0. Database'!H55 -> 22112 | H16: ='0. Database'!I55 -> 18484.5 | I16: ='0. Database'!J55 -> 29145 | ... S16: ='0. Database'!T55 -> 127804.37
A17: ORCL | B17: ='0. Database'!C73 -> 10926 | C17: ='0. Database'!D73 -> 10955 | D17: ='0. Database'!E73 -> 9938 | E17: ='0. Database'!F73 -> 8900 | F17: ='0. Database'!G73 -> 9334 | G17: ='0. Database'!H73 -> 3587 | H17: ='0. Database'!I73 -> 11083 | I17: ='0. Database'!J73 -> 10135 | ... S17: ='0. Database'!T73 -> 44104.48
A19: E. EPS ($)
A20: Company | B20: 2013A | C20: 2014A | D20: 2015A | E20: 2016A | F20: 2017A | G20: 2018A | H20: 2019A | I20: 2020A | J20: 2021A | K20: 2022A | L20: 2023A | M20: 2024A | N20: 2025E | O20: 2026E | P20: 2027E | Q20: 2028E | R20: 2029E | S20: 2030E
A21: MSFT | B21: ='0. Database'!C8 -> 2.63 | C21: ='0. Database'!D8 -> 2.66 | D21: ='0. Database'!E8 -> 2.59 | E21: ='0. Database'!F8 -> 2.79 | F21: ='0. Database'!G8 -> 3.29 | G21: ='0. Database'!H8 -> 3.88 | H21: ='0. Database'!I8 -> 4.75 | I21: ='0. Database'!J8 -> 5.76 | ... S21: ='0. Database'!T8 -> 34.82
A22: AMZN | B22: ='0. Database'!C24 -> 0.03 | C22: ='0. Database'!D24 -> -0.03 | D22: ='0. Database'!E24 -> 0.06 | E22: ='0. Database'!F24 -> 0.24 | F22: ='0. Database'!G24 -> 0.31 | G22: ='0. Database'!H24 -> 1.01 | H22: ='0. Database'!I24 -> 1.15 | I22: ='0. Database'!J24 -> 2.08 | ... S22: ='0. Database'!T24 -> 18.92
A23: GOOGL | B23: ='0. Database'!C39 -> 0.94 | C23: ='0. Database'!D39 -> 1.03 | D23: ='0. Database'!E39 -> 1.18 | E23: ='0. Database'!F39 -> 1.39 | F23: ='0. Database'!G39 -> 0.9 | G23: ='0. Database'!H39 -> 2.19 | H23: ='0. Database'!I39 -> 2.46 | I23: ='0. Database'!J39 -> 2.93 | ... S23: ='0. Database'!T39 -> 22.99
A24: META | B24: ='0. Database'!C56 -> 0.59 | C24: ='0. Database'!D56 -> 1.1 | D24: ='0. Database'!E56 -> 1.28 | E24: ='0. Database'!F56 -> 3.48 | F24: ='0. Database'!G56 -> 5.39 | G24: ='0. Database'!H56 -> 7.66 | H24: ='0. Database'!I56 -> 6.44 | I24: ='0. Database'!J56 -> 10.08 | ... S24: ='0. Database'!T56 -> 47.52
A25: ORCL | B25: ='0. Database'!C74 -> 2.26 | C25: ='0. Database'!D74 -> 2.38 | D25: ='0. Database'!E74 -> 2.21 | E25: ='0. Database'!F74 -> 2.07 | F25: ='0. Database'!G74 -> 2.21 | G25: ='0. Database'!H74 -> 0.85 | H25: ='0. Database'!I74 -> 2.97 | I25: ='0. Database'!J74 -> 3.08 | ... S25: ='0. Database'!T74 -> 14.32
A27: G. Diluted Shares (mm)
A28: Company | B28: 2013A | C28: 2014A | D28: 2015A | E28: 2016A | F28: 2017A | G28: 2018A | H28: 2019A | I28: 2020A | J28: 2021A | K28: 2022A | L28: 2023A | M28: 2024A | N28: 2025E | O28: 2026E | P28: 2027E | Q28: 2028E | R28: 2029E | S28: 2030E
A29: MSFT | B29: ='0. Database'!C9 -> 8452.25 | C29: ='0. Database'!D9 -> 8385.25 | D29: ='0. Database'!E9 -> 8254 | E29: ='0. Database'!F9 -> 8012.25 | F29: ='0. Database'!G9 -> 7831.25 | G29: ='0. Database'!H9 -> 7792.25 | H29: ='0. Database'!I9 -> 7752 | I29: ='0. Database'!J9 -> 7681.5 | ... S29: ='0. Database'!T9 -> 7436.22
A30: AMZN | B30: ='0. Database'!C25 -> 9340 | C30: ='0. Database'!D25 -> 9440 | D30: ='0. Database'!E25 -> 9620 | E30: ='0. Database'!F25 -> 9720 | F30: ='0. Database'!G25 -> 9910 | G30: ='0. Database'!H25 -> 10020 | H30: ='0. Database'!I25 -> 10100 | I30: ='0. Database'!J25 -> 10254 | ... S30: ='0. Database'!T25 -> 11201.4
A31: GOOGL | B31: ='0. Database'!C40 -> 13552.38 | C31: ='0. Database'!D40 -> 13741.41 | D31: ='0. Database'!E40 -> 13858.6 | E31: ='0. Database'!F40 -> 13974.09 | F31: ='0. Database'!G40 -> 14071.67 | G31: ='0. Database'!H40 -> 14065.69 | H31: ='0. Database'!I40 -> 13971.13 | I31: ='0. Database'!J40 -> 13740.56 | ... S31: ='0. Database'!T40 -> 12436.85
A32: META | B32: ='0. Database'!C57 -> 2521.75 | C32: ='0. Database'!D57 -> 2671 | D32: ='0. Database'!E57 -> 2856.75 | E32: ='0. Database'!F57 -> 2923.75 | F32: ='0. Database'!G57 -> 2954 | G32: ='0. Database'!H57 -> 2886 | H32: ='0. Database'!I57 -> 2871 | I32: ='0. Database'!J57 -> 2890 | ... S32: ='0. Database'!T57 -> 2689.4
A33: ORCL | B33: ='0. Database'!C75 -> 4843.75 | C33: ='0. Database'!D75 -> 4604.5 | D33: ='0. Database'!E75 -> 4502.5 | E33: ='0. Database'!F75 -> 4305.5 | F33: ='0. Database'!G75 -> 4217 | G33: ='0. Database'!H75 -> 4238 | H33: ='0. Database'!I75 -> 3732 | I33: ='0. Database'!J75 -> 3293.5 | ... S33: ='0. Database'!T75 -> 3079.57
A35: H. SBC ($mm)
A36: Company | B36: 2013A | C36: 2014A | D36: 2015A | E36: 2016A | F36: 2017A | G36: 2018A | H36: 2019A | I36: 2020A | J36: 2021A | K36: 2022A | L36: 2023A | M36: 2024A | N36: 2025E | O36: 2026E | P36: 2027E | Q36: 2028E | R36: 2029E | S36: 2030E
A37: MSFT | B37: ='0. Database'!C10 -> 2406 | C37: ='0. Database'!D10 -> 2446 | D37: ='0. Database'!E10 -> 2574 | E37: ='0. Database'!F10 -> 2668 | F37: ='0. Database'!G10 -> 3266 | G37: ='0. Database'!H10 -> 3940 | H37: ='0. Database'!I10 -> 4652 | I37: ='0. Database'!J10 -> 5289 | ... S37: ='0. Database'!T10 -> 14871.62
A38: AMZN | B38: ='0. Database'!C26 -> -1134 | C38: ='0. Database'!D26 -> -1497 | D38: ='0. Database'!E26 -> -2120 | E38: ='0. Database'!F26 -> -2975 | F38: ='0. Database'!G26 -> -4214 | G38: ='0. Database'!H26 -> -5418 | H38: ='0. Database'!I26 -> -6864 | I38: ='0. Database'!J26 -> -9208 | ... S38: ='0. Database'!T26 -> -20744.82
A39: GOOGL | B39: ='0. Database'!C41 -> -3268 | C39: ='0. Database'!D41 -> -4175 | D39: ='0. Database'!E41 -> -4903 | E39: ='0. Database'!F41 -> -6703 | F39: ='0. Database'!G41 -> -7679 | G39: ='0. Database'!H41 -> -9353 | H39: ='0. Database'!I41 -> -10794 | I39: ='0. Database'!J41 -> -12991 | ... S39: ='0. Database'!T41 -> -35339.95
A40: META | B40: ='0. Database'!C58 -> -906 | C40: ='0. Database'!D58 -> -1837 | D40: ='0. Database'!E58 -> -2969 | E40: ='0. Database'!F58 -> -3202 | F40: ='0. Database'!G58 -> -3723 | G40: ='0. Database'!H58 -> -4152 | H40: ='0. Database'!I58 -> -4835 | I40: ='0. Database'!J58 -> -6536 | ... S40: ='0. Database'!T58 -> -28834.48
A41: ORCL | B41: ='0. Database'!C76 -> 755 | C41: ='0. Database'!D76 -> 805 | D41: ='0. Database'!E76 -> 933 | E41: ='0. Database'!F76 -> 1037 | F41: ='0. Database'!G76 -> 1350 | G41: ='0. Database'!H76 -> 1607 | H41: ='0. Database'!I76 -> 1653 | I41: ='0. Database'!J76 -> 1590 | ... S41: ='0. Database'!T76 -> 11212.32
A43: (Revenue)
A44: Company | B44: 2013A | C44: 2014A | D44: 2015A | E44: 2016A | F44: 2017A | G44: 2018A | H44: 2019A | I44: 2020A | J44: 2021A | K44: 2022A | L44: 2023A | M44: 2024A | N44: 2025E | O44: 2026E | P44: 2027E | Q44: 2028E | R44: 2029E | S44: 2030E
A45: MSFT | B45: ='0. Database'!C5 -> 77849 | C45: ='0. Database'!D5 -> 86833 | D45: ='0. Database'!E5 -> 93580 | E45: ='0. Database'!F5 -> 85320 | F45: ='0. Database'!G5 -> 96571 | G45: ='0. Database'!H5 -> 110360 | H45: ='0. Database'!I5 -> 125843 | I45: ='0. Database'!J5 -> 143015 | ... S45: ='0. Database'!T5 -> 652772.62
A46: AMZN | B46: ='0. Database'!C21 -> 74453 | C46: ='0. Database'!D21 -> 88988.4 | D46: ='0. Database'!E21 -> 107006.6 | E46: ='0. Database'!F21 -> 135987 | F46: ='0. Database'!G21 -> 177866 | G46: ='0. Database'!H21 -> 232887 | H46: ='0. Database'!I21 -> 280522 | I46: ='0. Database'!J21 -> 386064 | ... S46: ='0. Database'!T21 -> 1305415.5
A47: GOOGL | B47: ='0. Database'!C36 -> 55519 | C47: ='0. Database'!D36 -> 66001 | D47: ='0. Database'!E36 -> 74989 | E47: ='0. Database'!F36 -> 90272 | F47: ='0. Database'!G36 -> 110855 | G47: ='0. Database'!H36 -> 136819 | H47: ='0. Database'!I36 -> 161857 | I47: ='0. Database'!J36 -> 182527 | ... S47: ='0. Database'!T36 -> 921874.95
A48: META | B48: ='0. Database'!C53 -> 7872 | C48: ='0. Database'!D53 -> 12466 | D48: ='0. Database'!E53 -> 17927 | E48: ='0. Database'!F53 -> 27638 | F48: ='0. Database'!G53 -> 40653 | G48: ='0. Database'!H53 -> 55838 | H48: ='0. Database'!I53 -> 70696.5 | I48: ='0. Database'!J53 -> 85966 | ... S48: ='0. Database'!T53 -> 456192.68
A49: ORCL | B49: ='0. Database'!C71 -> 37253 | C49: ='0. Database'!D71 -> 38305 | D49: ='0. Database'!E71 -> 38253 | E49: ='0. Database'!F71 -> 37057 | F49: ='0. Database'!G71 -> 37899 | G49: ='0. Database'!H71 -> 39431 | H49: ='0. Database'!I71 -> 39525 | I49: ='0. Database'!J71 -> 39073 | ... S49: ='0. Database'!T71 -> 185555.08
A51: B. Operating Margin %
A52: Company | B52: 2013A | C52: 2014A | D52: 2015A | E52: 2016A | F52: 2017A | G52: 2018A | H52: 2019A | I52: 2020A | J52: 2021A | K52: 2022A | L52: 2023A | M52: 2024A | N52: 2025E | O52: 2026E | P52: 2027E | Q52: 2028E | R52: 2029E | S52: 2030E
A53: MSFT | B53: =IFERROR(B5/B45,"") -> 0.34379375 | C53: =IFERROR(C5/C45,"") -> 0.31968261 | D53: =IFERROR(D5/D45,"") -> 0.19406925 | E53: =IFERROR(E5/E45,"") -> 0.23654477 | F53: =IFERROR(F5/F45,"") -> 0.30055607 | G53: =IFERROR(G5/G45,"") -> 0.31766945 | H53: =IFERROR(H5/H45,"") -> 0.3413698 | I53: =IFERROR(I5/I45,"") -> 0.37030381 | ... S53: =IFERROR(S5/S45,"") -> 0.487821
A54: AMZN | B54: =IFERROR(B6/B46,"") -> 0.010006313 | C54: =IFERROR(C6/C46,"") -> 0.0020047557 | D54: =IFERROR(D6/D46,"") -> 0.020864134 | E54: =IFERROR(E6/E46,"") -> 0.030782354 | F54: =IFERROR(F6/F46,"") -> 0.023090416 | G54: =IFERROR(G6/G46,"") -> 0.053330585 | H54: =IFERROR(H6/H46,"") -> 0.051831942 | I54: =IFERROR(I6/I46,"") -> 0.059314 | ... S54: =IFERROR(S6/S46,"") -> 0.2026806
A55: GOOGL | B55: =IFERROR(B7/B47,"") -> 0.27743655 | C55: =IFERROR(C7/C47,"") -> 0.24993561 | D55: =IFERROR(D7/D47,"") -> 0.2581712 | E55: =IFERROR(E7/E47,"") -> 0.26271712 | F55: =IFERROR(F7/F47,"") -> 0.23585765 | G55: =IFERROR(G7/G47,"") -> 0.19699749 | H55: =IFERROR(H7/H47,"") -> 0.21148915 | I55: =IFERROR(I7/I47,"") -> 0.22585152 | ... S55: =IFERROR(S7/S47,"") -> 0.36702057
A56: META | B56: =IFERROR(B8/B48,"") -> 0.35619919 | C56: =IFERROR(C8/C48,"") -> 0.40067383 | D56: =IFERROR(D8/D48,"") -> 0.34724159 | E56: =IFERROR(E8/E48,"") -> 0.44963456 | F56: =IFERROR(F8/F48,"") -> 0.4969375 | G56: =IFERROR(G8/G48,"") -> 0.44616569 | H56: =IFERROR(H8/H48,"") -> 0.33927422 | I56: =IFERROR(I8/I48,"") -> 0.3800456 | ... S56: =IFERROR(S8/S48,"") -> 0.31305779
A57: ORCL | B57: =IFERROR(B9/B49,"") -> 0.3941696 | C57: =IFERROR(C9/C49,"") -> 0.38527607 | D57: =IFERROR(D9/D49,"") -> 0.36258594 | E57: =IFERROR(E9/E49,"") -> 0.34012467 | F57: =IFERROR(F9/F49,"") -> 0.33536505 | G57: =IFERROR(G9/G49,"") -> 0.33638508 | H57: =IFERROR(H9/H49,"") -> 0.34244149 | I57: =IFERROR(I9/I49,"") -> 0.3556676 | ... S57: =IFERROR(S9/S49,"") -> 0.31232139
A59: D. Net Margin %
A60: Company | B60: 2013A | C60: 2014A | D60: 2015A | E60: 2016A | F60: 2017A | G60: 2018A | H60: 2019A | I60: 2020A | J60: 2021A | K60: 2022A | L60: 2023A | M60: 2024A | N60: 2025E | O60: 2026E | P60: 2027E | Q60: 2028E | R60: 2029E | S60: 2030E
A61: MSFT | B61: =IFERROR(B13/B45,"") -> 0.28083855 | C61: =IFERROR(C13/C45,"") -> 0.25421211 | D61: =IFERROR(D13/D45,"") -> 0.13029493 | E61: =IFERROR(E13/E45,"") -> 0.19688233 | F61: =IFERROR(F13/F45,"") -> 0.26394052 | G61: =IFERROR(G13/G45,"") -> 0.15015404 | H61: =IFERROR(H13/H45,"") -> 0.31181711 | I61: =IFERROR(I13/I45,"") -> 0.30962486 | ... S61: =IFERROR(S13/S45,"") -> 0.39668998
A62: AMZN | B62: =IFERROR(B14/B46,"") -> 0.0036667428 | C62: =IFERROR(C14/C46,"") -> -0.0027037232 | D62: =IFERROR(D14/D46,"") -> 0.0055706844 | E62: =IFERROR(E14/E46,"") -> 0.01743549 | F62: =IFERROR(F14/F46,"") -> 0.017052163 | G62: =IFERROR(G14/G46,"") -> 0.043252736 | H62: =IFERROR(H14/H46,"") -> 0.041308703 | I62: =IFERROR(I14/I46,"") -> 0.055252497 | ... S62: =IFERROR(S14/S46,"") -> 0.16234371
A63: GOOGL | B63: =IFERROR(B15/B47,"") -> 0.22911075 | C63: =IFERROR(C15/C47,"") -> 0.21417857 | D63: =IFERROR(D15/D47,"") -> 0.21800531 | E63: =IFERROR(E15/E47,"") -> 0.21577012 | F63: =IFERROR(F15/F47,"") -> 0.11422128 | G63: =IFERROR(G15/G47,"") -> 0.22464716 | H63: =IFERROR(H15/H47,"") -> 0.21218112 | I63: =IFERROR(I15/I47,"") -> 0.22061942 | ... S63: =IFERROR(S15/S47,"") -> 0.31021101
A64: META | B64: =IFERROR(B16/B48,"") -> 0.18940549 | C64: =IFERROR(C16/C48,"") -> 0.23462217 | D64: =IFERROR(D16/D48,"") -> 0.20466336 | E64: =IFERROR(E16/E48,"") -> 0.36859396 | F64: =IFERROR(F16/F48,"") -> 0.39158242 | G64: =IFERROR(G16/G48,"") -> 0.39600272 | H64: =IFERROR(H16/H48,"") -> 0.26146273 | I64: =IFERROR(I16/I48,"") -> 0.33902938 | ... S64: =IFERROR(S16/S48,"") -> 0.28015436
A65: ORCL | B65: =IFERROR(B17/B49,"") -> 0.29329182 | C65: =IFERROR(C17/C49,"") -> 0.285994 | D65: =IFERROR(D17/D49,"") -> 0.25979662 | E65: =IFERROR(E17/E49,"") -> 0.24017055 | F65: =IFERROR(F17/F49,"") -> 0.24628618 | G65: =IFERROR(G17/G49,"") -> 0.090969035 | H65: =IFERROR(H17/H49,"") -> 0.28040481 | I65: =IFERROR(I17/I49,"") -> 0.25938628 | ... S65: =IFERROR(S17/S49,"") -> 0.23768942
A67: F. EPS YoY %
A68: Company | B68: 2013A | C68: 2014A | D68: 2015A | E68: 2016A | F68: 2017A | G68: 2018A | H68: 2019A | I68: 2020A | J68: 2021A | K68: 2022A | L68: 2023A | M68: 2024A | N68: 2025E | O68: 2026E | P68: 2027E | Q68: 2028E | R68: 2029E | S68: 2030E
A69: MSFT | C69: =IFERROR(C21/B21-1,"") -> 0.011406844 | D69: =IFERROR(D21/C21-1,"") -> -0.026315789 | E69: =IFERROR(E21/D21-1,"") -> 0.077220077 | F69: =IFERROR(F21/E21-1,"") -> 0.17921147 | G69: =IFERROR(G21/F21-1,"") -> 0.17933131 | H69: =IFERROR(H21/G21-1,"") -> 0.2242268 | I69: =IFERROR(I21/H21-1,"") -> 0.21263158 | J69: =IFERROR(J21/I21-1,"") -> 0.38368056 | ... S69: =IFERROR(S21/R21-1,"") -> 0.20193303
A70: AMZN | C70: =IFERROR(C22/B22-1,"") -> -2 | D70: =IFERROR(D22/C22-1,"") -> -3 | E70: =IFERROR(E22/D22-1,"") -> 3 | F70: =IFERROR(F22/E22-1,"") -> 0.29166667 | G70: =IFERROR(G22/F22-1,"") -> 2.2580645 | H70: =IFERROR(H22/G22-1,"") -> 0.13861386 | I70: =IFERROR(I22/H22-1,"") -> 0.80869565 | J70: =IFERROR(J22/I22-1,"") -> 0.5625 | ... S70: =IFERROR(S22/R22-1,"") -> 0.18844221
A71: GOOGL | C71: =IFERROR(C23/B23-1,"") -> 0.095744681 | D71: =IFERROR(D23/C23-1,"") -> 0.14563107 | E71: =IFERROR(E23/D23-1,"") -> 0.1779661 | F71: =IFERROR(F23/E23-1,"") -> -0.35251799 | G71: =IFERROR(G23/F23-1,"") -> 1.4333333 | H71: =IFERROR(H23/G23-1,"") -> 0.12328767 | I71: =IFERROR(I23/H23-1,"") -> 0.19105691 | J71: =IFERROR(J23/I23-1,"") -> 0.91467577 | ... S71: =IFERROR(S23/R23-1,"") -> 0.14264414
A72: META | C72: =IFERROR(C24/B24-1,"") -> 0.86440678 | D72: =IFERROR(D24/C24-1,"") -> 0.16363636 | E72: =IFERROR(E24/D24-1,"") -> 1.71875 | F72: =IFERROR(F24/E24-1,"") -> 0.54885057 | G72: =IFERROR(G24/F24-1,"") -> 0.42115028 | H72: =IFERROR(H24/G24-1,"") -> -0.15926893 | I72: =IFERROR(I24/H24-1,"") -> 0.56521739 | J72: =IFERROR(J24/I24-1,"") -> 0.39583333 | ... S72: =IFERROR(S24/R24-1,"") -> 0.092162721
A73: ORCL | C73: =IFERROR(C25/B25-1,"") -> 0.053097345 | D73: =IFERROR(D25/C25-1,"") -> -0.071428571 | E73: =IFERROR(E25/D25-1,"") -> -0.063348416 | F73: =IFERROR(F25/E25-1,"") -> 0.06763285 | G73: =IFERROR(G25/F25-1,"") -> -0.61538462 | H73: =IFERROR(H25/G25-1,"") -> 2.4941176 | I73: =IFERROR(I25/H25-1,"") -> 0.037037037 | J73: =IFERROR(J25/I25-1,"") -> 0.47727273 | ... S73: =IFERROR(S25/R25-1,"") -> 0.088973384

Sheet 6. 折旧敏感性 Depreciation
A1: 折旧敏感性分析: 基于 MSFT 实际 PP&E 拆分的 Proxy 方法
A3: A. MSFT 实际 PP&E/Capex 拆分 (来源: 你的模型 Capex sheet — ✅ 硬数据)
A4: 蓝字 = 直接从 MSFT 模型 Capex sheet 提取的实际数据. 这是整个分析的基石 — 唯一有公司级 PP&E 明细的标的.
A5: 指标 (MSFT FY) | B5: FY2020A | C5: FY2021A | D5: FY2022A | E5: FY2023A | F5: FY2024A | G5: FY2025A | H5: FY2026E | I5: FY2027E | J5: FY2028E | K5: FY2029E | L5: FY2030E
A6: IT设备 Capex ($mm) | B6: 7438 | C6: 9989 | D6: 9381 | E6: 14330 | F6: 18819 | G6: 41432 | H6: 85947 | I6: 144612 | J6: 166321 | K6: 174122 | L6: 176677
A7: 建筑 Capex ($mm) | B7: 4377 | C7: 6197 | D7: 7805 | E7: 10301 | F7: 13768 | G7: 36747 | H7: 50201 | I7: 83886 | J7: 100380 | K7: 105090 | L7: 106632
A8: 融资租赁 Capex ($mm) | B8: 3330 | C8: 3736 | D8: 3281 | E8: 3150 | F8: 11710 | G8: 21628 | H8: 32878 | I8: 42085 | J8: 37876 | K8: 30301 | L8: 21211
A9: 其他 Capex ($mm) | B9: 396 | C9: 2380 | D9: 2525 | E9: 2053 | F9: 3823 | G9: 10020 | H9: 9745 | I9: 16765 | J9: 20059 | K9: 20999 | L9: 21308
A10: 总 Capex ($mm) | B10: 19000 | C10: 24200 | D10: 29200 | E10: 31900 | F10: 55700 | G10: 88200 | H10: 145871 | I10: 245263 | J10: 286760 | K10: 300211 | L10: 304616
A11: IT设备 % of Capex | B11: 0.39 | C11: 0.41 | D11: 0.32 | E11: 0.45 | F11: 0.34 | G11: 0.47 | H11: 0.59 | I11: 0.59 | J11: 0.58 | K11: 0.58 | L11: 0.58
A12: IT设备 D&A ($mm) | E12: 2231 | F12: 10063 | G12: 14563 | H12: 23911 | I12: 43743 | J12: 68286 | K12: 94877 | L12: 121252
A13: 建筑 D&A ($mm) | E13: 680 | F13: 3304 | G13: 5132 | H13: 8149 | I13: 12605 | J13: 18775 | K13: 25426 | L13: 32434
A14: 总 D&A ($mm) | B14: 10700 | C14: 9300 | D14: 12600 | E14: 11000 | F14: 15200 | G14: 22000 | H14: 34839 | I14: 59542 | J14: 92995 | K14: 129654 | L14: 165840
A15: IT D&A % of 总D&A | E15: 0.2 | F15: 0.66 | G15: 0.66 | H15: 0.69 | I15: 0.73 | J15: 0.73 | K15: 0.73 | L15: 0.73
A16: IT设备折旧年限 | B16: 6 | C16: 6 | D16: 6 | E16: 6 | F16: 6 | G16: 6 | H16: 6 | I16: 6 | J16: 6 | K16: 6 | L16: 6
A17: 建筑折旧年限 | B17: 15 | C17: 15 | D17: 15 | E17: 15 | F17: 15 | G17: 15 | H17: 15 | I17: 15 | J17: 15 | K17: 15 | L17: 15
A19: 📌 关键发现: IT设备从 pre-AI 的 ~35% 跳到 AI 时代的 59%. IT 贡献了 66-73% 的总折旧 (因为 IT 6年 vs 建筑 15年). 这就是 Burry 论点的真正攻击面.
A21: B. IT设备占比估算: MSFT 硬数据 → 其他 4 家 Proxy (⚠️ 估计值, 有据但不可完全验证)
A22: 公司 | B22: IT设备占 Capex比例 | C22: 估算依据 (可信度) | D22: IT设备 折旧年限 | E22: 建筑+电力 占Capex% | F22: 建筑 折旧年限 | G22: 其他 (物流/办公)% | H22: 其他 折旧年限
A23: MSFT | B23: 0.59 | C23: ✅ 硬数据: 模型 Capex sheet Row 90 = 50.1% gross PP&E; capex share 59% | D23: 6 | E23: 0.36 | F23: 15 | G23: 0.05 | H23: 10
A24: AMZN | B24: 0.42 | C24: ⚠️ 估计: 10-K Equipment $185B 含卡车/飞机/机器人; AWS服务器仅 ~40-45% (Behind the Balance Sheet分析) | D24: 5 | E24: 0.35 | F24: 18 | G24: 0.23 | H24: 8
A25: GOOGL | B25: 0.57 | C25: ⚠️ 估计: MBI Deep Dives确认 IT assets 稳定 ~45% of PP&E; capex share应更高 (自研TPU集中在IT) | D25: 6 | E25: 0.35 | F25: 20 | G25: 0.08 | H25: 10
A26: META | B26: 0.62 | C26: ⚠️ 估计: 纯数据中心公司, 无物流/零售; 1.3M GPU; server+network是PP&E最大最快增长项 (MBI) | D26: 5.5 | E26: 0.33 | F26: 22 | G26: 0.05 | H26: 10
A27: ORCL | B27: 0.5 | C27: ⚠️ 估计: OCI从零建起, 新建期 buildings比例偏高; 但策略偏租赁+GPU采购; IT占比中等 | D27: 5.5 | E27: 0.4 | F27: 20 | G27: 0.1 | H27: 10
A30: C. 2026E 基础数据 (从 Database sheet 拉取)
A31: 公司 | B31: 2026E Capex ($mm) | C31: 2026E D&A ($mm) | D31: 2026E NI ($mm) | E31: 2026E EPS ($) | F31: Shares (mm) | G31: Tax Rate (可编辑) | H31: Depr Base = Capex×wtd life
A32: MSFT | B32: ='0. Database'!P12 -> 145871.3 | C32: ='0. Database'!P11 -> 39638.96 | D32: ='0. Database'!P7 -> 129372.86 | E32: ='0. Database'!P8 -> 16.75 | F32: ='0. Database'!P9 -> 7453.97 | G32: 0.18 | H32: =$C$32*($B$23*$D$23+$E$23*$F$23+$G$23*$H$23) -> 374191.78
A33: AMZN | B33: ='0. Database'!P28 -> 200104.98 | C33: ='0. Database'!P27 -> 81175.82 | D33: ='0. Database'!P23 -> 98333.72 | E33: ='0. Database'!P24 -> 9.02 | F33: ='0. Database'!P25 -> 10907.55 | G33: 0.2 | H33: =$C$33*($B$24*$D$24+$E$24*$F$24+$G$24*$H$24) -> 831240.4
A34: GOOGL | B34: ='0. Database'!P43 -> 185234.28 | C34: ='0. Database'!P42 -> 42874.7 | D34: ='0. Database'!P38 -> 168543.28 | E34: ='0. Database'!P39 -> 13.73 | F34: ='0. Database'!P40 -> 12275.96 | G34: 0.16 | H34: =$C$34*($B$25*$D$25+$E$25*$F$25+$G$25*$H$25) -> 481054.13
A35: META | B35: ='0. Database'!P60 -> 135583.71 | C35: ='0. Database'!P59 -> 35955.99 | D35: ='0. Database'!P55 -> 85782.86 | E35: ='0. Database'!P56 -> 33.28 | F35: ='0. Database'!P57 -> 2577.79 | G35: 0.13 | H35: =$C$35*($B$26*$D$26+$E$26*$F$26+$G$26*$H$26) -> 401628.41
A36: ORCL | B36: ='0. Database'!P78 -> 51882 | C36: ='0. Database'!P77 -> 7501.53 | D36: ='0. Database'!P73 -> 15820.55 | E36: ='0. Database'!P74 -> 5.43 | F36: ='0. Database'!P75 -> 2915.76 | G36: 0.2 | H36: =$C$36*($B$27*$D$27+$E$27*$F$27+$G$27*$H$27) -> 88142.977
A39: D. 核心敏感性: 仅压缩 IT设备寿命 (建筑/电力不变) — Straight-Line
A40: 逻辑: 新D&A = IT部分按新寿命折旧 + 建筑按原寿命不变 + 其他按原寿命不变. 仅IT部分受Burry论点影响.
A41: IT设备寿命 = 6 年 (建筑/其他不变)
A42: 公司 | B42: IT新D&A ($mm) | C42: 建筑D&A (不变,$mm) | D42: 其他D&A (不变,$mm) | E42: 新总D&A ($mm) | F42: 当前D&A ($mm) | G42: ΔD&A ($mm) | H42: Δ税后 ($mm) | I42: 调整NI ($mm) | J42: 调整EPS ($) | K42: EPS变化%
A43: MSFT | B43: =$H$32*$B$23/6 -> 36795.525 | C43: =$H$32*$E$23/$F$23 -> 8980.6028 | D43: =$H$32*$G$23/$H$23 -> 1870.9589 | E43: =$B$43+$C$43+$D$43 -> 47647.087 | F43: =$C$32 -> 39638.96 | G43: =$E$43-$C$32 -> 8008.127 | H43: =$G$43*(1-$G$32) -> 6566.6641 | I43: =$D$32-$H$43 -> 122806.2 | J43: =$I$43/$F$32 -> 16.475274 | K43: =IFERROR($J$43/$E$32-1,"") -> -0.01640157
A44: AMZN | B44: =$H$33*$B$24/6 -> 58186.828 | C44: =$H$33*$E$24/$F$24 -> 16163.008 | D44: =$H$33*$G$24/$H$24 -> 23898.161 | E44: =$B$44+$C$44+$D$44 -> 98247.997 | F44: =$C$33 -> 81175.82 | G44: =$E$44-$C$33 -> 17072.177 | H44: =$G$44*(1-$G$33) -> 13657.742 | I44: =$D$33-$H$44 -> 84675.978 | J44: =$I$44/$F$33 -> 7.7630612 | K44: =IFERROR($J$44/$E$33-1,"") -> -0.1393502
A45: GOOGL | B45: =$H$34*$B$25/6 -> 45700.143 | C45: =$H$34*$E$25/$F$25 -> 8418.4473 | D45: =$H$34*$G$25/$H$25 -> 3848.4331 | E45: =$B$45+$C$45+$D$45 -> 57967.023 | F45: =$C$34 -> 42874.7 | G45: =$E$45-$C$34 -> 15092.323 | H45: =$G$45*(1-$G$34) -> 12677.551 | I45: =$D$34-$H$45 -> 155865.73 | J45: =$I$45/$F$34 -> 12.696826 | K45: =IFERROR($J$45/$E$34-1,"") -> -0.075249378
A46: META | B46: =$H$35*$B$26/6 -> 41501.602 | C46: =$H$35*$E$26/$F$26 -> 6024.4261 | D46: =$H$35*$G$26/$H$26 -> 2008.142 | E46: =$B$46+$C$46+$D$46 -> 49534.17 | F46: =$C$35 -> 35955.99 | G46: =$E$46-$C$35 -> 13578.18 | H46: =$G$46*(1-$G$35) -> 11813.017 | I46: =$D$35-$H$46 -> 73969.843 | J46: =$I$46/$F$35 -> 28.695062 | K46: =IFERROR($J$46/$E$35-1,"") -> -0.13776858
A47: ORCL | B47: =$H$36*$B$27/6 -> 7345.2481 | C47: =$H$36*$E$27/$F$27 -> 1762.8595 | D47: =$H$36*$G$27/$H$27 -> 881.42977 | E47: =$B$47+$C$47+$D$47 -> 9989.5374 | F47: =$C$36 -> 7501.53 | G47: =$E$47-$C$36 -> 2488.0075 | H47: =$G$47*(1-$G$36) -> 1990.406 | I47: =$D$36-$H$47 -> 13830.144 | J47: =$I$47/$F$36 -> 4.7432381 | K47: =IFERROR($J$47/$E$36-1,"") -> -0.12647548
A49: IT设备寿命 = 5 年 (建筑/其他不变)
A50: 公司 | B50: IT新D&A ($mm) | C50: 建筑D&A (不变,$mm) | D50: 其他D&A (不变,$mm) | E50: 新总D&A ($mm) | F50: 当前D&A ($mm) | G50: ΔD&A ($mm) | H50: Δ税后 ($mm) | I50: 调整NI ($mm) | J50: 调整EPS ($) | K50: EPS变化%
A51: MSFT | B51: =$H$32*$B$23/5 -> 44154.63 | C51: =$H$32*$E$23/$F$23 -> 8980.6028 | D51: =$H$32*$G$23/$H$23 -> 1870.9589 | E51: =$B$51+$C$51+$D$51 -> 55006.192 | F51: =$C$32 -> 39638.96 | G51: =$E$51-$C$32 -> 15367.232 | H51: =$G$51*(1-$G$32) -> 12601.13 | I51: =$D$32-$H$51 -> 116771.73 | J51: =$I$51/$F$32 -> 15.66571 | K51: =IFERROR($J$51/$E$32-1,"") -> -0.064733752
A52: AMZN | B52: =$H$33*$B$24/5 -> 69824.193 | C52: =$H$33*$E$24/$F$24 -> 16163.008 | D52: =$H$33*$G$24/$H$24 -> 23898.161 | E52: =$B$52+$C$52+$D$52 -> 109885.36 | F52: =$C$33 -> 81175.82 | G52: =$E$52-$C$33 -> 28709.542 | H52: =$G$52*(1-$G$33) -> 22967.634 | I52: =$D$33-$H$52 -> 75366.086 | J52: =$I$52/$F$33 -> 6.9095339 | K52: =IFERROR($J$52/$E$33-1,"") -> -0.23397629
A53: GOOGL | B53: =$H$34*$B$25/5 -> 54840.171 | C53: =$H$34*$E$25/$F$25 -> 8418.4473 | D53: =$H$34*$G$25/$H$25 -> 3848.4331 | E53: =$B$53+$C$53+$D$53 -> 67107.052 | F53: =$C$34 -> 42874.7 | G53: =$E$53-$C$34 -> 24232.352 | H53: =$G$53*(1-$G$34) -> 20355.175 | I53: =$D$34-$H$53 -> 148188.1 | J53: =$I$53/$F$34 -> 12.071407 | K53: =IFERROR($J$53/$E$34-1,"") -> -0.12080068
A54: META | B54: =$H$35*$B$26/5 -> 49801.923 | C54: =$H$35*$E$26/$F$26 -> 6024.4261 | D54: =$H$35*$G$26/$H$26 -> 2008.142 | E54: =$B$54+$C$54+$D$54 -> 57834.491 | F54: =$C$35 -> 35955.99 | G54: =$E$54-$C$35 -> 21878.501 | H54: =$G$54*(1-$G$35) -> 19034.296 | I54: =$D$35-$H$54 -> 66748.564 | J54: =$I$54/$F$35 -> 25.893717 | K54: =IFERROR($J$54/$E$35-1,"") -> -0.2219436
A55: ORCL | B55: =$H$36*$B$27/5 -> 8814.2977 | C55: =$H$36*$E$27/$F$27 -> 1762.8595 | D55: =$H$36*$G$27/$H$27 -> 881.42977 | E55: =$B$55+$C$55+$D$55 -> 11458.587 | F55: =$C$36 -> 7501.53 | G55: =$E$55-$C$36 -> 3957.0571 | H55: =$G$55*(1-$G$36) -> 3165.6457 | I55: =$D$36-$H$55 -> 12654.904 | J55: =$I$55/$F$36 -> 4.3401735 | K55: =IFERROR($J$55/$E$36-1,"") -> -0.20070469
A57: IT设备寿命 = 4 年 (建筑/其他不变)
A58: 公司 | B58: IT新D&A ($mm) | C58: 建筑D&A (不变,$mm) | D58: 其他D&A (不变,$mm) | E58: 新总D&A ($mm) | F58: 当前D&A ($mm) | G58: ΔD&A ($mm) | H58: Δ税后 ($mm) | I58: 调整NI ($mm) | J58: 调整EPS ($) | K58: EPS变化%
A59: MSFT | B59: =$H$32*$B$23/4 -> 55193.288 | C59: =$H$32*$E$23/$F$23 -> 8980.6028 | D59: =$H$32*$G$23/$H$23 -> 1870.9589 | E59: =$B$59+$C$59+$D$59 -> 66044.85 | F59: =$C$32 -> 39638.96 | G59: =$E$59-$C$32 -> 26405.89 | H59: =$G$59*(1-$G$32) -> 21652.829 | I59: =$D$32-$H$59 -> 107720.03 | J59: =$I$59/$F$32 -> 14.451364 | K59: =IFERROR($J$59/$E$32-1,"") -> -0.13723203
A60: AMZN | B60: =$H$33*$B$24/4 -> 87280.242 | C60: =$H$33*$E$24/$F$24 -> 16163.008 | D60: =$H$33*$G$24/$H$24 -> 23898.161 | E60: =$B$60+$C$60+$D$60 -> 127341.41 | F60: =$C$33 -> 81175.82 | G60: =$E$60-$C$33 -> 46165.591 | H60: =$G$60*(1-$G$33) -> 36932.473 | I60: =$D$33-$H$60 -> 61401.247 | J60: =$I$60/$F$33 -> 5.6292428 | K60: =IFERROR($J$60/$E$33-1,"") -> -0.37591543
A61: GOOGL | B61: =$H$34*$B$25/4 -> 68550.214 | C61: =$H$34*$E$25/$F$25 -> 8418.4473 | D61: =$H$34*$G$25/$H$25 -> 3848.4331 | E61: =$B$61+$C$61+$D$61 -> 80817.095 | F61: =$C$34 -> 42874.7 | G61: =$E$61-$C$34 -> 37942.395 | H61: =$G$61*(1-$G$34) -> 31871.611 | I61: =$D$34-$H$61 -> 136671.67 | J61: =$I$61/$F$34 -> 11.133277 | K61: =IFERROR($J$61/$E$34-1,"") -> -0.18912764
A62: META | B62: =$H$35*$B$26/4 -> 62252.403 | C62: =$H$35*$E$26/$F$26 -> 6024.4261 | D62: =$H$35*$G$26/$H$26 -> 2008.142 | E62: =$B$62+$C$62+$D$62 -> 70284.971 | F62: =$C$35 -> 35955.99 | G62: =$E$62-$C$35 -> 34328.981 | H62: =$G$62*(1-$G$35) -> 29866.214 | I62: =$D$35-$H$62 -> 55916.646 | J62: =$I$62/$F$35 -> 21.6917 | K62: =IFERROR($J$62/$E$35-1,"") -> -0.34820614
A63: ORCL | B63: =$H$36*$B$27/4 -> 11017.872 | C63: =$H$36*$E$27/$F$27 -> 1762.8595 | D63: =$H$36*$G$27/$H$27 -> 881.42977 | E63: =$B$63+$C$63+$D$63 -> 13662.162 | F63: =$C$36 -> 7501.53 | G63: =$E$63-$C$36 -> 6160.6315 | H63: =$G$63*(1-$G$36) -> 4928.5052 | I63: =$D$36-$H$63 -> 10892.045 | J63: =$I$63/$F$36 -> 3.7355766 | K63: =IFERROR($J$63/$E$36-1,"") -> -0.31204851
A65: IT设备寿命 = 3 年 (建筑/其他不变)
A66: 公司 | B66: IT新D&A ($mm) | C66: 建筑D&A (不变,$mm) | D66: 其他D&A (不变,$mm) | E66: 新总D&A ($mm) | F66: 当前D&A ($mm) | G66: ΔD&A ($mm) | H66: Δ税后 ($mm) | I66: 调整NI ($mm) | J66: 调整EPS ($) | K66: EPS变化%
A67: MSFT | B67: =$H$32*$B$23/3 -> 73591.051 | C67: =$H$32*$E$23/$F$23 -> 8980.6028 | D67: =$H$32*$G$23/$H$23 -> 1870.9589 | E67: =$B$67+$C$67+$D$67 -> 84442.612 | F67: =$C$32 -> 39638.96 | G67: =$E$67-$C$32 -> 44803.652 | H67: =$G$67*(1-$G$32) -> 36738.995 | I67: =$D$32-$H$67 -> 92633.865 | J67: =$I$67/$F$32 -> 12.427453 | K67: =IFERROR($J$67/$E$32-1,"") -> -0.25806248
A68: AMZN | B68: =$H$33*$B$24/3 -> 116373.66 | C68: =$H$33*$E$24/$F$24 -> 16163.008 | D68: =$H$33*$G$24/$H$24 -> 23898.161 | E68: =$B$68+$C$68+$D$68 -> 156434.82 | F68: =$C$33 -> 81175.82 | G68: =$E$68-$C$33 -> 75259.005 | H68: =$G$68*(1-$G$33) -> 60207.204 | I68: =$D$33-$H$68 -> 38126.516 | J68: =$I$68/$F$33 -> 3.4954244 | K68: =IFERROR($J$68/$E$33-1,"") -> -0.61248067
A69: GOOGL | B69: =$H$34*$B$25/3 -> 91400.285 | C69: =$H$34*$E$25/$F$25 -> 8418.4473 | D69: =$H$34*$G$25/$H$25 -> 3848.4331 | E69: =$B$69+$C$69+$D$69 -> 103667.17 | F69: =$C$34 -> 42874.7 | G69: =$E$69-$C$34 -> 60792.466 | H69: =$G$69*(1-$G$34) -> 51065.671 | I69: =$D$34-$H$69 -> 117477.61 | J69: =$I$69/$F$34 -> 9.5697289 | K69: =IFERROR($J$69/$E$34-1,"") -> -0.30300591
A70: META | B70: =$H$35*$B$26/3 -> 83003.204 | C70: =$H$35*$E$26/$F$26 -> 6024.4261 | D70: =$H$35*$G$26/$H$26 -> 2008.142 | E70: =$B$70+$C$70+$D$70 -> 91035.773 | F70: =$C$35 -> 35955.99 | G70: =$E$70-$C$35 -> 55079.783 | H70: =$G$70*(1-$G$35) -> 47919.411 | I70: =$D$35-$H$70 -> 37863.449 | J70: =$I$70/$F$35 -> 14.688337 | K70: =IFERROR($J$70/$E$35-1,"") -> -0.55864371
A71: ORCL | B71: =$H$36*$B$27/3 -> 14690.496 | C71: =$H$36*$E$27/$F$27 -> 1762.8595 | D71: =$H$36*$G$27/$H$27 -> 881.42977 | E71: =$B$71+$C$71+$D$71 -> 17334.786 | F71: =$C$36 -> 7501.53 | G71: =$E$71-$C$36 -> 9833.2556 | H71: =$G$71*(1-$G$36) -> 7866.6045 | I71: =$D$36-$H$71 -> 7953.9455 | J71: =$I$71/$F$36 -> 2.727915 | K71: =IFERROR($J$71/$E$36-1,"") -> -0.49762154
A73: IT设备寿命 = 2 年 (建筑/其他不变)
A74: 公司 | B74: IT新D&A ($mm) | C74: 建筑D&A (不变,$mm) | D74: 其他D&A (不变,$mm) | E74: 新总D&A ($mm) | F74: 当前D&A ($mm) | G74: ΔD&A ($mm) | H74: Δ税后 ($mm) | I74: 调整NI ($mm) | J74: 调整EPS ($) | K74: EPS变化%
A75: MSFT | B75: =$H$32*$B$23/2 -> 110386.58 | C75: =$H$32*$E$23/$F$23 -> 8980.6028 | D75: =$H$32*$G$23/$H$23 -> 1870.9589 | E75: =$B$75+$C$75+$D$75 -> 121238.14 | F75: =$C$32 -> 39638.96 | G75: =$E$75-$C$32 -> 81599.177 | H75: =$G$75*(1-$G$32) -> 66911.326 | I75: =$D$32-$H$75 -> 62461.534 | J75: =$I$75/$F$32 -> 8.3796332 | K75: =IFERROR($J$75/$E$32-1,"") -> -0.49972339
A76: AMZN | B76: =$H$33*$B$24/2 -> 174560.48 | C76: =$H$33*$E$24/$F$24 -> 16163.008 | D76: =$H$33*$G$24/$H$24 -> 23898.161 | E76: =$B$76+$C$76+$D$76 -> 214621.65 | F76: =$C$33 -> 81175.82 | G76: =$E$76-$C$33 -> 133445.83 | H76: =$G$76*(1-$G$33) -> 106756.67 | I76: =$D$33-$H$76 -> -8422.946 | J76: =$I$76/$F$33 -> -0.77221245 | K76: =IFERROR($J$76/$E$33-1,"") -> -1.0856111
A77: GOOGL | B77: =$H$34*$B$25/2 -> 137100.43 | C77: =$H$34*$E$25/$F$25 -> 8418.4473 | D77: =$H$34*$G$25/$H$25 -> 3848.4331 | E77: =$B$77+$C$77+$D$77 -> 149367.31 | F77: =$C$34 -> 42874.7 | G77: =$E$77-$C$34 -> 106492.61 | H77: =$G$77*(1-$G$34) -> 89453.791 | I77: =$D$34-$H$77 -> 79089.489 | J77: =$I$77/$F$34 -> 6.4426317 | K77: =IFERROR($J$77/$E$34-1,"") -> -0.53076244
A78: META | B78: =$H$35*$B$26/2 -> 124504.81 | C78: =$H$35*$E$26/$F$26 -> 6024.4261 | D78: =$H$35*$G$26/$H$26 -> 2008.142 | E78: =$B$78+$C$78+$D$78 -> 132537.37 | F78: =$C$35 -> 35955.99 | G78: =$E$78-$C$35 -> 96581.385 | H78: =$G$78*(1-$G$35) -> 84025.805 | I78: =$D$35-$H$78 -> 1757.0553 | J78: =$I$78/$F$35 -> 0.68161304 | K78: =IFERROR($J$78/$E$35-1,"") -> -0.97951884
A79: ORCL | B79: =$H$36*$B$27/2 -> 22035.744 | C79: =$H$36*$E$27/$F$27 -> 1762.8595 | D79: =$H$36*$G$27/$H$27 -> 881.42977 | E79: =$B$79+$C$79+$D$79 -> 24680.034 | F79: =$C$36 -> 7501.53 | G79: =$E$79-$C$36 -> 17178.504 | H79: =$G$79*(1-$G$36) -> 13742.803 | I79: =$D$36-$H$79 -> 2077.747 | J79: =$I$79/$F$36 -> 0.71259193 | K79: =IFERROR($J$79/$E$36-1,"") -> -0.8687676
A82: E. 汇总: 2026E EPS 影响 (%) — 仅压缩IT设备 vs Burry的全压法 对比
A83: ★ 修正法 = 只压缩IT设备寿命, 建筑/电力不变. Burry全压法 = 对全部D&A做寿命压缩 (过于激进).
A84: 公司 | B84: IT占比 (来源) | C84: 当前 加权寿命 | D84: ★修正法 IT→4yr EPS Δ% | E84: ★修正法 IT→3yr EPS Δ% | F84: Burry全压 →4yr EPS Δ% | G84: Burry全压 →3yr EPS Δ% | H84: 修正法 杀伤力 (vs全压) | I84: 结论
A85: MSFT | B85: =$B$23 -> 0.59 | C85: =$B$23*$D$23+$E$23*$F$23+$G$23*$H$23 -> 9.44 | D85: =IFERROR(($D$32-($H$32*$B$23/4+$H$32*$E$23/$F$23+$H$32*$G$23/$H$23-$C$32)*(1-$G$32))/$F$32/$E$32-1,"") -> -0.13723203 | E85: =IFERROR(($D$32-($H$32*$B$23/3+$H$32*$E$23/$F$23+$H$32*$G$23/$H$23-$C$32)*(1-$G$32))/$F$32/$E$32-1,"") -> -0.25806248 | F85: =IFERROR(($D$32-($C$32*($B$23*$D$23+$E$23*$F$23+$G$23*$H$23)/4-$C$32)*(1-$G$32))/$F$32/$E$32-1,"") -> -0.31786332 | G85: =IFERROR(($D$32-($C$32*($B$23*$D$23+$E$23*$F$23+$G$23*$H$23)/3-$C$32)*(1-$G$32))/$F$32/$E$32-1,"") -> -0.5226607 | H85: =IFERROR(E85/G85,"") -> 0.49374763 | I85: 最安全. IT占比有硬数据支撑. 已主动缩寿到4.9yr.
A86: AMZN | B86: =$B$24 -> 0.42 | C86: =$B$24*$D$24+$E$24*$F$24+$G$24*$H$24 -> 10.24 | D86: =IFERROR(($D$33-($H$33*$B$24/4+$H$33*$E$24/$F$24+$H$33*$G$24/$H$24-$C$33)*(1-$G$33))/$F$33/$E$33-1,"") -> -0.37591543 | E86: =IFERROR(($D$33-($H$33*$B$24/3+$H$33*$E$24/$F$24+$H$33*$G$24/$H$24-$C$33)*(1-$G$33))/$F$33/$E$33-1,"") -> -0.61248067 | F86: =IFERROR(($D$33-($C$33*($B$24*$D$24+$E$24*$F$24+$G$24*$H$24)/4-$C$33)*(1-$G$33))/$F$33/$E$33-1,"") -> -1.0302248 | G86: =IFERROR(($D$33-($C$33*($B$24*$D$24+$E$24*$F$24+$G$24*$H$24)/3-$C$33)*(1-$G$33))/$F$33/$E$33-1,"") -> -1.5934754 | H86: =IFERROR(E86/G86,"") -> 0.38436782 | I86: 物流资产大幅稀释. 但D&A绝对额最大, 仍需关注.
A87: GOOGL | B87: =$B$25 -> 0.57 | C87: =$B$25*$D$25+$E$25*$F$25+$G$25*$H$25 -> 11.22 | D87: =IFERROR(($D$34-($H$34*$B$25/4+$H$34*$E$25/$F$25+$H$34*$G$25/$H$25-$C$34)*(1-$G$34))/$F$34/$E$34-1,"") -> -0.18912764 | E87: =IFERROR(($D$34-($H$34*$B$25/3+$H$34*$E$25/$F$25+$H$34*$G$25/$H$25-$C$34)*(1-$G$34))/$F$34/$E$34-1,"") -> -0.30300591 | F87: =IFERROR(($D$34-($C$34*($B$25*$D$25+$E$25*$F$25+$G$25*$H$25)/4-$C$34)*(1-$G$34))/$F$34/$E$34-1,"") -> -0.38571749 | G87: =IFERROR(($D$34-($C$34*($B$25*$D$25+$E$25*$F$25+$G$25*$H$25)/3-$C$34)*(1-$G$34))/$F$34/$E$34-1,"") -> -0.58550392 | H87: =IFERROR(E87/G87,"") -> 0.51751303 | I87: 自研TPU增加不确定性. IT占比估计中等可信.
A88: META | B88: =$B$26 -> 0.62 | C88: =$B$26*$D$26+$E$26*$F$26+$G$26*$H$26 -> 11.17 | D88: =IFERROR(($D$35-($H$35*$B$26/4+$H$35*$E$26/$F$26+$H$35*$G$26/$H$26-$C$35)*(1-$G$35))/$F$35/$E$35-1,"") -> -0.34820614 | E88: =IFERROR(($D$35-($H$35*$B$26/3+$H$35*$E$26/$F$26+$H$35*$G$26/$H$26-$C$35)*(1-$G$35))/$F$35/$E$35-1,"") -> -0.55864371 | F88: =IFERROR(($D$35-($C$35*($B$26*$D$26+$E$26*$F$26+$G$26*$H$26)/4-$C$35)*(1-$G$35))/$F$35/$E$35-1,"") -> -0.65368003 | G88: =IFERROR(($D$35-($C$35*($B$26*$D$26+$E$26*$F$26+$G$26*$H$26)/3-$C$35)*(1-$G$35))/$F$35/$E$35-1,"") -> -0.99309546 | H88: =IFERROR(E88/G88,"") -> 0.56252771 | I88: GPU浓度最高的纯DC公司. 冲击比例最大.
A89: ORCL | B89: =$B$27 -> 0.5 | C89: =$B$27*$D$27+$E$27*$F$27+$G$27*$H$27 -> 11.75 | D89: =IFERROR(($D$36-($H$36*$B$27/4+$H$36*$E$27/$F$27+$H$36*$G$27/$H$27-$C$36)*(1-$G$36))/$F$36/$E$36-1,"") -> -0.31204851 | E89: =IFERROR(($D$36-($H$36*$B$27/3+$H$36*$E$27/$F$27+$H$36*$G$27/$H$27-$C$36)*(1-$G$36))/$F$36/$E$36-1,"") -> -0.49762154 | F89: =IFERROR(($D$36-($C$36*($B$27*$D$27+$E$27*$F$27+$G$27*$H$27)/4-$C$36)*(1-$G$36))/$F$36/$E$36-1,"") -> -0.73515502 | G89: =IFERROR(($D$36-($C$36*($B$27*$D$27+$E$27*$F$27+$G$27*$H$27)/3-$C$36)*(1-$G$36))/$F$36/$E$36-1,"") -> -1.1063011 | H89: =IFERROR(E89/G89,"") -> 0.44980661 | I89: OCI新建期, building比例暂高. 但NI基数小, 相对冲击大.
A92: 数据可信度说明
A93: ✅ MSFT IT设备占比 (59% capex, 44.5% PP&E): 来自你的模型 Capex sheet Row 74/90/114 — 完全可验证
A94: ✅ MSFT 折旧年限 (IT 6yr, 建筑 15yr): 来自模型 Capex sheet Row 121-125 — 完全可验证
A95: ✅ 5家的 D&A, NI, EPS, Shares, Capex: 来自各自模型 — 完全可验证
A96: ⚠️ AMZN/GOOGL/META/ORCL IT设备占比: 基于 MSFT proxy + 行业报告 (MBI, Epoch AI, Behind the Balance Sheet) — 方向正确但具体数字是估计
A97: ⚠️ IT设备中 'AI GPU' 占多少: 任何公司的 10-K 都不披露这个细项 — 完全不可知
A98: ❌ DDB 方法: GAAP下无任何hyperscaler使用DDB折旧IT设备 — 仅作极端压力测试参考, 不代表现实可能性

Sheet 7. SP500 AI EPS Split
A1: S&P 500: AI vs Non-AI EPS Decomposition + Dual P/E Valuation
A3: A. S&P 500 Actual Operating EPS + sell-side Cash Spending Framework
A4: EPS: FactSet actual (2018-2024), consensus estimates (2025+). Capex/Buybacks: sell-side research (May 7 2026 report). Yellow = editable.
A5: Metric | B5: 2018A | C5: 2019A | D5: 2020A | E5: 2021A | F5: 2022A | G5: 2023A | H5: 2024A | I5: 2025A | J5: 2026E | K5: 2027E | L5: 2028E | M5: 2029E | N5: 2030E
A6: S&P 500 Operating EPS ($) | B6: 162 | C6: 164 | D6: 140 | E6: 209 | F6: 219 | G6: 221 | H6: 246 | I6: 275 | J6: 309 | K6: 342 | L6: 370 | M6: 396 | N6: 420
A7: S&P 500 Capex ($B) — sell-side research | B7: 644 | C7: 697 | D7: 591 | E7: 739 | F7: 892 | G7: 958 | H7: 1077 | I7: 1296 | J7: 1724 | K7: 2103 | L7: 2400 | M7: 2600 | N7: 2750
A8: Hyperscaler AI Capex ($B) — 5 cos | B8: 50 | C8: 55 | D8: 60 | E8: 86 | F8: 158 | G8: 154 | H8: 237 | I8: 412 | J8: 755 | K8: 892 | L8: 950 | M8: 980 | N8: 1000
A9: S&P 500 Buybacks ($B) — sell-side research | B9: 770 | C9: 729 | D9: 520 | E9: 919 | F9: 950 | G9: 823 | H9: 982 | I9: 1066 | J9: 1098 | K9: 1153 | L9: 1200 | M9: 1250 | N9: 1300
A10: Hyperscaler % of S&P Capex | B10: =B8/B7 -> 0.077639752 | C10: =C8/C7 -> 0.078909613 | D10: =D8/D7 -> 0.10152284 | E10: =E8/E7 -> 0.11637348 | F10: =F8/F7 -> 0.17713004 | G10: =G8/G7 -> 0.16075157 | H10: =H8/H7 -> 0.22005571 | I10: =I8/I7 -> 0.31790123 | ... N10: =N8/N7 -> 0.36363636
A12: B. AI-Driven EPS Estimation: Hyperscaler Capex → Supply Chain Profit → S&P 500 EPS
A13: Logic: Hyperscaler capex = revenue for NVDA/AVGO/MU/ANET/etc. Their net margin × capex = AI-driven NI. Divide by S&P 500 share count ≈ AI EPS.
A14: Metric | B14: 2018A | C14: 2019A | D14: 2020A | E14: 2021A | F14: 2022A | G14: 2023A | H14: 2024A | I14: 2025A | J14: 2026E | K14: 2027E | L14: 2028E | M14: 2029E | N14: 2030E
A15: % of Hyp Capex → S&P 500 co revenue (editable) | B15: 0.55 | C15: 0.55 | D15: 0.55 | E15: 0.55 | F15: 0.55 | G15: 0.55 | H15: 0.55 | I15: 0.6 | J15: 0.65 | K15: 0.65 | L15: 0.65 | M15: 0.63 | N15: 0.6
A16: Wtd avg net margin of AI supply chain (editable) | B16: 0.2 | C16: 0.2 | D16: 0.2 | E16: 0.22 | F16: 0.25 | G16: 0.3 | H16: 0.35 | I16: 0.4 | J16: 0.45 | K16: 0.42 | L16: 0.38 | M16: 0.35 | N16: 0.33
A17: AI Revenue to S&P 500 cos ($B) | B17: =B8*B15 -> 27.5 | C17: =C8*C15 -> 30.25 | D17: =D8*D15 -> 33 | E17: =E8*E15 -> 47.3 | F17: =F8*F15 -> 86.9 | G17: =G8*G15 -> 84.7 | H17: =H8*H15 -> 130.35 | I17: =I8*I15 -> 247.2 | ... N17: =N8*N15 -> 600
A18: AI Net Income to S&P 500 cos ($B) | B18: =B17*B16 -> 5.5 | C18: =C17*C16 -> 6.05 | D18: =D17*D16 -> 6.6 | E18: =E17*E16 -> 10.406 | F18: =F17*F16 -> 21.725 | G18: =G17*G16 -> 25.41 | H18: =H17*H16 -> 45.6225 | I18: =I17*I16 -> 98.88 | ... N18: =N17*N16 -> 198
A19: S&P 500 Aggregate NI ($B) ≈ EPS × 7.7B shares | B19: =B6*7.7 -> 1247.4 | C19: =C6*7.7 -> 1262.8 | D19: =D6*7.7 -> 1078 | E19: =E6*7.7 -> 1609.3 | F19: =F6*7.7 -> 1686.3 | G19: =G6*7.7 -> 1701.7 | H19: =H6*7.7 -> 1894.2 | I19: =I6*7.7 -> 2117.5 | ... N19: =N6*7.7 -> 3234
A20: AI-Driven EPS ($) = AI NI / 7.7B shares | B20: =B18/7.7 -> 0.71428571 | C20: =C18/7.7 -> 0.78571429 | D20: =D18/7.7 -> 0.85714286 | E20: =E18/7.7 -> 1.3514286 | F20: =F18/7.7 -> 2.8214286 | G20: =G18/7.7 -> 3.3 | H20: =H18/7.7 -> 5.925 | I20: =I18/7.7 -> 12.841558 | ... N20: =N18/7.7 -> 25.714286
A21: Non-AI EPS ($) = Total - AI | B21: =B6-B20 -> 161.28571 | C21: =C6-C20 -> 163.21429 | D21: =D6-D20 -> 139.14286 | E21: =E6-E20 -> 207.64857 | F21: =F6-F20 -> 216.17857 | G21: =G6-G20 -> 217.7 | H21: =H6-H20 -> 240.075 | I21: =I6-I20 -> 262.15844 | ... N21: =N6-N20 -> 394.28571
A22: AI % of Total EPS | B22: =IFERROR(B20/B6,"") -> 0.0044091711 | C22: =IFERROR(C20/C6,"") -> 0.0047909408 | D22: =IFERROR(D20/D6,"") -> 0.006122449 | E22: =IFERROR(E20/E6,"") -> 0.0064661654 | F22: =IFERROR(F20/F6,"") -> 0.012883235 | G22: =IFERROR(G20/G6,"") -> 0.014932127 | H22: =IFERROR(H20/H6,"") -> 0.024085366 | I22: =IFERROR(I20/I6,"") -> 0.046696576 | ... N22: =IFERROR(N20/N6,"") -> 0.06122449
A23: AI EPS YoY % | C23: =IFERROR(C20/B20-1,"") -> 0.1 | D23: =IFERROR(D20/C20-1,"") -> 0.090909091 | E23: =IFERROR(E20/D20-1,"") -> 0.57666667 | F23: =IFERROR(F20/E20-1,"") -> 1.0877378 | G23: =IFERROR(G20/F20-1,"") -> 0.16962025 | H23: =IFERROR(H20/G20-1,"") -> 0.79545455 | I23: =IFERROR(I20/H20-1,"") -> 1.1673516 | J23: =IFERROR(J20/I20-1,"") -> 1.233389 | ... N23: =IFERROR(N20/M20-1,"") -> -0.083715119
A25: C. Dual P/E Valuation — Separate Multiples for AI vs Non-AI EPS
A26: Non-AI P/E (editable) — hist avg ~18x | B26: 18
A27: AI P/E (editable) — NVDA ~30-40x fwd | B27: 35
A29: Valuation Component | B29: 2024A | C29: 2025A | D29: 2026E | E29: 2027E | F29: 2028E | G29: 2029E | H29: 2030E
A30: Non-AI Value = Non-AI EPS × P/E | B30: =H21*$B$26 -> 4321.35 | C30: =I21*$B$26 -> 4718.8519 | D30: =J21*$B$26 -> 5045.7565 | E30: =K21*$B$26 -> 5586.7418 | F30: =L21*$B$26 -> 6111.4675 | G30: =M21*$B$26 -> 6622.8545 | H30: =N21*$B$26 -> 7097.1429
A31: AI Value = AI EPS × P/E | B31: =H20*$B$27 -> 207.375 | C31: =I20*$B$27 -> 449.45455 | D31: =J20*$B$27 -> 1003.8068 | E31: =K20*$B$27 -> 1106.8909 | F31: =L20*$B$27 -> 1066.5909 | G31: =M20*$B$27 -> 982.22727 | H31: =N20*$B$27 -> 900
A32: Implied S&P 500 Level | B32: =B30+B31 -> 4528.725 | C32: =C30+C31 -> 5168.3065 | D32: =D30+D31 -> 6049.5633 | E32: =E30+E31 -> 6693.6327 | F32: =F30+F31 -> 7178.0584 | G32: =G30+G31 -> 7605.0818 | H32: =H30+H31 -> 7997.1429
A33: Blended P/E (implied) | B33: =IFERROR(B32/H6,"") -> 18.409451 | C33: =IFERROR(C32/I6,"") -> 18.793842 | D33: =IFERROR(D32/J6,"") -> 19.577875 | E33: =IFERROR(E32/K6,"") -> 19.572026 | F33: =IFERROR(F32/L6,"") -> 19.400158 | G33: =IFERROR(G32/M6,"") -> 19.204752 | H33: =IFERROR(H32/N6,"") -> 19.040816
A35: D. Scenario Grid: 2026E Implied S&P 500 Under Different P/E Assumptions
A36: Reads: 'If Non-AI trades at Xpe and AI trades at Ype, 2026E S&P 500 = Z'. Uses AI/Non-AI EPS from Section B. Change yellow cells above to update.
A37: AI P/E ↓ Non-AI P/E → | B37: 22x | C37: 20x | D37: 18x | E37: 16x | F37: 14x
A38: 40x | B38: =J21*22+J20*40 -> 7314.2435 | C38: =J21*20+J20*40 -> 6753.6039 | D38: =J21*18+J20*40 -> 6192.9643 | E38: =J21*16+J20*40 -> 5632.3247 | F38: =J21*14+J20*40 -> 5071.6851
A39: 35x | B39: =J21*22+J20*35 -> 7170.8425 | C39: =J21*20+J20*35 -> 6610.2029 | D39: =J21*18+J20*35 -> 6049.5633 | E39: =J21*16+J20*35 -> 5488.9237 | F39: =J21*14+J20*35 -> 4928.2841
A40: 30x | B40: =J21*22+J20*30 -> 7027.4416 | C40: =J21*20+J20*30 -> 6466.8019 | D40: =J21*18+J20*30 -> 5906.1623 | E40: =J21*16+J20*30 -> 5345.5227 | F40: =J21*14+J20*30 -> 4784.8831
A41: 25x | B41: =J21*22+J20*25 -> 6884.0406 | C41: =J21*20+J20*25 -> 6323.401 | D41: =J21*18+J20*25 -> 5762.7614 | E41: =J21*16+J20*25 -> 5202.1218 | F41: =J21*14+J20*25 -> 4641.4821
A42: 20x | B42: =J21*22+J20*20 -> 6740.6396 | C42: =J21*20+J20*20 -> 6180 | D42: =J21*18+J20*20 -> 5619.3604 | E42: =J21*16+J20*20 -> 5058.7208 | F42: =J21*14+J20*20 -> 4498.0812
A43: 15x | B43: =J21*22+J20*15 -> 6597.2386 | C43: =J21*20+J20*15 -> 6036.599 | D43: =J21*18+J20*15 -> 5475.9594 | E43: =J21*16+J20*15 -> 4915.3198 | F43: =J21*14+J20*15 -> 4354.6802
A44: 10x | B44: =J21*22+J20*10 -> 6453.8377 | C44: =J21*20+J20*10 -> 5893.1981 | D44: =J21*18+J20*10 -> 5332.5584 | E44: =J21*16+J20*10 -> 4771.9188 | F44: =J21*14+J20*10 -> 4211.2792
A46: E. Stress Test: What Happens to S&P 500 if AI Capex Slows?
A47: Base Case (AI PE=35x, Non-AI PE=18x)
A48: Current trajectory. AI capex sustains. NVDA margin holds.
B49: 2024A | C49: 2025A | D49: 2026E | E49: 2027E | F49: 2028E | G49: 2029E | H49: 2030E
A50: AI EPS ($) | B50: 5.9 | C50: 12.8 | D50: 28.7 | E50: 31.6 | F50: 30.5 | G50: 28.1 | H50: 25.7
A51: Non-AI EPS ($) | B51: =H21 -> 240.075 | C51: =I21 -> 262.15844 | D51: =J21 -> 280.31981 | E51: =K21 -> 310.37455 | F51: =L21 -> 339.52597 | G51: =M21 -> 367.93636 | H51: =N21 -> 394.28571
A52: Implied S&P 500 | B52: =B50*35+B51*18 -> 4527.85 | C52: =C50*35+C51*18 -> 5166.8519 | D52: =D50*35+D51*18 -> 6050.2565 | E52: =E50*35+E51*18 -> 6692.7418 | F52: =F50*35+F51*18 -> 7178.9675 | G52: =G50*35+G51*18 -> 7606.3545 | H52: =H50*35+H51*18 -> 7996.6429
A54: Capex Slowdown (AI PE=25x, Non-AI PE=18x)
A55: 2027+ capex growth decelerates to +10%. NVDA margin compresses. AI PE de-rates.
B56: 2024A | C56: 2025A | D56: 2026E | E56: 2027E | F56: 2028E | G56: 2029E | H56: 2030E
A57: AI EPS ($) | B57: 5.9 | C57: 12.8 | D57: 26.8 | E57: 26.6 | F57: 23.8 | G57: 21.5 | H57: 20
A58: Non-AI EPS ($) | B58: =H21 -> 240.075 | C58: =I21 -> 262.15844 | D58: =J21 -> 280.31981 | E58: =K21 -> 310.37455 | F58: =L21 -> 339.52597 | G58: =M21 -> 367.93636 | H58: =N21 -> 394.28571
A59: Implied S&P 500 | B59: =B57*25+B58*18 -> 4468.85 | C59: =C57*25+C58*18 -> 5038.8519 | D59: =D57*25+D58*18 -> 5715.7565 | E59: =E57*25+E58*18 -> 6251.7418 | F59: =F57*25+F58*18 -> 6706.4675 | G59: =G57*25+G58*18 -> 7160.3545 | H59: =H57*25+H58*18 -> 7597.1429
A60: Δ vs Base | B60: =IFERROR(B59/B52-1,"") -> -0.013030467 | C60: =IFERROR(C59/C52-1,"") -> -0.024773305 | D60: =IFERROR(D59/D52-1,"") -> -0.055286912 | E60: =IFERROR(E59/E52-1,"") -> -0.065892277 | F60: =IFERROR(F59/F52-1,"") -> -0.065817264 | G60: =IFERROR(G59/G52-1,"") -> -0.058635184 | H60: =IFERROR(H59/H52-1,"") -> -0.049958465
A62: AI Bust (AI PE=15x, Non-AI PE=17x)
A63: Customer crack. Capex cut 30% from 2027. Massive write-downs. AI PE crashes to market avg.
B64: 2024A | C64: 2025A | D64: 2026E | E64: 2027E | F64: 2028E | G64: 2029E | H64: 2030E
A65: AI EPS ($) | B65: 5.9 | C65: 12.8 | D65: 28.7 | E65: 12.4 | F65: 7.1 | G65: 5.5 | H65: 4.5
A66: Non-AI EPS ($) | B66: =H21 -> 240.075 | C66: =I21 -> 262.15844 | D66: =J21 -> 280.31981 | E66: =K21 -> 310.37455 | F66: =L21 -> 339.52597 | G66: =M21 -> 367.93636 | H66: =N21 -> 394.28571
A67: Implied S&P 500 | B67: =B65*15+B66*17 -> 4169.775 | C67: =C65*15+C66*17 -> 4648.6935 | D67: =D65*15+D66*17 -> 5195.9367 | E67: =E65*15+E66*17 -> 5462.3673 | F67: =F65*15+F66*17 -> 5878.4416 | G67: =G65*15+G66*17 -> 6337.4182 | H67: =H65*15+H66*17 -> 6770.3571
A68: Δ vs Base | B68: =IFERROR(B67/B52-1,"") -> -0.079082788 | C68: =IFERROR(C67/C52-1,"") -> -0.10028513 | D68: =IFERROR(D67/D52-1,"") -> -0.1412039 | E68: =IFERROR(E67/E52-1,"") -> -0.18383714 | F68: =IFERROR(F67/F52-1,"") -> -0.1811578 | G68: =IFERROR(G67/G52-1,"") -> -0.16682582 | H68: =IFERROR(H67/H52-1,"") -> -0.15335007

Sheet 8. Charts
A1: Visual Summary (2013-2030)
A3: Capex/Rev %
B4: 2013 | C4: 2014 | D4: 2015 | E4: 2016 | F4: 2017 | G4: 2018 | H4: 2019 | I4: 2020 | J4: 2021 | K4: 2022 | L4: 2023 | M4: 2024 | N4: 2025 | O4: 2026 | P4: 2027 | Q4: 2028 | R4: 2029 | S4: 2030
A5: MSFT | B5: =IFERROR('0. Database'!C12/'0. Database'!C5,"") -> 0.054682783 | C5: =IFERROR('0. Database'!D12/'0. Database'!D5,"") -> 0.063167229 | D5: =IFERROR('0. Database'!E12/'0. Database'!E5,"") -> 0.063517846 | E5: =IFERROR('0. Database'!F12/'0. Database'!F5,"") -> 0.10468823 | F5: =IFERROR('0. Database'!G12/'0. Database'!G5,"") -> 0.10562177 | G5: =IFERROR('0. Database'!H12/'0. Database'!H5,"") -> 0.12323306 | H5: =IFERROR('0. Database'!I12/'0. Database'!I5,"") -> 0.13429432 | I5: =IFERROR('0. Database'!J12/'0. Database'!J5,"") -> 0.1328532 | ... S5: =IFERROR('0. Database'!T12/'0. Database'!T5,"") -> 0.46664954
A6: AMZN | B6: =IFERROR('0. Database'!C28/'0. Database'!C21,"") -> 0.046243939 | C6: =IFERROR('0. Database'!D28/'0. Database'!D21,"") -> 0.054973457 | D6: =IFERROR('0. Database'!E28/'0. Database'!E21,"") -> 0.04287586 | E6: =IFERROR('0. Database'!F28/'0. Database'!F21,"") -> 0.049534147 | F6: =IFERROR('0. Database'!G28/'0. Database'!G21,"") -> 0.056542566 | G6: =IFERROR('0. Database'!H28/'0. Database'!H21,"") -> 0.048615852 | H6: =IFERROR('0. Database'!I28/'0. Database'!I21,"") -> 0.045237094 | I6: =IFERROR('0. Database'!J28/'0. Database'!J21,"") -> 0.090777695 | ... S6: =IFERROR('0. Database'!T28/'0. Database'!T21,"") -> 0.23955807
A7: GOOGL | B7: =IFERROR('0. Database'!C43/'0. Database'!C36,"") -> 0.13253121 | C7: =IFERROR('0. Database'!D43/'0. Database'!D36,"") -> 0.16604294 | D7: =IFERROR('0. Database'!E43/'0. Database'!E36,"") -> 0.13221939 | E7: =IFERROR('0. Database'!F43/'0. Database'!F36,"") -> 0.11280353 | F7: =IFERROR('0. Database'!G43/'0. Database'!G36,"") -> 0.11893013 | G7: =IFERROR('0. Database'!H43/'0. Database'!H36,"") -> 0.1837391 | H7: =IFERROR('0. Database'!I43/'0. Database'!I36,"") -> 0.14548645 | I7: =IFERROR('0. Database'!J43/'0. Database'!J36,"") -> 0.12206961 | ... S7: =IFERROR('0. Database'!T43/'0. Database'!T36,"") -> 0.34115258
A8: META | B8: =IFERROR('0. Database'!C60/'0. Database'!C53,"") -> 0.17301829 | C8: =IFERROR('0. Database'!D60/'0. Database'!D53,"") -> 0.14687951 | D8: =IFERROR('0. Database'!E60/'0. Database'!E53,"") -> 0.14073744 | E8: =IFERROR('0. Database'!F60/'0. Database'!F53,"") -> 0.16249367 | F8: =IFERROR('0. Database'!G60/'0. Database'!G53,"") -> 0.16559663 | G8: =IFERROR('0. Database'!H60/'0. Database'!H53,"") -> 0.25036713 | H8: =IFERROR('0. Database'!I60/'0. Database'!I53,"") -> 0.21361736 | I8: =IFERROR('0. Database'!J60/'0. Database'!J53,"") -> 0.17582533 | ... S8: =IFERROR('0. Database'!T60/'0. Database'!T53,"") -> 0.45713217
A9: ORCL | B9: =IFERROR('0. Database'!C78/'0. Database'!C71,"") -> 0.017448259 | C9: =IFERROR('0. Database'!D78/'0. Database'!D71,"") -> 0.015141626 | D9: =IFERROR('0. Database'!E78/'0. Database'!E71,"") -> 0.036363161 | E9: =IFERROR('0. Database'!F78/'0. Database'!F71,"") -> 0.032085706 | F9: =IFERROR('0. Database'!G78/'0. Database'!G71,"") -> 0.053325945 | G9: =IFERROR('0. Database'!H78/'0. Database'!H71,"") -> 0.044026274 | H9: =IFERROR('0. Database'!I78/'0. Database'!I71,"") -> 0.041998735 | I9: =IFERROR('0. Database'!J78/'0. Database'!J71,"") -> 0.040027641 | ... S9: =IFERROR('0. Database'!T78/'0. Database'!T71,"") -> 0.35816783
A12: FCF Margin %
B13: 2013 | C13: 2014 | D13: 2015 | E13: 2016 | F13: 2017 | G13: 2018 | H13: 2019 | I13: 2020 | J13: 2021 | K13: 2022 | L13: 2023 | M13: 2024 | N13: 2025 | O13: 2026 | P13: 2027 | Q13: 2028 | R13: 2029 | S13: 2030
A14: MSFT | B14: =IFERROR('0. Database'!C14/'0. Database'!C5,"") -> 0.31568806 | C14: =IFERROR('0. Database'!D14/'0. Database'!D5,"") -> 0.30801654 | D14: =IFERROR('0. Database'!E14/'0. Database'!E5,"") -> 0.24723231 | E14: =IFERROR('0. Database'!F14/'0. Database'!F5,"") -> 0.28590014 | F14: =IFERROR('0. Database'!G14/'0. Database'!G5,"") -> 0.3034762 | G14: =IFERROR('0. Database'!H14/'0. Database'!H5,"") -> 0.27441102 | H14: =IFERROR('0. Database'!I14/'0. Database'!I5,"") -> 0.28038906 | I14: =IFERROR('0. Database'!J14/'0. Database'!J5,"") -> 0.291403 | ... S14: =IFERROR('0. Database'!T14/'0. Database'!T5,"") -> 0.20517536
A15: AMZN | B15: =IFERROR('0. Database'!C30/'0. Database'!C21,"") -> 0.027278955 | C15: =IFERROR('0. Database'!D30/'0. Database'!D21,"") -> 0.021906226 | D15: =IFERROR('0. Database'!E30/'0. Database'!E21,"") -> 0.068520073 | E15: =IFERROR('0. Database'!F30/'0. Database'!F21,"") -> 0.077470641 | F15: =IFERROR('0. Database'!G30/'0. Database'!G21,"") -> 0.047097253 | G15: =IFERROR('0. Database'!H30/'0. Database'!H21,"") -> 0.08331079 | H15: =IFERROR('0. Database'!I30/'0. Database'!I21,"") -> 0.092060516 | I15: =IFERROR('0. Database'!J30/'0. Database'!J21,"") -> 0.080344192 | ... S15: =IFERROR('0. Database'!T30/'0. Database'!T21,"") -> 0.067685424
A16: GOOGL | B16: =IFERROR('0. Database'!C45/'0. Database'!C36,"") -> 0.20220105 | C16: =IFERROR('0. Database'!D45/'0. Database'!D36,"") -> 0.17140649 | D16: =IFERROR('0. Database'!E45/'0. Database'!E36,"") -> 0.21221779 | E16: =IFERROR('0. Database'!F45/'0. Database'!F36,"") -> 0.28639002 | F16: =IFERROR('0. Database'!G45/'0. Database'!G36,"") -> 0.2156601 | G16: =IFERROR('0. Database'!H45/'0. Database'!H36,"") -> 0.16687741 | H16: =IFERROR('0. Database'!I45/'0. Database'!I36,"") -> 0.1913541 | I16: =IFERROR('0. Database'!J45/'0. Database'!J36,"") -> 0.23472144 | ... S16: =IFERROR('0. Database'!T45/'0. Database'!T36,"") -> 0.19131372
A17: META | B17: =IFERROR('0. Database'!C62/'0. Database'!C53,"") -> 0.36331301 | C17: =IFERROR('0. Database'!D62/'0. Database'!D53,"") -> 0.29494625 | D17: =IFERROR('0. Database'!E62/'0. Database'!E53,"") -> 0.33937636 | E17: =IFERROR('0. Database'!F62/'0. Database'!F53,"") -> 0.41862653 | F17: =IFERROR('0. Database'!G62/'0. Database'!G53,"") -> 0.43007896 | G17: =IFERROR('0. Database'!H62/'0. Database'!H53,"") -> 0.27506358 | H17: =IFERROR('0. Database'!I62/'0. Database'!I53,"") -> 0.30002192 | I17: =IFERROR('0. Database'!J62/'0. Database'!J53,"") -> 0.27489938 | ... S17: =IFERROR('0. Database'!T62/'0. Database'!T53,"") -> 0.2322224
A18: ORCL | B18: =IFERROR('0. Database'!C80/'0. Database'!C71,"") -> 0.36440018 | C18: =IFERROR('0. Database'!D80/'0. Database'!D71,"") -> 0.37438977 | D18: =IFERROR('0. Database'!E80/'0. Database'!E71,"") -> 0.33840483 | E18: =IFERROR('0. Database'!F80/'0. Database'!F71,"") -> 0.33383706 | F18: =IFERROR('0. Database'!G80/'0. Database'!G71,"") -> 0.31937518 | G18: =IFERROR('0. Database'!H80/'0. Database'!H71,"") -> 0.34617433 | H18: =IFERROR('0. Database'!I80/'0. Database'!I71,"") -> 0.32614801 | I18: =IFERROR('0. Database'!J80/'0. Database'!J71,"") -> 0.29624037 | ... S18: =IFERROR('0. Database'!T80/'0. Database'!T71,"") -> 0.099723812
A21: Capex ($mm)
B22: 2013 | C22: 2014 | D22: 2015 | E22: 2016 | F22: 2017 | G22: 2018 | H22: 2019 | I22: 2020 | J22: 2021 | K22: 2022 | L22: 2023 | M22: 2024 | N22: 2025 | O22: 2026 | P22: 2027 | Q22: 2028 | R22: 2029 | S22: 2030
A23: MSFT | B23: ='0. Database'!C12 -> 4257 | C23: ='0. Database'!D12 -> 5485 | D23: ='0. Database'!E12 -> 5944 | E23: ='0. Database'!F12 -> 8932 | F23: ='0. Database'!G12 -> 10200 | G23: ='0. Database'!H12 -> 13600 | H23: ='0. Database'!I12 -> 16900 | I23: ='0. Database'!J12 -> 19000 | ... S23: ='0. Database'!T12 -> 304616.04
A24: AMZN | B24: ='0. Database'!C28 -> 3443 | C24: ='0. Database'!D28 -> 4892 | D24: ='0. Database'!E28 -> 4588 | E24: ='0. Database'!F28 -> 6736 | F24: ='0. Database'!G28 -> 10057 | G24: ='0. Database'!H28 -> 11322 | H24: ='0. Database'!I28 -> 12690 | I24: ='0. Database'!J28 -> 35046 | ... S24: ='0. Database'!T28 -> 312722.81
A25: GOOGL | B25: ='0. Database'!C43 -> 7358 | C25: ='0. Database'!D43 -> 10959 | D25: ='0. Database'!E43 -> 9915 | E25: ='0. Database'!F43 -> 10183 | F25: ='0. Database'!G43 -> 13184 | G25: ='0. Database'!H43 -> 25139 | H25: ='0. Database'!I43 -> 23548 | I25: ='0. Database'!J43 -> 22281 | ... S25: ='0. Database'!T43 -> 314500.02
A26: META | B26: ='0. Database'!C60 -> 1362 | C26: ='0. Database'!D60 -> 1831 | D26: ='0. Database'!E60 -> 2523 | E26: ='0. Database'!F60 -> 4491 | F26: ='0. Database'!G60 -> 6732 | G26: ='0. Database'!H60 -> 13980 | H26: ='0. Database'!I60 -> 15102 | I26: ='0. Database'!J60 -> 15115 | ... S26: ='0. Database'!T60 -> 208540.35
A27: ORCL | B27: ='0. Database'!C78 -> 650 | C27: ='0. Database'!D78 -> 580 | D27: ='0. Database'!E78 -> 1391 | E27: ='0. Database'!F78 -> 1189 | F27: ='0. Database'!G78 -> 2021 | G27: ='0. Database'!H78 -> 1736 | H27: ='0. Database'!I78 -> 1660 | I27: ='0. Database'!J78 -> 1564 | ... S27: ='0. Database'!T78 -> 66459.86
A30: Rev YoY %
B31: 2013 | C31: 2014 | D31: 2015 | E31: 2016 | F31: 2017 | G31: 2018 | H31: 2019 | I31: 2020 | J31: 2021 | K31: 2022 | L31: 2023 | M31: 2024 | N31: 2025 | O31: 2026 | P31: 2027 | Q31: 2028 | R31: 2029 | S31: 2030
A32: MSFT | C32: =IFERROR('0. Database'!D5/'0. Database'!C5-1,"") -> 0.1154029 | D32: =IFERROR('0. Database'!E5/'0. Database'!D5-1,"") -> 0.077700874 | E32: =IFERROR('0. Database'!F5/'0. Database'!E5-1,"") -> -0.088266724 | F32: =IFERROR('0. Database'!G5/'0. Database'!F5-1,"") -> 0.13186826 | G32: =IFERROR('0. Database'!H5/'0. Database'!G5-1,"") -> 0.14278614 | H32: =IFERROR('0. Database'!I5/'0. Database'!H5-1,"") -> 0.1402954 | I32: =IFERROR('0. Database'!J5/'0. Database'!I5-1,"") -> 0.13645574 | J32: =IFERROR('0. Database'!K5/'0. Database'!J5-1,"") -> 0.17531727 | ... S32: =IFERROR('0. Database'!T5/'0. Database'!S5-1,"") -> 0.17889742
A33: AMZN | C33: =IFERROR('0. Database'!D21/'0. Database'!C21-1,"") -> 0.19522921 | D33: =IFERROR('0. Database'!E21/'0. Database'!D21-1,"") -> 0.20247808 | E33: =IFERROR('0. Database'!F21/'0. Database'!E21-1,"") -> 0.27082815 | F33: =IFERROR('0. Database'!G21/'0. Database'!F21-1,"") -> 0.30796326 | G33: =IFERROR('0. Database'!H21/'0. Database'!G21-1,"") -> 0.30933962 | H33: =IFERROR('0. Database'!I21/'0. Database'!H21-1,"") -> 0.20454126 | I33: =IFERROR('0. Database'!J21/'0. Database'!I21-1,"") -> 0.37623431 | J33: =IFERROR('0. Database'!K21/'0. Database'!J21-1,"") -> 0.21695367 | ... S33: =IFERROR('0. Database'!T21/'0. Database'!S21-1,"") -> 0.10336905
A34: GOOGL | C34: =IFERROR('0. Database'!D36/'0. Database'!C36-1,"") -> 0.18880023 | D34: =IFERROR('0. Database'!E36/'0. Database'!D36-1,"") -> 0.13617975 | E34: =IFERROR('0. Database'!F36/'0. Database'!E36-1,"") -> 0.20380322 | F34: =IFERROR('0. Database'!G36/'0. Database'!F36-1,"") -> 0.2280109 | G34: =IFERROR('0. Database'!H36/'0. Database'!G36-1,"") -> 0.23421587 | H34: =IFERROR('0. Database'!I36/'0. Database'!H36-1,"") -> 0.1830009 | I34: =IFERROR('0. Database'!J36/'0. Database'!I36-1,"") -> 0.12770532 | J34: =IFERROR('0. Database'!K36/'0. Database'!J36-1,"") -> 0.41150076 | ... S34: =IFERROR('0. Database'!T36/'0. Database'!S36-1,"") -> 0.13075076
A35: META | C35: =IFERROR('0. Database'!D53/'0. Database'!C53-1,"") -> 0.5835874 | D35: =IFERROR('0. Database'!E53/'0. Database'!D53-1,"") -> 0.43807155 | E35: =IFERROR('0. Database'!F53/'0. Database'!E53-1,"") -> 0.54169688 | F35: =IFERROR('0. Database'!G53/'0. Database'!F53-1,"") -> 0.47090962 | G35: =IFERROR('0. Database'!H53/'0. Database'!G53-1,"") -> 0.37352717 | H35: =IFERROR('0. Database'!I53/'0. Database'!H53-1,"") -> 0.26610015 | I35: =IFERROR('0. Database'!J53/'0. Database'!I53-1,"") -> 0.21598665 | J35: =IFERROR('0. Database'!K53/'0. Database'!J53-1,"") -> 0.37180979 | ... S35: =IFERROR('0. Database'!T53/'0. Database'!S53-1,"") -> 0.11989806
A36: ORCL | C36: =IFERROR('0. Database'!D71/'0. Database'!C71-1,"") -> 0.028239336 | D36: =IFERROR('0. Database'!E71/'0. Database'!D71-1,"") -> -0.0013575251 | E36: =IFERROR('0. Database'!F71/'0. Database'!E71-1,"") -> -0.031265522 | F36: =IFERROR('0. Database'!G71/'0. Database'!F71-1,"") -> 0.022721753 | G36: =IFERROR('0. Database'!H71/'0. Database'!G71-1,"") -> 0.04042323 | H36: =IFERROR('0. Database'!I71/'0. Database'!H71-1,"") -> 0.0023839111 | I36: =IFERROR('0. Database'!J71/'0. Database'!I71-1,"") -> -0.0114358 | J36: =IFERROR('0. Database'!K71/'0. Database'!J71-1,"") -> 0.036035114 | ... S36: =IFERROR('0. Database'!T71/'0. Database'!S71-1,"") -> 0.12326264
A39: OpMargin %
B40: 2013 | C40: 2014 | D40: 2015 | E40: 2016 | F40: 2017 | G40: 2018 | H40: 2019 | I40: 2020 | J40: 2021 | K40: 2022 | L40: 2023 | M40: 2024 | N40: 2025 | O40: 2026 | P40: 2027 | Q40: 2028 | R40: 2029 | S40: 2030
A41: MSFT | B41: =IFERROR('0. Database'!C6/'0. Database'!C5,"") -> 0.34379375 | C41: =IFERROR('0. Database'!D6/'0. Database'!D5,"") -> 0.31968261 | D41: =IFERROR('0. Database'!E6/'0. Database'!E5,"") -> 0.19406925 | E41: =IFERROR('0. Database'!F6/'0. Database'!F5,"") -> 0.23654477 | F41: =IFERROR('0. Database'!G6/'0. Database'!G5,"") -> 0.30055607 | G41: =IFERROR('0. Database'!H6/'0. Database'!H5,"") -> 0.31766945 | H41: =IFERROR('0. Database'!I6/'0. Database'!I5,"") -> 0.3413698 | I41: =IFERROR('0. Database'!J6/'0. Database'!J5,"") -> 0.37030381 | ... S41: =IFERROR('0. Database'!T6/'0. Database'!T5,"") -> 0.487821
A42: AMZN | B42: =IFERROR('0. Database'!C22/'0. Database'!C21,"") -> 0.010006313 | C42: =IFERROR('0. Database'!D22/'0. Database'!D21,"") -> 0.0020047557 | D42: =IFERROR('0. Database'!E22/'0. Database'!E21,"") -> 0.020864134 | E42: =IFERROR('0. Database'!F22/'0. Database'!F21,"") -> 0.030782354 | F42: =IFERROR('0. Database'!G22/'0. Database'!G21,"") -> 0.023090416 | G42: =IFERROR('0. Database'!H22/'0. Database'!H21,"") -> 0.053330585 | H42: =IFERROR('0. Database'!I22/'0. Database'!I21,"") -> 0.051831942 | I42: =IFERROR('0. Database'!J22/'0. Database'!J21,"") -> 0.059314 | ... S42: =IFERROR('0. Database'!T22/'0. Database'!T21,"") -> 0.2026806
A43: GOOGL | B43: =IFERROR('0. Database'!C37/'0. Database'!C36,"") -> 0.27743655 | C43: =IFERROR('0. Database'!D37/'0. Database'!D36,"") -> 0.24993561 | D43: =IFERROR('0. Database'!E37/'0. Database'!E36,"") -> 0.2581712 | E43: =IFERROR('0. Database'!F37/'0. Database'!F36,"") -> 0.26271712 | F43: =IFERROR('0. Database'!G37/'0. Database'!G36,"") -> 0.23585765 | G43: =IFERROR('0. Database'!H37/'0. Database'!H36,"") -> 0.19699749 | H43: =IFERROR('0. Database'!I37/'0. Database'!I36,"") -> 0.21148915 | I43: =IFERROR('0. Database'!J37/'0. Database'!J36,"") -> 0.22585152 | ... S43: =IFERROR('0. Database'!T37/'0. Database'!T36,"") -> 0.36702057
A44: META | B44: =IFERROR('0. Database'!C54/'0. Database'!C53,"") -> 0.35619919 | C44: =IFERROR('0. Database'!D54/'0. Database'!D53,"") -> 0.40067383 | D44: =IFERROR('0. Database'!E54/'0. Database'!E53,"") -> 0.34724159 | E44: =IFERROR('0. Database'!F54/'0. Database'!F53,"") -> 0.44963456 | F44: =IFERROR('0. Database'!G54/'0. Database'!G53,"") -> 0.4969375 | G44: =IFERROR('0. Database'!H54/'0. Database'!H53,"") -> 0.44616569 | H44: =IFERROR('0. Database'!I54/'0. Database'!I53,"") -> 0.33927422 | I44: =IFERROR('0. Database'!J54/'0. Database'!J53,"") -> 0.3800456 | ... S44: =IFERROR('0. Database'!T54/'0. Database'!T53,"") -> 0.31305779
A45: ORCL | B45: =IFERROR('0. Database'!C72/'0. Database'!C71,"") -> 0.3941696 | C45: =IFERROR('0. Database'!D72/'0. Database'!D71,"") -> 0.38527607 | D45: =IFERROR('0. Database'!E72/'0. Database'!E71,"") -> 0.36258594 | E45: =IFERROR('0. Database'!F72/'0. Database'!F71,"") -> 0.34012467 | F45: =IFERROR('0. Database'!G72/'0. Database'!G71,"") -> 0.33536505 | G45: =IFERROR('0. Database'!H72/'0. Database'!H71,"") -> 0.33638508 | H45: =IFERROR('0. Database'!I72/'0. Database'!I71,"") -> 0.34244149 | I45: =IFERROR('0. Database'!J72/'0. Database'!J71,"") -> 0.3556676 | ... S45: =IFERROR('0. Database'!T72/'0. Database'!T71,"") -> 0.31232139
A48: D&A/Rev %
B49: 2013 | C49: 2014 | D49: 2015 | E49: 2016 | F49: 2017 | G49: 2018 | H49: 2019 | I49: 2020 | J49: 2021 | K49: 2022 | L49: 2023 | M49: 2024 | N49: 2025 | O49: 2026 | P49: 2027 | Q49: 2028 | R49: 2029 | S49: 2030
A50: MSFT | B50: =IFERROR('0. Database'!C11/'0. Database'!C5,"") -> 0.042890724 | C50: =IFERROR('0. Database'!D11/'0. Database'!D5,"") -> 0.048886944 | D50: =IFERROR('0. Database'!E11/'0. Database'!E5,"") -> 0.057704638 | E50: =IFERROR('0. Database'!F11/'0. Database'!F5,"") -> 0.068893577 | F50: =IFERROR('0. Database'!G11/'0. Database'!G5,"") -> 0.080769589 | G50: =IFERROR('0. Database'!H11/'0. Database'!H5,"") -> 0.089706415 | H50: =IFERROR('0. Database'!I11/'0. Database'!I5,"") -> 0.092178349 | I50: =IFERROR('0. Database'!J11/'0. Database'!J5,"") -> 0.086004965 | ... S50: =IFERROR('0. Database'!T11/'0. Database'!T5,"") -> 0.25619883
A51: AMZN | B51: =IFERROR('0. Database'!C27/'0. Database'!C21,"") -> 0.043691994 | C51: =IFERROR('0. Database'!D27/'0. Database'!D21,"") -> 0.053321557 | D51: =IFERROR('0. Database'!E27/'0. Database'!E21,"") -> 0.058697314 | E51: =IFERROR('0. Database'!F27/'0. Database'!F21,"") -> 0.059689529 | F51: =IFERROR('0. Database'!G27/'0. Database'!G21,"") -> 0.064531726 | G51: =IFERROR('0. Database'!H27/'0. Database'!H21,"") -> 0.065873149 | H51: =IFERROR('0. Database'!I27/'0. Database'!I21,"") -> 0.077673052 | I51: =IFERROR('0. Database'!J27/'0. Database'!J21,"") -> 0.065406254 | ... S51: =IFERROR('0. Database'!T27/'0. Database'!T21,"") -> 0.13440276
A52: GOOGL | B52: =IFERROR('0. Database'!C42/'0. Database'!C36,"") -> 0.05009096 | C52: =IFERROR('0. Database'!D42/'0. Database'!D36,"") -> 0.053377979 | D52: =IFERROR('0. Database'!E42/'0. Database'!E36,"") -> 0.055101415 | E52: =IFERROR('0. Database'!F42/'0. Database'!F36,"") -> 0.058345888 | F52: =IFERROR('0. Database'!G42/'0. Database'!G36,"") -> 0.055053899 | G52: =IFERROR('0. Database'!H42/'0. Database'!H36,"") -> 0.059670075 | H52: =IFERROR('0. Database'!I42/'0. Database'!I36,"") -> 0.067071551 | I52: =IFERROR('0. Database'!J42/'0. Database'!J36,"") -> 0.070701869 | ... S52: =IFERROR('0. Database'!T42/'0. Database'!T36,"") -> 0.16938867
A53: META | B53: =IFERROR('0. Database'!C59/'0. Database'!C53,"") -> 0.12842988 | C53: =IFERROR('0. Database'!D59/'0. Database'!D53,"") -> 0.099711215 | D53: =IFERROR('0. Database'!E59/'0. Database'!E53,"") -> 0.10849557 | E53: =IFERROR('0. Database'!F59/'0. Database'!F53,"") -> 0.084738404 | F53: =IFERROR('0. Database'!G59/'0. Database'!G53,"") -> 0.074410253 | G53: =IFERROR('0. Database'!H59/'0. Database'!H53,"") -> 0.077277123 | H53: =IFERROR('0. Database'!I59/'0. Database'!I53,"") -> 0.081206283 | I53: =IFERROR('0. Database'!J59/'0. Database'!J53,"") -> 0.079822255 | ... S53: =IFERROR('0. Database'!T59/'0. Database'!T53,"") -> 0.2651009
A54: ORCL | B54: =IFERROR('0. Database'!C77/'0. Database'!C71,"") -> 0.014656538 | C54: =IFERROR('0. Database'!D77/'0. Database'!D71,"") -> 0.015872601 | D54: =IFERROR('0. Database'!E77/'0. Database'!E71,"") -> 0.018612919 | E54: =IFERROR('0. Database'!F77/'0. Database'!F71,"") -> 0.023504331 | F54: =IFERROR('0. Database'!G77/'0. Database'!G71,"") -> 0.02638592 | G54: =IFERROR('0. Database'!H77/'0. Database'!H71,"") -> 0.029545282 | H54: =IFERROR('0. Database'!I77/'0. Database'!I71,"") -> 0.031119545 | I54: =IFERROR('0. Database'!J77/'0. Database'!J71,"") -> 0.035369693 | ... S54: =IFERROR('0. Database'!T77/'0. Database'!T71,"") -> 0.26
