Workbook

Sheet 0. Database
A1: Centralized Database (USD mm except EPS/shares) — Blue = input
A3: Ticker | B3: Metric | C3: 2013A | D3: 2014A | E3: 2015A | F3: 2016A | G3: 2017A | H3: 2018A | I3: 2019A | J3: 2020A | K3: 2021A | L3: 2022A | M3: 2023A | N3: 2024A | O3: 2025E | P3: 2026E | Q3: 2027E | R3: 2028E | S3: 2029E | T3: 2030E
A4: MSFT (FY(Jun))
A5: MSFT | B5: Revenue | C5: 77849 | D5: 86833 | E5: 93580 | F5: 85320 | G5: 96571 | H5: 110360 | I5: 125843 | J5: 143015 | K5: 168088 | L5: 198270 | M5: 211915 | N5: 245122 | O5: 281724 | P5: 329440.24 | Q5: 387103.71 | R5: 463474.17 | S5: 553714.52 | T5: 652772.62
A6: MSFT | B6: Operating Income | C6: 26764 | D6: 27759 | E6: 18161 | F6: 20182 | G6: 29025 | H6: 35058 | I6: 42959 | J6: 52959 | K6: 69916 | L6: 83383 | M6: 88523 | N6: 109433 | O6: 128528 | P6: 153454.1 | Q6: 179274.53 | R6: 217551.82 | S6: 266239.28 | T6: 318436.19
A7: MSFT | B7: Net Income | C7: 21863 | D7: 22074 | E7: 12193 | F7: 16798 | G7: 25489 | H7: 16571 | I7: 39240 | J7: 44281 | K7: 61271 | L7: 72738 | M7: 72361 | N7: 88136 | O7: 101832 | P7: 129372.86 | Q7: 144971.56 | R7: 175683.92 | S7: 215472.22 | T7: 258948.36
A8: MSFT | B8: EPS | C8: 2.63 | D8: 2.66 | E8: 2.59 | F8: 2.79 | G8: 3.29 | H8: 3.88 | I8: 4.75 | J8: 5.76 | K8: 7.97 | L8: 9.21 | M8: 9.81 | N8: 11.8 | O8: 13.91 | P8: 16.75 | Q8: 19.47 | R8: 23.61 | S8: 28.97 | T8: 34.82
A9: MSFT | B9: Diluted Shares (mm) | C9: 8452.25 | D9: 8385.25 | E9: 8254 | F9: 8012.25 | G9: 7831.25 | H9: 7792.25 | I9: 7752 | J9: 7681.5 | K9: 7607.75 | L9: 7540.5 | M9: 7472.25 | N9: 7468.5 | O9: 7467.75 | P9: 7453.97 | Q9: 7446.49 | R9: 7440.67 | S9: 7436.61 | T9: 7436.22
A10: MSFT | B10: SBC | C10: 2406 | D10: 2446 | E10: 2574 | F10: 2668 | G10: 3266 | H10: 3940 | I10: 4652 | J10: 5289 | K10: 6118 | L10: 7502 | M10: 9611 | N10: 10734 | O10: 11974 | P10: 12189 | Q10: 10478.4 | R10: 11434.24 | S10: 12826.56 | T10: 14871.62
A11: MSFT | B11: D&A | C11: 3339 | D11: 4245 | E11: 5400 | F11: 5878 | G11: 7800 | H11: 9900 | I11: 11600 | J11: 12300 | K11: 10900 | L11: 14600 | M11: 13500 | N11: 20000 | O11: 28000 | P11: 39638.96 | Q11: 62441.96 | R11: 94995.43 | S11: 131504.45 | T11: 167239.58
A12: MSFT | B12: Capex | C12: 4257 | D12: 5485 | E12: 5944 | F12: 8932 | G12: 10200 | H12: 13600 | I12: 16900 | J12: 19000 | K12: 24200 | L12: 29200 | M12: 31900 | N12: 55700 | O12: 88200 | P12: 145871.3 | Q12: 245263.45 | R12: 286760.35 | S12: 300210.91 | T12: 304616.04
A13: MSFT | B13: CFO | C13: 28833 | D13: 32231 | E13: 29080 | F13: 33325 | G13: 39507 | H13: 43884 | I13: 52185 | J13: 60675 | K13: 76740 | L13: 89035 | M13: 87582 | N13: 118548 | O13: 136162 | P13: 174558.18 | Q13: 232097.78 | R13: 294570.35 | S13: 359672.36 | T13: 438548.9
A14: MSFT | B14: FCF | C14: 24576 | D14: 26746 | E14: 23136 | F14: 24393 | G14: 29307 | H14: 30284 | I14: 35285 | J14: 41675 | K14: 52540 | L14: 59835 | M14: 55682 | N14: 62848 | O14: 47962 | P14: 28686.88 | Q14: -13165.67 | R14: 7810 | S14: 59461.45 | T14: 133932.86
A15: MSFT | B15: Buybacks | C15: 5360 | D15: 7316 | E15: 14443 | F15: 15969 | G15: 11788 | H15: 10721 | I15: 19543 | J15: 22968 | K15: 27385 | L15: 32696 | M15: 22245 | N15: 17254 | O15: 18420 | P15: 22499.7 | Q15: 19070.28 | R15: 19500.41 | S15: 20126.95 | T15: 21047.23
A16: MSFT | B16: Intell Cloud | C16: 0 | D16: 0 | E16: 0 | F16: 0 | G16: 0 | H16: 0 | I16: 0 | J16: 0 | K16: 0 | L16: 0 | M16: 72314 | N16: 87464 | O16: 106265 | P16: 136688.31 | Q16: 180358.14 | R16: 235873.55 | S16: 304531.45 | T16: 384276.13
... A18: MSFT | B18: Useful Life(yr) | C18: 3.16 | D18: 2.69 | E18: 2.81 | F18: 2.83 | G18: 2.71 | H18: 2.73 | I18: 2.74 | J18: 3.08 | K18: 4.33 | L18: 4.12 | M18: 6.1 | N18: 5.59 | O18: 5.26 | P18: 4.89 | Q18: 4.36 | R18: 4.38 | S18: 4.6 | T18: 4.7
A20: AMZN (CY)
A21: AMZN | B21: Revenue | C21: 74453 | D21: 88988.4 | E21: 107006.6 | F21: 135987 | G21: 177866 | H21: 232887 | I21: 280522 | J21: 386064 | K21: 469822 | L21: 513983 | M21: 574785 | N21: 637959 | O21: 716924 | P21: 827599.51 | Q21: 946630.91 | R21: 1063340.6 | S21: 1183117.7 | T21: 1305415.5
A22: AMZN | B22: Operating Income | C22: 745 | D22: 178.4 | E22: 2232.6 | F22: 4186 | G22: 4107 | H22: 12420 | I22: 14540 | J22: 22899 | K22: 24879 | L22: 12248 | M22: 36852 | N22: 68593 | O22: 79975 | P22: 109001.86 | Q22: 146127.4 | R22: 183469.22 | S22: 223208.87 | T22: 264582.39
A23: AMZN | B23: Net Income | C23: 273 | D23: -240.6 | E23: 596.1 | F23: 2371 | G23: 3033 | H23: 10073 | I23: 11588 | J23: 21331 | K23: 33364 | L23: -2722 | M23: 30425 | N23: 59248 | O23: 77670 | P23: 98333.72 | Q23: 116218.4 | R23: 145016.4 | S23: 177176.2 | T23: 211925.99
A24: AMZN | B24: EPS | C24: 0.03 | D24: -0.03 | E24: 0.06 | F24: 0.24 | G24: 0.31 | H24: 1.01 | I24: 1.15 | J24: 2.08 | K24: 3.25 | L24: -0.26 | M24: 2.88 | N24: 5.53 | O24: 7.17 | P24: 9.02 | Q24: 10.58 | R24: 13.11 | S24: 15.92 | T24: 18.92
A25: AMZN | B25: Diluted Shares (mm) | C25: 9340 | D25: 9440 | E25: 9620 | F25: 9720 | G25: 9910 | H25: 10020 | I25: 10100 | J25: 10254 | K25: 10274.5 | L25: 10296.5 | M25: 10568.69 | N25: 10721 | O25: 10827 | P25: 10907.55 | Q25: 10986.16 | R25: 11059.39 | S25: 11131.13 | T25: 11201.4
A26: AMZN | B26: SBC | C26: -1134 | D26: -1497 | E26: -2120 | F26: -2975 | G26: -4214 | H26: -5418 | I26: -6864 | J26: -9208 | K26: -12757 | L26: -19621 | M26: -24023 | N26: -22077.4 | O26: -19467 | P26: -18863.32 | Q26: -17920.15 | R26: -18816.16 | S26: -19756.97 | T26: -20744.82
A27: AMZN | B27: D&A | C27: 3253 | D27: 4745 | E27: 6281 | F27: 8117 | G27: 11478 | H27: 15341 | I27: 21789 | J27: 25251 | K27: 34296 | L27: 41461 | M27: 48663 | N27: 52795 | O27: 65756 | P27: 81175.82 | Q27: 90716.93 | R27: 120533.23 | S27: 150703.05 | T27: 175451.44
A28: AMZN | B28: Capex | C28: 3443 | D28: 4892 | E28: 4588 | F28: 6736 | G28: 10057 | H28: 11322 | I28: 12690 | J28: 35046 | K28: 55396 | L28: 58321 | M28: 48133 | N28: 77658 | O28: 128320 | P28: 200104.98 | Q28: 270141.72 | R28: 283648.81 | S28: 297831.25 | T28: 312722.81
A29: AMZN | B29: CFO | C29: 5474 | D29: 6841.4 | E29: 11920.1 | F29: 17271 | G29: 18434 | H29: 30724 | I29: 38515 | J29: 66064 | K29: 46327 | L29: 46752 | M29: 84946 | N29: 115877 | O29: 139514 | P29: 181004.31 | Q29: 224443.7 | R29: 281471.71 | S29: 342814.42 | T29: 401080.41
A30: AMZN | B30: FCF | C30: 2031 | D30: 1949.4 | E30: 7332.1 | F30: 10535 | G30: 8377 | H30: 19402 | I30: 25825 | J30: 31018 | K30: -9069 | L30: -11569 | M30: 36813 | N30: 38219 | O30: 11194 | P30: -19100.67 | Q30: -45698.02 | R30: -2177.1 | S30: 44983.17 | T30: 88357.6
A31: AMZN | B31: Buybacks | C31: 0 | D31: 0 | E31: 0 | F31: 0 | G31: 0 | H31: 0 | I31: 0 | J31: 0 | K31: 0 | L31: 6000 | M31: 0 | N31: 0 | O31: 0 | P31: 0 | Q31: 0 | R31: 0 | S31: 0 | T31: 0
A32: AMZN | B32: AWS Rev | C32: 3107.57 | D32: 4644 | E32: 7880 | F32: 12219 | G32: 17458 | H32: 25656 | I32: 35026 | J32: 45370 | K32: 62202 | L32: 80096 | M32: 90757 | N32: 107556 | O32: 128725 | P32: 171284.9 | Q32: 225587.94 | R32: 274421.67 | S32: 323817.58 | T32: 374009.3
A33: AMZN | B33: AWS OI | D33: 458 | E33: 1508 | F33: 3109 | G33: 4331 | H33: 7296 | I33: 9201 | J33: 13531 | K33: 18532 | L33: 22841 | M33: 24631 | N33: 39834 | O33: 45606 | P33: 61254.41 | Q33: 81248.3 | R33: 100888.47 | S33: 121477.03 | T33: 143111.04
A35: GOOGL (CY)
A36: GOOGL | B36: Revenue | C36: 55519 | D36: 66001 | E36: 74989 | F36: 90272 | G36: 110855 | H36: 136819 | I36: 161857 | J36: 182527 | K36: 257637 | L36: 282836 | M36: 307394 | N36: 350018 | O36: 402836 | P36: 488278.6 | Q36: 591935.74 | R36: 701414.49 | S36: 815276.88 | T36: 921874.95
A37: GOOGL | B37: Operating Income | C37: 15403 | D37: 16496 | E37: 19360 | F37: 23716 | G37: 26146 | H37: 26953 | I37: 34231 | J37: 41224 | K37: 78714 | L37: 74842 | M37: 84293 | N37: 112390 | O37: 129039 | P37: 167318.21 | Q37: 210287.33 | R37: 253779.42 | S37: 298519.7 | T37: 338347.07
A38: GOOGL | B38: Net Income | C38: 12720 | D38: 14136 | E38: 16348 | F38: 19478 | G38: 12662 | H38: 30736 | I38: 34343 | J38: 40269 | K38: 76033 | L38: 59972 | M38: 73795 | N38: 100118 | O38: 132170 | P38: 168543.28 | Q38: 174626.97 | R38: 210753.44 | S38: 249488.6 | T38: 285975.76
A39: GOOGL | B39: EPS | C39: 0.94 | D39: 1.03 | E39: 1.18 | F39: 1.39 | G39: 0.9 | H39: 2.19 | I39: 2.46 | J39: 2.93 | K39: 5.61 | L39: 4.56 | M39: 5.8 | N39: 8.04 | O39: 10.81 | P39: 13.73 | Q39: 14.16 | R39: 17.04 | S39: 20.12 | T39: 22.99
A40: GOOGL | B40: Diluted Shares (mm) | C40: 13552.38 | D40: 13741.41 | E40: 13858.6 | F40: 13974.09 | G40: 14071.67 | H40: 14065.69 | I40: 13971.13 | J40: 13740.56 | K40: 13553 | L40: 13159 | M40: 12722 | N40: 12447 | O40: 12230 | P40: 12275.96 | Q40: 12335.53 | R40: 12366.42 | S40: 12399.99 | T40: 12436.85
A41: GOOGL | B41: SBC | C41: -3268 | D41: -4175 | E41: -4903 | F41: -6703 | G41: -7679 | H41: -9353 | I41: -10794 | J41: -12991 | K41: -15376 | L41: -19362 | M41: -22460 | N41: -22785 | O41: -24953 | P41: -27937.33 | Q41: -30032.63 | R41: -31979.73 | S41: -33657.1 | T41: -35339.95
A42: GOOGL | B42: D&A | C42: 2781 | D42: 3523 | E42: 4132 | F42: 5267 | G42: 6103 | H42: 8164 | I42: 10856 | J42: 12905 | K42: 11555 | L42: 15287 | M42: 13326 | N42: 15311 | O42: 21136 | P42: 42874.7 | Q42: 69582.72 | R42: 98340.16 | S42: 127674.93 | T42: 156155.17
A43: GOOGL | B43: Capex | C43: 7358 | D43: 10959 | E43: 9915 | F43: 10183 | G43: 13184 | H43: 25139 | I43: 23548 | J43: 22281 | K43: 24640 | L43: 31485 | M43: 32251 | N43: 52535 | O43: 91447 | P43: 185234.28 | Q43: 259327.99 | R43: 285260.79 | S43: 299523.83 | T43: 314500.02
A44: GOOGL | B44: CFO | C44: 18584 | D44: 22272 | E44: 25829 | F44: 36036 | G44: 37091 | H44: 47971 | I44: 54520 | J44: 65124 | K44: 91652 | L44: 91495 | M44: 101746 | N44: 125299 | O44: 164713 | P44: 211985.47 | Q44: 282346.21 | R44: 352943.8 | S44: 424226.82 | T44: 490867.35
A45: GOOGL | B45: FCF | C45: 11226 | D45: 11313 | E45: 15914 | F45: 25853 | G45: 23907 | H45: 22832 | I45: 30972 | J45: 42843 | K45: 67012 | L45: 60010 | M45: 69495 | N45: 72764 | O45: 73266 | P45: 26751.19 | Q45: 23018.22 | R45: 67683.01 | S45: 124702.99 | T45: 176367.33
A46: GOOGL | B46: Buybacks | C46: 0 | D46: 0 | E46: 1827 | F46: 3693 | G46: 4846 | H46: 9075 | I46: 18396 | J46: 31149 | K46: 50274 | L46: 59296 | M46: 61504 | N46: 62222 | O46: 45709 | P46: 0 | Q46: 20000 | R46: 20000 | S46: 20000 | T46: 15000
A47: GOOGL | B47: Cloud Rev | G47: 4056 | H47: 5838 | I47: 8918 | J47: 13059 | K47: 19206 | L47: 26280 | M47: 33088 | N47: 43229 | O47: 58705 | P47: 99085.93 | Q47: 157303.91 | R47: 220225.47 | S47: 286293.12 | T47: 343551.74
A48: GOOGL | B48: Search Rev | G48: 69811 | H48: 85296 | I48: 98115 | J48: 104062 | K48: 148951 | L48: 162450 | M48: 175033 | N48: 198084 | O48: 224532 | P48: 258723.55 | Q48: 291360.5 | R48: 324483.39 | S48: 358139.29 | T48: 392613.71
A49: GOOGL | B49: YouTube Rev | G49: 8150 | H49: 11115 | I49: 15149 | J49: 19772 | K49: 28845 | L49: 29243 | M49: 31510 | N49: 36147 | O49: 40367 | P49: 43997.73 | Q49: 49277.45 | R49: 54574.78 | S49: 59759.38 | T49: 64838.93
A50: GOOGL | B50: GCloud OI | H50: -4348 | I50: -4645 | J50: -5607 | K50: -2282 | L50: -1922 | M50: 1716 | N50: 6112 | O50: 13910 | P50: 32420.97 | Q50: 57771.82 | R50: 85285.05 | S50: 113733.5 | T50: 138713.29
A52: META (CY)
A53: META | B53: Revenue | C53: 7872 | D53: 12466 | E53: 17927 | F53: 27638 | G53: 40653 | H53: 55838 | I53: 70696.5 | J53: 85966 | K53: 117929 | L53: 116609 | M53: 134901 | N53: 164500 | O53: 200965 | P53: 255175.56 | Q53: 306410.52 | R53: 357336.07 | S53: 407351.97 | T53: 456192.68
A54: META | B54: Operating Income | C54: 2804 | D54: 4994.8 | E54: 6225 | F54: 12427 | G54: 20202 | H54: 24913 | I54: 23985.5 | J54: 32671 | K54: 46753 | L54: 28945 | M54: 46751 | N54: 69380 | O54: 83276 | P54: 90489.79 | Q54: 104437.61 | R54: 118413.08 | S54: 131523.75 | T54: 142814.67
A55: META | B55: Net Income | C55: 1491 | D55: 2924.8 | E55: 3669 | F55: 10187.2 | G55: 15919 | H55: 22112 | I55: 18484.5 | J55: 29145 | K55: 39370 | L55: 23199 | M55: 39097 | N55: 62360 | O55: 60458 | P55: 85782.86 | Q55: 91160.94 | R55: 103452.71 | S55: 115846.5 | T55: 127804.37
A56: META | B56: EPS | C56: 0.59 | D56: 1.1 | E56: 1.28 | F56: 3.48 | G56: 5.39 | H56: 7.66 | I56: 6.44 | J56: 10.08 | K56: 14.07 | L56: 8.79 | M56: 14.87 | N56: 23.99 | O56: 23.49 | P56: 33.28 | Q56: 34.94 | R56: 39.24 | S56: 43.51 | T56: 47.52
A57: META | B57: Diluted Shares (mm) | C57: 2521.75 | D57: 2671 | E57: 2856.75 | F57: 2923.75 | G57: 2954 | H57: 2886 | I57: 2871 | J57: 2890 | K57: 2799 | L57: 2640 | M57: 2630 | N57: 2599 | O57: 2574 | P57: 2577.79 | Q57: 2609.3 | R57: 2636.12 | S57: 2662.83 | T57: 2689.4
A58: META | B58: SBC | C58: -906 | D58: -1837 | E58: -2969 | F58: -3202 | G58: -3723 | H58: -4152 | I58: -4835 | J58: -6536 | K58: -9163 | L58: -11991 | M58: -14027 | N58: -16690 | O58: -20426 | P58: -23722.2 | Q58: -24908.31 | R58: -26153.73 | S58: -27461.41 | T58: -28834.48
A59: META | B59: D&A | C59: 1011 | D59: 1243 | E59: 1945 | F59: 2342 | G59: 3025 | H59: 4315 | I59: 5741 | J59: 6862 | K59: 7966 | L59: 8686 | M59: 11177 | N59: 15498 | O59: 18616 | P59: 35955.99 | Q59: 56602.9 | R59: 78641.85 | S59: 100070.74 | T59: 120937.09
A60: META | B60: Capex | C60: 1362 | D60: 1831 | E60: 2523 | F60: 4491 | G60: 6732 | H60: 13980 | I60: 15102 | J60: 15115 | K60: 18567 | L60: 31186 | M60: 27045 | N60: 37256 | O60: 69691 | P60: 135583.71 | Q60: 165714.44 | R60: 185600.17 | S60: 196736.18 | T60: 208540.35
A61: META | B61: CFO | C61: 4222 | D61: 5507.8 | E61: 8607 | F61: 16061 | G61: 24216 | H61: 29339 | I61: 36312.5 | J61: 38747 | K61: 57683 | L61: 50475 | M61: 71113 | N61: 91328 | O61: 115800 | P61: 180250.64 | Q61: 206102.96 | R61: 243250.01 | S61: 279015.98 | T61: 314478.51
A62: META | B62: FCF | C62: 2860 | D62: 3676.8 | E62: 6084 | F62: 11570 | G62: 17484 | H62: 15359 | I62: 21210.5 | J62: 23632 | K62: 39116 | L62: 19289 | M62: 44068 | N62: 54072 | O62: 46109 | P62: 44666.93 | Q62: 40388.52 | R62: 57649.84 | S62: 82279.8 | T62: 105938.16
A63: META | B63: Buybacks | C63: 0 | D63: 0 | E63: 0 | F63: 0 | G63: 1976 | H63: 12879 | I63: 4201 | J63: 6272 | K63: 44538 | L63: 27956 | M63: 19775 | N63: 30125 | O63: 26248 | P63: 0 | Q63: 6000 | R63: 6000 | S63: 6000 | T63: 6000
A64: META | B64: Ad Rev(META) | C64: 6986 | D64: 11492 | E64: 17080 | F64: 26885 | G64: 39942 | H64: 55012 | I64: 69654.5 | J64: 84169 | K64: 114934 | L64: 113641 | M64: 131948 | N64: 160632 | O64: 196174 | P64: 248664.66 | Q64: 298597.44 | R64: 348271.65 | S64: 397194.59 | T64: 444912.31
A65: META | B65: FOA Rev | I65: 70196 | J65: 84826 | K65: 115655 | L65: 114450 | M65: 133005 | N65: 162354 | O65: 198758 | P65: 252529.81 | Q65: 303235.62 | R65: 353605.56 | S65: 403061.89 | T65: 451366.33
A66: META | B66: FOA OI | I66: 28489 | J66: 39294 | K66: 56947 | L66: 42662 | M66: 62870 | N66: 87109 | O66: 102469 | P66: 109500.79 | Q66: 122498.06 | R66: 135570.51 | S66: 147823.31 | T66: 158299.25
A67: META | B67: RL Rev | I67: 501 | J67: 1139 | K67: 2274 | L67: 2159 | M67: 1896 | N67: 2146 | O67: 2207 | P67: 2645.75 | Q67: 3174.9 | R67: 3730.51 | S67: 4290.08 | T67: 4826.34
A68: META | B68: RL OI | I68: -4503 | J68: -6623 | K68: -10194 | L68: -13717 | M68: -16119 | N68: -17729 | O68: -19193 | P68: -19011 | Q68: -18060.45 | R68: -17157.43 | S68: -16299.56 | T68: -15484.58
A70: ORCL (FY(May))
A71: ORCL | B71: Revenue | C71: 37253 | D71: 38305 | E71: 38253 | F71: 37057 | G71: 37899 | H71: 39431 | I71: 39525 | J71: 39073 | K71: 40481 | L71: 42441 | M71: 49955 | N71: 52961 | O71: 57399 | P71: 67286.75 | Q71: 88782.02 | R71: 125445.05 | S71: 165192.96 | T71: 185555.08
A72: ORCL | B72: Operating Income | C72: 14684 | D72: 14758 | E72: 13870 | F72: 12604 | G72: 12710 | H72: 13264 | I72: 13535 | J72: 13897 | K72: 15214 | L72: 10927 | M72: 13094 | N72: 15354 | O72: 17678 | P72: 19462.44 | Q72: 21128.19 | R72: 36930.86 | S72: 53057.71 | T72: 57952.82
A73: ORCL | B73: Net Income | C73: 10926 | D73: 10955 | E73: 9938 | F73: 8900 | G73: 9334 | H73: 3587 | I73: 11083 | J73: 10135 | K73: 13747 | L73: 6718 | M73: 8504 | N73: 10467 | O73: 12443 | P73: 15820.55 | Q73: 13363.1 | R73: 26776.66 | S73: 39834.82 | T73: 44104.48
A74: ORCL | B74: EPS | C74: 2.26 | D74: 2.38 | E74: 2.21 | F74: 2.07 | G74: 2.21 | H74: 0.85 | I74: 2.97 | J74: 3.08 | K74: 4.55 | L74: 2.41 | M74: 3.07 | N74: 3.71 | O74: 4.34 | P74: 5.43 | Q74: 4.54 | R74: 8.98 | S74: 13.15 | T74: 14.32
A75: ORCL | B75: Diluted Shares (mm) | C75: 4843.75 | D75: 4604.5 | E75: 4502.5 | F75: 4305.5 | G75: 4217 | H75: 4238 | I75: 3732 | J75: 3293.5 | K75: 3022.5 | L75: 2785.5 | M75: 2766.25 | N75: 2823.25 | O75: 2866.25 | P75: 2915.76 | Q75: 2940.66 | R75: 2980.3 | S75: 3028.26 | T75: 3079.57
A76: ORCL | B76: SBC | C76: 755 | D76: 805 | E76: 933 | F76: 1037 | G76: 1350 | H76: 1607 | I76: 1653 | J76: 1590 | K76: 1837 | L76: 2613 | M76: 3547 | N76: 3974 | O76: 4674 | P76: 5069.6 | Q76: 6473.15 | R76: 8609.75 | S76: 10649.61 | T76: 11212.32
A77: ORCL | B77: D&A | C77: 546 | D77: 608 | E77: 712 | F77: 871 | G77: 1000 | H77: 1165 | I77: 1230 | J77: 1382 | K77: 1537 | L77: 1972 | M77: 2526 | N77: 3129 | O77: 3867 | P77: 7501.53 | Q77: 16868.58 | R77: 27597.91 | S77: 39646.31 | T77: 48244.32
A78: ORCL | B78: Capex | C78: 650 | D78: 580 | E78: 1391 | F78: 1189 | G78: 2021 | H78: 1736 | I78: 1660 | J78: 1564 | K78: 2135 | L78: 4511 | M78: 8695 | N78: 6866 | O78: 21215 | P78: 51882 | Q78: 52141.41 | R78: 69869.49 | S78: 81048.61 | T78: 66459.86
A79: ORCL | B79: CFO | C79: 14225 | D79: 14921 | E79: 14336 | F79: 13560 | G79: 14125 | H79: 15386 | I79: 14551 | J79: 13139 | K79: 15888 | L79: 9540 | M79: 17166 | N79: 18673 | O79: 20821 | P79: 25457.17 | Q79: 33694.38 | R79: 50132.95 | S79: 66529.01 | T79: 84964.12
A80: ORCL | B80: FCF | C80: 13575 | D80: 14341 | E80: 12945 | F80: 12371 | G80: 12104 | H80: 13650 | I80: 12891 | J80: 11575 | K80: 13753 | L80: 5029 | M80: 8471 | N80: 11807 | O80: -394 | P80: -26424.83 | Q80: -18447.03 | R80: -19736.54 | S80: -14519.6 | T80: 18504.26
A81: ORCL | B81: Buybacks | C81: 11021 | D81: 9813 | E81: 8087 | F81: 10440 | G81: 3561 | H81: 11347 | I81: 36140 | J81: 19240 | K81: 20934 | L81: 16248 | M81: 1300 | N81: 1202 | O81: 600 | P81: 95 | Q81: 0 | R81: 0 | S81: 0 | T81: 0
A82: ORCL | B82: Cloud Total(ORCL) | C82: 1365 | D82: 1577 | E82: 2094 | F82: 2854 | G82: 4572 | H82: 6189.17 | I82: 6918.19 | J82: 7811.32 | K82: 8945 | L82: 10809 | M82: 15882 | N82: 19775 | O82: 24507 | P82: 34020.24 | Q82: 55591.76 | R82: 92351.27 | S82: 132214.36 | T82: 152708.94
A83: ORCL | B83: IaaS Rev | L83: 2760.74 | M83: 4500 | N83: 6800 | O83: 10234 | P83: 18064.4 | Q83: 37935.24 | R83: 72977.07 | S83: 111105.3 | T83: 129847.66
A84: ORCL | B84: SaaS Rev | L84: 7999.33 | M84: 11400 | N84: 12949 | O84: 14272 | P84: 15955.84 | Q84: 17656.52 | R84: 19374.2 | S84: 21109.07 | T84: 22861.28
A85: ORCL | B85: RPO | I85: 36200 | J85: 37000 | K85: 41300 | L85: 46600 | M85: 67900 | N85: 98000 | O85: 138000
A86: ORCL | B86: OpInc(Adj) | C86: 17612 | D86: 18108 | E86: 17396 | F86: 15785 | G86: 16168 | H86: 17155 | I86: 17384 | J86: 17383 | K86: 19000 | L86: 19592 | M86: 20904 | N86: 23054 | O86: 25034 | P86: 28113.04 | Q86: 28489.16 | R86: 46280.73 | S86: 64368.1 | T86: 69758.92
A87: ORCL | B87: EPS(Adj) | C87: 2.68 | D87: 2.87 | E87: 2.77 | F87: 2.61 | G87: 2.74 | H87: 3.05 | I87: 3.52 | J87: 3.85 | K87: 4.67 | L87: 4.9 | M87: 5.12 | N87: 5.56 | O87: 6.03 | P87: 7.32 | Q87: 6.09 | R87: 10.59 | S87: 14.81 | T87: 15.94

Sheet 1. Summary
B2: AI Capex Cycle: Hyperscaler Deep-Dive (2013-2030)
B3: MSFT | AMZN | GOOGL | META | ORCL + S&P 500 AI EPS Decomposition
B5: SHEETS
B6: 0. Database — 2013-2030 centralized data. Blue=input. All other sheets reference this.
B7: 1. Summary — This page
B8: 2. Revenue — Total rev, YoY%, Cloud/AI proxy. Derived metrics reference SAME sheet cells (black font).
B9: 3. Capex & D&A — Capex, Capex/Rev, D&A, D&A/Rev. Local formulas reference raw data on same sheet.
B10: 4. FCF & Cash — CFO, FCF margin, FCF/NI, Capex/CFO. All ratios use same-sheet references.
B11: 5. EPS & Margins — OpMargin, Net Margin, EPS YoY. Same-sheet referencing pattern.
B12: 6. Burry Sensitivity — GPU life compression on 2026E EPS. Editable tax rate assumptions.
B13: 7. S&P 500 AI EPS Split — AI vs Non-AI EPS decomposition + dual P/E valuation + 4 stress scenarios.
B14: 8. Charts — 6 visualizations (Capex/Rev, FCF Margin, Capex absolute, Rev YoY, OpMargin, D&A/Rev).

Sheet 2. Revenue
A1: Revenue & AI/Cloud Detail (2013-2030E)
A3: A. Total Revenue ($mm)
A4: Company | B4: 2013A | C4: 2014A | D4: 2015A | E4: 2016A | F4: 2017A | G4: 2018A | H4: 2019A | I4: 2020A | J4: 2021A | K4: 2022A | L4: 2023A | M4: 2024A | N4: 2025E | O4: 2026E | P4: 2027E | Q4: 2028E | R4: 2029E | S4: 2030E
A5: MSFT | B5: ='0. Database'!C5 -> 77849 | C5: ='0. Database'!D5 -> 86833 | D5: ='0. Database'!E5 -> 93580 | E5: ='0. Database'!F5 -> 85320 | F5: ='0. Database'!G5 -> 96571 | G5: ='0. Database'!H5 -> 110360 | H5: ='0. Database'!I5 -> 125843 | I5: ='0. Database'!J5 -> 143015 | ... S5: ='0. Database'!T5 -> 652772.62
A6: AMZN | B6: ='0. Database'!C21 -> 74453 | C6: ='0. Database'!D21 -> 88988.4 | D6: ='0. Database'!E21 -> 107006.6 | E6: ='0. Database'!F21 -> 135987 | F6: ='0. Database'!G21 -> 177866 | G6: ='0. Database'!H21 -> 232887 | H6: ='0. Database'!I21 -> 280522 | I6: ='0. Database'!J21 -> 386064 | ... S6: ='0. Database'!T21 -> 1305415.5
A7: GOOGL | B7: ='0. Database'!C36 -> 55519 | C7: ='0. Database'!D36 -> 66001 | D7: ='0. Database'!E36 -> 74989 | E7: ='0. Database'!F36 -> 90272 | F7: ='0. Database'!G36 -> 110855 | G7: ='0. Database'!H36 -> 136819 | H7: ='0. Database'!I36 -> 161857 | I7: ='0. Database'!J36 -> 182527 | ... S7: ='0. Database'!T36 -> 921874.95
A8: META | B8: ='0. Database'!C53 -> 7872 | C8: ='0. Database'!D53 -> 12466 | D8: ='0. Database'!E53 -> 17927 | E8: ='0. Database'!F53 -> 27638 | F8: ='0. Database'!G53 -> 40653 | G8: ='0. Database'!H53 -> 55838 | H8: ='0. Database'!I53 -> 70696.5 | I8: ='0. Database'!J53 -> 85966 | ... S8: ='0. Database'!T53 -> 456192.68
A9: ORCL | B9: ='0. Database'!C71 -> 37253 | C9: ='0. Database'!D71 -> 38305 | D9: ='0. Database'!E71 -> 38253 | E9: ='0. Database'!F71 -> 37057 | F9: ='0. Database'!G71 -> 37899 | G9: ='0. Database'!H71 -> 39431 | H9: ='0. Database'!I71 -> 39525 | I9: ='0. Database'!J71 -> 39073 | ... S9: ='0. Database'!T71 -> 185555.08
A11: C. Cloud / AI Proxy Revenue ($mm)
A12: Company | B12: 2013A | C12: 2014A | D12: 2015A | E12: 2016A | F12: 2017A | G12: 2018A | H12: 2019A | I12: 2020A | J12: 2021A | K12: 2022A | L12: 2023A | M12: 2024A | N12: 2025E | O12: 2026E | P12: 2027E | Q12: 2028E | R12: 2029E | S12: 2030E
A13: MSFT — Azure
A14: AMZN — AWS | B14: ='0. Database'!C32 -> 3107.57 | C14: ='0. Database'!D32 -> 4644 | D14: ='0. Database'!E32 -> 7880 | E14: ='0. Database'!F32 -> 12219 | F14: ='0. Database'!G32 -> 17458 | G14: ='0. Database'!H32 -> 25656 | H14: ='0. Database'!I32 -> 35026 | I14: ='0. Database'!J32 -> 45370 | ... S14: ='0. Database'!T32 -> 374009.3
A15: GOOGL — Cloud | B15: ='0. Database'!C47 -> 0 | C15: ='0. Database'!D47 -> 0 | D15: ='0. Database'!E47 -> 0 | E15: ='0. Database'!F47 -> 0 | F15: ='0. Database'!G47 -> 4056 | G15: ='0. Database'!H47 -> 5838 | H15: ='0. Database'!I47 -> 8918 | I15: ='0. Database'!J47 -> 13059 | ... S15: ='0. Database'!T47 -> 343551.74
A16: META — Advertising | B16: ='0. Database'!C64 -> 6986 | C16: ='0. Database'!D64 -> 11492 | D16: ='0. Database'!E64 -> 17080 | E16: ='0. Database'!F64 -> 26885 | F16: ='0. Database'!G64 -> 39942 | G16: ='0. Database'!H64 -> 55012 | H16: ='0. Database'!I64 -> 69654.5 | I16: ='0. Database'!J64 -> 84169 | ... S16: ='0. Database'!T64 -> 444912.31
A17: ORCL — Cloud Total | B17: ='0. Database'!C82 -> 1365 | C17: ='0. Database'!D82 -> 1577 | D17: ='0. Database'!E82 -> 2094 | E17: ='0. Database'!F82 -> 2854 | F17: ='0. Database'!G82 -> 4572 | G17: ='0. Database'!H82 -> 6189.17 | H17: ='0. Database'!I82 -> 6918.19 | I17: ='0. Database'!J82 -> 7811.32 | ... S17: ='0. Database'!T82 -> 152708.94
A19: B. Revenue YoY %
A20: Company | B20: 2013A | C20: 2014A | D20: 2015A | E20: 2016A | F20: 2017A | G20: 2018A | H20: 2019A | I20: 2020A | J20: 2021A | K20: 2022A | L20: 2023A | M20: 2024A | N20: 2025E | O20: 2026E | P20: 2027E | Q20: 2028E | R20: 2029E | S20: 2030E
A21: MSFT | C21: =IFERROR(C5/B5-1,"") -> 0.1154029 | D21: =IFERROR(D5/C5-1,"") -> 0.077700874 | E21: =IFERROR(E5/D5-1,"") -> -0.088266724 | F21: =IFERROR(F5/E5-1,"") -> 0.13186826 | G21: =IFERROR(G5/F5-1,"") -> 0.14278614 | H21: =IFERROR(H5/G5-1,"") -> 0.1402954 | I21: =IFERROR(I5/H5-1,"") -> 0.13645574 | J21: =IFERROR(J5/I5-1,"") -> 0.17531727 | ... S21: =IFERROR(S5/R5-1,"") -> 0.17889742
A22: AMZN | C22: =IFERROR(C6/B6-1,"") -> 0.19522921 | D22: =IFERROR(D6/C6-1,"") -> 0.20247808 | E22: =IFERROR(E6/D6-1,"") -> 0.27082815 | F22: =IFERROR(F6/E6-1,"") -> 0.30796326 | G22: =IFERROR(G6/F6-1,"") -> 0.30933962 | H22: =IFERROR(H6/G6-1,"") -> 0.20454126 | I22: =IFERROR(I6/H6-1,"") -> 0.37623431 | J22: =IFERROR(J6/I6-1,"") -> 0.21695367 | ... S22: =IFERROR(S6/R6-1,"") -> 0.10336905
A23: GOOGL | C23: =IFERROR(C7/B7-1,"") -> 0.18880023 | D23: =IFERROR(D7/C7-1,"") -> 0.13617975 | E23: =IFERROR(E7/D7-1,"") -> 0.20380322 | F23: =IFERROR(F7/E7-1,"") -> 0.2280109 | G23: =IFERROR(G7/F7-1,"") -> 0.23421587 | H23: =IFERROR(H7/G7-1,"") -> 0.1830009 | I23: =IFERROR(I7/H7-1,"") -> 0.12770532 | J23: =IFERROR(J7/I7-1,"") -> 0.41150076 | ... S23: =IFERROR(S7/R7-1,"") -> 0.13075076
A24: META | C24: =IFERROR(C8/B8-1,"") -> 0.5835874 | D24: =IFERROR(D8/C8-1,"") -> 0.43807155 | E24: =IFERROR(E8/D8-1,"") -> 0.54169688 | F24: =IFERROR(F8/E8-1,"") -> 0.47090962 | G24: =IFERROR(G8/F8-1,"") -> 0.37352717 | H24: =IFERROR(H8/G8-1,"") -> 0.26610015 | I24: =IFERROR(I8/H8-1,"") -> 0.21598665 | J24: =IFERROR(J8/I8-1,"") -> 0.37180979 | ... S24: =IFERROR(S8/R8-1,"") -> 0.11989806
A25: ORCL | C25: =IFERROR(C9/B9-1,"") -> 0.028239336 | D25: =IFERROR(D9/C9-1,"") -> -0.0013575251 | E25: =IFERROR(E9/D9-1,"") -> -0.031265522 | F25: =IFERROR(F9/E9-1,"") -> 0.022721753 | G25: =IFERROR(G9/F9-1,"") -> 0.04042323 | H25: =IFERROR(H9/G9-1,"") -> 0.0023839111 | I25: =IFERROR(I9/H9-1,"") -> -0.0114358 | J25: =IFERROR(J9/I9-1,"") -> 0.036035114 | ... S25: =IFERROR(S9/R9-1,"") -> 0.12326264

Sheet 3. Capex & D&A
A1: Capex & Depreciation (2013-2030E)
A3: A. Capex ($mm)
A4: Company | B4: 2013A | C4: 2014A | D4: 2015A | E4: 2016A | F4: 2017A | G4: 2018A | H4: 2019A | I4: 2020A | J4: 2021A | K4: 2022A | L4: 2023A | M4: 2024A | N4: 2025E | O4: 2026E | P4: 2027E | Q4: 2028E | R4: 2029E | S4: 2030E
A5: MSFT | B5: ='0. Database'!C12 -> 4257 | C5: ='0. Database'!D12 -> 5485 | D5: ='0. Database'!E12 -> 5944 | E5: ='0. Database'!F12 -> 8932 | F5: ='0. Database'!G12 -> 10200 | G5: ='0. Database'!H12 -> 13600 | H5: ='0. Database'!I12 -> 16900 | I5: ='0. Database'!J12 -> 19000 | ... S5: ='0. Database'!T12 -> 304616.04
A6: AMZN | B6: ='0. Database'!C28 -> 3443 | C6: ='0. Database'!D28 -> 4892 | D6: ='0. Database'!E28 -> 4588 | E6: ='0. Database'!F28 -> 6736 | F6: ='0. Database'!G28 -> 10057 | G6: ='0. Database'!H28 -> 11322 | H6: ='0. Database'!I28 -> 12690 | I6: ='0. Database'!J28 -> 35046 | ... S6: ='0. Database'!T28 -> 312722.81
A7: GOOGL | B7: ='0. Database'!C43 -> 7358 | C7: ='0. Database'!D43 -> 10959 | D7: ='0. Database'!E43 -> 9915 | E7: ='0. Database'!F43 -> 10183 | F7: ='0. Database'!G43 -> 13184 | G7: ='0. Database'!H43 -> 25139 | H7: ='0. Database'!I43 -> 23548 | I7: ='0. Database'!J43 -> 22281 | ... S7: ='0. Database'!T43 -> 314500.02
A8: META | B8: ='0. Database'!C60 -> 1362 | C8: ='0. Database'!D60 -> 1831 | D8: ='0. Database'!E60 -> 2523 | E8: ='0. Database'!F60 -> 4491 | F8: ='0. Database'!G60 -> 6732 | G8: ='0. Database'!H60 -> 13980 | H8: ='0. Database'!I60 -> 15102 | I8: ='0. Database'!J60 -> 15115 | ... S8: ='0. Database'!T60 -> 208540.35
A9: ORCL | B9: ='0. Database'!C78 -> 650 | C9: ='0. Database'!D78 -> 580 | D9: ='0. Database'!E78 -> 1391 | E9: ='0. Database'!F78 -> 1189 | F9: ='0. Database'!G78 -> 2021 | G9: ='0. Database'!H78 -> 1736 | H9: ='0. Database'!I78 -> 1660 | I9: ='0. Database'!J78 -> 1564 | ... S9: ='0. Database'!T78 -> 66459.86
A11: D. D&A ($mm)
A12: Company | B12: 2013A | C12: 2014A | D12: 2015A | E12: 2016A | F12: 2017A | G12: 2018A | H12: 2019A | I12: 2020A | J12: 2021A | K12: 2022A | L12: 2023A | M12: 2024A | N12: 2025E | O12: 2026E | P12: 2027E | Q12: 2028E | R12: 2029E | S12: 2030E
A13: MSFT | B13: ='0. Database'!C11 -> 3339 | C13: ='0. Database'!D11 -> 4245 | D13: ='0. Database'!E11 -> 5400 | E13: ='0. Database'!F11 -> 5878 | F13: ='0. Database'!G11 -> 7800 | G13: ='0. Database'!H11 -> 9900 | H13: ='0. Database'!I11 -> 11600 | I13: ='0. Database'!J11 -> 12300 | ... S13: ='0. Database'!T11 -> 167239.58
A14: AMZN | B14: ='0. Database'!C27 -> 3253 | C14: ='0. Database'!D27 -> 4745 | D14: ='0. Database'!E27 -> 6281 | E14: ='0. Database'!F27 -> 8117 | F14: ='0. Database'!G27 -> 11478 | G14: ='0. Database'!H27 -> 15341 | H14: ='0. Database'!I27 -> 21789 | I14: ='0. Database'!J27 -> 25251 | ... S14: ='0. Database'!T27 -> 175451.44
A15: GOOGL | B15: ='0. Database'!C42 -> 2781 | C15: ='0. Database'!D42 -> 3523 | D15: ='0. Database'!E42 -> 4132 | E15: ='0. Database'!F42 -> 5267 | F15: ='0. Database'!G42 -> 6103 | G15: ='0. Database'!H42 -> 8164 | H15: ='0. Database'!I42 -> 10856 | I15: ='0. Database'!J42 -> 12905 | ... S15: ='0. Database'!T42 -> 156155.17
A16: META | B16: ='0. Database'!C59 -> 1011 | C16: ='0. Database'!D59 -> 1243 | D16: ='0. Database'!E59 -> 1945 | E16: ='0. Database'!F59 -> 2342 | F16: ='0. Database'!G59 -> 3025 | G16: ='0. Database'!H59 -> 4315 | H16: ='0. Database'!I59 -> 5741 | I16: ='0. Database'!J59 -> 6862 | ... S16: ='0. Database'!T59 -> 120937.09
A17: ORCL | B17: ='0. Database'!C77 -> 546 | C17: ='0. Database'!D77 -> 608 | D17: ='0. Database'!E77 -> 712 | E17: ='0. Database'!F77 -> 871 | F17: ='0. Database'!G77 -> 1000 | G17: ='0. Database'!H77 -> 1165 | H17: ='0. Database'!I77 -> 1230 | I17: ='0. Database'!J77 -> 1382 | ... S17: ='0. Database'!T77 -> 48244.32
A19: (Revenue — for ratios)
A20: Company | B20: 2013A | C20: 2014A | D20: 2015A | E20: 2016A | F20: 2017A | G20: 2018A | H20: 2019A | I20: 2020A | J20: 2021A | K20: 2022A | L20: 2023A | M20: 2024A | N20: 2025E | O20: 2026E | P20: 2027E | Q20: 2028E | R20: 2029E | S20: 2030E
A21: MSFT | B21: ='0. Database'!C5 -> 77849 | C21: ='0. Database'!D5 -> 86833 | D21: ='0. Database'!E5 -> 93580 | E21: ='0. Database'!F5 -> 85320 | F21: ='0. Database'!G5 -> 96571 | G21: ='0. Database'!H5 -> 110360 | H21: ='0. Database'!I5 -> 125843 | I21: ='0. Database'!J5 -> 143015 | ... S21: ='0. Database'!T5 -> 652772.62
A22: AMZN | B22: ='0. Database'!C21 -> 74453 | C22: ='0. Database'!D21 -> 88988.4 | D22: ='0. Database'!E21 -> 107006.6 | E22: ='0. Database'!F21 -> 135987 | F22: ='0. Database'!G21 -> 177866 | G22: ='0. Database'!H21 -> 232887 | H22: ='0. Database'!I21 -> 280522 | I22: ='0. Database'!J21 -> 386064 | ... S22: ='0. Database'!T21 -> 1305415.5
A23: GOOGL | B23: ='0. Database'!C36 -> 55519 | C23: ='0. Database'!D36 -> 66001 | D23: ='0. Database'!E36 -> 74989 | E23: ='0. Database'!F36 -> 90272 | F23: ='0. Database'!G36 -> 110855 | G23: ='0. Database'!H36 -> 136819 | H23: ='0. Database'!I36 -> 161857 | I23: ='0. Database'!J36 -> 182527 | ... S23: ='0. Database'!T36 -> 921874.95
A24: META | B24: ='0. Database'!C53 -> 7872 | C24: ='0. Database'!D53 -> 12466 | D24: ='0. Database'!E53 -> 17927 | E24: ='0. Database'!F53 -> 27638 | F24: ='0. Database'!G53 -> 40653 | G24: ='0. Database'!H53 -> 55838 | H24: ='0. Database'!I53 -> 70696.5 | I24: ='0. Database'!J53 -> 85966 | ... S24: ='0. Database'!T53 -> 456192.68
A25: ORCL | B25: ='0. Database'!C71 -> 37253 | C25: ='0. Database'!D71 -> 38305 | D25: ='0. Database'!E71 -> 38253 | E25: ='0. Database'!F71 -> 37057 | F25: ='0. Database'!G71 -> 37899 | G25: ='0. Database'!H71 -> 39431 | H25: ='0. Database'!I71 -> 39525 | I25: ='0. Database'!J71 -> 39073 | ... S25: ='0. Database'!T71 -> 185555.08
A27: B. Capex YoY %
A28: Company | B28: 2013A | C28: 2014A | D28: 2015A | E28: 2016A | F28: 2017A | G28: 2018A | H28: 2019A | I28: 2020A | J28: 2021A | K28: 2022A | L28: 2023A | M28: 2024A | N28: 2025E | O28: 2026E | P28: 2027E | Q28: 2028E | R28: 2029E | S28: 2030E
A29: MSFT | C29: =IFERROR(C5/B5-1,"") -> 0.28846606 | D29: =IFERROR(D5/C5-1,"") -> 0.083682771 | E29: =IFERROR(E5/D5-1,"") -> 0.50269179 | F29: =IFERROR(F5/E5-1,"") -> 0.14196149 | G29: =IFERROR(G5/F5-1,"") -> 0.33333333 | H29: =IFERROR(H5/G5-1,"") -> 0.24264706 | I29: =IFERROR(I5/H5-1,"") -> 0.12426036 | J29: =IFERROR(J5/I5-1,"") -> 0.27368421 | ... S29: =IFERROR(S5/R5-1,"") -> 0.014673451
A30: AMZN | C30: =IFERROR(C6/B6-1,"") -> 0.42085391 | D30: =IFERROR(D6/C6-1,"") -> -0.062142273 | E30: =IFERROR(E6/D6-1,"") -> 0.46817786 | F30: =IFERROR(F6/E6-1,"") -> 0.49302257 | G30: =IFERROR(G6/F6-1,"") -> 0.12578304 | H30: =IFERROR(H6/G6-1,"") -> 0.12082671 | I30: =IFERROR(I6/H6-1,"") -> 1.7617021 | J30: =IFERROR(J6/I6-1,"") -> 0.58066541 | ... S30: =IFERROR(S6/R6-1,"") -> 0.049999992
A31: GOOGL | C31: =IFERROR(C7/B7-1,"") -> 0.48939929 | D31: =IFERROR(D7/C7-1,"") -> -0.095264166 | E31: =IFERROR(E7/D7-1,"") -> 0.027029753 | F31: =IFERROR(F7/E7-1,"") -> 0.29470686 | G31: =IFERROR(G7/F7-1,"") -> 0.90678095 | H31: =IFERROR(H7/G7-1,"") -> -0.063288118 | I31: =IFERROR(I7/H7-1,"") -> -0.053804994 | J31: =IFERROR(J7/I7-1,"") -> 0.10587496 | ... S31: =IFERROR(S7/R7-1,"") -> 0.049999995
A32: META | C32: =IFERROR(C8/B8-1,"") -> 0.34434655 | D32: =IFERROR(D8/C8-1,"") -> 0.37793555 | E32: =IFERROR(E8/D8-1,"") -> 0.78002378 | F32: =IFERROR(F8/E8-1,"") -> 0.498998 | G32: =IFERROR(G8/F8-1,"") -> 1.0766488 | H32: =IFERROR(H8/G8-1,"") -> 0.080257511 | I32: =IFERROR(I8/H8-1,"") -> 0.00086081314 | J32: =IFERROR(J8/I8-1,"") -> 0.2283824 | ... S32: =IFERROR(S8/R8-1,"") -> 0.059999996
A33: ORCL | C33: =IFERROR(C9/B9-1,"") -> -0.10769231 | D33: =IFERROR(D9/C9-1,"") -> 1.3982759 | E33: =IFERROR(E9/D9-1,"") -> -0.14521927 | F33: =IFERROR(F9/E9-1,"") -> 0.69974769 | G33: =IFERROR(G9/F9-1,"") -> -0.1410193 | H33: =IFERROR(H9/G9-1,"") -> -0.043778802 | I33: =IFERROR(I9/H9-1,"") -> -0.057831325 | J33: =IFERROR(J9/I9-1,"") -> 0.36508951 | ... S33: =IFERROR(S9/R9-1,"") -> -0.18
A35: C. Capex / Revenue %
A36: Company | B36: 2013A | C36: 2014A | D36: 2015A | E36: 2016A | F36: 2017A | G36: 2018A | H36: 2019A | I36: 2020A | J36: 2021A | K36: 2022A | L36: 2023A | M36: 2024A | N36: 2025E | O36: 2026E | P36: 2027E | Q36: 2028E | R36: 2029E | S36: 2030E
A37: MSFT | B37: =IFERROR(B5/B21,"") -> 0.054682783 | C37: =IFERROR(C5/C21,"") -> 0.063167229 | D37: =IFERROR(D5/D21,"") -> 0.063517846 | E37: =IFERROR(E5/E21,"") -> 0.10468823 | F37: =IFERROR(F5/F21,"") -> 0.10562177 | G37: =IFERROR(G5/G21,"") -> 0.12323306 | H37: =IFERROR(H5/H21,"") -> 0.13429432 | I37: =IFERROR(I5/I21,"") -> 0.1328532 | ... S37: =IFERROR(S5/S21,"") -> 0.46664954
A38: AMZN | B38: =IFERROR(B6/B22,"") -> 0.046243939 | C38: =IFERROR(C6/C22,"") -> 0.054973457 | D38: =IFERROR(D6/D22,"") -> 0.04287586 | E38: =IFERROR(E6/E22,"") -> 0.049534147 | F38: =IFERROR(F6/F22,"") -> 0.056542566 | G38: =IFERROR(G6/G22,"") -> 0.048615852 | H38: =IFERROR(H6/H22,"") -> 0.045237094 | I38: =IFERROR(I6/I22,"") -> 0.090777695 | ... S38: =IFERROR(S6/S22,"") -> 0.23955807
A39: GOOGL | B39: =IFERROR(B7/B23,"") -> 0.13253121 | C39: =IFERROR(C7/C23,"") -> 0.16604294 | D39: =IFERROR(D7/D23,"") -> 0.13221939 | E39: =IFERROR(E7/E23,"") -> 0.11280353 | F39: =IFERROR(F7/F23,"") -> 0.11893013 | G39: =IFERROR(G7/G23,"") -> 0.1837391 | H39: =IFERROR(H7/H23,"") -> 0.14548645 | I39: =IFERROR(I7/I23,"") -> 0.12206961 | ... S39: =IFERROR(S7/S23,"") -> 0.34115258
A40: META | B40: =IFERROR(B8/B24,"") -> 0.17301829 | C40: =IFERROR(C8/C24,"") -> 0.14687951 | D40: =IFERROR(D8/D24,"") -> 0.14073744 | E40: =IFERROR(E8/E24,"") -> 0.16249367 | F40: =IFERROR(F8/F24,"") -> 0.16559663 | G40: =IFERROR(G8/G24,"") -> 0.25036713 | H40: =IFERROR(H8/H24,"") -> 0.21361736 | I40: =IFERROR(I8/I24,"") -> 0.17582533 | ... S40: =IFERROR(S8/S24,"") -> 0.45713217
A41: ORCL | B41: =IFERROR(B9/B25,"") -> 0.017448259 | C41: =IFERROR(C9/C25,"") -> 0.015141626 | D41: =IFERROR(D9/D25,"") -> 0.036363161 | E41: =IFERROR(E9/E25,"") -> 0.032085706 | F41: =IFERROR(F9/F25,"") -> 0.053325945 | G41: =IFERROR(G9/G25,"") -> 0.044026274 | H41: =IFERROR(H9/H25,"") -> 0.041998735 | I41: =IFERROR(I9/I25,"") -> 0.040027641 | ... S41: =IFERROR(S9/S25,"") -> 0.35816783
A43: E. D&A / Revenue %
A44: Company | B44: 2013A | C44: 2014A | D44: 2015A | E44: 2016A | F44: 2017A | G44: 2018A | H44: 2019A | I44: 2020A | J44: 2021A | K44: 2022A | L44: 2023A | M44: 2024A | N44: 2025E | O44: 2026E | P44: 2027E | Q44: 2028E | R44: 2029E | S44: 2030E
A45: MSFT | B45: =IFERROR(B13/B21,"") -> 0.042890724 | C45: =IFERROR(C13/C21,"") -> 0.048886944 | D45: =IFERROR(D13/D21,"") -> 0.057704638 | E45: =IFERROR(E13/E21,"") -> 0.068893577 | F45: =IFERROR(F13/F21,"") -> 0.080769589 | G45: =IFERROR(G13/G21,"") -> 0.089706415 | H45: =IFERROR(H13/H21,"") -> 0.092178349 | I45: =IFERROR(I13/I21,"") -> 0.086004965 | ... S45: =IFERROR(S13/S21,"") -> 0.25619883
A46: AMZN | B46: =IFERROR(B14/B22,"") -> 0.043691994 | C46: =IFERROR(C14/C22,"") -> 0.053321557 | D46: =IFERROR(D14/D22,"") -> 0.058697314 | E46: =IFERROR(E14/E22,"") -> 0.059689529 | F46: =IFERROR(F14/F22,"") -> 0.064531726 | G46: =IFERROR(G14/G22,"") -> 0.065873149 | H46: =IFERROR(H14/H22,"") -> 0.077673052 | I46: =IFERROR(I14/I22,"") -> 0.065406254 | ... S46: =IFERROR(S14/S22,"") -> 0.13440276
A47: GOOGL | B47: =IFERROR(B15/B23,"") -> 0.05009096 | C47: =IFERROR(C15/C23,"") -> 0.053377979 | D47: =IFERROR(D15/D23,"") -> 0.055101415 | E47: =IFERROR(E15/E23,"") -> 0.058345888 | F47: =IFERROR(F15/F23,"") -> 0.055053899 | G47: =IFERROR(G15/G23,"") -> 0.059670075 | H47: =IFERROR(H15/H23,"") -> 0.067071551 | I47: =IFERROR(I15/I23,"") -> 0.070701869 | ... S47: =IFERROR(S15/S23,"") -> 0.16938867
A48: META | B48: =IFERROR(B16/B24,"") -> 0.12842988 | C48: =IFERROR(C16/C24,"") -> 0.099711215 | D48: =IFERROR(D16/D24,"") -> 0.10849557 | E48: =IFERROR(E16/E24,"") -> 0.084738404 | F48: =IFERROR(F16/F24,"") -> 0.074410253 | G48: =IFERROR(G16/G24,"") -> 0.077277123 | H48: =IFERROR(H16/H24,"") -> 0.081206283 | I48: =IFERROR(I16/I24,"") -> 0.079822255 | ... S48: =IFERROR(S16/S24,"") -> 0.2651009
A49: ORCL | B49: =IFERROR(B17/B25,"") -> 0.014656538 | C49: =IFERROR(C17/C25,"") -> 0.015872601 | D49: =IFERROR(D17/D25,"") -> 0.018612919 | E49: =IFERROR(E17/E25,"") -> 0.023504331 | F49: =IFERROR(F17/F25,"") -> 0.02638592 | G49: =IFERROR(G17/G25,"") -> 0.029545282 | H49: =IFERROR(H17/H25,"") -> 0.031119545 | I49: =IFERROR(I17/I25,"") -> 0.035369693 | ... S49: =IFERROR(S17/S25,"") -> 0.26
A51: F. D&A YoY %
A52: Company | B52: 2013A | C52: 2014A | D52: 2015A | E52: 2016A | F52: 2017A | G52: 2018A | H52: 2019A | I52: 2020A | J52: 2021A | K52: 2022A | L52: 2023A | M52: 2024A | N52: 2025E | O52: 2026E | P52: 2027E | Q52: 2028E | R52: 2029E | S52: 2030E
A53: MSFT | C53: =IFERROR(C13/B13-1,"") -> 0.27133872 | D53: =IFERROR(D13/C13-1,"") -> 0.27208481 | E53: =IFERROR(E13/D13-1,"") -> 0.088518519 | F53: =IFERROR(F13/E13-1,"") -> 0.32698197 | G53: =IFERROR(G13/F13-1,"") -> 0.26923077 | H53: =IFERROR(H13/G13-1,"") -> 0.17171717 | I53: =IFERROR(I13/H13-1,"") -> 0.060344828 | J53: =IFERROR(J13/I13-1,"") -> -0.11382114 | ... S53: =IFERROR(S13/R13-1,"") -> 0.27174084
A54: AMZN | C54: =IFERROR(C14/B14-1,"") -> 0.45865355 | D54: =IFERROR(D14/C14-1,"") -> 0.32370917 | E54: =IFERROR(E14/D14-1,"") -> 0.29231014 | F54: =IFERROR(F14/E14-1,"") -> 0.41406924 | G54: =IFERROR(G14/F14-1,"") -> 0.33655689 | H54: =IFERROR(H14/G14-1,"") -> 0.42031158 | I54: =IFERROR(I14/H14-1,"") -> 0.15888751 | J54: =IFERROR(J14/I14-1,"") -> 0.35820364 | ... S54: =IFERROR(S14/R14-1,"") -> 0.16421957
A55: GOOGL | C55: =IFERROR(C15/B15-1,"") -> 0.2668105 | D55: =IFERROR(D15/C15-1,"") -> 0.17286404 | E55: =IFERROR(E15/D15-1,"") -> 0.27468538 | F55: =IFERROR(F15/E15-1,"") -> 0.15872413 | G55: =IFERROR(G15/F15-1,"") -> 0.33770277 | H55: =IFERROR(H15/G15-1,"") -> 0.32974032 | I55: =IFERROR(I15/H15-1,"") -> 0.18874355 | J55: =IFERROR(J15/I15-1,"") -> -0.10461062 | ... S55: =IFERROR(S15/R15-1,"") -> 0.22306838
A56: META | C56: =IFERROR(C16/B16-1,"") -> 0.22947577 | D56: =IFERROR(D16/C16-1,"") -> 0.56476267 | E56: =IFERROR(E16/D16-1,"") -> 0.20411311 | F56: =IFERROR(F16/E16-1,"") -> 0.29163108 | G56: =IFERROR(G16/F16-1,"") -> 0.42644628 | H56: =IFERROR(H16/G16-1,"") -> 0.33047509 | I56: =IFERROR(I16/H16-1,"") -> 0.19526215 | J56: =IFERROR(J16/I16-1,"") -> 0.16088604 | ... S56: =IFERROR(S16/R16-1,"") -> 0.208516
A57: ORCL | C57: =IFERROR(C17/B17-1,"") -> 0.11355311 | D57: =IFERROR(D17/C17-1,"") -> 0.17105263 | E57: =IFERROR(E17/D17-1,"") -> 0.22331461 | F57: =IFERROR(F17/E17-1,"") -> 0.14810563 | G57: =IFERROR(G17/F17-1,"") -> 0.165 | H57: =IFERROR(H17/G17-1,"") -> 0.055793991 | I57: =IFERROR(I17/H17-1,"") -> 0.12357724 | J57: =IFERROR(J17/I17-1,"") -> 0.1121563 | ... S57: =IFERROR(S17/R17-1,"") -> 0.21686785

Sheet 4. FCF & Cash
A1: FCF & Cash Quality (2013-2030E)
A3: A. CFO ($mm)
A4: Company | B4: 2013A | C4: 2014A | D4: 2015A | E4: 2016A | F4: 2017A | G4: 2018A | H4: 2019A | I4: 2020A | J4: 2021A | K4: 2022A | L4: 2023A | M4: 2024A | N4: 2025E | O4: 2026E | P4: 2027E | Q4: 2028E | R4: 2029E | S4: 2030E
A5: MSFT | B5: ='0. Database'!C13 -> 28833 | C5: ='0. Database'!D13 -> 32231 | D5: ='0. Database'!E13 -> 29080 | E5: ='0. Database'!F13 -> 33325 | F5: ='0. Database'!G13 -> 39507 | G5: ='0. Database'!H13 -> 43884 | H5: ='0. Database'!I13 -> 52185 | I5: ='0. Database'!J13 -> 60675 | ... S5: ='0. Database'!T13 -> 438548.9
A6: AMZN | B6: ='0. Database'!C29 -> 5474 | C6: ='0. Database'!D29 -> 6841.4 | D6: ='0. Database'!E29 -> 11920.1 | E6: ='0. Database'!F29 -> 17271 | F6: ='0. Database'!G29 -> 18434 | G6: ='0. Database'!H29 -> 30724 | H6: ='0. Database'!I29 -> 38515 | I6: ='0. Database'!J29 -> 66064 | ... S6: ='0. Database'!T29 -> 401080.41
A7: GOOGL | B7: ='0. Database'!C44 -> 18584 | C7: ='0. Database'!D44 -> 22272 | D7: ='0. Database'!E44 -> 25829 | E7: ='0. Database'!F44 -> 36036 | F7: ='0. Database'!G44 -> 37091 | G7: ='0. Database'!H44 -> 47971 | H7: ='0. Database'!I44 -> 54520 | I7: ='0. Database'!J44 -> 65124 | ... S7: ='0. Database'!T44 -> 490867.35
A8: META | B8: ='0. Database'!C61 -> 4222 | C8: ='0. Database'!D61 -> 5507.8 | D8: ='0. Database'!E61 -> 8607 | E8: ='0. Database'!F61 -> 16061 | F8: ='0. Database'!G61 -> 24216 | G8: ='0. Database'!H61 -> 29339 | H8: ='0. Database'!I61 -> 36312.5 | I8: ='0. Database'!J61 -> 38747 | ... S8: ='0. Database'!T61 -> 314478.51
A9: ORCL | B9: ='0. Database'!C79 -> 14225 | C9: ='0. Database'!D79 -> 14921 | D9: ='0. Database'!E79 -> 14336 | E9: ='0. Database'!F79 -> 13560 | F9: ='0. Database'!G79 -> 14125 | G9: ='0. Database'!H79 -> 15386 | H9: ='0. Database'!I79 -> 14551 | I9: ='0. Database'!J79 -> 13139 | ... S9: ='0. Database'!T79 -> 84964.12
A11: B. FCF ($mm)
A12: Company | B12: 2013A | C12: 2014A | D12: 2015A | E12: 2016A | F12: 2017A | G12: 2018A | H12: 2019A | I12: 2020A | J12: 2021A | K12: 2022A | L12: 2023A | M12: 2024A | N12: 2025E | O12: 2026E | P12: 2027E | Q12: 2028E | R12: 2029E | S12: 2030E
A13: MSFT | B13: ='0. Database'!C14 -> 24576 | C13: ='0. Database'!D14 -> 26746 | D13: ='0. Database'!E14 -> 23136 | E13: ='0. Database'!F14 -> 24393 | F13: ='0. Database'!G14 -> 29307 | G13: ='0. Database'!H14 -> 30284 | H13: ='0. Database'!I14 -> 35285 | I13: ='0. Database'!J14 -> 41675 | ... S13: ='0. Database'!T14 -> 133932.86
A14: AMZN | B14: ='0. Database'!C30 -> 2031 | C14: ='0. Database'!D30 -> 1949.4 | D14: ='0. Database'!E30 -> 7332.1 | E14: ='0. Database'!F30 -> 10535 | F14: ='0. Database'!G30 -> 8377 | G14: ='0. Database'!H30 -> 19402 | H14: ='0. Database'!I30 -> 25825 | I14: ='0. Database'!J30 -> 31018 | ... S14: ='0. Database'!T30 -> 88357.6
A15: GOOGL | B15: ='0. Database'!C45 -> 11226 | C15: ='0. Database'!D45 -> 11313 | D15: ='0. Database'!E45 -> 15914 | E15: ='0. Database'!F45 -> 25853 | F15: ='0. Database'!G45 -> 23907 | G15: ='0. Database'!H45 -> 22832 | H15: ='0. Database'!I45 -> 30972 | I15: ='0. Database'!J45 -> 42843 | ... S15: ='0. Database'!T45 -> 176367.33
A16: META | B16: ='0. Database'!C62 -> 2860 | C16: ='0. Database'!D62 -> 3676.8 | D16: ='0. Database'!E62 -> 6084 | E16: ='0. Database'!F62 -> 11570 | F16: ='0. Database'!G62 -> 17484 | G16: ='0. Database'!H62 -> 15359 | H16: ='0. Database'!I62 -> 21210.5 | I16: ='0. Database'!J62 -> 23632 | ... S16: ='0. Database'!T62 -> 105938.16
A17: ORCL | B17: ='0. Database'!C80 -> 13575 | C17: ='0. Database'!D80 -> 14341 | D17: ='0. Database'!E80 -> 12945 | E17: ='0. Database'!F80 -> 12371 | F17: ='0. Database'!G80 -> 12104 | G17: ='0. Database'!H80 -> 13650 | H17: ='0. Database'!I80 -> 12891 | I17: ='0. Database'!J80 -> 11575 | ... S17: ='0. Database'!T80 -> 18504.26
A19: E. Buybacks ($mm)
A20: Company | B20: 2013A | C20: 2014A | D20: 2015A | E20: 2016A | F20: 2017A | G20: 2018A | H20: 2019A | I20: 2020A | J20: 2021A | K20: 2022A | L20: 2023A | M20: 2024A | N20: 2025E | O20: 2026E | P20: 2027E | Q20: 2028E | R20: 2029E | S20: 2030E
A21: MSFT | B21: ='0. Database'!C15 -> 5360 | C21: ='0. Database'!D15 -> 7316 | D21: ='0. Database'!E15 -> 14443 | E21: ='0. Database'!F15 -> 15969 | F21: ='0. Database'!G15 -> 11788 | G21: ='0. Database'!H15 -> 10721 | H21: ='0. Database'!I15 -> 19543 | I21: ='0. Database'!J15 -> 22968 | ... S21: ='0. Database'!T15 -> 21047.23
A22: AMZN | B22: ='0. Database'!C31 -> 0 | C22: ='0. Database'!D31 -> 0 | D22: ='0. Database'!E31 -> 0 | E22: ='0. Database'!F31 -> 0 | F22: ='0. Database'!G31 -> 0 | G22: ='0. Database'!H31 -> 0 | H22: ='0. Database'!I31 -> 0 | I22: ='0. Database'!J31 -> 0 | ... S22: ='0. Database'!T31 -> 0
A23: GOOGL | B23: ='0. Database'!C46 -> 0 | C23: ='0. Database'!D46 -> 0 | D23: ='0. Database'!E46 -> 1827 | E23: ='0. Database'!F46 -> 3693 | F23: ='0. Database'!G46 -> 4846 | G23: ='0. Database'!H46 -> 9075 | H23: ='0. Database'!I46 -> 18396 | I23: ='0. Database'!J46 -> 31149 | ... S23: ='0. Database'!T46 -> 15000
A24: META | B24: ='0. Database'!C63 -> 0 | C24: ='0. Database'!D63 -> 0 | D24: ='0. Database'!E63 -> 0 | E24: ='0. Database'!F63 -> 0 | F24: ='0. Database'!G63 -> 1976 | G24: ='0. Database'!H63 -> 12879 | H24: ='0. Database'!I63 -> 4201 | I24: ='0. Database'!J63 -> 6272 | ... S24: ='0. Database'!T63 -> 6000
A25: ORCL | B25: ='0. Database'!C81 -> 11021 | C25: ='0. Database'!D81 -> 9813 | D25: ='0. Database'!E81 -> 8087 | E25: ='0. Database'!F81 -> 10440 | F25: ='0. Database'!G81 -> 3561 | G25: ='0. Database'!H81 -> 11347 | H25: ='0. Database'!I81 -> 36140 | I25: ='0. Database'!J81 -> 19240 | ... S25: ='0. Database'!T81 -> 0
A27: (Revenue)
A28: Company | B28: 2013A | C28: 2014A | D28: 2015A | E28: 2016A | F28: 2017A | G28: 2018A | H28: 2019A | I28: 2020A | J28: 2021A | K28: 2022A | L28: 2023A | M28: 2024A | N28: 2025E | O28: 2026E | P28: 2027E | Q28: 2028E | R28: 2029E | S28: 2030E
A29: MSFT | B29: ='0. Database'!C5 -> 77849 | C29: ='0. Database'!D5 -> 86833 | D29: ='0. Database'!E5 -> 93580 | E29: ='0. Database'!F5 -> 85320 | F29: ='0. Database'!G5 -> 96571 | G29: ='0. Database'!H5 -> 110360 | H29: ='0. Database'!I5 -> 125843 | I29: ='0. Database'!J5 -> 143015 | ... S29: ='0. Database'!T5 -> 652772.62
A30: AMZN | B30: ='0. Database'!C21 -> 74453 | C30: ='0. Database'!D21 -> 88988.4 | D30: ='0. Database'!E21 -> 107006.6 | E30: ='0. Database'!F21 -> 135987 | F30: ='0. Database'!G21 -> 177866 | G30: ='0. Database'!H21 -> 232887 | H30: ='0. Database'!I21 -> 280522 | I30: ='0. Database'!J21 -> 386064 | ... S30: ='0. Database'!T21 -> 1305415.5
A31: GOOGL | B31: ='0. Database'!C36 -> 55519 | C31: ='0. Database'!D36 -> 66001 | D31: ='0. Database'!E36 -> 74989 | E31: ='0. Database'!F36 -> 90272 | F31: ='0. Database'!G36 -> 110855 | G31: ='0. Database'!H36 -> 136819 | H31: ='0. Database'!I36 -> 161857 | I31: ='0. Database'!J36 -> 182527 | ... S31: ='0. Database'!T36 -> 921874.95
A32: META | B32: ='0. Database'!C53 -> 7872 | C32: ='0. Database'!D53 -> 12466 | D32: ='0. Database'!E53 -> 17927 | E32: ='0. Database'!F53 -> 27638 | F32: ='0. Database'!G53 -> 40653 | G32: ='0. Database'!H53 -> 55838 | H32: ='0. Database'!I53 -> 70696.5 | I32: ='0. Database'!J53 -> 85966 | ... S32: ='0. Database'!T53 -> 456192.68
A33: ORCL | B33: ='0. Database'!C71 -> 37253 | C33: ='0. Database'!D71 -> 38305 | D33: ='0. Database'!E71 -> 38253 | E33: ='0. Database'!F71 -> 37057 | F33: ='0. Database'!G71 -> 37899 | G33: ='0. Database'!H71 -> 39431 | H33: ='0. Database'!I71 -> 39525 | I33: ='0. Database'!J71 -> 39073 | ... S33: ='0. Database'!T71 -> 185555.08
A35: (NI)
A36: Company | B36: 2013A | C36: 2014A | D36: 2015A | E36: 2016A | F36: 2017A | G36: 2018A | H36: 2019A | I36: 2020A | J36: 2021A | K36: 2022A | L36: 2023A | M36: 2024A | N36: 2025E | O36: 2026E | P36: 2027E | Q36: 2028E | R36: 2029E | S36: 2030E
A37: MSFT | B37: ='0. Database'!C7 -> 21863 | C37: ='0. Database'!D7 -> 22074 | D37: ='0. Database'!E7 -> 12193 | E37: ='0. Database'!F7 -> 16798 | F37: ='0. Database'!G7 -> 25489 | G37: ='0. Database'!H7 -> 16571 | H37: ='0. Database'!I7 -> 39240 | I37: ='0. Database'!J7 -> 44281 | ... S37: ='0. Database'!T7 -> 258948.36
A38: AMZN | B38: ='0. Database'!C23 -> 273 | C38: ='0. Database'!D23 -> -240.6 | D38: ='0. Database'!E23 -> 596.1 | E38: ='0. Database'!F23 -> 2371 | F38: ='0. Database'!G23 -> 3033 | G38: ='0. Database'!H23 -> 10073 | H38: ='0. Database'!I23 -> 11588 | I38: ='0. Database'!J23 -> 21331 | ... S38: ='0. Database'!T23 -> 211925.99
A39: GOOGL | B39: ='0. Database'!C38 -> 12720 | C39: ='0. Database'!D38 -> 14136 | D39: ='0. Database'!E38 -> 16348 | E39: ='0. Database'!F38 -> 19478 | F39: ='0. Database'!G38 -> 12662 | G39: ='0. Database'!H38 -> 30736 | H39: ='0. Database'!I38 -> 34343 | I39: ='0. Database'!J38 -> 40269 | ... S39: ='0. Database'!T38 -> 285975.76
A40: META | B40: ='0. Database'!C55 -> 1491 | C40: ='0. Database'!D55 -> 2924.8 | D40: ='0. Database'!E55 -> 3669 | E40: ='0. Database'!F55 -> 10187.2 | F40: ='0. Database'!G55 -> 15919 | G40: ='0. Database'!H55 -> 22112 | H40: ='0. Database'!I55 -> 18484.5 | I40: ='0. Database'!J55 -> 29145 | ... S40: ='0. Database'!T55 -> 127804.37
A41: ORCL | B41: ='0. Database'!C73 -> 10926 | C41: ='0. Database'!D73 -> 10955 | D41: ='0. Database'!E73 -> 9938 | E41: ='0. Database'!F73 -> 8900 | F41: ='0. Database'!G73 -> 9334 | G41: ='0. Database'!H73 -> 3587 | H41: ='0. Database'!I73 -> 11083 | I41: ='0. Database'!J73 -> 10135 | ... S41: ='0. Database'!T73 -> 44104.48
A43: (Capex)
A44: Company | B44: 2013A | C44: 2014A | D44: 2015A | E44: 2016A | F44: 2017A | G44: 2018A | H44: 2019A | I44: 2020A | J44: 2021A | K44: 2022A | L44: 2023A | M44: 2024A | N44: 2025E | O44: 2026E | P44: 2027E | Q44: 2028E | R44: 2029E | S44: 2030E
A45: MSFT | B45: ='0. Database'!C12 -> 4257 | C45: ='0. Database'!D12 -> 5485 | D45: ='0. Database'!E12 -> 5944 | E45: ='0. Database'!F12 -> 8932 | F45: ='0. Database'!G12 -> 10200 | G45: ='0. Database'!H12 -> 13600 | H45: ='0. Database'!I12 -> 16900 | I45: ='0. Database'!J12 -> 19000 | ... S45: ='0. Database'!T12 -> 304616.04
A46: AMZN | B46: ='0. Database'!C28 -> 3443 | C46: ='0. Database'!D28 -> 4892 | D46: ='0. Database'!E28 -> 4588 | E46: ='0. Database'!F28 -> 6736 | F46: ='0. Database'!G28 -> 10057 | G46: ='0. Database'!H28 -> 11322 | H46: ='0. Database'!I28 -> 12690 | I46: ='0. Database'!J28 -> 35046 | ... S46: ='0. Database'!T28 -> 312722.81
A47: GOOGL | B47: ='0. Database'!C43 -> 7358 | C47: ='0. Database'!D43 -> 10959 | D47: ='0. Database'!E43 -> 9915 | E47: ='0. Database'!F43 -> 10183 | F47: ='0. Database'!G43 -> 13184 | G47: ='0. Database'!H43 -> 25139 | H47: ='0. Database'!I43 -> 23548 | I47: ='0. Database'!J43 -> 22281 | ... S47: ='0. Database'!T43 -> 314500.02
A48: META | B48: ='0. Database'!C60 -> 1362 | C48: ='0. Database'!D60 -> 1831 | D48: ='0. Database'!E60 -> 2523 | E48: ='0. Database'!F60 -> 4491 | F48: ='0. Database'!G60 -> 6732 | G48: ='0. Database'!H60 -> 13980 | H48: ='0. Database'!I60 -> 15102 | I48: ='0. Database'!J60 -> 15115 | ... S48: ='0. Database'!T60 -> 208540.35
A49: ORCL | B49: ='0. Database'!C78 -> 650 | C49: ='0. Database'!D78 -> 580 | D49: ='0. Database'!E78 -> 1391 | E49: ='0. Database'!F78 -> 1189 | F49: ='0. Database'!G78 -> 2021 | G49: ='0. Database'!H78 -> 1736 | H49: ='0. Database'!I78 -> 1660 | I49: ='0. Database'!J78 -> 1564 | ... S49: ='0. Database'!T78 -> 66459.86
A51: C. FCF Margin %
A52: Company | B52: 2013A | C52: 2014A | D52: 2015A | E52: 2016A | F52: 2017A | G52: 2018A | H52: 2019A | I52: 2020A | J52: 2021A | K52: 2022A | L52: 2023A | M52: 2024A | N52: 2025E | O52: 2026E | P52: 2027E | Q52: 2028E | R52: 2029E | S52: 2030E
A53: MSFT | B53: =IFERROR(B13/B29,"") -> 0.31568806 | C53: =IFERROR(C13/C29,"") -> 0.30801654 | D53: =IFERROR(D13/D29,"") -> 0.24723231 | E53: =IFERROR(E13/E29,"") -> 0.28590014 | F53: =IFERROR(F13/F29,"") -> 0.3034762 | G53: =IFERROR(G13/G29,"") -> 0.27441102 | H53: =IFERROR(H13/H29,"") -> 0.28038906 | I53: =IFERROR(I13/I29,"") -> 0.291403 | ... S53: =IFERROR(S13/S29,"") -> 0.20517536
A54: AMZN | B54: =IFERROR(B14/B30,"") -> 0.027278955 | C54: =IFERROR(C14/C30,"") -> 0.021906226 | D54: =IFERROR(D14/D30,"") -> 0.068520073 | E54: =IFERROR(E14/E30,"") -> 0.077470641 | F54: =IFERROR(F14/F30,"") -> 0.047097253 | G54: =IFERROR(G14/G30,"") -> 0.08331079 | H54: =IFERROR(H14/H30,"") -> 0.092060516 | I54: =IFERROR(I14/I30,"") -> 0.080344192 | ... S54: =IFERROR(S14/S30,"") -> 0.067685424
A55: GOOGL | B55: =IFERROR(B15/B31,"") -> 0.20220105 | C55: =IFERROR(C15/C31,"") -> 0.17140649 | D55: =IFERROR(D15/D31,"") -> 0.21221779 | E55: =IFERROR(E15/E31,"") -> 0.28639002 | F55: =IFERROR(F15/F31,"") -> 0.2156601 | G55: =IFERROR(G15/G31,"") -> 0.16687741 | H55: =IFERROR(H15/H31,"") -> 0.1913541 | I55: =IFERROR(I15/I31,"") -> 0.23472144 | ... S55: =IFERROR(S15/S31,"") -> 0.19131372
A56: META | B56: =IFERROR(B16/B32,"") -> 0.36331301 | C56: =IFERROR(C16/C32,"") -> 0.29494625 | D56: =IFERROR(D16/D32,"") -> 0.33937636 | E56: =IFERROR(E16/E32,"") -> 0.41862653 | F56: =IFERROR(F16/F32,"") -> 0.43007896 | G56: =IFERROR(G16/G32,"") -> 0.27506358 | H56: =IFERROR(H16/H32,"") -> 0.30002192 | I56: =IFERROR(I16/I32,"") -> 0.27489938 | ... S56: =IFERROR(S16/S32,"") -> 0.2322224
A57: ORCL | B57: =IFERROR(B17/B33,"") -> 0.36440018 | C57: =IFERROR(C17/C33,"") -> 0.37438977 | D57: =IFERROR(D17/D33,"") -> 0.33840483 | E57: =IFERROR(E17/E33,"") -> 0.33383706 | F57: =IFERROR(F17/F33,"") -> 0.31937518 | G57: =IFERROR(G17/G33,"") -> 0.34617433 | H57: =IFERROR(H17/H33,"") -> 0.32614801 | I57: =IFERROR(I17/I33,"") -> 0.29624037 | ... S57: =IFERROR(S17/S33,"") -> 0.099723812
A59: D. FCF / Net Income %
A60: Company | B60: 2013A | C60: 2014A | D60: 2015A | E60: 2016A | F60: 2017A | G60: 2018A | H60: 2019A | I60: 2020A | J60: 2021A | K60: 2022A | L60: 2023A | M60: 2024A | N60: 2025E | O60: 2026E | P60: 2027E | Q60: 2028E | R60: 2029E | S60: 2030E
A61: MSFT | B61: =IFERROR(B13/B37,"") -> 1.1240909 | C61: =IFERROR(C13/C37,"") -> 1.2116517 | D61: =IFERROR(D13/D37,"") -> 1.8974822 | E61: =IFERROR(E13/E37,"") -> 1.4521372 | F61: =IFERROR(F13/F37,"") -> 1.1497901 | G61: =IFERROR(G13/G37,"") -> 1.82753 | H61: =IFERROR(H13/H37,"") -> 0.89920999 | I61: =IFERROR(I13/I37,"") -> 0.94114857 | ... S61: =IFERROR(S13/S37,"") -> 0.51721841
A62: AMZN | B62: =IFERROR(B14/B38,"") -> 7.4395604 | C62: =IFERROR(C14/C38,"") -> -8.1022444 | D62: =IFERROR(D14/D38,"") -> 12.300117 | E62: =IFERROR(E14/E38,"") -> 4.4432729 | F62: =IFERROR(F14/F38,"") -> 2.7619519 | G62: =IFERROR(G14/G38,"") -> 1.9261392 | H62: =IFERROR(H14/H38,"") -> 2.2285986 | I62: =IFERROR(I14/I38,"") -> 1.4541278 | ... S62: =IFERROR(S14/S38,"") -> 0.41692668
A63: GOOGL | B63: =IFERROR(B15/B39,"") -> 0.88254717 | C63: =IFERROR(C15/C39,"") -> 0.80029711 | D63: =IFERROR(D15/D39,"") -> 0.97345241 | E63: =IFERROR(E15/E39,"") -> 1.3272923 | F63: =IFERROR(F15/F39,"") -> 1.8880903 | G63: =IFERROR(G15/G39,"") -> 0.74284227 | H63: =IFERROR(H15/H39,"") -> 0.90184317 | I63: =IFERROR(I15/I39,"") -> 1.0639201 | ... S63: =IFERROR(S15/S39,"") -> 0.61672126
A64: META | B64: =IFERROR(B16/B40,"") -> 1.9181757 | C64: =IFERROR(C16/C40,"") -> 1.2571116 | D64: =IFERROR(D16/D40,"") -> 1.6582175 | E64: =IFERROR(E16/E40,"") -> 1.135739 | F64: =IFERROR(F16/F40,"") -> 1.0983102 | G64: =IFERROR(G16/G40,"") -> 0.69460022 | H64: =IFERROR(H16/H40,"") -> 1.1474749 | I64: =IFERROR(I16/I40,"") -> 0.81084234 | ... S64: =IFERROR(S16/S40,"") -> 0.82890875
A65: ORCL | B65: =IFERROR(B17/B41,"") -> 1.2424492 | C65: =IFERROR(C17/C41,"") -> 1.3090826 | D65: =IFERROR(D17/D41,"") -> 1.302576 | E65: =IFERROR(E17/E41,"") -> 1.39 | F65: =IFERROR(F17/F41,"") -> 1.2967645 | G65: =IFERROR(G17/G41,"") -> 3.8054084 | H65: =IFERROR(H17/H41,"") -> 1.1631327 | I65: =IFERROR(I17/I41,"") -> 1.1420819 | ... S65: =IFERROR(S17/S41,"") -> 0.41955511
A67: F. Capex / CFO %
A68: Company | B68: 2013A | C68: 2014A | D68: 2015A | E68: 2016A | F68: 2017A | G68: 2018A | H68: 2019A | I68: 2020A | J68: 2021A | K68: 2022A | L68: 2023A | M68: 2024A | N68: 2025E | O68: 2026E | P68: 2027E | Q68: 2028E | R68: 2029E | S68: 2030E
A69: MSFT | B69: =IFERROR(B45/B5,"") -> 0.14764333 | C69: =IFERROR(C45/C5,"") -> 0.17017778 | D69: =IFERROR(D45/D5,"") -> 0.20440165 | E69: =IFERROR(E45/E5,"") -> 0.26802701 | F69: =IFERROR(F45/F5,"") -> 0.25818209 | G69: =IFERROR(G45/G5,"") -> 0.30990794 | H69: =IFERROR(H45/H5,"") -> 0.32384785 | I69: =IFERROR(I45/I5,"") -> 0.3131438 | ... S69: =IFERROR(S45/S5,"") -> 0.69459994
A70: AMZN | B70: =IFERROR(B46/B6,"") -> 0.62897333 | C70: =IFERROR(C46/C6,"") -> 0.71505832 | D70: =IFERROR(D46/D6,"") -> 0.3848961 | E70: =IFERROR(E46/E6,"") -> 0.39001795 | F70: =IFERROR(F46/F6,"") -> 0.54556797 | G70: =IFERROR(G46/G6,"") -> 0.3685067 | H70: =IFERROR(H46/H6,"") -> 0.32948202 | I70: =IFERROR(I46/I6,"") -> 0.53048559 | ... S70: =IFERROR(S46/S6,"") -> 0.77970103
A71: GOOGL | B71: =IFERROR(B47/B7,"") -> 0.39593198 | C71: =IFERROR(C47/C7,"") -> 0.4920528 | D71: =IFERROR(D47/D7,"") -> 0.38387084 | E71: =IFERROR(E47/E7,"") -> 0.28257853 | F71: =IFERROR(F47/F7,"") -> 0.35545011 | G71: =IFERROR(G47/G7,"") -> 0.52404578 | H71: =IFERROR(H47/H7,"") -> 0.43191489 | I71: =IFERROR(I47/I7,"") -> 0.34213193 | ... S71: =IFERROR(S47/S7,"") -> 0.64070267
A72: META | B72: =IFERROR(B48/B8,"") -> 0.32259593 | C72: =IFERROR(C48/C8,"") -> 0.33243763 | D72: =IFERROR(D48/D8,"") -> 0.2931335 | E72: =IFERROR(E48/E8,"") -> 0.27962144 | F72: =IFERROR(F48/F8,"") -> 0.27799802 | G72: =IFERROR(G48/G8,"") -> 0.47649886 | H72: =IFERROR(H48/H8,"") -> 0.41588985 | I72: =IFERROR(I48/I8,"") -> 0.39009472 | ... S72: =IFERROR(S48/S8,"") -> 0.66313069
A73: ORCL | B73: =IFERROR(B49/B9,"") -> 0.0456942 | C73: =IFERROR(C49/C9,"") -> 0.038871389 | D73: =IFERROR(D49/D9,"") -> 0.09702846 | E73: =IFERROR(E49/E9,"") -> 0.087684366 | F73: =IFERROR(F49/F9,"") -> 0.14307965 | G73: =IFERROR(G49/G9,"") -> 0.11282985 | H73: =IFERROR(H49/H9,"") -> 0.11408151 | I73: =IFERROR(I49/I9,"") -> 0.11903493 | ... S73: =IFERROR(S49/S9,"") -> 0.78221089

Sheet 5. EPS & Margins
A1: EPS, OpMargin & Profitability (2013-2030E)
A3: A. Operating Income ($mm)
A4: Company | B4: 2013A | C4: 2014A | D4: 2015A | E4: 2016A | F4: 2017A | G4: 2018A | H4: 2019A | I4: 2020A | J4: 2021A | K4: 2022A | L4: 2023A | M4: 2024A | N4: 2025E | O4: 2026E | P4: 2027E | Q4: 2028E | R4: 2029E | S4: 2030E
A5: MSFT | B5: ='0. Database'!C6 -> 26764 | C5: ='0. Database'!D6 -> 27759 | D5: ='0. Database'!E6 -> 18161 | E5: ='0. Database'!F6 -> 20182 | F5: ='0. Database'!G6 -> 29025 | G5: ='0. Database'!H6 -> 35058 | H5: ='0. Database'!I6 -> 42959 | I5: ='0. Database'!J6 -> 52959 | ... S5: ='0. Database'!T6 -> 318436.19
A6: AMZN | B6: ='0. Database'!C22 -> 745 | C6: ='0. Database'!D22 -> 178.4 | D6: ='0. Database'!E22 -> 2232.6 | E6: ='0. Database'!F22 -> 4186 | F6: ='0. Database'!G22 -> 4107 | G6: ='0. Database'!H22 -> 12420 | H6: ='0. Database'!I22 -> 14540 | I6: ='0. Database'!J22 -> 22899 | ... S6: ='0. Database'!T22 -> 264582.39
A7: GOOGL | B7: ='0. Database'!C37 -> 15403 | C7: ='0. Database'!D37 -> 16496 | D7: ='0. Database'!E37 -> 19360 | E7: ='0. Database'!F37 -> 23716 | F7: ='0. Database'!G37 -> 26146 | G7: ='0. Database'!H37 -> 26953 | H7: ='0. Database'!I37 -> 34231 | I7: ='0. Database'!J37 -> 41224 | ... S7: ='0. Database'!T37 -> 338347.07
A8: META | B8: ='0. Database'!C54 -> 2804 | C8: ='0. Database'!D54 -> 4994.8 | D8: ='0. Database'!E54 -> 6225 | E8: ='0. Database'!F54 -> 12427 | F8: ='0. Database'!G54 -> 20202 | G8: ='0. Database'!H54 -> 24913 | H8: ='0. Database'!I54 -> 23985.5 | I8: ='0. Database'!J54 -> 32671 | ... S8: ='0. Database'!T54 -> 142814.67
A9: ORCL | B9: ='0. Database'!C72 -> 14684 | C9: ='0. Database'!D72 -> 14758 | D9: ='0. Database'!E72 -> 13870 | E9: ='0. Database'!F72 -> 12604 | F9: ='0. Database'!G72 -> 12710 | G9: ='0. Database'!H72 -> 13264 | H9: ='0. Database'!I72 -> 13535 | I9: ='0. Database'!J72 -> 13897 | ... S9: ='0. Database'!T72 -> 57952.82
A11: C. Net Income ($mm)
A12: Company | B12: 2013A | C12: 2014A | D12: 2015A | E12: 2016A | F12: 2017A | G12: 2018A | H12: 2019A | I12: 2020A | J12: 2021A | K12: 2022A | L12: 2023A | M12: 2024A | N12: 2025E | O12: 2026E | P12: 2027E | Q12: 2028E | R12: 2029E | S12: 2030E
A13: MSFT | B13: ='0. Database'!C7 -> 21863 | C13: ='0. Database'!D7 -> 22074 | D13: ='0. Database'!E7 -> 12193 | E13: ='0. Database'!F7 -> 16798 | F13: ='0. Database'!G7 -> 25489 | G13: ='0. Database'!H7 -> 16571 | H13: ='0. Database'!I7 -> 39240 | I13: ='0. Database'!J7 -> 44281 | ... S13: ='0. Database'!T7 -> 258948.36
A14: AMZN | B14: ='0. Database'!C23 -> 273 | C14: ='0. Database'!D23 -> -240.6 | D14: ='0. Database'!E23 -> 596.1 | E14: ='0. Database'!F23 -> 2371 | F14: ='0. Database'!G23 -> 3033 | G14: ='0. Database'!H23 -> 10073 | H14: ='0. Database'!I23 -> 11588 | I14: ='0. Database'!J23 -> 21331 | ... S14: ='0. Database'!T23 -> 211925.99
A15: GOOGL | B15: ='0. Database'!C38 -> 12720 | C15: ='0. Database'!D38 -> 14136 | D15: ='0. Database'!E38 -> 16348 | E15: ='0. Database'!F38 -> 19478 | F15: ='0. Database'!G38 -> 12662 | G15: ='0. Database'!H38 -> 30736 | H15: ='0. Database'!I38 -> 34343 | I15: ='0. Database'!J38 -> 40269 | ... S15: ='0. Database'!T38 -> 285975.76
A16: META | B16: ='0. Database'!C55 -> 1491 | C16: ='0. Database'!D55 -> 2924.8 | D16: ='0. Database'!E55 -> 3669 | E16: ='0. Database'!F55 -> 10187.2 | F16: ='0. Database'!G55 -> 15919 | G16: ='0. Database'!H55 -> 22112 | H16: ='0. Database'!I55 -> 18484.5 | I16: ='0. Database'!J55 -> 29145 | ... S16: ='0. Database'!T55 -> 127804.37
A17: ORCL | B17: ='0. Database'!C73 -> 10926 | C17: ='0. Database'!D73 -> 10955 | D17: ='0. Database'!E73 -> 9938 | E17: ='0. Database'!F73 -> 8900 | F17: ='0. Database'!G73 -> 9334 | G17: ='0. Database'!H73 -> 3587 | H17: ='0. Database'!I73 -> 11083 | I17: ='0. Database'!J73 -> 10135 | ... S17: ='0. Database'!T73 -> 44104.48
A19: E. EPS ($)
A20: Company | B20: 2013A | C20: 2014A | D20: 2015A | E20: 2016A | F20: 2017A | G20: 2018A | H20: 2019A | I20: 2020A | J20: 2021A | K20: 2022A | L20: 2023A | M20: 2024A | N20: 2025E | O20: 2026E | P20: 2027E | Q20: 2028E | R20: 2029E | S20: 2030E
A21: MSFT | B21: ='0. Database'!C8 -> 2.63 | C21: ='0. Database'!D8 -> 2.66 | D21: ='0. Database'!E8 -> 2.59 | E21: ='0. Database'!F8 -> 2.79 | F21: ='0. Database'!G8 -> 3.29 | G21: ='0. Database'!H8 -> 3.88 | H21: ='0. Database'!I8 -> 4.75 | I21: ='0. Database'!J8 -> 5.76 | ... S21: ='0. Database'!T8 -> 34.82
A22: AMZN | B22: ='0. Database'!C24 -> 0.03 | C22: ='0. Database'!D24 -> -0.03 | D22: ='0. Database'!E24 -> 0.06 | E22: ='0. Database'!F24 -> 0.24 | F22: ='0. Database'!G24 -> 0.31 | G22: ='0. Database'!H24 -> 1.01 | H22: ='0. Database'!I24 -> 1.15 | I22: ='0. Database'!J24 -> 2.08 | ... S22: ='0. Database'!T24 -> 18.92
A23: GOOGL | B23: ='0. Database'!C39 -> 0.94 | C23: ='0. Database'!D39 -> 1.03 | D23: ='0. Database'!E39 -> 1.18 | E23: ='0. Database'!F39 -> 1.39 | F23: ='0. Database'!G39 -> 0.9 | G23: ='0. Database'!H39 -> 2.19 | H23: ='0. Database'!I39 -> 2.46 | I23: ='0. Database'!J39 -> 2.93 | ... S23: ='0. Database'!T39 -> 22.99
A24: META | B24: ='0. Database'!C56 -> 0.59 | C24: ='0. Database'!D56 -> 1.1 | D24: ='0. Database'!E56 -> 1.28 | E24: ='0. Database'!F56 -> 3.48 | F24: ='0. Database'!G56 -> 5.39 | G24: ='0. Database'!H56 -> 7.66 | H24: ='0. Database'!I56 -> 6.44 | I24: ='0. Database'!J56 -> 10.08 | ... S24: ='0. Database'!T56 -> 47.52
A25: ORCL | B25: ='0. Database'!C74 -> 2.26 | C25: ='0. Database'!D74 -> 2.38 | D25: ='0. Database'!E74 -> 2.21 | E25: ='0. Database'!F74 -> 2.07 | F25: ='0. Database'!G74 -> 2.21 | G25: ='0. Database'!H74 -> 0.85 | H25: ='0. Database'!I74 -> 2.97 | I25: ='0. Database'!J74 -> 3.08 | ... S25: ='0. Database'!T74 -> 14.32
A27: G. Diluted Shares (mm)
A28: Company | B28: 2013A | C28: 2014A | D28: 2015A | E28: 2016A | F28: 2017A | G28: 2018A | H28: 2019A | I28: 2020A | J28: 2021A | K28: 2022A | L28: 2023A | M28: 2024A | N28: 2025E | O28: 2026E | P28: 2027E | Q28: 2028E | R28: 2029E | S28: 2030E
A29: MSFT | B29: ='0. Database'!C9 -> 8452.25 | C29: ='0. Database'!D9 -> 8385.25 | D29: ='0. Database'!E9 -> 8254 | E29: ='0. Database'!F9 -> 8012.25 | F29: ='0. Database'!G9 -> 7831.25 | G29: ='0. Database'!H9 -> 7792.25 | H29: ='0. Database'!I9 -> 7752 | I29: ='0. Database'!J9 -> 7681.5 | ... S29: ='0. Database'!T9 -> 7436.22
A30: AMZN | B30: ='0. Database'!C25 -> 9340 | C30: ='0. Database'!D25 -> 9440 | D30: ='0. Database'!E25 -> 9620 | E30: ='0. Database'!F25 -> 9720 | F30: ='0. Database'!G25 -> 9910 | G30: ='0. Database'!H25 -> 10020 | H30: ='0. Database'!I25 -> 10100 | I30: ='0. Database'!J25 -> 10254 | ... S30: ='0. Database'!T25 -> 11201.4
A31: GOOGL | B31: ='0. Database'!C40 -> 13552.38 | C31: ='0. Database'!D40 -> 13741.41 | D31: ='0. Database'!E40 -> 13858.6 | E31: ='0. Database'!F40 -> 13974.09 | F31: ='0. Database'!G40 -> 14071.67 | G31: ='0. Database'!H40 -> 14065.69 | H31: ='0. Database'!I40 -> 13971.13 | I31: ='0. Database'!J40 -> 13740.56 | ... S31: ='0. Database'!T40 -> 12436.85
A32: META | B32: ='0. Database'!C57 -> 2521.75 | C32: ='0. Database'!D57 -> 2671 | D32: ='0. Database'!E57 -> 2856.75 | E32: ='0. Database'!F57 -> 2923.75 | F32: ='0. Database'!G57 -> 2954 | G32: ='0. Database'!H57 -> 2886 | H32: ='0. Database'!I57 -> 2871 | I32: ='0. Database'!J57 -> 2890 | ... S32: ='0. Database'!T57 -> 2689.4
A33: ORCL | B33: ='0. Database'!C75 -> 4843.75 | C33: ='0. Database'!D75 -> 4604.5 | D33: ='0. Database'!E75 -> 4502.5 | E33: ='0. Database'!F75 -> 4305.5 | F33: ='0. Database'!G75 -> 4217 | G33: ='0. Database'!H75 -> 4238 | H33: ='0. Database'!I75 -> 3732 | I33: ='0. Database'!J75 -> 3293.5 | ... S33: ='0. Database'!T75 -> 3079.57
A35: H. SBC ($mm)
A36: Company | B36: 2013A | C36: 2014A | D36: 2015A | E36: 2016A | F36: 2017A | G36: 2018A | H36: 2019A | I36: 2020A | J36: 2021A | K36: 2022A | L36: 2023A | M36: 2024A | N36: 2025E | O36: 2026E | P36: 2027E | Q36: 2028E | R36: 2029E | S36: 2030E
A37: MSFT | B37: ='0. Database'!C10 -> 2406 | C37: ='0. Database'!D10 -> 2446 | D37: ='0. Database'!E10 -> 2574 | E37: ='0. Database'!F10 -> 2668 | F37: ='0. Database'!G10 -> 3266 | G37: ='0. Database'!H10 -> 3940 | H37: ='0. Database'!I10 -> 4652 | I37: ='0. Database'!J10 -> 5289 | ... S37: ='0. Database'!T10 -> 14871.62
A38: AMZN | B38: ='0. Database'!C26 -> -1134 | C38: ='0. Database'!D26 -> -1497 | D38: ='0. Database'!E26 -> -2120 | E38: ='0. Database'!F26 -> -2975 | F38: ='0. Database'!G26 -> -4214 | G38: ='0. Database'!H26 -> -5418 | H38: ='0. Database'!I26 -> -6864 | I38: ='0. Database'!J26 -> -9208 | ... S38: ='0. Database'!T26 -> -20744.82
A39: GOOGL | B39: ='0. Database'!C41 -> -3268 | C39: ='0. Database'!D41 -> -4175 | D39: ='0. Database'!E41 -> -4903 | E39: ='0. Database'!F41 -> -6703 | F39: ='0. Database'!G41 -> -7679 | G39: ='0. Database'!H41 -> -9353 | H39: ='0. Database'!I41 -> -10794 | I39: ='0. Database'!J41 -> -12991 | ... S39: ='0. Database'!T41 -> -35339.95
A40: META | B40: ='0. Database'!C58 -> -906 | C40: ='0. Database'!D58 -> -1837 | D40: ='0. Database'!E58 -> -2969 | E40: ='0. Database'!F58 -> -3202 | F40: ='0. Database'!G58 -> -3723 | G40: ='0. Database'!H58 -> -4152 | H40: ='0. Database'!I58 -> -4835 | I40: ='0. Database'!J58 -> -6536 | ... S40: ='0. Database'!T58 -> -28834.48
A41: ORCL | B41: ='0. Database'!C76 -> 755 | C41: ='0. Database'!D76 -> 805 | D41: ='0. Database'!E76 -> 933 | E41: ='0. Database'!F76 -> 1037 | F41: ='0. Database'!G76 -> 1350 | G41: ='0. Database'!H76 -> 1607 | H41: ='0. Database'!I76 -> 1653 | I41: ='0. Database'!J76 -> 1590 | ... S41: ='0. Database'!T76 -> 11212.32
A43: (Revenue)
A44: Company | B44: 2013A | C44: 2014A | D44: 2015A | E44: 2016A | F44: 2017A | G44: 2018A | H44: 2019A | I44: 2020A | J44: 2021A | K44: 2022A | L44: 2023A | M44: 2024A | N44: 2025E | O44: 2026E | P44: 2027E | Q44: 2028E | R44: 2029E | S44: 2030E
A45: MSFT | B45: ='0. Database'!C5 -> 77849 | C45: ='0. Database'!D5 -> 86833 | D45: ='0. Database'!E5 -> 93580 | E45: ='0. Database'!F5 -> 85320 | F45: ='0. Database'!G5 -> 96571 | G45: ='0. Database'!H5 -> 110360 | H45: ='0. Database'!I5 -> 125843 | I45: ='0. Database'!J5 -> 143015 | ... S45: ='0. Database'!T5 -> 652772.62
A46: AMZN | B46: ='0. Database'!C21 -> 74453 | C46: ='0. Database'!D21 -> 88988.4 | D46: ='0. Database'!E21 -> 107006.6 | E46: ='0. Database'!F21 -> 135987 | F46: ='0. Database'!G21 -> 177866 | G46: ='0. Database'!H21 -> 232887 | H46: ='0. Database'!I21 -> 280522 | I46: ='0. Database'!J21 -> 386064 | ... S46: ='0. Database'!T21 -> 1305415.5
A47: GOOGL | B47: ='0. Database'!C36 -> 55519 | C47: ='0. Database'!D36 -> 66001 | D47: ='0. Database'!E36 -> 74989 | E47: ='0. Database'!F36 -> 90272 | F47: ='0. Database'!G36 -> 110855 | G47: ='0. Database'!H36 -> 136819 | H47: ='0. Database'!I36 -> 161857 | I47: ='0. Database'!J36 -> 182527 | ... S47: ='0. Database'!T36 -> 921874.95
A48: META | B48: ='0. Database'!C53 -> 7872 | C48: ='0. Database'!D53 -> 12466 | D48: ='0. Database'!E53 -> 17927 | E48: ='0. Database'!F53 -> 27638 | F48: ='0. Database'!G53 -> 40653 | G48: ='0. Database'!H53 -> 55838 | H48: ='0. Database'!I53 -> 70696.5 | I48: ='0. Database'!J53 -> 85966 | ... S48: ='0. Database'!T53 -> 456192.68
A49: ORCL | B49: ='0. Database'!C71 -> 37253 | C49: ='0. Database'!D71 -> 38305 | D49: ='0. Database'!E71 -> 38253 | E49: ='0. Database'!F71 -> 37057 | F49: ='0. Database'!G71 -> 37899 | G49: ='0. Database'!H71 -> 39431 | H49: ='0. Database'!I71 -> 39525 | I49: ='0. Database'!J71 -> 39073 | ... S49: ='0. Database'!T71 -> 185555.08
A51: B. Operating Margin %
A52: Company | B52: 2013A | C52: 2014A | D52: 2015A | E52: 2016A | F52: 2017A | G52: 2018A | H52: 2019A | I52: 2020A | J52: 2021A | K52: 2022A | L52: 2023A | M52: 2024A | N52: 2025E | O52: 2026E | P52: 2027E | Q52: 2028E | R52: 2029E | S52: 2030E
A53: MSFT | B53: =IFERROR(B5/B45,"") -> 0.34379375 | C53: =IFERROR(C5/C45,"") -> 0.31968261 | D53: =IFERROR(D5/D45,"") -> 0.19406925 | E53: =IFERROR(E5/E45,"") -> 0.23654477 | F53: =IFERROR(F5/F45,"") -> 0.30055607 | G53: =IFERROR(G5/G45,"") -> 0.31766945 | H53: =IFERROR(H5/H45,"") -> 0.3413698 | I53: =IFERROR(I5/I45,"") -> 0.37030381 | ... S53: =IFERROR(S5/S45,"") -> 0.487821
A54: AMZN | B54: =IFERROR(B6/B46,"") -> 0.010006313 | C54: =IFERROR(C6/C46,"") -> 0.0020047557 | D54: =IFERROR(D6/D46,"") -> 0.020864134 | E54: =IFERROR(E6/E46,"") -> 0.030782354 | F54: =IFERROR(F6/F46,"") -> 0.023090416 | G54: =IFERROR(G6/G46,"") -> 0.053330585 | H54: =IFERROR(H6/H46,"") -> 0.051831942 | I54: =IFERROR(I6/I46,"") -> 0.059314 | ... S54: =IFERROR(S6/S46,"") -> 0.2026806
A55: GOOGL | B55: =IFERROR(B7/B47,"") -> 0.27743655 | C55: =IFERROR(C7/C47,"") -> 0.24993561 | D55: =IFERROR(D7/D47,"") -> 0.2581712 | E55: =IFERROR(E7/E47,"") -> 0.26271712 | F55: =IFERROR(F7/F47,"") -> 0.23585765 | G55: =IFERROR(G7/G47,"") -> 0.19699749 | H55: =IFERROR(H7/H47,"") -> 0.21148915 | I55: =IFERROR(I7/I47,"") -> 0.22585152 | ... S55: =IFERROR(S7/S47,"") -> 0.36702057
A56: META | B56: =IFERROR(B8/B48,"") -> 0.35619919 | C56: =IFERROR(C8/C48,"") -> 0.40067383 | D56: =IFERROR(D8/D48,"") -> 0.34724159 | E56: =IFERROR(E8/E48,"") -> 0.44963456 | F56: =IFERROR(F8/F48,"") -> 0.4969375 | G56: =IFERROR(G8/G48,"") -> 0.44616569 | H56: =IFERROR(H8/H48,"") -> 0.33927422 | I56: =IFERROR(I8/I48,"") -> 0.3800456 | ... S56: =IFERROR(S8/S48,"") -> 0.31305779
A57: ORCL | B57: =IFERROR(B9/B49,"") -> 0.3941696 | C57: =IFERROR(C9/C49,"") -> 0.38527607 | D57: =IFERROR(D9/D49,"") -> 0.36258594 | E57: =IFERROR(E9/E49,"") -> 0.34012467 | F57: =IFERROR(F9/F49,"") -> 0.33536505 | G57: =IFERROR(G9/G49,"") -> 0.33638508 | H57: =IFERROR(H9/H49,"") -> 0.34244149 | I57: =IFERROR(I9/I49,"") -> 0.3556676 | ... S57: =IFERROR(S9/S49,"") -> 0.31232139
A59: D. Net Margin %
A60: Company | B60: 2013A | C60: 2014A | D60: 2015A | E60: 2016A | F60: 2017A | G60: 2018A | H60: 2019A | I60: 2020A | J60: 2021A | K60: 2022A | L60: 2023A | M60: 2024A | N60: 2025E | O60: 2026E | P60: 2027E | Q60: 2028E | R60: 2029E | S60: 2030E
A61: MSFT | B61: =IFERROR(B13/B45,"") -> 0.28083855 | C61: =IFERROR(C13/C45,"") -> 0.25421211 | D61: =IFERROR(D13/D45,"") -> 0.13029493 | E61: =IFERROR(E13/E45,"") -> 0.19688233 | F61: =IFERROR(F13/F45,"") -> 0.26394052 | G61: =IFERROR(G13/G45,"") -> 0.15015404 | H61: =IFERROR(H13/H45,"") -> 0.31181711 | I61: =IFERROR(I13/I45,"") -> 0.30962486 | ... S61: =IFERROR(S13/S45,"") -> 0.39668998
A62: AMZN | B62: =IFERROR(B14/B46,"") -> 0.0036667428 | C62: =IFERROR(C14/C46,"") -> -0.0027037232 | D62: =IFERROR(D14/D46,"") -> 0.0055706844 | E62: =IFERROR(E14/E46,"") -> 0.01743549 | F62: =IFERROR(F14/F46,"") -> 0.017052163 | G62: =IFERROR(G14/G46,"") -> 0.043252736 | H62: =IFERROR(H14/H46,"") -> 0.041308703 | I62: =IFERROR(I14/I46,"") -> 0.055252497 | ... S62: =IFERROR(S14/S46,"") -> 0.16234371
A63: GOOGL | B63: =IFERROR(B15/B47,"") -> 0.22911075 | C63: =IFERROR(C15/C47,"") -> 0.21417857 | D63: =IFERROR(D15/D47,"") -> 0.21800531 | E63: =IFERROR(E15/E47,"") -> 0.21577012 | F63: =IFERROR(F15/F47,"") -> 0.11422128 | G63: =IFERROR(G15/G47,"") -> 0.22464716 | H63: =IFERROR(H15/H47,"") -> 0.21218112 | I63: =IFERROR(I15/I47,"") -> 0.22061942 | ... S63: =IFERROR(S15/S47,"") -> 0.31021101
A64: META | B64: =IFERROR(B16/B48,"") -> 0.18940549 | C64: =IFERROR(C16/C48,"") -> 0.23462217 | D64: =IFERROR(D16/D48,"") -> 0.20466336 | E64: =IFERROR(E16/E48,"") -> 0.36859396 | F64: =IFERROR(F16/F48,"") -> 0.39158242 | G64: =IFERROR(G16/G48,"") -> 0.39600272 | H64: =IFERROR(H16/H48,"") -> 0.26146273 | I64: =IFERROR(I16/I48,"") -> 0.33902938 | ... S64: =IFERROR(S16/S48,"") -> 0.28015436
A65: ORCL | B65: =IFERROR(B17/B49,"") -> 0.29329182 | C65: =IFERROR(C17/C49,"") -> 0.285994 | D65: =IFERROR(D17/D49,"") -> 0.25979662 | E65: =IFERROR(E17/E49,"") -> 0.24017055 | F65: =IFERROR(F17/F49,"") -> 0.24628618 | G65: =IFERROR(G17/G49,"") -> 0.090969035 | H65: =IFERROR(H17/H49,"") -> 0.28040481 | I65: =IFERROR(I17/I49,"") -> 0.25938628 | ... S65: =IFERROR(S17/S49,"") -> 0.23768942
A67: F. EPS YoY %
A68: Company | B68: 2013A | C68: 2014A | D68: 2015A | E68: 2016A | F68: 2017A | G68: 2018A | H68: 2019A | I68: 2020A | J68: 2021A | K68: 2022A | L68: 2023A | M68: 2024A | N68: 2025E | O68: 2026E | P68: 2027E | Q68: 2028E | R68: 2029E | S68: 2030E
A69: MSFT | C69: =IFERROR(C21/B21-1,"") -> 0.011406844 | D69: =IFERROR(D21/C21-1,"") -> -0.026315789 | E69: =IFERROR(E21/D21-1,"") -> 0.077220077 | F69: =IFERROR(F21/E21-1,"") -> 0.17921147 | G69: =IFERROR(G21/F21-1,"") -> 0.17933131 | H69: =IFERROR(H21/G21-1,"") -> 0.2242268 | I69: =IFERROR(I21/H21-1,"") -> 0.21263158 | J69: =IFERROR(J21/I21-1,"") -> 0.38368056 | ... S69: =IFERROR(S21/R21-1,"") -> 0.20193303
A70: AMZN | C70: =IFERROR(C22/B22-1,"") -> -2 | D70: =IFERROR(D22/C22-1,"") -> -3 | E70: =IFERROR(E22/D22-1,"") -> 3 | F70: =IFERROR(F22/E22-1,"") -> 0.29166667 | G70: =IFERROR(G22/F22-1,"") -> 2.2580645 | H70: =IFERROR(H22/G22-1,"") -> 0.13861386 | I70: =IFERROR(I22/H22-1,"") -> 0.80869565 | J70: =IFERROR(J22/I22-1,"") -> 0.5625 | ... S70: =IFERROR(S22/R22-1,"") -> 0.18844221
A71: GOOGL | C71: =IFERROR(C23/B23-1,"") -> 0.095744681 | D71: =IFERROR(D23/C23-1,"") -> 0.14563107 | E71: =IFERROR(E23/D23-1,"") -> 0.1779661 | F71: =IFERROR(F23/E23-1,"") -> -0.35251799 | G71: =IFERROR(G23/F23-1,"") -> 1.4333333 | H71: =IFERROR(H23/G23-1,"") -> 0.12328767 | I71: =IFERROR(I23/H23-1,"") -> 0.19105691 | J71: =IFERROR(J23/I23-1,"") -> 0.91467577 | ... S71: =IFERROR(S23/R23-1,"") -> 0.14264414
A72: META | C72: =IFERROR(C24/B24-1,"") -> 0.86440678 | D72: =IFERROR(D24/C24-1,"") -> 0.16363636 | E72: =IFERROR(E24/D24-1,"") -> 1.71875 | F72: =IFERROR(F24/E24-1,"") -> 0.54885057 | G72: =IFERROR(G24/F24-1,"") -> 0.42115028 | H72: =IFERROR(H24/G24-1,"") -> -0.15926893 | I72: =IFERROR(I24/H24-1,"") -> 0.56521739 | J72: =IFERROR(J24/I24-1,"") -> 0.39583333 | ... S72: =IFERROR(S24/R24-1,"") -> 0.092162721
A73: ORCL | C73: =IFERROR(C25/B25-1,"") -> 0.053097345 | D73: =IFERROR(D25/C25-1,"") -> -0.071428571 | E73: =IFERROR(E25/D25-1,"") -> -0.063348416 | F73: =IFERROR(F25/E25-1,"") -> 0.06763285 | G73: =IFERROR(G25/F25-1,"") -> -0.61538462 | H73: =IFERROR(H25/G25-1,"") -> 2.4941176 | I73: =IFERROR(I25/H25-1,"") -> 0.037037037 | J73: =IFERROR(J25/I25-1,"") -> 0.47727273 | ... S73: =IFERROR(S25/R25-1,"") -> 0.088973384

Sheet 6. Depreciation Sensitivity
A1: Depreciation Sensitivity: Useful Life × Method → D&A & EPS Impact
A3: A. Current Depreciation Assumptions (2026E)
A4: Company | B4: 2026E D&A ($mm) | C4: 2026E NI ($mm) | D4: 2026E EPS ($) | E4: Shares (mm) | F4: Tax Rate (editable) | G4: Current Wtd Avg Life (yr) | H4: Depreciable Base ($mm) | I4: D&A Check = Base/Life
A5: MSFT | B5: ='0. Database'!P11 -> 39638.96 | C5: ='0. Database'!P7 -> 129372.86 | D5: ='0. Database'!P8 -> 16.75 | E5: ='0. Database'!P9 -> 7453.97 | F5: 0.18 | G5: 4.9 | H5: =$B$5*$G$5 -> 194230.9 | I5: =IFERROR($H$5/$G$5,"") -> 39638.96
A6: AMZN | B6: ='0. Database'!P27 -> 81175.82 | C6: ='0. Database'!P23 -> 98333.72 | D6: ='0. Database'!P24 -> 9.02 | E6: ='0. Database'!P25 -> 10907.55 | F6: 0.2 | G6: 5.5 | H6: =$B$6*$G$6 -> 446467.01 | I6: =IFERROR($H$6/$G$6,"") -> 81175.82
A7: GOOGL | B7: ='0. Database'!P42 -> 42874.7 | C7: ='0. Database'!P38 -> 168543.28 | D7: ='0. Database'!P39 -> 13.73 | E7: ='0. Database'!P40 -> 12275.96 | F7: 0.16 | G7: 6 | H7: =$B$7*$G$7 -> 257248.2 | I7: =IFERROR($H$7/$G$7,"") -> 42874.7
A8: META | B8: ='0. Database'!P59 -> 35955.99 | C8: ='0. Database'!P55 -> 85782.86 | D8: ='0. Database'!P56 -> 33.28 | E8: ='0. Database'!P57 -> 2577.79 | F8: 0.13 | G8: 5.5 | H8: =$B$8*$G$8 -> 197757.95 | I8: =IFERROR($H$8/$G$8,"") -> 35955.99
A9: ORCL | B9: ='0. Database'!P77 -> 7501.53 | C9: ='0. Database'!P73 -> 15820.55 | D9: ='0. Database'!P74 -> 5.43 | E9: ='0. Database'!P75 -> 2915.76 | F9: 0.2 | G9: 5.5 | H9: =$B$9*$G$9 -> 41258.415 | I9: =IFERROR($H$9/$G$9,"") -> 7501.53
A12: B. Straight-Line: If Useful Life = X Years → D&A & EPS Impact
A13: Formula: New D&A = Depreciable Base / New Life. ΔD&A after-tax hits NI. New EPS = (NI - ΔD&A × (1-tax)) / Shares.
A14: Useful Life = 6 Years (Straight-Line)
A15: Company | B15: New D&A ($mm) | C15: Δ D&A ($mm) | D15: Δ After-tax ($mm) | E15: Adj NI ($mm) | F15: Adj EPS ($) | G15: EPS Δ% vs Current
A16: MSFT | B16: =$H$5/6 -> 32371.817 | C16: =$B$16-$B$5 -> -7267.1427 | D16: =$C$16*(1-$F$5) -> -5959.057 | E16: =$C$5-$D$16 -> 135331.92 | F16: =$E$16/$E$5 -> 18.155683 | G16: =IFERROR($F$16/$D$5-1,"") -> 0.083921378
A17: AMZN | B17: =$H$6/6 -> 74411.168 | C17: =$B$17-$B$6 -> -6764.6517 | D17: =$C$17*(1-$F$6) -> -5411.7213 | E17: =$C$6-$D$17 -> 103745.44 | F17: =$E$17/$E$6 -> 9.5113423 | G17: =IFERROR($F$17/$D$6-1,"") -> 0.054472535
A18: GOOGL | B18: =$H$7/6 -> 42874.7 | C18: =$B$18-$B$7 -> 0 | D18: =$C$18*(1-$F$7) -> 0 | E18: =$C$7-$D$18 -> 168543.28 | F18: =$E$18/$E$7 -> 13.72954 | G18: =IFERROR($F$18/$D$7-1,"") -> -3.3526169e-05
A19: META | B19: =$H$8/6 -> 32959.658 | C19: =$B$19-$B$8 -> -2996.3325 | D19: =$C$19*(1-$F$8) -> -2606.8093 | E19: =$C$8-$D$19 -> 88389.669 | F19: =$E$19/$E$8 -> 34.288933 | G19: =IFERROR($F$19/$D$8-1,"") -> 0.030316504
A20: ORCL | B20: =$H$9/6 -> 6876.4025 | C20: =$B$20-$B$9 -> -625.1275 | D20: =$C$20*(1-$F$9) -> -500.102 | E20: =$C$9-$D$20 -> 16320.652 | F20: =$E$20/$E$9 -> 5.5973921 | G20: =IFERROR($F$20/$D$9-1,"") -> 0.030827275
A22: Useful Life = 5 Years (Straight-Line)
A23: Company | B23: New D&A ($mm) | C23: Δ D&A ($mm) | D23: Δ After-tax ($mm) | E23: Adj NI ($mm) | F23: Adj EPS ($) | G23: EPS Δ% vs Current
A24: MSFT | B24: =$H$5/5 -> 38846.181 | C24: =$B$24-$B$5 -> -792.7792 | D24: =$C$24*(1-$F$5) -> -650.07894 | E24: =$C$5-$D$24 -> 130022.94 | F24: =$E$24/$E$5 -> 17.443448 | G24: =IFERROR($F$24/$D$5-1,"") -> 0.041399887
A25: AMZN | B25: =$H$6/5 -> 89293.402 | C25: =$B$25-$B$6 -> 8117.582 | D25: =$C$25*(1-$F$6) -> 6494.0656 | E25: =$C$6-$D$25 -> 91839.654 | F25: =$E$25/$E$6 -> 8.4198243 | G25: =IFERROR($F$25/$D$6-1,"") -> -0.066538327
A26: GOOGL | B26: =$H$7/5 -> 51449.64 | C26: =$B$26-$B$7 -> 8574.94 | D26: =$C$26*(1-$F$7) -> 7202.9496 | E26: =$C$7-$D$26 -> 161340.33 | F26: =$E$26/$E$7 -> 13.142787 | G26: =IFERROR($F$26/$D$7-1,"") -> -0.042768592
A27: META | B27: =$H$8/5 -> 39551.589 | C27: =$B$27-$B$8 -> 3595.599 | D27: =$C$27*(1-$F$8) -> 3128.1711 | E27: =$C$8-$D$27 -> 82654.689 | F27: =$E$27/$E$8 -> 32.064167 | G27: =IFERROR($F$27/$D$8-1,"") -> -0.036533446
A28: ORCL | B28: =$H$9/5 -> 8251.683 | C28: =$B$28-$B$9 -> 750.153 | D28: =$C$28*(1-$F$9) -> 600.1224 | E28: =$C$9-$D$28 -> 15220.428 | F28: =$E$28/$E$9 -> 5.220055 | G28: =IFERROR($F$28/$D$9-1,"") -> -0.038663902
A30: Useful Life = 4 Years (Straight-Line)
A31: Company | B31: New D&A ($mm) | C31: Δ D&A ($mm) | D31: Δ After-tax ($mm) | E31: Adj NI ($mm) | F31: Adj EPS ($) | G31: EPS Δ% vs Current
A32: MSFT | B32: =$H$5/4 -> 48557.726 | C32: =$B$32-$B$5 -> 8918.766 | D32: =$C$32*(1-$F$5) -> 7313.3881 | E32: =$C$5-$D$32 -> 122059.47 | F32: =$E$32/$E$5 -> 16.375096 | G32: =IFERROR($F$32/$D$5-1,"") -> -0.022382348
A33: AMZN | B33: =$H$6/4 -> 111616.75 | C33: =$B$33-$B$6 -> 30440.932 | D33: =$C$33*(1-$F$6) -> 24352.746 | E33: =$C$6-$D$33 -> 73980.974 | F33: =$E$33/$E$6 -> 6.7825473 | G33: =IFERROR($F$33/$D$6-1,"") -> -0.24805462
A34: GOOGL | B34: =$H$7/4 -> 64312.05 | C34: =$B$34-$B$7 -> 21437.35 | D34: =$C$34*(1-$F$7) -> 18007.374 | E34: =$C$7-$D$34 -> 150535.91 | F34: =$E$34/$E$7 -> 12.262659 | G34: =IFERROR($F$34/$D$7-1,"") -> -0.10687119
A35: META | B35: =$H$8/4 -> 49439.486 | C35: =$B$35-$B$8 -> 13483.496 | D35: =$C$35*(1-$F$8) -> 11730.642 | E35: =$C$8-$D$35 -> 74052.218 | F35: =$E$35/$E$8 -> 28.727017 | G35: =IFERROR($F$35/$D$8-1,"") -> -0.13680837
A36: ORCL | B36: =$H$9/4 -> 10314.604 | C36: =$B$36-$B$9 -> 2813.0738 | D36: =$C$36*(1-$F$9) -> 2250.459 | E36: =$C$9-$D$36 -> 13570.091 | F36: =$E$36/$E$9 -> 4.6540494 | G36: =IFERROR($F$36/$D$9-1,"") -> -0.14290067
A38: Useful Life = 3 Years (Straight-Line)
A39: Company | B39: New D&A ($mm) | C39: Δ D&A ($mm) | D39: Δ After-tax ($mm) | E39: Adj NI ($mm) | F39: Adj EPS ($) | G39: EPS Δ% vs Current
A40: MSFT | B40: =$H$5/3 -> 64743.635 | C40: =$B$40-$B$5 -> 25104.675 | D40: =$C$40*(1-$F$5) -> 20585.833 | E40: =$C$5-$D$40 -> 108787.03 | F40: =$E$40/$E$5 -> 14.594508 | G40: =IFERROR($F$40/$D$5-1,"") -> -0.12868607
A41: AMZN | B41: =$H$6/3 -> 148822.34 | C41: =$B$41-$B$6 -> 67646.517 | D41: =$C$41*(1-$F$6) -> 54117.213 | E41: =$C$6-$D$41 -> 44216.507 | F41: =$E$41/$E$6 -> 4.0537524 | G41: =IFERROR($F$41/$D$6-1,"") -> -0.55058178
A42: GOOGL | B42: =$H$7/3 -> 85749.4 | C42: =$B$42-$B$7 -> 42874.7 | D42: =$C$42*(1-$F$7) -> 36014.748 | E42: =$C$7-$D$42 -> 132528.53 | F42: =$E$42/$E$7 -> 10.795777 | G42: =IFERROR($F$42/$D$7-1,"") -> -0.21370885
A43: META | B43: =$H$8/3 -> 65919.315 | C43: =$B$43-$B$8 -> 29963.325 | D43: =$C$43*(1-$F$8) -> 26068.093 | E43: =$C$8-$D$43 -> 59714.767 | F43: =$E$43/$E$8 -> 23.165102 | G43: =IFERROR($F$43/$D$8-1,"") -> -0.30393325
A44: ORCL | B44: =$H$9/3 -> 13752.805 | C44: =$B$44-$B$9 -> 6251.275 | D44: =$C$44*(1-$F$9) -> 5001.02 | E44: =$C$9-$D$44 -> 10819.53 | F44: =$E$44/$E$9 -> 3.7107066 | G44: =IFERROR($F$44/$D$9-1,"") -> -0.31662861
A46: Useful Life = 2 Years (Straight-Line)
A47: Company | B47: New D&A ($mm) | C47: Δ D&A ($mm) | D47: Δ After-tax ($mm) | E47: Adj NI ($mm) | F47: Adj EPS ($) | G47: EPS Δ% vs Current
A48: MSFT | B48: =$H$5/2 -> 97115.452 | C48: =$B$48-$B$5 -> 57476.492 | D48: =$C$48*(1-$F$5) -> 47130.723 | E48: =$C$5-$D$48 -> 82242.137 | F48: =$E$48/$E$5 -> 11.033333 | G48: =IFERROR($F$48/$D$5-1,"") -> -0.34129353
A49: AMZN | B49: =$H$6/2 -> 223233.51 | C49: =$B$49-$B$6 -> 142057.68 | D49: =$C$49*(1-$F$6) -> 113646.15 | E49: =$C$6-$D$49 -> -15312.428 | F49: =$E$49/$E$6 -> -1.4038375 | G49: =IFERROR($F$49/$D$6-1,"") -> -1.1556361
A50: GOOGL | B50: =$H$7/2 -> 128624.1 | C50: =$B$50-$B$7 -> 85749.4 | D50: =$C$50*(1-$F$7) -> 72029.496 | E50: =$C$7-$D$50 -> 96513.784 | F50: =$E$50/$E$7 -> 7.8620152 | G50: =IFERROR($F$50/$D$7-1,"") -> -0.42738418
A51: META | B51: =$H$8/2 -> 98878.973 | C51: =$B$51-$B$8 -> 62922.982 | D51: =$C$51*(1-$F$8) -> 54742.995 | E51: =$C$8-$D$51 -> 31039.865 | F51: =$E$51/$E$8 -> 12.04127 | G51: =IFERROR($F$51/$D$8-1,"") -> -0.63818299
A52: ORCL | B52: =$H$9/2 -> 20629.208 | C52: =$B$52-$B$9 -> 13127.677 | D52: =$C$52*(1-$F$9) -> 10502.142 | E52: =$C$9-$D$52 -> 5318.408 | F52: =$E$52/$E$9 -> 1.8240212 | G52: =IFERROR($F$52/$D$9-1,"") -> -0.6640845
A55: C. Accelerated Depreciation (Double-Declining Balance) vs Straight-Line
A56: DDB rate = 2/life. For a growing capex portfolio, DDB front-loads depreciation heavily on newest (largest) purchases. Modeled as: DDB D&A ≈ Base × (2/life) for current-year impact.
A57: DDB with 6-Year Life (DDB rate = 33%/yr)
A58: Company | B58: SL D&A = Base/6 | C58: DDB D&A = Base×33% | D58: DDB vs SL Δ ($mm) | E58: DDB Δ After-tax | F58: DDB Adj EPS ($) | G58: DDB EPS Δ% vs Current | H58: SL EPS Δ% (ref)
A59: MSFT | B59: =$H$5/6 -> 32371.817 | C59: =$H$5*0.3333 -> 64737.16 | D59: =$C$59-$B$5 -> 25098.2 | E59: =$D$59*(1-$F$5) -> 20580.524 | F59: =($C$5-$E$59)/$E$5 -> 14.595221 | G59: =IFERROR($F$59/$D$5-1,"") -> -0.12864355 | H59: =IFERROR(($C$5-($B$59-$B$5)*(1-$F$5))/$E$5/$D$5-1,"") -> 0.083921378
A60: AMZN | B60: =$H$6/6 -> 74411.168 | C60: =$H$6*0.3333 -> 148807.45 | D60: =$C$60-$B$6 -> 67631.634 | E60: =$D$60*(1-$F$6) -> 54105.308 | F60: =($C$6-$E$60)/$E$6 -> 4.0548439 | G60: =IFERROR($F$60/$D$6-1,"") -> -0.55046077 | H60: =IFERROR(($C$6-($B$60-$B$6)*(1-$F$6))/$E$6/$D$6-1,"") -> 0.054472535
A61: GOOGL | B61: =$H$7/6 -> 42874.7 | C61: =$H$7*0.3333 -> 85740.825 | D61: =$C$61-$B$7 -> 42866.125 | E61: =$D$61*(1-$F$7) -> 36007.545 | F61: =($C$7-$E$61)/$E$7 -> 10.796364 | G61: =IFERROR($F$61/$D$7-1,"") -> -0.21366612 | H61: =IFERROR(($C$7-($B$61-$B$7)*(1-$F$7))/$E$7/$D$7-1,"") -> -3.3526169e-05
A62: META | B62: =$H$8/6 -> 32959.658 | C62: =$H$8*0.3333 -> 65912.723 | D62: =$C$62-$B$8 -> 29956.733 | E62: =$D$62*(1-$F$8) -> 26062.358 | F62: =($C$8-$E$62)/$E$8 -> 23.167326 | G62: =IFERROR($F$62/$D$8-1,"") -> -0.3038664 | H62: =IFERROR(($C$8-($B$62-$B$8)*(1-$F$8))/$E$8/$D$8-1,"") -> 0.030316504
A63: ORCL | B63: =$H$9/6 -> 6876.4025 | C63: =$H$9*0.3333 -> 13751.43 | D63: =$C$63-$B$9 -> 6249.8997 | E63: =$D$63*(1-$F$9) -> 4999.9198 | F63: =($C$9-$E$63)/$E$9 -> 3.711084 | G63: =IFERROR($F$63/$D$9-1,"") -> -0.31655912 | H63: =IFERROR(($C$9-($B$63-$B$9)*(1-$F$9))/$E$9/$D$9-1,"") -> 0.030827275
A65: DDB with 5-Year Life (DDB rate = 40%/yr)
A66: Company | B66: SL D&A = Base/5 | C66: DDB D&A = Base×40% | D66: DDB vs SL Δ ($mm) | E66: DDB Δ After-tax | F66: DDB Adj EPS ($) | G66: DDB EPS Δ% vs Current | H66: SL EPS Δ% (ref)
A67: MSFT | B67: =$H$5/5 -> 38846.181 | C67: =$H$5*0.4 -> 77692.362 | D67: =$C$67-$B$5 -> 38053.402 | E67: =$D$67*(1-$F$5) -> 31203.789 | F67: =($C$5-$E$67)/$E$5 -> 13.170038 | G67: =IFERROR($F$67/$D$5-1,"") -> -0.21372905 | H67: =IFERROR(($C$5-($B$67-$B$5)*(1-$F$5))/$E$5/$D$5-1,"") -> 0.041399887
A68: AMZN | B68: =$H$6/5 -> 89293.402 | C68: =$H$6*0.4 -> 178586.8 | D68: =$C$68-$B$6 -> 97410.984 | E68: =$D$68*(1-$F$6) -> 77928.787 | F68: =($C$6-$E$68)/$E$6 -> 1.8707164 | G68: =IFERROR($F$68/$D$6-1,"") -> -0.7926035 | H68: =IFERROR(($C$6-($B$68-$B$6)*(1-$F$6))/$E$6/$D$6-1,"") -> -0.066538327
A69: GOOGL | B69: =$H$7/5 -> 51449.64 | C69: =$H$7*0.4 -> 102899.28 | D69: =$C$69-$B$7 -> 60024.58 | E69: =$D$69*(1-$F$7) -> 50420.647 | F69: =($C$7-$E$69)/$E$7 -> 9.6222725 | G69: =IFERROR($F$69/$D$7-1,"") -> -0.29917898 | H69: =IFERROR(($C$7-($B$69-$B$7)*(1-$F$7))/$E$7/$D$7-1,"") -> -0.042768592
A70: META | B70: =$H$8/5 -> 39551.589 | C70: =$H$8*0.4 -> 79103.178 | D70: =$C$70-$B$8 -> 43147.188 | E70: =$D$70*(1-$F$8) -> 37538.054 | F70: =($C$8-$E$70)/$E$8 -> 18.715569 | G70: =IFERROR($F$70/$D$8-1,"") -> -0.43763315 | H70: =IFERROR(($C$8-($B$70-$B$8)*(1-$F$8))/$E$8/$D$8-1,"") -> -0.036533446
A71: ORCL | B71: =$H$9/5 -> 8251.683 | C71: =$H$9*0.4 -> 16503.366 | D71: =$C$71-$B$9 -> 9001.836 | E71: =$D$71*(1-$F$9) -> 7201.4688 | F71: =($C$9-$E$71)/$E$9 -> 2.9560325 | G71: =IFERROR($F$71/$D$9-1,"") -> -0.45561097 | H71: =IFERROR(($C$9-($B$71-$B$9)*(1-$F$9))/$E$9/$D$9-1,"") -> -0.038663902
A73: DDB with 4-Year Life (DDB rate = 50%/yr)
A74: Company | B74: SL D&A = Base/4 | C74: DDB D&A = Base×50% | D74: DDB vs SL Δ ($mm) | E74: DDB Δ After-tax | F74: DDB Adj EPS ($) | G74: DDB EPS Δ% vs Current | H74: SL EPS Δ% (ref)
A75: MSFT | B75: =$H$5/4 -> 48557.726 | C75: =$H$5*0.5 -> 97115.452 | D75: =$C$75-$B$5 -> 57476.492 | E75: =$D$75*(1-$F$5) -> 47130.723 | F75: =($C$5-$E$75)/$E$5 -> 11.033333 | G75: =IFERROR($F$75/$D$5-1,"") -> -0.34129353 | H75: =IFERROR(($C$5-($B$75-$B$5)*(1-$F$5))/$E$5/$D$5-1,"") -> -0.022382348
A76: AMZN | B76: =$H$6/4 -> 111616.75 | C76: =$H$6*0.5 -> 223233.51 | D76: =$C$76-$B$6 -> 142057.68 | E76: =$D$76*(1-$F$6) -> 113646.15 | F76: =($C$6-$E$76)/$E$6 -> -1.4038375 | G76: =IFERROR($F$76/$D$6-1,"") -> -1.1556361 | H76: =IFERROR(($C$6-($B$76-$B$6)*(1-$F$6))/$E$6/$D$6-1,"") -> -0.24805462
A77: GOOGL | B77: =$H$7/4 -> 64312.05 | C77: =$H$7*0.5 -> 128624.1 | D77: =$C$77-$B$7 -> 85749.4 | E77: =$D$77*(1-$F$7) -> 72029.496 | F77: =($C$7-$E$77)/$E$7 -> 7.8620152 | G77: =IFERROR($F$77/$D$7-1,"") -> -0.42738418 | H77: =IFERROR(($C$7-($B$77-$B$7)*(1-$F$7))/$E$7/$D$7-1,"") -> -0.10687119
A78: META | B78: =$H$8/4 -> 49439.486 | C78: =$H$8*0.5 -> 98878.973 | D78: =$C$78-$B$8 -> 62922.982 | E78: =$D$78*(1-$F$8) -> 54742.995 | F78: =($C$8-$E$78)/$E$8 -> 12.04127 | G78: =IFERROR($F$78/$D$8-1,"") -> -0.63818299 | H78: =IFERROR(($C$8-($B$78-$B$8)*(1-$F$8))/$E$8/$D$8-1,"") -> -0.13680837
A79: ORCL | B79: =$H$9/4 -> 10314.604 | C79: =$H$9*0.5 -> 20629.208 | D79: =$C$79-$B$9 -> 13127.677 | E79: =$D$79*(1-$F$9) -> 10502.142 | F79: =($C$9-$E$79)/$E$9 -> 1.8240212 | G79: =IFERROR($F$79/$D$9-1,"") -> -0.6640845 | H79: =IFERROR(($C$9-($B$79-$B$9)*(1-$F$9))/$E$9/$D$9-1,"") -> -0.14290067
A81: DDB with 3-Year Life (DDB rate = 67%/yr)
A82: Company | B82: SL D&A = Base/3 | C82: DDB D&A = Base×67% | D82: DDB vs SL Δ ($mm) | E82: DDB Δ After-tax | F82: DDB Adj EPS ($) | G82: DDB EPS Δ% vs Current | H82: SL EPS Δ% (ref)
A83: MSFT | B83: =$H$5/3 -> 64743.635 | C83: =$H$5*0.6667 -> 129493.74 | D83: =$C$83-$B$5 -> 89854.784 | E83: =$D$83*(1-$F$5) -> 73680.923 | F83: =($C$5-$E$83)/$E$5 -> 7.4714464 | G83: =IFERROR($F$83/$D$5-1,"") -> -0.5539435 | H83: =IFERROR(($C$5-($B$83-$B$5)*(1-$F$5))/$E$5/$D$5-1,"") -> -0.12868607
A84: AMZN | B84: =$H$6/3 -> 148822.34 | C84: =$H$6*0.6667 -> 297659.56 | D84: =$C$84-$B$6 -> 216483.74 | E84: =$D$84*(1-$F$6) -> 173186.99 | F84: =($C$6-$E$84)/$E$6 -> -6.8625189 | G84: =IFERROR($F$84/$D$6-1,"") -> -1.7608114 | H84: =IFERROR(($C$6-($B$84-$B$6)*(1-$F$6))/$E$6/$D$6-1,"") -> -0.55058178
A85: GOOGL | B85: =$H$7/3 -> 85749.4 | C85: =$H$7*0.6667 -> 171507.37 | D85: =$C$85-$B$7 -> 128632.67 | E85: =$D$85*(1-$F$7) -> 108051.45 | F85: =($C$7-$E$85)/$E$7 -> 4.9276662 | G85: =IFERROR($F$85/$D$7-1,"") -> -0.64110224 | H85: =IFERROR(($C$7-($B$85-$B$7)*(1-$F$7))/$E$7/$D$7-1,"") -> -0.21370885
A86: META | B86: =$H$8/3 -> 65919.315 | C86: =$H$8*0.6667 -> 131845.22 | D86: =$C$86-$B$8 -> 95889.232 | E86: =$D$86*(1-$F$8) -> 83423.632 | F86: =($C$8-$E$86)/$E$8 -> 0.9152135 | G86: =IFERROR($F$86/$D$8-1,"") -> -0.97249959 | H86: =IFERROR(($C$8-($B$86-$B$8)*(1-$F$8))/$E$8/$D$8-1,"") -> -0.30393325
A87: ORCL | B87: =$H$9/3 -> 13752.805 | C87: =$H$9*0.6667 -> 27506.985 | D87: =$C$87-$B$9 -> 20005.455 | E87: =$D$87*(1-$F$9) -> 16004.364 | F87: =($C$9-$E$87)/$E$9 -> -0.063041617 | G87: =IFERROR($F$87/$D$9-1,"") -> -1.0116099 | H87: =IFERROR(($C$9-($B$87-$B$9)*(1-$F$9))/$E$9/$D$9-1,"") -> -0.31662861
A90: D. Summary: EPS Impact (%) Under Each Scenario
A91: Negative = EPS overstated under current policy. Read: 'If true life = X, 2026E EPS would be Y% lower.'
A92: Company | B92: Curr Life | C92: SL 6yr | D92: SL 5yr | E92: SL 4yr | F92: SL 3yr | G92: SL 2yr | H92: DDB 6yr | I92: DDB 5yr | J92: DDB 4yr | K92: DDB 3yr
A93: MSFT | B93: =$G$5 -> 4.9 | C93: =IFERROR(($C$5-($H$5/6-$B$5)*(1-$F$5))/$E$5/$D$5-1,"") -> 0.083921378 | D93: =IFERROR(($C$5-($H$5/5-$B$5)*(1-$F$5))/$E$5/$D$5-1,"") -> 0.041399887 | E93: =IFERROR(($C$5-($H$5/4-$B$5)*(1-$F$5))/$E$5/$D$5-1,"") -> -0.022382348 | F93: =IFERROR(($C$5-($H$5/3-$B$5)*(1-$F$5))/$E$5/$D$5-1,"") -> -0.12868607 | G93: =IFERROR(($C$5-($H$5/2-$B$5)*(1-$F$5))/$E$5/$D$5-1,"") -> -0.34129353 | H93: =IFERROR(($C$5-($H$5*0.3333-$B$5)*(1-$F$5))/$E$5/$D$5-1,"") -> -0.12864355 | I93: =IFERROR(($C$5-($H$5*0.4-$B$5)*(1-$F$5))/$E$5/$D$5-1,"") -> -0.21372905 | J93: =IFERROR(($C$5-($H$5*0.5-$B$5)*(1-$F$5))/$E$5/$D$5-1,"") -> -0.34129353 | K93: =IFERROR(($C$5-($H$5*0.6667-$B$5)*(1-$F$5))/$E$5/$D$5-1,"") -> -0.5539435
A94: AMZN | B94: =$G$6 -> 5.5 | C94: =IFERROR(($C$6-($H$6/6-$B$6)*(1-$F$6))/$E$6/$D$6-1,"") -> 0.054472535 | D94: =IFERROR(($C$6-($H$6/5-$B$6)*(1-$F$6))/$E$6/$D$6-1,"") -> -0.066538327 | E94: =IFERROR(($C$6-($H$6/4-$B$6)*(1-$F$6))/$E$6/$D$6-1,"") -> -0.24805462 | F94: =IFERROR(($C$6-($H$6/3-$B$6)*(1-$F$6))/$E$6/$D$6-1,"") -> -0.55058178 | G94: =IFERROR(($C$6-($H$6/2-$B$6)*(1-$F$6))/$E$6/$D$6-1,"") -> -1.1556361 | H94: =IFERROR(($C$6-($H$6*0.3333-$B$6)*(1-$F$6))/$E$6/$D$6-1,"") -> -0.55046077 | I94: =IFERROR(($C$6-($H$6*0.4-$B$6)*(1-$F$6))/$E$6/$D$6-1,"") -> -0.7926035 | J94: =IFERROR(($C$6-($H$6*0.5-$B$6)*(1-$F$6))/$E$6/$D$6-1,"") -> -1.1556361 | K94: =IFERROR(($C$6-($H$6*0.6667-$B$6)*(1-$F$6))/$E$6/$D$6-1,"") -> -1.7608114
A95: GOOGL | B95: =$G$7 -> 6 | C95: =IFERROR(($C$7-($H$7/6-$B$7)*(1-$F$7))/$E$7/$D$7-1,"") -> -3.3526169e-05 | D95: =IFERROR(($C$7-($H$7/5-$B$7)*(1-$F$7))/$E$7/$D$7-1,"") -> -0.042768592 | E95: =IFERROR(($C$7-($H$7/4-$B$7)*(1-$F$7))/$E$7/$D$7-1,"") -> -0.10687119 | F95: =IFERROR(($C$7-($H$7/3-$B$7)*(1-$F$7))/$E$7/$D$7-1,"") -> -0.21370885 | G95: =IFERROR(($C$7-($H$7/2-$B$7)*(1-$F$7))/$E$7/$D$7-1,"") -> -0.42738418 | H95: =IFERROR(($C$7-($H$7*0.3333-$B$7)*(1-$F$7))/$E$7/$D$7-1,"") -> -0.21366612 | I95: =IFERROR(($C$7-($H$7*0.4-$B$7)*(1-$F$7))/$E$7/$D$7-1,"") -> -0.29917898 | J95: =IFERROR(($C$7-($H$7*0.5-$B$7)*(1-$F$7))/$E$7/$D$7-1,"") -> -0.42738418 | K95: =IFERROR(($C$7-($H$7*0.6667-$B$7)*(1-$F$7))/$E$7/$D$7-1,"") -> -0.64110224
A96: META | B96: =$G$8 -> 5.5 | C96: =IFERROR(($C$8-($H$8/6-$B$8)*(1-$F$8))/$E$8/$D$8-1,"") -> 0.030316504 | D96: =IFERROR(($C$8-($H$8/5-$B$8)*(1-$F$8))/$E$8/$D$8-1,"") -> -0.036533446 | E96: =IFERROR(($C$8-($H$8/4-$B$8)*(1-$F$8))/$E$8/$D$8-1,"") -> -0.13680837 | F96: =IFERROR(($C$8-($H$8/3-$B$8)*(1-$F$8))/$E$8/$D$8-1,"") -> -0.30393325 | G96: =IFERROR(($C$8-($H$8/2-$B$8)*(1-$F$8))/$E$8/$D$8-1,"") -> -0.63818299 | H96: =IFERROR(($C$8-($H$8*0.3333-$B$8)*(1-$F$8))/$E$8/$D$8-1,"") -> -0.3038664 | I96: =IFERROR(($C$8-($H$8*0.4-$B$8)*(1-$F$8))/$E$8/$D$8-1,"") -> -0.43763315 | J96: =IFERROR(($C$8-($H$8*0.5-$B$8)*(1-$F$8))/$E$8/$D$8-1,"") -> -0.63818299 | K96: =IFERROR(($C$8-($H$8*0.6667-$B$8)*(1-$F$8))/$E$8/$D$8-1,"") -> -0.97249959
A97: ORCL | B97: =$G$9 -> 5.5 | C97: =IFERROR(($C$9-($H$9/6-$B$9)*(1-$F$9))/$E$9/$D$9-1,"") -> 0.030827275 | D97: =IFERROR(($C$9-($H$9/5-$B$9)*(1-$F$9))/$E$9/$D$9-1,"") -> -0.038663902 | E97: =IFERROR(($C$9-($H$9/4-$B$9)*(1-$F$9))/$E$9/$D$9-1,"") -> -0.14290067 | F97: =IFERROR(($C$9-($H$9/3-$B$9)*(1-$F$9))/$E$9/$D$9-1,"") -> -0.31662861 | G97: =IFERROR(($C$9-($H$9/2-$B$9)*(1-$F$9))/$E$9/$D$9-1,"") -> -0.6640845 | H97: =IFERROR(($C$9-($H$9*0.3333-$B$9)*(1-$F$9))/$E$9/$D$9-1,"") -> -0.31655912 | I97: =IFERROR(($C$9-($H$9*0.4-$B$9)*(1-$F$9))/$E$9/$D$9-1,"") -> -0.45561097 | J97: =IFERROR(($C$9-($H$9*0.5-$B$9)*(1-$F$9))/$E$9/$D$9-1,"") -> -0.6640845 | K97: =IFERROR(($C$9-($H$9*0.6667-$B$9)*(1-$F$9))/$E$9/$D$9-1,"") -> -1.0116099

Sheet 7. SP500 AI EPS Split
A1: S&P 500 EPS Decomposition: AI vs Non-AI + Valuation Framework
A3: A. S&P 500 EPS Decomposition (Historical + Estimates)
A4: Metric | B4: 2018A | C4: 2019A | D4: 2020A | E4: 2021A | F4: 2022A | G4: 2023A | H4: 2024A | I4: 2025A | J4: 2026E | K4: 2027E | L4: 2028E | M4: 2029E | N4: 2030E
A5: S&P 500 Total EPS ($) | B5: 152 | C5: 157 | D5: 139 | E5: 208 | F5: 218 | G5: 221 | H5: 240 | I5: 262 | J5: 275 | K5: 300 | L5: 325 | M5: 350 | N5: 375
A6: AI-Driven EPS ($) — assumption | B6: 0 | C6: 0 | D6: 0 | E6: 0 | F6: 2 | G6: 8 | H6: 22 | I6: 40 | J6: 55 | K6: 65 | L6: 70 | M6: 72 | N6: 73
A7: Non-AI EPS ($) = Total - AI | B7: =B5-B6 -> 152 | C7: =C5-C6 -> 157 | D7: =D5-D6 -> 139 | E7: =E5-E6 -> 208 | F7: =F5-F6 -> 216 | G7: =G5-G6 -> 213 | H7: =H5-H6 -> 218 | I7: =I5-I6 -> 222 | ... N7: =N5-N6 -> 302
A8: AI % of Total EPS | B8: =IFERROR(B6/B5,"") -> 0 | C8: =IFERROR(C6/C5,"") -> 0 | D8: =IFERROR(D6/D5,"") -> 0 | E8: =IFERROR(E6/E5,"") -> 0 | F8: =IFERROR(F6/F5,"") -> 0.0091743119 | G8: =IFERROR(G6/G5,"") -> 0.036199095 | H8: =IFERROR(H6/H5,"") -> 0.091666667 | I8: =IFERROR(I6/I5,"") -> 0.15267176 | ... N8: =IFERROR(N6/N5,"") -> 0.19466667
A9: AI EPS YoY % | C9: =IFERROR(C6/B6-1,"") | D9: =IFERROR(D6/C6-1,"") | E9: =IFERROR(E6/D6-1,"") | F9: =IFERROR(F6/E6-1,"") | G9: =IFERROR(G6/F6-1,"") -> 3 | H9: =IFERROR(H6/G6-1,"") -> 1.75 | I9: =IFERROR(I6/H6-1,"") -> 0.81818182 | J9: =IFERROR(J6/I6-1,"") -> 0.375 | ... N9: =IFERROR(N6/M6-1,"") -> 0.013888889
A10: Non-AI EPS YoY % | C10: =IFERROR(C7/B7-1,"") -> 0.032894737 | D10: =IFERROR(D7/C7-1,"") -> -0.11464968 | E10: =IFERROR(E7/D7-1,"") -> 0.49640288 | F10: =IFERROR(F7/E7-1,"") -> 0.038461538 | G10: =IFERROR(G7/F7-1,"") -> -0.013888889 | H10: =IFERROR(H7/G7-1,"") -> 0.023474178 | I10: =IFERROR(I7/H7-1,"") -> 0.018348624 | J10: =IFERROR(J7/I7-1,"") -> -0.009009009 | ... N10: =IFERROR(N7/M7-1,"") -> 0.086330935
A12: B. Dual P/E Valuation — Different Multiples for AI vs Non-AI EPS
A13: Yellow cells = editable assumptions. Change P/E multiples to see impact on implied S&P 500 level.
A14: Non-AI P/E Multiple (editable) | B14: 18 | C14: (historical avg ~18-20x for broad market ex-tech)
A15: AI P/E Multiple (editable) | B15: 35 | C15: (NVDA trades ~30-40x fwd; AI infra basket ~35x)
A17: Metric | B17: 2024A | C17: 2025A | D17: 2026E | E17: 2027E | F17: 2028E | G17: 2029E | H17: 2030E
A18: Non-AI Value Component | B18: =H7*$B$14 -> 3924 | C18: =I7*$B$14 -> 3996 | D18: =J7*$B$14 -> 3960 | E18: =K7*$B$14 -> 4230 | F18: =L7*$B$14 -> 4590 | G18: =M7*$B$14 -> 5004 | H18: =N7*$B$14 -> 5436
A19: AI Value Component | B19: =H6*$B$15 -> 770 | C19: =I6*$B$15 -> 1400 | D19: =J6*$B$15 -> 1925 | E19: =K6*$B$15 -> 2275 | F19: =L6*$B$15 -> 2450 | G19: =M6*$B$15 -> 2520 | H19: =N6*$B$15 -> 2555
A20: Implied S&P 500 Level | B20: =B18+B19 -> 4694 | C20: =C18+C19 -> 5396 | D20: =D18+D19 -> 5885 | E20: =E18+E19 -> 6505 | F20: =F18+F19 -> 7040 | G20: =G18+G19 -> 7524 | H20: =H18+H19 -> 7991
A21: Blended P/E (implied) | B21: =IFERROR(B20/H5,"") -> 19.558333 | C21: =IFERROR(C20/I5,"") -> 20.59542 | D21: =IFERROR(D20/J5,"") -> 21.4 | E21: =IFERROR(E20/K5,"") -> 21.683333 | F21: =IFERROR(F20/L5,"") -> 21.661538 | G21: =IFERROR(G20/M5,"") -> 21.497143 | H21: =IFERROR(H20/N5,"") -> 21.309333
A23: C. Stress Test Scenarios — What if AI Capex Slows / Collapses?
A24: Scenario: Base Case
A25: Current consensus. AI EPS keeps growing as capex sustains.
A26: Metric | B26: 2024A | C26: 2025A | D26: 2026E | E26: 2027E | F26: 2028E | G26: 2029E | H26: 2030E
A27: AI EPS ($) | B27: 22 | C27: 40 | D27: 55 | E27: 65 | F27: 70 | G27: 72 | H27: 73
A28: Non-AI EPS ($) | B28: 218 | C28: 222 | D28: 220 | E28: 235 | F28: 255 | G28: 278 | H28: 302
A29: Implied S&P 500 (AI PE=35x, Other=18x) | B29: =B27*35+B28*18 -> 4694 | C29: =C27*35+C28*18 -> 5396 | D29: =D27*35+D28*18 -> 5885 | E29: =E27*35+E28*18 -> 6505 | F29: =F27*35+F28*18 -> 7040 | G29: =G27*35+G28*18 -> 7524 | H29: =H27*35+H28*18 -> 7991
A31: Scenario: Slowdown (-30% AI EPS)
A32: AI capex growth decelerates 2027+. Nvidia/Broadcom revenue stalls. AI P/E compresses.
A33: Metric | B33: 2024A | C33: 2025A | D33: 2026E | E33: 2027E | F33: 2028E | G33: 2029E | H33: 2030E
A34: AI EPS ($) | B34: 22 | C34: 40 | D34: 39 | E34: 46 | F34: 49 | G34: 50 | H34: 51
A35: Non-AI EPS ($) | B35: 218 | C35: 222 | D35: 220 | E35: 235 | F35: 255 | G35: 278 | H35: 302
A36: Implied S&P 500 (AI PE=25x, Other=18x) | B36: =B34*25+B35*18 -> 4474 | C36: =C34*25+C35*18 -> 4996 | D36: =D34*25+D35*18 -> 4935 | E36: =E34*25+E35*18 -> 5380 | F36: =F34*25+F35*18 -> 5815 | G36: =G34*25+G35*18 -> 6254 | H36: =H34*25+H35*18 -> 6711
A37: Δ vs Base Case | B37: =IFERROR(B36/B29-1,"") -> -0.046868343 | C37: =IFERROR(C36/C29-1,"") -> -0.074128984 | D37: =IFERROR(D36/D29-1,"") -> -0.16142736 | E37: =IFERROR(E36/E29-1,"") -> -0.17294389 | F37: =IFERROR(F36/F29-1,"") -> -0.17400568 | G37: =IFERROR(G36/G29-1,"") -> -0.1687932 | H37: =IFERROR(H36/H29-1,"") -> -0.1601802
A39: Scenario: Collapse (-60% AI EPS)
A40: Customer crack (OpenAI/Anthropic). Capex cut 40%. Massive write-downs. AI P/E crashes.
A41: Metric | B41: 2024A | C41: 2025A | D41: 2026E | E41: 2027E | F41: 2028E | G41: 2029E | H41: 2030E
A42: AI EPS ($) | B42: 22 | C42: 40 | D42: 55 | E42: 26 | F42: 22 | G42: 20 | H42: 20
A43: Non-AI EPS ($) | B43: 218 | C43: 222 | D43: 220 | E43: 235 | F43: 255 | G43: 278 | H43: 302
A44: Implied S&P 500 (AI PE=15x, Other=18x) | B44: =B42*15+B43*18 -> 4254 | C44: =C42*15+C43*18 -> 4596 | D44: =D42*15+D43*18 -> 4785 | E44: =E42*15+E43*18 -> 4620 | F44: =F42*15+F43*18 -> 4920 | G44: =G42*15+G43*18 -> 5304 | H44: =H42*15+H43*18 -> 5736
A45: Δ vs Base Case | B45: =IFERROR(B44/B29-1,"") -> -0.093736685 | C45: =IFERROR(C44/C29-1,"") -> -0.14825797 | D45: =IFERROR(D44/D29-1,"") -> -0.18691589 | E45: =IFERROR(E44/E29-1,"") -> -0.28977709 | F45: =IFERROR(F44/F29-1,"") -> -0.30113636 | G45: =IFERROR(G44/G29-1,"") -> -0.29505582 | H45: =IFERROR(H44/H29-1,"") -> -0.28219247
A47: Scenario: Bubble Pop (no AI premium)
A48: AI EPS holds but market stops paying a premium. AI P/E = Non-AI P/E.
A49: Metric | B49: 2024A | C49: 2025A | D49: 2026E | E49: 2027E | F49: 2028E | G49: 2029E | H49: 2030E
A50: AI EPS ($) | B50: 22 | C50: 40 | D50: 55 | E50: 65 | F50: 70 | G50: 72 | H50: 73
A51: Non-AI EPS ($) | B51: 218 | C51: 222 | D51: 220 | E51: 235 | F51: 255 | G51: 278 | H51: 302
A52: Implied S&P 500 (AI PE=18x, Other=18x) | B52: =B50*18+B51*18 -> 4320 | C52: =C50*18+C51*18 -> 4716 | D52: =D50*18+D51*18 -> 4950 | E52: =E50*18+E51*18 -> 5400 | F52: =F50*18+F51*18 -> 5850 | G52: =G50*18+G51*18 -> 6300 | H52: =H50*18+H51*18 -> 6750
A53: Δ vs Base Case | B53: =IFERROR(B52/B29-1,"") -> -0.079676182 | C53: =IFERROR(C52/C29-1,"") -> -0.12601927 | D53: =IFERROR(D52/D29-1,"") -> -0.1588785 | E53: =IFERROR(E52/E29-1,"") -> -0.16986933 | F53: =IFERROR(F52/F29-1,"") -> -0.16903409 | G53: =IFERROR(G52/G29-1,"") -> -0.16267943 | H53: =IFERROR(H52/H29-1,"") -> -0.15529971
A55: D. AI EPS Bridge — Where Does $55 of AI EPS Come From? (2026E Estimate)
A56: Source | B56: Revenue / NI Basis | I56: Est. S&P 500 EPS ($)
A57: Nvidia (GPU/accelerator) | B57: $140-165B NI → ~$28-33 of S&P EPS | I57: $30
A58: Broadcom (custom AI + networking) | B58: $18-20B NI | I58: $4
A59: Micron (HBM memory) | B59: $8-10B NI | I59: $2
A60: AMD (MI300/400 series) | B60: $5-7B AI-attributable NI | I60: $1
A61: TSMC (foundry — NOT in S&P, but via ADR) | B61: Not directly in S&P 500 | I61: $0
A62: Arista / Cisco (networking) | B62: $5-7B combined AI NI | I62: $1
A63: Vertiv / Eaton / power infra | B63: $2-3B NI | I63: $0.5
A64: Construction / utilities / other | B64: $7-10B NI | I64: $1.5
A65: Hyperscaler AI-specific revenue margin | B65: $30-40B incremental NI from AI cloud rev | I65: $8
A66: AI software / SaaS (early) | B66: $3-5B NI | I66: $1
A67: Subtotal: direct AI EPS contribution | I67: ~$49-52
A68: Multiplier / 2nd-order effects | B68: Capex flows → wages, suppliers, etc. | I68: ~$3-6
A69: TOTAL AI-DRIVEN EPS (est.) | I69: ~$55

Sheet 8. Charts
A1: Visual Summary (2013-2030)
A3: Capex/Rev %
B4: 2013 | C4: 2014 | D4: 2015 | E4: 2016 | F4: 2017 | G4: 2018 | H4: 2019 | I4: 2020 | J4: 2021 | K4: 2022 | L4: 2023 | M4: 2024 | N4: 2025 | O4: 2026 | P4: 2027 | Q4: 2028 | R4: 2029 | S4: 2030
A5: MSFT | B5: =IFERROR('0. Database'!C12/'0. Database'!C5,"") -> 0.054682783 | C5: =IFERROR('0. Database'!D12/'0. Database'!D5,"") -> 0.063167229 | D5: =IFERROR('0. Database'!E12/'0. Database'!E5,"") -> 0.063517846 | E5: =IFERROR('0. Database'!F12/'0. Database'!F5,"") -> 0.10468823 | F5: =IFERROR('0. Database'!G12/'0. Database'!G5,"") -> 0.10562177 | G5: =IFERROR('0. Database'!H12/'0. Database'!H5,"") -> 0.12323306 | H5: =IFERROR('0. Database'!I12/'0. Database'!I5,"") -> 0.13429432 | I5: =IFERROR('0. Database'!J12/'0. Database'!J5,"") -> 0.1328532 | ... S5: =IFERROR('0. Database'!T12/'0. Database'!T5,"") -> 0.46664954
A6: AMZN | B6: =IFERROR('0. Database'!C28/'0. Database'!C21,"") -> 0.046243939 | C6: =IFERROR('0. Database'!D28/'0. Database'!D21,"") -> 0.054973457 | D6: =IFERROR('0. Database'!E28/'0. Database'!E21,"") -> 0.04287586 | E6: =IFERROR('0. Database'!F28/'0. Database'!F21,"") -> 0.049534147 | F6: =IFERROR('0. Database'!G28/'0. Database'!G21,"") -> 0.056542566 | G6: =IFERROR('0. Database'!H28/'0. Database'!H21,"") -> 0.048615852 | H6: =IFERROR('0. Database'!I28/'0. Database'!I21,"") -> 0.045237094 | I6: =IFERROR('0. Database'!J28/'0. Database'!J21,"") -> 0.090777695 | ... S6: =IFERROR('0. Database'!T28/'0. Database'!T21,"") -> 0.23955807
A7: GOOGL | B7: =IFERROR('0. Database'!C43/'0. Database'!C36,"") -> 0.13253121 | C7: =IFERROR('0. Database'!D43/'0. Database'!D36,"") -> 0.16604294 | D7: =IFERROR('0. Database'!E43/'0. Database'!E36,"") -> 0.13221939 | E7: =IFERROR('0. Database'!F43/'0. Database'!F36,"") -> 0.11280353 | F7: =IFERROR('0. Database'!G43/'0. Database'!G36,"") -> 0.11893013 | G7: =IFERROR('0. Database'!H43/'0. Database'!H36,"") -> 0.1837391 | H7: =IFERROR('0. Database'!I43/'0. Database'!I36,"") -> 0.14548645 | I7: =IFERROR('0. Database'!J43/'0. Database'!J36,"") -> 0.12206961 | ... S7: =IFERROR('0. Database'!T43/'0. Database'!T36,"") -> 0.34115258
A8: META | B8: =IFERROR('0. Database'!C60/'0. Database'!C53,"") -> 0.17301829 | C8: =IFERROR('0. Database'!D60/'0. Database'!D53,"") -> 0.14687951 | D8: =IFERROR('0. Database'!E60/'0. Database'!E53,"") -> 0.14073744 | E8: =IFERROR('0. Database'!F60/'0. Database'!F53,"") -> 0.16249367 | F8: =IFERROR('0. Database'!G60/'0. Database'!G53,"") -> 0.16559663 | G8: =IFERROR('0. Database'!H60/'0. Database'!H53,"") -> 0.25036713 | H8: =IFERROR('0. Database'!I60/'0. Database'!I53,"") -> 0.21361736 | I8: =IFERROR('0. Database'!J60/'0. Database'!J53,"") -> 0.17582533 | ... S8: =IFERROR('0. Database'!T60/'0. Database'!T53,"") -> 0.45713217
A9: ORCL | B9: =IFERROR('0. Database'!C78/'0. Database'!C71,"") -> 0.017448259 | C9: =IFERROR('0. Database'!D78/'0. Database'!D71,"") -> 0.015141626 | D9: =IFERROR('0. Database'!E78/'0. Database'!E71,"") -> 0.036363161 | E9: =IFERROR('0. Database'!F78/'0. Database'!F71,"") -> 0.032085706 | F9: =IFERROR('0. Database'!G78/'0. Database'!G71,"") -> 0.053325945 | G9: =IFERROR('0. Database'!H78/'0. Database'!H71,"") -> 0.044026274 | H9: =IFERROR('0. Database'!I78/'0. Database'!I71,"") -> 0.041998735 | I9: =IFERROR('0. Database'!J78/'0. Database'!J71,"") -> 0.040027641 | ... S9: =IFERROR('0. Database'!T78/'0. Database'!T71,"") -> 0.35816783
A12: FCF Margin %
B13: 2013 | C13: 2014 | D13: 2015 | E13: 2016 | F13: 2017 | G13: 2018 | H13: 2019 | I13: 2020 | J13: 2021 | K13: 2022 | L13: 2023 | M13: 2024 | N13: 2025 | O13: 2026 | P13: 2027 | Q13: 2028 | R13: 2029 | S13: 2030
A14: MSFT | B14: =IFERROR('0. Database'!C14/'0. Database'!C5,"") -> 0.31568806 | C14: =IFERROR('0. Database'!D14/'0. Database'!D5,"") -> 0.30801654 | D14: =IFERROR('0. Database'!E14/'0. Database'!E5,"") -> 0.24723231 | E14: =IFERROR('0. Database'!F14/'0. Database'!F5,"") -> 0.28590014 | F14: =IFERROR('0. Database'!G14/'0. Database'!G5,"") -> 0.3034762 | G14: =IFERROR('0. Database'!H14/'0. Database'!H5,"") -> 0.27441102 | H14: =IFERROR('0. Database'!I14/'0. Database'!I5,"") -> 0.28038906 | I14: =IFERROR('0. Database'!J14/'0. Database'!J5,"") -> 0.291403 | ... S14: =IFERROR('0. Database'!T14/'0. Database'!T5,"") -> 0.20517536
A15: AMZN | B15: =IFERROR('0. Database'!C30/'0. Database'!C21,"") -> 0.027278955 | C15: =IFERROR('0. Database'!D30/'0. Database'!D21,"") -> 0.021906226 | D15: =IFERROR('0. Database'!E30/'0. Database'!E21,"") -> 0.068520073 | E15: =IFERROR('0. Database'!F30/'0. Database'!F21,"") -> 0.077470641 | F15: =IFERROR('0. Database'!G30/'0. Database'!G21,"") -> 0.047097253 | G15: =IFERROR('0. Database'!H30/'0. Database'!H21,"") -> 0.08331079 | H15: =IFERROR('0. Database'!I30/'0. Database'!I21,"") -> 0.092060516 | I15: =IFERROR('0. Database'!J30/'0. Database'!J21,"") -> 0.080344192 | ... S15: =IFERROR('0. Database'!T30/'0. Database'!T21,"") -> 0.067685424
A16: GOOGL | B16: =IFERROR('0. Database'!C45/'0. Database'!C36,"") -> 0.20220105 | C16: =IFERROR('0. Database'!D45/'0. Database'!D36,"") -> 0.17140649 | D16: =IFERROR('0. Database'!E45/'0. Database'!E36,"") -> 0.21221779 | E16: =IFERROR('0. Database'!F45/'0. Database'!F36,"") -> 0.28639002 | F16: =IFERROR('0. Database'!G45/'0. Database'!G36,"") -> 0.2156601 | G16: =IFERROR('0. Database'!H45/'0. Database'!H36,"") -> 0.16687741 | H16: =IFERROR('0. Database'!I45/'0. Database'!I36,"") -> 0.1913541 | I16: =IFERROR('0. Database'!J45/'0. Database'!J36,"") -> 0.23472144 | ... S16: =IFERROR('0. Database'!T45/'0. Database'!T36,"") -> 0.19131372
A17: META | B17: =IFERROR('0. Database'!C62/'0. Database'!C53,"") -> 0.36331301 | C17: =IFERROR('0. Database'!D62/'0. Database'!D53,"") -> 0.29494625 | D17: =IFERROR('0. Database'!E62/'0. Database'!E53,"") -> 0.33937636 | E17: =IFERROR('0. Database'!F62/'0. Database'!F53,"") -> 0.41862653 | F17: =IFERROR('0. Database'!G62/'0. Database'!G53,"") -> 0.43007896 | G17: =IFERROR('0. Database'!H62/'0. Database'!H53,"") -> 0.27506358 | H17: =IFERROR('0. Database'!I62/'0. Database'!I53,"") -> 0.30002192 | I17: =IFERROR('0. Database'!J62/'0. Database'!J53,"") -> 0.27489938 | ... S17: =IFERROR('0. Database'!T62/'0. Database'!T53,"") -> 0.2322224
A18: ORCL | B18: =IFERROR('0. Database'!C80/'0. Database'!C71,"") -> 0.36440018 | C18: =IFERROR('0. Database'!D80/'0. Database'!D71,"") -> 0.37438977 | D18: =IFERROR('0. Database'!E80/'0. Database'!E71,"") -> 0.33840483 | E18: =IFERROR('0. Database'!F80/'0. Database'!F71,"") -> 0.33383706 | F18: =IFERROR('0. Database'!G80/'0. Database'!G71,"") -> 0.31937518 | G18: =IFERROR('0. Database'!H80/'0. Database'!H71,"") -> 0.34617433 | H18: =IFERROR('0. Database'!I80/'0. Database'!I71,"") -> 0.32614801 | I18: =IFERROR('0. Database'!J80/'0. Database'!J71,"") -> 0.29624037 | ... S18: =IFERROR('0. Database'!T80/'0. Database'!T71,"") -> 0.099723812
A21: Capex ($mm)
B22: 2013 | C22: 2014 | D22: 2015 | E22: 2016 | F22: 2017 | G22: 2018 | H22: 2019 | I22: 2020 | J22: 2021 | K22: 2022 | L22: 2023 | M22: 2024 | N22: 2025 | O22: 2026 | P22: 2027 | Q22: 2028 | R22: 2029 | S22: 2030
A23: MSFT | B23: ='0. Database'!C12 -> 4257 | C23: ='0. Database'!D12 -> 5485 | D23: ='0. Database'!E12 -> 5944 | E23: ='0. Database'!F12 -> 8932 | F23: ='0. Database'!G12 -> 10200 | G23: ='0. Database'!H12 -> 13600 | H23: ='0. Database'!I12 -> 16900 | I23: ='0. Database'!J12 -> 19000 | ... S23: ='0. Database'!T12 -> 304616.04
A24: AMZN | B24: ='0. Database'!C28 -> 3443 | C24: ='0. Database'!D28 -> 4892 | D24: ='0. Database'!E28 -> 4588 | E24: ='0. Database'!F28 -> 6736 | F24: ='0. Database'!G28 -> 10057 | G24: ='0. Database'!H28 -> 11322 | H24: ='0. Database'!I28 -> 12690 | I24: ='0. Database'!J28 -> 35046 | ... S24: ='0. Database'!T28 -> 312722.81
A25: GOOGL | B25: ='0. Database'!C43 -> 7358 | C25: ='0. Database'!D43 -> 10959 | D25: ='0. Database'!E43 -> 9915 | E25: ='0. Database'!F43 -> 10183 | F25: ='0. Database'!G43 -> 13184 | G25: ='0. Database'!H43 -> 25139 | H25: ='0. Database'!I43 -> 23548 | I25: ='0. Database'!J43 -> 22281 | ... S25: ='0. Database'!T43 -> 314500.02
A26: META | B26: ='0. Database'!C60 -> 1362 | C26: ='0. Database'!D60 -> 1831 | D26: ='0. Database'!E60 -> 2523 | E26: ='0. Database'!F60 -> 4491 | F26: ='0. Database'!G60 -> 6732 | G26: ='0. Database'!H60 -> 13980 | H26: ='0. Database'!I60 -> 15102 | I26: ='0. Database'!J60 -> 15115 | ... S26: ='0. Database'!T60 -> 208540.35
A27: ORCL | B27: ='0. Database'!C78 -> 650 | C27: ='0. Database'!D78 -> 580 | D27: ='0. Database'!E78 -> 1391 | E27: ='0. Database'!F78 -> 1189 | F27: ='0. Database'!G78 -> 2021 | G27: ='0. Database'!H78 -> 1736 | H27: ='0. Database'!I78 -> 1660 | I27: ='0. Database'!J78 -> 1564 | ... S27: ='0. Database'!T78 -> 66459.86
A30: Rev YoY %
B31: 2013 | C31: 2014 | D31: 2015 | E31: 2016 | F31: 2017 | G31: 2018 | H31: 2019 | I31: 2020 | J31: 2021 | K31: 2022 | L31: 2023 | M31: 2024 | N31: 2025 | O31: 2026 | P31: 2027 | Q31: 2028 | R31: 2029 | S31: 2030
A32: MSFT | C32: =IFERROR('0. Database'!D5/'0. Database'!C5-1,"") -> 0.1154029 | D32: =IFERROR('0. Database'!E5/'0. Database'!D5-1,"") -> 0.077700874 | E32: =IFERROR('0. Database'!F5/'0. Database'!E5-1,"") -> -0.088266724 | F32: =IFERROR('0. Database'!G5/'0. Database'!F5-1,"") -> 0.13186826 | G32: =IFERROR('0. Database'!H5/'0. Database'!G5-1,"") -> 0.14278614 | H32: =IFERROR('0. Database'!I5/'0. Database'!H5-1,"") -> 0.1402954 | I32: =IFERROR('0. Database'!J5/'0. Database'!I5-1,"") -> 0.13645574 | J32: =IFERROR('0. Database'!K5/'0. Database'!J5-1,"") -> 0.17531727 | ... S32: =IFERROR('0. Database'!T5/'0. Database'!S5-1,"") -> 0.17889742
A33: AMZN | C33: =IFERROR('0. Database'!D21/'0. Database'!C21-1,"") -> 0.19522921 | D33: =IFERROR('0. Database'!E21/'0. Database'!D21-1,"") -> 0.20247808 | E33: =IFERROR('0. Database'!F21/'0. Database'!E21-1,"") -> 0.27082815 | F33: =IFERROR('0. Database'!G21/'0. Database'!F21-1,"") -> 0.30796326 | G33: =IFERROR('0. Database'!H21/'0. Database'!G21-1,"") -> 0.30933962 | H33: =IFERROR('0. Database'!I21/'0. Database'!H21-1,"") -> 0.20454126 | I33: =IFERROR('0. Database'!J21/'0. Database'!I21-1,"") -> 0.37623431 | J33: =IFERROR('0. Database'!K21/'0. Database'!J21-1,"") -> 0.21695367 | ... S33: =IFERROR('0. Database'!T21/'0. Database'!S21-1,"") -> 0.10336905
A34: GOOGL | C34: =IFERROR('0. Database'!D36/'0. Database'!C36-1,"") -> 0.18880023 | D34: =IFERROR('0. Database'!E36/'0. Database'!D36-1,"") -> 0.13617975 | E34: =IFERROR('0. Database'!F36/'0. Database'!E36-1,"") -> 0.20380322 | F34: =IFERROR('0. Database'!G36/'0. Database'!F36-1,"") -> 0.2280109 | G34: =IFERROR('0. Database'!H36/'0. Database'!G36-1,"") -> 0.23421587 | H34: =IFERROR('0. Database'!I36/'0. Database'!H36-1,"") -> 0.1830009 | I34: =IFERROR('0. Database'!J36/'0. Database'!I36-1,"") -> 0.12770532 | J34: =IFERROR('0. Database'!K36/'0. Database'!J36-1,"") -> 0.41150076 | ... S34: =IFERROR('0. Database'!T36/'0. Database'!S36-1,"") -> 0.13075076
A35: META | C35: =IFERROR('0. Database'!D53/'0. Database'!C53-1,"") -> 0.5835874 | D35: =IFERROR('0. Database'!E53/'0. Database'!D53-1,"") -> 0.43807155 | E35: =IFERROR('0. Database'!F53/'0. Database'!E53-1,"") -> 0.54169688 | F35: =IFERROR('0. Database'!G53/'0. Database'!F53-1,"") -> 0.47090962 | G35: =IFERROR('0. Database'!H53/'0. Database'!G53-1,"") -> 0.37352717 | H35: =IFERROR('0. Database'!I53/'0. Database'!H53-1,"") -> 0.26610015 | I35: =IFERROR('0. Database'!J53/'0. Database'!I53-1,"") -> 0.21598665 | J35: =IFERROR('0. Database'!K53/'0. Database'!J53-1,"") -> 0.37180979 | ... S35: =IFERROR('0. Database'!T53/'0. Database'!S53-1,"") -> 0.11989806
A36: ORCL | C36: =IFERROR('0. Database'!D71/'0. Database'!C71-1,"") -> 0.028239336 | D36: =IFERROR('0. Database'!E71/'0. Database'!D71-1,"") -> -0.0013575251 | E36: =IFERROR('0. Database'!F71/'0. Database'!E71-1,"") -> -0.031265522 | F36: =IFERROR('0. Database'!G71/'0. Database'!F71-1,"") -> 0.022721753 | G36: =IFERROR('0. Database'!H71/'0. Database'!G71-1,"") -> 0.04042323 | H36: =IFERROR('0. Database'!I71/'0. Database'!H71-1,"") -> 0.0023839111 | I36: =IFERROR('0. Database'!J71/'0. Database'!I71-1,"") -> -0.0114358 | J36: =IFERROR('0. Database'!K71/'0. Database'!J71-1,"") -> 0.036035114 | ... S36: =IFERROR('0. Database'!T71/'0. Database'!S71-1,"") -> 0.12326264
A39: OpMargin %
B40: 2013 | C40: 2014 | D40: 2015 | E40: 2016 | F40: 2017 | G40: 2018 | H40: 2019 | I40: 2020 | J40: 2021 | K40: 2022 | L40: 2023 | M40: 2024 | N40: 2025 | O40: 2026 | P40: 2027 | Q40: 2028 | R40: 2029 | S40: 2030
A41: MSFT | B41: =IFERROR('0. Database'!C6/'0. Database'!C5,"") -> 0.34379375 | C41: =IFERROR('0. Database'!D6/'0. Database'!D5,"") -> 0.31968261 | D41: =IFERROR('0. Database'!E6/'0. Database'!E5,"") -> 0.19406925 | E41: =IFERROR('0. Database'!F6/'0. Database'!F5,"") -> 0.23654477 | F41: =IFERROR('0. Database'!G6/'0. Database'!G5,"") -> 0.30055607 | G41: =IFERROR('0. Database'!H6/'0. Database'!H5,"") -> 0.31766945 | H41: =IFERROR('0. Database'!I6/'0. Database'!I5,"") -> 0.3413698 | I41: =IFERROR('0. Database'!J6/'0. Database'!J5,"") -> 0.37030381 | ... S41: =IFERROR('0. Database'!T6/'0. Database'!T5,"") -> 0.487821
A42: AMZN | B42: =IFERROR('0. Database'!C22/'0. Database'!C21,"") -> 0.010006313 | C42: =IFERROR('0. Database'!D22/'0. Database'!D21,"") -> 0.0020047557 | D42: =IFERROR('0. Database'!E22/'0. Database'!E21,"") -> 0.020864134 | E42: =IFERROR('0. Database'!F22/'0. Database'!F21,"") -> 0.030782354 | F42: =IFERROR('0. Database'!G22/'0. Database'!G21,"") -> 0.023090416 | G42: =IFERROR('0. Database'!H22/'0. Database'!H21,"") -> 0.053330585 | H42: =IFERROR('0. Database'!I22/'0. Database'!I21,"") -> 0.051831942 | I42: =IFERROR('0. Database'!J22/'0. Database'!J21,"") -> 0.059314 | ... S42: =IFERROR('0. Database'!T22/'0. Database'!T21,"") -> 0.2026806
A43: GOOGL | B43: =IFERROR('0. Database'!C37/'0. Database'!C36,"") -> 0.27743655 | C43: =IFERROR('0. Database'!D37/'0. Database'!D36,"") -> 0.24993561 | D43: =IFERROR('0. Database'!E37/'0. Database'!E36,"") -> 0.2581712 | E43: =IFERROR('0. Database'!F37/'0. Database'!F36,"") -> 0.26271712 | F43: =IFERROR('0. Database'!G37/'0. Database'!G36,"") -> 0.23585765 | G43: =IFERROR('0. Database'!H37/'0. Database'!H36,"") -> 0.19699749 | H43: =IFERROR('0. Database'!I37/'0. Database'!I36,"") -> 0.21148915 | I43: =IFERROR('0. Database'!J37/'0. Database'!J36,"") -> 0.22585152 | ... S43: =IFERROR('0. Database'!T37/'0. Database'!T36,"") -> 0.36702057
A44: META | B44: =IFERROR('0. Database'!C54/'0. Database'!C53,"") -> 0.35619919 | C44: =IFERROR('0. Database'!D54/'0. Database'!D53,"") -> 0.40067383 | D44: =IFERROR('0. Database'!E54/'0. Database'!E53,"") -> 0.34724159 | E44: =IFERROR('0. Database'!F54/'0. Database'!F53,"") -> 0.44963456 | F44: =IFERROR('0. Database'!G54/'0. Database'!G53,"") -> 0.4969375 | G44: =IFERROR('0. Database'!H54/'0. Database'!H53,"") -> 0.44616569 | H44: =IFERROR('0. Database'!I54/'0. Database'!I53,"") -> 0.33927422 | I44: =IFERROR('0. Database'!J54/'0. Database'!J53,"") -> 0.3800456 | ... S44: =IFERROR('0. Database'!T54/'0. Database'!T53,"") -> 0.31305779
A45: ORCL | B45: =IFERROR('0. Database'!C72/'0. Database'!C71,"") -> 0.3941696 | C45: =IFERROR('0. Database'!D72/'0. Database'!D71,"") -> 0.38527607 | D45: =IFERROR('0. Database'!E72/'0. Database'!E71,"") -> 0.36258594 | E45: =IFERROR('0. Database'!F72/'0. Database'!F71,"") -> 0.34012467 | F45: =IFERROR('0. Database'!G72/'0. Database'!G71,"") -> 0.33536505 | G45: =IFERROR('0. Database'!H72/'0. Database'!H71,"") -> 0.33638508 | H45: =IFERROR('0. Database'!I72/'0. Database'!I71,"") -> 0.34244149 | I45: =IFERROR('0. Database'!J72/'0. Database'!J71,"") -> 0.3556676 | ... S45: =IFERROR('0. Database'!T72/'0. Database'!T71,"") -> 0.31232139
A48: D&A/Rev %
B49: 2013 | C49: 2014 | D49: 2015 | E49: 2016 | F49: 2017 | G49: 2018 | H49: 2019 | I49: 2020 | J49: 2021 | K49: 2022 | L49: 2023 | M49: 2024 | N49: 2025 | O49: 2026 | P49: 2027 | Q49: 2028 | R49: 2029 | S49: 2030
A50: MSFT | B50: =IFERROR('0. Database'!C11/'0. Database'!C5,"") -> 0.042890724 | C50: =IFERROR('0. Database'!D11/'0. Database'!D5,"") -> 0.048886944 | D50: =IFERROR('0. Database'!E11/'0. Database'!E5,"") -> 0.057704638 | E50: =IFERROR('0. Database'!F11/'0. Database'!F5,"") -> 0.068893577 | F50: =IFERROR('0. Database'!G11/'0. Database'!G5,"") -> 0.080769589 | G50: =IFERROR('0. Database'!H11/'0. Database'!H5,"") -> 0.089706415 | H50: =IFERROR('0. Database'!I11/'0. Database'!I5,"") -> 0.092178349 | I50: =IFERROR('0. Database'!J11/'0. Database'!J5,"") -> 0.086004965 | ... S50: =IFERROR('0. Database'!T11/'0. Database'!T5,"") -> 0.25619883
A51: AMZN | B51: =IFERROR('0. Database'!C27/'0. Database'!C21,"") -> 0.043691994 | C51: =IFERROR('0. Database'!D27/'0. Database'!D21,"") -> 0.053321557 | D51: =IFERROR('0. Database'!E27/'0. Database'!E21,"") -> 0.058697314 | E51: =IFERROR('0. Database'!F27/'0. Database'!F21,"") -> 0.059689529 | F51: =IFERROR('0. Database'!G27/'0. Database'!G21,"") -> 0.064531726 | G51: =IFERROR('0. Database'!H27/'0. Database'!H21,"") -> 0.065873149 | H51: =IFERROR('0. Database'!I27/'0. Database'!I21,"") -> 0.077673052 | I51: =IFERROR('0. Database'!J27/'0. Database'!J21,"") -> 0.065406254 | ... S51: =IFERROR('0. Database'!T27/'0. Database'!T21,"") -> 0.13440276
A52: GOOGL | B52: =IFERROR('0. Database'!C42/'0. Database'!C36,"") -> 0.05009096 | C52: =IFERROR('0. Database'!D42/'0. Database'!D36,"") -> 0.053377979 | D52: =IFERROR('0. Database'!E42/'0. Database'!E36,"") -> 0.055101415 | E52: =IFERROR('0. Database'!F42/'0. Database'!F36,"") -> 0.058345888 | F52: =IFERROR('0. Database'!G42/'0. Database'!G36,"") -> 0.055053899 | G52: =IFERROR('0. Database'!H42/'0. Database'!H36,"") -> 0.059670075 | H52: =IFERROR('0. Database'!I42/'0. Database'!I36,"") -> 0.067071551 | I52: =IFERROR('0. Database'!J42/'0. Database'!J36,"") -> 0.070701869 | ... S52: =IFERROR('0. Database'!T42/'0. Database'!T36,"") -> 0.16938867
A53: META | B53: =IFERROR('0. Database'!C59/'0. Database'!C53,"") -> 0.12842988 | C53: =IFERROR('0. Database'!D59/'0. Database'!D53,"") -> 0.099711215 | D53: =IFERROR('0. Database'!E59/'0. Database'!E53,"") -> 0.10849557 | E53: =IFERROR('0. Database'!F59/'0. Database'!F53,"") -> 0.084738404 | F53: =IFERROR('0. Database'!G59/'0. Database'!G53,"") -> 0.074410253 | G53: =IFERROR('0. Database'!H59/'0. Database'!H53,"") -> 0.077277123 | H53: =IFERROR('0. Database'!I59/'0. Database'!I53,"") -> 0.081206283 | I53: =IFERROR('0. Database'!J59/'0. Database'!J53,"") -> 0.079822255 | ... S53: =IFERROR('0. Database'!T59/'0. Database'!T53,"") -> 0.2651009
A54: ORCL | B54: =IFERROR('0. Database'!C77/'0. Database'!C71,"") -> 0.014656538 | C54: =IFERROR('0. Database'!D77/'0. Database'!D71,"") -> 0.015872601 | D54: =IFERROR('0. Database'!E77/'0. Database'!E71,"") -> 0.018612919 | E54: =IFERROR('0. Database'!F77/'0. Database'!F71,"") -> 0.023504331 | F54: =IFERROR('0. Database'!G77/'0. Database'!G71,"") -> 0.02638592 | G54: =IFERROR('0. Database'!H77/'0. Database'!H71,"") -> 0.029545282 | H54: =IFERROR('0. Database'!I77/'0. Database'!I71,"") -> 0.031119545 | I54: =IFERROR('0. Database'!J77/'0. Database'!J71,"") -> 0.035369693 | ... S54: =IFERROR('0. Database'!T77/'0. Database'!T71,"") -> 0.26
