Workbook

Sheet 0. Database
A1: Centralized Database (USD mm except EPS/shares) — Blue = input
A3: Ticker | B3: Metric | C3: 2013A | D3: 2014A | E3: 2015A | F3: 2016A | G3: 2017A | H3: 2018A | I3: 2019A | J3: 2020A | K3: 2021A | L3: 2022A | M3: 2023A | N3: 2024A | O3: 2025E | P3: 2026E | Q3: 2027E | R3: 2028E | S3: 2029E | T3: 2030E
A4: MSFT (FY(Jun))
A5: MSFT | B5: Revenue | C5: 77849 | D5: 86833 | E5: 93580 | F5: 85320 | G5: 96571 | H5: 110360 | I5: 125843 | J5: 143015 | K5: 168088 | L5: 198270 | M5: 211915 | N5: 245122 | O5: 281724 | P5: 329440.24 | Q5: 387103.71 | R5: 463474.17 | S5: 553714.52 | T5: 652772.62
A6: MSFT | B6: Operating Income | C6: 26764 | D6: 27759 | E6: 18161 | F6: 20182 | G6: 29025 | H6: 35058 | I6: 42959 | J6: 52959 | K6: 69916 | L6: 83383 | M6: 88523 | N6: 109433 | O6: 128528 | P6: 153454.1 | Q6: 179274.53 | R6: 217551.82 | S6: 266239.28 | T6: 318436.19
A7: MSFT | B7: Net Income | C7: 21863 | D7: 22074 | E7: 12193 | F7: 16798 | G7: 25489 | H7: 16571 | I7: 39240 | J7: 44281 | K7: 61271 | L7: 72738 | M7: 72361 | N7: 88136 | O7: 101832 | P7: 129372.86 | Q7: 144971.56 | R7: 175683.92 | S7: 215472.22 | T7: 258948.36
A8: MSFT | B8: EPS | C8: 2.63 | D8: 2.66 | E8: 2.59 | F8: 2.79 | G8: 3.29 | H8: 3.88 | I8: 4.75 | J8: 5.76 | K8: 7.97 | L8: 9.21 | M8: 9.81 | N8: 11.8 | O8: 13.91 | P8: 16.75 | Q8: 19.47 | R8: 23.61 | S8: 28.97 | T8: 34.82
A9: MSFT | B9: Diluted Shares (mm) | C9: 8452.25 | D9: 8385.25 | E9: 8254 | F9: 8012.25 | G9: 7831.25 | H9: 7792.25 | I9: 7752 | J9: 7681.5 | K9: 7607.75 | L9: 7540.5 | M9: 7472.25 | N9: 7468.5 | O9: 7467.75 | P9: 7453.97 | Q9: 7446.49 | R9: 7440.67 | S9: 7436.61 | T9: 7436.22
A10: MSFT | B10: SBC | C10: 2406 | D10: 2446 | E10: 2574 | F10: 2668 | G10: 3266 | H10: 3940 | I10: 4652 | J10: 5289 | K10: 6118 | L10: 7502 | M10: 9611 | N10: 10734 | O10: 11974 | P10: 12189 | Q10: 10478.4 | R10: 11434.24 | S10: 12826.56 | T10: 14871.62
A11: MSFT | B11: D&A | C11: 3339 | D11: 4245 | E11: 5400 | F11: 5878 | G11: 7800 | H11: 9900 | I11: 11600 | J11: 12300 | K11: 10900 | L11: 14600 | M11: 13500 | N11: 20000 | O11: 28000 | P11: 39638.96 | Q11: 62441.96 | R11: 94995.43 | S11: 131504.45 | T11: 167239.58
A12: MSFT | B12: Capex | C12: 4257 | D12: 5485 | E12: 5944 | F12: 8932 | G12: 10200 | H12: 13600 | I12: 16900 | J12: 19000 | K12: 24200 | L12: 29200 | M12: 31900 | N12: 55700 | O12: 88200 | P12: 145871.3 | Q12: 245263.45 | R12: 286760.35 | S12: 300210.91 | T12: 304616.04
A13: MSFT | B13: CFO | C13: 28833 | D13: 32231 | E13: 29080 | F13: 33325 | G13: 39507 | H13: 43884 | I13: 52185 | J13: 60675 | K13: 76740 | L13: 89035 | M13: 87582 | N13: 118548 | O13: 136162 | P13: 174558.18 | Q13: 232097.78 | R13: 294570.35 | S13: 359672.36 | T13: 438548.9
A14: MSFT | B14: FCF | C14: 24576 | D14: 26746 | E14: 23136 | F14: 24393 | G14: 29307 | H14: 30284 | I14: 35285 | J14: 41675 | K14: 52540 | L14: 59835 | M14: 55682 | N14: 62848 | O14: 47962 | P14: 28686.88 | Q14: -13165.67 | R14: 7810 | S14: 59461.45 | T14: 133932.86
A15: MSFT | B15: Buybacks | C15: 5360 | D15: 7316 | E15: 14443 | F15: 15969 | G15: 11788 | H15: 10721 | I15: 19543 | J15: 22968 | K15: 27385 | L15: 32696 | M15: 22245 | N15: 17254 | O15: 18420 | P15: 22499.7 | Q15: 19070.28 | R15: 19500.41 | S15: 20126.95 | T15: 21047.23
A16: MSFT | B16: Intell Cloud | C16: 0 | D16: 0 | E16: 0 | F16: 0 | G16: 0 | H16: 0 | I16: 0 | J16: 0 | K16: 0 | L16: 0 | M16: 72314 | N16: 87464 | O16: 106265 | P16: 136688.31 | Q16: 180358.14 | R16: 235873.55 | S16: 304531.45 | T16: 384276.13
... A18: MSFT | B18: Useful Life(yr) | C18: 3.16 | D18: 2.69 | E18: 2.81 | F18: 2.83 | G18: 2.71 | H18: 2.73 | I18: 2.74 | J18: 3.08 | K18: 4.33 | L18: 4.12 | M18: 6.1 | N18: 5.59 | O18: 5.26 | P18: 4.89 | Q18: 4.36 | R18: 4.38 | S18: 4.6 | T18: 4.7
A20: AMZN (CY)
A21: AMZN | B21: Revenue | C21: 74453 | D21: 88988.4 | E21: 107006.6 | F21: 135987 | G21: 177866 | H21: 232887 | I21: 280522 | J21: 386064 | K21: 469822 | L21: 513983 | M21: 574785 | N21: 637959 | O21: 716924 | P21: 827599.51 | Q21: 946630.91 | R21: 1063340.6 | S21: 1183117.7 | T21: 1305415.5
A22: AMZN | B22: Operating Income | C22: 745 | D22: 178.4 | E22: 2232.6 | F22: 4186 | G22: 4107 | H22: 12420 | I22: 14540 | J22: 22899 | K22: 24879 | L22: 12248 | M22: 36852 | N22: 68593 | O22: 79975 | P22: 109001.86 | Q22: 146127.4 | R22: 183469.22 | S22: 223208.87 | T22: 264582.39
A23: AMZN | B23: Net Income | C23: 273 | D23: -240.6 | E23: 596.1 | F23: 2371 | G23: 3033 | H23: 10073 | I23: 11588 | J23: 21331 | K23: 33364 | L23: -2722 | M23: 30425 | N23: 59248 | O23: 77670 | P23: 98333.72 | Q23: 116218.4 | R23: 145016.4 | S23: 177176.2 | T23: 211925.99
A24: AMZN | B24: EPS | C24: 0.03 | D24: -0.03 | E24: 0.06 | F24: 0.24 | G24: 0.31 | H24: 1.01 | I24: 1.15 | J24: 2.08 | K24: 3.25 | L24: -0.26 | M24: 2.88 | N24: 5.53 | O24: 7.17 | P24: 9.02 | Q24: 10.58 | R24: 13.11 | S24: 15.92 | T24: 18.92
A25: AMZN | B25: Diluted Shares (mm) | C25: 9340 | D25: 9440 | E25: 9620 | F25: 9720 | G25: 9910 | H25: 10020 | I25: 10100 | J25: 10254 | K25: 10274.5 | L25: 10296.5 | M25: 10568.69 | N25: 10721 | O25: 10827 | P25: 10907.55 | Q25: 10986.16 | R25: 11059.39 | S25: 11131.13 | T25: 11201.4
A26: AMZN | B26: SBC | C26: -1134 | D26: -1497 | E26: -2120 | F26: -2975 | G26: -4214 | H26: -5418 | I26: -6864 | J26: -9208 | K26: -12757 | L26: -19621 | M26: -24023 | N26: -22077.4 | O26: -19467 | P26: -18863.32 | Q26: -17920.15 | R26: -18816.16 | S26: -19756.97 | T26: -20744.82
A27: AMZN | B27: D&A | C27: 3253 | D27: 4745 | E27: 6281 | F27: 8117 | G27: 11478 | H27: 15341 | I27: 21789 | J27: 25251 | K27: 34296 | L27: 41461 | M27: 48663 | N27: 52795 | O27: 65756 | P27: 81175.82 | Q27: 90716.93 | R27: 120533.23 | S27: 150703.05 | T27: 175451.44
A28: AMZN | B28: Capex | C28: 3443 | D28: 4892 | E28: 4588 | F28: 6736 | G28: 10057 | H28: 11322 | I28: 12690 | J28: 35046 | K28: 55396 | L28: 58321 | M28: 48133 | N28: 77658 | O28: 128320 | P28: 200104.98 | Q28: 270141.72 | R28: 283648.81 | S28: 297831.25 | T28: 312722.81
A29: AMZN | B29: CFO | C29: 5474 | D29: 6841.4 | E29: 11920.1 | F29: 17271 | G29: 18434 | H29: 30724 | I29: 38515 | J29: 66064 | K29: 46327 | L29: 46752 | M29: 84946 | N29: 115877 | O29: 139514 | P29: 181004.31 | Q29: 224443.7 | R29: 281471.71 | S29: 342814.42 | T29: 401080.41
A30: AMZN | B30: FCF | C30: 2031 | D30: 1949.4 | E30: 7332.1 | F30: 10535 | G30: 8377 | H30: 19402 | I30: 25825 | J30: 31018 | K30: -9069 | L30: -11569 | M30: 36813 | N30: 38219 | O30: 11194 | P30: -19100.67 | Q30: -45698.02 | R30: -2177.1 | S30: 44983.17 | T30: 88357.6
A31: AMZN | B31: Buybacks | C31: 0 | D31: 0 | E31: 0 | F31: 0 | G31: 0 | H31: 0 | I31: 0 | J31: 0 | K31: 0 | L31: 6000 | M31: 0 | N31: 0 | O31: 0 | P31: 0 | Q31: 0 | R31: 0 | S31: 0 | T31: 0
A32: AMZN | B32: AWS Rev | C32: 3107.57 | D32: 4644 | E32: 7880 | F32: 12219 | G32: 17458 | H32: 25656 | I32: 35026 | J32: 45370 | K32: 62202 | L32: 80096 | M32: 90757 | N32: 107556 | O32: 128725 | P32: 171284.9 | Q32: 225587.94 | R32: 274421.67 | S32: 323817.58 | T32: 374009.3
A33: AMZN | B33: AWS OI | D33: 458 | E33: 1508 | F33: 3109 | G33: 4331 | H33: 7296 | I33: 9201 | J33: 13531 | K33: 18532 | L33: 22841 | M33: 24631 | N33: 39834 | O33: 45606 | P33: 61254.41 | Q33: 81248.3 | R33: 100888.47 | S33: 121477.03 | T33: 143111.04
A35: GOOGL (CY)
A36: GOOGL | B36: Revenue | C36: 55519 | D36: 66001 | E36: 74989 | F36: 90272 | G36: 110855 | H36: 136819 | I36: 161857 | J36: 182527 | K36: 257637 | L36: 282836 | M36: 307394 | N36: 350018 | O36: 402836 | P36: 488278.6 | Q36: 591935.74 | R36: 701414.49 | S36: 815276.88 | T36: 921874.95
A37: GOOGL | B37: Operating Income | C37: 15403 | D37: 16496 | E37: 19360 | F37: 23716 | G37: 26146 | H37: 26953 | I37: 34231 | J37: 41224 | K37: 78714 | L37: 74842 | M37: 84293 | N37: 112390 | O37: 129039 | P37: 167318.21 | Q37: 210287.33 | R37: 253779.42 | S37: 298519.7 | T37: 338347.07
A38: GOOGL | B38: Net Income | C38: 12720 | D38: 14136 | E38: 16348 | F38: 19478 | G38: 12662 | H38: 30736 | I38: 34343 | J38: 40269 | K38: 76033 | L38: 59972 | M38: 73795 | N38: 100118 | O38: 132170 | P38: 168543.28 | Q38: 174626.97 | R38: 210753.44 | S38: 249488.6 | T38: 285975.76
A39: GOOGL | B39: EPS | C39: 0.94 | D39: 1.03 | E39: 1.18 | F39: 1.39 | G39: 0.9 | H39: 2.19 | I39: 2.46 | J39: 2.93 | K39: 5.61 | L39: 4.56 | M39: 5.8 | N39: 8.04 | O39: 10.81 | P39: 13.73 | Q39: 14.16 | R39: 17.04 | S39: 20.12 | T39: 22.99
A40: GOOGL | B40: Diluted Shares (mm) | C40: 13552.38 | D40: 13741.41 | E40: 13858.6 | F40: 13974.09 | G40: 14071.67 | H40: 14065.69 | I40: 13971.13 | J40: 13740.56 | K40: 13553 | L40: 13159 | M40: 12722 | N40: 12447 | O40: 12230 | P40: 12275.96 | Q40: 12335.53 | R40: 12366.42 | S40: 12399.99 | T40: 12436.85
A41: GOOGL | B41: SBC | C41: -3268 | D41: -4175 | E41: -4903 | F41: -6703 | G41: -7679 | H41: -9353 | I41: -10794 | J41: -12991 | K41: -15376 | L41: -19362 | M41: -22460 | N41: -22785 | O41: -24953 | P41: -27937.33 | Q41: -30032.63 | R41: -31979.73 | S41: -33657.1 | T41: -35339.95
A42: GOOGL | B42: D&A | C42: 2781 | D42: 3523 | E42: 4132 | F42: 5267 | G42: 6103 | H42: 8164 | I42: 10856 | J42: 12905 | K42: 11555 | L42: 15287 | M42: 13326 | N42: 15311 | O42: 21136 | P42: 42874.7 | Q42: 69582.72 | R42: 98340.16 | S42: 127674.93 | T42: 156155.17
A43: GOOGL | B43: Capex | C43: 7358 | D43: 10959 | E43: 9915 | F43: 10183 | G43: 13184 | H43: 25139 | I43: 23548 | J43: 22281 | K43: 24640 | L43: 31485 | M43: 32251 | N43: 52535 | O43: 91447 | P43: 185234.28 | Q43: 259327.99 | R43: 285260.79 | S43: 299523.83 | T43: 314500.02
A44: GOOGL | B44: CFO | C44: 18584 | D44: 22272 | E44: 25829 | F44: 36036 | G44: 37091 | H44: 47971 | I44: 54520 | J44: 65124 | K44: 91652 | L44: 91495 | M44: 101746 | N44: 125299 | O44: 164713 | P44: 211985.47 | Q44: 282346.21 | R44: 352943.8 | S44: 424226.82 | T44: 490867.35
A45: GOOGL | B45: FCF | C45: 11226 | D45: 11313 | E45: 15914 | F45: 25853 | G45: 23907 | H45: 22832 | I45: 30972 | J45: 42843 | K45: 67012 | L45: 60010 | M45: 69495 | N45: 72764 | O45: 73266 | P45: 26751.19 | Q45: 23018.22 | R45: 67683.01 | S45: 124702.99 | T45: 176367.33
A46: GOOGL | B46: Buybacks | C46: 0 | D46: 0 | E46: 1827 | F46: 3693 | G46: 4846 | H46: 9075 | I46: 18396 | J46: 31149 | K46: 50274 | L46: 59296 | M46: 61504 | N46: 62222 | O46: 45709 | P46: 0 | Q46: 20000 | R46: 20000 | S46: 20000 | T46: 15000
A47: GOOGL | B47: Cloud Rev | G47: 4056 | H47: 5838 | I47: 8918 | J47: 13059 | K47: 19206 | L47: 26280 | M47: 33088 | N47: 43229 | O47: 58705 | P47: 99085.93 | Q47: 157303.91 | R47: 220225.47 | S47: 286293.12 | T47: 343551.74
A48: GOOGL | B48: Search Rev | G48: 69811 | H48: 85296 | I48: 98115 | J48: 104062 | K48: 148951 | L48: 162450 | M48: 175033 | N48: 198084 | O48: 224532 | P48: 258723.55 | Q48: 291360.5 | R48: 324483.39 | S48: 358139.29 | T48: 392613.71
A49: GOOGL | B49: YouTube Rev | G49: 8150 | H49: 11115 | I49: 15149 | J49: 19772 | K49: 28845 | L49: 29243 | M49: 31510 | N49: 36147 | O49: 40367 | P49: 43997.73 | Q49: 49277.45 | R49: 54574.78 | S49: 59759.38 | T49: 64838.93
A50: GOOGL | B50: GCloud OI | H50: -4348 | I50: -4645 | J50: -5607 | K50: -2282 | L50: -1922 | M50: 1716 | N50: 6112 | O50: 13910 | P50: 32420.97 | Q50: 57771.82 | R50: 85285.05 | S50: 113733.5 | T50: 138713.29
A52: META (CY)
A53: META | B53: Revenue | C53: 7872 | D53: 12466 | E53: 17927 | F53: 27638 | G53: 40653 | H53: 55838 | I53: 70696.5 | J53: 85966 | K53: 117929 | L53: 116609 | M53: 134901 | N53: 164500 | O53: 200965 | P53: 255175.56 | Q53: 306410.52 | R53: 357336.07 | S53: 407351.97 | T53: 456192.68
A54: META | B54: Operating Income | C54: 2804 | D54: 4994.8 | E54: 6225 | F54: 12427 | G54: 20202 | H54: 24913 | I54: 23985.5 | J54: 32671 | K54: 46753 | L54: 28945 | M54: 46751 | N54: 69380 | O54: 83276 | P54: 90489.79 | Q54: 104437.61 | R54: 118413.08 | S54: 131523.75 | T54: 142814.67
A55: META | B55: Net Income | C55: 1491 | D55: 2924.8 | E55: 3669 | F55: 10187.2 | G55: 15919 | H55: 22112 | I55: 18484.5 | J55: 29145 | K55: 39370 | L55: 23199 | M55: 39097 | N55: 62360 | O55: 60458 | P55: 85782.86 | Q55: 91160.94 | R55: 103452.71 | S55: 115846.5 | T55: 127804.37
A56: META | B56: EPS | C56: 0.59 | D56: 1.1 | E56: 1.28 | F56: 3.48 | G56: 5.39 | H56: 7.66 | I56: 6.44 | J56: 10.08 | K56: 14.07 | L56: 8.79 | M56: 14.87 | N56: 23.99 | O56: 23.49 | P56: 33.28 | Q56: 34.94 | R56: 39.24 | S56: 43.51 | T56: 47.52
A57: META | B57: Diluted Shares (mm) | C57: 2521.75 | D57: 2671 | E57: 2856.75 | F57: 2923.75 | G57: 2954 | H57: 2886 | I57: 2871 | J57: 2890 | K57: 2799 | L57: 2640 | M57: 2630 | N57: 2599 | O57: 2574 | P57: 2577.79 | Q57: 2609.3 | R57: 2636.12 | S57: 2662.83 | T57: 2689.4
A58: META | B58: SBC | C58: -906 | D58: -1837 | E58: -2969 | F58: -3202 | G58: -3723 | H58: -4152 | I58: -4835 | J58: -6536 | K58: -9163 | L58: -11991 | M58: -14027 | N58: -16690 | O58: -20426 | P58: -23722.2 | Q58: -24908.31 | R58: -26153.73 | S58: -27461.41 | T58: -28834.48
A59: META | B59: D&A | C59: 1011 | D59: 1243 | E59: 1945 | F59: 2342 | G59: 3025 | H59: 4315 | I59: 5741 | J59: 6862 | K59: 7966 | L59: 8686 | M59: 11177 | N59: 15498 | O59: 18616 | P59: 35955.99 | Q59: 56602.9 | R59: 78641.85 | S59: 100070.74 | T59: 120937.09
A60: META | B60: Capex | C60: 1362 | D60: 1831 | E60: 2523 | F60: 4491 | G60: 6732 | H60: 13980 | I60: 15102 | J60: 15115 | K60: 18567 | L60: 31186 | M60: 27045 | N60: 37256 | O60: 69691 | P60: 135583.71 | Q60: 165714.44 | R60: 185600.17 | S60: 196736.18 | T60: 208540.35
A61: META | B61: CFO | C61: 4222 | D61: 5507.8 | E61: 8607 | F61: 16061 | G61: 24216 | H61: 29339 | I61: 36312.5 | J61: 38747 | K61: 57683 | L61: 50475 | M61: 71113 | N61: 91328 | O61: 115800 | P61: 180250.64 | Q61: 206102.96 | R61: 243250.01 | S61: 279015.98 | T61: 314478.51
A62: META | B62: FCF | C62: 2860 | D62: 3676.8 | E62: 6084 | F62: 11570 | G62: 17484 | H62: 15359 | I62: 21210.5 | J62: 23632 | K62: 39116 | L62: 19289 | M62: 44068 | N62: 54072 | O62: 46109 | P62: 44666.93 | Q62: 40388.52 | R62: 57649.84 | S62: 82279.8 | T62: 105938.16
A63: META | B63: Buybacks | C63: 0 | D63: 0 | E63: 0 | F63: 0 | G63: 1976 | H63: 12879 | I63: 4201 | J63: 6272 | K63: 44538 | L63: 27956 | M63: 19775 | N63: 30125 | O63: 26248 | P63: 0 | Q63: 6000 | R63: 6000 | S63: 6000 | T63: 6000
A64: META | B64: Ad Rev(META) | C64: 6986 | D64: 11492 | E64: 17080 | F64: 26885 | G64: 39942 | H64: 55012 | I64: 69654.5 | J64: 84169 | K64: 114934 | L64: 113641 | M64: 131948 | N64: 160632 | O64: 196174 | P64: 248664.66 | Q64: 298597.44 | R64: 348271.65 | S64: 397194.59 | T64: 444912.31
A65: META | B65: FOA Rev | I65: 70196 | J65: 84826 | K65: 115655 | L65: 114450 | M65: 133005 | N65: 162354 | O65: 198758 | P65: 252529.81 | Q65: 303235.62 | R65: 353605.56 | S65: 403061.89 | T65: 451366.33
A66: META | B66: FOA OI | I66: 28489 | J66: 39294 | K66: 56947 | L66: 42662 | M66: 62870 | N66: 87109 | O66: 102469 | P66: 109500.79 | Q66: 122498.06 | R66: 135570.51 | S66: 147823.31 | T66: 158299.25
A67: META | B67: RL Rev | I67: 501 | J67: 1139 | K67: 2274 | L67: 2159 | M67: 1896 | N67: 2146 | O67: 2207 | P67: 2645.75 | Q67: 3174.9 | R67: 3730.51 | S67: 4290.08 | T67: 4826.34
A68: META | B68: RL OI | I68: -4503 | J68: -6623 | K68: -10194 | L68: -13717 | M68: -16119 | N68: -17729 | O68: -19193 | P68: -19011 | Q68: -18060.45 | R68: -17157.43 | S68: -16299.56 | T68: -15484.58
A70: ORCL (FY(May))
A71: ORCL | B71: Revenue | C71: 37253 | D71: 38305 | E71: 38253 | F71: 37057 | G71: 37899 | H71: 39431 | I71: 39525 | J71: 39073 | K71: 40481 | L71: 42441 | M71: 49955 | N71: 52961 | O71: 57399 | P71: 67286.75 | Q71: 88782.02 | R71: 125445.05 | S71: 165192.96 | T71: 185555.08
A72: ORCL | B72: Operating Income | C72: 14684 | D72: 14758 | E72: 13870 | F72: 12604 | G72: 12710 | H72: 13264 | I72: 13535 | J72: 13897 | K72: 15214 | L72: 10927 | M72: 13094 | N72: 15354 | O72: 17678 | P72: 19462.44 | Q72: 21128.19 | R72: 36930.86 | S72: 53057.71 | T72: 57952.82
A73: ORCL | B73: Net Income | C73: 10926 | D73: 10955 | E73: 9938 | F73: 8900 | G73: 9334 | H73: 3587 | I73: 11083 | J73: 10135 | K73: 13747 | L73: 6718 | M73: 8504 | N73: 10467 | O73: 12443 | P73: 15820.55 | Q73: 13363.1 | R73: 26776.66 | S73: 39834.82 | T73: 44104.48
A74: ORCL | B74: EPS | C74: 2.26 | D74: 2.38 | E74: 2.21 | F74: 2.07 | G74: 2.21 | H74: 0.85 | I74: 2.97 | J74: 3.08 | K74: 4.55 | L74: 2.41 | M74: 3.07 | N74: 3.71 | O74: 4.34 | P74: 5.43 | Q74: 4.54 | R74: 8.98 | S74: 13.15 | T74: 14.32
A75: ORCL | B75: Diluted Shares (mm) | C75: 4843.75 | D75: 4604.5 | E75: 4502.5 | F75: 4305.5 | G75: 4217 | H75: 4238 | I75: 3732 | J75: 3293.5 | K75: 3022.5 | L75: 2785.5 | M75: 2766.25 | N75: 2823.25 | O75: 2866.25 | P75: 2915.76 | Q75: 2940.66 | R75: 2980.3 | S75: 3028.26 | T75: 3079.57
A76: ORCL | B76: SBC | C76: 755 | D76: 805 | E76: 933 | F76: 1037 | G76: 1350 | H76: 1607 | I76: 1653 | J76: 1590 | K76: 1837 | L76: 2613 | M76: 3547 | N76: 3974 | O76: 4674 | P76: 5069.6 | Q76: 6473.15 | R76: 8609.75 | S76: 10649.61 | T76: 11212.32
A77: ORCL | B77: D&A | C77: 546 | D77: 608 | E77: 712 | F77: 871 | G77: 1000 | H77: 1165 | I77: 1230 | J77: 1382 | K77: 1537 | L77: 1972 | M77: 2526 | N77: 3129 | O77: 3867 | P77: 7501.53 | Q77: 16868.58 | R77: 27597.91 | S77: 39646.31 | T77: 48244.32
A78: ORCL | B78: Capex | C78: 650 | D78: 580 | E78: 1391 | F78: 1189 | G78: 2021 | H78: 1736 | I78: 1660 | J78: 1564 | K78: 2135 | L78: 4511 | M78: 8695 | N78: 6866 | O78: 21215 | P78: 51882 | Q78: 52141.41 | R78: 69869.49 | S78: 81048.61 | T78: 66459.86
A79: ORCL | B79: CFO | C79: 14225 | D79: 14921 | E79: 14336 | F79: 13560 | G79: 14125 | H79: 15386 | I79: 14551 | J79: 13139 | K79: 15888 | L79: 9540 | M79: 17166 | N79: 18673 | O79: 20821 | P79: 25457.17 | Q79: 33694.38 | R79: 50132.95 | S79: 66529.01 | T79: 84964.12
A80: ORCL | B80: FCF | C80: 13575 | D80: 14341 | E80: 12945 | F80: 12371 | G80: 12104 | H80: 13650 | I80: 12891 | J80: 11575 | K80: 13753 | L80: 5029 | M80: 8471 | N80: 11807 | O80: -394 | P80: -26424.83 | Q80: -18447.03 | R80: -19736.54 | S80: -14519.6 | T80: 18504.26
A81: ORCL | B81: Buybacks | C81: 11021 | D81: 9813 | E81: 8087 | F81: 10440 | G81: 3561 | H81: 11347 | I81: 36140 | J81: 19240 | K81: 20934 | L81: 16248 | M81: 1300 | N81: 1202 | O81: 600 | P81: 95 | Q81: 0 | R81: 0 | S81: 0 | T81: 0
A82: ORCL | B82: CloudTotalRevenue(ORCL) | C82: 1365 | D82: 1577 | E82: 2094 | F82: 2854 | G82: 4572 | H82: 6189.17 | I82: 6918.19 | J82: 7811.32 | K82: 8945 | L82: 10809 | M82: 15882 | N82: 19775 | O82: 24507 | P82: 34020.24 | Q82: 55591.76 | R82: 92351.27 | S82: 132214.36 | T82: 152708.94
A83: ORCL | B83: IaaS Rev | L83: 2760.74 | M83: 4500 | N83: 6800 | O83: 10234 | P83: 18064.4 | Q83: 37935.24 | R83: 72977.07 | S83: 111105.3 | T83: 129847.66
A84: ORCL | B84: SaaS Rev | L84: 7999.33 | M84: 11400 | N84: 12949 | O84: 14272 | P84: 15955.84 | Q84: 17656.52 | R84: 19374.2 | S84: 21109.07 | T84: 22861.28
A85: ORCL | B85: RPO | I85: 36200 | J85: 37000 | K85: 41300 | L85: 46600 | M85: 67900 | N85: 98000 | O85: 138000
A86: ORCL | B86: Operating Income(Adjusted) | C86: 17612 | D86: 18108 | E86: 17396 | F86: 15785 | G86: 16168 | H86: 17155 | I86: 17384 | J86: 17383 | K86: 19000 | L86: 19592 | M86: 20904 | N86: 23054 | O86: 25034 | P86: 28113.04 | Q86: 28489.16 | R86: 46280.73 | S86: 64368.1 | T86: 69758.92
A87: ORCL | B87: EPS(Adjusted) | C87: 2.68 | D87: 2.87 | E87: 2.77 | F87: 2.61 | G87: 2.74 | H87: 3.05 | I87: 3.52 | J87: 3.85 | K87: 4.67 | L87: 4.9 | M87: 5.12 | N87: 5.56 | O87: 6.03 | P87: 7.32 | Q87: 6.09 | R87: 10.59 | S87: 14.81 | T87: 15.94

Sheet 1. Summary
B2: AI Capex Cycle: Hyperscaler Deep-Dive (2013-2030)
B3: MSFT | AMZN | GOOGL | META | ORCL + S&P 500 AI EPS Decomposition
B5: CONTENTS
B6: 0. Database — 2013-2030 centralized data. Blue=input. All other sheets reference this.
B7: 1. Summary — This page
B8: 2. Revenue — Total rev, YoY%, Cloud/AI proxy. Derived metrics reference SAME sheet cells (black font).
B9: 3. Capex & D&A — Capex, Capex/Rev, D&A, D&A/Rev. Local formulas reference raw data on same sheet.
B10: 4. FCF & Cash — CFO, FCF margin, FCF/NI, Capex/CFO. All ratios use same-sheet references.
B11: 5. EPS & Margins — OpMargin, Net Margin, EPSYoY. Same-sheet referencing pattern.
B12: 6. Burry Sensitivity — GPU life compression on 2026E EPS. Editable tax rate assumptions.
B13: 7. S&P 500 AI EPS Split — AI vs Non-AI EPS decomposition + dual P/E valuation + 4 stress scenarios.
B14: 8. Charts — 6 visualizations (Capex/Rev, Free Cash FlowMargin, Capex absolute, Rev YoY, OpMargin, D&A/Rev).

Sheet 2. Revenue & Growth
A1: Revenue&AI/CloudSegment Detail (2013-2030E)
A3: A. Total Revenue ($mm)
A4: Company | B4: 2013A | C4: 2014A | D4: 2015A | E4: 2016A | F4: 2017A | G4: 2018A | H4: 2019A | I4: 2020A | J4: 2021A | K4: 2022A | L4: 2023A | M4: 2024A | N4: 2025E | O4: 2026E | P4: 2027E | Q4: 2028E | R4: 2029E | S4: 2030E
A5: MSFT | B5: ='0. Database'!C5 | C5: ='0. Database'!D5 | D5: ='0. Database'!E5 | E5: ='0. Database'!F5 | F5: ='0. Database'!G5 | G5: ='0. Database'!H5 | H5: ='0. Database'!I5 | I5: ='0. Database'!J5 | ... S5: ='0. Database'!T5
A6: AMZN | B6: ='0. Database'!C21 | C6: ='0. Database'!D21 | D6: ='0. Database'!E21 | E6: ='0. Database'!F21 | F6: ='0. Database'!G21 | G6: ='0. Database'!H21 | H6: ='0. Database'!I21 | I6: ='0. Database'!J21 | ... S6: ='0. Database'!T21
A7: GOOGL | B7: ='0. Database'!C36 | C7: ='0. Database'!D36 | D7: ='0. Database'!E36 | E7: ='0. Database'!F36 | F7: ='0. Database'!G36 | G7: ='0. Database'!H36 | H7: ='0. Database'!I36 | I7: ='0. Database'!J36 | ... S7: ='0. Database'!T36
A8: META | B8: ='0. Database'!C53 | C8: ='0. Database'!D53 | D8: ='0. Database'!E53 | E8: ='0. Database'!F53 | F8: ='0. Database'!G53 | G8: ='0. Database'!H53 | H8: ='0. Database'!I53 | I8: ='0. Database'!J53 | ... S8: ='0. Database'!T53
A9: ORCL | B9: ='0. Database'!C71 | C9: ='0. Database'!D71 | D9: ='0. Database'!E71 | E9: ='0. Database'!F71 | F9: ='0. Database'!G71 | G9: ='0. Database'!H71 | H9: ='0. Database'!I71 | I9: ='0. Database'!J71 | ... S9: ='0. Database'!T71
A11: C. Cloud / AI Proxy Revenue ($mm)
A12: Company | B12: 2013A | C12: 2014A | D12: 2015A | E12: 2016A | F12: 2017A | G12: 2018A | H12: 2019A | I12: 2020A | J12: 2021A | K12: 2022A | L12: 2023A | M12: 2024A | N12: 2025E | O12: 2026E | P12: 2027E | Q12: 2028E | R12: 2029E | S12: 2030E
A13: MSFT — Azure
A14: AMZN — AWS | B14: ='0. Database'!C32 | C14: ='0. Database'!D32 | D14: ='0. Database'!E32 | E14: ='0. Database'!F32 | F14: ='0. Database'!G32 | G14: ='0. Database'!H32 | H14: ='0. Database'!I32 | I14: ='0. Database'!J32 | ... S14: ='0. Database'!T32
A15: GOOGL — Cloud | B15: ='0. Database'!C47 | C15: ='0. Database'!D47 | D15: ='0. Database'!E47 | E15: ='0. Database'!F47 | F15: ='0. Database'!G47 | G15: ='0. Database'!H47 | H15: ='0. Database'!I47 | I15: ='0. Database'!J47 | ... S15: ='0. Database'!T47
A16: META — Advertising | B16: ='0. Database'!C64 | C16: ='0. Database'!D64 | D16: ='0. Database'!E64 | E16: ='0. Database'!F64 | F16: ='0. Database'!G64 | G16: ='0. Database'!H64 | H16: ='0. Database'!I64 | I16: ='0. Database'!J64 | ... S16: ='0. Database'!T64
A17: ORCL — CloudTotalRevenue | B17: ='0. Database'!C82 | C17: ='0. Database'!D82 | D17: ='0. Database'!E82 | E17: ='0. Database'!F82 | F17: ='0. Database'!G82 | G17: ='0. Database'!H82 | H17: ='0. Database'!I82 | I17: ='0. Database'!J82 | ... S17: ='0. Database'!T82
A19: B. Revenue YoY %
A20: Company | B20: 2013A | C20: 2014A | D20: 2015A | E20: 2016A | F20: 2017A | G20: 2018A | H20: 2019A | I20: 2020A | J20: 2021A | K20: 2022A | L20: 2023A | M20: 2024A | N20: 2025E | O20: 2026E | P20: 2027E | Q20: 2028E | R20: 2029E | S20: 2030E
A21: MSFT | C21: =IFERROR(C5/B5-1,"") | D21: =IFERROR(D5/C5-1,"") | E21: =IFERROR(E5/D5-1,"") | F21: =IFERROR(F5/E5-1,"") | G21: =IFERROR(G5/F5-1,"") | H21: =IFERROR(H5/G5-1,"") | I21: =IFERROR(I5/H5-1,"") | J21: =IFERROR(J5/I5-1,"") | ... S21: =IFERROR(S5/R5-1,"")
A22: AMZN | C22: =IFERROR(C6/B6-1,"") | D22: =IFERROR(D6/C6-1,"") | E22: =IFERROR(E6/D6-1,"") | F22: =IFERROR(F6/E6-1,"") | G22: =IFERROR(G6/F6-1,"") | H22: =IFERROR(H6/G6-1,"") | I22: =IFERROR(I6/H6-1,"") | J22: =IFERROR(J6/I6-1,"") | ... S22: =IFERROR(S6/R6-1,"")
A23: GOOGL | C23: =IFERROR(C7/B7-1,"") | D23: =IFERROR(D7/C7-1,"") | E23: =IFERROR(E7/D7-1,"") | F23: =IFERROR(F7/E7-1,"") | G23: =IFERROR(G7/F7-1,"") | H23: =IFERROR(H7/G7-1,"") | I23: =IFERROR(I7/H7-1,"") | J23: =IFERROR(J7/I7-1,"") | ... S23: =IFERROR(S7/R7-1,"")
A24: META | C24: =IFERROR(C8/B8-1,"") | D24: =IFERROR(D8/C8-1,"") | E24: =IFERROR(E8/D8-1,"") | F24: =IFERROR(F8/E8-1,"") | G24: =IFERROR(G8/F8-1,"") | H24: =IFERROR(H8/G8-1,"") | I24: =IFERROR(I8/H8-1,"") | J24: =IFERROR(J8/I8-1,"") | ... S24: =IFERROR(S8/R8-1,"")
A25: ORCL | C25: =IFERROR(C9/B9-1,"") | D25: =IFERROR(D9/C9-1,"") | E25: =IFERROR(E9/D9-1,"") | F25: =IFERROR(F9/E9-1,"") | G25: =IFERROR(G9/F9-1,"") | H25: =IFERROR(H9/G9-1,"") | I25: =IFERROR(I9/H9-1,"") | J25: =IFERROR(J9/I9-1,"") | ... S25: =IFERROR(S9/R9-1,"")

Sheet 3. Capex & D&A
A1: Capex&D&A (2013-2030E)
A3: A. Capex ($mm)
A4: Company | B4: 2013A | C4: 2014A | D4: 2015A | E4: 2016A | F4: 2017A | G4: 2018A | H4: 2019A | I4: 2020A | J4: 2021A | K4: 2022A | L4: 2023A | M4: 2024A | N4: 2025E | O4: 2026E | P4: 2027E | Q4: 2028E | R4: 2029E | S4: 2030E
A5: MSFT | B5: ='0. Database'!C12 | C5: ='0. Database'!D12 | D5: ='0. Database'!E12 | E5: ='0. Database'!F12 | F5: ='0. Database'!G12 | G5: ='0. Database'!H12 | H5: ='0. Database'!I12 | I5: ='0. Database'!J12 | ... S5: ='0. Database'!T12
A6: AMZN | B6: ='0. Database'!C28 | C6: ='0. Database'!D28 | D6: ='0. Database'!E28 | E6: ='0. Database'!F28 | F6: ='0. Database'!G28 | G6: ='0. Database'!H28 | H6: ='0. Database'!I28 | I6: ='0. Database'!J28 | ... S6: ='0. Database'!T28
A7: GOOGL | B7: ='0. Database'!C43 | C7: ='0. Database'!D43 | D7: ='0. Database'!E43 | E7: ='0. Database'!F43 | F7: ='0. Database'!G43 | G7: ='0. Database'!H43 | H7: ='0. Database'!I43 | I7: ='0. Database'!J43 | ... S7: ='0. Database'!T43
A8: META | B8: ='0. Database'!C60 | C8: ='0. Database'!D60 | D8: ='0. Database'!E60 | E8: ='0. Database'!F60 | F8: ='0. Database'!G60 | G8: ='0. Database'!H60 | H8: ='0. Database'!I60 | I8: ='0. Database'!J60 | ... S8: ='0. Database'!T60
A9: ORCL | B9: ='0. Database'!C78 | C9: ='0. Database'!D78 | D9: ='0. Database'!E78 | E9: ='0. Database'!F78 | F9: ='0. Database'!G78 | G9: ='0. Database'!H78 | H9: ='0. Database'!I78 | I9: ='0. Database'!J78 | ... S9: ='0. Database'!T78
A11: D. D&A ($mm)
A12: Company | B12: 2013A | C12: 2014A | D12: 2015A | E12: 2016A | F12: 2017A | G12: 2018A | H12: 2019A | I12: 2020A | J12: 2021A | K12: 2022A | L12: 2023A | M12: 2024A | N12: 2025E | O12: 2026E | P12: 2027E | Q12: 2028E | R12: 2029E | S12: 2030E
A13: MSFT | B13: ='0. Database'!C11 | C13: ='0. Database'!D11 | D13: ='0. Database'!E11 | E13: ='0. Database'!F11 | F13: ='0. Database'!G11 | G13: ='0. Database'!H11 | H13: ='0. Database'!I11 | I13: ='0. Database'!J11 | ... S13: ='0. Database'!T11
A14: AMZN | B14: ='0. Database'!C27 | C14: ='0. Database'!D27 | D14: ='0. Database'!E27 | E14: ='0. Database'!F27 | F14: ='0. Database'!G27 | G14: ='0. Database'!H27 | H14: ='0. Database'!I27 | I14: ='0. Database'!J27 | ... S14: ='0. Database'!T27
A15: GOOGL | B15: ='0. Database'!C42 | C15: ='0. Database'!D42 | D15: ='0. Database'!E42 | E15: ='0. Database'!F42 | F15: ='0. Database'!G42 | G15: ='0. Database'!H42 | H15: ='0. Database'!I42 | I15: ='0. Database'!J42 | ... S15: ='0. Database'!T42
A16: META | B16: ='0. Database'!C59 | C16: ='0. Database'!D59 | D16: ='0. Database'!E59 | E16: ='0. Database'!F59 | F16: ='0. Database'!G59 | G16: ='0. Database'!H59 | H16: ='0. Database'!I59 | I16: ='0. Database'!J59 | ... S16: ='0. Database'!T59
A17: ORCL | B17: ='0. Database'!C77 | C17: ='0. Database'!D77 | D17: ='0. Database'!E77 | E17: ='0. Database'!F77 | F17: ='0. Database'!G77 | G17: ='0. Database'!H77 | H17: ='0. Database'!I77 | I17: ='0. Database'!J77 | ... S17: ='0. Database'!T77
A19: (Revenue — for ratios)
A20: Company | B20: 2013A | C20: 2014A | D20: 2015A | E20: 2016A | F20: 2017A | G20: 2018A | H20: 2019A | I20: 2020A | J20: 2021A | K20: 2022A | L20: 2023A | M20: 2024A | N20: 2025E | O20: 2026E | P20: 2027E | Q20: 2028E | R20: 2029E | S20: 2030E
A21: MSFT | B21: ='0. Database'!C5 | C21: ='0. Database'!D5 | D21: ='0. Database'!E5 | E21: ='0. Database'!F5 | F21: ='0. Database'!G5 | G21: ='0. Database'!H5 | H21: ='0. Database'!I5 | I21: ='0. Database'!J5 | ... S21: ='0. Database'!T5
A22: AMZN | B22: ='0. Database'!C21 | C22: ='0. Database'!D21 | D22: ='0. Database'!E21 | E22: ='0. Database'!F21 | F22: ='0. Database'!G21 | G22: ='0. Database'!H21 | H22: ='0. Database'!I21 | I22: ='0. Database'!J21 | ... S22: ='0. Database'!T21
A23: GOOGL | B23: ='0. Database'!C36 | C23: ='0. Database'!D36 | D23: ='0. Database'!E36 | E23: ='0. Database'!F36 | F23: ='0. Database'!G36 | G23: ='0. Database'!H36 | H23: ='0. Database'!I36 | I23: ='0. Database'!J36 | ... S23: ='0. Database'!T36
A24: META | B24: ='0. Database'!C53 | C24: ='0. Database'!D53 | D24: ='0. Database'!E53 | E24: ='0. Database'!F53 | F24: ='0. Database'!G53 | G24: ='0. Database'!H53 | H24: ='0. Database'!I53 | I24: ='0. Database'!J53 | ... S24: ='0. Database'!T53
A25: ORCL | B25: ='0. Database'!C71 | C25: ='0. Database'!D71 | D25: ='0. Database'!E71 | E25: ='0. Database'!F71 | F25: ='0. Database'!G71 | G25: ='0. Database'!H71 | H25: ='0. Database'!I71 | I25: ='0. Database'!J71 | ... S25: ='0. Database'!T71
A27: B. CapexYoY %
A28: Company | B28: 2013A | C28: 2014A | D28: 2015A | E28: 2016A | F28: 2017A | G28: 2018A | H28: 2019A | I28: 2020A | J28: 2021A | K28: 2022A | L28: 2023A | M28: 2024A | N28: 2025E | O28: 2026E | P28: 2027E | Q28: 2028E | R28: 2029E | S28: 2030E
A29: MSFT | C29: =IFERROR(C5/B5-1,"") | D29: =IFERROR(D5/C5-1,"") | E29: =IFERROR(E5/D5-1,"") | F29: =IFERROR(F5/E5-1,"") | G29: =IFERROR(G5/F5-1,"") | H29: =IFERROR(H5/G5-1,"") | I29: =IFERROR(I5/H5-1,"") | J29: =IFERROR(J5/I5-1,"") | ... S29: =IFERROR(S5/R5-1,"")
A30: AMZN | C30: =IFERROR(C6/B6-1,"") | D30: =IFERROR(D6/C6-1,"") | E30: =IFERROR(E6/D6-1,"") | F30: =IFERROR(F6/E6-1,"") | G30: =IFERROR(G6/F6-1,"") | H30: =IFERROR(H6/G6-1,"") | I30: =IFERROR(I6/H6-1,"") | J30: =IFERROR(J6/I6-1,"") | ... S30: =IFERROR(S6/R6-1,"")
A31: GOOGL | C31: =IFERROR(C7/B7-1,"") | D31: =IFERROR(D7/C7-1,"") | E31: =IFERROR(E7/D7-1,"") | F31: =IFERROR(F7/E7-1,"") | G31: =IFERROR(G7/F7-1,"") | H31: =IFERROR(H7/G7-1,"") | I31: =IFERROR(I7/H7-1,"") | J31: =IFERROR(J7/I7-1,"") | ... S31: =IFERROR(S7/R7-1,"")
A32: META | C32: =IFERROR(C8/B8-1,"") | D32: =IFERROR(D8/C8-1,"") | E32: =IFERROR(E8/D8-1,"") | F32: =IFERROR(F8/E8-1,"") | G32: =IFERROR(G8/F8-1,"") | H32: =IFERROR(H8/G8-1,"") | I32: =IFERROR(I8/H8-1,"") | J32: =IFERROR(J8/I8-1,"") | ... S32: =IFERROR(S8/R8-1,"")
A33: ORCL | C33: =IFERROR(C9/B9-1,"") | D33: =IFERROR(D9/C9-1,"") | E33: =IFERROR(E9/D9-1,"") | F33: =IFERROR(F9/E9-1,"") | G33: =IFERROR(G9/F9-1,"") | H33: =IFERROR(H9/G9-1,"") | I33: =IFERROR(I9/H9-1,"") | J33: =IFERROR(J9/I9-1,"") | ... S33: =IFERROR(S9/R9-1,"")
A35: C. Capex / Revenue %
A36: Company | B36: 2013A | C36: 2014A | D36: 2015A | E36: 2016A | F36: 2017A | G36: 2018A | H36: 2019A | I36: 2020A | J36: 2021A | K36: 2022A | L36: 2023A | M36: 2024A | N36: 2025E | O36: 2026E | P36: 2027E | Q36: 2028E | R36: 2029E | S36: 2030E
A37: MSFT | B37: =IFERROR(B5/B21,"") | C37: =IFERROR(C5/C21,"") | D37: =IFERROR(D5/D21,"") | E37: =IFERROR(E5/E21,"") | F37: =IFERROR(F5/F21,"") | G37: =IFERROR(G5/G21,"") | H37: =IFERROR(H5/H21,"") | I37: =IFERROR(I5/I21,"") | ... S37: =IFERROR(S5/S21,"")
A38: AMZN | B38: =IFERROR(B6/B22,"") | C38: =IFERROR(C6/C22,"") | D38: =IFERROR(D6/D22,"") | E38: =IFERROR(E6/E22,"") | F38: =IFERROR(F6/F22,"") | G38: =IFERROR(G6/G22,"") | H38: =IFERROR(H6/H22,"") | I38: =IFERROR(I6/I22,"") | ... S38: =IFERROR(S6/S22,"")
A39: GOOGL | B39: =IFERROR(B7/B23,"") | C39: =IFERROR(C7/C23,"") | D39: =IFERROR(D7/D23,"") | E39: =IFERROR(E7/E23,"") | F39: =IFERROR(F7/F23,"") | G39: =IFERROR(G7/G23,"") | H39: =IFERROR(H7/H23,"") | I39: =IFERROR(I7/I23,"") | ... S39: =IFERROR(S7/S23,"")
A40: META | B40: =IFERROR(B8/B24,"") | C40: =IFERROR(C8/C24,"") | D40: =IFERROR(D8/D24,"") | E40: =IFERROR(E8/E24,"") | F40: =IFERROR(F8/F24,"") | G40: =IFERROR(G8/G24,"") | H40: =IFERROR(H8/H24,"") | I40: =IFERROR(I8/I24,"") | ... S40: =IFERROR(S8/S24,"")
A41: ORCL | B41: =IFERROR(B9/B25,"") | C41: =IFERROR(C9/C25,"") | D41: =IFERROR(D9/D25,"") | E41: =IFERROR(E9/E25,"") | F41: =IFERROR(F9/F25,"") | G41: =IFERROR(G9/G25,"") | H41: =IFERROR(H9/H25,"") | I41: =IFERROR(I9/I25,"") | ... S41: =IFERROR(S9/S25,"")
A43: E. D&A / Revenue %
A44: Company | B44: 2013A | C44: 2014A | D44: 2015A | E44: 2016A | F44: 2017A | G44: 2018A | H44: 2019A | I44: 2020A | J44: 2021A | K44: 2022A | L44: 2023A | M44: 2024A | N44: 2025E | O44: 2026E | P44: 2027E | Q44: 2028E | R44: 2029E | S44: 2030E
A45: MSFT | B45: =IFERROR(B13/B21,"") | C45: =IFERROR(C13/C21,"") | D45: =IFERROR(D13/D21,"") | E45: =IFERROR(E13/E21,"") | F45: =IFERROR(F13/F21,"") | G45: =IFERROR(G13/G21,"") | H45: =IFERROR(H13/H21,"") | I45: =IFERROR(I13/I21,"") | ... S45: =IFERROR(S13/S21,"")
A46: AMZN | B46: =IFERROR(B14/B22,"") | C46: =IFERROR(C14/C22,"") | D46: =IFERROR(D14/D22,"") | E46: =IFERROR(E14/E22,"") | F46: =IFERROR(F14/F22,"") | G46: =IFERROR(G14/G22,"") | H46: =IFERROR(H14/H22,"") | I46: =IFERROR(I14/I22,"") | ... S46: =IFERROR(S14/S22,"")
A47: GOOGL | B47: =IFERROR(B15/B23,"") | C47: =IFERROR(C15/C23,"") | D47: =IFERROR(D15/D23,"") | E47: =IFERROR(E15/E23,"") | F47: =IFERROR(F15/F23,"") | G47: =IFERROR(G15/G23,"") | H47: =IFERROR(H15/H23,"") | I47: =IFERROR(I15/I23,"") | ... S47: =IFERROR(S15/S23,"")
A48: META | B48: =IFERROR(B16/B24,"") | C48: =IFERROR(C16/C24,"") | D48: =IFERROR(D16/D24,"") | E48: =IFERROR(E16/E24,"") | F48: =IFERROR(F16/F24,"") | G48: =IFERROR(G16/G24,"") | H48: =IFERROR(H16/H24,"") | I48: =IFERROR(I16/I24,"") | ... S48: =IFERROR(S16/S24,"")
A49: ORCL | B49: =IFERROR(B17/B25,"") | C49: =IFERROR(C17/C25,"") | D49: =IFERROR(D17/D25,"") | E49: =IFERROR(E17/E25,"") | F49: =IFERROR(F17/F25,"") | G49: =IFERROR(G17/G25,"") | H49: =IFERROR(H17/H25,"") | I49: =IFERROR(I17/I25,"") | ... S49: =IFERROR(S17/S25,"")
A51: F. D&AYoY %
A52: Company | B52: 2013A | C52: 2014A | D52: 2015A | E52: 2016A | F52: 2017A | G52: 2018A | H52: 2019A | I52: 2020A | J52: 2021A | K52: 2022A | L52: 2023A | M52: 2024A | N52: 2025E | O52: 2026E | P52: 2027E | Q52: 2028E | R52: 2029E | S52: 2030E
A53: MSFT | C53: =IFERROR(C13/B13-1,"") | D53: =IFERROR(D13/C13-1,"") | E53: =IFERROR(E13/D13-1,"") | F53: =IFERROR(F13/E13-1,"") | G53: =IFERROR(G13/F13-1,"") | H53: =IFERROR(H13/G13-1,"") | I53: =IFERROR(I13/H13-1,"") | J53: =IFERROR(J13/I13-1,"") | ... S53: =IFERROR(S13/R13-1,"")
A54: AMZN | C54: =IFERROR(C14/B14-1,"") | D54: =IFERROR(D14/C14-1,"") | E54: =IFERROR(E14/D14-1,"") | F54: =IFERROR(F14/E14-1,"") | G54: =IFERROR(G14/F14-1,"") | H54: =IFERROR(H14/G14-1,"") | I54: =IFERROR(I14/H14-1,"") | J54: =IFERROR(J14/I14-1,"") | ... S54: =IFERROR(S14/R14-1,"")
A55: GOOGL | C55: =IFERROR(C15/B15-1,"") | D55: =IFERROR(D15/C15-1,"") | E55: =IFERROR(E15/D15-1,"") | F55: =IFERROR(F15/E15-1,"") | G55: =IFERROR(G15/F15-1,"") | H55: =IFERROR(H15/G15-1,"") | I55: =IFERROR(I15/H15-1,"") | J55: =IFERROR(J15/I15-1,"") | ... S55: =IFERROR(S15/R15-1,"")
A56: META | C56: =IFERROR(C16/B16-1,"") | D56: =IFERROR(D16/C16-1,"") | E56: =IFERROR(E16/D16-1,"") | F56: =IFERROR(F16/E16-1,"") | G56: =IFERROR(G16/F16-1,"") | H56: =IFERROR(H16/G16-1,"") | I56: =IFERROR(I16/H16-1,"") | J56: =IFERROR(J16/I16-1,"") | ... S56: =IFERROR(S16/R16-1,"")
A57: ORCL | C57: =IFERROR(C17/B17-1,"") | D57: =IFERROR(D17/C17-1,"") | E57: =IFERROR(E17/D17-1,"") | F57: =IFERROR(F17/E17-1,"") | G57: =IFERROR(G17/F17-1,"") | H57: =IFERROR(H17/G17-1,"") | I57: =IFERROR(I17/H17-1,"") | J57: =IFERROR(J17/I17-1,"") | ... S57: =IFERROR(S17/R17-1,"")

Sheet 4. FCF & Cash
A1: Free Cash Flow&Cash Quality (2013-2030E)
A3: A. CFO ($mm)
A4: Company | B4: 2013A | C4: 2014A | D4: 2015A | E4: 2016A | F4: 2017A | G4: 2018A | H4: 2019A | I4: 2020A | J4: 2021A | K4: 2022A | L4: 2023A | M4: 2024A | N4: 2025E | O4: 2026E | P4: 2027E | Q4: 2028E | R4: 2029E | S4: 2030E
A5: MSFT | B5: ='0. Database'!C13 | C5: ='0. Database'!D13 | D5: ='0. Database'!E13 | E5: ='0. Database'!F13 | F5: ='0. Database'!G13 | G5: ='0. Database'!H13 | H5: ='0. Database'!I13 | I5: ='0. Database'!J13 | ... S5: ='0. Database'!T13
A6: AMZN | B6: ='0. Database'!C29 | C6: ='0. Database'!D29 | D6: ='0. Database'!E29 | E6: ='0. Database'!F29 | F6: ='0. Database'!G29 | G6: ='0. Database'!H29 | H6: ='0. Database'!I29 | I6: ='0. Database'!J29 | ... S6: ='0. Database'!T29
A7: GOOGL | B7: ='0. Database'!C44 | C7: ='0. Database'!D44 | D7: ='0. Database'!E44 | E7: ='0. Database'!F44 | F7: ='0. Database'!G44 | G7: ='0. Database'!H44 | H7: ='0. Database'!I44 | I7: ='0. Database'!J44 | ... S7: ='0. Database'!T44
A8: META | B8: ='0. Database'!C61 | C8: ='0. Database'!D61 | D8: ='0. Database'!E61 | E8: ='0. Database'!F61 | F8: ='0. Database'!G61 | G8: ='0. Database'!H61 | H8: ='0. Database'!I61 | I8: ='0. Database'!J61 | ... S8: ='0. Database'!T61
A9: ORCL | B9: ='0. Database'!C79 | C9: ='0. Database'!D79 | D9: ='0. Database'!E79 | E9: ='0. Database'!F79 | F9: ='0. Database'!G79 | G9: ='0. Database'!H79 | H9: ='0. Database'!I79 | I9: ='0. Database'!J79 | ... S9: ='0. Database'!T79
A11: B. FCF ($mm)
A12: Company | B12: 2013A | C12: 2014A | D12: 2015A | E12: 2016A | F12: 2017A | G12: 2018A | H12: 2019A | I12: 2020A | J12: 2021A | K12: 2022A | L12: 2023A | M12: 2024A | N12: 2025E | O12: 2026E | P12: 2027E | Q12: 2028E | R12: 2029E | S12: 2030E
A13: MSFT | B13: ='0. Database'!C14 | C13: ='0. Database'!D14 | D13: ='0. Database'!E14 | E13: ='0. Database'!F14 | F13: ='0. Database'!G14 | G13: ='0. Database'!H14 | H13: ='0. Database'!I14 | I13: ='0. Database'!J14 | ... S13: ='0. Database'!T14
A14: AMZN | B14: ='0. Database'!C30 | C14: ='0. Database'!D30 | D14: ='0. Database'!E30 | E14: ='0. Database'!F30 | F14: ='0. Database'!G30 | G14: ='0. Database'!H30 | H14: ='0. Database'!I30 | I14: ='0. Database'!J30 | ... S14: ='0. Database'!T30
A15: GOOGL | B15: ='0. Database'!C45 | C15: ='0. Database'!D45 | D15: ='0. Database'!E45 | E15: ='0. Database'!F45 | F15: ='0. Database'!G45 | G15: ='0. Database'!H45 | H15: ='0. Database'!I45 | I15: ='0. Database'!J45 | ... S15: ='0. Database'!T45
A16: META | B16: ='0. Database'!C62 | C16: ='0. Database'!D62 | D16: ='0. Database'!E62 | E16: ='0. Database'!F62 | F16: ='0. Database'!G62 | G16: ='0. Database'!H62 | H16: ='0. Database'!I62 | I16: ='0. Database'!J62 | ... S16: ='0. Database'!T62
A17: ORCL | B17: ='0. Database'!C80 | C17: ='0. Database'!D80 | D17: ='0. Database'!E80 | E17: ='0. Database'!F80 | F17: ='0. Database'!G80 | G17: ='0. Database'!H80 | H17: ='0. Database'!I80 | I17: ='0. Database'!J80 | ... S17: ='0. Database'!T80
A19: E. Buybacks ($mm)
A20: Company | B20: 2013A | C20: 2014A | D20: 2015A | E20: 2016A | F20: 2017A | G20: 2018A | H20: 2019A | I20: 2020A | J20: 2021A | K20: 2022A | L20: 2023A | M20: 2024A | N20: 2025E | O20: 2026E | P20: 2027E | Q20: 2028E | R20: 2029E | S20: 2030E
A21: MSFT | B21: ='0. Database'!C15 | C21: ='0. Database'!D15 | D21: ='0. Database'!E15 | E21: ='0. Database'!F15 | F21: ='0. Database'!G15 | G21: ='0. Database'!H15 | H21: ='0. Database'!I15 | I21: ='0. Database'!J15 | ... S21: ='0. Database'!T15
A22: AMZN | B22: ='0. Database'!C31 | C22: ='0. Database'!D31 | D22: ='0. Database'!E31 | E22: ='0. Database'!F31 | F22: ='0. Database'!G31 | G22: ='0. Database'!H31 | H22: ='0. Database'!I31 | I22: ='0. Database'!J31 | ... S22: ='0. Database'!T31
A23: GOOGL | B23: ='0. Database'!C46 | C23: ='0. Database'!D46 | D23: ='0. Database'!E46 | E23: ='0. Database'!F46 | F23: ='0. Database'!G46 | G23: ='0. Database'!H46 | H23: ='0. Database'!I46 | I23: ='0. Database'!J46 | ... S23: ='0. Database'!T46
A24: META | B24: ='0. Database'!C63 | C24: ='0. Database'!D63 | D24: ='0. Database'!E63 | E24: ='0. Database'!F63 | F24: ='0. Database'!G63 | G24: ='0. Database'!H63 | H24: ='0. Database'!I63 | I24: ='0. Database'!J63 | ... S24: ='0. Database'!T63
A25: ORCL | B25: ='0. Database'!C81 | C25: ='0. Database'!D81 | D25: ='0. Database'!E81 | E25: ='0. Database'!F81 | F25: ='0. Database'!G81 | G25: ='0. Database'!H81 | H25: ='0. Database'!I81 | I25: ='0. Database'!J81 | ... S25: ='0. Database'!T81
A27: (Revenue)
A28: Company | B28: 2013A | C28: 2014A | D28: 2015A | E28: 2016A | F28: 2017A | G28: 2018A | H28: 2019A | I28: 2020A | J28: 2021A | K28: 2022A | L28: 2023A | M28: 2024A | N28: 2025E | O28: 2026E | P28: 2027E | Q28: 2028E | R28: 2029E | S28: 2030E
A29: MSFT | B29: ='0. Database'!C5 | C29: ='0. Database'!D5 | D29: ='0. Database'!E5 | E29: ='0. Database'!F5 | F29: ='0. Database'!G5 | G29: ='0. Database'!H5 | H29: ='0. Database'!I5 | I29: ='0. Database'!J5 | ... S29: ='0. Database'!T5
A30: AMZN | B30: ='0. Database'!C21 | C30: ='0. Database'!D21 | D30: ='0. Database'!E21 | E30: ='0. Database'!F21 | F30: ='0. Database'!G21 | G30: ='0. Database'!H21 | H30: ='0. Database'!I21 | I30: ='0. Database'!J21 | ... S30: ='0. Database'!T21
A31: GOOGL | B31: ='0. Database'!C36 | C31: ='0. Database'!D36 | D31: ='0. Database'!E36 | E31: ='0. Database'!F36 | F31: ='0. Database'!G36 | G31: ='0. Database'!H36 | H31: ='0. Database'!I36 | I31: ='0. Database'!J36 | ... S31: ='0. Database'!T36
A32: META | B32: ='0. Database'!C53 | C32: ='0. Database'!D53 | D32: ='0. Database'!E53 | E32: ='0. Database'!F53 | F32: ='0. Database'!G53 | G32: ='0. Database'!H53 | H32: ='0. Database'!I53 | I32: ='0. Database'!J53 | ... S32: ='0. Database'!T53
A33: ORCL | B33: ='0. Database'!C71 | C33: ='0. Database'!D71 | D33: ='0. Database'!E71 | E33: ='0. Database'!F71 | F33: ='0. Database'!G71 | G33: ='0. Database'!H71 | H33: ='0. Database'!I71 | I33: ='0. Database'!J71 | ... S33: ='0. Database'!T71
A35: (NI)
A36: Company | B36: 2013A | C36: 2014A | D36: 2015A | E36: 2016A | F36: 2017A | G36: 2018A | H36: 2019A | I36: 2020A | J36: 2021A | K36: 2022A | L36: 2023A | M36: 2024A | N36: 2025E | O36: 2026E | P36: 2027E | Q36: 2028E | R36: 2029E | S36: 2030E
A37: MSFT | B37: ='0. Database'!C7 | C37: ='0. Database'!D7 | D37: ='0. Database'!E7 | E37: ='0. Database'!F7 | F37: ='0. Database'!G7 | G37: ='0. Database'!H7 | H37: ='0. Database'!I7 | I37: ='0. Database'!J7 | ... S37: ='0. Database'!T7
A38: AMZN | B38: ='0. Database'!C23 | C38: ='0. Database'!D23 | D38: ='0. Database'!E23 | E38: ='0. Database'!F23 | F38: ='0. Database'!G23 | G38: ='0. Database'!H23 | H38: ='0. Database'!I23 | I38: ='0. Database'!J23 | ... S38: ='0. Database'!T23
A39: GOOGL | B39: ='0. Database'!C38 | C39: ='0. Database'!D38 | D39: ='0. Database'!E38 | E39: ='0. Database'!F38 | F39: ='0. Database'!G38 | G39: ='0. Database'!H38 | H39: ='0. Database'!I38 | I39: ='0. Database'!J38 | ... S39: ='0. Database'!T38
A40: META | B40: ='0. Database'!C55 | C40: ='0. Database'!D55 | D40: ='0. Database'!E55 | E40: ='0. Database'!F55 | F40: ='0. Database'!G55 | G40: ='0. Database'!H55 | H40: ='0. Database'!I55 | I40: ='0. Database'!J55 | ... S40: ='0. Database'!T55
A41: ORCL | B41: ='0. Database'!C73 | C41: ='0. Database'!D73 | D41: ='0. Database'!E73 | E41: ='0. Database'!F73 | F41: ='0. Database'!G73 | G41: ='0. Database'!H73 | H41: ='0. Database'!I73 | I41: ='0. Database'!J73 | ... S41: ='0. Database'!T73
A43: (Capex)
A44: Company | B44: 2013A | C44: 2014A | D44: 2015A | E44: 2016A | F44: 2017A | G44: 2018A | H44: 2019A | I44: 2020A | J44: 2021A | K44: 2022A | L44: 2023A | M44: 2024A | N44: 2025E | O44: 2026E | P44: 2027E | Q44: 2028E | R44: 2029E | S44: 2030E
A45: MSFT | B45: ='0. Database'!C12 | C45: ='0. Database'!D12 | D45: ='0. Database'!E12 | E45: ='0. Database'!F12 | F45: ='0. Database'!G12 | G45: ='0. Database'!H12 | H45: ='0. Database'!I12 | I45: ='0. Database'!J12 | ... S45: ='0. Database'!T12
A46: AMZN | B46: ='0. Database'!C28 | C46: ='0. Database'!D28 | D46: ='0. Database'!E28 | E46: ='0. Database'!F28 | F46: ='0. Database'!G28 | G46: ='0. Database'!H28 | H46: ='0. Database'!I28 | I46: ='0. Database'!J28 | ... S46: ='0. Database'!T28
A47: GOOGL | B47: ='0. Database'!C43 | C47: ='0. Database'!D43 | D47: ='0. Database'!E43 | E47: ='0. Database'!F43 | F47: ='0. Database'!G43 | G47: ='0. Database'!H43 | H47: ='0. Database'!I43 | I47: ='0. Database'!J43 | ... S47: ='0. Database'!T43
A48: META | B48: ='0. Database'!C60 | C48: ='0. Database'!D60 | D48: ='0. Database'!E60 | E48: ='0. Database'!F60 | F48: ='0. Database'!G60 | G48: ='0. Database'!H60 | H48: ='0. Database'!I60 | I48: ='0. Database'!J60 | ... S48: ='0. Database'!T60
A49: ORCL | B49: ='0. Database'!C78 | C49: ='0. Database'!D78 | D49: ='0. Database'!E78 | E49: ='0. Database'!F78 | F49: ='0. Database'!G78 | G49: ='0. Database'!H78 | H49: ='0. Database'!I78 | I49: ='0. Database'!J78 | ... S49: ='0. Database'!T78
A51: C. Free Cash FlowMargin %
A52: Company | B52: 2013A | C52: 2014A | D52: 2015A | E52: 2016A | F52: 2017A | G52: 2018A | H52: 2019A | I52: 2020A | J52: 2021A | K52: 2022A | L52: 2023A | M52: 2024A | N52: 2025E | O52: 2026E | P52: 2027E | Q52: 2028E | R52: 2029E | S52: 2030E
A53: MSFT | B53: =IFERROR(B13/B29,"") | C53: =IFERROR(C13/C29,"") | D53: =IFERROR(D13/D29,"") | E53: =IFERROR(E13/E29,"") | F53: =IFERROR(F13/F29,"") | G53: =IFERROR(G13/G29,"") | H53: =IFERROR(H13/H29,"") | I53: =IFERROR(I13/I29,"") | ... S53: =IFERROR(S13/S29,"")
A54: AMZN | B54: =IFERROR(B14/B30,"") | C54: =IFERROR(C14/C30,"") | D54: =IFERROR(D14/D30,"") | E54: =IFERROR(E14/E30,"") | F54: =IFERROR(F14/F30,"") | G54: =IFERROR(G14/G30,"") | H54: =IFERROR(H14/H30,"") | I54: =IFERROR(I14/I30,"") | ... S54: =IFERROR(S14/S30,"")
A55: GOOGL | B55: =IFERROR(B15/B31,"") | C55: =IFERROR(C15/C31,"") | D55: =IFERROR(D15/D31,"") | E55: =IFERROR(E15/E31,"") | F55: =IFERROR(F15/F31,"") | G55: =IFERROR(G15/G31,"") | H55: =IFERROR(H15/H31,"") | I55: =IFERROR(I15/I31,"") | ... S55: =IFERROR(S15/S31,"")
A56: META | B56: =IFERROR(B16/B32,"") | C56: =IFERROR(C16/C32,"") | D56: =IFERROR(D16/D32,"") | E56: =IFERROR(E16/E32,"") | F56: =IFERROR(F16/F32,"") | G56: =IFERROR(G16/G32,"") | H56: =IFERROR(H16/H32,"") | I56: =IFERROR(I16/I32,"") | ... S56: =IFERROR(S16/S32,"")
A57: ORCL | B57: =IFERROR(B17/B33,"") | C57: =IFERROR(C17/C33,"") | D57: =IFERROR(D17/D33,"") | E57: =IFERROR(E17/E33,"") | F57: =IFERROR(F17/F33,"") | G57: =IFERROR(G17/G33,"") | H57: =IFERROR(H17/H33,"") | I57: =IFERROR(I17/I33,"") | ... S57: =IFERROR(S17/S33,"")
A59: D. FCF / Net Income %
A60: Company | B60: 2013A | C60: 2014A | D60: 2015A | E60: 2016A | F60: 2017A | G60: 2018A | H60: 2019A | I60: 2020A | J60: 2021A | K60: 2022A | L60: 2023A | M60: 2024A | N60: 2025E | O60: 2026E | P60: 2027E | Q60: 2028E | R60: 2029E | S60: 2030E
A61: MSFT | B61: =IFERROR(B13/B37,"") | C61: =IFERROR(C13/C37,"") | D61: =IFERROR(D13/D37,"") | E61: =IFERROR(E13/E37,"") | F61: =IFERROR(F13/F37,"") | G61: =IFERROR(G13/G37,"") | H61: =IFERROR(H13/H37,"") | I61: =IFERROR(I13/I37,"") | ... S61: =IFERROR(S13/S37,"")
A62: AMZN | B62: =IFERROR(B14/B38,"") | C62: =IFERROR(C14/C38,"") | D62: =IFERROR(D14/D38,"") | E62: =IFERROR(E14/E38,"") | F62: =IFERROR(F14/F38,"") | G62: =IFERROR(G14/G38,"") | H62: =IFERROR(H14/H38,"") | I62: =IFERROR(I14/I38,"") | ... S62: =IFERROR(S14/S38,"")
A63: GOOGL | B63: =IFERROR(B15/B39,"") | C63: =IFERROR(C15/C39,"") | D63: =IFERROR(D15/D39,"") | E63: =IFERROR(E15/E39,"") | F63: =IFERROR(F15/F39,"") | G63: =IFERROR(G15/G39,"") | H63: =IFERROR(H15/H39,"") | I63: =IFERROR(I15/I39,"") | ... S63: =IFERROR(S15/S39,"")
A64: META | B64: =IFERROR(B16/B40,"") | C64: =IFERROR(C16/C40,"") | D64: =IFERROR(D16/D40,"") | E64: =IFERROR(E16/E40,"") | F64: =IFERROR(F16/F40,"") | G64: =IFERROR(G16/G40,"") | H64: =IFERROR(H16/H40,"") | I64: =IFERROR(I16/I40,"") | ... S64: =IFERROR(S16/S40,"")
A65: ORCL | B65: =IFERROR(B17/B41,"") | C65: =IFERROR(C17/C41,"") | D65: =IFERROR(D17/D41,"") | E65: =IFERROR(E17/E41,"") | F65: =IFERROR(F17/F41,"") | G65: =IFERROR(G17/G41,"") | H65: =IFERROR(H17/H41,"") | I65: =IFERROR(I17/I41,"") | ... S65: =IFERROR(S17/S41,"")
A67: F. Capex/CFO %
A68: Company | B68: 2013A | C68: 2014A | D68: 2015A | E68: 2016A | F68: 2017A | G68: 2018A | H68: 2019A | I68: 2020A | J68: 2021A | K68: 2022A | L68: 2023A | M68: 2024A | N68: 2025E | O68: 2026E | P68: 2027E | Q68: 2028E | R68: 2029E | S68: 2030E
A69: MSFT | B69: =IFERROR(B45/B5,"") | C69: =IFERROR(C45/C5,"") | D69: =IFERROR(D45/D5,"") | E69: =IFERROR(E45/E5,"") | F69: =IFERROR(F45/F5,"") | G69: =IFERROR(G45/G5,"") | H69: =IFERROR(H45/H5,"") | I69: =IFERROR(I45/I5,"") | ... S69: =IFERROR(S45/S5,"")
A70: AMZN | B70: =IFERROR(B46/B6,"") | C70: =IFERROR(C46/C6,"") | D70: =IFERROR(D46/D6,"") | E70: =IFERROR(E46/E6,"") | F70: =IFERROR(F46/F6,"") | G70: =IFERROR(G46/G6,"") | H70: =IFERROR(H46/H6,"") | I70: =IFERROR(I46/I6,"") | ... S70: =IFERROR(S46/S6,"")
A71: GOOGL | B71: =IFERROR(B47/B7,"") | C71: =IFERROR(C47/C7,"") | D71: =IFERROR(D47/D7,"") | E71: =IFERROR(E47/E7,"") | F71: =IFERROR(F47/F7,"") | G71: =IFERROR(G47/G7,"") | H71: =IFERROR(H47/H7,"") | I71: =IFERROR(I47/I7,"") | ... S71: =IFERROR(S47/S7,"")
A72: META | B72: =IFERROR(B48/B8,"") | C72: =IFERROR(C48/C8,"") | D72: =IFERROR(D48/D8,"") | E72: =IFERROR(E48/E8,"") | F72: =IFERROR(F48/F8,"") | G72: =IFERROR(G48/G8,"") | H72: =IFERROR(H48/H8,"") | I72: =IFERROR(I48/I8,"") | ... S72: =IFERROR(S48/S8,"")
A73: ORCL | B73: =IFERROR(B49/B9,"") | C73: =IFERROR(C49/C9,"") | D73: =IFERROR(D49/D9,"") | E73: =IFERROR(E49/E9,"") | F73: =IFERROR(F49/F9,"") | G73: =IFERROR(G49/G9,"") | H73: =IFERROR(H49/H9,"") | I73: =IFERROR(I49/I9,"") | ... S73: =IFERROR(S49/S9,"")

Sheet 5. EPS & Margins
A1: EPS、Operating IncomeMargin&Profitability (2013-2030E)
A3: A. Operating Income ($mm)
A4: Company | B4: 2013A | C4: 2014A | D4: 2015A | E4: 2016A | F4: 2017A | G4: 2018A | H4: 2019A | I4: 2020A | J4: 2021A | K4: 2022A | L4: 2023A | M4: 2024A | N4: 2025E | O4: 2026E | P4: 2027E | Q4: 2028E | R4: 2029E | S4: 2030E
A5: MSFT | B5: ='0. Database'!C6 | C5: ='0. Database'!D6 | D5: ='0. Database'!E6 | E5: ='0. Database'!F6 | F5: ='0. Database'!G6 | G5: ='0. Database'!H6 | H5: ='0. Database'!I6 | I5: ='0. Database'!J6 | ... S5: ='0. Database'!T6
A6: AMZN | B6: ='0. Database'!C22 | C6: ='0. Database'!D22 | D6: ='0. Database'!E22 | E6: ='0. Database'!F22 | F6: ='0. Database'!G22 | G6: ='0. Database'!H22 | H6: ='0. Database'!I22 | I6: ='0. Database'!J22 | ... S6: ='0. Database'!T22
A7: GOOGL | B7: ='0. Database'!C37 | C7: ='0. Database'!D37 | D7: ='0. Database'!E37 | E7: ='0. Database'!F37 | F7: ='0. Database'!G37 | G7: ='0. Database'!H37 | H7: ='0. Database'!I37 | I7: ='0. Database'!J37 | ... S7: ='0. Database'!T37
A8: META | B8: ='0. Database'!C54 | C8: ='0. Database'!D54 | D8: ='0. Database'!E54 | E8: ='0. Database'!F54 | F8: ='0. Database'!G54 | G8: ='0. Database'!H54 | H8: ='0. Database'!I54 | I8: ='0. Database'!J54 | ... S8: ='0. Database'!T54
A9: ORCL | B9: ='0. Database'!C72 | C9: ='0. Database'!D72 | D9: ='0. Database'!E72 | E9: ='0. Database'!F72 | F9: ='0. Database'!G72 | G9: ='0. Database'!H72 | H9: ='0. Database'!I72 | I9: ='0. Database'!J72 | ... S9: ='0. Database'!T72
A11: C. Net Income ($mm)
A12: Company | B12: 2013A | C12: 2014A | D12: 2015A | E12: 2016A | F12: 2017A | G12: 2018A | H12: 2019A | I12: 2020A | J12: 2021A | K12: 2022A | L12: 2023A | M12: 2024A | N12: 2025E | O12: 2026E | P12: 2027E | Q12: 2028E | R12: 2029E | S12: 2030E
A13: MSFT | B13: ='0. Database'!C7 | C13: ='0. Database'!D7 | D13: ='0. Database'!E7 | E13: ='0. Database'!F7 | F13: ='0. Database'!G7 | G13: ='0. Database'!H7 | H13: ='0. Database'!I7 | I13: ='0. Database'!J7 | ... S13: ='0. Database'!T7
A14: AMZN | B14: ='0. Database'!C23 | C14: ='0. Database'!D23 | D14: ='0. Database'!E23 | E14: ='0. Database'!F23 | F14: ='0. Database'!G23 | G14: ='0. Database'!H23 | H14: ='0. Database'!I23 | I14: ='0. Database'!J23 | ... S14: ='0. Database'!T23
A15: GOOGL | B15: ='0. Database'!C38 | C15: ='0. Database'!D38 | D15: ='0. Database'!E38 | E15: ='0. Database'!F38 | F15: ='0. Database'!G38 | G15: ='0. Database'!H38 | H15: ='0. Database'!I38 | I15: ='0. Database'!J38 | ... S15: ='0. Database'!T38
A16: META | B16: ='0. Database'!C55 | C16: ='0. Database'!D55 | D16: ='0. Database'!E55 | E16: ='0. Database'!F55 | F16: ='0. Database'!G55 | G16: ='0. Database'!H55 | H16: ='0. Database'!I55 | I16: ='0. Database'!J55 | ... S16: ='0. Database'!T55
A17: ORCL | B17: ='0. Database'!C73 | C17: ='0. Database'!D73 | D17: ='0. Database'!E73 | E17: ='0. Database'!F73 | F17: ='0. Database'!G73 | G17: ='0. Database'!H73 | H17: ='0. Database'!I73 | I17: ='0. Database'!J73 | ... S17: ='0. Database'!T73
A19: E. EPS ($)
A20: Company | B20: 2013A | C20: 2014A | D20: 2015A | E20: 2016A | F20: 2017A | G20: 2018A | H20: 2019A | I20: 2020A | J20: 2021A | K20: 2022A | L20: 2023A | M20: 2024A | N20: 2025E | O20: 2026E | P20: 2027E | Q20: 2028E | R20: 2029E | S20: 2030E
A21: MSFT | B21: ='0. Database'!C8 | C21: ='0. Database'!D8 | D21: ='0. Database'!E8 | E21: ='0. Database'!F8 | F21: ='0. Database'!G8 | G21: ='0. Database'!H8 | H21: ='0. Database'!I8 | I21: ='0. Database'!J8 | ... S21: ='0. Database'!T8
A22: AMZN | B22: ='0. Database'!C24 | C22: ='0. Database'!D24 | D22: ='0. Database'!E24 | E22: ='0. Database'!F24 | F22: ='0. Database'!G24 | G22: ='0. Database'!H24 | H22: ='0. Database'!I24 | I22: ='0. Database'!J24 | ... S22: ='0. Database'!T24
A23: GOOGL | B23: ='0. Database'!C39 | C23: ='0. Database'!D39 | D23: ='0. Database'!E39 | E23: ='0. Database'!F39 | F23: ='0. Database'!G39 | G23: ='0. Database'!H39 | H23: ='0. Database'!I39 | I23: ='0. Database'!J39 | ... S23: ='0. Database'!T39
A24: META | B24: ='0. Database'!C56 | C24: ='0. Database'!D56 | D24: ='0. Database'!E56 | E24: ='0. Database'!F56 | F24: ='0. Database'!G56 | G24: ='0. Database'!H56 | H24: ='0. Database'!I56 | I24: ='0. Database'!J56 | ... S24: ='0. Database'!T56
A25: ORCL | B25: ='0. Database'!C74 | C25: ='0. Database'!D74 | D25: ='0. Database'!E74 | E25: ='0. Database'!F74 | F25: ='0. Database'!G74 | G25: ='0. Database'!H74 | H25: ='0. Database'!I74 | I25: ='0. Database'!J74 | ... S25: ='0. Database'!T74
A27: G. Diluted Shares (mm)
A28: Company | B28: 2013A | C28: 2014A | D28: 2015A | E28: 2016A | F28: 2017A | G28: 2018A | H28: 2019A | I28: 2020A | J28: 2021A | K28: 2022A | L28: 2023A | M28: 2024A | N28: 2025E | O28: 2026E | P28: 2027E | Q28: 2028E | R28: 2029E | S28: 2030E
A29: MSFT | B29: ='0. Database'!C9 | C29: ='0. Database'!D9 | D29: ='0. Database'!E9 | E29: ='0. Database'!F9 | F29: ='0. Database'!G9 | G29: ='0. Database'!H9 | H29: ='0. Database'!I9 | I29: ='0. Database'!J9 | ... S29: ='0. Database'!T9
A30: AMZN | B30: ='0. Database'!C25 | C30: ='0. Database'!D25 | D30: ='0. Database'!E25 | E30: ='0. Database'!F25 | F30: ='0. Database'!G25 | G30: ='0. Database'!H25 | H30: ='0. Database'!I25 | I30: ='0. Database'!J25 | ... S30: ='0. Database'!T25
A31: GOOGL | B31: ='0. Database'!C40 | C31: ='0. Database'!D40 | D31: ='0. Database'!E40 | E31: ='0. Database'!F40 | F31: ='0. Database'!G40 | G31: ='0. Database'!H40 | H31: ='0. Database'!I40 | I31: ='0. Database'!J40 | ... S31: ='0. Database'!T40
A32: META | B32: ='0. Database'!C57 | C32: ='0. Database'!D57 | D32: ='0. Database'!E57 | E32: ='0. Database'!F57 | F32: ='0. Database'!G57 | G32: ='0. Database'!H57 | H32: ='0. Database'!I57 | I32: ='0. Database'!J57 | ... S32: ='0. Database'!T57
A33: ORCL | B33: ='0. Database'!C75 | C33: ='0. Database'!D75 | D33: ='0. Database'!E75 | E33: ='0. Database'!F75 | F33: ='0. Database'!G75 | G33: ='0. Database'!H75 | H33: ='0. Database'!I75 | I33: ='0. Database'!J75 | ... S33: ='0. Database'!T75
A35: H. SBC ($mm)
A36: Company | B36: 2013A | C36: 2014A | D36: 2015A | E36: 2016A | F36: 2017A | G36: 2018A | H36: 2019A | I36: 2020A | J36: 2021A | K36: 2022A | L36: 2023A | M36: 2024A | N36: 2025E | O36: 2026E | P36: 2027E | Q36: 2028E | R36: 2029E | S36: 2030E
A37: MSFT | B37: ='0. Database'!C10 | C37: ='0. Database'!D10 | D37: ='0. Database'!E10 | E37: ='0. Database'!F10 | F37: ='0. Database'!G10 | G37: ='0. Database'!H10 | H37: ='0. Database'!I10 | I37: ='0. Database'!J10 | ... S37: ='0. Database'!T10
A38: AMZN | B38: ='0. Database'!C26 | C38: ='0. Database'!D26 | D38: ='0. Database'!E26 | E38: ='0. Database'!F26 | F38: ='0. Database'!G26 | G38: ='0. Database'!H26 | H38: ='0. Database'!I26 | I38: ='0. Database'!J26 | ... S38: ='0. Database'!T26
A39: GOOGL | B39: ='0. Database'!C41 | C39: ='0. Database'!D41 | D39: ='0. Database'!E41 | E39: ='0. Database'!F41 | F39: ='0. Database'!G41 | G39: ='0. Database'!H41 | H39: ='0. Database'!I41 | I39: ='0. Database'!J41 | ... S39: ='0. Database'!T41
A40: META | B40: ='0. Database'!C58 | C40: ='0. Database'!D58 | D40: ='0. Database'!E58 | E40: ='0. Database'!F58 | F40: ='0. Database'!G58 | G40: ='0. Database'!H58 | H40: ='0. Database'!I58 | I40: ='0. Database'!J58 | ... S40: ='0. Database'!T58
A41: ORCL | B41: ='0. Database'!C76 | C41: ='0. Database'!D76 | D41: ='0. Database'!E76 | E41: ='0. Database'!F76 | F41: ='0. Database'!G76 | G41: ='0. Database'!H76 | H41: ='0. Database'!I76 | I41: ='0. Database'!J76 | ... S41: ='0. Database'!T76
A43: (Revenue)
A44: Company | B44: 2013A | C44: 2014A | D44: 2015A | E44: 2016A | F44: 2017A | G44: 2018A | H44: 2019A | I44: 2020A | J44: 2021A | K44: 2022A | L44: 2023A | M44: 2024A | N44: 2025E | O44: 2026E | P44: 2027E | Q44: 2028E | R44: 2029E | S44: 2030E
A45: MSFT | B45: ='0. Database'!C5 | C45: ='0. Database'!D5 | D45: ='0. Database'!E5 | E45: ='0. Database'!F5 | F45: ='0. Database'!G5 | G45: ='0. Database'!H5 | H45: ='0. Database'!I5 | I45: ='0. Database'!J5 | ... S45: ='0. Database'!T5
A46: AMZN | B46: ='0. Database'!C21 | C46: ='0. Database'!D21 | D46: ='0. Database'!E21 | E46: ='0. Database'!F21 | F46: ='0. Database'!G21 | G46: ='0. Database'!H21 | H46: ='0. Database'!I21 | I46: ='0. Database'!J21 | ... S46: ='0. Database'!T21
A47: GOOGL | B47: ='0. Database'!C36 | C47: ='0. Database'!D36 | D47: ='0. Database'!E36 | E47: ='0. Database'!F36 | F47: ='0. Database'!G36 | G47: ='0. Database'!H36 | H47: ='0. Database'!I36 | I47: ='0. Database'!J36 | ... S47: ='0. Database'!T36
A48: META | B48: ='0. Database'!C53 | C48: ='0. Database'!D53 | D48: ='0. Database'!E53 | E48: ='0. Database'!F53 | F48: ='0. Database'!G53 | G48: ='0. Database'!H53 | H48: ='0. Database'!I53 | I48: ='0. Database'!J53 | ... S48: ='0. Database'!T53
A49: ORCL | B49: ='0. Database'!C71 | C49: ='0. Database'!D71 | D49: ='0. Database'!E71 | E49: ='0. Database'!F71 | F49: ='0. Database'!G71 | G49: ='0. Database'!H71 | H49: ='0. Database'!I71 | I49: ='0. Database'!J71 | ... S49: ='0. Database'!T71
A51: B. Operating IncomeMargin %
A52: Company | B52: 2013A | C52: 2014A | D52: 2015A | E52: 2016A | F52: 2017A | G52: 2018A | H52: 2019A | I52: 2020A | J52: 2021A | K52: 2022A | L52: 2023A | M52: 2024A | N52: 2025E | O52: 2026E | P52: 2027E | Q52: 2028E | R52: 2029E | S52: 2030E
A53: MSFT | B53: =IFERROR(B5/B45,"") | C53: =IFERROR(C5/C45,"") | D53: =IFERROR(D5/D45,"") | E53: =IFERROR(E5/E45,"") | F53: =IFERROR(F5/F45,"") | G53: =IFERROR(G5/G45,"") | H53: =IFERROR(H5/H45,"") | I53: =IFERROR(I5/I45,"") | ... S53: =IFERROR(S5/S45,"")
A54: AMZN | B54: =IFERROR(B6/B46,"") | C54: =IFERROR(C6/C46,"") | D54: =IFERROR(D6/D46,"") | E54: =IFERROR(E6/E46,"") | F54: =IFERROR(F6/F46,"") | G54: =IFERROR(G6/G46,"") | H54: =IFERROR(H6/H46,"") | I54: =IFERROR(I6/I46,"") | ... S54: =IFERROR(S6/S46,"")
A55: GOOGL | B55: =IFERROR(B7/B47,"") | C55: =IFERROR(C7/C47,"") | D55: =IFERROR(D7/D47,"") | E55: =IFERROR(E7/E47,"") | F55: =IFERROR(F7/F47,"") | G55: =IFERROR(G7/G47,"") | H55: =IFERROR(H7/H47,"") | I55: =IFERROR(I7/I47,"") | ... S55: =IFERROR(S7/S47,"")
A56: META | B56: =IFERROR(B8/B48,"") | C56: =IFERROR(C8/C48,"") | D56: =IFERROR(D8/D48,"") | E56: =IFERROR(E8/E48,"") | F56: =IFERROR(F8/F48,"") | G56: =IFERROR(G8/G48,"") | H56: =IFERROR(H8/H48,"") | I56: =IFERROR(I8/I48,"") | ... S56: =IFERROR(S8/S48,"")
A57: ORCL | B57: =IFERROR(B9/B49,"") | C57: =IFERROR(C9/C49,"") | D57: =IFERROR(D9/D49,"") | E57: =IFERROR(E9/E49,"") | F57: =IFERROR(F9/F49,"") | G57: =IFERROR(G9/G49,"") | H57: =IFERROR(H9/H49,"") | I57: =IFERROR(I9/I49,"") | ... S57: =IFERROR(S9/S49,"")
A59: D. Net Margin %
A60: Company | B60: 2013A | C60: 2014A | D60: 2015A | E60: 2016A | F60: 2017A | G60: 2018A | H60: 2019A | I60: 2020A | J60: 2021A | K60: 2022A | L60: 2023A | M60: 2024A | N60: 2025E | O60: 2026E | P60: 2027E | Q60: 2028E | R60: 2029E | S60: 2030E
A61: MSFT | B61: =IFERROR(B13/B45,"") | C61: =IFERROR(C13/C45,"") | D61: =IFERROR(D13/D45,"") | E61: =IFERROR(E13/E45,"") | F61: =IFERROR(F13/F45,"") | G61: =IFERROR(G13/G45,"") | H61: =IFERROR(H13/H45,"") | I61: =IFERROR(I13/I45,"") | ... S61: =IFERROR(S13/S45,"")
A62: AMZN | B62: =IFERROR(B14/B46,"") | C62: =IFERROR(C14/C46,"") | D62: =IFERROR(D14/D46,"") | E62: =IFERROR(E14/E46,"") | F62: =IFERROR(F14/F46,"") | G62: =IFERROR(G14/G46,"") | H62: =IFERROR(H14/H46,"") | I62: =IFERROR(I14/I46,"") | ... S62: =IFERROR(S14/S46,"")
A63: GOOGL | B63: =IFERROR(B15/B47,"") | C63: =IFERROR(C15/C47,"") | D63: =IFERROR(D15/D47,"") | E63: =IFERROR(E15/E47,"") | F63: =IFERROR(F15/F47,"") | G63: =IFERROR(G15/G47,"") | H63: =IFERROR(H15/H47,"") | I63: =IFERROR(I15/I47,"") | ... S63: =IFERROR(S15/S47,"")
A64: META | B64: =IFERROR(B16/B48,"") | C64: =IFERROR(C16/C48,"") | D64: =IFERROR(D16/D48,"") | E64: =IFERROR(E16/E48,"") | F64: =IFERROR(F16/F48,"") | G64: =IFERROR(G16/G48,"") | H64: =IFERROR(H16/H48,"") | I64: =IFERROR(I16/I48,"") | ... S64: =IFERROR(S16/S48,"")
A65: ORCL | B65: =IFERROR(B17/B49,"") | C65: =IFERROR(C17/C49,"") | D65: =IFERROR(D17/D49,"") | E65: =IFERROR(E17/E49,"") | F65: =IFERROR(F17/F49,"") | G65: =IFERROR(G17/G49,"") | H65: =IFERROR(H17/H49,"") | I65: =IFERROR(I17/I49,"") | ... S65: =IFERROR(S17/S49,"")
A67: F. EPSYoY %
A68: Company | B68: 2013A | C68: 2014A | D68: 2015A | E68: 2016A | F68: 2017A | G68: 2018A | H68: 2019A | I68: 2020A | J68: 2021A | K68: 2022A | L68: 2023A | M68: 2024A | N68: 2025E | O68: 2026E | P68: 2027E | Q68: 2028E | R68: 2029E | S68: 2030E
A69: MSFT | C69: =IFERROR(C21/B21-1,"") | D69: =IFERROR(D21/C21-1,"") | E69: =IFERROR(E21/D21-1,"") | F69: =IFERROR(F21/E21-1,"") | G69: =IFERROR(G21/F21-1,"") | H69: =IFERROR(H21/G21-1,"") | I69: =IFERROR(I21/H21-1,"") | J69: =IFERROR(J21/I21-1,"") | ... S69: =IFERROR(S21/R21-1,"")
A70: AMZN | C70: =IFERROR(C22/B22-1,"") | D70: =IFERROR(D22/C22-1,"") | E70: =IFERROR(E22/D22-1,"") | F70: =IFERROR(F22/E22-1,"") | G70: =IFERROR(G22/F22-1,"") | H70: =IFERROR(H22/G22-1,"") | I70: =IFERROR(I22/H22-1,"") | J70: =IFERROR(J22/I22-1,"") | ... S70: =IFERROR(S22/R22-1,"")
A71: GOOGL | C71: =IFERROR(C23/B23-1,"") | D71: =IFERROR(D23/C23-1,"") | E71: =IFERROR(E23/D23-1,"") | F71: =IFERROR(F23/E23-1,"") | G71: =IFERROR(G23/F23-1,"") | H71: =IFERROR(H23/G23-1,"") | I71: =IFERROR(I23/H23-1,"") | J71: =IFERROR(J23/I23-1,"") | ... S71: =IFERROR(S23/R23-1,"")
A72: META | C72: =IFERROR(C24/B24-1,"") | D72: =IFERROR(D24/C24-1,"") | E72: =IFERROR(E24/D24-1,"") | F72: =IFERROR(F24/E24-1,"") | G72: =IFERROR(G24/F24-1,"") | H72: =IFERROR(H24/G24-1,"") | I72: =IFERROR(I24/H24-1,"") | J72: =IFERROR(J24/I24-1,"") | ... S72: =IFERROR(S24/R24-1,"")
A73: ORCL | C73: =IFERROR(C25/B25-1,"") | D73: =IFERROR(D25/C25-1,"") | E73: =IFERROR(E25/D25-1,"") | F73: =IFERROR(F25/E25-1,"") | G73: =IFERROR(G25/F25-1,"") | H73: =IFERROR(H25/G25-1,"") | I73: =IFERROR(I25/H25-1,"") | J73: =IFERROR(J25/I25-1,"") | ... S73: =IFERROR(S25/R25-1,"")

Sheet 6. Depreciation Sensitivity
A1: D&AAnalysis: Based on MSFT Actual PP&E Breakdown's Proxy
A3: A. MSFT Actual PP&E/Capex Breakdown (Source: 's Capex sheet — ✅ Hard Data)
A4: MSFT Capex Sheet actual PP&E analysis. Company-level asset breakdown.
A5: Metric (MSFT FY) | B5: FY2020A | C5: FY2021A | D5: FY2022A | E5: FY2023A | F5: FY2024A | G5: FY2025A | H5: FY2026E | I5: FY2027E | J5: FY2028E | K5: FY2029E | L5: FY2030E
A6: IT Equipment Capex ($mm) | B6: 7438 | C6: 9989 | D6: 9381 | E6: 14330 | F6: 18819 | G6: 41432 | H6: 85947 | I6: 144612 | J6: 166321 | K6: 174122 | L6: 176677
A7: Buildings Capex ($mm) | B7: 4377 | C7: 6197 | D7: 7805 | E7: 10301 | F7: 13768 | G7: 36747 | H7: 50201 | I7: 83886 | J7: 100380 | K7: 105090 | L7: 106632
A8: Finance Leases Capex ($mm) | B8: 3330 | C8: 3736 | D8: 3281 | E8: 3150 | F8: 11710 | G8: 21628 | H8: 32878 | I8: 42085 | J8: 37876 | K8: 30301 | L8: 21211
A9: Capex ($mm) | B9: 396 | C9: 2380 | D9: 2525 | E9: 2053 | F9: 3823 | G9: 10020 | H9: 9745 | I9: 16765 | J9: 20059 | K9: 20999 | L9: 21308
A10: Total Capex ($mm) | B10: 19000 | C10: 24200 | D10: 29200 | E10: 31900 | F10: 55700 | G10: 88200 | H10: 145871 | I10: 245263 | J10: 286760 | K10: 300211 | L10: 304616
A11: IT Equipment % of Capex | B11: 0.39 | C11: 0.41 | D11: 0.32 | E11: 0.45 | F11: 0.34 | G11: 0.47 | H11: 0.59 | I11: 0.59 | J11: 0.58 | K11: 0.58 | L11: 0.58
A12: IT Equipment D&A ($mm) | E12: 2231 | F12: 10063 | G12: 14563 | H12: 23911 | I12: 43743 | J12: 68286 | K12: 94877 | L12: 121252
A13: Buildings D&A ($mm) | E13: 680 | F13: 3304 | G13: 5132 | H13: 8149 | I13: 12605 | J13: 18775 | K13: 25426 | L13: 32434
A14: Total D&A ($mm) | B14: 10700 | C14: 9300 | D14: 12600 | E14: 11000 | F14: 15200 | G14: 22000 | H14: 34839 | I14: 59542 | J14: 92995 | K14: 129654 | L14: 165840
A15: IT D&A % of TotalD&A | E15: 0.2 | F15: 0.66 | G15: 0.66 | H15: 0.69 | I15: 0.73 | J15: 0.73 | K15: 0.73 | L15: 0.73
A16: IT EquipmentUseful Life | B16: 6 | C16: 6 | D16: 6 | E16: 6 | F16: 6 | G16: 6 | H16: 6 | I16: 6 | J16: 6 | K16: 6 | L16: 6
A17: BuildingsUseful Life | B17: 15 | C17: 15 | D17: 15 | E17: 15 | F17: 15 | G17: 15 | H17: 15 | I17: 15 | J17: 15 | K17: 15 | L17: 15
A19: 📌 Key Finding: IT Equipment pre-AI 's ~35% jumped to AI 's 59%. IT contributes 66-73% 'sTotalD&A (because IT 6Year vs Buildings 15Year). This is Burry thesis attack surface.
A21: B. IT EquipmentShare ofEstimation: MSFT Hard Data → 4 Proxy (⚠️ Estimate (directionally correct but unverifiable))
A22: Company | B22: IT EquipmentShare of Capex | C22: Estimation Basis (Confidence) | D22: IT Equipment Useful Life | E22: Buildings+ Share ofCapex% | F22: Buildings Useful Life | G22: (/)% | H22: Useful Life
A23: MSFT | B23: 0.59 | C23: ✅ Hard Data: Capex sheet Row 90 = 50.1% gross PP&E; capex share 59% | D23: 6 | E23: 0.36 | F23: 15 | G23: 0.05 | H23: 10
A24: AMZN | B24: 0.42 | C24: ⚠️ : 10-K Equipment $185B //; AWS ~40-45% (Behind the Balance SheetAnalysis) | D24: 5 | E24: 0.35 | F24: 18 | G24: 0.23 | H24: 8
A25: GOOGL | B25: 0.57 | C25: ⚠️ : MBI Deep Dives IT assets ~45% of PP&E; capex share (TPUIT) | D25: 6 | E25: 0.35 | F25: 20 | G25: 0.08 | H25: 10
A26: META | B26: 0.62 | C26: ⚠️ : Company, /; 1.3M GPU; server+networkPP&E (MBI) | D26: 5.5 | E26: 0.33 | F26: 22 | G26: 0.05 | H26: 10
A27: ORCL | B27: 0.5 | C27: ⚠️ : OCI, buildings; But+GPU; ITShare of | D27: 5.5 | E27: 0.4 | F27: 20 | G27: 0.1 | H27: 10
A30: C. 2026E / 2027E Base Data (From Database Sheet)
A31: Company | B31: 2026E Capex ($mm) | C31: 2026E D&A ($mm) | D31: 2026E NI ($mm) | E31: 2026E EPS ($) | F31: Shares (mm) | G31: Tax Rate (Editable) | H31: Depr Base = Capex×wtd life | I31: 2027E Capex ($mm) | J31: 2027E D&A ($mm) | K31: 2027E NI ($mm) | L31: 2027E EPS ($) | M31: 2027E Shares (mm) | N31: 2027E Base = D&A×wtdLife
A32: MSFT | B32: ='0. Database'!P12 | C32: ='0. Database'!P11 | D32: ='0. Database'!P7 | E32: ='0. Database'!P8 | F32: ='0. Database'!P9 | G32: 0.18 | H32: =$C$32*($B$23*$D$23+$E$23*$F$23+$G$23*$H$23) | I32: ='0. Database'!Q12 | J32: ='0. Database'!Q11 | K32: ='0. Database'!Q7 | L32: ='0. Database'!Q8
A33: AMZN | B33: ='0. Database'!P28 | C33: ='0. Database'!P27 | D33: ='0. Database'!P23 | E33: ='0. Database'!P24 | F33: ='0. Database'!P25 | G33: 0.2 | H33: =$C$33*($B$24*$D$24+$E$24*$F$24+$G$24*$H$24) | I33: ='0. Database'!Q28 | J33: ='0. Database'!Q27 | K33: ='0. Database'!Q23 | L33: ='0. Database'!Q24
A34: GOOGL | B34: ='0. Database'!P43 | C34: ='0. Database'!P42 | D34: ='0. Database'!P38 | E34: ='0. Database'!P39 | F34: ='0. Database'!P40 | G34: 0.16 | H34: =$C$34*($B$25*$D$25+$E$25*$F$25+$G$25*$H$25) | I34: ='0. Database'!Q43 | J34: ='0. Database'!Q42 | K34: ='0. Database'!Q38 | L34: ='0. Database'!Q39
A35: META | B35: ='0. Database'!P60 | C35: ='0. Database'!P59 | D35: ='0. Database'!P55 | E35: ='0. Database'!P56 | F35: ='0. Database'!P57 | G35: 0.13 | H35: =$C$35*($B$26*$D$26+$E$26*$F$26+$G$26*$H$26) | I35: ='0. Database'!Q60 | J35: ='0. Database'!Q59 | K35: ='0. Database'!Q55 | L35: ='0. Database'!Q56
A36: ORCL | B36: ='0. Database'!P78 | C36: ='0. Database'!P77 | D36: ='0. Database'!P73 | E36: ='0. Database'!P74 | F36: ='0. Database'!P75 | G36: 0.2 | H36: =$C$36*($B$27*$D$27+$E$27*$F$27+$G$27*$H$27) | I36: ='0. Database'!Q78 | J36: ='0. Database'!Q77 | K36: ='0. Database'!Q73 | L36: ='0. Database'!Q74
A39: D. Core Sensitivity: Compress Only IT Equipment (Buildings/) — Straight-Line
A40: Logic: D&A = ITD&A + Buildings + . ITBurry.
A41: IT Equipment = 6 Year (Buildings/)
A42: Company | B42: ITD&A ($mm) | C42: BuildingsD&A (,$mm) | D42: D&A (,$mm) | E42: New Total D&A ($mm) | F42: Current D&A ($mm) | G42: ΔD&A ($mm) | H42: Δ ($mm) | I42: Adj NI ($mm) | J42: Adj EPS ($) | K42: EPS Change%
A43: MSFT | B43: =$H$32*$B$23/6 | C43: =$H$32*$E$23/$F$23 | D43: =$H$32*$G$23/$H$23 | E43: =$B$43+$C$43+$D$43 | F43: =$C$32 | G43: =$E$43-$C$32 | H43: =$G$43*(1-$G$32) | I43: =$D$32-$H$43 | J43: =$I$43/$F$32 | K43: =IFERROR($J$43/$E$32-1,"")
A44: AMZN | B44: =$H$33*$B$24/6 | C44: =$H$33*$E$24/$F$24 | D44: =$H$33*$G$24/$H$24 | E44: =$B$44+$C$44+$D$44 | F44: =$C$33 | G44: =$E$44-$C$33 | H44: =$G$44*(1-$G$33) | I44: =$D$33-$H$44 | J44: =$I$44/$F$33 | K44: =IFERROR($J$44/$E$33-1,"")
A45: GOOGL | B45: =$H$34*$B$25/6 | C45: =$H$34*$E$25/$F$25 | D45: =$H$34*$G$25/$H$25 | E45: =$B$45+$C$45+$D$45 | F45: =$C$34 | G45: =$E$45-$C$34 | H45: =$G$45*(1-$G$34) | I45: =$D$34-$H$45 | J45: =$I$45/$F$34 | K45: =IFERROR($J$45/$E$34-1,"")
A46: META | B46: =$H$35*$B$26/6 | C46: =$H$35*$E$26/$F$26 | D46: =$H$35*$G$26/$H$26 | E46: =$B$46+$C$46+$D$46 | F46: =$C$35 | G46: =$E$46-$C$35 | H46: =$G$46*(1-$G$35) | I46: =$D$35-$H$46 | J46: =$I$46/$F$35 | K46: =IFERROR($J$46/$E$35-1,"")
A47: ORCL | B47: =$H$36*$B$27/6 | C47: =$H$36*$E$27/$F$27 | D47: =$H$36*$G$27/$H$27 | E47: =$B$47+$C$47+$D$47 | F47: =$C$36 | G47: =$E$47-$C$36 | H47: =$G$47*(1-$G$36) | I47: =$D$36-$H$47 | J47: =$I$47/$F$36 | K47: =IFERROR($J$47/$E$36-1,"")
A49: IT Equipment = 5 Year (Buildings/)
A50: Company | B50: ITD&A ($mm) | C50: BuildingsD&A (,$mm) | D50: D&A (,$mm) | E50: New Total D&A ($mm) | F50: Current D&A ($mm) | G50: ΔD&A ($mm) | H50: Δ ($mm) | I50: Adj NI ($mm) | J50: Adj EPS ($) | K50: EPS Change%
A51: MSFT | B51: =$H$32*$B$23/5 | C51: =$H$32*$E$23/$F$23 | D51: =$H$32*$G$23/$H$23 | E51: =$B$51+$C$51+$D$51 | F51: =$C$32 | G51: =$E$51-$C$32 | H51: =$G$51*(1-$G$32) | I51: =$D$32-$H$51 | J51: =$I$51/$F$32 | K51: =IFERROR($J$51/$E$32-1,"")
A52: AMZN | B52: =$H$33*$B$24/5 | C52: =$H$33*$E$24/$F$24 | D52: =$H$33*$G$24/$H$24 | E52: =$B$52+$C$52+$D$52 | F52: =$C$33 | G52: =$E$52-$C$33 | H52: =$G$52*(1-$G$33) | I52: =$D$33-$H$52 | J52: =$I$52/$F$33 | K52: =IFERROR($J$52/$E$33-1,"")
A53: GOOGL | B53: =$H$34*$B$25/5 | C53: =$H$34*$E$25/$F$25 | D53: =$H$34*$G$25/$H$25 | E53: =$B$53+$C$53+$D$53 | F53: =$C$34 | G53: =$E$53-$C$34 | H53: =$G$53*(1-$G$34) | I53: =$D$34-$H$53 | J53: =$I$53/$F$34 | K53: =IFERROR($J$53/$E$34-1,"")
A54: META | B54: =$H$35*$B$26/5 | C54: =$H$35*$E$26/$F$26 | D54: =$H$35*$G$26/$H$26 | E54: =$B$54+$C$54+$D$54 | F54: =$C$35 | G54: =$E$54-$C$35 | H54: =$G$54*(1-$G$35) | I54: =$D$35-$H$54 | J54: =$I$54/$F$35 | K54: =IFERROR($J$54/$E$35-1,"")
A55: ORCL | B55: =$H$36*$B$27/5 | C55: =$H$36*$E$27/$F$27 | D55: =$H$36*$G$27/$H$27 | E55: =$B$55+$C$55+$D$55 | F55: =$C$36 | G55: =$E$55-$C$36 | H55: =$G$55*(1-$G$36) | I55: =$D$36-$H$55 | J55: =$I$55/$F$36 | K55: =IFERROR($J$55/$E$36-1,"")
A57: IT Equipment = 4 Year (Buildings/)
A58: Company | B58: ITD&A ($mm) | C58: BuildingsD&A (,$mm) | D58: D&A (,$mm) | E58: New Total D&A ($mm) | F58: Current D&A ($mm) | G58: ΔD&A ($mm) | H58: Δ ($mm) | I58: Adj NI ($mm) | J58: Adj EPS ($) | K58: EPS Change%
A59: MSFT | B59: =$H$32*$B$23/4 | C59: =$H$32*$E$23/$F$23 | D59: =$H$32*$G$23/$H$23 | E59: =$B$59+$C$59+$D$59 | F59: =$C$32 | G59: =$E$59-$C$32 | H59: =$G$59*(1-$G$32) | I59: =$D$32-$H$59 | J59: =$I$59/$F$32 | K59: =IFERROR($J$59/$E$32-1,"")
A60: AMZN | B60: =$H$33*$B$24/4 | C60: =$H$33*$E$24/$F$24 | D60: =$H$33*$G$24/$H$24 | E60: =$B$60+$C$60+$D$60 | F60: =$C$33 | G60: =$E$60-$C$33 | H60: =$G$60*(1-$G$33) | I60: =$D$33-$H$60 | J60: =$I$60/$F$33 | K60: =IFERROR($J$60/$E$33-1,"")
A61: GOOGL | B61: =$H$34*$B$25/4 | C61: =$H$34*$E$25/$F$25 | D61: =$H$34*$G$25/$H$25 | E61: =$B$61+$C$61+$D$61 | F61: =$C$34 | G61: =$E$61-$C$34 | H61: =$G$61*(1-$G$34) | I61: =$D$34-$H$61 | J61: =$I$61/$F$34 | K61: =IFERROR($J$61/$E$34-1,"")
A62: META | B62: =$H$35*$B$26/4 | C62: =$H$35*$E$26/$F$26 | D62: =$H$35*$G$26/$H$26 | E62: =$B$62+$C$62+$D$62 | F62: =$C$35 | G62: =$E$62-$C$35 | H62: =$G$62*(1-$G$35) | I62: =$D$35-$H$62 | J62: =$I$62/$F$35 | K62: =IFERROR($J$62/$E$35-1,"")
A63: ORCL | B63: =$H$36*$B$27/4 | C63: =$H$36*$E$27/$F$27 | D63: =$H$36*$G$27/$H$27 | E63: =$B$63+$C$63+$D$63 | F63: =$C$36 | G63: =$E$63-$C$36 | H63: =$G$63*(1-$G$36) | I63: =$D$36-$H$63 | J63: =$I$63/$F$36 | K63: =IFERROR($J$63/$E$36-1,"")
A65: IT Equipment = 3 Year (Buildings/)
A66: Company | B66: ITD&A ($mm) | C66: BuildingsD&A (,$mm) | D66: D&A (,$mm) | E66: New Total D&A ($mm) | F66: Current D&A ($mm) | G66: ΔD&A ($mm) | H66: Δ ($mm) | I66: Adj NI ($mm) | J66: Adj EPS ($) | K66: EPS Change%
A67: MSFT | B67: =$H$32*$B$23/3 | C67: =$H$32*$E$23/$F$23 | D67: =$H$32*$G$23/$H$23 | E67: =$B$67+$C$67+$D$67 | F67: =$C$32 | G67: =$E$67-$C$32 | H67: =$G$67*(1-$G$32) | I67: =$D$32-$H$67 | J67: =$I$67/$F$32 | K67: =IFERROR($J$67/$E$32-1,"")
A68: AMZN | B68: =$H$33*$B$24/3 | C68: =$H$33*$E$24/$F$24 | D68: =$H$33*$G$24/$H$24 | E68: =$B$68+$C$68+$D$68 | F68: =$C$33 | G68: =$E$68-$C$33 | H68: =$G$68*(1-$G$33) | I68: =$D$33-$H$68 | J68: =$I$68/$F$33 | K68: =IFERROR($J$68/$E$33-1,"")
A69: GOOGL | B69: =$H$34*$B$25/3 | C69: =$H$34*$E$25/$F$25 | D69: =$H$34*$G$25/$H$25 | E69: =$B$69+$C$69+$D$69 | F69: =$C$34 | G69: =$E$69-$C$34 | H69: =$G$69*(1-$G$34) | I69: =$D$34-$H$69 | J69: =$I$69/$F$34 | K69: =IFERROR($J$69/$E$34-1,"")
A70: META | B70: =$H$35*$B$26/3 | C70: =$H$35*$E$26/$F$26 | D70: =$H$35*$G$26/$H$26 | E70: =$B$70+$C$70+$D$70 | F70: =$C$35 | G70: =$E$70-$C$35 | H70: =$G$70*(1-$G$35) | I70: =$D$35-$H$70 | J70: =$I$70/$F$35 | K70: =IFERROR($J$70/$E$35-1,"")
A71: ORCL | B71: =$H$36*$B$27/3 | C71: =$H$36*$E$27/$F$27 | D71: =$H$36*$G$27/$H$27 | E71: =$B$71+$C$71+$D$71 | F71: =$C$36 | G71: =$E$71-$C$36 | H71: =$G$71*(1-$G$36) | I71: =$D$36-$H$71 | J71: =$I$71/$F$36 | K71: =IFERROR($J$71/$E$36-1,"")
A73: IT Equipment = 2 Year (Buildings/)
A74: Company | B74: ITD&A ($mm) | C74: BuildingsD&A (,$mm) | D74: D&A (,$mm) | E74: New Total D&A ($mm) | F74: Current D&A ($mm) | G74: ΔD&A ($mm) | H74: Δ ($mm) | I74: Adj NI ($mm) | J74: Adj EPS ($) | K74: EPS Change%
A75: MSFT | B75: =$H$32*$B$23/2 | C75: =$H$32*$E$23/$F$23 | D75: =$H$32*$G$23/$H$23 | E75: =$B$75+$C$75+$D$75 | F75: =$C$32 | G75: =$E$75-$C$32 | H75: =$G$75*(1-$G$32) | I75: =$D$32-$H$75 | J75: =$I$75/$F$32 | K75: =IFERROR($J$75/$E$32-1,"")
A76: AMZN | B76: =$H$33*$B$24/2 | C76: =$H$33*$E$24/$F$24 | D76: =$H$33*$G$24/$H$24 | E76: =$B$76+$C$76+$D$76 | F76: =$C$33 | G76: =$E$76-$C$33 | H76: =$G$76*(1-$G$33) | I76: =$D$33-$H$76 | J76: =$I$76/$F$33 | K76: =IFERROR($J$76/$E$33-1,"")
A77: GOOGL | B77: =$H$34*$B$25/2 | C77: =$H$34*$E$25/$F$25 | D77: =$H$34*$G$25/$H$25 | E77: =$B$77+$C$77+$D$77 | F77: =$C$34 | G77: =$E$77-$C$34 | H77: =$G$77*(1-$G$34) | I77: =$D$34-$H$77 | J77: =$I$77/$F$34 | K77: =IFERROR($J$77/$E$34-1,"")
A78: META | B78: =$H$35*$B$26/2 | C78: =$H$35*$E$26/$F$26 | D78: =$H$35*$G$26/$H$26 | E78: =$B$78+$C$78+$D$78 | F78: =$C$35 | G78: =$E$78-$C$35 | H78: =$G$78*(1-$G$35) | I78: =$D$35-$H$78 | J78: =$I$78/$F$35 | K78: =IFERROR($J$78/$E$35-1,"")
A79: ORCL | B79: =$H$36*$B$27/2 | C79: =$H$36*$E$27/$F$27 | D79: =$H$36*$G$27/$H$27 | E79: =$B$79+$C$79+$D$79 | F79: =$C$36 | G79: =$E$79-$C$36 | H79: =$G$79*(1-$G$36) | I79: =$D$36-$H$79 | J79: =$I$79/$F$36 | K79: =IFERROR($J$79/$E$36-1,"")
A82: E. Summary: 2026E EPS (%) — Compress OnlyIT Equipment vs Burry'sFull Compression Comparison
A83: ★ Adjusted Method = IT Equipment, Buildings/. BurryFull Compression = D&A ().
A84: Company | B84: ITShare of (Source) | C84: Current | D84: ★Adjusted Method IT→4yr EPS Δ% | E84: ★Adjusted Method IT→3yr EPS Δ% | F84: Burry →4yr EPS Δ% | G84: Burry →3yr EPS Δ% | H84: Adjusted Method (vs) | I84: Conclusion | J84: 2027E IT→4yr EPS Δ% | K84: 2027E IT→3yr EPS Δ%
A85: MSFT | B85: =$B$23 | C85: =$B$23*$D$23+$E$23*$F$23+$G$23*$H$23 | D85: =IFERROR(($D$32-($H$32*$B$23/4+$H$32*$E$23/$F$23+$H$32*$G$23/$H$23-$C$32)*(1-$G$32))/$F$32/$E$32-1,"") | E85: =IFERROR(($D$32-($H$32*$B$23/3+$H$32*$E$23/$F$23+$H$32*$G$23/$H$23-$C$32)*(1-$G$32))/$F$32/$E$32-1,"") | F85: =IFERROR(($D$32-($C$32*($B$23*$D$23+$E$23*$F$23+$G$23*$H$23)/4-$C$32)*(1-$G$32))/$F$32/$E$32-1,"") | G85: =IFERROR(($D$32-($C$32*($B$23*$D$23+$E$23*$F$23+$G$23*$H$23)/3-$C$32)*(1-$G$32))/$F$32/$E$32-1,"") | H85: =IFERROR(E85/G85,"") | I85: . ITShare ofHard Data. 4.9yr.
A86: AMZN | B86: =$B$24 | C86: =$B$24*$D$24+$E$24*$F$24+$G$24*$H$24 | D86: =IFERROR(($D$33-($H$33*$B$24/4+$H$33*$E$24/$F$24+$H$33*$G$24/$H$24-$C$33)*(1-$G$33))/$F$33/$E$33-1,"") | E86: =IFERROR(($D$33-($H$33*$B$24/3+$H$33*$E$24/$F$24+$H$33*$G$24/$H$24-$C$33)*(1-$G$33))/$F$33/$E$33-1,"") | F86: =IFERROR(($D$33-($C$33*($B$24*$D$24+$E$24*$F$24+$G$24*$H$24)/4-$C$33)*(1-$G$33))/$F$33/$E$33-1,"") | G86: =IFERROR(($D$33-($C$33*($B$24*$D$24+$E$24*$F$24+$G$24*$H$24)/3-$C$33)*(1-$G$33))/$F$33/$E$33-1,"") | H86: =IFERROR(E86/G86,"") | I86: . ButD&A, .
A87: GOOGL | B87: =$B$25 | C87: =$B$25*$D$25+$E$25*$F$25+$G$25*$H$25 | D87: =IFERROR(($D$34-($H$34*$B$25/4+$H$34*$E$25/$F$25+$H$34*$G$25/$H$25-$C$34)*(1-$G$34))/$F$34/$E$34-1,"") | E87: =IFERROR(($D$34-($H$34*$B$25/3+$H$34*$E$25/$F$25+$H$34*$G$25/$H$25-$C$34)*(1-$G$34))/$F$34/$E$34-1,"") | F87: =IFERROR(($D$34-($C$34*($B$25*$D$25+$E$25*$F$25+$G$25*$H$25)/4-$C$34)*(1-$G$34))/$F$34/$E$34-1,"") | G87: =IFERROR(($D$34-($C$34*($B$25*$D$25+$E$25*$F$25+$G$25*$H$25)/3-$C$34)*(1-$G$34))/$F$34/$E$34-1,"") | H87: =IFERROR(E87/G87,"") | I87: TPU. ITShare of.
A88: META | B88: =$B$26 | C88: =$B$26*$D$26+$E$26*$F$26+$G$26*$H$26 | D88: =IFERROR(($D$35-($H$35*$B$26/4+$H$35*$E$26/$F$26+$H$35*$G$26/$H$26-$C$35)*(1-$G$35))/$F$35/$E$35-1,"") | E88: =IFERROR(($D$35-($H$35*$B$26/3+$H$35*$E$26/$F$26+$H$35*$G$26/$H$26-$C$35)*(1-$G$35))/$F$35/$E$35-1,"") | F88: =IFERROR(($D$35-($C$35*($B$26*$D$26+$E$26*$F$26+$G$26*$H$26)/4-$C$35)*(1-$G$35))/$F$35/$E$35-1,"") | G88: =IFERROR(($D$35-($C$35*($B$26*$D$26+$E$26*$F$26+$G$26*$H$26)/3-$C$35)*(1-$G$35))/$F$35/$E$35-1,"") | H88: =IFERROR(E88/G88,"") | I88: GPU'sDCCompany. .
A89: ORCL | B89: =$B$27 | C89: =$B$27*$D$27+$E$27*$F$27+$G$27*$H$27 | D89: =IFERROR(($D$36-($H$36*$B$27/4+$H$36*$E$27/$F$27+$H$36*$G$27/$H$27-$C$36)*(1-$G$36))/$F$36/$E$36-1,"") | E89: =IFERROR(($D$36-($H$36*$B$27/3+$H$36*$E$27/$F$27+$H$36*$G$27/$H$27-$C$36)*(1-$G$36))/$F$36/$E$36-1,"") | F89: =IFERROR(($D$36-($C$36*($B$27*$D$27+$E$27*$F$27+$G$27*$H$27)/4-$C$36)*(1-$G$36))/$F$36/$E$36-1,"") | G89: =IFERROR(($D$36-($C$36*($B$27*$D$27+$E$27*$F$27+$G$27*$H$27)/3-$C$36)*(1-$G$36))/$F$36/$E$36-1,"") | H89: =IFERROR(E89/G89,"") | I89: OCI, building. ButNI, .
A92: Confidence
A93: ✅ MSFT IT EquipmentShare of (59% capex, 44.5% PP&E): From your model Capex sheet Row 74/90/114 — Fully verifiable
A94: ✅ MSFT Useful Life (IT 6yr, Buildings 15yr): Capex sheet Row 121-125 — Fully verifiable
A95: ✅ 5's D&A, NI, EPS, Shares, Capex: — Fully verifiable
A96: ⚠️ AMZN/GOOGL/META/ORCL IT EquipmentShare of: Based on MSFT proxy + Industry Reports (MBI, Epoch AI, Behind the Balance Sheet) — Directionally correct but estimate
A97: ⚠️ IT Equipment 'AI GPU' Share of: Company's 10-K does not disclose this — Unknowable
A98: ❌ DDB : GAAPno hyperscaler useshyperscalerDDBD&AIT Equipment — Stress Test, Does not represent realistic possibility
A101: H. 2027E D&A (, IT Equipment, Buildings)
A102: 2027E D&A(), D&A. 'sITShare of.
A103: Company | B103: 2027E D&A | C103: 2027E NI | D103: 2027E EPS | E103: Shares | F103: Tax | G103: ITShare of | H103: BuildingsShare of | I103: Share of | J103: ★IT→4yr EPS Δ% | K103: ★IT→3yr EPS Δ%
A104: MSFT | B104: ='0. Database'!Q11 | C104: ='0. Database'!Q7 | D104: ='0. Database'!Q8 | F104: 0.18 | G104: 0.59 | H104: 0.36 | I104: 0.05 | J104: =IFERROR(($C$104-(($B$104*($G$104*6+$H$104*15+$I$104*10))*$G$104/4+($B$104*($G$104*6+$H$104*15+$I$104*10))*$H$104/15+($B$104*($G$104*6+$H$104*15+$I$104*10))*$I$104/10-$B$104)*(1-$F$104))/$E$104/$D$104-1,"") | K104: =IFERROR(($C$104-(($B$104*($G$104*6+$H$104*15+$I$104*10))*$G$104/3+($B$104*($G$104*6+$H$104*15+$I$104*10))*$H$104/15+($B$104*($G$104*6+$H$104*15+$I$104*10))*$I$104/10-$B$104)*(1-$F$104))/$E$104/$D$104-1,"")
A105: AMZN | B105: ='0. Database'!Q27 | C105: ='0. Database'!Q23 | D105: ='0. Database'!Q24 | F105: 0.2 | G105: 0.42 | H105: 0.35 | I105: 0.23 | J105: =IFERROR(($C$105-(($B$105*($G$105*5.5+$H$105*18+$I$105*8))*$G$105/4+($B$105*($G$105*5.5+$H$105*18+$I$105*8))*$H$105/18+($B$105*($G$105*5.5+$H$105*18+$I$105*8))*$I$105/8-$B$105)*(1-$F$105))/$E$105/$D$105-1,"") | K105: =IFERROR(($C$105-(($B$105*($G$105*5.5+$H$105*18+$I$105*8))*$G$105/3+($B$105*($G$105*5.5+$H$105*18+$I$105*8))*$H$105/18+($B$105*($G$105*5.5+$H$105*18+$I$105*8))*$I$105/8-$B$105)*(1-$F$105))/$E$105/$D$105-1,"")
A106: GOOGL | B106: ='0. Database'!Q42 | C106: ='0. Database'!Q38 | D106: ='0. Database'!Q39 | F106: 0.16 | G106: 0.57 | H106: 0.35 | I106: 0.08 | J106: =IFERROR(($C$106-(($B$106*($G$106*6+$H$106*20+$I$106*10))*$G$106/4+($B$106*($G$106*6+$H$106*20+$I$106*10))*$H$106/20+($B$106*($G$106*6+$H$106*20+$I$106*10))*$I$106/10-$B$106)*(1-$F$106))/$E$106/$D$106-1,"") | K106: =IFERROR(($C$106-(($B$106*($G$106*6+$H$106*20+$I$106*10))*$G$106/3+($B$106*($G$106*6+$H$106*20+$I$106*10))*$H$106/20+($B$106*($G$106*6+$H$106*20+$I$106*10))*$I$106/10-$B$106)*(1-$F$106))/$E$106/$D$106-1,"")
A107: META | B107: ='0. Database'!Q59 | C107: ='0. Database'!Q55 | D107: ='0. Database'!Q56 | F107: 0.13 | G107: 0.62 | H107: 0.33 | I107: 0.05 | J107: =IFERROR(($C$107-(($B$107*($G$107*5.5+$H$107*22+$I$107*10))*$G$107/4+($B$107*($G$107*5.5+$H$107*22+$I$107*10))*$H$107/22+($B$107*($G$107*5.5+$H$107*22+$I$107*10))*$I$107/10-$B$107)*(1-$F$107))/$E$107/$D$107-1,"") | K107: =IFERROR(($C$107-(($B$107*($G$107*5.5+$H$107*22+$I$107*10))*$G$107/3+($B$107*($G$107*5.5+$H$107*22+$I$107*10))*$H$107/22+($B$107*($G$107*5.5+$H$107*22+$I$107*10))*$I$107/10-$B$107)*(1-$F$107))/$E$107/$D$107-1,"")
A108: ORCL | B108: ='0. Database'!Q77 | C108: ='0. Database'!Q73 | D108: ='0. Database'!Q74 | F108: 0.2 | G108: 0.5 | H108: 0.4 | I108: 0.1 | J108: =IFERROR(($C$108-(($B$108*($G$108*5.5+$H$108*20+$I$108*10))*$G$108/4+($B$108*($G$108*5.5+$H$108*20+$I$108*10))*$H$108/20+($B$108*($G$108*5.5+$H$108*20+$I$108*10))*$I$108/10-$B$108)*(1-$F$108))/$E$108/$D$108-1,"") | K108: =IFERROR(($C$108-(($B$108*($G$108*5.5+$H$108*20+$I$108*10))*$G$108/3+($B$108*($G$108*5.5+$H$108*20+$I$108*10))*$H$108/20+($B$108*($G$108*5.5+$H$108*20+$I$108*10))*$I$108/10-$B$108)*(1-$F$108))/$E$108/$D$108-1,"")

Sheet 7. SP500 AI EPS Split
A1: S&P 500: AI vs Non-AI EPSBreakdown + Dual P/E Valuation
A3: A. S&P 500 Actual Operating EPS + sell-side Cash Spending Framework
A4: EPS: FactSet actual (2018-2024), sell-side/consensus estimates (2025+). Capex/Buybacks: sell-side data (May 7 2026 report). Yellow = editable.
A5: Metric | B5: 2018A | C5: 2019A | D5: 2020A | E5: 2021A | F5: 2022A | G5: 2023A | H5: 2024A | I5: 2025A | J5: 2026E | K5: 2027E | L5: 2028E | M5: 2029E | N5: 2030E
A6: S&P 500 Operating EPS ($) | B6: 162 | C6: 164 | D6: 140 | E6: 209 | F6: 219 | G6: 221 | H6: 246 | I6: 275 | J6: 309 | K6: 342 | L6: 370 | M6: 396 | N6: 420
A7: S&P 500Capex ($B) — sell-side data | B7: 644 | C7: 697 | D7: 591 | E7: 739 | F7: 892 | G7: 958 | H7: 1077 | I7: 1296 | J7: 1724 | K7: 2103 | L7: 2400 | M7: 2600 | N7: 2750
A8: AICapex ($B) — 5 cos | B8: 50 | C8: 55 | D8: 60 | E8: 86 | F8: 158 | G8: 154 | H8: 237 | I8: 412 | J8: 755 | K8: 892 | L8: 950 | M8: 980 | N8: 1000
A9: S&P 500 Buybacks ($B) — sell-side data | B9: 770 | C9: 729 | D9: 520 | E9: 919 | F9: 950 | G9: 823 | H9: 982 | I9: 1066 | J9: 1098 | K9: 1153 | L9: 1200 | M9: 1250 | N9: 1300
A10: Share ofCapex% | B10: 50 | C10: 55 | D10: 60 | E10: 86 | F10: 158 | G10: 154 | H10: 237 | I10: 412 | J10: 755 | K10: 892 | L10: 950 | M10: 980 | N10: 1000
A12: B. AI-Driven EPS Estimation: Hyperscaler Capex → Supply Chain Profit → S&P 500 EPS
A13: Logic: Hyperscaler capex = revenue for NVDA/AVGO/MU/ANET/etc. Their net margin × capex = AI-driven NI. Divide by S&P 500 share count ≈ AI EPS.
A14: Metric | B14: 2018A | C14: 2019A | D14: 2020A | E14: 2021A | F14: 2022A | G14: 2023A | H14: 2024A | I14: 2025A | J14: 2026E | K14: 2027E | L14: 2028E | M14: 2029E | N14: 2030E
A15: % of Hyp Capex → S&P 500 co revenue (editable) | B15: 0.55 | C15: 0.55 | D15: 0.55 | E15: 0.55 | F15: 0.55 | G15: 0.55 | H15: 0.55 | I15: 0.6 | J15: 0.65 | K15: 0.65 | L15: 0.65 | M15: 0.63 | N15: 0.6
A16: Wtd avg net margin of AI supply chain (editable) | B16: 0.2 | C16: 0.2 | D16: 0.2 | E16: 0.22 | F16: 0.25 | G16: 0.3 | H16: 0.35 | I16: 0.4 | J16: 0.45 | K16: 0.42 | L16: 0.38 | M16: 0.35 | N16: 0.33
A17: AI Revenue to S&P 500 cos ($B) | B17: =B8*B15 | C17: =C8*C15 | D17: =D8*D15 | E17: =E8*E15 | F17: =F8*F15 | G17: =G8*G15 | H17: =H8*H15 | I17: =I8*I15 | ... N17: =N8*N15
A18: AI Net Income to S&P 500 cos ($B) | B18: =B17*B16 | C18: =C17*C16 | D18: =D17*D16 | E18: =E17*E16 | F18: =F17*F16 | G18: =G17*G16 | H18: =H17*H16 | I18: =I17*I16 | ... N18: =N17*N16
A19: S&P 500TotalNet Income ($B) ≈ EPS × 7.7B shares | B19: =B6*7.7 | C19: =C6*7.7 | D19: =D6*7.7 | E19: =E6*7.7 | F19: =F6*7.7 | G19: =G6*7.7 | H19: =H6*7.7 | I19: =I6*7.7 | ... N19: =N6*7.7
A20: AI-Driven EPS ($) = AI NI / 7.7B shares | B20: =B18/7.7 | C20: =C18/7.7 | D20: =D18/7.7 | E20: =E18/7.7 | F20: =F18/7.7 | G20: =G18/7.7 | H20: =H18/7.7 | I20: =I18/7.7 | ... N20: =N18/7.7
A21: Non-AI EPS ($) = Total - AI | B21: =B6-B20 | C21: =C6-C20 | D21: =D6-D20 | E21: =E6-E20 | F21: =F6-F20 | G21: =G6-G20 | H21: =H6-H20 | I21: =I6-I20 | ... N21: =N6-N20
A22: AI % of Total EPS | B22: =IFERROR(B20/B6,"") | C22: =IFERROR(C20/C6,"") | D22: =IFERROR(D20/D6,"") | E22: =IFERROR(E20/E6,"") | F22: =IFERROR(F20/F6,"") | G22: =IFERROR(G20/G6,"") | H22: =IFERROR(H20/H6,"") | I22: =IFERROR(I20/I6,"") | ... N22: =IFERROR(N20/N6,"")
A23: AI EPS YoY % | C23: =IFERROR(C20/B20-1,"") | D23: =IFERROR(D20/C20-1,"") | E23: =IFERROR(E20/D20-1,"") | F23: =IFERROR(F20/E20-1,"") | G23: =IFERROR(G20/F20-1,"") | H23: =IFERROR(H20/G20-1,"") | I23: =IFERROR(I20/H20-1,"") | J23: =IFERROR(J20/I20-1,"") | ... N23: =IFERROR(N20/M20-1,"")
A25: C. Dual P/E Valuation — Separate Multiples for AI vs Non-AI EPS
A26: AI P/E (editable) — hist avg ~18x | B26: 18
A27: AI P/E (editable) — NVDA ~30-40x fwd | B27: 35
A29: Valuation Component | B29: 2024A | C29: 2025A | D29: 2026E | E29: 2027E | F29: 2028E | G29: 2029E | H29: 2030E
A30: AI = Non-AI EPS × P/E | B30: =H21*$B$26 | C30: =I21*$B$26 | D30: =J21*$B$26 | E30: =K21*$B$26 | F30: =L21*$B$26 | G30: =M21*$B$26 | H30: =N21*$B$26
A31: AI = AI EPS × P/E | B31: =H20*$B$27 | C31: =I20*$B$27 | D31: =J20*$B$27 | E31: =K20*$B$27 | F31: =L20*$B$27 | G31: =M20*$B$27 | H31: =N20*$B$27
A32: Implied S&P 500 Level | B32: =B30+B31 | C32: =C30+C31 | D32: =D30+D31 | E32: =E30+E31 | F32: =F30+F31 | G32: =G30+G31 | H32: =H30+H31
A33: Blended P/E (implied) | B33: =IFERROR(B32/H6,"") | C33: =IFERROR(C32/I6,"") | D33: =IFERROR(D32/J6,"") | E33: =IFERROR(E32/K6,"") | F33: =IFERROR(F32/L6,"") | G33: =IFERROR(G32/M6,"") | H33: =IFERROR(H32/N6,"")
A35: D. Scenario Grid: 2026E Implied S&P 500 Under Different P/E Assumptions
A36: Reads: 'If Non-AI trades at Xpe and AI trades at Ype, 2026E S&P 500 = Z'. Uses AI/Non-AI EPS from Section B. Change yellow cells above to update.
A37: AI P/E ↓ AI P/E → | B37: 22x | C37: 20x | D37: 18x | E37: 16x | F37: 14x
A38: 40x | B38: =J21*22+J20*40 | C38: =J21*20+J20*40 | D38: =J21*18+J20*40 | E38: =J21*16+J20*40 | F38: =J21*14+J20*40
A39: 35x | B39: =J21*22+J20*35 | C39: =J21*20+J20*35 | D39: =J21*18+J20*35 | E39: =J21*16+J20*35 | F39: =J21*14+J20*35
A40: 30x | B40: =J21*22+J20*30 | C40: =J21*20+J20*30 | D40: =J21*18+J20*30 | E40: =J21*16+J20*30 | F40: =J21*14+J20*30
A41: 25x | B41: =J21*22+J20*25 | C41: =J21*20+J20*25 | D41: =J21*18+J20*25 | E41: =J21*16+J20*25 | F41: =J21*14+J20*25
A42: 20x | B42: =J21*22+J20*20 | C42: =J21*20+J20*20 | D42: =J21*18+J20*20 | E42: =J21*16+J20*20 | F42: =J21*14+J20*20
A43: 15x | B43: =J21*22+J20*15 | C43: =J21*20+J20*15 | D43: =J21*18+J20*15 | E43: =J21*16+J20*15 | F43: =J21*14+J20*15
A44: 10x | B44: =J21*22+J20*10 | C44: =J21*20+J20*10 | D44: =J21*18+J20*10 | E44: =J21*16+J20*10 | F44: =J21*14+J20*10
A46: E. Stress Test: What Happens to S&P 500 if AI Capex Slows?
A47: Base Case (AI PE=35x, Non-AI PE=18x)
A48: Current. AI capex sustains. NVDA margin holds.
B49: 2024A | C49: 2025A | D49: 2026E | E49: 2027E | F49: 2028E | G49: 2029E | H49: 2030E
A50: AI EPS ($) | B50: 5.9 | C50: 12.8 | D50: 28.7 | E50: 31.6 | F50: 30.5 | G50: 28.1 | H50: 25.7
A51: Non-AI EPS ($) | B51: =H21 | C51: =I21 | D51: =J21 | E51: =K21 | F51: =L21 | G51: =M21 | H51: =N21
A52: Implied S&P 500 | B52: =B50*35+B51*18 | C52: =C50*35+C51*18 | D52: =D50*35+D51*18 | E52: =E50*35+E51*18 | F52: =F50*35+F51*18 | G52: =G50*35+G51*18 | H52: =H50*35+H51*18
A54: Capex (AI PE=25x, Non-AI PE=18x)
A55: 2027+ capex growth decelerates to +10%. NVDA margin compresses. AI PE de-rates.
B56: 2024A | C56: 2025A | D56: 2026E | E56: 2027E | F56: 2028E | G56: 2029E | H56: 2030E
A57: AI EPS ($) | B57: 5.9 | C57: 12.8 | D57: 26.8 | E57: 26.6 | F57: 23.8 | G57: 21.5 | H57: 20
A58: Non-AI EPS ($) | B58: =H21 | C58: =I21 | D58: =J21 | E58: =K21 | F58: =L21 | G58: =M21 | H58: =N21
A59: Implied S&P 500 | B59: =B57*25+B58*18 | C59: =C57*25+C58*18 | D59: =D57*25+D58*18 | E59: =E57*25+E58*18 | F59: =F57*25+F58*18 | G59: =G57*25+G58*18 | H59: =H57*25+H58*18
A60: vs Base Delta | B60: =IFERROR(B59/B52-1,"") | C60: =IFERROR(C59/C52-1,"") | D60: =IFERROR(D59/D52-1,"") | E60: =IFERROR(E59/E52-1,"") | F60: =IFERROR(F59/F52-1,"") | G60: =IFERROR(G59/G52-1,"") | H60: =IFERROR(H59/H52-1,"")
A62: AI Bust (AI PE=15x, Non-AI PE=17x)
A63: Customer Crack. Capex cut 30% from 2027. Massive write-downs. AI PE crashes to market avg.
B64: 2024A | C64: 2025A | D64: 2026E | E64: 2027E | F64: 2028E | G64: 2029E | H64: 2030E
A65: AI EPS ($) | B65: 5.9 | C65: 12.8 | D65: 28.7 | E65: 12.4 | F65: 7.1 | G65: 5.5 | H65: 4.5
A66: Non-AI EPS ($) | B66: =H21 | C66: =I21 | D66: =J21 | E66: =K21 | F66: =L21 | G66: =M21 | H66: =N21
A67: Implied S&P 500 | B67: =B65*15+B66*17 | C67: =C65*15+C66*17 | D67: =D65*15+D66*17 | E67: =E65*15+E66*17 | F67: =F65*15+F66*17 | G67: =G65*15+G66*17 | H67: =H65*15+H66*17
A68: vs Base Delta | B68: =IFERROR(B67/B52-1,"") | C68: =IFERROR(C67/C52-1,"") | D68: =IFERROR(D67/D52-1,"") | E68: =IFERROR(E67/E52-1,"") | F68: =IFERROR(F67/F52-1,"") | G68: =IFERROR(G67/G52-1,"") | H68: =IFERROR(H67/H52-1,"")
A71: F. AI: AI？
A72: : AWS/Azure/GCPSustain30%+; Inference Demand(Agent); NVDA margin; AI$60B→$200B+; capexButFCF2028.
B73: 2024A | C73: 2025A | D73: 2026E | E73: 2027E | F73: 2028E | G73: 2029E | H73: 2030E
A74: AI EPS ($) — | B74: 7.2 | C74: 19.3 | D74: 32.2 | E74: 52 | F74: 72 | G74: 88 | H74: 100
A75: Non-AI EPS ($) | B75: 236 | C75: 243 | D75: 248 | E75: 248 | F75: 248 | G75: 250 | H75: 255
A76: Total EPS ($) | B76: =B74+B75 | C76: =C74+C75 | D76: =D74+D75 | E76: =E74+E75 | F76: =F74+F75 | G76: =G74+G75 | H76: =H74+H75
A77: Implied S&P 500 (AI 45x + AI 20x) | B77: =B74*45+B75*20 | C77: =C74*45+C75*20 | D77: =D74*45+D75*20 | E77: =E74*45+E75*20 | F77: =F74*45+F75*20 | G77: =G74*45+G75*20 | H77: =H74*45+H75*20
A78: P/E | B78: =IFERROR(B77/(B74+B75),"") | C78: =IFERROR(C77/(C74+C75),"") | D78: =IFERROR(D77/(D74+D75),"") | E78: =IFERROR(E77/(E74+E75),"") | F78: =IFERROR(F77/(F74+F75),"") | G78: =IFERROR(G77/(G74+G75),"") | H78: =IFERROR(H77/(H74+H75),"")
A80: 'sKey:
A81: 1. AI EPS: NVDA FY27 rev $300B+ (margin 60%+), AVGO AI rev, MU HBM →
A82: 2. CapexButROI: Cloud30%+Revenue → hyperscaler D&ARevenue
A83: 3. Agent: AI Agent/// → IT → Inference Demand>
A84: 4. AI: EPS5-8%/Year,
A85: 5. AI: AI1990s's → 40-50x forward PE
A86: 6. 2028-2030 FCF: capex+80%+10%, D&Acapex → hyperscaler FCF
A87: 7. : Inference Demand, pricing power, AI EPS2028-2029

Sheet 8. Charts
A1: Visual Summary (2013-2030)
A3: Capex/Revenue %
B4: 2013 | C4: 2014 | D4: 2015 | E4: 2016 | F4: 2017 | G4: 2018 | H4: 2019 | I4: 2020 | J4: 2021 | K4: 2022 | L4: 2023 | M4: 2024 | N4: 2025 | O4: 2026 | P4: 2027 | Q4: 2028 | R4: 2029 | S4: 2030
A5: MSFT | B5: =IFERROR('0. Database'!C12/'0. Database'!C5,NA()) | C5: =IFERROR('0. Database'!D12/'0. Database'!D5,NA()) | D5: =IFERROR('0. Database'!E12/'0. Database'!E5,NA()) | E5: =IFERROR('0. Database'!F12/'0. Database'!F5,NA()) | F5: =IFERROR('0. Database'!G12/'0. Database'!G5,NA()) | G5: =IFERROR('0. Database'!H12/'0. Database'!H5,NA()) | H5: =IFERROR('0. Database'!I12/'0. Database'!I5,NA()) | I5: =IFERROR('0. Database'!J12/'0. Database'!J5,NA()) | ... S5: =IFERROR('0. Database'!T12/'0. Database'!T5,NA())
A6: AMZN | B6: =IFERROR('0. Database'!C28/'0. Database'!C21,NA()) | C6: =IFERROR('0. Database'!D28/'0. Database'!D21,NA()) | D6: =IFERROR('0. Database'!E28/'0. Database'!E21,NA()) | E6: =IFERROR('0. Database'!F28/'0. Database'!F21,NA()) | F6: =IFERROR('0. Database'!G28/'0. Database'!G21,NA()) | G6: =IFERROR('0. Database'!H28/'0. Database'!H21,NA()) | H6: =IFERROR('0. Database'!I28/'0. Database'!I21,NA()) | I6: =IFERROR('0. Database'!J28/'0. Database'!J21,NA()) | ... S6: =IFERROR('0. Database'!T28/'0. Database'!T21,NA())
A7: GOOGL | B7: =IFERROR('0. Database'!C43/'0. Database'!C36,NA()) | C7: =IFERROR('0. Database'!D43/'0. Database'!D36,NA()) | D7: =IFERROR('0. Database'!E43/'0. Database'!E36,NA()) | E7: =IFERROR('0. Database'!F43/'0. Database'!F36,NA()) | F7: =IFERROR('0. Database'!G43/'0. Database'!G36,NA()) | G7: =IFERROR('0. Database'!H43/'0. Database'!H36,NA()) | H7: =IFERROR('0. Database'!I43/'0. Database'!I36,NA()) | I7: =IFERROR('0. Database'!J43/'0. Database'!J36,NA()) | ... S7: =IFERROR('0. Database'!T43/'0. Database'!T36,NA())
A8: META | B8: =IFERROR('0. Database'!C60/'0. Database'!C53,NA()) | C8: =IFERROR('0. Database'!D60/'0. Database'!D53,NA()) | D8: =IFERROR('0. Database'!E60/'0. Database'!E53,NA()) | E8: =IFERROR('0. Database'!F60/'0. Database'!F53,NA()) | F8: =IFERROR('0. Database'!G60/'0. Database'!G53,NA()) | G8: =IFERROR('0. Database'!H60/'0. Database'!H53,NA()) | H8: =IFERROR('0. Database'!I60/'0. Database'!I53,NA()) | I8: =IFERROR('0. Database'!J60/'0. Database'!J53,NA()) | ... S8: =IFERROR('0. Database'!T60/'0. Database'!T53,NA())
A9: ORCL | B9: =IFERROR('0. Database'!C78/'0. Database'!C82,NA()) | C9: =IFERROR('0. Database'!D78/'0. Database'!D82,NA()) | D9: =IFERROR('0. Database'!E78/'0. Database'!E82,NA()) | E9: =IFERROR('0. Database'!F78/'0. Database'!F82,NA()) | F9: =IFERROR('0. Database'!G78/'0. Database'!G82,NA()) | G9: =IFERROR('0. Database'!H78/'0. Database'!H82,NA()) | H9: =IFERROR('0. Database'!I78/'0. Database'!I82,NA()) | I9: =IFERROR('0. Database'!J78/'0. Database'!J82,NA()) | ... S9: =IFERROR('0. Database'!T78/'0. Database'!T82,NA())
A28: FCF Margin %
B29: 2013 | C29: 2014 | D29: 2015 | E29: 2016 | F29: 2017 | G29: 2018 | H29: 2019 | I29: 2020 | J29: 2021 | K29: 2022 | L29: 2023 | M29: 2024 | N29: 2025 | O29: 2026 | P29: 2027 | Q29: 2028 | R29: 2029 | S29: 2030
A30: MSFT
A31: AMZN
A32: GOOGL
A33: META
A34: ORCL
A53: Capex ($mm)
B54: 2013 | C54: 2014 | D54: 2015 | E54: 2016 | F54: 2017 | G54: 2018 | H54: 2019 | I54: 2020 | J54: 2021 | K54: 2022 | L54: 2023 | M54: 2024 | N54: 2025 | O54: 2026 | P54: 2027 | Q54: 2028 | R54: 2029 | S54: 2030
A55: MSFT | B55: =IFERROR('0. Database'!C12,NA()) | C55: =IFERROR('0. Database'!D12,NA()) | D55: =IFERROR('0. Database'!E12,NA()) | E55: =IFERROR('0. Database'!F12,NA()) | F55: =IFERROR('0. Database'!G12,NA()) | G55: =IFERROR('0. Database'!H12,NA()) | H55: =IFERROR('0. Database'!I12,NA()) | I55: =IFERROR('0. Database'!J12,NA()) | ... S55: =IFERROR('0. Database'!T12,NA())
A56: AMZN | B56: =IFERROR('0. Database'!C28,NA()) | C56: =IFERROR('0. Database'!D28,NA()) | D56: =IFERROR('0. Database'!E28,NA()) | E56: =IFERROR('0. Database'!F28,NA()) | F56: =IFERROR('0. Database'!G28,NA()) | G56: =IFERROR('0. Database'!H28,NA()) | H56: =IFERROR('0. Database'!I28,NA()) | I56: =IFERROR('0. Database'!J28,NA()) | ... S56: =IFERROR('0. Database'!T28,NA())
A57: GOOGL | B57: =IFERROR('0. Database'!C43,NA()) | C57: =IFERROR('0. Database'!D43,NA()) | D57: =IFERROR('0. Database'!E43,NA()) | E57: =IFERROR('0. Database'!F43,NA()) | F57: =IFERROR('0. Database'!G43,NA()) | G57: =IFERROR('0. Database'!H43,NA()) | H57: =IFERROR('0. Database'!I43,NA()) | I57: =IFERROR('0. Database'!J43,NA()) | ... S57: =IFERROR('0. Database'!T43,NA())
A58: META | B58: =IFERROR('0. Database'!C60,NA()) | C58: =IFERROR('0. Database'!D60,NA()) | D58: =IFERROR('0. Database'!E60,NA()) | E58: =IFERROR('0. Database'!F60,NA()) | F58: =IFERROR('0. Database'!G60,NA()) | G58: =IFERROR('0. Database'!H60,NA()) | H58: =IFERROR('0. Database'!I60,NA()) | I58: =IFERROR('0. Database'!J60,NA()) | ... S58: =IFERROR('0. Database'!T60,NA())
A59: ORCL | B59: =IFERROR('0. Database'!C78,NA()) | C59: =IFERROR('0. Database'!D78,NA()) | D59: =IFERROR('0. Database'!E78,NA()) | E59: =IFERROR('0. Database'!F78,NA()) | F59: =IFERROR('0. Database'!G78,NA()) | G59: =IFERROR('0. Database'!H78,NA()) | H59: =IFERROR('0. Database'!I78,NA()) | I59: =IFERROR('0. Database'!J78,NA()) | ... S59: =IFERROR('0. Database'!T78,NA())
A78: Revenue YoY %
B79: 2013 | C79: 2014 | D79: 2015 | E79: 2016 | F79: 2017 | G79: 2018 | H79: 2019 | I79: 2020 | J79: 2021 | K79: 2022 | L79: 2023 | M79: 2024 | N79: 2025 | O79: 2026 | P79: 2027 | Q79: 2028 | R79: 2029 | S79: 2030
A80: MSFT | C80: =IFERROR('0. Database'!D5/'0. Database'!C5-1,NA()) | D80: =IFERROR('0. Database'!E5/'0. Database'!D5-1,NA()) | E80: =IFERROR('0. Database'!F5/'0. Database'!E5-1,NA()) | F80: =IFERROR('0. Database'!G5/'0. Database'!F5-1,NA()) | G80: =IFERROR('0. Database'!H5/'0. Database'!G5-1,NA()) | H80: =IFERROR('0. Database'!I5/'0. Database'!H5-1,NA()) | I80: =IFERROR('0. Database'!J5/'0. Database'!I5-1,NA()) | J80: =IFERROR('0. Database'!K5/'0. Database'!J5-1,NA()) | ... S80: =IFERROR('0. Database'!T5/'0. Database'!S5-1,NA())
A81: AMZN | C81: =IFERROR('0. Database'!D21/'0. Database'!C21-1,NA()) | D81: =IFERROR('0. Database'!E21/'0. Database'!D21-1,NA()) | E81: =IFERROR('0. Database'!F21/'0. Database'!E21-1,NA()) | F81: =IFERROR('0. Database'!G21/'0. Database'!F21-1,NA()) | G81: =IFERROR('0. Database'!H21/'0. Database'!G21-1,NA()) | H81: =IFERROR('0. Database'!I21/'0. Database'!H21-1,NA()) | I81: =IFERROR('0. Database'!J21/'0. Database'!I21-1,NA()) | J81: =IFERROR('0. Database'!K21/'0. Database'!J21-1,NA()) | ... S81: =IFERROR('0. Database'!T21/'0. Database'!S21-1,NA())
A82: GOOGL | C82: =IFERROR('0. Database'!D36/'0. Database'!C36-1,NA()) | D82: =IFERROR('0. Database'!E36/'0. Database'!D36-1,NA()) | E82: =IFERROR('0. Database'!F36/'0. Database'!E36-1,NA()) | F82: =IFERROR('0. Database'!G36/'0. Database'!F36-1,NA()) | G82: =IFERROR('0. Database'!H36/'0. Database'!G36-1,NA()) | H82: =IFERROR('0. Database'!I36/'0. Database'!H36-1,NA()) | I82: =IFERROR('0. Database'!J36/'0. Database'!I36-1,NA()) | J82: =IFERROR('0. Database'!K36/'0. Database'!J36-1,NA()) | ... S82: =IFERROR('0. Database'!T36/'0. Database'!S36-1,NA())
A83: META | C83: =IFERROR('0. Database'!D53/'0. Database'!C53-1,NA()) | D83: =IFERROR('0. Database'!E53/'0. Database'!D53-1,NA()) | E83: =IFERROR('0. Database'!F53/'0. Database'!E53-1,NA()) | F83: =IFERROR('0. Database'!G53/'0. Database'!F53-1,NA()) | G83: =IFERROR('0. Database'!H53/'0. Database'!G53-1,NA()) | H83: =IFERROR('0. Database'!I53/'0. Database'!H53-1,NA()) | I83: =IFERROR('0. Database'!J53/'0. Database'!I53-1,NA()) | J83: =IFERROR('0. Database'!K53/'0. Database'!J53-1,NA()) | ... S83: =IFERROR('0. Database'!T53/'0. Database'!S53-1,NA())
A84: ORCL | C84: =IFERROR('0. Database'!D82/'0. Database'!C82-1,NA()) | D84: =IFERROR('0. Database'!E82/'0. Database'!D82-1,NA()) | E84: =IFERROR('0. Database'!F82/'0. Database'!E82-1,NA()) | F84: =IFERROR('0. Database'!G82/'0. Database'!F82-1,NA()) | G84: =IFERROR('0. Database'!H82/'0. Database'!G82-1,NA()) | H84: =IFERROR('0. Database'!I82/'0. Database'!H82-1,NA()) | I84: =IFERROR('0. Database'!J82/'0. Database'!I82-1,NA()) | J84: =IFERROR('0. Database'!K82/'0. Database'!J82-1,NA()) | ... S84: =IFERROR('0. Database'!T82/'0. Database'!S82-1,NA())
A103: Operating Margin %
B104: 2013 | C104: 2014 | D104: 2015 | E104: 2016 | F104: 2017 | G104: 2018 | H104: 2019 | I104: 2020 | J104: 2021 | K104: 2022 | L104: 2023 | M104: 2024 | N104: 2025 | O104: 2026 | P104: 2027 | Q104: 2028 | R104: 2029 | S104: 2030
A105: MSFT | B105: =IFERROR('0. Database'!C6/'0. Database'!C5,NA()) | C105: =IFERROR('0. Database'!D6/'0. Database'!D5,NA()) | D105: =IFERROR('0. Database'!E6/'0. Database'!E5,NA()) | E105: =IFERROR('0. Database'!F6/'0. Database'!F5,NA()) | F105: =IFERROR('0. Database'!G6/'0. Database'!G5,NA()) | G105: =IFERROR('0. Database'!H6/'0. Database'!H5,NA()) | H105: =IFERROR('0. Database'!I6/'0. Database'!I5,NA()) | I105: =IFERROR('0. Database'!J6/'0. Database'!J5,NA()) | ... S105: =IFERROR('0. Database'!T6/'0. Database'!T5,NA())
A106: AMZN | B106: =IFERROR('0. Database'!C22/'0. Database'!C21,NA()) | C106: =IFERROR('0. Database'!D22/'0. Database'!D21,NA()) | D106: =IFERROR('0. Database'!E22/'0. Database'!E21,NA()) | E106: =IFERROR('0. Database'!F22/'0. Database'!F21,NA()) | F106: =IFERROR('0. Database'!G22/'0. Database'!G21,NA()) | G106: =IFERROR('0. Database'!H22/'0. Database'!H21,NA()) | H106: =IFERROR('0. Database'!I22/'0. Database'!I21,NA()) | I106: =IFERROR('0. Database'!J22/'0. Database'!J21,NA()) | ... S106: =IFERROR('0. Database'!T22/'0. Database'!T21,NA())
A107: GOOGL | B107: =IFERROR('0. Database'!C37/'0. Database'!C36,NA()) | C107: =IFERROR('0. Database'!D37/'0. Database'!D36,NA()) | D107: =IFERROR('0. Database'!E37/'0. Database'!E36,NA()) | E107: =IFERROR('0. Database'!F37/'0. Database'!F36,NA()) | F107: =IFERROR('0. Database'!G37/'0. Database'!G36,NA()) | G107: =IFERROR('0. Database'!H37/'0. Database'!H36,NA()) | H107: =IFERROR('0. Database'!I37/'0. Database'!I36,NA()) | I107: =IFERROR('0. Database'!J37/'0. Database'!J36,NA()) | ... S107: =IFERROR('0. Database'!T37/'0. Database'!T36,NA())
A108: META | B108: =IFERROR('0. Database'!C54/'0. Database'!C53,NA()) | C108: =IFERROR('0. Database'!D54/'0. Database'!D53,NA()) | D108: =IFERROR('0. Database'!E54/'0. Database'!E53,NA()) | E108: =IFERROR('0. Database'!F54/'0. Database'!F53,NA()) | F108: =IFERROR('0. Database'!G54/'0. Database'!G53,NA()) | G108: =IFERROR('0. Database'!H54/'0. Database'!H53,NA()) | H108: =IFERROR('0. Database'!I54/'0. Database'!I53,NA()) | I108: =IFERROR('0. Database'!J54/'0. Database'!J53,NA()) | ... S108: =IFERROR('0. Database'!T54/'0. Database'!T53,NA())
A109: ORCL | B109: =IFERROR('0. Database'!C86/'0. Database'!C82,NA()) | C109: =IFERROR('0. Database'!D86/'0. Database'!D82,NA()) | D109: =IFERROR('0. Database'!E86/'0. Database'!E82,NA()) | E109: =IFERROR('0. Database'!F86/'0. Database'!F82,NA()) | F109: =IFERROR('0. Database'!G86/'0. Database'!G82,NA()) | G109: =IFERROR('0. Database'!H86/'0. Database'!H82,NA()) | H109: =IFERROR('0. Database'!I86/'0. Database'!I82,NA()) | I109: =IFERROR('0. Database'!J86/'0. Database'!J82,NA()) | ... S109: =IFERROR('0. Database'!T86/'0. Database'!T82,NA())
A128: D&A / Revenue %
B129: 2013 | C129: 2014 | D129: 2015 | E129: 2016 | F129: 2017 | G129: 2018 | H129: 2019 | I129: 2020 | J129: 2021 | K129: 2022 | L129: 2023 | M129: 2024 | N129: 2025 | O129: 2026 | P129: 2027 | Q129: 2028 | R129: 2029 | S129: 2030
A130: MSFT | B130: =IFERROR('0. Database'!C11/'0. Database'!C5,NA()) | C130: =IFERROR('0. Database'!D11/'0. Database'!D5,NA()) | D130: =IFERROR('0. Database'!E11/'0. Database'!E5,NA()) | E130: =IFERROR('0. Database'!F11/'0. Database'!F5,NA()) | F130: =IFERROR('0. Database'!G11/'0. Database'!G5,NA()) | G130: =IFERROR('0. Database'!H11/'0. Database'!H5,NA()) | H130: =IFERROR('0. Database'!I11/'0. Database'!I5,NA()) | I130: =IFERROR('0. Database'!J11/'0. Database'!J5,NA()) | ... S130: =IFERROR('0. Database'!T11/'0. Database'!T5,NA())
A131: AMZN | B131: =IFERROR('0. Database'!C27/'0. Database'!C21,NA()) | C131: =IFERROR('0. Database'!D27/'0. Database'!D21,NA()) | D131: =IFERROR('0. Database'!E27/'0. Database'!E21,NA()) | E131: =IFERROR('0. Database'!F27/'0. Database'!F21,NA()) | F131: =IFERROR('0. Database'!G27/'0. Database'!G21,NA()) | G131: =IFERROR('0. Database'!H27/'0. Database'!H21,NA()) | H131: =IFERROR('0. Database'!I27/'0. Database'!I21,NA()) | I131: =IFERROR('0. Database'!J27/'0. Database'!J21,NA()) | ... S131: =IFERROR('0. Database'!T27/'0. Database'!T21,NA())
A132: GOOGL | B132: =IFERROR('0. Database'!C42/'0. Database'!C36,NA()) | C132: =IFERROR('0. Database'!D42/'0. Database'!D36,NA()) | D132: =IFERROR('0. Database'!E42/'0. Database'!E36,NA()) | E132: =IFERROR('0. Database'!F42/'0. Database'!F36,NA()) | F132: =IFERROR('0. Database'!G42/'0. Database'!G36,NA()) | G132: =IFERROR('0. Database'!H42/'0. Database'!H36,NA()) | H132: =IFERROR('0. Database'!I42/'0. Database'!I36,NA()) | I132: =IFERROR('0. Database'!J42/'0. Database'!J36,NA()) | ... S132: =IFERROR('0. Database'!T42/'0. Database'!T36,NA())
A133: META | B133: =IFERROR('0. Database'!C59/'0. Database'!C53,NA()) | C133: =IFERROR('0. Database'!D59/'0. Database'!D53,NA()) | D133: =IFERROR('0. Database'!E59/'0. Database'!E53,NA()) | E133: =IFERROR('0. Database'!F59/'0. Database'!F53,NA()) | F133: =IFERROR('0. Database'!G59/'0. Database'!G53,NA()) | G133: =IFERROR('0. Database'!H59/'0. Database'!H53,NA()) | H133: =IFERROR('0. Database'!I59/'0. Database'!I53,NA()) | I133: =IFERROR('0. Database'!J59/'0. Database'!J53,NA()) | ... S133: =IFERROR('0. Database'!T59/'0. Database'!T53,NA())
A134: ORCL | B134: =IFERROR('0. Database'!C77/'0. Database'!C82,NA()) | C134: =IFERROR('0. Database'!D77/'0. Database'!D82,NA()) | D134: =IFERROR('0. Database'!E77/'0. Database'!E82,NA()) | E134: =IFERROR('0. Database'!F77/'0. Database'!F82,NA()) | F134: =IFERROR('0. Database'!G77/'0. Database'!G82,NA()) | G134: =IFERROR('0. Database'!H77/'0. Database'!H82,NA()) | H134: =IFERROR('0. Database'!I77/'0. Database'!I82,NA()) | I134: =IFERROR('0. Database'!J77/'0. Database'!J82,NA()) | ... S134: =IFERROR('0. Database'!T77/'0. Database'!T82,NA())

Sheet 9. Bubble & Valuation
A1: Bubble Risk: 2000 vs 2026 + Valuation + Triggers
A3: A. S&P 500 Forecasts (May 2026)
A4: Source | B4: 2024A | C4: 2025A | D4: 2026E | E4: 2027E | F4: YE2026 Target | G4: Notes
A5: Sell-side Top-Down | B5: $246 | C5: $275 | D5: $309 (+12%) | E5: $342 (+10%) | F5: 7,600 | G5: Exhibit 27/28
A6: Bottom-Up Consensus | B6: $246 | C6: $275 | D6: $337 (+23%) | E6: $387 (+15%) | F6: — | G6: Higher due to idiosyncratic
A7: Our AI Split Model | B7: $246 | C7: $275 | D7: $309 | E7: $342 | F7: 5,528* | G7: *Non-AI 18x + AI 35x
A9: B. 2027E Implied S&P 500 = EPS x P/E
A10: EPS Scenario | B10: 18x | C10: 19x | D10: 20x | E10: 21x | F10: 22x | G10: 23x | H10: 24x
A11: Top-Down $342 | B11: 6156 | C11: 6498 | D11: 6840 | E11: 7182 | F11: 7524 | G11: 7866 | H11: 8208
A12: Consensus $387 | B12: 6966 | C12: 7353 | D12: 7740 | E12: 8127 | F12: 8514 | G12: 8901 | H12: 9288
A13: Stress $300 | B13: 5400 | C13: 5700 | D13: 6000 | E13: 6300 | F13: 6600 | G13: 6900 | H13: 7200
A14: Crash $260 | B14: 4680 | C14: 4940 | D14: 5200 | E14: 5460 | F14: 5720 | G14: 5980 | H14: 6240
A16: C. Current Valuation vs History
A17: Metric | B17: Current | C17: 10yr %ile | D17: 30yr %ile | E17: 2000 Peak | F17: Verdict
A18: S&P 500 Fwd P/E | B18: 21x | C18: 64% | D18: 82% | E18: 24x | F18: Expensive but not extreme
A19: IT Weight | B19: 36% | C19: 99% | D19: 99% | E19: 33% | F19: EXCEEDS 2000
A20: Top 10 Earnings | B20: 33% | C20: 99% | D20: 99% | E20: ~25% | F20: Record concentration
A21: EPS Beat Reward | B21: +20bp | C21: 2% | D21: 2% | E21: +100bp | F21: 25yr low
A22: Capex/CFO Hyper | B22: 100% | C22: 99% | D22: 99% | E22: 80-90% | F22: EXCEEDS 2000 telco
A23: Hyper Net Debt/EBITDA | B23: 0.3x | C23: Low | D23: Low | E23: 3x+ telco | F23: Still healthy
A25: D. 2000 Bubble 5-Phase Timeline vs AI 2026
A26: Phase | B26: 2000 Telecom | C26: AI 2026 | D26: Status | E26: Next Trigger
A27: 1. Valuation Mania | B27: Nasdaq 200x PE | C27: NVDA 30-40x; S&P 21x (82nd %ile) | D27: PARTIAL | E27: PE>25x
A28: 2. Liquidity Signal | B28: Greenspan hikes | C28: Fed hold 3.7%; not cutting | D28: BORDERLINE | E28: Fed hawkish or IG>100bp
A29: 3. Customer Deaths | B29: Pets.com 9mo post-IPO | C29: OpenAI burns $17B/yr, still raising | D29: NOT YET | E29: AI lab funding delay/down round
A30: 4. Capex Crack | B30: Telcos stop; 85% dark fiber | C30: Hyperscalers +83%; cRPO record | D30: NOT YET | E30: Any name cuts 2027 guide
A31: 5. Accounting | B31: Enron $38B; WorldCom bankrupt | C31: Circular financing exists | D31: NOT YET | E31: AI stake write-down
A33: Position: Between Phase 1-2. Phases 3/4/5 NOT occurred. Burst window: 2027 H1-H2 (D&A wave locked in). Distance: 2-4 quarters.

Sheet 10. AI Monetization
A1: Can AI Capex Be Monetized? The $725B Question
A3: A. The EPS Growth Puzzle: Why Does EPS Rise When D&A Explodes?
A4: Analysts project EPS growth of 15-25% in 2026-27E despite D&A surging 50-100%. The answer is in incremental economics: as long as each $1 of new D&A is offset by >$1 of new gross profit, margins can expand. The table below quantifies this for each company.
A5: Company | B5: Year | C5: dRev ($B) | D5: dD&A ($B) | E5: D&A Absorbs % of dRev | F5: dOpInc ($B) | G5: OI Captures % of dRev | H5: Margin Direction | I5: Analyst Assumption
A6: MSFT | B6: 2026E | C6: 48 | D6: 12 | E6: 24% | F6: 25 | G6: 52% | H6: Expand | I6: Azure +40% sustains; cloud mix shift to higher-margin AI copilot
A7: MSFT | B7: 2027E | C7: 58 | D7: 23 | E7: 40% | F7: 26 | G7: 45% | H7: Flat | I7: Rev growth +17.5% just offsets D&A wave; margin flat at 46%
A8: AMZN | B8: 2026E | C8: 111 | D8: 15 | E8: 14% | F8: 29 | G8: 26% | H8: Expand | I8: AWS reaccel to +33%; ads +20%; retail efficiency gains
A9: AMZN | B9: 2027E | C9: 119 | D9: 10 | E9: 8% | F9: 37 | G9: 31% | H9: Expand | I9: D&A growth briefly pauses (capex front-loaded); AWS margin expands
A10: GOOGL | B10: 2026E | C10: 85 | D10: 22 | E10: 25% | F10: 38 | G10: 45% | H10: Expand | I10: Cloud +69% inflection; Search +15%; YouTube +9%
A11: GOOGL | B11: 2027E | C11: 104 | D11: 27 | E11: 26% | F11: 43 | G11: 41% | H11: Expand | I11: Cloud margin 30%+ fully kicks in; but NI hit by equity gain reversal
A12: META | B12: 2026E | C12: 54 | D12: 17 | E12: 32% | F12: 7 | G12: 13% | H12: Compress | I12: D&A +93% swamps rev growth; OpMargin 42%->35.5%. EPS still +42% on base effect
A13: META | B13: 2027E | C13: 51 | D13: 21 | E13: 40% | F13: 14 | G13: 27% | H13: Compress | I13: D&A keeps accelerating; OpMargin 34%; EPS only +5%
A14: ORCL | B14: 2026E | C14: 10 | D14: 4 | E14: 37% | F14: 2 | G14: 18% | H14: Compress | I14: OCI rev +76% but D&A+interest eat most of it; margin 31%->29%
A15: ORCL | B15: 2027E | C15: 21 | D15: 9 | E15: 44% | F15: 2 | G15: 8% | H15: Collapse | I15: D&A +125% ($17B) destroys margins; EPS DECLINES -16.4%
A17: B. The Famine Analogy: Scarcity-Driven Demand vs Profit-Driven Demand
A18: Your Insight | B18: If food only feeds 80% of people, prices spike until 20% die (or stop bidding). GPU demand follows the same logic: scarcity drives pricing, not ROI.
A19: Current State (2025-2026) | B19: Every tech giant is hoarding GPUs out of fear of being left behind — not because each GPU generates positive ROI today. This is FOMO-driven procurement, like wartime grain hoarding. H100 resale prices have NOT declined because demand > supply.
A20: Evidence of FOMO Buying | B20: META has 1.3M GPUs but zero external AI revenue — all GPUs serve internal ad targeting. ORCL is spending 77% of revenue on capex for contracts with OpenAI that may never be profitable. Hyperscalers are spending 100% of CFO on capex.
A21: The Key Question | B21: What happens when supply catches up with demand? GPU scarcity = high prices = high margins for NVDA. But: (1) NVDA ships Blackwell at 2-3x volume; (2) AMD MI300/400 gains share; (3) custom chips (TPU, Trainium, Inferentia) scale. When the famine ends, prices collapse.
A22: Historical Parallel | B22: Telecom 2000: fiber was scarce in 1998-99 → telcos paid any price → fiber glut by 2001 → 85% became 'dark fiber' → prices collapsed 90%. The question is not IF supply catches up, but WHEN.
A24: C. AI Revenue vs AI Capex: The Monetization Gap ($B)
A25: Metric | B25: 2023A | C25: 2024A | D25: 2025E | E25: 2026E | F25: 2027E | G25: Source
A26: Hyperscaler AI Capex ($B) | B26: 154 | C26: 237 | D26: 412 | E26: 755 | F26: 892 | G26: Our model (5 cos)
A27: NVDA Data Center Revenue ($B) | B27: 47 | C27: 115 | D27: 216 | E27: 300 | F27: 400 | G27: NVDA FY reports (shifted to CY)
A28: Global Cloud AI Revenue ($B) | B28: 10 | C28: 20 | D28: 40 | E28: 70 | F28: 110 | G28: Synergy/Gartner est.
A29: OpenAI Revenue ($B) | B29: 1.6 | C29: 3.7 | D29: 13 | E29: 25 | F29: 45 | G29: Sacra/press; $25B ARR Feb'26
A30: Anthropic Revenue ($B) | B30: 0.2 | C30: 0.9 | D30: 4 | E30: 30 | F30: 50 | G30: Sacra; $30B ARR Apr'26
A31: Total AI End-User Revenue ($B) | B31: 15 | C31: 30 | D31: 65 | E31: 140 | F31: 230 | G31: Cloud AI + AI lab + enterprise
A32: Capex / AI Revenue Ratio | B32: 10.3 | C32: 7.9 | D32: 6.3 | E32: 5.4 | F32: 3.9 | G32: Hyperscaler capex / end-user rev
A33: NVDA Gross Margin % | B33: 73% | C33: 75% | D33: 73% | E33: 70% | F33: 65% | G33: NVDA reports; compress as competition
A35: Key: $755B capex chasing ~$140B of AI end-user revenue in 2026E = 5.4x ratio. For every $1 of AI revenue, $5.4 is being spent on infrastructure. This ratio MUST compress to <2x for the cycle to be sustainable.
A37: D. What If Models Commoditize? The Price War Scenario
A38: Current State (May 2026) | B38: Models are differentiating but converging. GPT-4o, Claude 4, Gemini 2.5, Llama 4 all score within 5% on MMLU/HumanEval. API pricing already falling: GPT-4 input went from $30/Mtok (Mar'24) to $2.50 (May'26) = -92% in 2 years.
A39: Price War Trigger | B39: Open-source (Llama, Mistral, DeepSeek) closes the gap. If Llama 5 matches GPT-5 at 1/10 the cost, enterprise customers shift to self-hosted → cloud AI margin collapses → hyperscaler capex ROI craters.
A40: Who Gets Hurt | B40: ORCL (77% Capex/Rev, single customer OpenAI) → existential. META (all internal, ad ROI must justify $140B capex). AMZN (Anthropic exposure + AWS margin pressure). MSFT partially insulated via Copilot enterprise lock-in.
A41: Who Survives | B41: GOOGL (owns TPU + largest search moat + Anthropic hedge). MSFT (enterprise lock-in + diversified cloud). NVDA hurt on margins but not existentially (still the picks-and-shovels play).
A42: Inference Cost Trajectory | B42: NVDA Blackwell: 4x inference throughput vs Hopper at same power. This DEFLATES inference cost per token. Good for users, bad for GPU ASP. If inference cost drops 50%/yr (historical trend), by 2028 most workloads run profitably on 2-year-old hardware.
A43: Endgame (2028-2030) | B43: Two possible equilibria: (A) 3-4 surviving AI platforms (like cloud: AWS/Azure/GCP) with 30-40% margins; or (B) commoditized inference (like bandwidth post-2000) with 5-10% margins. The difference determines $3T vs $500B of total market value.
A45: E. How This Story Evolves: 3 Paths + Valuation Implications
A46: Path 1: AI = New Internet (Bull, P=30%)
A47: Story | B47: Agents work. Enterprise ROI validates within 12 months. Inference demand grows 100%+/yr. AI revenue reaches $500B by 2029. Capex/AI Rev ratio compresses to 2x naturally. NVDA margin holds at 60%+. GPU supply stays tight. Hyperscaler EPS growth 15-20%/yr through 2030. S&P 500 AI EPS grows from $29 to $80+.
A48: Valuation Impact | B48: S&P 500: 8,000-9,000 by YE2027 NVDA: $250+ (40x fwd) Hyperscalers: 25-30x fwd PE Key signal: AWS/Azure AI revenue >$30B/qtr by Q4 2026
A50: Path 2: AI = Mobile (Base, P=45%)
A51: Story | B51: AI is real but slower to monetize than expected. Agents take 3-5 years, not 1-2. Revenue grows 40-50%/yr but capex grows 20-30%. Capex/AI Rev ratio compresses slowly to 3x by 2028. NVDA margin compresses to 55-60%. Some GPU oversupply by 2028. Hyperscaler EPS growth decelerates to 8-12%. D&A wave hits 2027-28. Some write-downs at ORCL.
A52: Valuation Impact | B52: S&P 500: 6,500-7,500 by YE2027 (range-bound) NVDA: $150-180 (25x fwd, margin compression) MSFT/GOOGL hold; ORCL -30-40%; META flat Key signal: inference token price drops >50%/yr
A54: Path 3: AI = Fiber Optic (Bear, P=25%)
A55: Story | B55: Models commoditize. Open-source closes gap. Enterprise ROI disappoints. Price war destroys cloud AI margins. Capex/AI Rev ratio NEVER compresses below 4x. NVDA margin drops to 45%. GPU glut by 2027 (like dark fiber). OpenAI/Anthropic funding stress. Hyperscaler write-downs $50-100B. ORCL credit event.
A56: Valuation Impact | B56: S&P 500: 5,000-5,500 by YE2027 (-25-30%) NVDA: $80-100 (15x fwd, margin + growth collapse) ORCL: -60%+; AMZN write-down $30-50B; META capex reversal Key signal: secondary GPU market price -40%+
A58: F. The Single Metric That Will Decide Everything
A59: Capex / AI End-User Revenue Ratio. Currently 5.4x. Must reach <2x for sustainability.
A60: 2023A | B60: 10.3x | C60: Famine mode: all spending, minimal revenue | G60: Pre-ChatGPT-enterprise era
A61: 2024A | B61: 7.9x | C61: Still extreme but improving | G61: Enterprise pilots starting
A62: 2025E | B62: 6.3x | C62: Improving on revenue acceleration | G62: Cloud AI reaches $40B
A63: 2026E | B63: 5.4x | C63: Bull narrative: 'it's compressing!' | G63: But still 5x+ is unsustainable long-term
A64: 2027E Bull | B64: 3.0x | C64: If AI rev hits $300B | G64: Agents work, inference explodes
A65: 2027E Base | B65: 3.9x | C65: If AI rev hits $230B | G65: Solid but not escape velocity
A66: 2027E Bear | B66: 6.0x | C66: If AI rev stalls at $150B | G66: Price war + slower enterprise adoption
A67: Sustainable | B67: <2.0x | C67: Cloud analogy: AWS capex/rev ~1.5x | G67: This is where the cycle MUST converge
A69: Bottom Line: The famine analogy is correct — companies are hoarding GPUs out of fear, not proven ROI. When supply normalizes (Blackwell volume + AMD + custom silicon by 2027-28), the pricing power evaporates. The winners will be those who converted GPU capex into recurring revenue (MSFT Copilot, GOOGL Cloud, AWS Bedrock) before the famine ends. Those who hoarded without monetizing (ORCL for OpenAI, META for internal ads) face the largest write-down risk.
A72: G. Open Source Correction: Does OSS Kill Hyperscaler Monetization?
A73: Short answer: No. Open source hurts AI lab API margins, NOT hyperscaler infrastructure revenue. Every model — open or closed — needs compute to run.
A74: Layer | B74: Open Source Impact | C74: Verdict
A75: GPU Makers (NVDA/AMD) | B75: Open source = more users = more GPUs needed | H75: BENEFICIARY
A76: Cloud Infra (AWS/Azure/GCP) | B76: Open models run ON cloud infra. Llama on Bedrock = AWS revenue. Enterprise self-deploy = still rents GPU instances. | H76: BENEFICIARY
A77: AI Lab API (OpenAI/Anthropic) | B77: Open source closes quality gap = API pricing power drops. GPT-4 input: $30/Mtok (Mar'24) -> $2.50 (May'26) = -92%. | H77: DAMAGED
A78: AI Lab Valuations | B78: If API margin compresses 33% -> 10%, $850B OpenAI valuation is hard to justify. Funding pressure rises. | H78: DAMAGED
A79: ORCL (OpenAI dependent) | B79: OpenAI funding stress -> Stargate commitment at risk. Indirect but existential for ORCL. | H79: INDIRECTLY DAMAGED
A80: META (internal use) | B80: Open source irrelevant — META uses GPUs for own ad targeting. No external monetization to lose. | H80: NEUTRAL
A82: Corrected Monetization Math: Hyperscaler capex serves ALL cloud + AI workloads, not just AI lab API revenue.
A83: Original denominator | B83: $140B (AI end-user revenue only) | E83: Capex/Rev = 5.4x | G83: Too narrow — ignores non-AI cloud + OSS inference + internal AI
A84: Corrected denominator | B84: $250B (full cloud AI + inference + SaaS) | E84: Capex/Rev = 3.0x | G84: More realistic — includes OSS inference on cloud + enterprise AI
A85: Full cloud market | B85: $500B+ (2026E total cloud infra) | E85: Capex/Rev = 1.5x | G85: If you count ALL cloud rev (not just AI), ratio already sustainable
A86: The real question | G86: How fast does AI-driven incremental cloud revenue grow? If +50%/yr -> 3.0x compresses to <2x by 2028. If +20%/yr -> stays at 3x+ through 2030.
A89: H. Daily Crash Watch Dashboard: What to Monitor If You Fear a Meltdown
A90: Organized by frequency: daily tradeable signals -> weekly/monthly structural -> quarterly fundamental. If 3+ red flags fire simultaneously, risk of 20%+ correction rises sharply.
A91: DAILY TRADEABLE SIGNALS (check every morning)
A92: # | B92: Indicator | C92: Where to Find | D92: Normal Range | E92: Yellow Flag | F92: Red Flag = ACT
A93: 1 | B93: NVDA stock price & volume | C93: Bloomberg/Yahoo Finance | D93: Tracks S&P; vol normal | E93: Down >5% on no news; unusual volume spike 3x+ avg | F93: Down >10% in a week on high volume = institutional exit signal
A94: 2 | B94: NVDA implied vol (30-day) | C94: CBOE VIX for NVDA options | D94: 25-35 | E94: 40-50 = hedging activity up | F94: 60+ = panic; last seen pre-earnings miss
A95: 3 | B95: VIX (S&P 500 implied vol) | C95: CBOE | D95: 12-18 | E95: 22-25 = elevated uncertainty | F95: 30+ = fear mode; 40+ = crisis
A96: 4 | B96: SOX (Phila Semi Index) | C96: Bloomberg SOX index | D96: Trend up / flat | E96: Down >8% from peak in <2 weeks | F96: Down >15% = semi cycle top signal
A97: 5 | B97: IG Credit Spreads (CDX.IG) | C97: Bloomberg / FRED | D97: 70-90bp | E97: 100-110bp | F97: 130bp+ = funding stress; hyperscaler debt cost rising
A98: 6 | B98: HY Credit Spreads | C98: Bloomberg | D98: 250-350bp | E98: 400-450bp | F98: 500bp+ = risk-off; ORCL bond spreads key
A99: 7 | B99: ORCL CDS spread | C99: Bloomberg | D99: 50-80bp | E99: 100-120bp | F99: 150bp+ = market pricing credit event risk
A100: 8 | B100: GPU secondary market prices | C100: CoreWeave, Lambda, vast.ai | D100: H100: $25-30K; stable | E100: H100 drops to $18-22K | F100: H100 below $15K = oversupply confirmed
A101: 9 | B101: AI token pricing (API) | C101: OpenAI/Anthropic pricing page | D101: Stable or slow decline | E101: Price cut >30% in one move | F101: Price war: 2+ providers cut >50% simultaneously
A102: 10 | B102: Mag-7 relative breadth | C102: Equal-weight Mag-7 vs cap-weight | D102: Spread <3% | E102: Spread >5% (1-2 names diverging) | F102: Spread >10% = leadership cracking
A104: WEEKLY / MONTHLY STRUCTURAL SIGNALS
A105: # | B105: Indicator | C105: Where to Find | D105: Normal Range | E105: Yellow Flag | F105: Red Flag = ACT
A106: 11 | B106: AI lab funding news | C106: TechCrunch / The Information / X | D106: Regular mega-rounds | E106: Round delayed >3 months; down round rumor | F106: Funding fails; valuation cut >30%; OpenAI/Anthropic layoffs
A107: 12 | B107: Hyperscaler bond issuance | C107: Bloomberg new issue monitor | D107: $5-10B/qtr normal | E107: $15B+/qtr = heavy borrowing | F107: $25B+/qtr + spread widening = desperation financing
A108: 13 | B108: Data center power permits | C108: DOE / utility filings / S&P Global | D108: Projects on track | E108: 2+ major projects delayed 6mo+ | F108: Mass cancellations; Gartner 40% constraint confirmed
A109: 14 | B109: Sell-side EPS revisions breadth | C109: FactSet / Bloomberg | D109: Net positive | E109: Breadth narrows to <+5% | F109: Turns negative = revision cycle peak
A110: 15 | B110: GSTHCAPX vs GSTHCASH basket | C110: Bloomberg baskets | D110: CAPX outperforms | E110: Gap narrows to <5pp over 3mo | F110: CASH outperforms CAPX = market rotating to quality/defense
A111: 16 | B111: Insider selling patterns | C111: SEC Form 4 / OpenInsider | D111: Normal scheduled sales | E111: Cluster selling at 2+ hyperscalers | F111: CEO/CFO selling unscheduled at 3+ names = extreme signal
A112: 17 | B112: Momentum factor (GSMEFMOM) | C112: Bloomberg | D112: Steady uptrend | E112: Reversal >5% in 2 weeks | F112: Reversal >10% = crowded trade unwinding
A114: QUARTERLY FUNDAMENTAL SIGNALS (earnings season)
A115: # | B115: Indicator | C115: Where to Find | D115: Normal Range | E115: Yellow Flag | F115: Red Flag = ACT
A116: 18 | B116: AWS / Azure / GCP YoY growth | C116: Earnings calls + 10-Q | D116: +28-40% (current) | E116: Any name <25% | F116: Any <20% or 2Q sequential decel = demand crack
A117: 19 | B117: MSFT cRPO QoQ growth | C117: MSFT earnings call | D117: +35-40% QoQ | E117: <20% | F117: <10% or turns negative = pipeline drying up
...
