Workbook

Sheet 0. Database
A1: Centralized Database (USD mm except EPS/shares) — Blue = input
A3: Ticker | B3: Metric | C3: 2013A | D3: 2014A | E3: 2015A | F3: 2016A | G3: 2017A | H3: 2018A | I3: 2019A | J3: 2020A | K3: 2021A | L3: 2022A | M3: 2023A | N3: 2024A | O3: 2025E | P3: 2026E | Q3: 2027E | R3: 2028E | S3: 2029E | T3: 2030E
A4: MSFT (FY(Jun))
A5: MSFT | B5: Revenue | C5: 77849 | D5: 86833 | E5: 93580 | F5: 91963 | G5: 96657 | H5: 110360 | I5: 125843 | J5: 143015 | K5: 168088 | L5: 198270 | M5: 211915 | N5: 245122 | O5: 281724 | P5: 329213.24 | Q5: 383408.94 | R5: 450123.14 | S5: 533860.75 | T5: 624709.64
A6: MSFT | B6: Operating Income | C6: 26764 | D6: 27759 | E6: 13359 | F6: 11756 | G6: 11389 | H6: 12924 | I6: 16219 | J6: 18724 | K6: 24351 | L6: 29687 | M6: 50074 | N6: 59661 | O6: 69773 | P6: 79541.62 | Q6: 85628.96 | R6: 69877.51 | S6: 101371.29 | T6: 108509.49
A7: MSFT | B7: Net Income | C7: 21863 | D7: 22074 | E7: 12193 | F7: 16798 | G7: 25489 | H7: 16571 | I7: 39240 | J7: 44281 | K7: 61271 | L7: 72738 | M7: 72361 | N7: 88136 | O7: 101832 | P7: 129372.86 | Q7: 144971.56 | R7: 175683.92 | S7: 215472.22 | T7: 258948.36
A8: MSFT | B8: EPS | C8: 2.58 | D8: 2.63 | E8: 1.48 | F8: 2.1 | G8: 2.71 | H8: 2.13 | I8: 5.06 | J8: 5.76 | K8: 8.05 | L8: 9.65 | M8: 9.68 | N8: 11.8 | O8: 13.64 | P8: 17.28 | Q8: 19.42 | R8: 22.81 | S8: 27 | T8: 31.49
A9: MSFT | B9: Diluted Shares (mm) | C9: 8375 | D9: 8299 | E9: 8177 | F9: 7925 | G9: 7746 | H9: 7700 | I9: 7673 | J9: 7610 | K9: 7547 | L9: 7496 | M9: 7446 | N9: 7431 | O9: 7433 | P9: 7425.9 | Q9: 7410.77 | R9: 7384.08 | S9: 7370.87 | T9: 7345.29
A10: MSFT | B10: SBC | C10: 2406 | D10: 2446 | E10: 2574 | F10: 2668 | G10: 3266 | H10: 3940 | I10: 4652 | J10: 5289 | K10: 6118 | L10: 7502 | M10: 9611 | N10: 10734 | O10: 11974 | P10: 12189 | Q10: 10478.4 | R10: 11434.24 | S10: 12826.56 | T10: 14871.62
A11: MSFT | B11: D&A | C11: 3755 | D11: 5212 | E11: 5957 | F11: 6622 | G11: 8778 | H11: 10261 | I11: 11682 | J11: 12796 | K11: 11686 | L11: 14460 | M11: 13861 | N11: 22287 | O11: 34153 | P11: 42005.11 | Q11: 55415.31 | R11: 73946.23 | S11: 97100.11 | T11: 127810.23
A12: MSFT | B12: Capex | C12: 4257 | D12: 5485 | E12: 5944 | F12: 8932 | G12: 10200 | H12: 13600 | I12: 16900 | J12: 19000 | K12: 24200 | L12: 29200 | M12: 31900 | N12: 55700 | O12: 88200 | P12: 145871.3 | Q12: 245263.45 | R12: 286760.35 | S12: 300210.91 | T12: 304616.04
A13: MSFT | B13: CFO | C13: 28833 | D13: 32231 | E13: 29080 | F13: 33325 | G13: 39507 | H13: 43884 | I13: 52185 | J13: 60675 | K13: 76740 | L13: 89035 | M13: 87582 | N13: 118548 | O13: 136162 | P13: 174558.18 | Q13: 232097.78 | R13: 294570.35 | S13: 359672.36 | T13: 438548.9
A14: MSFT | B14: FCF | C14: 24576 | D14: 26746 | E14: 23136 | F14: 24393 | G14: 29307 | H14: 30284 | I14: 35285 | J14: 41675 | K14: 52540 | L14: 59835 | M14: 55682 | N14: 62848 | O14: 47962 | P14: 28686.88 | Q14: -13165.67 | R14: 7810 | S14: 59461.45 | T14: 133932.86
A15: MSFT | B15: Buybacks | C15: 5360 | D15: 7316 | E15: 14443 | F15: 15969 | G15: 11788 | H15: 10721 | I15: 19543 | J15: 22968 | K15: 27385 | L15: 32696 | M15: 22245 | N15: 17254 | O15: 18420 | P15: 22499.7 | Q15: 19070.28 | R15: 19500.41 | S15: 20126.95 | T15: 21047.23
A16: MSFT | B16: Intell Cloud | C16: 0 | D16: 0 | E16: 0 | F16: 0 | G16: 0 | H16: 0 | I16: 0 | J16: 0 | K16: 0 | L16: 0 | M16: 72314 | N16: 87464 | O16: 106265 | P16: 136688.31 | Q16: 180358.14 | R16: 235873.55 | S16: 304531.45 | T16: 384276.13
... A18: MSFT | B18: Useful Life(yr) | C18: 3.16 | D18: 2.69 | E18: 2.81 | F18: 2.83 | G18: 2.71 | H18: 2.73 | I18: 2.74 | J18: 3.08 | K18: 4.33 | L18: 4.12 | M18: 6.1 | N18: 5.59 | O18: 5.26 | P18: 4.89 | Q18: 4.36 | R18: 4.38 | S18: 4.6 | T18: 4.7
A20: AMZN (CY)
A21: AMZN | B21: Revenue | C21: 74452 | D21: 88988 | E21: 107006 | F21: 135987 | G21: 177866 | H21: 232887 | I21: 280522 | J21: 386064 | K21: 469822 | L21: 513983 | M21: 574785 | N21: 637959 | O21: 716924 | P21: 824745.86 | Q21: 933246.82 | R21: 1035581.9 | S21: 1167156.7 | T21: 1303433.7
A22: AMZN | B22: Operating Income | C22: 673 | D22: 458 | E22: 1507 | F22: 3108 | G22: 4331 | H22: 7296 | I22: 9201 | J22: 13531 | K22: 18532 | L22: 22841 | M22: 24631 | N22: 39834 | O22: 45606 | P22: 58892.45 | Q22: 76144.3 | R22: 98372.18 | S22: 123330.71 | T22: 152115.05
A23: AMZN | B23: Net Income | C23: 273 | D23: -240.6 | E23: 596.1 | F23: 2371 | G23: 3033 | H23: 10073 | I23: 11588 | J23: 21331 | K23: 33364 | L23: -2722 | M23: 30425 | N23: 59248 | O23: 77670 | P23: 98333.72 | Q23: 116218.4 | R23: 145016.4 | S23: 177176.2 | T23: 211925.99
A24: AMZN | B24: EPS | C24: 0.03 | D24: -0.03 | E24: 0.06 | F24: 0.25 | G24: 0.23 | H24: 1.01 | I24: 1.15 | J24: 2.09 | K24: 2.33 | L24: 0.72 | M24: 2.84 | N24: 5.53 | O24: 7.17 | P24: 8.79 | Q24: 10.03 | R24: 12.92 | S24: 14.34 | T24: 17.13
A25: AMZN | B25: Diluted Shares (mm) | C25: 9140 | D25: 9240 | E25: 9340 | F25: 9480 | G25: 9600 | H25: 9740 | I25: 9880 | J25: 10000 | K25: 10120 | L25: 10189 | M25: 10304 | N25: 10473 | O25: 10656 | P25: 10862.95 | Q25: 10969.88 | R25: 11057.54 | S25: 11153.52 | T25: 11258.12
A26: AMZN | B26: SBC | C26: -1134 | D26: -1497 | E26: -2120 | F26: -2975 | G26: -4214 | H26: -5418 | I26: -6864 | J26: -9208 | K26: -12757 | L26: -19621 | M26: -24023 | N26: -22077.4 | O26: -19467 | P26: -18863.32 | Q26: -17920.15 | R26: -18816.16 | S26: -19756.97 | T26: -20744.82
A27: AMZN | B27: D&A | C27: 3253 | D27: 4746 | E27: 6281 | F27: 8116 | G27: 11478 | H27: 15341 | I27: 21789 | J27: 25180 | K27: 34433 | L27: 41921 | M27: 48663 | N27: 52795 | O27: 65756 | P27: 84391.58 | Q27: 107181.82 | R27: 131811.18 | S27: 145951.12 | T27: 164275.19
A28: AMZN | B28: Capex | C28: 3443 | D28: 4892 | E28: 4588 | F28: 6736 | G28: 10057 | H28: 11322 | I28: 12690 | J28: 35046 | K28: 55396 | L28: 58321 | M28: 48133 | N28: 77658 | O28: 128320 | P28: 200104.98 | Q28: 270141.72 | R28: 283648.81 | S28: 297831.25 | T28: 312722.81
A29: AMZN | B29: CFO | C29: 5474 | D29: 6841.4 | E29: 11920.1 | F29: 17271 | G29: 18434 | H29: 30724 | I29: 38515 | J29: 66064 | K29: 46327 | L29: 46752 | M29: 84946 | N29: 115877 | O29: 139514 | P29: 181004.31 | Q29: 224443.7 | R29: 281471.71 | S29: 342814.42 | T29: 401080.41
A30: AMZN | B30: FCF | C30: 2031 | D30: 1949.4 | E30: 7332.1 | F30: 10535 | G30: 8377 | H30: 19402 | I30: 25825 | J30: 31018 | K30: -9069 | L30: -11569 | M30: 36813 | N30: 38219 | O30: 11194 | P30: -19100.67 | Q30: -45698.02 | R30: -2177.1 | S30: 44983.17 | T30: 88357.6
A31: AMZN | B31: Buybacks | C31: 0 | D31: 0 | E31: 0 | F31: 0 | G31: 0 | H31: 0 | I31: 0 | J31: 0 | K31: 0 | L31: 6000 | M31: 0 | N31: 0 | O31: 0 | P31: 0 | Q31: 0 | R31: 0 | S31: 0 | T31: 0
A32: AMZN | B32: AWS Rev | C32: 3107.57 | D32: 4644 | E32: 7880 | F32: 12219 | G32: 17458 | H32: 25656 | I32: 35026 | J32: 45370 | K32: 62202 | L32: 80096 | M32: 90757 | N32: 107556 | O32: 128725 | P32: 171284.9 | Q32: 225587.94 | R32: 274421.67 | S32: 323817.58 | T32: 374009.3
A33: AMZN | B33: AWS OI | D33: 458 | E33: 1508 | F33: 3109 | G33: 4331 | H33: 7296 | I33: 9201 | J33: 13531 | K33: 18532 | L33: 22841 | M33: 24631 | N33: 39834 | O33: 45606 | P33: 61254.41 | Q33: 81248.3 | R33: 100888.47 | S33: 121477.03 | T33: 143111.04
A35: GOOGL (CY)
A36: GOOGL | B36: Revenue | C36: 55519 | D36: 66001 | E36: 74989 | F36: 90272 | G36: 110855 | H36: 136819 | I36: 161857 | J36: 182527 | K36: 257637 | L36: 282836 | M36: 307394 | N36: 350018 | O36: 402836 | P36: 486455.79 | Q36: 578508.88 | R36: 684008.77 | S36: 805409.01 | T36: 941245.16
A37: GOOGL | B37: Operating Income | C37: 16260 | D37: 18965 | E37: 23319 | F37: 27055 | G37: 32456 | H37: 43137 | I37: 48999 | J37: 54606 | K37: 91855 | L37: 82699 | M37: 95858 | N37: 121263 | O37: 139404 | P37: 166048.71 | Q37: 188404.24 | R37: 207483.23 | S37: 229196.58 | T37: 258679.36
A38: GOOGL | B38: Net Income | C38: 12720 | D38: 14136 | E38: 16348 | F38: 19478 | G38: 12662 | H38: 30736 | I38: 34343 | J38: 40269 | K38: 76033 | L38: 59972 | M38: 73795 | N38: 100118 | O38: 132170 | P38: 168543.28 | Q38: 174626.97 | R38: 210753.44 | S38: 249488.6 | T38: 285975.76
A39: GOOGL | B39: EPS | C39: 0.9 | D39: 1.01 | E39: 1.14 | F39: 1.39 | G39: 1.6 | H39: 2.19 | I39: 2.33 | J39: 2.93 | K39: 5.61 | L39: 4.56 | M39: 5.8 | N39: 8.04 | O39: 10.81 | P39: 14.19 | Q39: 14.69 | R39: 17.35 | S39: 21.25 | T39: 26.04
A40: GOOGL | B40: Diluted Shares (mm) | C40: 13313.88 | D40: 13518.7 | E40: 13692.52 | F40: 13842.18 | G40: 13858.02 | H40: 13902.8 | I40: 13851.92 | J40: 13616.32 | K40: 13353 | L40: 13063 | M40: 12630 | N40: 12319 | O40: 12116 | P40: 12096.35 | Q40: 12055.53 | R40: 12150.69 | S40: 12227.42 | T40: 12193.09
A41: GOOGL | B41: SBC | C41: -3268 | D41: -4175 | E41: -4903 | F41: -6703 | G41: -7679 | H41: -9353 | I41: -10794 | J41: -12991 | K41: -15376 | L41: -19362 | M41: -22460 | N41: -22785 | O41: -24953 | P41: -27937.33 | Q41: -30032.63 | R41: -31979.73 | S41: -33657.1 | T41: -35339.95
A42: GOOGL | B42: D&A | C42: 2781 | D42: 3523 | E42: 4132 | F42: 5267 | G42: 6103 | H42: 8164 | I42: 10856 | J42: 12905 | K42: 11555 | L42: 15287 | M42: 13326 | N42: 15311 | O42: 21136 | P42: 42874.7 | Q42: 69582.72 | R42: 98340.16 | S42: 127674.93 | T42: 156155.17
A43: GOOGL | B43: Capex | C43: 7358 | D43: 10959 | E43: 9915 | F43: 10183 | G43: 13184 | H43: 25139 | I43: 23548 | J43: 22281 | K43: 24640 | L43: 31485 | M43: 32251 | N43: 52535 | O43: 91447 | P43: 185234.28 | Q43: 259327.99 | R43: 285260.79 | S43: 299523.83 | T43: 314500.02
A44: GOOGL | B44: CFO | C44: 18584 | D44: 22272 | E44: 25829 | F44: 36036 | G44: 37091 | H44: 47971 | I44: 54520 | J44: 65124 | K44: 91652 | L44: 91495 | M44: 101746 | N44: 125299 | O44: 164713 | P44: 211985.47 | Q44: 282346.21 | R44: 352943.8 | S44: 424226.82 | T44: 490867.35
A45: GOOGL | B45: FCF | C45: 11226 | D45: 11313 | E45: 15914 | F45: 25853 | G45: 23907 | H45: 22832 | I45: 30972 | J45: 42843 | K45: 67012 | L45: 60010 | M45: 69495 | N45: 72764 | O45: 73266 | P45: 26751.19 | Q45: 23018.22 | R45: 67683.01 | S45: 124702.99 | T45: 176367.33
A46: GOOGL | B46: Buybacks | C46: 0 | D46: 0 | E46: 1827 | F46: 3693 | G46: 4846 | H46: 9075 | I46: 18396 | J46: 31149 | K46: 50274 | L46: 59296 | M46: 61504 | N46: 62222 | O46: 45709 | P46: 0 | Q46: 20000 | R46: 20000 | S46: 20000 | T46: 15000
A47: GOOGL | B47: Cloud Rev | G47: 4056 | H47: 5838 | I47: 8918 | J47: 13059 | K47: 19206 | L47: 26280 | M47: 33088 | N47: 43229 | O47: 58705 | P47: 99085.93 | Q47: 157303.91 | R47: 220225.47 | S47: 286293.12 | T47: 343551.74
A48: GOOGL | B48: Search Rev | G48: 69811 | H48: 85296 | I48: 98115 | J48: 104062 | K48: 148951 | L48: 162450 | M48: 175033 | N48: 198084 | O48: 224532 | P48: 258723.55 | Q48: 291360.5 | R48: 324483.39 | S48: 358139.29 | T48: 392613.71
A49: GOOGL | B49: YouTube Rev | G49: 8150 | H49: 11115 | I49: 15149 | J49: 19772 | K49: 28845 | L49: 29243 | M49: 31510 | N49: 36147 | O49: 40367 | P49: 43997.73 | Q49: 49277.45 | R49: 54574.78 | S49: 59759.38 | T49: 64838.93
A50: GOOGL | B50: GCloud OI | H50: -4348 | I50: -4645 | J50: -5607 | K50: -2282 | L50: -1922 | M50: 1716 | N50: 6112 | O50: 13910 | P50: 32420.97 | Q50: 57771.82 | R50: 85285.05 | S50: 113733.5 | T50: 138713.29
A52: META (CY)
A53: META | B53: Revenue | C53: 7872 | D53: 12466 | E53: 17928 | F53: 27638 | G53: 40653 | H53: 55838 | I53: 70697 | J53: 85965 | K53: 117929 | L53: 116609 | M53: 134902 | N53: 164501 | O53: 200966 | P53: 252898.15 | Q53: 301231.94 | R53: 352191.64 | S53: 403671.7 | T53: 456699.5
A54: META | B54: Operating Income | C54: 2804 | D54: 4994.8 | E54: 6225 | F54: 12427 | G54: 20202 | H54: 24913 | I54: 28489 | J54: 39294 | K54: 56946 | L54: 42661 | M54: 62871 | N54: 87109 | O54: 102469 | P54: 107256.35 | Q54: 123332.59 | R54: 142728 | S54: 179457.68 | T54: 192345.26
A55: META | B55: Net Income | C55: 1491 | D55: 2924.8 | E55: 3669 | F55: 10187.2 | G55: 15919 | H55: 22112 | I55: 18484.5 | J55: 29145 | K55: 39370 | L55: 23199 | M55: 39097 | N55: 62360 | O55: 60458 | P55: 85782.86 | Q55: 91160.94 | R55: 103452.71 | S55: 115846.5 | T55: 127804.37
A56: META | B56: EPS | C56: 0.6 | D56: 1.1 | E56: 1.29 | F56: 3.49 | G56: 6.16 | H56: 7.57 | I56: 8.56 | J56: 9.78 | K56: 13.77 | L56: 8.59 | M56: 14.87 | N56: 23.86 | O56: 23.49 | P56: 32.2 | Q56: 34.9 | R56: 40.5 | S56: 48.62 | T56: 57
A57: META | B57: Diluted Shares (mm) | C57: 2420 | D57: 2614 | E57: 2803 | F57: 2863 | G57: 2901 | H57: 2890 | I57: 2854 | J57: 2851 | K57: 2815 | L57: 2687 | M57: 2574 | N57: 2534 | O57: 2521 | P57: 2541.31 | Q57: 2546.74 | R57: 2570.97 | S57: 2587.5 | T57: 2579.74
A58: META | B58: SBC | C58: -906 | D58: -1837 | E58: -2969 | F58: -3202 | G58: -3723 | H58: -4152 | I58: -4835 | J58: -6536 | K58: -9163 | L58: -11991 | M58: -14027 | N58: -16690 | O58: -20426 | P58: -23722.2 | Q58: -24908.31 | R58: -26153.73 | S58: -27461.41 | T58: -28834.48
A59: META | B59: D&A | C59: 1011 | D59: 1243 | E59: 1945 | F59: 2342 | G59: 3025 | H59: 4315 | I59: 5741 | J59: 6862 | K59: 7967 | L59: 8686 | M59: 11178 | N59: 15498 | O59: 18616 | P59: 29596.55 | Q59: 43105.48 | R59: 57217.37 | S59: 74363.38 | T59: 87724.37
A60: META | B60: Capex | C60: 1362 | D60: 1831 | E60: 2523 | F60: 4491 | G60: 6732 | H60: 13980 | I60: 15102 | J60: 15115 | K60: 18567 | L60: 31186 | M60: 27045 | N60: 37256 | O60: 69691 | P60: 135583.71 | Q60: 165714.44 | R60: 185600.17 | S60: 196736.18 | T60: 208540.35
A61: META | B61: CFO | C61: 4222 | D61: 5507.8 | E61: 8607 | F61: 16061 | G61: 24216 | H61: 29339 | I61: 36312.5 | J61: 38747 | K61: 57683 | L61: 50475 | M61: 71113 | N61: 91328 | O61: 115800 | P61: 180250.64 | Q61: 206102.96 | R61: 243250.01 | S61: 279015.98 | T61: 314478.51
A62: META | B62: FCF | C62: 2860 | D62: 3676.8 | E62: 6084 | F62: 11570 | G62: 17484 | H62: 15359 | I62: 21210.5 | J62: 23632 | K62: 39116 | L62: 19289 | M62: 44068 | N62: 54072 | O62: 46109 | P62: 44666.93 | Q62: 40388.52 | R62: 57649.84 | S62: 82279.8 | T62: 105938.16
A63: META | B63: Buybacks | C63: 0 | D63: 0 | E63: 0 | F63: 0 | G63: 1976 | H63: 12879 | I63: 4201 | J63: 6272 | K63: 44538 | L63: 27956 | M63: 19775 | N63: 30125 | O63: 26248 | P63: 0 | Q63: 6000 | R63: 6000 | S63: 6000 | T63: 6000
A64: META | B64: Ad Rev(META) | C64: 6986 | D64: 11492 | E64: 17080 | F64: 26885 | G64: 39942 | H64: 55012 | I64: 69654.5 | J64: 84169 | K64: 114934 | L64: 113641 | M64: 131948 | N64: 160632 | O64: 196174 | P64: 248664.66 | Q64: 298597.44 | R64: 348271.65 | S64: 397194.59 | T64: 444912.31
A65: META | B65: FOA Rev | I65: 70196 | J65: 84826 | K65: 115655 | L65: 114450 | M65: 133005 | N65: 162354 | O65: 198758 | P65: 252529.81 | Q65: 303235.62 | R65: 353605.56 | S65: 403061.89 | T65: 451366.33
A66: META | B66: FOA OI | I66: 28489 | J66: 39294 | K66: 56947 | L66: 42662 | M66: 62870 | N66: 87109 | O66: 102469 | P66: 109500.79 | Q66: 122498.06 | R66: 135570.51 | S66: 147823.31 | T66: 158299.25
A67: META | B67: RL Rev | I67: 501 | J67: 1139 | K67: 2274 | L67: 2159 | M67: 1896 | N67: 2146 | O67: 2207 | P67: 2645.75 | Q67: 3174.9 | R67: 3730.51 | S67: 4290.08 | T67: 4826.34
A68: META | B68: RL OI | I68: -4503 | J68: -6623 | K68: -10194 | L68: -13717 | M68: -16119 | N68: -17729 | O68: -19193 | P68: -19011 | Q68: -18060.45 | R68: -17157.43 | S68: -16299.56 | T68: -15484.58
A70: ORCL (FY(May))
A71: ORCL | B71: Revenue | C71: 37253 | D71: 38306 | E71: 38253 | F71: 37057 | G71: 37899 | H71: 39878 | I71: 39526 | J71: 39068 | K71: 40481 | L71: 42440 | M71: 49954 | N71: 52961 | O71: 57399 | P71: 67256.59 | Q71: 89106.44 | R71: 130482.44 | S71: 183189.61 | T71: 223043.24
A72: ORCL | B72: Operating Income | C72: 14684 | D72: 14758 | E72: 13870 | F72: 12604 | G72: 12710 | H72: 13264 | I72: 13535 | J72: 13897 | K72: 15214 | L72: 10927 | M72: 13094 | N72: 15354 | O72: 17678 | P72: 19462.44 | Q72: 21128.19 | R72: 36930.86 | S72: 53057.71 | T72: 57952.82
A73: ORCL | B73: Net Income | C73: 10926 | D73: 10955 | E73: 9938 | F73: 8900 | G73: 9334 | H73: 3587 | I73: 11083 | J73: 10135 | K73: 13747 | L73: 6718 | M73: 8504 | N73: 10467 | O73: 12443 | P73: 15820.55 | Q73: 13363.1 | R73: 26776.66 | S73: 39834.82 | T73: 44104.48
A74: ORCL | B74: EPS | C74: 2.26 | D74: 2.38 | E74: 2.21 | F74: 2.07 | G74: 2.21 | H74: 0.9 | I74: 2.97 | J74: 3.08 | K74: 4.55 | L74: 2.41 | M74: 3.07 | N74: 3.71 | O74: 4.34 | P74: 5.85 | Q74: 6.26 | R74: 8.79 | S74: 12.89 | T74: 16.76
A75: ORCL | B75: Diluted Shares (mm) | C75: 4769 | D75: 4528 | E75: 4404 | F75: 4221 | G75: 4115 | H75: 4121 | I75: 3634 | J75: 3211 | K75: 2945 | L75: 2700 | M75: 2696 | N75: 2744 | O75: 2789 | P75: 2864.8 | Q75: 2932.9 | R75: 2976.37 | S75: 3004.08 | T75: 3041.61
A76: ORCL | B76: SBC | C76: 755 | D76: 805 | E76: 933 | F76: 1037 | G76: 1350 | H76: 1607 | I76: 1653 | J76: 1590 | K76: 1837 | L76: 2613 | M76: 3547 | N76: 3974 | O76: 4674 | P76: 5069.6 | Q76: 6473.15 | R76: 8609.75 | S76: 10649.61 | T76: 11212.32
A77: ORCL | B77: D&A | C77: 2931 | D77: 2908 | E77: 2861 | F77: 2509 | G77: 2451 | H77: 2785 | I77: 2919 | J77: 2968 | K77: 2916 | L77: 3122 | M77: 6108 | N77: 6139 | O77: 6174 | P77: 9142.32 | Q77: 13499.83 | R77: 21615.57 | S77: 30404.77 | T77: 37972.18
A78: ORCL | B78: Capex | C78: 650 | D78: 580 | E78: 1391 | F78: 1189 | G78: 2021 | H78: 1736 | I78: 1660 | J78: 1564 | K78: 2135 | L78: 4511 | M78: 8695 | N78: 6866 | O78: 21215 | P78: 51882 | Q78: 52141.41 | R78: 69869.49 | S78: 81048.61 | T78: 66459.86
A79: ORCL | B79: CFO | C79: 14225 | D79: 14921 | E79: 14336 | F79: 13560 | G79: 14125 | H79: 15386 | I79: 14551 | J79: 13139 | K79: 15888 | L79: 9540 | M79: 17166 | N79: 18673 | O79: 20821 | P79: 25457.17 | Q79: 33694.38 | R79: 50132.95 | S79: 66529.01 | T79: 84964.12
A80: ORCL | B80: FCF | C80: 13575 | D80: 14341 | E80: 12945 | F80: 12371 | G80: 12104 | H80: 13650 | I80: 12891 | J80: 11575 | K80: 13753 | L80: 5029 | M80: 8471 | N80: 11807 | O80: -394 | P80: -26424.83 | Q80: -18447.03 | R80: -19736.54 | S80: -14519.6 | T80: 18504.26
A81: ORCL | B81: Buybacks | C81: 11021 | D81: 9813 | E81: 8087 | F81: 10440 | G81: 3561 | H81: 11347 | I81: 36140 | J81: 19240 | K81: 20934 | L81: 16248 | M81: 1300 | N81: 1202 | O81: 600 | P81: 95 | Q81: 0 | R81: 0 | S81: 0 | T81: 0
A82: ORCL | B82: CloudTotalRevenue(ORCL) | C82: 1365 | D82: 38306 | E82: 38253 | F82: 37057 | G82: 37899 | H82: 39878 | I82: 39526 | J82: 39068 | K82: 40481 | L82: 42440 | M82: 49954 | N82: 52961 | O82: 57399 | P82: 67256.59 | Q82: 89106.44 | R82: 130482.44 | S82: 183189.61 | T82: 223043.24
A83: ORCL | B83: IaaS Rev | L83: 2760.74 | M83: 4500 | N83: 6800 | O83: 10234 | P83: 18064.4 | Q83: 37935.24 | R83: 72977.07 | S83: 111105.3 | T83: 129847.66
A84: ORCL | B84: SaaS Rev | L84: 7999.33 | M84: 11400 | N84: 12949 | O84: 14272 | P84: 15955.84 | Q84: 17656.52 | R84: 19374.2 | S84: 21109.07 | T84: 22861.28
A85: ORCL | B85: RPO | I85: 36200 | J85: 37000 | K85: 41300 | L85: 46600 | M85: 67900 | N85: 98000 | O85: 138000
A86: ORCL | B86: Operating Income(Adjusted) | C86: 17612 | D86: 18108 | E86: 17396 | F86: 15785 | G86: 16168 | H86: 17155 | I86: 17384 | J86: 17383 | K86: 19000 | L86: 19592 | M86: 20904 | N86: 23054 | O86: 25034 | P86: 28113.04 | Q86: 28489.16 | R86: 46280.73 | S86: 64368.1 | T86: 69758.92
A87: ORCL | B87: EPS(Adjusted) | C87: 2.68 | D87: 2.38 | E87: 2.21 | F87: 2.07 | G87: 2.21 | H87: 0.9 | I87: 2.97 | J87: 3.08 | K87: 4.55 | L87: 2.41 | M87: 3.07 | N87: 3.71 | O87: 4.34 | P87: 5.85 | Q87: 6.26 | R87: 8.79 | S87: 12.89 | T87: 16.76
A89: NVDA (FY Jan)
A90: NVDA | B90: Revenue | D90: 4130.16 | E90: 4681.51 | F90: 5010 | G90: 6910 | H90: 9714 | I90: 11716 | J90: 10918 | K90: 16675 | L90: 26914 | M90: 26974 | N90: 60922 | O90: 130497 | P90: 215938 | Q90: 379513.47 | R90: 519798.97 | S90: 625601.86 | T90: 664318.86
A91: NVDA | B91: Operating Income | J91: 751 | K91: 2548 | L91: 4598 | M91: 5083 | N91: 32016 | O91: 82875 | P91: 130141 | Q91: 245259.44 | R91: 309757.26 | S91: 392712.72 | T91: 481971.82
A92: NVDA | B92: D&A
A93: NVDA | B93: EPS | D93: 0.02 | E93: 0.03 | F93: 0.03 | G93: 0.06 | H93: 0.12 | I93: 0.17 | J93: 0.11 | K93: 0.17 | L93: 0.39 | M93: 0.17 | N93: 1.19 | O93: 2.94 | P93: 4.9 | Q93: 8.97 | R93: 12.06 | S93: 14.09 | T93: 15.84
A94: NVDA | B94: Diluted Shares (mm) | D94: 23520 | E94: 22080 | F94: 21720 | G94: 21640 | H94: 23960 | I94: 24320 | J94: 24390 | K94: 24670 | L94: 24960 | M94: 24870 | N94: 24690 | O94: 24555 | P94: 24359 | Q94: 24298.14 | R94: 24143.46 | S94: 23883.77 | T94: 16685.95
A95: NVDA | B95: Free Cash Flow | D95: 580 | E95: 784 | F95: 1089 | G95: 1496 | H95: 2909 | I95: 3143 | J95: 4272 | K95: 4694 | L95: 8132 | M95: 3808 | N95: 27021 | O95: 60853 | P95: 96676 | Q95: 196546.7 | R95: 268143.94 | S95: 304204.5 | T95: 297544.37
A97: MU (FY Aug)
A98: MU | B98: Revenue | C98: 9073 | D98: 16358 | E98: 16192 | F98: 12399 | G98: 20322 | H98: 30391 | I98: 23406 | J98: 21435 | K98: 27705 | L98: 30758 | M98: 15540 | N98: 25111 | O98: 37378 | P98: 110164.58 | Q98: 178992.05 | R98: 173460.16 | S98: 171120 | T98: 170949
A99: MU | B99: D&A | C99: 1804 | D99: 2103 | E99: 2667 | F99: 2980 | G99: 3861 | H99: 4759 | I99: 5424 | J99: 5650 | K99: 6214 | L99: 7116 | M99: 7756 | N99: 7780 | O99: 8352 | P99: 9862.13 | Q99: 12539.03 | R99: 16162.36 | S99: 21543.79 | T99: 27453.5
A100: MU | B100: EPS | C100: 1.13 | D100: 2.54 | E100: 2.47 | F100: -0.27 | G100: 4.41 | H100: 11.51 | I100: 5.51 | J100: 2.37 | K100: 5.14 | L100: 7.75 | M100: -5.34 | N100: 0.7 | O100: 7.59 | P100: 58.9 | Q100: 102.73 | R100: 96.36 | S100: 89.91 | T100: 62.55
A101: MU | B101: Diluted Shares (mm) | C101: 1022 | D101: 1060 | E101: 1070 | F101: 1036 | G101: 1089 | H101: 1152 | I101: 1114 | J101: 1110 | K101: 1120 | L101: 1112 | M101: 1093 | N101: 1105 | O101: 1116 | P101: 1131.87 | Q101: 1131.16 | R101: 1126.9 | S101: 847.04 | T101: 740.81

Sheet 1. Summary
B2: AI Capex Cycle: Hyperscaler Deep-Dive (2013-2030)
B3: MSFT | AMZN | GOOGL | META | ORCL + S&P 500 AI EPS Decomposition
B5: CONTENTS
B6: 0. Database — 2013-2030 centralized data. Blue=input. All other sheets reference this.
B7: 1. Summary — This page
B8: 2. Revenue — Total rev, YoY%, Cloud/AI proxy. Derived metrics reference SAME sheet cells (black font).
B9: 3. Capex & D&A — Capex, Capex/Rev, D&A, D&A/Rev. Local formulas reference raw data on same sheet.
B10: 4. FCF & Cash — CFO, FCF margin, FCF/NI, Capex/CFO. All ratios use same-sheet references.
B11: 5. EPS & Margins — OpMargin, Net Margin, EPSYoY. Same-sheet referencing pattern.
B12: 6. Burry Sensitivity — GPU life compression on 2026E EPS. Editable tax rate assumptions.
B13: 7. S&P 500 AI EPS Split — AI vs Non-AI EPS decomposition + dual P/E valuation + 4 stress scenarios.
B14: 8. Charts — 6 visualizations (Capex/Rev, Free Cash FlowMargin, Capex absolute, Rev YoY, OpMargin, D&A/Rev).

Sheet 2. Revenue & Growth
A1: Revenue&AI/CloudSegment Detail (2013-2030E)
A3: A. Total Revenue ($mm)
A4: Company | B4: 2013A | C4: 2014A | D4: 2015A | E4: 2016A | F4: 2017A | G4: 2018A | H4: 2019A | I4: 2020A | J4: 2021A | K4: 2022A | L4: 2023A | M4: 2024A | N4: 2025E | O4: 2026E | P4: 2027E | Q4: 2028E | R4: 2029E | S4: 2030E
A5: MSFT | B5: ='0. Database'!C5 -> 77849 | C5: ='0. Database'!D5 -> 86833 | D5: ='0. Database'!E5 -> 93580 | E5: ='0. Database'!F5 -> 91963 | F5: ='0. Database'!G5 -> 96657 | G5: ='0. Database'!H5 -> 110360 | H5: ='0. Database'!I5 -> 125843 | I5: ='0. Database'!J5 -> 143015 | ... S5: ='0. Database'!T5 -> 624709.64
A6: AMZN | B6: ='0. Database'!C21 -> 74452 | C6: ='0. Database'!D21 -> 88988 | D6: ='0. Database'!E21 -> 107006 | E6: ='0. Database'!F21 -> 135987 | F6: ='0. Database'!G21 -> 177866 | G6: ='0. Database'!H21 -> 232887 | H6: ='0. Database'!I21 -> 280522 | I6: ='0. Database'!J21 -> 386064 | ... S6: ='0. Database'!T21 -> 1303433.7
A7: GOOGL | B7: ='0. Database'!C36 -> 55519 | C7: ='0. Database'!D36 -> 66001 | D7: ='0. Database'!E36 -> 74989 | E7: ='0. Database'!F36 -> 90272 | F7: ='0. Database'!G36 -> 110855 | G7: ='0. Database'!H36 -> 136819 | H7: ='0. Database'!I36 -> 161857 | I7: ='0. Database'!J36 -> 182527 | ... S7: ='0. Database'!T36 -> 941245.16
A8: META | B8: ='0. Database'!C53 -> 7872 | C8: ='0. Database'!D53 -> 12466 | D8: ='0. Database'!E53 -> 17928 | E8: ='0. Database'!F53 -> 27638 | F8: ='0. Database'!G53 -> 40653 | G8: ='0. Database'!H53 -> 55838 | H8: ='0. Database'!I53 -> 70697 | I8: ='0. Database'!J53 -> 85965 | ... S8: ='0. Database'!T53 -> 456699.5
A9: ORCL | B9: ='0. Database'!C71 -> 37253 | C9: ='0. Database'!D71 -> 38306 | D9: ='0. Database'!E71 -> 38253 | E9: ='0. Database'!F71 -> 37057 | F9: ='0. Database'!G71 -> 37899 | G9: ='0. Database'!H71 -> 39878 | H9: ='0. Database'!I71 -> 39526 | I9: ='0. Database'!J71 -> 39068 | ... S9: ='0. Database'!T71 -> 223043.24
A11: C. Cloud / AI Proxy Revenue ($mm)
A12: Company | B12: 2013A | C12: 2014A | D12: 2015A | E12: 2016A | F12: 2017A | G12: 2018A | H12: 2019A | I12: 2020A | J12: 2021A | K12: 2022A | L12: 2023A | M12: 2024A | N12: 2025E | O12: 2026E | P12: 2027E | Q12: 2028E | R12: 2029E | S12: 2030E
A13: MSFT — Azure
A14: AMZN — AWS | B14: ='0. Database'!C32 -> 3107.57 | C14: ='0. Database'!D32 -> 4644 | D14: ='0. Database'!E32 -> 7880 | E14: ='0. Database'!F32 -> 12219 | F14: ='0. Database'!G32 -> 17458 | G14: ='0. Database'!H32 -> 25656 | H14: ='0. Database'!I32 -> 35026 | I14: ='0. Database'!J32 -> 45370 | ... S14: ='0. Database'!T32 -> 374009.3
A15: GOOGL — Cloud | B15: ='0. Database'!C47 -> 0 | C15: ='0. Database'!D47 -> 0 | D15: ='0. Database'!E47 -> 0 | E15: ='0. Database'!F47 -> 0 | F15: ='0. Database'!G47 -> 4056 | G15: ='0. Database'!H47 -> 5838 | H15: ='0. Database'!I47 -> 8918 | I15: ='0. Database'!J47 -> 13059 | ... S15: ='0. Database'!T47 -> 343551.74
A16: META — Advertising | B16: ='0. Database'!C64 -> 6986 | C16: ='0. Database'!D64 -> 11492 | D16: ='0. Database'!E64 -> 17080 | E16: ='0. Database'!F64 -> 26885 | F16: ='0. Database'!G64 -> 39942 | G16: ='0. Database'!H64 -> 55012 | H16: ='0. Database'!I64 -> 69654.5 | I16: ='0. Database'!J64 -> 84169 | ... S16: ='0. Database'!T64 -> 444912.31
A17: ORCL — CloudTotalRevenue | B17: ='0. Database'!C82 -> 1365 | C17: ='0. Database'!D82 -> 38306 | D17: ='0. Database'!E82 -> 38253 | E17: ='0. Database'!F82 -> 37057 | F17: ='0. Database'!G82 -> 37899 | G17: ='0. Database'!H82 -> 39878 | H17: ='0. Database'!I82 -> 39526 | I17: ='0. Database'!J82 -> 39068 | ... S17: ='0. Database'!T82 -> 223043.24
A19: B. Revenue YoY %
A20: Company | B20: 2013A | C20: 2014A | D20: 2015A | E20: 2016A | F20: 2017A | G20: 2018A | H20: 2019A | I20: 2020A | J20: 2021A | K20: 2022A | L20: 2023A | M20: 2024A | N20: 2025E | O20: 2026E | P20: 2027E | Q20: 2028E | R20: 2029E | S20: 2030E
A21: MSFT | C21: =IFERROR(C5/B5-1,"") -> 0.1154029 | D21: =IFERROR(D5/C5-1,"") -> 0.077700874 | E21: =IFERROR(E5/D5-1,"") -> -0.017279333 | F21: =IFERROR(F5/E5-1,"") -> 0.051042267 | G21: =IFERROR(G5/F5-1,"") -> 0.14176935 | H21: =IFERROR(H5/G5-1,"") -> 0.1402954 | I21: =IFERROR(I5/H5-1,"") -> 0.13645574 | J21: =IFERROR(J5/I5-1,"") -> 0.17531727 | ... S21: =IFERROR(S5/R5-1,"") -> 0.17017338
A22: AMZN | C22: =IFERROR(C6/B6-1,"") -> 0.19523989 | D22: =IFERROR(D6/C6-1,"") -> 0.20247674 | E22: =IFERROR(E6/D6-1,"") -> 0.27083528 | F22: =IFERROR(F6/E6-1,"") -> 0.30796326 | G22: =IFERROR(G6/F6-1,"") -> 0.30933962 | H22: =IFERROR(H6/G6-1,"") -> 0.20454126 | I22: =IFERROR(I6/H6-1,"") -> 0.37623431 | J22: =IFERROR(J6/I6-1,"") -> 0.21695367 | ... S22: =IFERROR(S6/R6-1,"") -> 0.11675976
A23: GOOGL | C23: =IFERROR(C7/B7-1,"") -> 0.18880023 | D23: =IFERROR(D7/C7-1,"") -> 0.13617975 | E23: =IFERROR(E7/D7-1,"") -> 0.20380322 | F23: =IFERROR(F7/E7-1,"") -> 0.2280109 | G23: =IFERROR(G7/F7-1,"") -> 0.23421587 | H23: =IFERROR(H7/G7-1,"") -> 0.1830009 | I23: =IFERROR(I7/H7-1,"") -> 0.12770532 | J23: =IFERROR(J7/I7-1,"") -> 0.41150076 | ... S23: =IFERROR(S7/R7-1,"") -> 0.16865487
A24: META | C24: =IFERROR(C8/B8-1,"") -> 0.5835874 | D24: =IFERROR(D8/C8-1,"") -> 0.43815177 | E24: =IFERROR(E8/D8-1,"") -> 0.54161089 | F24: =IFERROR(F8/E8-1,"") -> 0.47090962 | G24: =IFERROR(G8/F8-1,"") -> 0.37352717 | H24: =IFERROR(H8/G8-1,"") -> 0.2661091 | I24: =IFERROR(I8/H8-1,"") -> 0.2159639 | J24: =IFERROR(J8/I8-1,"") -> 0.37182574 | ... S24: =IFERROR(S8/R8-1,"") -> 0.13136368
A25: ORCL | C25: =IFERROR(C9/B9-1,"") -> 0.02826618 | D25: =IFERROR(D9/C9-1,"") -> -0.0013835953 | E25: =IFERROR(E9/D9-1,"") -> -0.031265522 | F25: =IFERROR(F9/E9-1,"") -> 0.022721753 | G25: =IFERROR(G9/F9-1,"") -> 0.052217737 | H25: =IFERROR(H9/G9-1,"") -> -0.0088269221 | I25: =IFERROR(I9/H9-1,"") -> -0.01158731 | J25: =IFERROR(J9/I9-1,"") -> 0.036167708 | ... S25: =IFERROR(S9/R9-1,"") -> 0.21755399

Sheet 3. Capex & D&A
A1: Capex&D&A (2013-2030E)
A3: A. Capex ($mm)
A4: Company | B4: 2013A | C4: 2014A | D4: 2015A | E4: 2016A | F4: 2017A | G4: 2018A | H4: 2019A | I4: 2020A | J4: 2021A | K4: 2022A | L4: 2023A | M4: 2024A | N4: 2025E | O4: 2026E | P4: 2027E | Q4: 2028E | R4: 2029E | S4: 2030E
A5: MSFT | B5: ='0. Database'!C12 -> 4257 | C5: ='0. Database'!D12 -> 5485 | D5: ='0. Database'!E12 -> 5944 | E5: ='0. Database'!F12 -> 8932 | F5: ='0. Database'!G12 -> 10200 | G5: ='0. Database'!H12 -> 13600 | H5: ='0. Database'!I12 -> 16900 | I5: ='0. Database'!J12 -> 19000 | ... S5: ='0. Database'!T12 -> 304616.04
A6: AMZN | B6: ='0. Database'!C28 -> 3443 | C6: ='0. Database'!D28 -> 4892 | D6: ='0. Database'!E28 -> 4588 | E6: ='0. Database'!F28 -> 6736 | F6: ='0. Database'!G28 -> 10057 | G6: ='0. Database'!H28 -> 11322 | H6: ='0. Database'!I28 -> 12690 | I6: ='0. Database'!J28 -> 35046 | ... S6: ='0. Database'!T28 -> 312722.81
A7: GOOGL | B7: ='0. Database'!C43 -> 7358 | C7: ='0. Database'!D43 -> 10959 | D7: ='0. Database'!E43 -> 9915 | E7: ='0. Database'!F43 -> 10183 | F7: ='0. Database'!G43 -> 13184 | G7: ='0. Database'!H43 -> 25139 | H7: ='0. Database'!I43 -> 23548 | I7: ='0. Database'!J43 -> 22281 | ... S7: ='0. Database'!T43 -> 314500.02
A8: META | B8: ='0. Database'!C60 -> 1362 | C8: ='0. Database'!D60 -> 1831 | D8: ='0. Database'!E60 -> 2523 | E8: ='0. Database'!F60 -> 4491 | F8: ='0. Database'!G60 -> 6732 | G8: ='0. Database'!H60 -> 13980 | H8: ='0. Database'!I60 -> 15102 | I8: ='0. Database'!J60 -> 15115 | ... S8: ='0. Database'!T60 -> 208540.35
A9: ORCL | B9: ='0. Database'!C78 -> 650 | C9: ='0. Database'!D78 -> 580 | D9: ='0. Database'!E78 -> 1391 | E9: ='0. Database'!F78 -> 1189 | F9: ='0. Database'!G78 -> 2021 | G9: ='0. Database'!H78 -> 1736 | H9: ='0. Database'!I78 -> 1660 | I9: ='0. Database'!J78 -> 1564 | ... S9: ='0. Database'!T78 -> 66459.86
A11: D. D&A ($mm)
A12: Company | B12: 2013A | C12: 2014A | D12: 2015A | E12: 2016A | F12: 2017A | G12: 2018A | H12: 2019A | I12: 2020A | J12: 2021A | K12: 2022A | L12: 2023A | M12: 2024A | N12: 2025E | O12: 2026E | P12: 2027E | Q12: 2028E | R12: 2029E | S12: 2030E
A13: MSFT | B13: ='0. Database'!C11 -> 3755 | C13: ='0. Database'!D11 -> 5212 | D13: ='0. Database'!E11 -> 5957 | E13: ='0. Database'!F11 -> 6622 | F13: ='0. Database'!G11 -> 8778 | G13: ='0. Database'!H11 -> 10261 | H13: ='0. Database'!I11 -> 11682 | I13: ='0. Database'!J11 -> 12796 | ... S13: ='0. Database'!T11 -> 127810.23
A14: AMZN | B14: ='0. Database'!C27 -> 3253 | C14: ='0. Database'!D27 -> 4746 | D14: ='0. Database'!E27 -> 6281 | E14: ='0. Database'!F27 -> 8116 | F14: ='0. Database'!G27 -> 11478 | G14: ='0. Database'!H27 -> 15341 | H14: ='0. Database'!I27 -> 21789 | I14: ='0. Database'!J27 -> 25180 | ... S14: ='0. Database'!T27 -> 164275.19
A15: GOOGL | B15: ='0. Database'!C42 -> 2781 | C15: ='0. Database'!D42 -> 3523 | D15: ='0. Database'!E42 -> 4132 | E15: ='0. Database'!F42 -> 5267 | F15: ='0. Database'!G42 -> 6103 | G15: ='0. Database'!H42 -> 8164 | H15: ='0. Database'!I42 -> 10856 | I15: ='0. Database'!J42 -> 12905 | ... S15: ='0. Database'!T42 -> 156155.17
A16: META | B16: ='0. Database'!C59 -> 1011 | C16: ='0. Database'!D59 -> 1243 | D16: ='0. Database'!E59 -> 1945 | E16: ='0. Database'!F59 -> 2342 | F16: ='0. Database'!G59 -> 3025 | G16: ='0. Database'!H59 -> 4315 | H16: ='0. Database'!I59 -> 5741 | I16: ='0. Database'!J59 -> 6862 | ... S16: ='0. Database'!T59 -> 87724.37
A17: ORCL | B17: ='0. Database'!C77 -> 2931 | C17: ='0. Database'!D77 -> 2908 | D17: ='0. Database'!E77 -> 2861 | E17: ='0. Database'!F77 -> 2509 | F17: ='0. Database'!G77 -> 2451 | G17: ='0. Database'!H77 -> 2785 | H17: ='0. Database'!I77 -> 2919 | I17: ='0. Database'!J77 -> 2968 | ... S17: ='0. Database'!T77 -> 37972.18
A19: (Revenue — for ratios)
A20: Company | B20: 2013A | C20: 2014A | D20: 2015A | E20: 2016A | F20: 2017A | G20: 2018A | H20: 2019A | I20: 2020A | J20: 2021A | K20: 2022A | L20: 2023A | M20: 2024A | N20: 2025E | O20: 2026E | P20: 2027E | Q20: 2028E | R20: 2029E | S20: 2030E
A21: MSFT | B21: ='0. Database'!C5 -> 77849 | C21: ='0. Database'!D5 -> 86833 | D21: ='0. Database'!E5 -> 93580 | E21: ='0. Database'!F5 -> 91963 | F21: ='0. Database'!G5 -> 96657 | G21: ='0. Database'!H5 -> 110360 | H21: ='0. Database'!I5 -> 125843 | I21: ='0. Database'!J5 -> 143015 | ... S21: ='0. Database'!T5 -> 624709.64
A22: AMZN | B22: ='0. Database'!C21 -> 74452 | C22: ='0. Database'!D21 -> 88988 | D22: ='0. Database'!E21 -> 107006 | E22: ='0. Database'!F21 -> 135987 | F22: ='0. Database'!G21 -> 177866 | G22: ='0. Database'!H21 -> 232887 | H22: ='0. Database'!I21 -> 280522 | I22: ='0. Database'!J21 -> 386064 | ... S22: ='0. Database'!T21 -> 1303433.7
A23: GOOGL | B23: ='0. Database'!C36 -> 55519 | C23: ='0. Database'!D36 -> 66001 | D23: ='0. Database'!E36 -> 74989 | E23: ='0. Database'!F36 -> 90272 | F23: ='0. Database'!G36 -> 110855 | G23: ='0. Database'!H36 -> 136819 | H23: ='0. Database'!I36 -> 161857 | I23: ='0. Database'!J36 -> 182527 | ... S23: ='0. Database'!T36 -> 941245.16
A24: META | B24: ='0. Database'!C53 -> 7872 | C24: ='0. Database'!D53 -> 12466 | D24: ='0. Database'!E53 -> 17928 | E24: ='0. Database'!F53 -> 27638 | F24: ='0. Database'!G53 -> 40653 | G24: ='0. Database'!H53 -> 55838 | H24: ='0. Database'!I53 -> 70697 | I24: ='0. Database'!J53 -> 85965 | ... S24: ='0. Database'!T53 -> 456699.5
A25: ORCL | B25: ='0. Database'!C71 -> 37253 | C25: ='0. Database'!D71 -> 38306 | D25: ='0. Database'!E71 -> 38253 | E25: ='0. Database'!F71 -> 37057 | F25: ='0. Database'!G71 -> 37899 | G25: ='0. Database'!H71 -> 39878 | H25: ='0. Database'!I71 -> 39526 | I25: ='0. Database'!J71 -> 39068 | ... S25: ='0. Database'!T71 -> 223043.24
A27: B. CapexYoY %
A28: Company | B28: 2013A | C28: 2014A | D28: 2015A | E28: 2016A | F28: 2017A | G28: 2018A | H28: 2019A | I28: 2020A | J28: 2021A | K28: 2022A | L28: 2023A | M28: 2024A | N28: 2025E | O28: 2026E | P28: 2027E | Q28: 2028E | R28: 2029E | S28: 2030E
A29: MSFT | C29: =IFERROR(C5/B5-1,"") -> 0.28846606 | D29: =IFERROR(D5/C5-1,"") -> 0.083682771 | E29: =IFERROR(E5/D5-1,"") -> 0.50269179 | F29: =IFERROR(F5/E5-1,"") -> 0.14196149 | G29: =IFERROR(G5/F5-1,"") -> 0.33333333 | H29: =IFERROR(H5/G5-1,"") -> 0.24264706 | I29: =IFERROR(I5/H5-1,"") -> 0.12426036 | J29: =IFERROR(J5/I5-1,"") -> 0.27368421 | ... S29: =IFERROR(S5/R5-1,"") -> 0.014673451
A30: AMZN | C30: =IFERROR(C6/B6-1,"") -> 0.42085391 | D30: =IFERROR(D6/C6-1,"") -> -0.062142273 | E30: =IFERROR(E6/D6-1,"") -> 0.46817786 | F30: =IFERROR(F6/E6-1,"") -> 0.49302257 | G30: =IFERROR(G6/F6-1,"") -> 0.12578304 | H30: =IFERROR(H6/G6-1,"") -> 0.12082671 | I30: =IFERROR(I6/H6-1,"") -> 1.7617021 | J30: =IFERROR(J6/I6-1,"") -> 0.58066541 | ... S30: =IFERROR(S6/R6-1,"") -> 0.049999992
A31: GOOGL | C31: =IFERROR(C7/B7-1,"") -> 0.48939929 | D31: =IFERROR(D7/C7-1,"") -> -0.095264166 | E31: =IFERROR(E7/D7-1,"") -> 0.027029753 | F31: =IFERROR(F7/E7-1,"") -> 0.29470686 | G31: =IFERROR(G7/F7-1,"") -> 0.90678095 | H31: =IFERROR(H7/G7-1,"") -> -0.063288118 | I31: =IFERROR(I7/H7-1,"") -> -0.053804994 | J31: =IFERROR(J7/I7-1,"") -> 0.10587496 | ... S31: =IFERROR(S7/R7-1,"") -> 0.049999995
A32: META | C32: =IFERROR(C8/B8-1,"") -> 0.34434655 | D32: =IFERROR(D8/C8-1,"") -> 0.37793555 | E32: =IFERROR(E8/D8-1,"") -> 0.78002378 | F32: =IFERROR(F8/E8-1,"") -> 0.498998 | G32: =IFERROR(G8/F8-1,"") -> 1.0766488 | H32: =IFERROR(H8/G8-1,"") -> 0.080257511 | I32: =IFERROR(I8/H8-1,"") -> 0.00086081314 | J32: =IFERROR(J8/I8-1,"") -> 0.2283824 | ... S32: =IFERROR(S8/R8-1,"") -> 0.059999996
A33: ORCL | C33: =IFERROR(C9/B9-1,"") -> -0.10769231 | D33: =IFERROR(D9/C9-1,"") -> 1.3982759 | E33: =IFERROR(E9/D9-1,"") -> -0.14521927 | F33: =IFERROR(F9/E9-1,"") -> 0.69974769 | G33: =IFERROR(G9/F9-1,"") -> -0.1410193 | H33: =IFERROR(H9/G9-1,"") -> -0.043778802 | I33: =IFERROR(I9/H9-1,"") -> -0.057831325 | J33: =IFERROR(J9/I9-1,"") -> 0.36508951 | ... S33: =IFERROR(S9/R9-1,"") -> -0.18
A35: C. Capex / Revenue %
A36: Company | B36: 2013A | C36: 2014A | D36: 2015A | E36: 2016A | F36: 2017A | G36: 2018A | H36: 2019A | I36: 2020A | J36: 2021A | K36: 2022A | L36: 2023A | M36: 2024A | N36: 2025E | O36: 2026E | P36: 2027E | Q36: 2028E | R36: 2029E | S36: 2030E
A37: MSFT | B37: =IFERROR(B5/B21,"") -> 0.054682783 | C37: =IFERROR(C5/C21,"") -> 0.063167229 | D37: =IFERROR(D5/D21,"") -> 0.063517846 | E37: =IFERROR(E5/E21,"") -> 0.097126018 | F37: =IFERROR(F5/F21,"") -> 0.10552779 | G37: =IFERROR(G5/G21,"") -> 0.12323306 | H37: =IFERROR(H5/H21,"") -> 0.13429432 | I37: =IFERROR(I5/I21,"") -> 0.1328532 | ... S37: =IFERROR(S5/S21,"") -> 0.4876122
A38: AMZN | B38: =IFERROR(B6/B22,"") -> 0.04624456 | C38: =IFERROR(C6/C22,"") -> 0.054973704 | D38: =IFERROR(D6/D22,"") -> 0.0428761 | E38: =IFERROR(E6/E22,"") -> 0.049534147 | F38: =IFERROR(F6/F22,"") -> 0.056542566 | G38: =IFERROR(G6/G22,"") -> 0.048615852 | H38: =IFERROR(H6/H22,"") -> 0.045237094 | I38: =IFERROR(I6/I22,"") -> 0.090777695 | ... S38: =IFERROR(S6/S22,"") -> 0.2399223
A39: GOOGL | B39: =IFERROR(B7/B23,"") -> 0.13253121 | C39: =IFERROR(C7/C23,"") -> 0.16604294 | D39: =IFERROR(D7/D23,"") -> 0.13221939 | E39: =IFERROR(E7/E23,"") -> 0.11280353 | F39: =IFERROR(F7/F23,"") -> 0.11893013 | G39: =IFERROR(G7/G23,"") -> 0.1837391 | H39: =IFERROR(H7/H23,"") -> 0.14548645 | I39: =IFERROR(I7/I23,"") -> 0.12206961 | ... S39: =IFERROR(S7/S23,"") -> 0.33413189
A40: META | B40: =IFERROR(B8/B24,"") -> 0.17301829 | C40: =IFERROR(C8/C24,"") -> 0.14687951 | D40: =IFERROR(D8/D24,"") -> 0.14072959 | E40: =IFERROR(E8/E24,"") -> 0.16249367 | F40: =IFERROR(F8/F24,"") -> 0.16559663 | G40: =IFERROR(G8/G24,"") -> 0.25036713 | H40: =IFERROR(H8/H24,"") -> 0.21361585 | I40: =IFERROR(I8/I24,"") -> 0.17582737 | ... S40: =IFERROR(S8/S24,"") -> 0.45662487
A41: ORCL | B41: =IFERROR(B9/B25,"") -> 0.017448259 | C41: =IFERROR(C9/C25,"") -> 0.015141231 | D41: =IFERROR(D9/D25,"") -> 0.036363161 | E41: =IFERROR(E9/E25,"") -> 0.032085706 | F41: =IFERROR(F9/F25,"") -> 0.053325945 | G41: =IFERROR(G9/G25,"") -> 0.043532775 | H41: =IFERROR(H9/H25,"") -> 0.041997672 | I41: =IFERROR(I9/I25,"") -> 0.040032763 | ... S41: =IFERROR(S9/S25,"") -> 0.2979685
A43: E. D&A / Revenue %
A44: Company | B44: 2013A | C44: 2014A | D44: 2015A | E44: 2016A | F44: 2017A | G44: 2018A | H44: 2019A | I44: 2020A | J44: 2021A | K44: 2022A | L44: 2023A | M44: 2024A | N44: 2025E | O44: 2026E | P44: 2027E | Q44: 2028E | R44: 2029E | S44: 2030E
A45: MSFT | B45: =IFERROR(B13/B21,"") -> 0.048234402 | C45: =IFERROR(C13/C21,"") -> 0.060023263 | D45: =IFERROR(D13/D21,"") -> 0.063656764 | E45: =IFERROR(E13/E21,"") -> 0.07200722 | F45: =IFERROR(F13/F21,"") -> 0.090815978 | G45: =IFERROR(G13/G21,"") -> 0.092977528 | H45: =IFERROR(H13/H21,"") -> 0.092829955 | I45: =IFERROR(I13/I21,"") -> 0.089473132 | ... S45: =IFERROR(S13/S21,"") -> 0.20459142
A46: AMZN | B46: =IFERROR(B14/B22,"") -> 0.04369258 | C46: =IFERROR(C14/C22,"") -> 0.053333034 | D46: =IFERROR(D14/D22,"") -> 0.058697643 | E46: =IFERROR(E14/E22,"") -> 0.059682176 | F46: =IFERROR(F14/F22,"") -> 0.064531726 | G46: =IFERROR(G14/G22,"") -> 0.065873149 | H46: =IFERROR(H14/H22,"") -> 0.077673052 | I46: =IFERROR(I14/I22,"") -> 0.065222347 | ... S46: =IFERROR(S14/S22,"") -> 0.12603264
A47: GOOGL | B47: =IFERROR(B15/B23,"") -> 0.05009096 | C47: =IFERROR(C15/C23,"") -> 0.053377979 | D47: =IFERROR(D15/D23,"") -> 0.055101415 | E47: =IFERROR(E15/E23,"") -> 0.058345888 | F47: =IFERROR(F15/F23,"") -> 0.055053899 | G47: =IFERROR(G15/G23,"") -> 0.059670075 | H47: =IFERROR(H15/H23,"") -> 0.067071551 | I47: =IFERROR(I15/I23,"") -> 0.070701869 | ... S47: =IFERROR(S15/S23,"") -> 0.16590276
A48: META | B48: =IFERROR(B16/B24,"") -> 0.12842988 | C48: =IFERROR(C16/C24,"") -> 0.099711215 | D48: =IFERROR(D16/D24,"") -> 0.10848951 | E48: =IFERROR(E16/E24,"") -> 0.084738404 | F48: =IFERROR(F16/F24,"") -> 0.074410253 | G48: =IFERROR(G16/G24,"") -> 0.077277123 | H48: =IFERROR(H16/H24,"") -> 0.081205709 | I48: =IFERROR(I16/I24,"") -> 0.079823184 | ... S48: =IFERROR(S16/S24,"") -> 0.19208335
A49: ORCL | B49: =IFERROR(B17/B25,"") -> 0.078678227 | C49: =IFERROR(C17/C25,"") -> 0.075915 | D49: =IFERROR(D17/D25,"") -> 0.07479152 | E49: =IFERROR(E17/E25,"") -> 0.067706506 | F49: =IFERROR(F17/F25,"") -> 0.064671891 | G49: =IFERROR(G17/G25,"") -> 0.069838006 | H49: =IFERROR(H17/H25,"") -> 0.073850124 | I49: =IFERROR(I17/I25,"") -> 0.075970103 | ... S49: =IFERROR(S17/S25,"") -> 0.17024582
A51: F. D&AYoY %
A52: Company | B52: 2013A | C52: 2014A | D52: 2015A | E52: 2016A | F52: 2017A | G52: 2018A | H52: 2019A | I52: 2020A | J52: 2021A | K52: 2022A | L52: 2023A | M52: 2024A | N52: 2025E | O52: 2026E | P52: 2027E | Q52: 2028E | R52: 2029E | S52: 2030E
A53: MSFT | C53: =IFERROR(C13/B13-1,"") -> 0.38801598 | D53: =IFERROR(D13/C13-1,"") -> 0.14293937 | E53: =IFERROR(E13/D13-1,"") -> 0.11163337 | F53: =IFERROR(F13/E13-1,"") -> 0.3255814 | G53: =IFERROR(G13/F13-1,"") -> 0.16894509 | H53: =IFERROR(H13/G13-1,"") -> 0.13848553 | I53: =IFERROR(I13/H13-1,"") -> 0.095360383 | J53: =IFERROR(J13/I13-1,"") -> -0.086745858 | ... S53: =IFERROR(S13/R13-1,"") -> 0.31627276
A54: AMZN | C54: =IFERROR(C14/B14-1,"") -> 0.45896096 | D54: =IFERROR(D14/C14-1,"") -> 0.32343026 | E54: =IFERROR(E14/D14-1,"") -> 0.29215093 | F54: =IFERROR(F14/E14-1,"") -> 0.41424347 | G54: =IFERROR(G14/F14-1,"") -> 0.33655689 | H54: =IFERROR(H14/G14-1,"") -> 0.42031158 | I54: =IFERROR(I14/H14-1,"") -> 0.15562899 | J54: =IFERROR(J14/I14-1,"") -> 0.36747419 | ... S54: =IFERROR(S14/R14-1,"") -> 0.12554936
A55: GOOGL | C55: =IFERROR(C15/B15-1,"") -> 0.2668105 | D55: =IFERROR(D15/C15-1,"") -> 0.17286404 | E55: =IFERROR(E15/D15-1,"") -> 0.27468538 | F55: =IFERROR(F15/E15-1,"") -> 0.15872413 | G55: =IFERROR(G15/F15-1,"") -> 0.33770277 | H55: =IFERROR(H15/G15-1,"") -> 0.32974032 | I55: =IFERROR(I15/H15-1,"") -> 0.18874355 | J55: =IFERROR(J15/I15-1,"") -> -0.10461062 | ... S55: =IFERROR(S15/R15-1,"") -> 0.22306838
A56: META | C56: =IFERROR(C16/B16-1,"") -> 0.22947577 | D56: =IFERROR(D16/C16-1,"") -> 0.56476267 | E56: =IFERROR(E16/D16-1,"") -> 0.20411311 | F56: =IFERROR(F16/E16-1,"") -> 0.29163108 | G56: =IFERROR(G16/F16-1,"") -> 0.42644628 | H56: =IFERROR(H16/G16-1,"") -> 0.33047509 | I56: =IFERROR(I16/H16-1,"") -> 0.19526215 | J56: =IFERROR(J16/I16-1,"") -> 0.16103177 | ... S56: =IFERROR(S16/R16-1,"") -> 0.17967163
A57: ORCL | C57: =IFERROR(C17/B17-1,"") -> -0.0078471511 | D57: =IFERROR(D17/C17-1,"") -> -0.016162311 | E57: =IFERROR(E17/D17-1,"") -> -0.1230339 | F57: =IFERROR(F17/E17-1,"") -> -0.02311678 | G57: =IFERROR(G17/F17-1,"") -> 0.13627091 | H57: =IFERROR(H17/G17-1,"") -> 0.048114901 | I57: =IFERROR(I17/H17-1,"") -> 0.016786571 | J57: =IFERROR(J17/I17-1,"") -> -0.017520216 | ... S57: =IFERROR(S17/R17-1,"") -> 0.24888891

Sheet 4. FCF & Cash
A1: Free Cash Flow&Cash Quality (2013-2030E)
A3: A. CFO ($mm)
A4: Company | B4: 2013A | C4: 2014A | D4: 2015A | E4: 2016A | F4: 2017A | G4: 2018A | H4: 2019A | I4: 2020A | J4: 2021A | K4: 2022A | L4: 2023A | M4: 2024A | N4: 2025E | O4: 2026E | P4: 2027E | Q4: 2028E | R4: 2029E | S4: 2030E
A5: MSFT | B5: ='0. Database'!C13 -> 28833 | C5: ='0. Database'!D13 -> 32231 | D5: ='0. Database'!E13 -> 29080 | E5: ='0. Database'!F13 -> 33325 | F5: ='0. Database'!G13 -> 39507 | G5: ='0. Database'!H13 -> 43884 | H5: ='0. Database'!I13 -> 52185 | I5: ='0. Database'!J13 -> 60675 | ... S5: ='0. Database'!T13 -> 438548.9
A6: AMZN | B6: ='0. Database'!C29 -> 5474 | C6: ='0. Database'!D29 -> 6841.4 | D6: ='0. Database'!E29 -> 11920.1 | E6: ='0. Database'!F29 -> 17271 | F6: ='0. Database'!G29 -> 18434 | G6: ='0. Database'!H29 -> 30724 | H6: ='0. Database'!I29 -> 38515 | I6: ='0. Database'!J29 -> 66064 | ... S6: ='0. Database'!T29 -> 401080.41
A7: GOOGL | B7: ='0. Database'!C44 -> 18584 | C7: ='0. Database'!D44 -> 22272 | D7: ='0. Database'!E44 -> 25829 | E7: ='0. Database'!F44 -> 36036 | F7: ='0. Database'!G44 -> 37091 | G7: ='0. Database'!H44 -> 47971 | H7: ='0. Database'!I44 -> 54520 | I7: ='0. Database'!J44 -> 65124 | ... S7: ='0. Database'!T44 -> 490867.35
A8: META | B8: ='0. Database'!C61 -> 4222 | C8: ='0. Database'!D61 -> 5507.8 | D8: ='0. Database'!E61 -> 8607 | E8: ='0. Database'!F61 -> 16061 | F8: ='0. Database'!G61 -> 24216 | G8: ='0. Database'!H61 -> 29339 | H8: ='0. Database'!I61 -> 36312.5 | I8: ='0. Database'!J61 -> 38747 | ... S8: ='0. Database'!T61 -> 314478.51
A9: ORCL | B9: ='0. Database'!C79 -> 14225 | C9: ='0. Database'!D79 -> 14921 | D9: ='0. Database'!E79 -> 14336 | E9: ='0. Database'!F79 -> 13560 | F9: ='0. Database'!G79 -> 14125 | G9: ='0. Database'!H79 -> 15386 | H9: ='0. Database'!I79 -> 14551 | I9: ='0. Database'!J79 -> 13139 | ... S9: ='0. Database'!T79 -> 84964.12
A11: B. FCF ($mm)
A12: Company | B12: 2013A | C12: 2014A | D12: 2015A | E12: 2016A | F12: 2017A | G12: 2018A | H12: 2019A | I12: 2020A | J12: 2021A | K12: 2022A | L12: 2023A | M12: 2024A | N12: 2025E | O12: 2026E | P12: 2027E | Q12: 2028E | R12: 2029E | S12: 2030E
A13: MSFT | B13: ='0. Database'!C14 -> 24576 | C13: ='0. Database'!D14 -> 26746 | D13: ='0. Database'!E14 -> 23136 | E13: ='0. Database'!F14 -> 24393 | F13: ='0. Database'!G14 -> 29307 | G13: ='0. Database'!H14 -> 30284 | H13: ='0. Database'!I14 -> 35285 | I13: ='0. Database'!J14 -> 41675 | ... S13: ='0. Database'!T14 -> 133932.86
A14: AMZN | B14: ='0. Database'!C30 -> 2031 | C14: ='0. Database'!D30 -> 1949.4 | D14: ='0. Database'!E30 -> 7332.1 | E14: ='0. Database'!F30 -> 10535 | F14: ='0. Database'!G30 -> 8377 | G14: ='0. Database'!H30 -> 19402 | H14: ='0. Database'!I30 -> 25825 | I14: ='0. Database'!J30 -> 31018 | ... S14: ='0. Database'!T30 -> 88357.6
A15: GOOGL | B15: ='0. Database'!C45 -> 11226 | C15: ='0. Database'!D45 -> 11313 | D15: ='0. Database'!E45 -> 15914 | E15: ='0. Database'!F45 -> 25853 | F15: ='0. Database'!G45 -> 23907 | G15: ='0. Database'!H45 -> 22832 | H15: ='0. Database'!I45 -> 30972 | I15: ='0. Database'!J45 -> 42843 | ... S15: ='0. Database'!T45 -> 176367.33
A16: META | B16: ='0. Database'!C62 -> 2860 | C16: ='0. Database'!D62 -> 3676.8 | D16: ='0. Database'!E62 -> 6084 | E16: ='0. Database'!F62 -> 11570 | F16: ='0. Database'!G62 -> 17484 | G16: ='0. Database'!H62 -> 15359 | H16: ='0. Database'!I62 -> 21210.5 | I16: ='0. Database'!J62 -> 23632 | ... S16: ='0. Database'!T62 -> 105938.16
A17: ORCL | B17: ='0. Database'!C80 -> 13575 | C17: ='0. Database'!D80 -> 14341 | D17: ='0. Database'!E80 -> 12945 | E17: ='0. Database'!F80 -> 12371 | F17: ='0. Database'!G80 -> 12104 | G17: ='0. Database'!H80 -> 13650 | H17: ='0. Database'!I80 -> 12891 | I17: ='0. Database'!J80 -> 11575 | ... S17: ='0. Database'!T80 -> 18504.26
A19: E. Buybacks ($mm)
A20: Company | B20: 2013A | C20: 2014A | D20: 2015A | E20: 2016A | F20: 2017A | G20: 2018A | H20: 2019A | I20: 2020A | J20: 2021A | K20: 2022A | L20: 2023A | M20: 2024A | N20: 2025E | O20: 2026E | P20: 2027E | Q20: 2028E | R20: 2029E | S20: 2030E
A21: MSFT | B21: ='0. Database'!C15 -> 5360 | C21: ='0. Database'!D15 -> 7316 | D21: ='0. Database'!E15 -> 14443 | E21: ='0. Database'!F15 -> 15969 | F21: ='0. Database'!G15 -> 11788 | G21: ='0. Database'!H15 -> 10721 | H21: ='0. Database'!I15 -> 19543 | I21: ='0. Database'!J15 -> 22968 | ... S21: ='0. Database'!T15 -> 21047.23
A22: AMZN | B22: ='0. Database'!C31 -> 0 | C22: ='0. Database'!D31 -> 0 | D22: ='0. Database'!E31 -> 0 | E22: ='0. Database'!F31 -> 0 | F22: ='0. Database'!G31 -> 0 | G22: ='0. Database'!H31 -> 0 | H22: ='0. Database'!I31 -> 0 | I22: ='0. Database'!J31 -> 0 | ... S22: ='0. Database'!T31 -> 0
A23: GOOGL | B23: ='0. Database'!C46 -> 0 | C23: ='0. Database'!D46 -> 0 | D23: ='0. Database'!E46 -> 1827 | E23: ='0. Database'!F46 -> 3693 | F23: ='0. Database'!G46 -> 4846 | G23: ='0. Database'!H46 -> 9075 | H23: ='0. Database'!I46 -> 18396 | I23: ='0. Database'!J46 -> 31149 | ... S23: ='0. Database'!T46 -> 15000
A24: META | B24: ='0. Database'!C63 -> 0 | C24: ='0. Database'!D63 -> 0 | D24: ='0. Database'!E63 -> 0 | E24: ='0. Database'!F63 -> 0 | F24: ='0. Database'!G63 -> 1976 | G24: ='0. Database'!H63 -> 12879 | H24: ='0. Database'!I63 -> 4201 | I24: ='0. Database'!J63 -> 6272 | ... S24: ='0. Database'!T63 -> 6000
A25: ORCL | B25: ='0. Database'!C81 -> 11021 | C25: ='0. Database'!D81 -> 9813 | D25: ='0. Database'!E81 -> 8087 | E25: ='0. Database'!F81 -> 10440 | F25: ='0. Database'!G81 -> 3561 | G25: ='0. Database'!H81 -> 11347 | H25: ='0. Database'!I81 -> 36140 | I25: ='0. Database'!J81 -> 19240 | ... S25: ='0. Database'!T81 -> 0
A27: (Revenue)
A28: Company | B28: 2013A | C28: 2014A | D28: 2015A | E28: 2016A | F28: 2017A | G28: 2018A | H28: 2019A | I28: 2020A | J28: 2021A | K28: 2022A | L28: 2023A | M28: 2024A | N28: 2025E | O28: 2026E | P28: 2027E | Q28: 2028E | R28: 2029E | S28: 2030E
A29: MSFT | B29: ='0. Database'!C5 -> 77849 | C29: ='0. Database'!D5 -> 86833 | D29: ='0. Database'!E5 -> 93580 | E29: ='0. Database'!F5 -> 91963 | F29: ='0. Database'!G5 -> 96657 | G29: ='0. Database'!H5 -> 110360 | H29: ='0. Database'!I5 -> 125843 | I29: ='0. Database'!J5 -> 143015 | ... S29: ='0. Database'!T5 -> 624709.64
A30: AMZN | B30: ='0. Database'!C21 -> 74452 | C30: ='0. Database'!D21 -> 88988 | D30: ='0. Database'!E21 -> 107006 | E30: ='0. Database'!F21 -> 135987 | F30: ='0. Database'!G21 -> 177866 | G30: ='0. Database'!H21 -> 232887 | H30: ='0. Database'!I21 -> 280522 | I30: ='0. Database'!J21 -> 386064 | ... S30: ='0. Database'!T21 -> 1303433.7
A31: GOOGL | B31: ='0. Database'!C36 -> 55519 | C31: ='0. Database'!D36 -> 66001 | D31: ='0. Database'!E36 -> 74989 | E31: ='0. Database'!F36 -> 90272 | F31: ='0. Database'!G36 -> 110855 | G31: ='0. Database'!H36 -> 136819 | H31: ='0. Database'!I36 -> 161857 | I31: ='0. Database'!J36 -> 182527 | ... S31: ='0. Database'!T36 -> 941245.16
A32: META | B32: ='0. Database'!C53 -> 7872 | C32: ='0. Database'!D53 -> 12466 | D32: ='0. Database'!E53 -> 17928 | E32: ='0. Database'!F53 -> 27638 | F32: ='0. Database'!G53 -> 40653 | G32: ='0. Database'!H53 -> 55838 | H32: ='0. Database'!I53 -> 70697 | I32: ='0. Database'!J53 -> 85965 | ... S32: ='0. Database'!T53 -> 456699.5
A33: ORCL | B33: ='0. Database'!C71 -> 37253 | C33: ='0. Database'!D71 -> 38306 | D33: ='0. Database'!E71 -> 38253 | E33: ='0. Database'!F71 -> 37057 | F33: ='0. Database'!G71 -> 37899 | G33: ='0. Database'!H71 -> 39878 | H33: ='0. Database'!I71 -> 39526 | I33: ='0. Database'!J71 -> 39068 | ... S33: ='0. Database'!T71 -> 223043.24
A35: (NI)
A36: Company | B36: 2013A | C36: 2014A | D36: 2015A | E36: 2016A | F36: 2017A | G36: 2018A | H36: 2019A | I36: 2020A | J36: 2021A | K36: 2022A | L36: 2023A | M36: 2024A | N36: 2025E | O36: 2026E | P36: 2027E | Q36: 2028E | R36: 2029E | S36: 2030E
A37: MSFT | B37: ='0. Database'!C7 -> 21863 | C37: ='0. Database'!D7 -> 22074 | D37: ='0. Database'!E7 -> 12193 | E37: ='0. Database'!F7 -> 16798 | F37: ='0. Database'!G7 -> 25489 | G37: ='0. Database'!H7 -> 16571 | H37: ='0. Database'!I7 -> 39240 | I37: ='0. Database'!J7 -> 44281 | ... S37: ='0. Database'!T7 -> 258948.36
A38: AMZN | B38: ='0. Database'!C23 -> 273 | C38: ='0. Database'!D23 -> -240.6 | D38: ='0. Database'!E23 -> 596.1 | E38: ='0. Database'!F23 -> 2371 | F38: ='0. Database'!G23 -> 3033 | G38: ='0. Database'!H23 -> 10073 | H38: ='0. Database'!I23 -> 11588 | I38: ='0. Database'!J23 -> 21331 | ... S38: ='0. Database'!T23 -> 211925.99
A39: GOOGL | B39: ='0. Database'!C38 -> 12720 | C39: ='0. Database'!D38 -> 14136 | D39: ='0. Database'!E38 -> 16348 | E39: ='0. Database'!F38 -> 19478 | F39: ='0. Database'!G38 -> 12662 | G39: ='0. Database'!H38 -> 30736 | H39: ='0. Database'!I38 -> 34343 | I39: ='0. Database'!J38 -> 40269 | ... S39: ='0. Database'!T38 -> 285975.76
A40: META | B40: ='0. Database'!C55 -> 1491 | C40: ='0. Database'!D55 -> 2924.8 | D40: ='0. Database'!E55 -> 3669 | E40: ='0. Database'!F55 -> 10187.2 | F40: ='0. Database'!G55 -> 15919 | G40: ='0. Database'!H55 -> 22112 | H40: ='0. Database'!I55 -> 18484.5 | I40: ='0. Database'!J55 -> 29145 | ... S40: ='0. Database'!T55 -> 127804.37
A41: ORCL | B41: ='0. Database'!C73 -> 10926 | C41: ='0. Database'!D73 -> 10955 | D41: ='0. Database'!E73 -> 9938 | E41: ='0. Database'!F73 -> 8900 | F41: ='0. Database'!G73 -> 9334 | G41: ='0. Database'!H73 -> 3587 | H41: ='0. Database'!I73 -> 11083 | I41: ='0. Database'!J73 -> 10135 | ... S41: ='0. Database'!T73 -> 44104.48
A43: (Capex)
A44: Company | B44: 2013A | C44: 2014A | D44: 2015A | E44: 2016A | F44: 2017A | G44: 2018A | H44: 2019A | I44: 2020A | J44: 2021A | K44: 2022A | L44: 2023A | M44: 2024A | N44: 2025E | O44: 2026E | P44: 2027E | Q44: 2028E | R44: 2029E | S44: 2030E
A45: MSFT | B45: ='0. Database'!C12 -> 4257 | C45: ='0. Database'!D12 -> 5485 | D45: ='0. Database'!E12 -> 5944 | E45: ='0. Database'!F12 -> 8932 | F45: ='0. Database'!G12 -> 10200 | G45: ='0. Database'!H12 -> 13600 | H45: ='0. Database'!I12 -> 16900 | I45: ='0. Database'!J12 -> 19000 | ... S45: ='0. Database'!T12 -> 304616.04
A46: AMZN | B46: ='0. Database'!C28 -> 3443 | C46: ='0. Database'!D28 -> 4892 | D46: ='0. Database'!E28 -> 4588 | E46: ='0. Database'!F28 -> 6736 | F46: ='0. Database'!G28 -> 10057 | G46: ='0. Database'!H28 -> 11322 | H46: ='0. Database'!I28 -> 12690 | I46: ='0. Database'!J28 -> 35046 | ... S46: ='0. Database'!T28 -> 312722.81
A47: GOOGL | B47: ='0. Database'!C43 -> 7358 | C47: ='0. Database'!D43 -> 10959 | D47: ='0. Database'!E43 -> 9915 | E47: ='0. Database'!F43 -> 10183 | F47: ='0. Database'!G43 -> 13184 | G47: ='0. Database'!H43 -> 25139 | H47: ='0. Database'!I43 -> 23548 | I47: ='0. Database'!J43 -> 22281 | ... S47: ='0. Database'!T43 -> 314500.02
A48: META | B48: ='0. Database'!C60 -> 1362 | C48: ='0. Database'!D60 -> 1831 | D48: ='0. Database'!E60 -> 2523 | E48: ='0. Database'!F60 -> 4491 | F48: ='0. Database'!G60 -> 6732 | G48: ='0. Database'!H60 -> 13980 | H48: ='0. Database'!I60 -> 15102 | I48: ='0. Database'!J60 -> 15115 | ... S48: ='0. Database'!T60 -> 208540.35
A49: ORCL | B49: ='0. Database'!C78 -> 650 | C49: ='0. Database'!D78 -> 580 | D49: ='0. Database'!E78 -> 1391 | E49: ='0. Database'!F78 -> 1189 | F49: ='0. Database'!G78 -> 2021 | G49: ='0. Database'!H78 -> 1736 | H49: ='0. Database'!I78 -> 1660 | I49: ='0. Database'!J78 -> 1564 | ... S49: ='0. Database'!T78 -> 66459.86
A51: C. Free Cash FlowMargin %
A52: Company | B52: 2013A | C52: 2014A | D52: 2015A | E52: 2016A | F52: 2017A | G52: 2018A | H52: 2019A | I52: 2020A | J52: 2021A | K52: 2022A | L52: 2023A | M52: 2024A | N52: 2025E | O52: 2026E | P52: 2027E | Q52: 2028E | R52: 2029E | S52: 2030E
A53: MSFT | B53: =IFERROR(B13/B29,"") -> 0.31568806 | C53: =IFERROR(C13/C29,"") -> 0.30801654 | D53: =IFERROR(D13/D29,"") -> 0.24723231 | E53: =IFERROR(E13/E29,"") -> 0.26524798 | F53: =IFERROR(F13/F29,"") -> 0.30320618 | G53: =IFERROR(G13/G29,"") -> 0.27441102 | H53: =IFERROR(H13/H29,"") -> 0.28038906 | I53: =IFERROR(I13/I29,"") -> 0.291403 | ... S53: =IFERROR(S13/S29,"") -> 0.21439218
A54: AMZN | B54: =IFERROR(B14/B30,"") -> 0.027279321 | C54: =IFERROR(C14/C30,"") -> 0.021906324 | D54: =IFERROR(D14/D30,"") -> 0.068520457 | E54: =IFERROR(E14/E30,"") -> 0.077470641 | F54: =IFERROR(F14/F30,"") -> 0.047097253 | G54: =IFERROR(G14/G30,"") -> 0.08331079 | H54: =IFERROR(H14/H30,"") -> 0.092060516 | I54: =IFERROR(I14/I30,"") -> 0.080344192 | ... S54: =IFERROR(S14/S30,"") -> 0.067788336
A55: GOOGL | B55: =IFERROR(B15/B31,"") -> 0.20220105 | C55: =IFERROR(C15/C31,"") -> 0.17140649 | D55: =IFERROR(D15/D31,"") -> 0.21221779 | E55: =IFERROR(E15/E31,"") -> 0.28639002 | F55: =IFERROR(F15/F31,"") -> 0.2156601 | G55: =IFERROR(G15/G31,"") -> 0.16687741 | H55: =IFERROR(H15/H31,"") -> 0.1913541 | I55: =IFERROR(I15/I31,"") -> 0.23472144 | ... S55: =IFERROR(S15/S31,"") -> 0.18737661
A56: META | B56: =IFERROR(B16/B32,"") -> 0.36331301 | C56: =IFERROR(C16/C32,"") -> 0.29494625 | D56: =IFERROR(D16/D32,"") -> 0.33935743 | E56: =IFERROR(E16/E32,"") -> 0.41862653 | F56: =IFERROR(F16/F32,"") -> 0.43007896 | G56: =IFERROR(G16/G32,"") -> 0.27506358 | H56: =IFERROR(H16/H32,"") -> 0.3000198 | I56: =IFERROR(I16/I32,"") -> 0.27490258 | ... S56: =IFERROR(S16/S32,"") -> 0.23196469
A57: ORCL | B57: =IFERROR(B17/B33,"") -> 0.36440018 | C57: =IFERROR(C17/C33,"") -> 0.37437999 | D57: =IFERROR(D17/D33,"") -> 0.33840483 | E57: =IFERROR(E17/E33,"") -> 0.33383706 | F57: =IFERROR(F17/F33,"") -> 0.31937518 | G57: =IFERROR(G17/G33,"") -> 0.342294 | H57: =IFERROR(H17/H33,"") -> 0.32613976 | I57: =IFERROR(I17/I33,"") -> 0.29627828 | ... S57: =IFERROR(S17/S33,"") -> 0.082962658
A59: D. FCF / Net Income %
A60: Company | B60: 2013A | C60: 2014A | D60: 2015A | E60: 2016A | F60: 2017A | G60: 2018A | H60: 2019A | I60: 2020A | J60: 2021A | K60: 2022A | L60: 2023A | M60: 2024A | N60: 2025E | O60: 2026E | P60: 2027E | Q60: 2028E | R60: 2029E | S60: 2030E
A61: MSFT | B61: =IFERROR(B13/B37,"") -> 1.1240909 | C61: =IFERROR(C13/C37,"") -> 1.2116517 | D61: =IFERROR(D13/D37,"") -> 1.8974822 | E61: =IFERROR(E13/E37,"") -> 1.4521372 | F61: =IFERROR(F13/F37,"") -> 1.1497901 | G61: =IFERROR(G13/G37,"") -> 1.82753 | H61: =IFERROR(H13/H37,"") -> 0.89920999 | I61: =IFERROR(I13/I37,"") -> 0.94114857 | ... S61: =IFERROR(S13/S37,"") -> 0.51721841
A62: AMZN | B62: =IFERROR(B14/B38,"") -> 7.4395604 | C62: =IFERROR(C14/C38,"") -> -8.1022444 | D62: =IFERROR(D14/D38,"") -> 12.300117 | E62: =IFERROR(E14/E38,"") -> 4.4432729 | F62: =IFERROR(F14/F38,"") -> 2.7619519 | G62: =IFERROR(G14/G38,"") -> 1.9261392 | H62: =IFERROR(H14/H38,"") -> 2.2285986 | I62: =IFERROR(I14/I38,"") -> 1.4541278 | ... S62: =IFERROR(S14/S38,"") -> 0.41692668
A63: GOOGL | B63: =IFERROR(B15/B39,"") -> 0.88254717 | C63: =IFERROR(C15/C39,"") -> 0.80029711 | D63: =IFERROR(D15/D39,"") -> 0.97345241 | E63: =IFERROR(E15/E39,"") -> 1.3272923 | F63: =IFERROR(F15/F39,"") -> 1.8880903 | G63: =IFERROR(G15/G39,"") -> 0.74284227 | H63: =IFERROR(H15/H39,"") -> 0.90184317 | I63: =IFERROR(I15/I39,"") -> 1.0639201 | ... S63: =IFERROR(S15/S39,"") -> 0.61672126
A64: META | B64: =IFERROR(B16/B40,"") -> 1.9181757 | C64: =IFERROR(C16/C40,"") -> 1.2571116 | D64: =IFERROR(D16/D40,"") -> 1.6582175 | E64: =IFERROR(E16/E40,"") -> 1.135739 | F64: =IFERROR(F16/F40,"") -> 1.0983102 | G64: =IFERROR(G16/G40,"") -> 0.69460022 | H64: =IFERROR(H16/H40,"") -> 1.1474749 | I64: =IFERROR(I16/I40,"") -> 0.81084234 | ... S64: =IFERROR(S16/S40,"") -> 0.82890875
A65: ORCL | B65: =IFERROR(B17/B41,"") -> 1.2424492 | C65: =IFERROR(C17/C41,"") -> 1.3090826 | D65: =IFERROR(D17/D41,"") -> 1.302576 | E65: =IFERROR(E17/E41,"") -> 1.39 | F65: =IFERROR(F17/F41,"") -> 1.2967645 | G65: =IFERROR(G17/G41,"") -> 3.8054084 | H65: =IFERROR(H17/H41,"") -> 1.1631327 | I65: =IFERROR(I17/I41,"") -> 1.1420819 | ... S65: =IFERROR(S17/S41,"") -> 0.41955511
A67: F. Capex/CFO %
A68: Company | B68: 2013A | C68: 2014A | D68: 2015A | E68: 2016A | F68: 2017A | G68: 2018A | H68: 2019A | I68: 2020A | J68: 2021A | K68: 2022A | L68: 2023A | M68: 2024A | N68: 2025E | O68: 2026E | P68: 2027E | Q68: 2028E | R68: 2029E | S68: 2030E
A69: MSFT | B69: =IFERROR(B45/B5,"") -> 0.14764333 | C69: =IFERROR(C45/C5,"") -> 0.17017778 | D69: =IFERROR(D45/D5,"") -> 0.20440165 | E69: =IFERROR(E45/E5,"") -> 0.26802701 | F69: =IFERROR(F45/F5,"") -> 0.25818209 | G69: =IFERROR(G45/G5,"") -> 0.30990794 | H69: =IFERROR(H45/H5,"") -> 0.32384785 | I69: =IFERROR(I45/I5,"") -> 0.3131438 | ... S69: =IFERROR(S45/S5,"") -> 0.69459994
A70: AMZN | B70: =IFERROR(B46/B6,"") -> 0.62897333 | C70: =IFERROR(C46/C6,"") -> 0.71505832 | D70: =IFERROR(D46/D6,"") -> 0.3848961 | E70: =IFERROR(E46/E6,"") -> 0.39001795 | F70: =IFERROR(F46/F6,"") -> 0.54556797 | G70: =IFERROR(G46/G6,"") -> 0.3685067 | H70: =IFERROR(H46/H6,"") -> 0.32948202 | I70: =IFERROR(I46/I6,"") -> 0.53048559 | ... S70: =IFERROR(S46/S6,"") -> 0.77970103
A71: GOOGL | B71: =IFERROR(B47/B7,"") -> 0.39593198 | C71: =IFERROR(C47/C7,"") -> 0.4920528 | D71: =IFERROR(D47/D7,"") -> 0.38387084 | E71: =IFERROR(E47/E7,"") -> 0.28257853 | F71: =IFERROR(F47/F7,"") -> 0.35545011 | G71: =IFERROR(G47/G7,"") -> 0.52404578 | H71: =IFERROR(H47/H7,"") -> 0.43191489 | I71: =IFERROR(I47/I7,"") -> 0.34213193 | ... S71: =IFERROR(S47/S7,"") -> 0.64070267
A72: META | B72: =IFERROR(B48/B8,"") -> 0.32259593 | C72: =IFERROR(C48/C8,"") -> 0.33243763 | D72: =IFERROR(D48/D8,"") -> 0.2931335 | E72: =IFERROR(E48/E8,"") -> 0.27962144 | F72: =IFERROR(F48/F8,"") -> 0.27799802 | G72: =IFERROR(G48/G8,"") -> 0.47649886 | H72: =IFERROR(H48/H8,"") -> 0.41588985 | I72: =IFERROR(I48/I8,"") -> 0.39009472 | ... S72: =IFERROR(S48/S8,"") -> 0.66313069
A73: ORCL | B73: =IFERROR(B49/B9,"") -> 0.0456942 | C73: =IFERROR(C49/C9,"") -> 0.038871389 | D73: =IFERROR(D49/D9,"") -> 0.09702846 | E73: =IFERROR(E49/E9,"") -> 0.087684366 | F73: =IFERROR(F49/F9,"") -> 0.14307965 | G73: =IFERROR(G49/G9,"") -> 0.11282985 | H73: =IFERROR(H49/H9,"") -> 0.11408151 | I73: =IFERROR(I49/I9,"") -> 0.11903493 | ... S73: =IFERROR(S49/S9,"") -> 0.78221089

Sheet 5. EPS & Margins
A1: EPS、Operating IncomeMargin&Profitability (2013-2030E)
A3: A. Operating Income ($mm)
A4: Company | B4: 2013A | C4: 2014A | D4: 2015A | E4: 2016A | F4: 2017A | G4: 2018A | H4: 2019A | I4: 2020A | J4: 2021A | K4: 2022A | L4: 2023A | M4: 2024A | N4: 2025E | O4: 2026E | P4: 2027E | Q4: 2028E | R4: 2029E | S4: 2030E
A5: MSFT | B5: ='0. Database'!C6 -> 26764 | C5: ='0. Database'!D6 -> 27759 | D5: ='0. Database'!E6 -> 13359 | E5: ='0. Database'!F6 -> 11756 | F5: ='0. Database'!G6 -> 11389 | G5: ='0. Database'!H6 -> 12924 | H5: ='0. Database'!I6 -> 16219 | I5: ='0. Database'!J6 -> 18724 | ... S5: ='0. Database'!T6 -> 108509.49
A6: AMZN | B6: ='0. Database'!C22 -> 673 | C6: ='0. Database'!D22 -> 458 | D6: ='0. Database'!E22 -> 1507 | E6: ='0. Database'!F22 -> 3108 | F6: ='0. Database'!G22 -> 4331 | G6: ='0. Database'!H22 -> 7296 | H6: ='0. Database'!I22 -> 9201 | I6: ='0. Database'!J22 -> 13531 | ... S6: ='0. Database'!T22 -> 152115.05
A7: GOOGL | B7: ='0. Database'!C37 -> 16260 | C7: ='0. Database'!D37 -> 18965 | D7: ='0. Database'!E37 -> 23319 | E7: ='0. Database'!F37 -> 27055 | F7: ='0. Database'!G37 -> 32456 | G7: ='0. Database'!H37 -> 43137 | H7: ='0. Database'!I37 -> 48999 | I7: ='0. Database'!J37 -> 54606 | ... S7: ='0. Database'!T37 -> 258679.36
A8: META | B8: ='0. Database'!C54 -> 2804 | C8: ='0. Database'!D54 -> 4994.8 | D8: ='0. Database'!E54 -> 6225 | E8: ='0. Database'!F54 -> 12427 | F8: ='0. Database'!G54 -> 20202 | G8: ='0. Database'!H54 -> 24913 | H8: ='0. Database'!I54 -> 28489 | I8: ='0. Database'!J54 -> 39294 | ... S8: ='0. Database'!T54 -> 192345.26
A9: ORCL | B9: ='0. Database'!C72 -> 14684 | C9: ='0. Database'!D72 -> 14758 | D9: ='0. Database'!E72 -> 13870 | E9: ='0. Database'!F72 -> 12604 | F9: ='0. Database'!G72 -> 12710 | G9: ='0. Database'!H72 -> 13264 | H9: ='0. Database'!I72 -> 13535 | I9: ='0. Database'!J72 -> 13897 | ... S9: ='0. Database'!T72 -> 57952.82
A11: C. Net Income ($mm)
A12: Company | B12: 2013A | C12: 2014A | D12: 2015A | E12: 2016A | F12: 2017A | G12: 2018A | H12: 2019A | I12: 2020A | J12: 2021A | K12: 2022A | L12: 2023A | M12: 2024A | N12: 2025E | O12: 2026E | P12: 2027E | Q12: 2028E | R12: 2029E | S12: 2030E
A13: MSFT | B13: ='0. Database'!C7 -> 21863 | C13: ='0. Database'!D7 -> 22074 | D13: ='0. Database'!E7 -> 12193 | E13: ='0. Database'!F7 -> 16798 | F13: ='0. Database'!G7 -> 25489 | G13: ='0. Database'!H7 -> 16571 | H13: ='0. Database'!I7 -> 39240 | I13: ='0. Database'!J7 -> 44281 | ... S13: ='0. Database'!T7 -> 258948.36
A14: AMZN | B14: ='0. Database'!C23 -> 273 | C14: ='0. Database'!D23 -> -240.6 | D14: ='0. Database'!E23 -> 596.1 | E14: ='0. Database'!F23 -> 2371 | F14: ='0. Database'!G23 -> 3033 | G14: ='0. Database'!H23 -> 10073 | H14: ='0. Database'!I23 -> 11588 | I14: ='0. Database'!J23 -> 21331 | ... S14: ='0. Database'!T23 -> 211925.99
A15: GOOGL | B15: ='0. Database'!C38 -> 12720 | C15: ='0. Database'!D38 -> 14136 | D15: ='0. Database'!E38 -> 16348 | E15: ='0. Database'!F38 -> 19478 | F15: ='0. Database'!G38 -> 12662 | G15: ='0. Database'!H38 -> 30736 | H15: ='0. Database'!I38 -> 34343 | I15: ='0. Database'!J38 -> 40269 | ... S15: ='0. Database'!T38 -> 285975.76
A16: META | B16: ='0. Database'!C55 -> 1491 | C16: ='0. Database'!D55 -> 2924.8 | D16: ='0. Database'!E55 -> 3669 | E16: ='0. Database'!F55 -> 10187.2 | F16: ='0. Database'!G55 -> 15919 | G16: ='0. Database'!H55 -> 22112 | H16: ='0. Database'!I55 -> 18484.5 | I16: ='0. Database'!J55 -> 29145 | ... S16: ='0. Database'!T55 -> 127804.37
A17: ORCL | B17: ='0. Database'!C73 -> 10926 | C17: ='0. Database'!D73 -> 10955 | D17: ='0. Database'!E73 -> 9938 | E17: ='0. Database'!F73 -> 8900 | F17: ='0. Database'!G73 -> 9334 | G17: ='0. Database'!H73 -> 3587 | H17: ='0. Database'!I73 -> 11083 | I17: ='0. Database'!J73 -> 10135 | ... S17: ='0. Database'!T73 -> 44104.48
A19: E. EPS ($)
A20: Company | B20: 2013A | C20: 2014A | D20: 2015A | E20: 2016A | F20: 2017A | G20: 2018A | H20: 2019A | I20: 2020A | J20: 2021A | K20: 2022A | L20: 2023A | M20: 2024A | N20: 2025E | O20: 2026E | P20: 2027E | Q20: 2028E | R20: 2029E | S20: 2030E
A21: MSFT | B21: ='0. Database'!C8 -> 2.58 | C21: ='0. Database'!D8 -> 2.63 | D21: ='0. Database'!E8 -> 1.48 | E21: ='0. Database'!F8 -> 2.1 | F21: ='0. Database'!G8 -> 2.71 | G21: ='0. Database'!H8 -> 2.13 | H21: ='0. Database'!I8 -> 5.06 | I21: ='0. Database'!J8 -> 5.76 | ... S21: ='0. Database'!T8 -> 31.49
A22: AMZN | B22: ='0. Database'!C24 -> 0.03 | C22: ='0. Database'!D24 -> -0.03 | D22: ='0. Database'!E24 -> 0.06 | E22: ='0. Database'!F24 -> 0.25 | F22: ='0. Database'!G24 -> 0.23 | G22: ='0. Database'!H24 -> 1.01 | H22: ='0. Database'!I24 -> 1.15 | I22: ='0. Database'!J24 -> 2.09 | ... S22: ='0. Database'!T24 -> 17.13
A23: GOOGL | B23: ='0. Database'!C39 -> 0.9 | C23: ='0. Database'!D39 -> 1.01 | D23: ='0. Database'!E39 -> 1.14 | E23: ='0. Database'!F39 -> 1.39 | F23: ='0. Database'!G39 -> 1.6 | G23: ='0. Database'!H39 -> 2.19 | H23: ='0. Database'!I39 -> 2.33 | I23: ='0. Database'!J39 -> 2.93 | ... S23: ='0. Database'!T39 -> 26.04
A24: META | B24: ='0. Database'!C56 -> 0.6 | C24: ='0. Database'!D56 -> 1.1 | D24: ='0. Database'!E56 -> 1.29 | E24: ='0. Database'!F56 -> 3.49 | F24: ='0. Database'!G56 -> 6.16 | G24: ='0. Database'!H56 -> 7.57 | H24: ='0. Database'!I56 -> 8.56 | I24: ='0. Database'!J56 -> 9.78 | ... S24: ='0. Database'!T56 -> 57
A25: ORCL | B25: ='0. Database'!C74 -> 2.26 | C25: ='0. Database'!D74 -> 2.38 | D25: ='0. Database'!E74 -> 2.21 | E25: ='0. Database'!F74 -> 2.07 | F25: ='0. Database'!G74 -> 2.21 | G25: ='0. Database'!H74 -> 0.9 | H25: ='0. Database'!I74 -> 2.97 | I25: ='0. Database'!J74 -> 3.08 | ... S25: ='0. Database'!T74 -> 16.76
A27: G. Diluted Shares (mm)
A28: Company | B28: 2013A | C28: 2014A | D28: 2015A | E28: 2016A | F28: 2017A | G28: 2018A | H28: 2019A | I28: 2020A | J28: 2021A | K28: 2022A | L28: 2023A | M28: 2024A | N28: 2025E | O28: 2026E | P28: 2027E | Q28: 2028E | R28: 2029E | S28: 2030E
A29: MSFT | B29: ='0. Database'!C9 -> 8375 | C29: ='0. Database'!D9 -> 8299 | D29: ='0. Database'!E9 -> 8177 | E29: ='0. Database'!F9 -> 7925 | F29: ='0. Database'!G9 -> 7746 | G29: ='0. Database'!H9 -> 7700 | H29: ='0. Database'!I9 -> 7673 | I29: ='0. Database'!J9 -> 7610 | ... S29: ='0. Database'!T9 -> 7345.29
A30: AMZN | B30: ='0. Database'!C25 -> 9140 | C30: ='0. Database'!D25 -> 9240 | D30: ='0. Database'!E25 -> 9340 | E30: ='0. Database'!F25 -> 9480 | F30: ='0. Database'!G25 -> 9600 | G30: ='0. Database'!H25 -> 9740 | H30: ='0. Database'!I25 -> 9880 | I30: ='0. Database'!J25 -> 10000 | ... S30: ='0. Database'!T25 -> 11258.12
A31: GOOGL | B31: ='0. Database'!C40 -> 13313.88 | C31: ='0. Database'!D40 -> 13518.7 | D31: ='0. Database'!E40 -> 13692.52 | E31: ='0. Database'!F40 -> 13842.18 | F31: ='0. Database'!G40 -> 13858.02 | G31: ='0. Database'!H40 -> 13902.8 | H31: ='0. Database'!I40 -> 13851.92 | I31: ='0. Database'!J40 -> 13616.32 | ... S31: ='0. Database'!T40 -> 12193.09
A32: META | B32: ='0. Database'!C57 -> 2420 | C32: ='0. Database'!D57 -> 2614 | D32: ='0. Database'!E57 -> 2803 | E32: ='0. Database'!F57 -> 2863 | F32: ='0. Database'!G57 -> 2901 | G32: ='0. Database'!H57 -> 2890 | H32: ='0. Database'!I57 -> 2854 | I32: ='0. Database'!J57 -> 2851 | ... S32: ='0. Database'!T57 -> 2579.74
A33: ORCL | B33: ='0. Database'!C75 -> 4769 | C33: ='0. Database'!D75 -> 4528 | D33: ='0. Database'!E75 -> 4404 | E33: ='0. Database'!F75 -> 4221 | F33: ='0. Database'!G75 -> 4115 | G33: ='0. Database'!H75 -> 4121 | H33: ='0. Database'!I75 -> 3634 | I33: ='0. Database'!J75 -> 3211 | ... S33: ='0. Database'!T75 -> 3041.61
A35: H. SBC ($mm)
A36: Company | B36: 2013A | C36: 2014A | D36: 2015A | E36: 2016A | F36: 2017A | G36: 2018A | H36: 2019A | I36: 2020A | J36: 2021A | K36: 2022A | L36: 2023A | M36: 2024A | N36: 2025E | O36: 2026E | P36: 2027E | Q36: 2028E | R36: 2029E | S36: 2030E
A37: MSFT | B37: ='0. Database'!C10 -> 2406 | C37: ='0. Database'!D10 -> 2446 | D37: ='0. Database'!E10 -> 2574 | E37: ='0. Database'!F10 -> 2668 | F37: ='0. Database'!G10 -> 3266 | G37: ='0. Database'!H10 -> 3940 | H37: ='0. Database'!I10 -> 4652 | I37: ='0. Database'!J10 -> 5289 | ... S37: ='0. Database'!T10 -> 14871.62
A38: AMZN | B38: ='0. Database'!C26 -> -1134 | C38: ='0. Database'!D26 -> -1497 | D38: ='0. Database'!E26 -> -2120 | E38: ='0. Database'!F26 -> -2975 | F38: ='0. Database'!G26 -> -4214 | G38: ='0. Database'!H26 -> -5418 | H38: ='0. Database'!I26 -> -6864 | I38: ='0. Database'!J26 -> -9208 | ... S38: ='0. Database'!T26 -> -20744.82
A39: GOOGL | B39: ='0. Database'!C41 -> -3268 | C39: ='0. Database'!D41 -> -4175 | D39: ='0. Database'!E41 -> -4903 | E39: ='0. Database'!F41 -> -6703 | F39: ='0. Database'!G41 -> -7679 | G39: ='0. Database'!H41 -> -9353 | H39: ='0. Database'!I41 -> -10794 | I39: ='0. Database'!J41 -> -12991 | ... S39: ='0. Database'!T41 -> -35339.95
A40: META | B40: ='0. Database'!C58 -> -906 | C40: ='0. Database'!D58 -> -1837 | D40: ='0. Database'!E58 -> -2969 | E40: ='0. Database'!F58 -> -3202 | F40: ='0. Database'!G58 -> -3723 | G40: ='0. Database'!H58 -> -4152 | H40: ='0. Database'!I58 -> -4835 | I40: ='0. Database'!J58 -> -6536 | ... S40: ='0. Database'!T58 -> -28834.48
A41: ORCL | B41: ='0. Database'!C76 -> 755 | C41: ='0. Database'!D76 -> 805 | D41: ='0. Database'!E76 -> 933 | E41: ='0. Database'!F76 -> 1037 | F41: ='0. Database'!G76 -> 1350 | G41: ='0. Database'!H76 -> 1607 | H41: ='0. Database'!I76 -> 1653 | I41: ='0. Database'!J76 -> 1590 | ... S41: ='0. Database'!T76 -> 11212.32
A43: (Revenue)
A44: Company | B44: 2013A | C44: 2014A | D44: 2015A | E44: 2016A | F44: 2017A | G44: 2018A | H44: 2019A | I44: 2020A | J44: 2021A | K44: 2022A | L44: 2023A | M44: 2024A | N44: 2025E | O44: 2026E | P44: 2027E | Q44: 2028E | R44: 2029E | S44: 2030E
A45: MSFT | B45: ='0. Database'!C5 -> 77849 | C45: ='0. Database'!D5 -> 86833 | D45: ='0. Database'!E5 -> 93580 | E45: ='0. Database'!F5 -> 91963 | F45: ='0. Database'!G5 -> 96657 | G45: ='0. Database'!H5 -> 110360 | H45: ='0. Database'!I5 -> 125843 | I45: ='0. Database'!J5 -> 143015 | ... S45: ='0. Database'!T5 -> 624709.64
A46: AMZN | B46: ='0. Database'!C21 -> 74452 | C46: ='0. Database'!D21 -> 88988 | D46: ='0. Database'!E21 -> 107006 | E46: ='0. Database'!F21 -> 135987 | F46: ='0. Database'!G21 -> 177866 | G46: ='0. Database'!H21 -> 232887 | H46: ='0. Database'!I21 -> 280522 | I46: ='0. Database'!J21 -> 386064 | ... S46: ='0. Database'!T21 -> 1303433.7
A47: GOOGL | B47: ='0. Database'!C36 -> 55519 | C47: ='0. Database'!D36 -> 66001 | D47: ='0. Database'!E36 -> 74989 | E47: ='0. Database'!F36 -> 90272 | F47: ='0. Database'!G36 -> 110855 | G47: ='0. Database'!H36 -> 136819 | H47: ='0. Database'!I36 -> 161857 | I47: ='0. Database'!J36 -> 182527 | ... S47: ='0. Database'!T36 -> 941245.16
A48: META | B48: ='0. Database'!C53 -> 7872 | C48: ='0. Database'!D53 -> 12466 | D48: ='0. Database'!E53 -> 17928 | E48: ='0. Database'!F53 -> 27638 | F48: ='0. Database'!G53 -> 40653 | G48: ='0. Database'!H53 -> 55838 | H48: ='0. Database'!I53 -> 70697 | I48: ='0. Database'!J53 -> 85965 | ... S48: ='0. Database'!T53 -> 456699.5
A49: ORCL | B49: ='0. Database'!C71 -> 37253 | C49: ='0. Database'!D71 -> 38306 | D49: ='0. Database'!E71 -> 38253 | E49: ='0. Database'!F71 -> 37057 | F49: ='0. Database'!G71 -> 37899 | G49: ='0. Database'!H71 -> 39878 | H49: ='0. Database'!I71 -> 39526 | I49: ='0. Database'!J71 -> 39068 | ... S49: ='0. Database'!T71 -> 223043.24
A51: B. Operating IncomeMargin %
A52: Company | B52: 2013A | C52: 2014A | D52: 2015A | E52: 2016A | F52: 2017A | G52: 2018A | H52: 2019A | I52: 2020A | J52: 2021A | K52: 2022A | L52: 2023A | M52: 2024A | N52: 2025E | O52: 2026E | P52: 2027E | Q52: 2028E | R52: 2029E | S52: 2030E
A53: MSFT | B53: =IFERROR(B5/B45,"") -> 0.34379375 | C53: =IFERROR(C5/C45,"") -> 0.31968261 | D53: =IFERROR(D5/D45,"") -> 0.14275486 | E53: =IFERROR(E5/E45,"") -> 0.12783402 | F53: =IFERROR(F5/F45,"") -> 0.11782902 | G53: =IFERROR(G5/G45,"") -> 0.11710765 | H53: =IFERROR(H5/H45,"") -> 0.12888281 | I53: =IFERROR(I5/I45,"") -> 0.13092333 | ... S53: =IFERROR(S5/S45,"") -> 0.17369588
A54: AMZN | B54: =IFERROR(B6/B46,"") -> 0.0090393811 | C54: =IFERROR(C6/C46,"") -> 0.0051467614 | D54: =IFERROR(D6/D46,"") -> 0.014083322 | E54: =IFERROR(E6/E46,"") -> 0.022855126 | F54: =IFERROR(F6/F46,"") -> 0.024349791 | G54: =IFERROR(G6/G46,"") -> 0.031328498 | H54: =IFERROR(H6/H46,"") -> 0.032799567 | I54: =IFERROR(I6/I46,"") -> 0.035048593 | ... S54: =IFERROR(S6/S46,"") -> 0.11670333
A55: GOOGL | B55: =IFERROR(B7/B47,"") -> 0.29287271 | C55: =IFERROR(C7/C47,"") -> 0.28734413 | D55: =IFERROR(D7/D47,"") -> 0.31096561 | E55: =IFERROR(E7/E47,"") -> 0.29970533 | F55: =IFERROR(F7/F47,"") -> 0.29277886 | G55: =IFERROR(G7/G47,"") -> 0.31528516 | H55: =IFERROR(H7/H47,"") -> 0.30273019 | I55: =IFERROR(I7/I47,"") -> 0.2991667 | ... S55: =IFERROR(S7/S47,"") -> 0.27482676
A56: META | B56: =IFERROR(B8/B48,"") -> 0.35619919 | C56: =IFERROR(C8/C48,"") -> 0.40067383 | D56: =IFERROR(D8/D48,"") -> 0.34722222 | E56: =IFERROR(E8/E48,"") -> 0.44963456 | F56: =IFERROR(F8/F48,"") -> 0.4969375 | G56: =IFERROR(G8/G48,"") -> 0.44616569 | H56: =IFERROR(H8/H48,"") -> 0.40297325 | I56: =IFERROR(I8/I48,"") -> 0.457093 | ... S56: =IFERROR(S8/S48,"") -> 0.42116372
A57: ORCL | B57: =IFERROR(B9/B49,"") -> 0.3941696 | C57: =IFERROR(C9/C49,"") -> 0.38526602 | D57: =IFERROR(D9/D49,"") -> 0.36258594 | E57: =IFERROR(E9/E49,"") -> 0.34012467 | F57: =IFERROR(F9/F49,"") -> 0.33536505 | G57: =IFERROR(G9/G49,"") -> 0.33261447 | H57: =IFERROR(H9/H49,"") -> 0.34243283 | I57: =IFERROR(I9/I49,"") -> 0.35571312 | ... S57: =IFERROR(S9/S49,"") -> 0.25982774
A59: D. Net Margin %
A60: Company | B60: 2013A | C60: 2014A | D60: 2015A | E60: 2016A | F60: 2017A | G60: 2018A | H60: 2019A | I60: 2020A | J60: 2021A | K60: 2022A | L60: 2023A | M60: 2024A | N60: 2025E | O60: 2026E | P60: 2027E | Q60: 2028E | R60: 2029E | S60: 2030E
A61: MSFT | B61: =IFERROR(B13/B45,"") -> 0.28083855 | C61: =IFERROR(C13/C45,"") -> 0.25421211 | D61: =IFERROR(D13/D45,"") -> 0.13029493 | E61: =IFERROR(E13/E45,"") -> 0.18266042 | F61: =IFERROR(F13/F45,"") -> 0.26370568 | G61: =IFERROR(G13/G45,"") -> 0.15015404 | H61: =IFERROR(H13/H45,"") -> 0.31181711 | I61: =IFERROR(I13/I45,"") -> 0.30962486 | ... S61: =IFERROR(S13/S45,"") -> 0.41450995
A62: AMZN | B62: =IFERROR(B14/B46,"") -> 0.003666792 | C62: =IFERROR(C14/C46,"") -> -0.0027037353 | D62: =IFERROR(D14/D46,"") -> 0.0055707157 | E62: =IFERROR(E14/E46,"") -> 0.01743549 | F62: =IFERROR(F14/F46,"") -> 0.017052163 | G62: =IFERROR(G14/G46,"") -> 0.043252736 | H62: =IFERROR(H14/H46,"") -> 0.041308703 | I62: =IFERROR(I14/I46,"") -> 0.055252497 | ... S62: =IFERROR(S14/S46,"") -> 0.16259054
A63: GOOGL | B63: =IFERROR(B15/B47,"") -> 0.22911075 | C63: =IFERROR(C15/C47,"") -> 0.21417857 | D63: =IFERROR(D15/D47,"") -> 0.21800531 | E63: =IFERROR(E15/E47,"") -> 0.21577012 | F63: =IFERROR(F15/F47,"") -> 0.11422128 | G63: =IFERROR(G15/G47,"") -> 0.22464716 | H63: =IFERROR(H15/H47,"") -> 0.21218112 | I63: =IFERROR(I15/I47,"") -> 0.22061942 | ... S63: =IFERROR(S15/S47,"") -> 0.30382707
A64: META | B64: =IFERROR(B16/B48,"") -> 0.18940549 | C64: =IFERROR(C16/C48,"") -> 0.23462217 | D64: =IFERROR(D16/D48,"") -> 0.20465194 | E64: =IFERROR(E16/E48,"") -> 0.36859396 | F64: =IFERROR(F16/F48,"") -> 0.39158242 | G64: =IFERROR(G16/G48,"") -> 0.39600272 | H64: =IFERROR(H16/H48,"") -> 0.26146088 | I64: =IFERROR(I16/I48,"") -> 0.33903333 | ... S64: =IFERROR(S16/S48,"") -> 0.27984346
A65: ORCL | B65: =IFERROR(B17/B49,"") -> 0.29329182 | C65: =IFERROR(C17/C49,"") -> 0.28598653 | D65: =IFERROR(D17/D49,"") -> 0.25979662 | E65: =IFERROR(E17/E49,"") -> 0.24017055 | F65: =IFERROR(F17/F49,"") -> 0.24628618 | G65: =IFERROR(G17/G49,"") -> 0.089949346 | H65: =IFERROR(H17/H49,"") -> 0.28039771 | I65: =IFERROR(I17/I49,"") -> 0.25941947 | ... S65: =IFERROR(S17/S49,"") -> 0.1977396
A67: F. EPSYoY %
A68: Company | B68: 2013A | C68: 2014A | D68: 2015A | E68: 2016A | F68: 2017A | G68: 2018A | H68: 2019A | I68: 2020A | J68: 2021A | K68: 2022A | L68: 2023A | M68: 2024A | N68: 2025E | O68: 2026E | P68: 2027E | Q68: 2028E | R68: 2029E | S68: 2030E
A69: MSFT | C69: =IFERROR(C21/B21-1,"") -> 0.019379845 | D69: =IFERROR(D21/C21-1,"") -> -0.43726236 | E69: =IFERROR(E21/D21-1,"") -> 0.41891892 | F69: =IFERROR(F21/E21-1,"") -> 0.29047619 | G69: =IFERROR(G21/F21-1,"") -> -0.21402214 | H69: =IFERROR(H21/G21-1,"") -> 1.3755869 | I69: =IFERROR(I21/H21-1,"") -> 0.13833992 | J69: =IFERROR(J21/I21-1,"") -> 0.39756944 | ... S69: =IFERROR(S21/R21-1,"") -> 0.1662963
A70: AMZN | C70: =IFERROR(C22/B22-1,"") -> -2 | D70: =IFERROR(D22/C22-1,"") -> -3 | E70: =IFERROR(E22/D22-1,"") -> 3.1666667 | F70: =IFERROR(F22/E22-1,"") -> -0.08 | G70: =IFERROR(G22/F22-1,"") -> 3.3913043 | H70: =IFERROR(H22/G22-1,"") -> 0.13861386 | I70: =IFERROR(I22/H22-1,"") -> 0.8173913 | J70: =IFERROR(J22/I22-1,"") -> 0.11483254 | ... S70: =IFERROR(S22/R22-1,"") -> 0.19456067
A71: GOOGL | C71: =IFERROR(C23/B23-1,"") -> 0.12222222 | D71: =IFERROR(D23/C23-1,"") -> 0.12871287 | E71: =IFERROR(E23/D23-1,"") -> 0.21929825 | F71: =IFERROR(F23/E23-1,"") -> 0.15107914 | G71: =IFERROR(G23/F23-1,"") -> 0.36875 | H71: =IFERROR(H23/G23-1,"") -> 0.063926941 | I71: =IFERROR(I23/H23-1,"") -> 0.25751073 | J71: =IFERROR(J23/I23-1,"") -> 0.91467577 | ... S71: =IFERROR(S23/R23-1,"") -> 0.22541176
A72: META | C72: =IFERROR(C24/B24-1,"") -> 0.83333333 | D72: =IFERROR(D24/C24-1,"") -> 0.17272727 | E72: =IFERROR(E24/D24-1,"") -> 1.7054264 | F72: =IFERROR(F24/E24-1,"") -> 0.76504298 | G72: =IFERROR(G24/F24-1,"") -> 0.2288961 | H72: =IFERROR(H24/G24-1,"") -> 0.13077939 | I72: =IFERROR(I24/H24-1,"") -> 0.14252336 | J72: =IFERROR(J24/I24-1,"") -> 0.40797546 | ... S72: =IFERROR(S24/R24-1,"") -> 0.17235705
A73: ORCL | C73: =IFERROR(C25/B25-1,"") -> 0.053097345 | D73: =IFERROR(D25/C25-1,"") -> -0.071428571 | E73: =IFERROR(E25/D25-1,"") -> -0.063348416 | F73: =IFERROR(F25/E25-1,"") -> 0.06763285 | G73: =IFERROR(G25/F25-1,"") -> -0.59276018 | H73: =IFERROR(H25/G25-1,"") -> 2.3 | I73: =IFERROR(I25/H25-1,"") -> 0.037037037 | J73: =IFERROR(J25/I25-1,"") -> 0.47727273 | ... S73: =IFERROR(S25/R25-1,"") -> 0.30023274

Sheet 6. Depreciation Sensitivity
A1: D&AAnalysis: Based on MSFT Actual PP&E Breakdown's Proxy
A3: A. MSFT Actual PP&E/Capex Breakdown (SEC filing)
A4: MSFT Capex Sheet actual PP&E analysis. Company-level asset breakdown.
A5: Metric (MSFT FY) | B5: FY2020A | C5: FY2021A | D5: FY2022A | E5: FY2023A | F5: FY2024A | G5: FY2025A | H5: FY2026E | I5: FY2027E | J5: FY2028E | K5: FY2029E | L5: FY2030E
A6: IT Equipment Capex ($mm) | B6: 7438 | C6: 9989 | D6: 9381 | E6: 14330 | F6: 18819 | G6: 41432 | H6: 85947 | I6: 144612 | J6: 166321 | K6: 174122 | L6: 176677
A7: Buildings Capex ($mm) | B7: 4377 | C7: 6197 | D7: 7805 | E7: 10301 | F7: 13768 | G7: 36747 | H7: 50201 | I7: 83886 | J7: 100380 | K7: 105090 | L7: 106632
A8: Finance Leases Capex ($mm) | B8: 3330 | C8: 3736 | D8: 3281 | E8: 3150 | F8: 11710 | G8: 21628 | H8: 32878 | I8: 42085 | J8: 37876 | K8: 30301 | L8: 21211
A9: Capex ($mm) | B9: 396 | C9: 2380 | D9: 2525 | E9: 2053 | F9: 3823 | G9: 10020 | H9: 9745 | I9: 16765 | J9: 20059 | K9: 20999 | L9: 21308
A10: Total Capex ($mm) | B10: 19000 | C10: 24200 | D10: 29200 | E10: 31900 | F10: 55700 | G10: 88200 | H10: 145871 | I10: 245263 | J10: 286760 | K10: 300211 | L10: 304616
A11: IT Equipment % of Capex | B11: 0.39 | C11: 0.41 | D11: 0.32 | E11: 0.45 | F11: 0.34 | G11: 0.47 | H11: 0.59 | I11: 0.59 | J11: 0.58 | K11: 0.58 | L11: 0.58
A12: IT Equipment D&A ($mm) | E12: 2231 | F12: 10063 | G12: 14563 | H12: 23911 | I12: 43743 | J12: 68286 | K12: 94877 | L12: 121252
A13: Buildings D&A ($mm) | E13: 680 | F13: 3304 | G13: 5132 | H13: 8149 | I13: 12605 | J13: 18775 | K13: 25426 | L13: 32434
A14: Total D&A ($mm) | B14: 10700 | C14: 9300 | D14: 12600 | E14: 11000 | F14: 15200 | G14: 22000 | H14: 34839 | I14: 59542 | J14: 92995 | K14: 129654 | L14: 165840
A15: IT D&A % of TotalD&A | E15: 0.2 | F15: 0.66 | G15: 0.66 | H15: 0.69 | I15: 0.73 | J15: 0.73 | K15: 0.73 | L15: 0.73
A16: IT EquipmentUseful Life | B16: 6 | C16: 6 | D16: 6 | E16: 6 | F16: 6 | G16: 6 | H16: 6 | I16: 6 | J16: 6 | K16: 6 | L16: 6
A17: BuildingsUseful Life | B17: 15 | C17: 15 | D17: 15 | E17: 15 | F17: 15 | G17: 15 | H17: 15 | I17: 15 | J17: 15 | K17: 15 | L17: 15
A19: 📌 Key Finding: IT Equipment pre-AI 's ~35% jumped to AI 's 59%. IT contributes 66-73% 'sTotalD&A (because IT 6Year vs Buildings 15Year). This is Burry thesis attack surface.
A21: B. IT EquipmentShare ofEstimation: MSFT Hard Data → 4 Proxy (⚠️ Estimate)
A22: Company | B22: IT EquipmentShare of Capex | C22: Estimation Basis (Confidence) | D22: IT Equipment Useful Life | E22: Buildings+ Share ofCapex% | F22: Buildings Useful Life | G22: (/)% | H22: Useful Life
A23: MSFT | B23: 0.59 | C23: ✅ Hard Data: Capex sheet Row 90 = 50.1% gross PP&E; capex share 59% | D23: 6 | E23: 0.36 | F23: 15 | G23: 0.05 | H23: 10
A24: AMZN | B24: 0.42 | C24: ⚠️ : 10-K Equipment $185B //; AWS ~40-45% (Behind the Balance SheetAnalysis) | D24: 5 | E24: 0.35 | F24: 18 | G24: 0.23 | H24: 8
A25: GOOGL | B25: 0.57 | C25: ⚠️ : MBI Deep Dives IT assets ~45% of PP&E; capex share (TPUIT) | D25: 6 | E25: 0.35 | F25: 20 | G25: 0.08 | H25: 10
A26: META | B26: 0.62 | C26: ⚠️ : Company, /; 1.3M GPU; server+networkPP&E (MBI) | D26: 5.5 | E26: 0.33 | F26: 22 | G26: 0.05 | H26: 10
A27: ORCL | B27: 0.5 | C27: ⚠️ : OCI, buildings; But+GPU; ITShare of | D27: 5.5 | E27: 0.4 | F27: 20 | G27: 0.1 | H27: 10
A30: C. 2026E / 2027E Base Data (From Database Sheet)
A31: Company | B31: 2026E Capex ($mm) | C31: 2026E D&A ($mm) | D31: 2026E NI ($mm) | E31: 2026E EPS ($) | F31: Shares (mm) | G31: Tax Rate (Editable) | H31: Depr Base = Capex×wtd life | I31: 2027E Capex ($mm) | J31: 2027E D&A ($mm) | K31: 2027E NI ($mm) | L31: 2027E EPS ($)
A32: MSFT | B32: ='0. Database'!P12 -> 145871.3 | C32: ='0. Database'!P11 -> 42005.11 | D32: ='0. Database'!P7 -> 129372.86 | E32: ='0. Database'!P8 -> 17.28 | F32: ='0. Database'!P9 -> 7425.9 | G32: 0.18 | H32: =$C$32*($B$23*$D$23+$E$23*$F$23+$G$23*$H$23) -> 396528.24 | I32: ='0. Database'!Q12 -> 245263.45 | J32: ='0. Database'!Q11 -> 55415.31 | K32: ='0. Database'!Q7 -> 144971.56 | L32: ='0. Database'!Q8 -> 19.42
A33: AMZN | B33: ='0. Database'!P28 -> 200104.98 | C33: ='0. Database'!P27 -> 84391.58 | D33: ='0. Database'!P23 -> 98333.72 | E33: ='0. Database'!P24 -> 8.79 | F33: ='0. Database'!P25 -> 10862.95 | G33: 0.2 | H33: =$C$33*($B$24*$D$24+$E$24*$F$24+$G$24*$H$24) -> 864169.78 | I33: ='0. Database'!Q28 -> 270141.72 | J33: ='0. Database'!Q27 -> 107181.82 | K33: ='0. Database'!Q23 -> 116218.4 | L33: ='0. Database'!Q24 -> 10.03
A34: GOOGL | B34: ='0. Database'!P43 -> 185234.28 | C34: ='0. Database'!P42 -> 42874.7 | D34: ='0. Database'!P38 -> 168543.28 | E34: ='0. Database'!P39 -> 14.19 | F34: ='0. Database'!P40 -> 12096.35 | G34: 0.16 | H34: =$C$34*($B$25*$D$25+$E$25*$F$25+$G$25*$H$25) -> 481054.13 | I34: ='0. Database'!Q43 -> 259327.99 | J34: ='0. Database'!Q42 -> 69582.72 | K34: ='0. Database'!Q38 -> 174626.97 | L34: ='0. Database'!Q39 -> 14.69
A35: META | B35: ='0. Database'!P60 -> 135583.71 | C35: ='0. Database'!P59 -> 29596.55 | D35: ='0. Database'!P55 -> 85782.86 | E35: ='0. Database'!P56 -> 32.2 | F35: ='0. Database'!P57 -> 2541.31 | G35: 0.13 | H35: =$C$35*($B$26*$D$26+$E$26*$F$26+$G$26*$H$26) -> 330593.46 | I35: ='0. Database'!Q60 -> 165714.44 | J35: ='0. Database'!Q59 -> 43105.48 | K35: ='0. Database'!Q55 -> 91160.94 | L35: ='0. Database'!Q56 -> 34.9
A36: ORCL | B36: ='0. Database'!P78 -> 51882 | C36: ='0. Database'!P77 -> 9142.32 | D36: ='0. Database'!P73 -> 15820.55 | E36: ='0. Database'!P74 -> 5.85 | F36: ='0. Database'!P75 -> 2864.8 | G36: 0.2 | H36: =$C$36*($B$27*$D$27+$E$27*$F$27+$G$27*$H$27) -> 107422.26 | I36: ='0. Database'!Q78 -> 52141.41 | J36: ='0. Database'!Q77 -> 13499.83 | K36: ='0. Database'!Q73 -> 13363.1 | L36: ='0. Database'!Q74 -> 6.26
A39: D. Core Sensitivity: Compress Only IT Equipment (Buildings/) — Straight-Line
A40: Logic: D&A = ITD&A + Buildings + . ITBurry.
A41: IT Equipment = 6 Year (Buildings/)
A42: Company | B42: ITD&A ($mm) | C42: BuildingsD&A (,$mm) | D42: D&A (,$mm) | E42: New Total D&A ($mm) | F42: Current D&A ($mm) | G42: ΔD&A ($mm) | H42: Δ ($mm) | I42: Adj NI ($mm) | J42: Adj EPS ($) | K42: EPS Change%
A43: MSFT | B43: =$H$32*$B$23/6 -> 38991.943 | C43: =$H$32*$E$23/$F$23 -> 9516.6777 | D43: =$H$32*$G$23/$H$23 -> 1982.6412 | E43: =$B$43+$C$43+$D$43 -> 50491.262 | F43: =$C$32 -> 42005.11 | G43: =$E$43-$C$32 -> 8486.1524 | H43: =$G$43*(1-$G$32) -> 6958.6449 | I43: =$D$32-$H$43 -> 122414.22 | J43: =$I$43/$F$32 -> 16.484765 | K43: =IFERROR($J$43/$E$32-1,"") -> -0.046020554
A44: AMZN | B44: =$H$33*$B$24/6 -> 60491.885 | C44: =$H$33*$E$24/$F$24 -> 16803.301 | D44: =$H$33*$G$24/$H$24 -> 24844.881 | E44: =$B$44+$C$44+$D$44 -> 102140.07 | F44: =$C$33 -> 84391.58 | G44: =$E$44-$C$33 -> 17748.487 | H44: =$G$44*(1-$G$33) -> 14198.79 | I44: =$D$33-$H$44 -> 84134.93 | J44: =$I$44/$F$33 -> 7.7451273 | K44: =IFERROR($J$44/$E$33-1,"") -> -0.11887062
A45: GOOGL | B45: =$H$34*$B$25/6 -> 45700.143 | C45: =$H$34*$E$25/$F$25 -> 8418.4473 | D45: =$H$34*$G$25/$H$25 -> 3848.4331 | E45: =$B$45+$C$45+$D$45 -> 57967.023 | F45: =$C$34 -> 42874.7 | G45: =$E$45-$C$34 -> 15092.323 | H45: =$G$45*(1-$G$34) -> 12677.551 | I45: =$D$34-$H$45 -> 155865.73 | J45: =$I$45/$F$34 -> 12.885352 | K45: =IFERROR($J$45/$E$34-1,"") -> -0.091941362
A46: META | B46: =$H$35*$B$26/6 -> 34161.325 | C46: =$H$35*$E$26/$F$26 -> 4958.902 | D46: =$H$35*$G$26/$H$26 -> 1652.9673 | E46: =$B$46+$C$46+$D$46 -> 40773.194 | F46: =$C$35 -> 29596.55 | G46: =$E$46-$C$35 -> 11176.644 | H46: =$G$46*(1-$G$35) -> 9723.6801 | I46: =$D$35-$H$46 -> 76059.18 | J46: =$I$46/$F$35 -> 29.929123 | K46: =IFERROR($J$46/$E$35-1,"") -> -0.070524127
A47: ORCL | B47: =$H$36*$B$27/6 -> 8951.855 | C47: =$H$36*$E$27/$F$27 -> 2148.4452 | D47: =$H$36*$G$27/$H$27 -> 1074.2226 | E47: =$B$47+$C$47+$D$47 -> 12174.523 | F47: =$C$36 -> 9142.32 | G47: =$E$47-$C$36 -> 3032.2028 | H47: =$G$47*(1-$G$36) -> 2425.7622 | I47: =$D$36-$H$47 -> 13394.788 | J47: =$I$47/$F$36 -> 4.675645 | K47: =IFERROR($J$47/$E$36-1,"") -> -0.20074445
A49: IT Equipment = 5 Year (Buildings/)
A50: Company | B50: ITD&A ($mm) | C50: BuildingsD&A (,$mm) | D50: D&A (,$mm) | E50: New Total D&A ($mm) | F50: Current D&A ($mm) | G50: ΔD&A ($mm) | H50: Δ ($mm) | I50: Adj NI ($mm) | J50: Adj EPS ($) | K50: EPS Change%
A51: MSFT | B51: =$H$32*$B$23/5 -> 46790.332 | C51: =$H$32*$E$23/$F$23 -> 9516.6777 | D51: =$H$32*$G$23/$H$23 -> 1982.6412 | E51: =$B$51+$C$51+$D$51 -> 58289.651 | F51: =$C$32 -> 42005.11 | G51: =$E$51-$C$32 -> 16284.541 | H51: =$G$51*(1-$G$32) -> 13353.324 | I51: =$D$32-$H$51 -> 116019.54 | J51: =$I$51/$F$32 -> 15.623633 | K51: =IFERROR($J$51/$E$32-1,"") -> -0.095854571
A52: AMZN | B52: =$H$33*$B$24/5 -> 72590.261 | C52: =$H$33*$E$24/$F$24 -> 16803.301 | D52: =$H$33*$G$24/$H$24 -> 24844.881 | E52: =$B$52+$C$52+$D$52 -> 114238.44 | F52: =$C$33 -> 84391.58 | G52: =$E$52-$C$33 -> 29846.864 | H52: =$G$52*(1-$G$33) -> 23877.491 | I52: =$D$33-$H$52 -> 74456.229 | J52: =$I$52/$F$33 -> 6.8541445 | K52: =IFERROR($J$52/$E$33-1,"") -> -0.22023385
A53: GOOGL | B53: =$H$34*$B$25/5 -> 54840.171 | C53: =$H$34*$E$25/$F$25 -> 8418.4473 | D53: =$H$34*$G$25/$H$25 -> 3848.4331 | E53: =$B$53+$C$53+$D$53 -> 67107.052 | F53: =$C$34 -> 42874.7 | G53: =$E$53-$C$34 -> 24232.352 | H53: =$G$53*(1-$G$34) -> 20355.175 | I53: =$D$34-$H$53 -> 148188.1 | J53: =$I$53/$F$34 -> 12.250646 | K53: =IFERROR($J$53/$E$34-1,"") -> -0.13667046
A54: META | B54: =$H$35*$B$26/5 -> 40993.589 | C54: =$H$35*$E$26/$F$26 -> 4958.902 | D54: =$H$35*$G$26/$H$26 -> 1652.9673 | E54: =$B$54+$C$54+$D$54 -> 47605.459 | F54: =$C$35 -> 29596.55 | G54: =$E$54-$C$35 -> 18008.909 | H54: =$G$54*(1-$G$35) -> 15667.751 | I54: =$D$35-$H$54 -> 70115.109 | J54: =$I$54/$F$35 -> 27.590144 | K54: =IFERROR($J$54/$E$35-1,"") -> -0.14316322
A55: ORCL | B55: =$H$36*$B$27/5 -> 10742.226 | C55: =$H$36*$E$27/$F$27 -> 2148.4452 | D55: =$H$36*$G$27/$H$27 -> 1074.2226 | E55: =$B$55+$C$55+$D$55 -> 13964.894 | F55: =$C$36 -> 9142.32 | G55: =$E$55-$C$36 -> 4822.5738 | H55: =$G$55*(1-$G$36) -> 3858.059 | I55: =$D$36-$H$55 -> 11962.491 | J55: =$I$55/$F$36 -> 4.175681 | K55: =IFERROR($J$55/$E$36-1,"") -> -0.28620837
A57: IT Equipment = 4 Year (Buildings/)
A58: Company | B58: ITD&A ($mm) | C58: BuildingsD&A (,$mm) | D58: D&A (,$mm) | E58: New Total D&A ($mm) | F58: Current D&A ($mm) | G58: ΔD&A ($mm) | H58: Δ ($mm) | I58: Adj NI ($mm) | J58: Adj EPS ($) | K58: EPS Change%
A59: MSFT | B59: =$H$32*$B$23/4 -> 58487.915 | C59: =$H$32*$E$23/$F$23 -> 9516.6777 | D59: =$H$32*$G$23/$H$23 -> 1982.6412 | E59: =$B$59+$C$59+$D$59 -> 69987.234 | F59: =$C$32 -> 42005.11 | G59: =$E$59-$C$32 -> 27982.124 | H59: =$G$59*(1-$G$32) -> 22945.342 | I59: =$D$32-$H$59 -> 106427.52 | J59: =$I$59/$F$32 -> 14.331935 | K59: =IFERROR($J$59/$E$32-1,"") -> -0.1706056
A60: AMZN | B60: =$H$33*$B$24/4 -> 90737.827 | C60: =$H$33*$E$24/$F$24 -> 16803.301 | D60: =$H$33*$G$24/$H$24 -> 24844.881 | E60: =$B$60+$C$60+$D$60 -> 132386.01 | F60: =$C$33 -> 84391.58 | G60: =$E$60-$C$33 -> 47994.429 | H60: =$G$60*(1-$G$33) -> 38395.543 | I60: =$D$33-$H$60 -> 59938.177 | J60: =$I$60/$F$33 -> 5.5176703 | K60: =IFERROR($J$60/$E$33-1,"") -> -0.37227869
A61: GOOGL | B61: =$H$34*$B$25/4 -> 68550.214 | C61: =$H$34*$E$25/$F$25 -> 8418.4473 | D61: =$H$34*$G$25/$H$25 -> 3848.4331 | E61: =$B$61+$C$61+$D$61 -> 80817.095 | F61: =$C$34 -> 42874.7 | G61: =$E$61-$C$34 -> 37942.395 | H61: =$G$61*(1-$G$34) -> 31871.611 | I61: =$D$34-$H$61 -> 136671.67 | J61: =$I$61/$F$34 -> 11.298587 | K61: =IFERROR($J$61/$E$34-1,"") -> -0.2037641
A62: META | B62: =$H$35*$B$26/4 -> 51241.987 | C62: =$H$35*$E$26/$F$26 -> 4958.902 | D62: =$H$35*$G$26/$H$26 -> 1652.9673 | E62: =$B$62+$C$62+$D$62 -> 57853.856 | F62: =$C$35 -> 29596.55 | G62: =$E$62-$C$35 -> 28257.306 | H62: =$G$62*(1-$G$35) -> 24583.856 | I62: =$D$35-$H$62 -> 61199.004 | J62: =$I$62/$F$35 -> 24.081676 | K62: =IFERROR($J$62/$E$35-1,"") -> -0.25212187
A63: ORCL | B63: =$H$36*$B$27/4 -> 13427.782 | C63: =$H$36*$E$27/$F$27 -> 2148.4452 | D63: =$H$36*$G$27/$H$27 -> 1074.2226 | E63: =$B$63+$C$63+$D$63 -> 16650.45 | F63: =$C$36 -> 9142.32 | G63: =$E$63-$C$36 -> 7508.1303 | H63: =$G$63*(1-$G$36) -> 6006.5042 | I63: =$D$36-$H$63 -> 9814.0458 | J63: =$I$63/$F$36 -> 3.425735 | K63: =IFERROR($J$63/$E$36-1,"") -> -0.41440427
A65: IT Equipment = 3 Year (Buildings/)
A66: Company | B66: ITD&A ($mm) | C66: BuildingsD&A (,$mm) | D66: D&A (,$mm) | E66: New Total D&A ($mm) | F66: Current D&A ($mm) | G66: ΔD&A ($mm) | H66: Δ ($mm) | I66: Adj NI ($mm) | J66: Adj EPS ($) | K66: EPS Change%
A67: MSFT | B67: =$H$32*$B$23/3 -> 77983.887 | C67: =$H$32*$E$23/$F$23 -> 9516.6777 | D67: =$H$32*$G$23/$H$23 -> 1982.6412 | E67: =$B$67+$C$67+$D$67 -> 89483.206 | F67: =$C$32 -> 42005.11 | G67: =$E$67-$C$32 -> 47478.096 | H67: =$G$67*(1-$G$32) -> 38932.039 | I67: =$D$32-$H$67 -> 90440.821 | J67: =$I$67/$F$32 -> 12.179106 | K67: =IFERROR($J$67/$E$32-1,"") -> -0.29519064
A68: AMZN | B68: =$H$33*$B$24/3 -> 120983.77 | C68: =$H$33*$E$24/$F$24 -> 16803.301 | D68: =$H$33*$G$24/$H$24 -> 24844.881 | E68: =$B$68+$C$68+$D$68 -> 162631.95 | F68: =$C$33 -> 84391.58 | G68: =$E$68-$C$33 -> 78240.372 | H68: =$G$68*(1-$G$33) -> 62592.297 | I68: =$D$33-$H$68 -> 35741.423 | J68: =$I$68/$F$33 -> 3.2902133 | K68: =IFERROR($J$68/$E$33-1,"") -> -0.62568677
A69: GOOGL | B69: =$H$34*$B$25/3 -> 91400.285 | C69: =$H$34*$E$25/$F$25 -> 8418.4473 | D69: =$H$34*$G$25/$H$25 -> 3848.4331 | E69: =$B$69+$C$69+$D$69 -> 103667.17 | F69: =$C$34 -> 42874.7 | G69: =$E$69-$C$34 -> 60792.466 | H69: =$G$69*(1-$G$34) -> 51065.671 | I69: =$D$34-$H$69 -> 117477.61 | J69: =$I$69/$F$34 -> 9.7118229 | K69: =IFERROR($J$69/$E$34-1,"") -> -0.31558683
A70: META | B70: =$H$35*$B$26/3 -> 68322.649 | C70: =$H$35*$E$26/$F$26 -> 4958.902 | D70: =$H$35*$G$26/$H$26 -> 1652.9673 | E70: =$B$70+$C$70+$D$70 -> 74934.518 | F70: =$C$35 -> 29596.55 | G70: =$E$70-$C$35 -> 45337.968 | H70: =$G$70*(1-$G$35) -> 39444.033 | I70: =$D$35-$H$70 -> 46338.827 | J70: =$I$70/$F$35 -> 18.234229 | K70: =IFERROR($J$70/$E$35-1,"") -> -0.43371961
A71: ORCL | B71: =$H$36*$B$27/3 -> 17903.71 | C71: =$H$36*$E$27/$F$27 -> 2148.4452 | D71: =$H$36*$G$27/$H$27 -> 1074.2226 | E71: =$B$71+$C$71+$D$71 -> 21126.378 | F71: =$C$36 -> 9142.32 | G71: =$E$71-$C$36 -> 11984.058 | H71: =$G$71*(1-$G$36) -> 9587.2462 | I71: =$D$36-$H$71 -> 6233.3038 | J71: =$I$71/$F$36 -> 2.1758251 | K71: =IFERROR($J$71/$E$36-1,"") -> -0.62806408
A73: IT Equipment = 2 Year (Buildings/)
A74: Company | B74: ITD&A ($mm) | C74: BuildingsD&A (,$mm) | D74: D&A (,$mm) | E74: New Total D&A ($mm) | F74: Current D&A ($mm) | G74: ΔD&A ($mm) | H74: Δ ($mm) | I74: Adj NI ($mm) | J74: Adj EPS ($) | K74: EPS Change%
A75: MSFT | B75: =$H$32*$B$23/2 -> 116975.83 | C75: =$H$32*$E$23/$F$23 -> 9516.6777 | D75: =$H$32*$G$23/$H$23 -> 1982.6412 | E75: =$B$75+$C$75+$D$75 -> 128475.15 | F75: =$C$32 -> 42005.11 | G75: =$E$75-$C$32 -> 86470.039 | H75: =$G$75*(1-$G$32) -> 70905.432 | I75: =$D$32-$H$75 -> 58467.428 | J75: =$I$75/$F$32 -> 7.8734467 | K75: =IFERROR($J$75/$E$32-1,"") -> -0.54436072
A76: AMZN | B76: =$H$33*$B$24/2 -> 181475.65 | C76: =$H$33*$E$24/$F$24 -> 16803.301 | D76: =$H$33*$G$24/$H$24 -> 24844.881 | E76: =$B$76+$C$76+$D$76 -> 223123.84 | F76: =$C$33 -> 84391.58 | G76: =$E$76-$C$33 -> 138732.26 | H76: =$G$76*(1-$G$33) -> 110985.8 | I76: =$D$33-$H$76 -> -12652.085 | J76: =$I$76/$F$33 -> -1.1647006 | K76: =IFERROR($J$76/$E$33-1,"") -> -1.1325029
A77: GOOGL | B77: =$H$34*$B$25/2 -> 137100.43 | C77: =$H$34*$E$25/$F$25 -> 8418.4473 | D77: =$H$34*$G$25/$H$25 -> 3848.4331 | E77: =$B$77+$C$77+$D$77 -> 149367.31 | F77: =$C$34 -> 42874.7 | G77: =$E$77-$C$34 -> 106492.61 | H77: =$G$77*(1-$G$34) -> 89453.791 | I77: =$D$34-$H$77 -> 79089.489 | J77: =$I$77/$F$34 -> 6.5382937 | K77: =IFERROR($J$77/$E$34-1,"") -> -0.5392323
A78: META | B78: =$H$35*$B$26/2 -> 102483.97 | C78: =$H$35*$E$26/$F$26 -> 4958.902 | D78: =$H$35*$G$26/$H$26 -> 1652.9673 | E78: =$B$78+$C$78+$D$78 -> 109095.84 | F78: =$C$35 -> 29596.55 | G78: =$E$78-$C$35 -> 79499.293 | H78: =$G$78*(1-$G$35) -> 69164.385 | I78: =$D$35-$H$78 -> 16618.475 | J78: =$I$78/$F$35 -> 6.5393341 | K78: =IFERROR($J$78/$E$35-1,"") -> -0.79691509
A79: ORCL | B79: =$H$36*$B$27/2 -> 26855.565 | C79: =$H$36*$E$27/$F$27 -> 2148.4452 | D79: =$H$36*$G$27/$H$27 -> 1074.2226 | E79: =$B$79+$C$79+$D$79 -> 30078.233 | F79: =$C$36 -> 9142.32 | G79: =$E$79-$C$36 -> 20935.913 | H79: =$G$79*(1-$G$36) -> 16748.73 | I79: =$D$36-$H$79 -> -928.18024 | J79: =$I$79/$F$36 -> -0.32399478 | K79: =IFERROR($J$79/$E$36-1,"") -> -1.0553837
A82: E. Summary: 2026E EPS (%) — Compress OnlyIT Equipment vs Burry'sFull Compression Comparison
A83: ★ Adjusted Method = IT Equipment, Buildings/. BurryFull Compression = D&A ().
A84: Company | B84: ITShare of (Source) | C84: Current | D84: ★Adjusted Method IT→4yr EPS Δ% | E84: ★Adjusted Method IT→3yr EPS Δ% | F84: Burry →4yr EPS Δ% | G84: Burry →3yr EPS Δ% | H84: Adjusted Method (vs) | I84: Conclusion
A85: MSFT | B85: =$B$23 -> 0.59 | C85: =$B$23*$D$23+$E$23*$F$23+$G$23*$H$23 -> 9.44 | D85: =IFERROR(($D$32-($H$32*$B$23/4+$H$32*$E$23/$F$23+$H$32*$G$23/$H$23-$C$32)*(1-$G$32))/$F$32/$E$32-1,"") -> -0.1706056 | E85: =IFERROR(($D$32-($H$32*$B$23/3+$H$32*$E$23/$F$23+$H$32*$G$23/$H$23-$C$32)*(1-$G$32))/$F$32/$E$32-1,"") -> -0.29519064 | F85: =IFERROR(($D$32-($C$32*($B$23*$D$23+$E$23*$F$23+$G$23*$H$23)/4-$C$32)*(1-$G$32))/$F$32/$E$32-1,"") -> -0.35684968 | G85: =IFERROR(($D$32-($C$32*($B$23*$D$23+$E$23*$F$23+$G$23*$H$23)/3-$C$32)*(1-$G$32))/$F$32/$E$32-1,"") -> -0.56801077 | H85: =IFERROR(E85/G85,"") -> 0.51969198 | I85: . ITShare ofHard Data. 4.9yr.
A86: AMZN | B86: =$B$24 -> 0.42 | C86: =$B$24*$D$24+$E$24*$F$24+$G$24*$H$24 -> 10.24 | D86: =IFERROR(($D$33-($H$33*$B$24/4+$H$33*$E$24/$F$24+$H$33*$G$24/$H$24-$C$33)*(1-$G$33))/$F$33/$E$33-1,"") -> -0.37227869 | E86: =IFERROR(($D$33-($H$33*$B$24/3+$H$33*$E$24/$F$24+$H$33*$G$24/$H$24-$C$33)*(1-$G$33))/$F$33/$E$33-1,"") -> -0.62568677 | F86: =IFERROR(($D$33-($C$33*($B$24*$D$24+$E$24*$F$24+$G$24*$H$24)/4-$C$33)*(1-$G$33))/$F$33/$E$33-1,"") -> -1.0731732 | G86: =IFERROR(($D$33-($C$33*($B$24*$D$24+$E$24*$F$24+$G$24*$H$24)/3-$C$33)*(1-$G$33))/$F$33/$E$33-1,"") -> -1.6765258 | H86: =IFERROR(E86/G86,"") -> 0.37320437 | I86: . ButD&A, .
A87: GOOGL | B87: =$B$25 -> 0.57 | C87: =$B$25*$D$25+$E$25*$F$25+$G$25*$H$25 -> 11.22 | D87: =IFERROR(($D$34-($H$34*$B$25/4+$H$34*$E$25/$F$25+$H$34*$G$25/$H$25-$C$34)*(1-$G$34))/$F$34/$E$34-1,"") -> -0.2037641 | E87: =IFERROR(($D$34-($H$34*$B$25/3+$H$34*$E$25/$F$25+$H$34*$G$25/$H$25-$C$34)*(1-$G$34))/$F$34/$E$34-1,"") -> -0.31558683 | F87: =IFERROR(($D$34-($C$34*($B$25*$D$25+$E$25*$F$25+$G$25*$H$25)/4-$C$34)*(1-$G$34))/$F$34/$E$34-1,"") -> -0.39680545 | G87: =IFERROR(($D$34-($C$34*($B$25*$D$25+$E$25*$F$25+$G$25*$H$25)/3-$C$34)*(1-$G$34))/$F$34/$E$34-1,"") -> -0.59298568 | H87: =IFERROR(E87/G87,"") -> 0.53219975 | I87: TPU. ITShare of.
A88: META | B88: =$B$26 -> 0.62 | C88: =$B$26*$D$26+$E$26*$F$26+$G$26*$H$26 -> 11.17 | D88: =IFERROR(($D$35-($H$35*$B$26/4+$H$35*$E$26/$F$26+$H$35*$G$26/$H$26-$C$35)*(1-$G$35))/$F$35/$E$35-1,"") -> -0.25212187 | E88: =IFERROR(($D$35-($H$35*$B$26/3+$H$35*$E$26/$F$26+$H$35*$G$26/$H$26-$C$35)*(1-$G$35))/$F$35/$E$35-1,"") -> -0.43371961 | F88: =IFERROR(($D$35-($C$35*($B$26*$D$26+$E$26*$F$26+$G$26*$H$26)/4-$C$35)*(1-$G$35))/$F$35/$E$35-1,"") -> -0.51573149 | G88: =IFERROR(($D$35-($C$35*($B$26*$D$26+$E$26*$F$26+$G$26*$H$26)/3-$C$35)*(1-$G$35))/$F$35/$E$35-1,"") -> -0.80863107 | H88: =IFERROR(E88/G88,"") -> 0.53636278 | I88: GPU'sDCCompany. .
A89: ORCL | B89: =$B$27 -> 0.5 | C89: =$B$27*$D$27+$E$27*$F$27+$G$27*$H$27 -> 11.75 | D89: =IFERROR(($D$36-($H$36*$B$27/4+$H$36*$E$27/$F$27+$H$36*$G$27/$H$27-$C$36)*(1-$G$36))/$F$36/$E$36-1,"") -> -0.41440427 | E89: =IFERROR(($D$36-($H$36*$B$27/3+$H$36*$E$27/$F$27+$H$36*$G$27/$H$27-$C$36)*(1-$G$36))/$F$36/$E$36-1,"") -> -0.62806408 | F89: =IFERROR(($D$36-($C$36*($B$27*$D$27+$E$27*$F$27+$G$27*$H$27)/4-$C$36)*(1-$G$36))/$F$36/$E$36-1,"") -> -0.90154865 | G89: =IFERROR(($D$36-($C$36*($B$27*$D$27+$E$27*$F$27+$G$27*$H$27)/3-$C$36)*(1-$G$36))/$F$36/$E$36-1,"") -> -1.3288683 | H89: =IFERROR(E89/G89,"") -> 0.4726308 | I89: OCI, building. ButNI, .

Sheet 7. SP500 AI EPS Split
A1: S&P 500: AI vs Non-AI EPSBreakdown + Dual P/E Valuation
A3: S&P 500 EPS — Bloomberg Consensus ($)
A4: EPS: FactSet actual (2018-2024), sell-side/consensus estimates (2025+). Capex/Buybacks: sell-side data (May 7 2026 report). Yellow = editable.
A5: Metric | B5: 2018A | C5: 2019A | D5: 2020A | E5: 2021A | F5: 2022A | G5: 2023A | H5: 2024A | I5: 2025A | J5: 2026E | K5: 2027E | L5: 2028E (ext) | M5: 2029E (ext) | N5: 2030E (ext)
A6: S&P 500 Operating EPS ($) | B6: 160 | C6: 165 | D6: 142 | E6: 200 | F6: 224 | G6: 222 | H6: 239 | I6: 269 | J6: 337 | K6: 386 | L6: 420 | M6: 450 | N6: 478
A7: S&P 500Capex ($B) — sell-side data | B7: 644 | C7: 697 | D7: 591 | E7: 739 | F7: 892 | G7: 958 | H7: 1077 | I7: 1296 | J7: 1724 | K7: 2103 | L7: 2400 | M7: 2600 | N7: 2750
A8: AICapex ($B) — 5 cos | B8: 50 | C8: 55 | D8: 60 | E8: 86 | F8: 158 | G8: 154 | H8: 237 | I8: 412 | J8: 755 | K8: 892 | L8: 950 | M8: 980 | N8: 1000
A9: S&P 500 Buybacks ($B) — sell-side data | B9: 770 | C9: 729 | D9: 520 | E9: 919 | F9: 950 | G9: 823 | H9: 982 | I9: 1066 | J9: 1098 | K9: 1153 | L9: 1200 | M9: 1250 | N9: 1300
A11: B. AI-Driven EPS Estimation: Hyperscaler Capex → Supply Chain Profit → S&P 500 EPS
A12: Logic: Hyperscaler capex = revenue for NVDA/AVGO/MU/ANET/etc. Their net margin × capex = AI-driven NI. Divide by S&P 500 share count ≈ AI EPS.
A13: Metric | B13: 2018A | C13: 2019A | D13: 2020A | E13: 2021A | F13: 2022A | G13: 2023A | H13: 2024A | I13: 2025A | J13: 2026E | K13: 2027E | L13: 2028E | M13: 2029E | N13: 2030E
A14: % of Hyp Capex → S&P 500 co revenue (editable) | B14: 0.55 | C14: 0.55 | D14: 0.55 | E14: 0.55 | F14: 0.55 | G14: 0.55 | H14: 0.55 | I14: 0.6 | J14: 0.65 | K14: 0.65 | L14: 0.65 | M14: 0.63 | N14: 0.6
A15: Wtd avg net margin of AI supply chain (editable) | B15: 0.2 | C15: 0.2 | D15: 0.2 | E15: 0.22 | F15: 0.25 | G15: 0.3 | H15: 0.35 | I15: 0.4 | J15: 0.45 | K15: 0.42 | L15: 0.38 | M15: 0.35 | N15: 0.33
A16: AI Revenue to S&P 500 cos ($B) | B16: =B8*B14 -> 27.5 | C16: =C8*C14 -> 30.25 | D16: =D8*D14 -> 33 | E16: =E8*E14 -> 47.3 | F16: =F8*F14 -> 86.9 | G16: =G8*G14 -> 84.7 | H16: =H8*H14 -> 130.35 | I16: =I8*I14 -> 247.2 | ... N16: =N8*N14 -> 600
A17: AI Net Income to S&P 500 cos ($B) | B17: =B16*B15 -> 5.5 | C17: =C16*C15 -> 6.05 | D17: =D16*D15 -> 6.6 | E17: =E16*E15 -> 10.406 | F17: =F16*F15 -> 21.725 | G17: =G16*G15 -> 25.41 | H17: =H16*H15 -> 45.6225 | I17: =I16*I15 -> 98.88 | ... N17: =N16*N15 -> 198
A18: S&P 500TotalNet Income ($B) ≈ EPS × 8.8B shares (S&P 500 Index Divisor) | B18: =B6*8.8 -> 1408 | C18: =C6*8.8 -> 1452 | D18: =D6*8.8 -> 1249.6 | E18: =E6*8.8 -> 1760 | F18: =F6*8.8 -> 1971.2 | G18: =G6*8.8 -> 1953.6 | H18: =H6*8.8 -> 2103.2 | I18: =I6*8.8 -> 2367.2 | ... N18: =N6*8.8 -> 4206.4
A19: AI-Driven EPS ($) = AI NI / 8.8B shares (S&P 500 Index Divisor) | B19: =B17/8.8 -> 0.625 | C19: =C17/8.8 -> 0.6875 | D19: =D17/8.8 -> 0.75 | E19: =E17/8.8 -> 1.1825 | F19: =F17/8.8 -> 2.46875 | G19: =G17/8.8 -> 2.8875 | H19: =H17/8.8 -> 5.184375 | I19: =I17/8.8 -> 11.236364 | ... N19: =N17/8.8 -> 22.5
A20: Non-AI EPS ($) = Total - AI | B20: =B6-B19 -> 159.375 | C20: =C6-C19 -> 164.3125 | D20: =D6-D19 -> 141.25 | E20: =E6-E19 -> 198.8175 | F20: =F6-F19 -> 221.53125 | G20: =G6-G19 -> 219.1125 | H20: =H6-H19 -> 233.81563 | I20: =I6-I19 -> 257.76364 | ... N20: =N6-N19 -> 455.5
A21: AI % of Total EPS | B21: =IFERROR(B19/B6,"") -> 0.00390625 | C21: =IFERROR(C19/C6,"") -> 0.0041666667 | D21: =IFERROR(D19/D6,"") -> 0.0052816901 | E21: =IFERROR(E19/E6,"") -> 0.0059125 | F21: =IFERROR(F19/F6,"") -> 0.011021205 | G21: =IFERROR(G19/G6,"") -> 0.013006757 | H21: =IFERROR(H19/H6,"") -> 0.021691946 | I21: =IFERROR(I19/I6,"") -> 0.041770869 | ... N21: =IFERROR(N19/N6,"") -> 0.04707113
A22: AI EPS YoY % | C22: =IFERROR(C19/B19-1,"") -> 0.1 | D22: =IFERROR(D19/C19-1,"") -> 0.090909091 | E22: =IFERROR(E19/D19-1,"") -> 0.57666667 | F22: =IFERROR(F19/E19-1,"") -> 1.0877378 | G22: =IFERROR(G19/F19-1,"") -> 0.16962025 | H22: =IFERROR(H19/G19-1,"") -> 0.79545455 | I22: =IFERROR(I19/H19-1,"") -> 1.1673516 | J22: =IFERROR(J19/I19-1,"") -> 1.233389 | ... N22: =IFERROR(N19/M19-1,"") -> -0.083715119
A24: C. Dual P/E Valuation — Separate Multiples for AI vs Non-AI EPS
A25: AI P/E (editable) — hist avg ~18x | B25: 21
A26: AI P/E (editable) — NVDA ~30-40x fwd | B26: 40
A28: Valuation Component | B28: 2024A | C28: 2025A | D28: 2026E | E28: 2027E | F28: 2028E | G28: 2029E | H28: 2030E
A29: AI = Non-AI EPS × P/E | B29: =H20*$B$25 -> 4910.1281 | C29: =I20*$B$25 -> 5413.0364 | D29: =J20*$B$25 -> 6550.0014 | E29: =K20*$B$25 -> 7524.8823 | F29: =L20*$B$25 -> 8260.0398 | G29: =M20*$B$25 -> 8934.3307 | H29: =N20*$B$25 -> 9565.5
A30: AI = AI EPS × P/E | B30: =H19*$B$26 -> 207.375 | C30: =I19*$B$26 -> 449.45455 | D30: =J19*$B$26 -> 1003.8068 | E30: =K19*$B$26 -> 1106.8909 | F30: =L19*$B$26 -> 1066.5909 | G30: =M19*$B$26 -> 982.22727 | H30: =N19*$B$26 -> 900
A31: Implied S&P 500 Level | B31: =B29+B30 -> 5117.5031 | C31: =C29+C30 -> 5862.4909 | D31: =D29+D30 -> 7553.8082 | E31: =E29+E30 -> 8631.7732 | F31: =F29+F30 -> 9326.6307 | G31: =G29+G30 -> 9916.558 | H31: =H29+H30 -> 10465.5
A32: Blended P/E (implied) | B32: =IFERROR(B31/H6,"") -> 21.412147 | C32: =IFERROR(C31/I6,"") -> 21.793647 | D32: =IFERROR(D31/J6,"") -> 22.414861 | E32: =IFERROR(E31/K6,"") -> 22.362107 | F32: =IFERROR(F31/L6,"") -> 22.206264 | G32: =IFERROR(G31/M6,"") -> 22.036795 | H32: =IFERROR(H31/N6,"") -> 21.894351
A34: D. Scenario Grid: 2026E Implied S&P 500 Under Different P/E Assumptions
A35: Reads: 'If Non-AI trades at Xpe and AI trades at Ype, 2026E S&P 500 = Z'. Uses AI/Non-AI EPS from Section B. Change yellow cells above to update.
A36: AI P/E ↓ AI P/E → | B36: 22x | C36: 20x | D36: 18x | E36: 16x | F36: 14x
A37: 40x | B37: =J20*22+J19*40 -> 7865.7131 | C37: =J20*20+J19*40 -> 7241.9034 | D37: =J20*18+J19*40 -> 6618.0938 | E37: =J20*16+J19*40 -> 5994.2841 | F37: =J20*14+J19*40 -> 5370.4744
A38: 35x | B38: =J20*22+J19*35 -> 7740.2372 | C38: =J20*20+J19*35 -> 7116.4276 | D38: =J20*18+J19*35 -> 6492.6179 | E38: =J20*16+J19*35 -> 5868.8082 | F38: =J20*14+J19*35 -> 5244.9986
A39: 30x | B39: =J20*22+J19*30 -> 7614.7614 | C39: =J20*20+J19*30 -> 6990.9517 | D39: =J20*18+J19*30 -> 6367.142 | E39: =J20*16+J19*30 -> 5743.3324 | F39: =J20*14+J19*30 -> 5119.5227
A40: 25x | B40: =J20*22+J19*25 -> 7489.2855 | C40: =J20*20+J19*25 -> 6865.4759 | D40: =J20*18+J19*25 -> 6241.6662 | E40: =J20*16+J19*25 -> 5617.8565 | F40: =J20*14+J19*25 -> 4994.0469
A41: 20x | B41: =J20*22+J19*20 -> 7363.8097 | C41: =J20*20+J19*20 -> 6740 | D41: =J20*18+J19*20 -> 6116.1903 | E41: =J20*16+J19*20 -> 5492.3807 | F41: =J20*14+J19*20 -> 4868.571
A42: 15x | B42: =J20*22+J19*15 -> 7238.3338 | C42: =J20*20+J19*15 -> 6614.5241 | D42: =J20*18+J19*15 -> 5990.7145 | E42: =J20*16+J19*15 -> 5366.9048 | F42: =J20*14+J19*15 -> 4743.0952
A43: 10x | B43: =J20*22+J19*10 -> 7112.858 | C43: =J20*20+J19*10 -> 6489.0483 | D43: =J20*18+J19*10 -> 5865.2386 | E43: =J20*16+J19*10 -> 5241.429 | F43: =J20*14+J19*10 -> 4617.6193
A45: E. Stress Test: What Happens to S&P 500 if AI Capex Slows?
A46: Base Case (AI PE=35x, Non-AI PE=18x)
A47: Current. AI capex sustains. NVDA margin holds.
B48: 2024A | C48: 2025A | D48: 2026E | E48: 2027E | F48: 2028E | G48: 2029E | H48: 2030E
A49: AI EPS ($) | B49: =H19 -> 5.184375 | C49: =I19 -> 11.236364 | D49: =J19 -> 25.09517 | E49: =K19 -> 27.672273 | F49: =L19 -> 26.664773 | G49: =M19 -> 24.555682 | H49: =N19 -> 22.5
A50: Non-AI EPS ($) | B50: =H20 -> 233.81563 | C50: =I20 -> 257.76364 | D50: =J20 -> 311.90483 | E50: =K20 -> 358.32773 | F50: =L20 -> 393.33523 | G50: =M20 -> 425.44432 | H50: =N20 -> 455.5
A51: Implied S&P 500 | B51: =B49*$B$26+B50*$B$25 -> 5117.5031 | C51: =C49*$B$26+C50*$B$25 -> 5862.4909 | D51: =D49*$B$26+D50*$B$25 -> 7553.8082 | E51: =E49*$B$26+E50*$B$25 -> 8631.7732 | F51: =F49*$B$26+F50*$B$25 -> 9326.6307 | G51: =G49*$B$26+G50*$B$25 -> 9916.558 | H51: =H49*$B$26+H50*$B$25 -> 10465.5
A53: Capex (AI PE=25x, Non-AI PE=18x)
A54: 2027+ capex growth decelerates to +10%. NVDA margin compresses. AI PE de-rates.
B55: 2024A | C55: 2025A | D55: 2026E | E55: 2027E | F55: 2028E | G55: 2029E | H55: 2030E | I55: AI PE: | J55: 25 | K55: Non-AI PE: | L55: 18
A56: AI EPS ($) | B56: =H19 -> 5.184375 | C56: =I19 -> 11.236364 | D56: =J19*0.93 -> 23.338509 | E56: =K19*0.82 -> 22.691264 | F56: =L19*0.7 -> 18.665341 | G56: =M19*0.6 -> 14.733409 | H56: =N19*0.55 -> 12.375
A57: Non-AI EPS ($) | B57: =H20 -> 233.81563 | C57: =I20 -> 257.76364 | D57: =J20 -> 311.90483 | E57: =K20 -> 358.32773 | F57: =L20 -> 393.33523 | G57: =M20 -> 425.44432 | H57: =N20 -> 455.5
A58: Implied S&P 500 | B58: =B56*$J$55+B57*$L$55 -> 4338.2906 | C58: =C56*$J$55+C57*$L$55 -> 4920.6545 | D58: =D56*$J$55+D57*$L$55 -> 6197.7496 | E58: =E56*$J$55+E57*$L$55 -> 7017.1807 | F58: =F56*$J$55+F57*$L$55 -> 7546.6676 | G58: =G56*$J$55+G57*$L$55 -> 8026.333 | H58: =H56*$J$55+H57*$L$55 -> 8508.375
A59: vs Base Delta | B59: =IFERROR(B58/B51-1,"") -> -0.1522642 | C59: =IFERROR(C58/C51-1,"") -> -0.16065464 | D59: =IFERROR(D58/D51-1,"") -> -0.17951986 | E59: =IFERROR(E58/E51-1,"") -> -0.18705224 | F59: =IFERROR(F58/F51-1,"") -> -0.19084738 | G59: =IFERROR(G58/G51-1,"") -> -0.19061301 | H59: =IFERROR(H58/H51-1,"") -> -0.18700731
A61: AI Bust (AI PE=15x, Non-AI PE=17x)
A62: Customer Crack. Capex cut 30% from 2027. Massive write-downs. AI PE crashes to market avg.
B63: 2024A | C63: 2025A | D63: 2026E | E63: 2027E | F63: 2028E | G63: 2029E | H63: 2030E | I63: AI PE: | J63: 17 | K63: Non-AI PE: | L63: 17
A64: AI EPS ($) | B64: =H19 -> 5.184375 | C64: =I19 -> 11.236364 | D64: =J19 -> 25.09517 | E64: =K19*0.38 -> 10.515464 | F64: =L19*0.21 -> 5.5996023 | G64: =M19*0.15 -> 3.6833523 | H64: =N19*0.12 -> 2.7
A65: Non-AI EPS ($) | B65: =H20 -> 233.81563 | C65: =I20 -> 257.76364 | D65: =J20 -> 311.90483 | E65: =K20 -> 358.32773 | F65: =L20 -> 393.33523 | G65: =M20 -> 425.44432 | H65: =N20 -> 455.5
A66: Implied S&P 500 | B66: =B64*$J$63+B65*$L$63 -> 4063 | C66: =C64*$J$63+C65*$L$63 -> 4573 | D66: =D64*$J$63+D65*$L$63 -> 5729 | E66: =E64*$J$63+E65*$L$63 -> 6270.3342 | F66: =F64*$J$63+F65*$L$63 -> 6781.8921 | G66: =G64*$J$63+G65*$L$63 -> 7295.1704 | H66: =H64*$J$63+H65*$L$63 -> 7789.4
A67: vs Base Delta | B67: =IFERROR(B66/B51-1,"") -> -0.20605813 | C67: =IFERROR(C66/C51-1,"") -> -0.21995615 | D67: =IFERROR(D66/D51-1,"") -> -0.2415746 | E67: =IFERROR(E66/E51-1,"") -> -0.27357518 | F67: =IFERROR(F66/F51-1,"") -> -0.2728465 | G67: =IFERROR(G66/G51-1,"") -> -0.2643445 | H67: =IFERROR(H66/H51-1,"") -> -0.25570685

Sheet 8. Charts
A1: Visual Summary (2013-2030)
A3: Capex / Revenue %
B4: 2013 | C4: 2014 | D4: 2015 | E4: 2016 | F4: 2017 | G4: 2018 | H4: 2019 | I4: 2020 | J4: 2021 | K4: 2022 | L4: 2023 | M4: 2024 | N4: 2025 | O4: 2026 | P4: 2027 | Q4: 2028 | R4: 2029 | S4: 2030
A5: MSFT | B5: 0.054682783 | C5: 0.063167229 | D5: 0.063517846 | E5: 0.097126018 | F5: 0.10552779 | G5: 0.12323306 | H5: 0.13429432 | I5: 0.1328532 | J5: 0.14397221 | K5: 0.14727392 | L5: 0.15053205 | M5: 0.22723379 | N5: 0.31307237 | O5: 0.44309062 | P5: 0.63969153 | Q5: 0.63707089 | R5: 0.56233936 | S5: 0.4876122
A6: AMZN | B6: 0.04624456 | C6: 0.054973704 | D6: 0.0428761 | E6: 0.049534147 | F6: 0.056542566 | G6: 0.048615852 | H6: 0.045237094 | I6: 0.090777695 | J6: 0.11790848 | K6: 0.11346873 | L6: 0.083740877 | M6: 0.12172883 | N6: 0.17898689 | O6: 0.24262623 | P6: 0.28946439 | Q6: 0.27390283 | R6: 0.25517674 | S6: 0.2399223
A7: GOOGL | B7: 0.13253121 | C7: 0.16604294 | D7: 0.13221939 | E7: 0.11280353 | F7: 0.11893013 | G7: 0.1837391 | H7: 0.14548645 | I7: 0.12206961 | J7: 0.095638437 | K7: 0.11131893 | L7: 0.10491747 | M7: 0.15009228 | N7: 0.22700801 | O7: 0.38078338 | P7: 0.44826968 | Q7: 0.41704259 | R7: 0.37189034 | S7: 0.33413189
A8: META | B8: 0.17301829 | C8: 0.14687951 | D8: 0.14072959 | E8: 0.16249367 | F8: 0.16559663 | G8: 0.25036713 | H8: 0.21361585 | I8: 0.17582737 | J8: 0.15744219 | K8: 0.26744076 | L8: 0.20047887 | M8: 0.22647887 | N8: 0.34678005 | O8: 0.53611982 | P8: 0.55012241 | Q8: 0.5269863 | R8: 0.48736679 | S8: 0.45662487
A9: ORCL | B9: 0.47619048 | C9: 0.015141231 | D9: 0.036363161 | E9: 0.032085706 | F9: 0.053325945 | G9: 0.043532775 | H9: 0.041997672 | I9: 0.040032763 | J9: 0.052740792 | K9: 0.10629123 | L9: 0.17406014 | M9: 0.12964257 | N9: 0.36960574 | O9: 0.77140396 | P9: 0.58515872 | Q9: 0.53547044 | R9: 0.44243017 | S9: 0.2979685
A26: Capex ($mm)
B27: 2013 | C27: 2014 | D27: 2015 | E27: 2016 | F27: 2017 | G27: 2018 | H27: 2019 | I27: 2020 | J27: 2021 | K27: 2022 | L27: 2023 | M27: 2024 | N27: 2025 | O27: 2026 | P27: 2027 | Q27: 2028 | R27: 2029 | S27: 2030
A28: MSFT | B28: 4257 | C28: 5485 | D28: 5944 | E28: 8932 | F28: 10200 | G28: 13600 | H28: 16900 | I28: 19000 | J28: 24200 | K28: 29200 | L28: 31900 | M28: 55700 | N28: 88200 | O28: 145871.3 | P28: 245263.45 | Q28: 286760.35 | R28: 300210.91 | S28: 304616.04
A29: AMZN | B29: 3443 | C29: 4892 | D29: 4588 | E29: 6736 | F29: 10057 | G29: 11322 | H29: 12690 | I29: 35046 | J29: 55396 | K29: 58321 | L29: 48133 | M29: 77658 | N29: 128320 | O29: 200104.98 | P29: 270141.72 | Q29: 283648.81 | R29: 297831.25 | S29: 312722.81
A30: GOOGL | B30: 7358 | C30: 10959 | D30: 9915 | E30: 10183 | F30: 13184 | G30: 25139 | H30: 23548 | I30: 22281 | J30: 24640 | K30: 31485 | L30: 32251 | M30: 52535 | N30: 91447 | O30: 185234.28 | P30: 259327.99 | Q30: 285260.79 | R30: 299523.83 | S30: 314500.02
A31: META | B31: 1362 | C31: 1831 | D31: 2523 | E31: 4491 | F31: 6732 | G31: 13980 | H31: 15102 | I31: 15115 | J31: 18567 | K31: 31186 | L31: 27045 | M31: 37256 | N31: 69691 | O31: 135583.71 | P31: 165714.44 | Q31: 185600.17 | R31: 196736.18 | S31: 208540.35
A32: ORCL | B32: 650 | C32: 580 | D32: 1391 | E32: 1189 | F32: 2021 | G32: 1736 | H32: 1660 | I32: 1564 | J32: 2135 | K32: 4511 | L32: 8695 | M32: 6866 | N32: 21215 | O32: 51882 | P32: 52141.41 | Q32: 69869.49 | R32: 81048.61 | S32: 66459.86
A49: Operating Margin %
B50: 2013 | C50: 2014 | D50: 2015 | E50: 2016 | F50: 2017 | G50: 2018 | H50: 2019 | I50: 2020 | J50: 2021 | K50: 2022 | L50: 2023 | M50: 2024 | N50: 2025 | O50: 2026 | P50: 2027 | Q50: 2028 | R50: 2029 | S50: 2030
A51: MSFT | B51: 0.34379375 | C51: 0.31968261 | D51: 0.14275486 | E51: 0.12783402 | F51: 0.11782902 | G51: 0.11710765 | H51: 0.12888281 | I51: 0.13092333 | J51: 0.14487054 | K51: 0.14973017 | L51: 0.23629285 | M51: 0.24339309 | N51: 0.24766438 | O51: 0.24161124 | P51: 0.22333585 | Q51: 0.15524087 | R51: 0.18988339 | S51: 0.17369588
A52: AMZN | B52: 0.0090393811 | C52: 0.0051467614 | D52: 0.014083322 | E52: 0.022855126 | F52: 0.024349791 | G52: 0.031328498 | H52: 0.032799567 | I52: 0.035048593 | J52: 0.039444726 | K52: 0.044439213 | L52: 0.042852545 | M52: 0.062439749 | N52: 0.063613437 | O52: 0.071406785 | P52: 0.081590741 | Q52: 0.094992178 | R52: 0.10566765 | S52: 0.11670333
A53: GOOGL | B53: 0.29287271 | C53: 0.28734413 | D53: 0.31096561 | E53: 0.29970533 | F53: 0.29277886 | G53: 0.31528516 | H53: 0.30273019 | I53: 0.2991667 | J53: 0.35652876 | K53: 0.29239206 | L53: 0.31184083 | M53: 0.3464479 | N53: 0.34605646 | O53: 0.34134389 | P53: 0.32567217 | Q53: 0.30333417 | R53: 0.28457166 | S53: 0.27482676
A54: META | B54: 0.35619919 | C54: 0.40067383 | D54: 0.34722222 | E54: 0.44963456 | F54: 0.4969375 | G54: 0.44616569 | H54: 0.40297325 | I54: 0.457093 | J54: 0.48288377 | K54: 0.36584655 | L54: 0.46604943 | M54: 0.52953477 | N54: 0.50988227 | O54: 0.42410888 | P54: 0.40942733 | Q54: 0.40525664 | R54: 0.44456344 | S54: 0.42116372
A55: ORCL | B55: 12.902564 | C55: 0.47271968 | D55: 0.45476172 | E55: 0.4259654 | F55: 0.42660756 | G55: 0.43018707 | H55: 0.43981177 | I55: 0.44494215 | J55: 0.46935599 | K55: 0.46163996 | L55: 0.41846499 | M55: 0.43530145 | N55: 0.43614 | O55: 0.41799681 | P55: 0.31972055 | Q55: 0.35468934 | R55: 0.35137419 | S55: 0.31275962

Sheet 9. Bubble & Valuation
A1: Bubble Risk: 2000 vs 2026 + Valuation + Triggers
A3: A. S&P 500 Forecasts (May 2026)
A4: Source | B4: 2024A | C4: 2025A | D4: 2026E | E4: 2027E | F4: YE2026 Target | G4: Notes
A5: Sell-side Top-Down | B5: $239 | C5: $269 | D5: $309 (+15%) | E5: $342 (+11%) | F5: 7,600 | G5: Top-down
A6: Bottom-Up Consensus | B6: $239 | C6: $269 | D6: $337 (+25%) | E6: $386 (+15%) | F6: — | G6: Bloomberg FA1
A7: Our AI Split Model | B7: $239 | C7: $269 | D7: $337 | E7: $386 | F7: 5,780* | G7: *Non-AI 21x + AI 40x
A9: B. 2027E Implied S&P 500 = EPS x P/E
A10: EPS Scenario | B10: 18x | C10: 19x | D10: 20x | E10: 21x | F10: 22x | G10: 23x | H10: 24x
A11: Top-Down $342 | B11: 6156 | C11: 6498 | D11: 6840 | E11: 7182 | F11: 7524 | G11: 7866 | H11: 8208
A12: Bloomberg $386 | B12: 6948 | C12: 7334 | D12: 7720 | E12: 8106 | F12: 8492 | G12: 8878 | H12: 9264
A13: Stress $300 | B13: 5400 | C13: 5700 | D13: 6000 | E13: 6300 | F13: 6600 | G13: 6900 | H13: 7200
A14: Crash $260 | B14: 4680 | C14: 4940 | D14: 5200 | E14: 5460 | F14: 5720 | G14: 5980 | H14: 6240
A16: C. Current Valuation vs History
A17: Metric | B17: Current | C17: 10yr %ile | D17: 30yr %ile | E17: 2000 Peak | F17: Verdict
A18: S&P 500 Fwd P/E | B18: 21x | C18: 64% | D18: 82% | E18: 24x | F18: Expensive but not extreme
A19: IT Weight | B19: 36% | C19: 99% | D19: 99% | E19: 33% | F19: EXCEEDS 2000
A21: D. 2000 Bubble 5-Phase Timeline vs AI 2026
A22: Phase | B22: 2000 Telecom | C22: AI 2026 | D22: Status | E22: Next Trigger
A23: 1. Valuation Mania | B23: Nasdaq 200x PE | C23: NVDA 30-40x; S&P 21x (82nd %ile) | D23: PARTIAL | E23: PE>25x
A24: 2. Liquidity Signal | B24: Greenspan hikes | C24: Fed hold; not cutting | D24: BORDERLINE | E24: Fed hawkish or IG>100bp
A25: 3. Customer Deaths | B25: Pets.com 9mo post-IPO | C25: OpenAI burns $17B/yr, still raising | D25: NOT YET | E25: AI lab funding delay/down round
A26: 4. Capex Crack | B26: Telcos;fiber | C26: Hyperscalers +83%; cRPO record | D26: NOT YET | E26: Any name cuts 2027 guide
A27: 5. Accounting | B27: Enron $38B; WorldCom bankrupt | C27: Circular financing exists | D27: NOT YET | E27: AI stake write-down
A29: Position: Between Phase 1-2. Phases 3/4/5 NOT occurred. Burst window: 2027 H1-H2 (D&A wave locked in). Distance: 2-4 quarters.

Sheet 10. Bloomberg Data
A1: S&P 500 Fundamentals — Bloomberg Terminal (FA1.xlsx)
A3: Metric | B3: 2009A | C3: 2010A | D3: 2011A | E3: 2012A | F3: 2013A | G3: 2014A | H3: 2015A | I3: 2016A | J3: 2017A | K3: 2018A | L3: 2019A | M3: 2020A | N3: 2021A | O3: 2022A | P3: 2023A | Q3: 2024A | R3: 2025A | S3: 2026E | T3: 2027E
A4: Sales/Share ($) | B4: 859 | C4: 924 | D4: 1018 | E4: 1054 | F4: 1120 | G4: 1144 | H4: 1129 | I4: 1129 | J4: 1190 | K4: 1307 | L4: 1356 | M4: 1326 | N4: 1510 | O4: 1704 | P4: 1785 | Q4: 1864 | R4: 1947 | S4: 2180 | T4: 2339
A5: Gross Margin (%) | B5: 33.1 | C5: 33.6 | D5: 32.6 | E5: 33.5 | F5: 33.6 | G5: 34.4 | H5: 34.9 | I5: 34.4 | J5: 35.2 | K5: 34.9 | L5: 35 | M5: 34 | N5: 35.5 | O5: 34.7 | P5: 33.6 | Q5: 33.8 | R5: 34.6 | S5: 38.6 | T5: 40.1
A6: EBIT/Share ($) | B6: 75.7 | C6: 116 | D6: 137 | E6: 136 | F6: 142 | G6: 160 | H6: 139 | I6: 139 | J6: 160 | K6: 179 | L6: 182 | M6: 146 | N6: 228 | O6: 251 | P6: 248 | Q6: 270 | R6: 303 | S6: 426 | T6: 495
A7: Op Margin (%) | B7: 8.7 | C7: 12.5 | D7: 13.3 | E7: 12.8 | F7: 12.6 | G7: 13.8 | H7: 12.2 | I7: 12.3 | J7: 13.3 | K7: 13.4 | L7: 13 | M7: 10.7 | N7: 14.9 | O7: 14.6 | P7: 13.5 | Q7: 13.9 | R7: 15 | S7: 19.5 | T7: 21.1
A8: EBITDA/Share ($) | B8: 136 | C8: 166 | D8: 187 | E8: 188 | F8: 198 | G8: 219 | H8: 199 | I8: 200 | J8: 229 | K8: 255 | L8: 270 | M8: 238 | N8: 310 | O8: 341 | P8: 357 | Q8: 393 | R8: 425 | S8: 520 | T8: 601
A9: EPS Aggregate ($) | B9: 57.6 | C9: 83.9 | D9: 99.6 | E9: 104 | F9: 112 | G9: 123 | H9: 120 | I9: 121 | J9: 129 | K9: 160 | L9: 165 | M9: 142 | N9: 200 | O9: 224 | P9: 222 | Q9: 239 | R9: 269 | S9: 337 | T9: 386
A11: EPS YoY % | C11: =IFERROR(C9/B9-1,NA()) -> 0.45659722 | D11: =IFERROR(D9/C9-1,NA()) -> 0.18712753 | E11: =IFERROR(E9/D9-1,NA()) -> 0.044176707 | F11: =IFERROR(F9/E9-1,NA()) -> 0.076923077 | G11: =IFERROR(G9/F9-1,NA()) -> 0.098214286 | H11: =IFERROR(H9/G9-1,NA()) -> -0.024390244 | I11: =IFERROR(I9/H9-1,NA()) -> 0.0083333333 | J11: =IFERROR(J9/I9-1,NA()) -> 0.066115702 | ... T11: =IFERROR(T9/S9-1,NA()) -> 0.14540059
A12: Sales YoY % | C12: =IFERROR(C4/B4-1,NA()) -> 0.075669383 | D12: =IFERROR(D4/C4-1,NA()) -> 0.1017316 | E12: =IFERROR(E4/D4-1,NA()) -> 0.035363458 | F12: =IFERROR(F4/E4-1,NA()) -> 0.062618596 | G12: =IFERROR(G4/F4-1,NA()) -> 0.021428571 | H12: =IFERROR(H4/G4-1,NA()) -> -0.013111888 | I12: =IFERROR(I4/H4-1,NA()) -> 0 | J12: =IFERROR(J4/I4-1,NA()) -> 0.054030115 | ... T12: =IFERROR(T4/S4-1,NA()) -> 0.07293578
A14: Key: 2026E OpMargin jumps from 15.0% to 19.5% = 450bp expansion. Most aggressive in 15 years. If only 200bp (to 17%), EPS~$295 vs $337 = 12% miss. Consensus is a bet on AI margin expansion.
