Workbook

Sheet 0. Database
A1: Centralized Database — All analysis sheets reference this via formulas (USD mm except EPS/shares)
A2: MSFT FY=Jun; ORCL FY=May; AMZN/GOOGL/META=CY. Blue text=hardcoded input. Green text=cross-sheet formula.
A4: Ticker | B4: Metric | C4: 2013A | D4: 2014A | E4: 2015A | F4: 2016A | G4: 2017A | H4: 2018A | I4: 2019A | J4: 2020A | K4: 2021A | L4: 2022A | M4: 2023A | N4: 2024A | O4: 2025E | P4: 2026E | Q4: 2027E | R4: 2028E | S4: 2029E | T4: 2030E | U4: 2031E
A5: MSFT (FY(Jun))
A6: MSFT | B6: Revenue | C6: 77849 | D6: 86833 | E6: 93580 | F6: 85320 | G6: 96571 | H6: 110360 | I6: 125843 | J6: 143015 | K6: 168088 | L6: 198270 | M6: 211915 | N6: 245122 | O6: 281724 | P6: 329440.24 | Q6: 387103.71 | R6: 463474.17 | S6: 553714.52 | T6: 652772.62
A7: MSFT | B7: Operating Income (GAAP) | C7: 26764 | D7: 27759 | E7: 18161 | F7: 20182 | G7: 29025 | H7: 35058 | I7: 42959 | J7: 52959 | K7: 69916 | L7: 83383 | M7: 88523 | N7: 109433 | O7: 128528 | P7: 153454.1 | Q7: 179274.53 | R7: 217551.82 | S7: 266239.28 | T7: 318436.19
A8: MSFT | B8: Net Income | C8: 21863 | D8: 22074 | E8: 12193 | F8: 16798 | G8: 25489 | H8: 16571 | I8: 39240 | J8: 44281 | K8: 61271 | L8: 72738 | M8: 72361 | N8: 88136 | O8: 101832 | P8: 129372.86 | Q8: 144971.56 | R8: 175683.92 | S8: 215472.22 | T8: 258948.36
A9: MSFT | B9: EPS (GAAP) | C9: 2.63 | D9: 2.66 | E9: 2.59 | F9: 2.79 | G9: 3.29 | H9: 3.88 | I9: 4.75 | J9: 5.76 | K9: 7.97 | L9: 9.21 | M9: 9.81 | N9: 11.8 | O9: 13.91 | P9: 16.75 | Q9: 19.47 | R9: 23.61 | S9: 28.97 | T9: 34.82
A10: MSFT | B10: Diluted Shares (mm) | C10: 8452.25 | D10: 8385.25 | E10: 8254 | F10: 8012.25 | G10: 7831.25 | H10: 7792.25 | I10: 7752 | J10: 7681.5 | K10: 7607.75 | L10: 7540.5 | M10: 7472.25 | N10: 7468.5 | O10: 7467.75 | P10: 7453.97 | Q10: 7446.49 | R10: 7440.67 | S10: 7436.61 | T10: 7436.22
A11: MSFT | B11: Stock-Based Comp | C11: 2406 | D11: 2446 | E11: 2574 | F11: 2668 | G11: 3266 | H11: 3940 | I11: 4652 | J11: 5289 | K11: 6118 | L11: 7502 | M11: 9611 | N11: 10734 | O11: 11974 | P11: 12189 | Q11: 10478.4 | R11: 11434.24 | S11: 12826.56 | T11: 14871.62
A12: MSFT | B12: D&A | C12: 3339 | D12: 4245 | E12: 5400 | F12: 5878 | G12: 7800 | H12: 9900 | I12: 11600 | J12: 12300 | K12: 10900 | L12: 14600 | M12: 13500 | N12: 20000 | O12: 28000 | P12: 39638.96 | Q12: 62441.96 | R12: 94995.43 | S12: 131504.45 | T12: 167239.58
A13: MSFT | B13: Capex | C13: 4257 | D13: 5485 | E13: 5944 | F13: 8932 | G13: 10200 | H13: 13600 | I13: 16900 | J13: 19000 | K13: 24200 | L13: 29200 | M13: 31900 | N13: 55700 | O13: 88200 | P13: 145871.3 | Q13: 245263.45 | R13: 286760.35 | S13: 300210.91 | T13: 304616.04
A14: MSFT | B14: PP&E Net | C14: 9991 | D14: 13011 | E14: 14731 | F14: 18356 | G14: 23734 | H14: 29460 | I14: 36477 | J14: 44151 | K14: 59715 | L14: 74398 | M14: 95641 | N14: 135591 | O14: 204966 | P14: 314226 | Q14: 499947.5 | R14: 693712.41 | S14: 864268.87 | T14: 1003045.3
A15: MSFT | B15: PP&E Useful Life (yrs) | C15: 3.16 | D15: 2.69 | E15: 2.81 | F15: 2.83 | G15: 2.71 | H15: 2.73 | I15: 2.74 | J15: 3.08 | K15: 4.33 | L15: 4.12 | M15: 6.1 | N15: 5.59 | O15: 5.26 | P15: 4.89 | Q15: 4.36 | R15: 4.38 | S15: 4.6 | T15: 4.7
A16: MSFT | B16: Cash from Operations | C16: 28833 | D16: 32231 | E16: 29080 | F16: 33325 | G16: 39507 | H16: 43884 | I16: 52185 | J16: 60675 | K16: 76740 | L16: 89035 | M16: 87582 | N16: 118548 | O16: 136162 | P16: 174558.18 | Q16: 232097.78 | R16: 294570.35 | S16: 359672.36 | T16: 438548.9
A17: MSFT | B17: Free Cash Flow | C17: 24576 | D17: 26746 | E17: 23136 | F17: 24393 | G17: 29307 | H17: 30284 | I17: 35285 | J17: 41675 | K17: 52540 | L17: 59835 | M17: 55682 | N17: 62848 | O17: 47962 | P17: 28686.88 | Q17: -13165.67 | R17: 7810 | S17: 59461.45 | T17: 133932.86
... A22: MSFT | B22: More Personal Computing | C22: 0 | D22: 0 | E22: 0 | F22: 0 | G22: 0 | H22: 0 | I22: 0 | J22: 0 | K22: 0 | L22: 0 | M22: 44820 | N22: 50838 | O22: 54649 | P22: 53304.95 | Q22: 49795.1 | R22: 51395.8 | S22: 52810.16 | T22: 54279.57
A24: AMZN (CY)
A25: AMZN | B25: Revenue | C25: 74453 | D25: 88988.4 | E25: 107006.6 | F25: 135987 | G25: 177866 | H25: 232887 | I25: 280522 | J25: 386064 | K25: 469822 | L25: 513983 | M25: 574785 | N25: 637959 | O25: 716924 | P25: 827599.51 | Q25: 946630.91 | R25: 1063340.6 | S25: 1183117.7 | T25: 1305415.5 | U25: 1427912.6
A26: AMZN | B26: Operating Income (GAAP) | C26: 745 | D26: 178.4 | E26: 2232.6 | F26: 4186 | G26: 4107 | H26: 12420 | I26: 14540 | J26: 22899 | K26: 24879 | L26: 12248 | M26: 36852 | N26: 68593 | O26: 79975 | P26: 109001.86 | Q26: 146127.4 | R26: 183469.22 | S26: 223208.87 | T26: 264582.39 | U26: 305413.69
A27: AMZN | B27: Net Income | C27: 273 | D27: -240.6 | E27: 596.1 | F27: 2371 | G27: 3033 | H27: 10073 | I27: 11588 | J27: 21331 | K27: 33364 | L27: -2722 | M27: 30425 | N27: 59248 | O27: 77670 | P27: 98333.72 | Q27: 116218.4 | R27: 145016.4 | S27: 177176.2 | T27: 211925.99 | U27: 247587.75
A28: AMZN | B28: EPS (GAAP) | C28: 0.03 | D28: -0.03 | E28: 0.06 | F28: 0.24 | G28: 0.31 | H28: 1.01 | I28: 1.15 | J28: 2.08 | K28: 3.25 | L28: -0.26 | M28: 2.88 | N28: 5.53 | O28: 7.17 | P28: 9.02 | Q28: 10.58 | R28: 13.11 | S28: 15.92 | T28: 18.92 | U28: 21.97
A29: AMZN | B29: Diluted Shares (mm) | C29: 9340 | D29: 9440 | E29: 9620 | F29: 9720 | G29: 9910 | H29: 10020 | I29: 10100 | J29: 10254 | K29: 10274.5 | L29: 10296.5 | M29: 10568.69 | N29: 10721 | O29: 10827 | P29: 10907.55 | Q29: 10986.16 | R29: 11059.39 | S29: 11131.13 | T29: 11201.4 | U29: 11270.24
A30: AMZN | B30: Stock-Based Comp | C30: -1134 | D30: -1497 | E30: -2120 | F30: -2975 | G30: -4214 | H30: -5418 | I30: -6864 | J30: -9208 | K30: -12757 | L30: -19621 | M30: -24023 | N30: -22077.4 | O30: -19467 | P30: -18863.32 | Q30: -17920.15 | R30: -18816.16 | S30: -19756.97 | T30: -20744.82 | U30: -21782.06
A31: AMZN | B31: D&A | C31: 3253 | D31: 4745 | E31: 6281 | F31: 8117 | G31: 11478 | H31: 15341 | I31: 21789 | J31: 25251 | K31: 34296 | L31: 41461 | M31: 48663 | N31: 52795 | O31: 65756 | P31: 81175.82 | Q31: 90716.93 | R31: 120533.23 | S31: 150703.05 | T31: 175451.44 | U31: 191789.29
A32: AMZN | B32: Capex | C32: 3443 | D32: 4892 | E32: 4588 | F32: 6736 | G32: 10057 | H32: 11322 | I32: 12690 | J32: 35046 | K32: 55396 | L32: 58321 | M32: 48133 | N32: 77658 | O32: 128320 | P32: 200104.98 | Q32: 270141.72 | R32: 283648.81 | S32: 297831.25 | T32: 312722.81 | U32: 328358.95
A33: AMZN | B33: Cash from Operations | C33: 5474 | D33: 6841.4 | E33: 11920.1 | F33: 17271 | G33: 18434 | H33: 30724 | I33: 38515 | J33: 66064 | K33: 46327 | L33: 46752 | M33: 84946 | N33: 115877 | O33: 139514 | P33: 181004.31 | Q33: 224443.7 | R33: 281471.71 | S33: 342814.42 | T33: 401080.41 | U33: 451875.96
A34: AMZN | B34: Free Cash Flow | C34: 2031 | D34: 1949.4 | E34: 7332.1 | F34: 10535 | G34: 8377 | H34: 19402 | I34: 25825 | J34: 31018 | K34: -9069 | L34: -11569 | M34: 36813 | N34: 38219 | O34: 11194 | P34: -19100.67 | Q34: -45698.02 | R34: -2177.1 | S34: 44983.17 | T34: 88357.6 | U34: 123517
A35: AMZN | B35: Buybacks | C35: 0 | D35: 0 | E35: 0 | F35: 0 | G35: 0 | H35: 0 | I35: 0 | J35: 0 | K35: 0 | L35: 6000 | M35: 0 | N35: 0 | O35: 0 | P35: 0 | Q35: 0 | R35: 0 | S35: 0 | T35: 0 | U35: 0
A36: AMZN | B36: AWS Revenue | C36: 3107.57 | D36: 4644 | E36: 7880 | F36: 12219 | G36: 17458 | H36: 25656 | I36: 35026 | J36: 45370 | K36: 62202 | L36: 80096 | M36: 90757 | N36: 107556 | O36: 128725 | P36: 171284.9 | Q36: 225587.94 | R36: 274421.67 | S36: 323817.58 | T36: 374009.3 | U36: 423565.53
A37: AMZN | B37: AWS Operating Income | D37: 458 | E37: 1508 | F37: 3109 | G37: 4331 | H37: 7296 | I37: 9201 | J37: 13531 | K37: 18532 | L37: 22841 | M37: 24631 | N37: 39834 | O37: 45606 | P37: 61254.41 | Q37: 81248.3 | R37: 100888.47 | S37: 121477.03 | T37: 143111.04 | U37: 165249.99
A38: AMZN | B38: N. America Revenue | C38: 41410.43 | D38: 50834 | E38: 63709 | F38: 79784 | G38: 106110 | H38: 141366 | I38: 170773 | J38: 236282 | K38: 279833 | L38: 315880 | M38: 352828 | N38: 387497 | O38: 426305 | P38: 470778.82 | Q38: 518831.61 | R38: 569322.64 | S38: 622020.48 | T38: 676638.44 | U38: 732834.43
A39: AMZN | B39: Int'l Revenue | C39: 29935 | D39: 33510.4 | E39: 35417.6 | F39: 43984 | G39: 54298 | H39: 65865 | I39: 74723 | J39: 104412 | K39: 127787 | L39: 118007 | M39: 131200 | N39: 142906 | O39: 161894 | P39: 185535.79 | Q39: 202211.37 | R39: 219596.27 | S39: 237279.67 | T39: 254767.75 | U39: 271512.66
A41: GOOGL (CY)
A42: GOOGL | B42: Revenue | C42: 55519 | D42: 66001 | E42: 74989 | F42: 90272 | G42: 110855 | H42: 136819 | I42: 161857 | J42: 182527 | K42: 257637 | L42: 282836 | M42: 307394 | N42: 350018 | O42: 402836 | P42: 488278.6 | Q42: 591935.74 | R42: 701414.49 | S42: 815276.88 | T42: 921874.95 | U42: 1029231.9
A43: GOOGL | B43: Operating Income (GAAP) | C43: 15403 | D43: 16496 | E43: 19360 | F43: 23716 | G43: 26146 | H43: 26953 | I43: 34231 | J43: 41224 | K43: 78714 | L43: 74842 | M43: 84293 | N43: 112390 | O43: 129039 | P43: 167318.21 | Q43: 210287.33 | R43: 253779.42 | S43: 298519.7 | T43: 338347.07 | U43: 380286.59
A44: GOOGL | B44: Net Income | C44: 12720 | D44: 14136 | E44: 16348 | F44: 19478 | G44: 12662 | H44: 30736 | I44: 34343 | J44: 40269 | K44: 76033 | L44: 59972 | M44: 73795 | N44: 100118 | O44: 132170 | P44: 168543.28 | Q44: 174626.97 | R44: 210753.44 | S44: 249488.6 | T44: 285975.76 | U44: 326302.42
A45: GOOGL | B45: EPS (GAAP) | C45: 0.94 | D45: 1.03 | E45: 1.18 | F45: 1.39 | G45: 0.9 | H45: 2.19 | I45: 2.46 | J45: 2.93 | K45: 5.61 | L45: 4.56 | M45: 5.8 | N45: 8.04 | O45: 10.81 | P45: 13.73 | Q45: 14.16 | R45: 17.04 | S45: 20.12 | T45: 22.99 | U45: 26.09
A46: GOOGL | B46: Diluted Shares (mm) | C46: 13552.38 | D46: 13741.41 | E46: 13858.6 | F46: 13974.09 | G46: 14071.67 | H46: 14065.69 | I46: 13971.13 | J46: 13740.56 | K46: 13553 | L46: 13159 | M46: 12722 | N46: 12447 | O46: 12230 | P46: 12275.96 | Q46: 12335.53 | R46: 12366.42 | S46: 12399.99 | T46: 12436.85 | U46: 12506.36
A47: GOOGL | B47: Stock-Based Comp | C47: -3268 | D47: -4175 | E47: -4903 | F47: -6703 | G47: -7679 | H47: -9353 | I47: -10794 | J47: -12991 | K47: -15376 | L47: -19362 | M47: -22460 | N47: -22785 | O47: -24953 | P47: -27937.33 | Q47: -30032.63 | R47: -31979.73 | S47: -33657.1 | T47: -35339.95 | U47: -37106.95
A48: GOOGL | B48: D&A | C48: 2781 | D48: 3523 | E48: 4132 | F48: 5267 | G48: 6103 | H48: 8164 | I48: 10856 | J48: 12905 | K48: 11555 | L48: 15287 | M48: 13326 | N48: 15311 | O48: 21136 | P48: 42874.7 | Q48: 69582.72 | R48: 98340.16 | S48: 127674.93 | T48: 156155.17 | U48: 181381.37
A49: GOOGL | B49: Capex | C49: 7358 | D49: 10959 | E49: 9915 | F49: 10183 | G49: 13184 | H49: 25139 | I49: 23548 | J49: 22281 | K49: 24640 | L49: 31485 | M49: 32251 | N49: 52535 | O49: 91447 | P49: 185234.28 | Q49: 259327.99 | R49: 285260.79 | S49: 299523.83 | T49: 314500.02 | U49: 330225.02
A50: GOOGL | B50: Cash from Operations | C50: 18584 | D50: 22272 | E50: 25829 | F50: 36036 | G50: 37091 | H50: 47971 | I50: 54520 | J50: 65124 | K50: 91652 | L50: 91495 | M50: 101746 | N50: 125299 | O50: 164713 | P50: 211985.47 | Q50: 282346.21 | R50: 352943.8 | S50: 424226.82 | T50: 490867.35 | U50: 557191.03
A51: GOOGL | B51: Free Cash Flow | C51: 11226 | D51: 11313 | E51: 15914 | F51: 25853 | G51: 23907 | H51: 22832 | I51: 30972 | J51: 42843 | K51: 67012 | L51: 60010 | M51: 69495 | N51: 72764 | O51: 73266 | P51: 26751.19 | Q51: 23018.22 | R51: 67683.01 | S51: 124702.99 | T51: 176367.33 | U51: 226966.01
A52: GOOGL | B52: Buybacks | C52: 0 | D52: 0 | E52: 1827 | F52: 3693 | G52: 4846 | H52: 9075 | I52: 18396 | J52: 31149 | K52: 50274 | L52: 59296 | M52: 61504 | N52: 62222 | O52: 45709 | P52: 0 | Q52: 20000 | R52: 20000 | S52: 20000 | T52: 15000 | U52: 0
A53: GOOGL | B53: Cloud Revenue | G53: 4056 | H53: 5838 | I53: 8918 | J53: 13059 | K53: 19206 | L53: 26280 | M53: 33088 | N53: 43229 | O53: 58705 | P53: 99085.93 | Q53: 157303.91 | R53: 220225.47 | S53: 286293.12 | T53: 343551.74 | U53: 400237.78
A54: GOOGL | B54: Search Revenue | G54: 69811 | H54: 85296 | I54: 98115 | J54: 104062 | K54: 148951 | L54: 162450 | M54: 175033 | N54: 198084 | O54: 224532 | P54: 258723.55 | Q54: 291360.5 | R54: 324483.39 | S54: 358139.29 | T54: 392613.71 | U54: 427477.22
A55: GOOGL | B55: YouTube Revenue | G55: 8150 | H55: 11115 | I55: 15149 | J55: 19772 | K55: 28845 | L55: 29243 | M55: 31510 | N55: 36147 | O55: 40367 | P55: 43997.73 | Q55: 49277.45 | R55: 54574.78 | S55: 59759.38 | T55: 64838.93 | U55: 70026.04
A56: GOOGL | B56: Google Cloud OI | H56: -4348 | I56: -4645 | J56: -5607 | K56: -2282 | L56: -1922 | M56: 1716 | N56: 6112 | O56: 13910 | P56: 32420.97 | Q56: 57771.82 | R56: 85285.05 | S56: 113733.5 | T56: 138713.29 | U56: 163201.93
A57: GOOGL | B57: Google Services Revenue | H57: 130524 | I57: 151825 | J57: 168635 | K57: 237529 | L57: 253528 | M57: 272543 | N57: 304930 | O57: 342721 | P57: 387820.32 | Q57: 433001.86 | R57: 479477.55 | S57: 527186.72 | T57: 576436.31 | U57: 627012.9
A58: GOOGL | B58: Google Services OI | C58: 15403 | D58: 17320 | E58: 23397 | F58: 27927 | G58: 32287 | H58: 36517 | I58: 44066 | J58: 54606 | K58: 88132 | L58: 82699 | M58: 95858 | N58: 121263 | O58: 139404 | P58: 169177.49 | Q58: 192692.38 | R58: 212413.88 | S58: 230941.87 | T58: 246073.7 | U58: 262165.65
A60: META (CY)
A61: META | B61: Revenue | C61: 7872 | D61: 12466 | E61: 17927 | F61: 27638 | G61: 40653 | H61: 55838 | I61: 70696.5 | J61: 85966 | K61: 117929 | L61: 116609 | M61: 134901 | N61: 164500 | O61: 200965 | P61: 255175.56 | Q61: 306410.52 | R61: 357336.07 | S61: 407351.97 | T61: 456192.68 | U61: 503691.81
A62: META | B62: Operating Income (GAAP) | C62: 2804 | D62: 4994.8 | E62: 6225 | F62: 12427 | G62: 20202 | H62: 24913 | I62: 23985.5 | J62: 32671 | K62: 46753 | L62: 28945 | M62: 46751 | N62: 69380 | O62: 83276 | P62: 90489.79 | Q62: 104437.61 | R62: 118413.08 | S62: 131523.75 | T62: 142814.67 | U62: 157939.61
A63: META | B63: Net Income | C63: 1491 | D63: 2924.8 | E63: 3669 | F63: 10187.2 | G63: 15919 | H63: 22112 | I63: 18484.5 | J63: 29145 | K63: 39370 | L63: 23199 | M63: 39097 | N63: 62360 | O63: 60458 | P63: 85782.86 | Q63: 91160.94 | R63: 103452.71 | S63: 115846.5 | T63: 127804.37 | U63: 143941.83
A64: META | B64: EPS (GAAP) | C64: 0.59 | D64: 1.1 | E64: 1.28 | F64: 3.48 | G64: 5.39 | H64: 7.66 | I64: 6.44 | J64: 10.08 | K64: 14.07 | L64: 8.79 | M64: 14.87 | N64: 23.99 | O64: 23.49 | P64: 33.28 | Q64: 34.94 | R64: 39.24 | S64: 43.51 | T64: 47.52 | U64: 52.96
A65: META | B65: Diluted Shares (mm) | C65: 2521.75 | D65: 2671 | E65: 2856.75 | F65: 2923.75 | G65: 2954 | H65: 2886 | I65: 2871 | J65: 2890 | K65: 2799 | L65: 2640 | M65: 2630 | N65: 2599 | O65: 2574 | P65: 2577.79 | Q65: 2609.3 | R65: 2636.12 | S65: 2662.83 | T65: 2689.4 | U65: 2718.12
A66: META | B66: Stock-Based Comp | C66: -906 | D66: -1837 | E66: -2969 | F66: -3202 | G66: -3723 | H66: -4152 | I66: -4835 | J66: -6536 | K66: -9163 | L66: -11991 | M66: -14027 | N66: -16690 | O66: -20426 | P66: -23722.2 | Q66: -24908.31 | R66: -26153.73 | S66: -27461.41 | T66: -28834.48 | U66: -30276.21
A67: META | B67: D&A | C67: 1011 | D67: 1243 | E67: 1945 | F67: 2342 | G67: 3025 | H67: 4315 | I67: 5741 | J67: 6862 | K67: 7966 | L67: 8686 | M67: 11177 | N67: 15498 | O67: 18616 | P67: 35955.99 | Q67: 56602.9 | R67: 78641.85 | S67: 100070.74 | T67: 120937.09 | U67: 136172.14
A68: META | B68: Capex | C68: 1362 | D68: 1831 | E68: 2523 | F68: 4491 | G68: 6732 | H68: 13980 | I68: 15102 | J68: 15115 | K68: 18567 | L68: 31186 | M68: 27045 | N68: 37256 | O68: 69691 | P68: 135583.71 | Q68: 165714.44 | R68: 185600.17 | S68: 196736.18 | T68: 208540.35 | U68: 221052.77
A69: META | B69: Cash from Operations | C69: 4222 | D69: 5507.8 | E69: 8607 | F69: 16061 | G69: 24216 | H69: 29339 | I69: 36312.5 | J69: 38747 | K69: 57683 | L69: 50475 | M69: 71113 | N69: 91328 | O69: 115800 | P69: 180250.64 | Q69: 206102.96 | R69: 243250.01 | S69: 279015.98 | T69: 314478.51 | U69: 340847.48
A70: META | B70: Free Cash Flow | C70: 2860 | D70: 3676.8 | E70: 6084 | F70: 11570 | G70: 17484 | H70: 15359 | I70: 21210.5 | J70: 23632 | K70: 39116 | L70: 19289 | M70: 44068 | N70: 54072 | O70: 46109 | P70: 44666.93 | Q70: 40388.52 | R70: 57649.84 | S70: 82279.8 | T70: 105938.16 | U70: 119794.71
A71: META | B71: Buybacks | C71: 0 | D71: 0 | E71: 0 | F71: 0 | G71: 1976 | H71: 12879 | I71: 4201 | J71: 6272 | K71: 44538 | L71: 27956 | M71: 19775 | N71: 30125 | O71: 26248 | P71: 0 | Q71: 6000 | R71: 6000 | S71: 6000 | T71: 6000 | U71: 1003
A72: META | B72: Family of Apps Revenue | I72: 70196 | J72: 84826 | K72: 115655 | L72: 114450 | M72: 133005 | N72: 162354 | O72: 198758 | P72: 252529.81 | Q72: 303235.62 | R72: 353605.56 | S72: 403061.89 | T72: 451366.33 | U72: 498382.83
A73: META | B73: Family of Apps OI | I73: 28489 | J73: 39294 | K73: 56947 | L73: 42662 | M73: 62870 | N73: 87109 | O73: 102469 | P73: 109500.79 | Q73: 122498.06 | R73: 135570.51 | S73: 147823.31 | T73: 158299.25 | U73: 172649.96
A74: META | B74: Advertising Revenue | C74: 6986 | D74: 11492 | E74: 17080 | F74: 26885 | G74: 39942 | H74: 55012 | I74: 69654.5 | J74: 84169 | K74: 114934 | L74: 113641 | M74: 131948 | N74: 160632 | O74: 196174 | P74: 248664.66 | Q74: 298597.44 | R74: 348271.65 | S74: 397194.59 | T74: 444912.31 | U74: 491283.4
A75: META | B75: Reality Labs Revenue | I75: 501 | J75: 1139 | K75: 2274 | L75: 2159 | M75: 1896 | N75: 2146 | O75: 2207 | P75: 2645.75 | Q75: 3174.9 | R75: 3730.51 | S75: 4290.08 | T75: 4826.34 | U75: 5308.98
A76: META | B76: Reality Labs OI | I76: -4503 | J76: -6623 | K76: -10194 | L76: -13717 | M76: -16119 | N76: -17729 | O76: -19193 | P76: -19011 | Q76: -18060.45 | R76: -17157.43 | S76: -16299.56 | T76: -15484.58 | U76: -14710.35
A78: ORCL (FY(May))
A79: ORCL | B79: Revenue | C79: 37253 | D79: 38305 | E79: 38253 | F79: 37057 | G79: 37899 | H79: 39431 | I79: 39525 | J79: 39073 | K79: 40481 | L79: 42441 | M79: 49955 | N79: 52961 | O79: 57399 | P79: 67286.75 | Q79: 88782.02 | R79: 125445.05 | S79: 165192.96 | T79: 185555.08
A80: ORCL | B80: Operating Income (GAAP) | C80: 14684 | D80: 14758 | E80: 13870 | F80: 12604 | G80: 12710 | H80: 13264 | I80: 13535 | J80: 13897 | K80: 15214 | L80: 10927 | M80: 13094 | N80: 15354 | O80: 17678 | P80: 19462.44 | Q80: 21128.19 | R80: 36930.86 | S80: 53057.71 | T80: 57952.82
A81: ORCL | B81: Operating Income (Adj) | C81: 17612 | D81: 18108 | E81: 17396 | F81: 15785 | G81: 16168 | H81: 17155 | I81: 17384 | J81: 17383 | K81: 19000 | L81: 19592 | M81: 20904 | N81: 23054 | O81: 25034 | P81: 28113.04 | Q81: 28489.16 | R81: 46280.73 | S81: 64368.1 | T81: 69758.92
A82: ORCL | B82: Net Income | C82: 10926 | D82: 10955 | E82: 9938 | F82: 8900 | G82: 9334 | H82: 3587 | I82: 11083 | J82: 10135 | K82: 13747 | L82: 6718 | M82: 8504 | N82: 10467 | O82: 12443 | P82: 15820.55 | Q82: 13363.1 | R82: 26776.66 | S82: 39834.82 | T82: 44104.48
A83: ORCL | B83: EPS (GAAP) | C83: 2.26 | D83: 2.38 | E83: 2.21 | F83: 2.07 | G83: 2.21 | H83: 0.85 | I83: 2.97 | J83: 3.08 | K83: 4.55 | L83: 2.41 | M83: 3.07 | N83: 3.71 | O83: 4.34 | P83: 5.43 | Q83: 4.54 | R83: 8.98 | S83: 13.15 | T83: 14.32
A84: ORCL | B84: EPS (Adjusted) | C84: 2.68 | D84: 2.87 | E84: 2.77 | F84: 2.61 | G84: 2.74 | H84: 3.05 | I84: 3.52 | J84: 3.85 | K84: 4.67 | L84: 4.9 | M84: 5.12 | N84: 5.56 | O84: 6.03 | P84: 7.32 | Q84: 6.09 | R84: 10.59 | S84: 14.81 | T84: 15.94
A85: ORCL | B85: Diluted Shares (mm) | C85: 4843.75 | D85: 4604.5 | E85: 4502.5 | F85: 4305.5 | G85: 4217 | H85: 4238 | I85: 3732 | J85: 3293.5 | K85: 3022.5 | L85: 2785.5 | M85: 2766.25 | N85: 2823.25 | O85: 2866.25 | P85: 2915.76 | Q85: 2940.66 | R85: 2980.3 | S85: 3028.26 | T85: 3079.57
A86: ORCL | B86: Stock-Based Comp | C86: 755 | D86: 805 | E86: 933 | F86: 1037 | G86: 1350 | H86: 1607 | I86: 1653 | J86: 1590 | K86: 1837 | L86: 2613 | M86: 3547 | N86: 3974 | O86: 4674 | P86: 5069.6 | Q86: 6473.15 | R86: 8609.75 | S86: 10649.61 | T86: 11212.32
A87: ORCL | B87: D&A | C87: 546 | D87: 608 | E87: 712 | F87: 871 | G87: 1000 | H87: 1165 | I87: 1230 | J87: 1382 | K87: 1537 | L87: 1972 | M87: 2526 | N87: 3129 | O87: 3867 | P87: 7501.53 | Q87: 16868.58 | R87: 27597.91 | S87: 39646.31 | T87: 48244.32
A88: ORCL | B88: Capex | C88: 650 | D88: 580 | E88: 1391 | F88: 1189 | G88: 2021 | H88: 1736 | I88: 1660 | J88: 1564 | K88: 2135 | L88: 4511 | M88: 8695 | N88: 6866 | O88: 21215 | P88: 51882 | Q88: 52141.41 | R88: 69869.49 | S88: 81048.61 | T88: 66459.86
A89: ORCL | B89: Cash from Operations | C89: 14225 | D89: 14921 | E89: 14336 | F89: 13560 | G89: 14125 | H89: 15386 | I89: 14551 | J89: 13139 | K89: 15888 | L89: 9540 | M89: 17166 | N89: 18673 | O89: 20821 | P89: 25457.17 | Q89: 33694.38 | R89: 50132.95 | S89: 66529.01 | T89: 84964.12
A90: ORCL | B90: Free Cash Flow | C90: 13575 | D90: 14341 | E90: 12945 | F90: 12371 | G90: 12104 | H90: 13650 | I90: 12891 | J90: 11575 | K90: 13753 | L90: 5029 | M90: 8471 | N90: 11807 | O90: -394 | P90: -26424.83 | Q90: -18447.03 | R90: -19736.54 | S90: -14519.6 | T90: 18504.26
... A93: ORCL | B93: Cloud Total (ORCL) | C93: 1365 | D93: 1577 | E93: 2094 | F93: 2854 | G93: 4572 | H93: 6189.17 | I93: 6918.19 | J93: 7811.32 | K93: 8945 | L93: 10809 | M93: 15882 | N93: 19775 | O93: 24507 | P93: 34020.24 | Q93: 55591.76 | R93: 92351.27 | S93: 132214.36 | T93: 152708.94
A94: ORCL | B94: IaaS / OCI Revenue | L94: 2760.74 | M94: 4500 | N94: 6800 | O94: 10234 | P94: 18064.4 | Q94: 37935.24 | R94: 72977.07 | S94: 111105.3 | T94: 129847.66
A95: ORCL | B95: SaaS Revenue | L95: 7999.33 | M95: 11400 | N95: 12949 | O95: 14272 | P95: 15955.84 | Q95: 17656.52 | R95: 19374.2 | S95: 21109.07 | T95: 22861.28
A96: ORCL | B96: Cloud Services Revenue | M96: 15882 | N96: 19775 | O96: 24507 | P96: 34020.24 | Q96: 55591.76 | R96: 92351.27 | S96: 132214.36 | T96: 152708.94
A97: ORCL | B97: RPO Backlog | I97: 36200 | J97: 37000 | K97: 41300 | L97: 46600 | M97: 67900 | N97: 98000 | O97: 138000

Sheet 1. Summary
B2: AI Capex Cycle: Hyperscaler Deep-Dive
B3: MSFT | AMZN | GOOGL | META | ORCL — 2013-2031E — Source: broker financial models
B5: KEY TAKEAWAYS
B6: 1. Revenue acceleration is real: all 5 show 2026E growth re-accelerating. Cloud/AI metrics (RPO, IaaS) confirm demand.
B7: 2. Capex intensity unprecedented: Capex/Rev 24-77% in 2026E. ORCL 77%, META 55% — telecom-bubble territory.
B8: 3. FCF breaking down at ORCL (-39%) and AMZN (-2%). Buybacks paused at META/GOOGL/ORCL in 2026E.
B9: 4. EPS bifurcating: MSFT/GOOGL=high quality. ORCL=low (FY27E EPS -17% per own model).
B10: 5. Burry GPU thesis: 3yr life → ORCL EPS -60%, AMZN -66%, META -37%, MSFT -25%, GOOGL -21%.
B11: 6. GS Q1'26 insight: 'other income' from private equity stakes = record 34% of hyperscaler Q1'26 profit. Strip → EPS growth 61%→25%. Circular financing warning.
B12: 7. Most likely burst window: 2027H1-H2 (D&A wave + concentration risk). Base case 45% probability.
B13: 8. Strategy: hold MSFT/GOOGL (defensible); reduce ORCL (floor); watch AMZN/META (threshold).
B15: SHEETS
... B25: 9. Charts — 6 visualizations (formula-linked)

Sheet 2. Revenue
A1: Revenue & AI/Cloud Detail (2013-2031E)
A3: A. Total Revenue ($mm)
A4: Company | B4: 2013A | C4: 2014A | D4: 2015A | E4: 2016A | F4: 2017A | G4: 2018A | H4: 2019A | I4: 2020A | J4: 2021A | K4: 2022A | L4: 2023A | M4: 2024A | N4: 2025E | O4: 2026E | P4: 2027E | Q4: 2028E | R4: 2029E | S4: 2030E | T4: 2031E
A5: MSFT | B5: ='0. Database'!C6 -> 77849 | C5: ='0. Database'!D6 -> 86833 | D5: ='0. Database'!E6 -> 93580 | E5: ='0. Database'!F6 -> 85320 | F5: ='0. Database'!G6 -> 96571 | G5: ='0. Database'!H6 -> 110360 | H5: ='0. Database'!I6 -> 125843 | I5: ='0. Database'!J6 -> 143015 | ... T5: ='0. Database'!U6 -> 0
A6: AMZN | B6: ='0. Database'!C25 -> 74453 | C6: ='0. Database'!D25 -> 88988.4 | D6: ='0. Database'!E25 -> 107006.6 | E6: ='0. Database'!F25 -> 135987 | F6: ='0. Database'!G25 -> 177866 | G6: ='0. Database'!H25 -> 232887 | H6: ='0. Database'!I25 -> 280522 | I6: ='0. Database'!J25 -> 386064 | ... T6: ='0. Database'!U25 -> 1427912.6
A7: GOOGL | B7: ='0. Database'!C42 -> 55519 | C7: ='0. Database'!D42 -> 66001 | D7: ='0. Database'!E42 -> 74989 | E7: ='0. Database'!F42 -> 90272 | F7: ='0. Database'!G42 -> 110855 | G7: ='0. Database'!H42 -> 136819 | H7: ='0. Database'!I42 -> 161857 | I7: ='0. Database'!J42 -> 182527 | ... T7: ='0. Database'!U42 -> 1029231.9
A8: META | B8: ='0. Database'!C61 -> 7872 | C8: ='0. Database'!D61 -> 12466 | D8: ='0. Database'!E61 -> 17927 | E8: ='0. Database'!F61 -> 27638 | F8: ='0. Database'!G61 -> 40653 | G8: ='0. Database'!H61 -> 55838 | H8: ='0. Database'!I61 -> 70696.5 | I8: ='0. Database'!J61 -> 85966 | ... T8: ='0. Database'!U61 -> 503691.81
A9: ORCL | B9: ='0. Database'!C79 -> 37253 | C9: ='0. Database'!D79 -> 38305 | D9: ='0. Database'!E79 -> 38253 | E9: ='0. Database'!F79 -> 37057 | F9: ='0. Database'!G79 -> 37899 | G9: ='0. Database'!H79 -> 39431 | H9: ='0. Database'!I79 -> 39525 | I9: ='0. Database'!J79 -> 39073 | ... T9: ='0. Database'!U79 -> 0
A12: B. Revenue YoY %
A13: Company | B13: 2013A | C13: 2014A | D13: 2015A | E13: 2016A | F13: 2017A | G13: 2018A | H13: 2019A | I13: 2020A | J13: 2021A | K13: 2022A | L13: 2023A | M13: 2024A | N13: 2025E | O13: 2026E | P13: 2027E | Q13: 2028E | R13: 2029E | S13: 2030E | T13: 2031E
A14: MSFT | C14: =IFERROR('0. Database'!D6/'0. Database'!C6-1,"") -> 0.1154029 | D14: =IFERROR('0. Database'!E6/'0. Database'!D6-1,"") -> 0.077700874 | E14: =IFERROR('0. Database'!F6/'0. Database'!E6-1,"") -> -0.088266724 | F14: =IFERROR('0. Database'!G6/'0. Database'!F6-1,"") -> 0.13186826 | G14: =IFERROR('0. Database'!H6/'0. Database'!G6-1,"") -> 0.14278614 | H14: =IFERROR('0. Database'!I6/'0. Database'!H6-1,"") -> 0.1402954 | I14: =IFERROR('0. Database'!J6/'0. Database'!I6-1,"") -> 0.13645574 | J14: =IFERROR('0. Database'!K6/'0. Database'!J6-1,"") -> 0.17531727 | ... T14: =IFERROR('0. Database'!U6/'0. Database'!T6-1,"") -> -1
A15: AMZN | C15: =IFERROR('0. Database'!D25/'0. Database'!C25-1,"") -> 0.19522921 | D15: =IFERROR('0. Database'!E25/'0. Database'!D25-1,"") -> 0.20247808 | E15: =IFERROR('0. Database'!F25/'0. Database'!E25-1,"") -> 0.27082815 | F15: =IFERROR('0. Database'!G25/'0. Database'!F25-1,"") -> 0.30796326 | G15: =IFERROR('0. Database'!H25/'0. Database'!G25-1,"") -> 0.30933962 | H15: =IFERROR('0. Database'!I25/'0. Database'!H25-1,"") -> 0.20454126 | I15: =IFERROR('0. Database'!J25/'0. Database'!I25-1,"") -> 0.37623431 | J15: =IFERROR('0. Database'!K25/'0. Database'!J25-1,"") -> 0.21695367 | ... T15: =IFERROR('0. Database'!U25/'0. Database'!T25-1,"") -> 0.093837665
A16: GOOGL | C16: =IFERROR('0. Database'!D42/'0. Database'!C42-1,"") -> 0.18880023 | D16: =IFERROR('0. Database'!E42/'0. Database'!D42-1,"") -> 0.13617975 | E16: =IFERROR('0. Database'!F42/'0. Database'!E42-1,"") -> 0.20380322 | F16: =IFERROR('0. Database'!G42/'0. Database'!F42-1,"") -> 0.2280109 | G16: =IFERROR('0. Database'!H42/'0. Database'!G42-1,"") -> 0.23421587 | H16: =IFERROR('0. Database'!I42/'0. Database'!H42-1,"") -> 0.1830009 | I16: =IFERROR('0. Database'!J42/'0. Database'!I42-1,"") -> 0.12770532 | J16: =IFERROR('0. Database'!K42/'0. Database'!J42-1,"") -> 0.41150076 | ... T16: =IFERROR('0. Database'!U42/'0. Database'!T42-1,"") -> 0.11645501
A17: META | C17: =IFERROR('0. Database'!D61/'0. Database'!C61-1,"") -> 0.5835874 | D17: =IFERROR('0. Database'!E61/'0. Database'!D61-1,"") -> 0.43807155 | E17: =IFERROR('0. Database'!F61/'0. Database'!E61-1,"") -> 0.54169688 | F17: =IFERROR('0. Database'!G61/'0. Database'!F61-1,"") -> 0.47090962 | G17: =IFERROR('0. Database'!H61/'0. Database'!G61-1,"") -> 0.37352717 | H17: =IFERROR('0. Database'!I61/'0. Database'!H61-1,"") -> 0.26610015 | I17: =IFERROR('0. Database'!J61/'0. Database'!I61-1,"") -> 0.21598665 | J17: =IFERROR('0. Database'!K61/'0. Database'!J61-1,"") -> 0.37180979 | ... T17: =IFERROR('0. Database'!U61/'0. Database'!T61-1,"") -> 0.10412076
A18: ORCL | C18: =IFERROR('0. Database'!D79/'0. Database'!C79-1,"") -> 0.028239336 | D18: =IFERROR('0. Database'!E79/'0. Database'!D79-1,"") -> -0.0013575251 | E18: =IFERROR('0. Database'!F79/'0. Database'!E79-1,"") -> -0.031265522 | F18: =IFERROR('0. Database'!G79/'0. Database'!F79-1,"") -> 0.022721753 | G18: =IFERROR('0. Database'!H79/'0. Database'!G79-1,"") -> 0.04042323 | H18: =IFERROR('0. Database'!I79/'0. Database'!H79-1,"") -> 0.0023839111 | I18: =IFERROR('0. Database'!J79/'0. Database'!I79-1,"") -> -0.0114358 | J18: =IFERROR('0. Database'!K79/'0. Database'!J79-1,"") -> 0.036035114 | ... T18: =IFERROR('0. Database'!U79/'0. Database'!T79-1,"") -> -1
A21: C. Cloud/AI Proxy Revenue ($mm) — AWS|GCloud|Azure|OCI|Ads
A22: Company | B22: 2013A | C22: 2014A | D22: 2015A | E22: 2016A | F22: 2017A | G22: 2018A | H22: 2019A | I22: 2020A | J22: 2021A | K22: 2022A | L22: 2023A | M22: 2024A | N22: 2025E | O22: 2026E | P22: 2027E | Q22: 2028E | R22: 2029E | S22: 2030E | T22: 2031E
A23: MSFT
A24: AMZN | B24: ='0. Database'!C36 -> 3107.57 | C24: ='0. Database'!D36 -> 4644 | D24: ='0. Database'!E36 -> 7880 | E24: ='0. Database'!F36 -> 12219 | F24: ='0. Database'!G36 -> 17458 | G24: ='0. Database'!H36 -> 25656 | H24: ='0. Database'!I36 -> 35026 | I24: ='0. Database'!J36 -> 45370 | ... T24: ='0. Database'!U36 -> 423565.53
A25: GOOGL | B25: ='0. Database'!C53 -> 0 | C25: ='0. Database'!D53 -> 0 | D25: ='0. Database'!E53 -> 0 | E25: ='0. Database'!F53 -> 0 | F25: ='0. Database'!G53 -> 4056 | G25: ='0. Database'!H53 -> 5838 | H25: ='0. Database'!I53 -> 8918 | I25: ='0. Database'!J53 -> 13059 | ... T25: ='0. Database'!U53 -> 400237.78
A26: META | B26: ='0. Database'!C74 -> 6986 | C26: ='0. Database'!D74 -> 11492 | D26: ='0. Database'!E74 -> 17080 | E26: ='0. Database'!F74 -> 26885 | F26: ='0. Database'!G74 -> 39942 | G26: ='0. Database'!H74 -> 55012 | H26: ='0. Database'!I74 -> 69654.5 | I26: ='0. Database'!J74 -> 84169 | ... T26: ='0. Database'!U74 -> 491283.4
A27: ORCL | B27: ='0. Database'!C93 -> 1365 | C27: ='0. Database'!D93 -> 1577 | D27: ='0. Database'!E93 -> 2094 | E27: ='0. Database'!F93 -> 2854 | F27: ='0. Database'!G93 -> 4572 | G27: ='0. Database'!H93 -> 6189.17 | H27: ='0. Database'!I93 -> 6918.19 | I27: ='0. Database'!J93 -> 7811.32 | ... T27: ='0. Database'!U93 -> 0

Sheet 3. Capex & D&A
A1: Capex & Depreciation (2013-2031E)
A3: A. Capex ($mm)
A4: Company | B4: 2013A | C4: 2014A | D4: 2015A | E4: 2016A | F4: 2017A | G4: 2018A | H4: 2019A | I4: 2020A | J4: 2021A | K4: 2022A | L4: 2023A | M4: 2024A | N4: 2025E | O4: 2026E | P4: 2027E | Q4: 2028E | R4: 2029E | S4: 2030E | T4: 2031E
A5: MSFT | B5: ='0. Database'!C13 -> 4257 | C5: ='0. Database'!D13 -> 5485 | D5: ='0. Database'!E13 -> 5944 | E5: ='0. Database'!F13 -> 8932 | F5: ='0. Database'!G13 -> 10200 | G5: ='0. Database'!H13 -> 13600 | H5: ='0. Database'!I13 -> 16900 | I5: ='0. Database'!J13 -> 19000 | ... T5: ='0. Database'!U13 -> 0
A6: AMZN | B6: ='0. Database'!C32 -> 3443 | C6: ='0. Database'!D32 -> 4892 | D6: ='0. Database'!E32 -> 4588 | E6: ='0. Database'!F32 -> 6736 | F6: ='0. Database'!G32 -> 10057 | G6: ='0. Database'!H32 -> 11322 | H6: ='0. Database'!I32 -> 12690 | I6: ='0. Database'!J32 -> 35046 | ... T6: ='0. Database'!U32 -> 328358.95
A7: GOOGL | B7: ='0. Database'!C49 -> 7358 | C7: ='0. Database'!D49 -> 10959 | D7: ='0. Database'!E49 -> 9915 | E7: ='0. Database'!F49 -> 10183 | F7: ='0. Database'!G49 -> 13184 | G7: ='0. Database'!H49 -> 25139 | H7: ='0. Database'!I49 -> 23548 | I7: ='0. Database'!J49 -> 22281 | ... T7: ='0. Database'!U49 -> 330225.02
A8: META | B8: ='0. Database'!C68 -> 1362 | C8: ='0. Database'!D68 -> 1831 | D8: ='0. Database'!E68 -> 2523 | E8: ='0. Database'!F68 -> 4491 | F8: ='0. Database'!G68 -> 6732 | G8: ='0. Database'!H68 -> 13980 | H8: ='0. Database'!I68 -> 15102 | I8: ='0. Database'!J68 -> 15115 | ... T8: ='0. Database'!U68 -> 221052.77
A9: ORCL | B9: ='0. Database'!C88 -> 650 | C9: ='0. Database'!D88 -> 580 | D9: ='0. Database'!E88 -> 1391 | E9: ='0. Database'!F88 -> 1189 | F9: ='0. Database'!G88 -> 2021 | G9: ='0. Database'!H88 -> 1736 | H9: ='0. Database'!I88 -> 1660 | I9: ='0. Database'!J88 -> 1564 | ... T9: ='0. Database'!U88 -> 0
A12: B. Capex YoY %
A13: Company | B13: 2013A | C13: 2014A | D13: 2015A | E13: 2016A | F13: 2017A | G13: 2018A | H13: 2019A | I13: 2020A | J13: 2021A | K13: 2022A | L13: 2023A | M13: 2024A | N13: 2025E | O13: 2026E | P13: 2027E | Q13: 2028E | R13: 2029E | S13: 2030E | T13: 2031E
A14: MSFT | C14: =IFERROR('0. Database'!D13/'0. Database'!C13-1,"") -> 0.28846606 | D14: =IFERROR('0. Database'!E13/'0. Database'!D13-1,"") -> 0.083682771 | E14: =IFERROR('0. Database'!F13/'0. Database'!E13-1,"") -> 0.50269179 | F14: =IFERROR('0. Database'!G13/'0. Database'!F13-1,"") -> 0.14196149 | G14: =IFERROR('0. Database'!H13/'0. Database'!G13-1,"") -> 0.33333333 | H14: =IFERROR('0. Database'!I13/'0. Database'!H13-1,"") -> 0.24264706 | I14: =IFERROR('0. Database'!J13/'0. Database'!I13-1,"") -> 0.12426036 | J14: =IFERROR('0. Database'!K13/'0. Database'!J13-1,"") -> 0.27368421 | ... T14: =IFERROR('0. Database'!U13/'0. Database'!T13-1,"") -> -1
A15: AMZN | C15: =IFERROR('0. Database'!D32/'0. Database'!C32-1,"") -> 0.42085391 | D15: =IFERROR('0. Database'!E32/'0. Database'!D32-1,"") -> -0.062142273 | E15: =IFERROR('0. Database'!F32/'0. Database'!E32-1,"") -> 0.46817786 | F15: =IFERROR('0. Database'!G32/'0. Database'!F32-1,"") -> 0.49302257 | G15: =IFERROR('0. Database'!H32/'0. Database'!G32-1,"") -> 0.12578304 | H15: =IFERROR('0. Database'!I32/'0. Database'!H32-1,"") -> 0.12082671 | I15: =IFERROR('0. Database'!J32/'0. Database'!I32-1,"") -> 1.7617021 | J15: =IFERROR('0. Database'!K32/'0. Database'!J32-1,"") -> 0.58066541 | ... T15: =IFERROR('0. Database'!U32/'0. Database'!T32-1,"") -> 0.049999998
A16: GOOGL | C16: =IFERROR('0. Database'!D49/'0. Database'!C49-1,"") -> 0.48939929 | D16: =IFERROR('0. Database'!E49/'0. Database'!D49-1,"") -> -0.095264166 | E16: =IFERROR('0. Database'!F49/'0. Database'!E49-1,"") -> 0.027029753 | F16: =IFERROR('0. Database'!G49/'0. Database'!F49-1,"") -> 0.29470686 | G16: =IFERROR('0. Database'!H49/'0. Database'!G49-1,"") -> 0.90678095 | H16: =IFERROR('0. Database'!I49/'0. Database'!H49-1,"") -> -0.063288118 | I16: =IFERROR('0. Database'!J49/'0. Database'!I49-1,"") -> -0.053804994 | J16: =IFERROR('0. Database'!K49/'0. Database'!J49-1,"") -> 0.10587496 | ... T16: =IFERROR('0. Database'!U49/'0. Database'!T49-1,"") -> 0.049999997
A17: META | C17: =IFERROR('0. Database'!D68/'0. Database'!C68-1,"") -> 0.34434655 | D17: =IFERROR('0. Database'!E68/'0. Database'!D68-1,"") -> 0.37793555 | E17: =IFERROR('0. Database'!F68/'0. Database'!E68-1,"") -> 0.78002378 | F17: =IFERROR('0. Database'!G68/'0. Database'!F68-1,"") -> 0.498998 | G17: =IFERROR('0. Database'!H68/'0. Database'!G68-1,"") -> 1.0766488 | H17: =IFERROR('0. Database'!I68/'0. Database'!H68-1,"") -> 0.080257511 | I17: =IFERROR('0. Database'!J68/'0. Database'!I68-1,"") -> 0.00086081314 | J17: =IFERROR('0. Database'!K68/'0. Database'!J68-1,"") -> 0.2283824 | ... T17: =IFERROR('0. Database'!U68/'0. Database'!T68-1,"") -> 0.059999995
A18: ORCL | C18: =IFERROR('0. Database'!D88/'0. Database'!C88-1,"") -> -0.10769231 | D18: =IFERROR('0. Database'!E88/'0. Database'!D88-1,"") -> 1.3982759 | E18: =IFERROR('0. Database'!F88/'0. Database'!E88-1,"") -> -0.14521927 | F18: =IFERROR('0. Database'!G88/'0. Database'!F88-1,"") -> 0.69974769 | G18: =IFERROR('0. Database'!H88/'0. Database'!G88-1,"") -> -0.1410193 | H18: =IFERROR('0. Database'!I88/'0. Database'!H88-1,"") -> -0.043778802 | I18: =IFERROR('0. Database'!J88/'0. Database'!I88-1,"") -> -0.057831325 | J18: =IFERROR('0. Database'!K88/'0. Database'!J88-1,"") -> 0.36508951 | ... T18: =IFERROR('0. Database'!U88/'0. Database'!T88-1,"") -> -1
A21: C. Capex / Revenue %
A22: Company | B22: 2013A | C22: 2014A | D22: 2015A | E22: 2016A | F22: 2017A | G22: 2018A | H22: 2019A | I22: 2020A | J22: 2021A | K22: 2022A | L22: 2023A | M22: 2024A | N22: 2025E | O22: 2026E | P22: 2027E | Q22: 2028E | R22: 2029E | S22: 2030E | T22: 2031E
A23: MSFT | B23: =IFERROR('0. Database'!C13/'0. Database'!C6,"") -> 0.054682783 | C23: =IFERROR('0. Database'!D13/'0. Database'!D6,"") -> 0.063167229 | D23: =IFERROR('0. Database'!E13/'0. Database'!E6,"") -> 0.063517846 | E23: =IFERROR('0. Database'!F13/'0. Database'!F6,"") -> 0.10468823 | F23: =IFERROR('0. Database'!G13/'0. Database'!G6,"") -> 0.10562177 | G23: =IFERROR('0. Database'!H13/'0. Database'!H6,"") -> 0.12323306 | H23: =IFERROR('0. Database'!I13/'0. Database'!I6,"") -> 0.13429432 | I23: =IFERROR('0. Database'!J13/'0. Database'!J6,"") -> 0.1328532 | ... T23: =IFERROR('0. Database'!U13/'0. Database'!U6,"")
A24: AMZN | B24: =IFERROR('0. Database'!C32/'0. Database'!C25,"") -> 0.046243939 | C24: =IFERROR('0. Database'!D32/'0. Database'!D25,"") -> 0.054973457 | D24: =IFERROR('0. Database'!E32/'0. Database'!E25,"") -> 0.04287586 | E24: =IFERROR('0. Database'!F32/'0. Database'!F25,"") -> 0.049534147 | F24: =IFERROR('0. Database'!G32/'0. Database'!G25,"") -> 0.056542566 | G24: =IFERROR('0. Database'!H32/'0. Database'!H25,"") -> 0.048615852 | H24: =IFERROR('0. Database'!I32/'0. Database'!I25,"") -> 0.045237094 | I24: =IFERROR('0. Database'!J32/'0. Database'!J25,"") -> 0.090777695 | ... T24: =IFERROR('0. Database'!U32/'0. Database'!U25,"") -> 0.22995731
A25: GOOGL | B25: =IFERROR('0. Database'!C49/'0. Database'!C42,"") -> 0.13253121 | C25: =IFERROR('0. Database'!D49/'0. Database'!D42,"") -> 0.16604294 | D25: =IFERROR('0. Database'!E49/'0. Database'!E42,"") -> 0.13221939 | E25: =IFERROR('0. Database'!F49/'0. Database'!F42,"") -> 0.11280353 | F25: =IFERROR('0. Database'!G49/'0. Database'!G42,"") -> 0.11893013 | G25: =IFERROR('0. Database'!H49/'0. Database'!H42,"") -> 0.1837391 | H25: =IFERROR('0. Database'!I49/'0. Database'!I42,"") -> 0.14548645 | I25: =IFERROR('0. Database'!J49/'0. Database'!J42,"") -> 0.12206961 | ... T25: =IFERROR('0. Database'!U49/'0. Database'!U42,"") -> 0.32084608
A26: META | B26: =IFERROR('0. Database'!C68/'0. Database'!C61,"") -> 0.17301829 | C26: =IFERROR('0. Database'!D68/'0. Database'!D61,"") -> 0.14687951 | D26: =IFERROR('0. Database'!E68/'0. Database'!E61,"") -> 0.14073744 | E26: =IFERROR('0. Database'!F68/'0. Database'!F61,"") -> 0.16249367 | F26: =IFERROR('0. Database'!G68/'0. Database'!G61,"") -> 0.16559663 | G26: =IFERROR('0. Database'!H68/'0. Database'!H61,"") -> 0.25036713 | H26: =IFERROR('0. Database'!I68/'0. Database'!I61,"") -> 0.21361736 | I26: =IFERROR('0. Database'!J68/'0. Database'!J61,"") -> 0.17582533 | ... T26: =IFERROR('0. Database'!U68/'0. Database'!U61,"") -> 0.43886513
A27: ORCL | B27: =IFERROR('0. Database'!C88/'0. Database'!C79,"") -> 0.017448259 | C27: =IFERROR('0. Database'!D88/'0. Database'!D79,"") -> 0.015141626 | D27: =IFERROR('0. Database'!E88/'0. Database'!E79,"") -> 0.036363161 | E27: =IFERROR('0. Database'!F88/'0. Database'!F79,"") -> 0.032085706 | F27: =IFERROR('0. Database'!G88/'0. Database'!G79,"") -> 0.053325945 | G27: =IFERROR('0. Database'!H88/'0. Database'!H79,"") -> 0.044026274 | H27: =IFERROR('0. Database'!I88/'0. Database'!I79,"") -> 0.041998735 | I27: =IFERROR('0. Database'!J88/'0. Database'!J79,"") -> 0.040027641 | ... T27: =IFERROR('0. Database'!U88/'0. Database'!U79,"")
A30: D. D&A ($mm)
A31: Company | B31: 2013A | C31: 2014A | D31: 2015A | E31: 2016A | F31: 2017A | G31: 2018A | H31: 2019A | I31: 2020A | J31: 2021A | K31: 2022A | L31: 2023A | M31: 2024A | N31: 2025E | O31: 2026E | P31: 2027E | Q31: 2028E | R31: 2029E | S31: 2030E | T31: 2031E
A32: MSFT | B32: ='0. Database'!C12 -> 3339 | C32: ='0. Database'!D12 -> 4245 | D32: ='0. Database'!E12 -> 5400 | E32: ='0. Database'!F12 -> 5878 | F32: ='0. Database'!G12 -> 7800 | G32: ='0. Database'!H12 -> 9900 | H32: ='0. Database'!I12 -> 11600 | I32: ='0. Database'!J12 -> 12300 | ... T32: ='0. Database'!U12 -> 0
A33: AMZN | B33: ='0. Database'!C31 -> 3253 | C33: ='0. Database'!D31 -> 4745 | D33: ='0. Database'!E31 -> 6281 | E33: ='0. Database'!F31 -> 8117 | F33: ='0. Database'!G31 -> 11478 | G33: ='0. Database'!H31 -> 15341 | H33: ='0. Database'!I31 -> 21789 | I33: ='0. Database'!J31 -> 25251 | ... T33: ='0. Database'!U31 -> 191789.29
A34: GOOGL | B34: ='0. Database'!C48 -> 2781 | C34: ='0. Database'!D48 -> 3523 | D34: ='0. Database'!E48 -> 4132 | E34: ='0. Database'!F48 -> 5267 | F34: ='0. Database'!G48 -> 6103 | G34: ='0. Database'!H48 -> 8164 | H34: ='0. Database'!I48 -> 10856 | I34: ='0. Database'!J48 -> 12905 | ... T34: ='0. Database'!U48 -> 181381.37
A35: META | B35: ='0. Database'!C67 -> 1011 | C35: ='0. Database'!D67 -> 1243 | D35: ='0. Database'!E67 -> 1945 | E35: ='0. Database'!F67 -> 2342 | F35: ='0. Database'!G67 -> 3025 | G35: ='0. Database'!H67 -> 4315 | H35: ='0. Database'!I67 -> 5741 | I35: ='0. Database'!J67 -> 6862 | ... T35: ='0. Database'!U67 -> 136172.14
A36: ORCL | B36: ='0. Database'!C87 -> 546 | C36: ='0. Database'!D87 -> 608 | D36: ='0. Database'!E87 -> 712 | E36: ='0. Database'!F87 -> 871 | F36: ='0. Database'!G87 -> 1000 | G36: ='0. Database'!H87 -> 1165 | H36: ='0. Database'!I87 -> 1230 | I36: ='0. Database'!J87 -> 1382 | ... T36: ='0. Database'!U87 -> 0
A39: E. D&A / Revenue %
A40: Company | B40: 2013A | C40: 2014A | D40: 2015A | E40: 2016A | F40: 2017A | G40: 2018A | H40: 2019A | I40: 2020A | J40: 2021A | K40: 2022A | L40: 2023A | M40: 2024A | N40: 2025E | O40: 2026E | P40: 2027E | Q40: 2028E | R40: 2029E | S40: 2030E | T40: 2031E
A41: MSFT | B41: =IFERROR('0. Database'!C12/'0. Database'!C6,"") -> 0.042890724 | C41: =IFERROR('0. Database'!D12/'0. Database'!D6,"") -> 0.048886944 | D41: =IFERROR('0. Database'!E12/'0. Database'!E6,"") -> 0.057704638 | E41: =IFERROR('0. Database'!F12/'0. Database'!F6,"") -> 0.068893577 | F41: =IFERROR('0. Database'!G12/'0. Database'!G6,"") -> 0.080769589 | G41: =IFERROR('0. Database'!H12/'0. Database'!H6,"") -> 0.089706415 | H41: =IFERROR('0. Database'!I12/'0. Database'!I6,"") -> 0.092178349 | I41: =IFERROR('0. Database'!J12/'0. Database'!J6,"") -> 0.086004965 | ... T41: =IFERROR('0. Database'!U12/'0. Database'!U6,"")
A42: AMZN | B42: =IFERROR('0. Database'!C31/'0. Database'!C25,"") -> 0.043691994 | C42: =IFERROR('0. Database'!D31/'0. Database'!D25,"") -> 0.053321557 | D42: =IFERROR('0. Database'!E31/'0. Database'!E25,"") -> 0.058697314 | E42: =IFERROR('0. Database'!F31/'0. Database'!F25,"") -> 0.059689529 | F42: =IFERROR('0. Database'!G31/'0. Database'!G25,"") -> 0.064531726 | G42: =IFERROR('0. Database'!H31/'0. Database'!H25,"") -> 0.065873149 | H42: =IFERROR('0. Database'!I31/'0. Database'!I25,"") -> 0.077673052 | I42: =IFERROR('0. Database'!J31/'0. Database'!J25,"") -> 0.065406254 | ... T42: =IFERROR('0. Database'!U31/'0. Database'!U25,"") -> 0.13431444
A43: GOOGL | B43: =IFERROR('0. Database'!C48/'0. Database'!C42,"") -> 0.05009096 | C43: =IFERROR('0. Database'!D48/'0. Database'!D42,"") -> 0.053377979 | D43: =IFERROR('0. Database'!E48/'0. Database'!E42,"") -> 0.055101415 | E43: =IFERROR('0. Database'!F48/'0. Database'!F42,"") -> 0.058345888 | F43: =IFERROR('0. Database'!G48/'0. Database'!G42,"") -> 0.055053899 | G43: =IFERROR('0. Database'!H48/'0. Database'!H42,"") -> 0.059670075 | H43: =IFERROR('0. Database'!I48/'0. Database'!I42,"") -> 0.067071551 | I43: =IFERROR('0. Database'!J48/'0. Database'!J42,"") -> 0.070701869 | ... T43: =IFERROR('0. Database'!U48/'0. Database'!U42,"") -> 0.17622984
A44: META | B44: =IFERROR('0. Database'!C67/'0. Database'!C61,"") -> 0.12842988 | C44: =IFERROR('0. Database'!D67/'0. Database'!D61,"") -> 0.099711215 | D44: =IFERROR('0. Database'!E67/'0. Database'!E61,"") -> 0.10849557 | E44: =IFERROR('0. Database'!F67/'0. Database'!F61,"") -> 0.084738404 | F44: =IFERROR('0. Database'!G67/'0. Database'!G61,"") -> 0.074410253 | G44: =IFERROR('0. Database'!H67/'0. Database'!H61,"") -> 0.077277123 | H44: =IFERROR('0. Database'!I67/'0. Database'!I61,"") -> 0.081206283 | I44: =IFERROR('0. Database'!J67/'0. Database'!J61,"") -> 0.079822255 | ... T44: =IFERROR('0. Database'!U67/'0. Database'!U61,"") -> 0.27034813
A45: ORCL | B45: =IFERROR('0. Database'!C87/'0. Database'!C79,"") -> 0.014656538 | C45: =IFERROR('0. Database'!D87/'0. Database'!D79,"") -> 0.015872601 | D45: =IFERROR('0. Database'!E87/'0. Database'!E79,"") -> 0.018612919 | E45: =IFERROR('0. Database'!F87/'0. Database'!F79,"") -> 0.023504331 | F45: =IFERROR('0. Database'!G87/'0. Database'!G79,"") -> 0.02638592 | G45: =IFERROR('0. Database'!H87/'0. Database'!H79,"") -> 0.029545282 | H45: =IFERROR('0. Database'!I87/'0. Database'!I79,"") -> 0.031119545 | I45: =IFERROR('0. Database'!J87/'0. Database'!J79,"") -> 0.035369693 | ... T45: =IFERROR('0. Database'!U87/'0. Database'!U79,"")
A48: F. D&A YoY %
A49: Company | B49: 2013A | C49: 2014A | D49: 2015A | E49: 2016A | F49: 2017A | G49: 2018A | H49: 2019A | I49: 2020A | J49: 2021A | K49: 2022A | L49: 2023A | M49: 2024A | N49: 2025E | O49: 2026E | P49: 2027E | Q49: 2028E | R49: 2029E | S49: 2030E | T49: 2031E
A50: MSFT | C50: =IFERROR('0. Database'!D12/'0. Database'!C12-1,"") -> 0.27133872 | D50: =IFERROR('0. Database'!E12/'0. Database'!D12-1,"") -> 0.27208481 | E50: =IFERROR('0. Database'!F12/'0. Database'!E12-1,"") -> 0.088518519 | F50: =IFERROR('0. Database'!G12/'0. Database'!F12-1,"") -> 0.32698197 | G50: =IFERROR('0. Database'!H12/'0. Database'!G12-1,"") -> 0.26923077 | H50: =IFERROR('0. Database'!I12/'0. Database'!H12-1,"") -> 0.17171717 | I50: =IFERROR('0. Database'!J12/'0. Database'!I12-1,"") -> 0.060344828 | J50: =IFERROR('0. Database'!K12/'0. Database'!J12-1,"") -> -0.11382114 | ... T50: =IFERROR('0. Database'!U12/'0. Database'!T12-1,"") -> -1
A51: AMZN | C51: =IFERROR('0. Database'!D31/'0. Database'!C31-1,"") -> 0.45865355 | D51: =IFERROR('0. Database'!E31/'0. Database'!D31-1,"") -> 0.32370917 | E51: =IFERROR('0. Database'!F31/'0. Database'!E31-1,"") -> 0.29231014 | F51: =IFERROR('0. Database'!G31/'0. Database'!F31-1,"") -> 0.41406924 | G51: =IFERROR('0. Database'!H31/'0. Database'!G31-1,"") -> 0.33655689 | H51: =IFERROR('0. Database'!I31/'0. Database'!H31-1,"") -> 0.42031158 | I51: =IFERROR('0. Database'!J31/'0. Database'!I31-1,"") -> 0.15888751 | J51: =IFERROR('0. Database'!K31/'0. Database'!J31-1,"") -> 0.35820364 | ... T51: =IFERROR('0. Database'!U31/'0. Database'!T31-1,"") -> 0.093118928
A52: GOOGL | C52: =IFERROR('0. Database'!D48/'0. Database'!C48-1,"") -> 0.2668105 | D52: =IFERROR('0. Database'!E48/'0. Database'!D48-1,"") -> 0.17286404 | E52: =IFERROR('0. Database'!F48/'0. Database'!E48-1,"") -> 0.27468538 | F52: =IFERROR('0. Database'!G48/'0. Database'!F48-1,"") -> 0.15872413 | G52: =IFERROR('0. Database'!H48/'0. Database'!G48-1,"") -> 0.33770277 | H52: =IFERROR('0. Database'!I48/'0. Database'!H48-1,"") -> 0.32974032 | I52: =IFERROR('0. Database'!J48/'0. Database'!I48-1,"") -> 0.18874355 | J52: =IFERROR('0. Database'!K48/'0. Database'!J48-1,"") -> -0.10461062 | ... T52: =IFERROR('0. Database'!U48/'0. Database'!T48-1,"") -> 0.16154572
A53: META | C53: =IFERROR('0. Database'!D67/'0. Database'!C67-1,"") -> 0.22947577 | D53: =IFERROR('0. Database'!E67/'0. Database'!D67-1,"") -> 0.56476267 | E53: =IFERROR('0. Database'!F67/'0. Database'!E67-1,"") -> 0.20411311 | F53: =IFERROR('0. Database'!G67/'0. Database'!F67-1,"") -> 0.29163108 | G53: =IFERROR('0. Database'!H67/'0. Database'!G67-1,"") -> 0.42644628 | H53: =IFERROR('0. Database'!I67/'0. Database'!H67-1,"") -> 0.33047509 | I53: =IFERROR('0. Database'!J67/'0. Database'!I67-1,"") -> 0.19526215 | J53: =IFERROR('0. Database'!K67/'0. Database'!J67-1,"") -> 0.16088604 | ... T53: =IFERROR('0. Database'!U67/'0. Database'!T67-1,"") -> 0.125975
A54: ORCL | C54: =IFERROR('0. Database'!D87/'0. Database'!C87-1,"") -> 0.11355311 | D54: =IFERROR('0. Database'!E87/'0. Database'!D87-1,"") -> 0.17105263 | E54: =IFERROR('0. Database'!F87/'0. Database'!E87-1,"") -> 0.22331461 | F54: =IFERROR('0. Database'!G87/'0. Database'!F87-1,"") -> 0.14810563 | G54: =IFERROR('0. Database'!H87/'0. Database'!G87-1,"") -> 0.165 | H54: =IFERROR('0. Database'!I87/'0. Database'!H87-1,"") -> 0.055793991 | I54: =IFERROR('0. Database'!J87/'0. Database'!I87-1,"") -> 0.12357724 | J54: =IFERROR('0. Database'!K87/'0. Database'!J87-1,"") -> 0.1121563 | ... T54: =IFERROR('0. Database'!U87/'0. Database'!T87-1,"") -> -1

Sheet 4. FCF & Cash
A1: FCF & Cash Quality (2013-2031E)
A3: A. CFO ($mm)
A4: Company | B4: 2013A | C4: 2014A | D4: 2015A | E4: 2016A | F4: 2017A | G4: 2018A | H4: 2019A | I4: 2020A | J4: 2021A | K4: 2022A | L4: 2023A | M4: 2024A | N4: 2025E | O4: 2026E | P4: 2027E | Q4: 2028E | R4: 2029E | S4: 2030E | T4: 2031E
A5: MSFT | B5: ='0. Database'!C16 -> 28833 | C5: ='0. Database'!D16 -> 32231 | D5: ='0. Database'!E16 -> 29080 | E5: ='0. Database'!F16 -> 33325 | F5: ='0. Database'!G16 -> 39507 | G5: ='0. Database'!H16 -> 43884 | H5: ='0. Database'!I16 -> 52185 | I5: ='0. Database'!J16 -> 60675 | ... T5: ='0. Database'!U16 -> 0
A6: AMZN | B6: ='0. Database'!C33 -> 5474 | C6: ='0. Database'!D33 -> 6841.4 | D6: ='0. Database'!E33 -> 11920.1 | E6: ='0. Database'!F33 -> 17271 | F6: ='0. Database'!G33 -> 18434 | G6: ='0. Database'!H33 -> 30724 | H6: ='0. Database'!I33 -> 38515 | I6: ='0. Database'!J33 -> 66064 | ... T6: ='0. Database'!U33 -> 451875.96
A7: GOOGL | B7: ='0. Database'!C50 -> 18584 | C7: ='0. Database'!D50 -> 22272 | D7: ='0. Database'!E50 -> 25829 | E7: ='0. Database'!F50 -> 36036 | F7: ='0. Database'!G50 -> 37091 | G7: ='0. Database'!H50 -> 47971 | H7: ='0. Database'!I50 -> 54520 | I7: ='0. Database'!J50 -> 65124 | ... T7: ='0. Database'!U50 -> 557191.03
A8: META | B8: ='0. Database'!C69 -> 4222 | C8: ='0. Database'!D69 -> 5507.8 | D8: ='0. Database'!E69 -> 8607 | E8: ='0. Database'!F69 -> 16061 | F8: ='0. Database'!G69 -> 24216 | G8: ='0. Database'!H69 -> 29339 | H8: ='0. Database'!I69 -> 36312.5 | I8: ='0. Database'!J69 -> 38747 | ... T8: ='0. Database'!U69 -> 340847.48
A9: ORCL | B9: ='0. Database'!C89 -> 14225 | C9: ='0. Database'!D89 -> 14921 | D9: ='0. Database'!E89 -> 14336 | E9: ='0. Database'!F89 -> 13560 | F9: ='0. Database'!G89 -> 14125 | G9: ='0. Database'!H89 -> 15386 | H9: ='0. Database'!I89 -> 14551 | I9: ='0. Database'!J89 -> 13139 | ... T9: ='0. Database'!U89 -> 0
A12: B. FCF ($mm)
A13: Company | B13: 2013A | C13: 2014A | D13: 2015A | E13: 2016A | F13: 2017A | G13: 2018A | H13: 2019A | I13: 2020A | J13: 2021A | K13: 2022A | L13: 2023A | M13: 2024A | N13: 2025E | O13: 2026E | P13: 2027E | Q13: 2028E | R13: 2029E | S13: 2030E | T13: 2031E
A14: MSFT | B14: ='0. Database'!C17 -> 24576 | C14: ='0. Database'!D17 -> 26746 | D14: ='0. Database'!E17 -> 23136 | E14: ='0. Database'!F17 -> 24393 | F14: ='0. Database'!G17 -> 29307 | G14: ='0. Database'!H17 -> 30284 | H14: ='0. Database'!I17 -> 35285 | I14: ='0. Database'!J17 -> 41675 | ... T14: ='0. Database'!U17 -> 0
A15: AMZN | B15: ='0. Database'!C34 -> 2031 | C15: ='0. Database'!D34 -> 1949.4 | D15: ='0. Database'!E34 -> 7332.1 | E15: ='0. Database'!F34 -> 10535 | F15: ='0. Database'!G34 -> 8377 | G15: ='0. Database'!H34 -> 19402 | H15: ='0. Database'!I34 -> 25825 | I15: ='0. Database'!J34 -> 31018 | ... T15: ='0. Database'!U34 -> 123517
A16: GOOGL | B16: ='0. Database'!C51 -> 11226 | C16: ='0. Database'!D51 -> 11313 | D16: ='0. Database'!E51 -> 15914 | E16: ='0. Database'!F51 -> 25853 | F16: ='0. Database'!G51 -> 23907 | G16: ='0. Database'!H51 -> 22832 | H16: ='0. Database'!I51 -> 30972 | I16: ='0. Database'!J51 -> 42843 | ... T16: ='0. Database'!U51 -> 226966.01
A17: META | B17: ='0. Database'!C70 -> 2860 | C17: ='0. Database'!D70 -> 3676.8 | D17: ='0. Database'!E70 -> 6084 | E17: ='0. Database'!F70 -> 11570 | F17: ='0. Database'!G70 -> 17484 | G17: ='0. Database'!H70 -> 15359 | H17: ='0. Database'!I70 -> 21210.5 | I17: ='0. Database'!J70 -> 23632 | ... T17: ='0. Database'!U70 -> 119794.71
A18: ORCL | B18: ='0. Database'!C90 -> 13575 | C18: ='0. Database'!D90 -> 14341 | D18: ='0. Database'!E90 -> 12945 | E18: ='0. Database'!F90 -> 12371 | F18: ='0. Database'!G90 -> 12104 | G18: ='0. Database'!H90 -> 13650 | H18: ='0. Database'!I90 -> 12891 | I18: ='0. Database'!J90 -> 11575 | ... T18: ='0. Database'!U90 -> 0
A21: C. FCF Margin %
A22: Company | B22: 2013A | C22: 2014A | D22: 2015A | E22: 2016A | F22: 2017A | G22: 2018A | H22: 2019A | I22: 2020A | J22: 2021A | K22: 2022A | L22: 2023A | M22: 2024A | N22: 2025E | O22: 2026E | P22: 2027E | Q22: 2028E | R22: 2029E | S22: 2030E | T22: 2031E
A23: MSFT | B23: =IFERROR('0. Database'!C17/'0. Database'!C6,"") -> 0.31568806 | C23: =IFERROR('0. Database'!D17/'0. Database'!D6,"") -> 0.30801654 | D23: =IFERROR('0. Database'!E17/'0. Database'!E6,"") -> 0.24723231 | E23: =IFERROR('0. Database'!F17/'0. Database'!F6,"") -> 0.28590014 | F23: =IFERROR('0. Database'!G17/'0. Database'!G6,"") -> 0.3034762 | G23: =IFERROR('0. Database'!H17/'0. Database'!H6,"") -> 0.27441102 | H23: =IFERROR('0. Database'!I17/'0. Database'!I6,"") -> 0.28038906 | I23: =IFERROR('0. Database'!J17/'0. Database'!J6,"") -> 0.291403 | ... T23: =IFERROR('0. Database'!U17/'0. Database'!U6,"")
A24: AMZN | B24: =IFERROR('0. Database'!C34/'0. Database'!C25,"") -> 0.027278955 | C24: =IFERROR('0. Database'!D34/'0. Database'!D25,"") -> 0.021906226 | D24: =IFERROR('0. Database'!E34/'0. Database'!E25,"") -> 0.068520073 | E24: =IFERROR('0. Database'!F34/'0. Database'!F25,"") -> 0.077470641 | F24: =IFERROR('0. Database'!G34/'0. Database'!G25,"") -> 0.047097253 | G24: =IFERROR('0. Database'!H34/'0. Database'!H25,"") -> 0.08331079 | H24: =IFERROR('0. Database'!I34/'0. Database'!I25,"") -> 0.092060516 | I24: =IFERROR('0. Database'!J34/'0. Database'!J25,"") -> 0.080344192 | ... T24: =IFERROR('0. Database'!U34/'0. Database'!U25,"") -> 0.086501792
A25: GOOGL | B25: =IFERROR('0. Database'!C51/'0. Database'!C42,"") -> 0.20220105 | C25: =IFERROR('0. Database'!D51/'0. Database'!D42,"") -> 0.17140649 | D25: =IFERROR('0. Database'!E51/'0. Database'!E42,"") -> 0.21221779 | E25: =IFERROR('0. Database'!F51/'0. Database'!F42,"") -> 0.28639002 | F25: =IFERROR('0. Database'!G51/'0. Database'!G42,"") -> 0.2156601 | G25: =IFERROR('0. Database'!H51/'0. Database'!H42,"") -> 0.16687741 | H25: =IFERROR('0. Database'!I51/'0. Database'!I42,"") -> 0.1913541 | I25: =IFERROR('0. Database'!J51/'0. Database'!J42,"") -> 0.23472144 | ... T25: =IFERROR('0. Database'!U51/'0. Database'!U42,"") -> 0.2205198
A26: META | B26: =IFERROR('0. Database'!C70/'0. Database'!C61,"") -> 0.36331301 | C26: =IFERROR('0. Database'!D70/'0. Database'!D61,"") -> 0.29494625 | D26: =IFERROR('0. Database'!E70/'0. Database'!E61,"") -> 0.33937636 | E26: =IFERROR('0. Database'!F70/'0. Database'!F61,"") -> 0.41862653 | F26: =IFERROR('0. Database'!G70/'0. Database'!G61,"") -> 0.43007896 | G26: =IFERROR('0. Database'!H70/'0. Database'!H61,"") -> 0.27506358 | H26: =IFERROR('0. Database'!I70/'0. Database'!I61,"") -> 0.30002192 | I26: =IFERROR('0. Database'!J70/'0. Database'!J61,"") -> 0.27489938 | ... T26: =IFERROR('0. Database'!U70/'0. Database'!U61,"") -> 0.23783335
A27: ORCL | B27: =IFERROR('0. Database'!C90/'0. Database'!C79,"") -> 0.36440018 | C27: =IFERROR('0. Database'!D90/'0. Database'!D79,"") -> 0.37438977 | D27: =IFERROR('0. Database'!E90/'0. Database'!E79,"") -> 0.33840483 | E27: =IFERROR('0. Database'!F90/'0. Database'!F79,"") -> 0.33383706 | F27: =IFERROR('0. Database'!G90/'0. Database'!G79,"") -> 0.31937518 | G27: =IFERROR('0. Database'!H90/'0. Database'!H79,"") -> 0.34617433 | H27: =IFERROR('0. Database'!I90/'0. Database'!I79,"") -> 0.32614801 | I27: =IFERROR('0. Database'!J90/'0. Database'!J79,"") -> 0.29624037 | ... T27: =IFERROR('0. Database'!U90/'0. Database'!U79,"")
A30: D. FCF / Net Income %
A31: Company | B31: 2013A | C31: 2014A | D31: 2015A | E31: 2016A | F31: 2017A | G31: 2018A | H31: 2019A | I31: 2020A | J31: 2021A | K31: 2022A | L31: 2023A | M31: 2024A | N31: 2025E | O31: 2026E | P31: 2027E | Q31: 2028E | R31: 2029E | S31: 2030E | T31: 2031E
A32: MSFT | B32: =IFERROR('0. Database'!C17/'0. Database'!C8,"") -> 1.1240909 | C32: =IFERROR('0. Database'!D17/'0. Database'!D8,"") -> 1.2116517 | D32: =IFERROR('0. Database'!E17/'0. Database'!E8,"") -> 1.8974822 | E32: =IFERROR('0. Database'!F17/'0. Database'!F8,"") -> 1.4521372 | F32: =IFERROR('0. Database'!G17/'0. Database'!G8,"") -> 1.1497901 | G32: =IFERROR('0. Database'!H17/'0. Database'!H8,"") -> 1.82753 | H32: =IFERROR('0. Database'!I17/'0. Database'!I8,"") -> 0.89920999 | I32: =IFERROR('0. Database'!J17/'0. Database'!J8,"") -> 0.94114857 | ... T32: =IFERROR('0. Database'!U17/'0. Database'!U8,"")
A33: AMZN | B33: =IFERROR('0. Database'!C34/'0. Database'!C27,"") -> 7.4395604 | C33: =IFERROR('0. Database'!D34/'0. Database'!D27,"") -> -8.1022444 | D33: =IFERROR('0. Database'!E34/'0. Database'!E27,"") -> 12.300117 | E33: =IFERROR('0. Database'!F34/'0. Database'!F27,"") -> 4.4432729 | F33: =IFERROR('0. Database'!G34/'0. Database'!G27,"") -> 2.7619519 | G33: =IFERROR('0. Database'!H34/'0. Database'!H27,"") -> 1.9261392 | H33: =IFERROR('0. Database'!I34/'0. Database'!I27,"") -> 2.2285986 | I33: =IFERROR('0. Database'!J34/'0. Database'!J27,"") -> 1.4541278 | ... T33: =IFERROR('0. Database'!U34/'0. Database'!U27,"") -> 0.49888171
A34: GOOGL | B34: =IFERROR('0. Database'!C51/'0. Database'!C44,"") -> 0.88254717 | C34: =IFERROR('0. Database'!D51/'0. Database'!D44,"") -> 0.80029711 | D34: =IFERROR('0. Database'!E51/'0. Database'!E44,"") -> 0.97345241 | E34: =IFERROR('0. Database'!F51/'0. Database'!F44,"") -> 1.3272923 | F34: =IFERROR('0. Database'!G51/'0. Database'!G44,"") -> 1.8880903 | G34: =IFERROR('0. Database'!H51/'0. Database'!H44,"") -> 0.74284227 | H34: =IFERROR('0. Database'!I51/'0. Database'!I44,"") -> 0.90184317 | I34: =IFERROR('0. Database'!J51/'0. Database'!J44,"") -> 1.0639201 | ... T34: =IFERROR('0. Database'!U51/'0. Database'!U44,"") -> 0.6955695
A35: META | B35: =IFERROR('0. Database'!C70/'0. Database'!C63,"") -> 1.9181757 | C35: =IFERROR('0. Database'!D70/'0. Database'!D63,"") -> 1.2571116 | D35: =IFERROR('0. Database'!E70/'0. Database'!E63,"") -> 1.6582175 | E35: =IFERROR('0. Database'!F70/'0. Database'!F63,"") -> 1.135739 | F35: =IFERROR('0. Database'!G70/'0. Database'!G63,"") -> 1.0983102 | G35: =IFERROR('0. Database'!H70/'0. Database'!H63,"") -> 0.69460022 | H35: =IFERROR('0. Database'!I70/'0. Database'!I63,"") -> 1.1474749 | I35: =IFERROR('0. Database'!J70/'0. Database'!J63,"") -> 0.81084234 | ... T35: =IFERROR('0. Database'!U70/'0. Database'!U63,"") -> 0.8322439
A36: ORCL | B36: =IFERROR('0. Database'!C90/'0. Database'!C82,"") -> 1.2424492 | C36: =IFERROR('0. Database'!D90/'0. Database'!D82,"") -> 1.3090826 | D36: =IFERROR('0. Database'!E90/'0. Database'!E82,"") -> 1.302576 | E36: =IFERROR('0. Database'!F90/'0. Database'!F82,"") -> 1.39 | F36: =IFERROR('0. Database'!G90/'0. Database'!G82,"") -> 1.2967645 | G36: =IFERROR('0. Database'!H90/'0. Database'!H82,"") -> 3.8054084 | H36: =IFERROR('0. Database'!I90/'0. Database'!I82,"") -> 1.1631327 | I36: =IFERROR('0. Database'!J90/'0. Database'!J82,"") -> 1.1420819 | ... T36: =IFERROR('0. Database'!U90/'0. Database'!U82,"")
A39: E. Buybacks ($mm)
A40: Company | B40: 2013A | C40: 2014A | D40: 2015A | E40: 2016A | F40: 2017A | G40: 2018A | H40: 2019A | I40: 2020A | J40: 2021A | K40: 2022A | L40: 2023A | M40: 2024A | N40: 2025E | O40: 2026E | P40: 2027E | Q40: 2028E | R40: 2029E | S40: 2030E | T40: 2031E
A41: MSFT | B41: ='0. Database'!C18 -> 5360 | C41: ='0. Database'!D18 -> 7316 | D41: ='0. Database'!E18 -> 14443 | E41: ='0. Database'!F18 -> 15969 | F41: ='0. Database'!G18 -> 11788 | G41: ='0. Database'!H18 -> 10721 | H41: ='0. Database'!I18 -> 19543 | I41: ='0. Database'!J18 -> 22968 | ... T41: ='0. Database'!U18 -> 0
A42: AMZN | B42: ='0. Database'!C35 -> 0 | C42: ='0. Database'!D35 -> 0 | D42: ='0. Database'!E35 -> 0 | E42: ='0. Database'!F35 -> 0 | F42: ='0. Database'!G35 -> 0 | G42: ='0. Database'!H35 -> 0 | H42: ='0. Database'!I35 -> 0 | I42: ='0. Database'!J35 -> 0 | ... T42: ='0. Database'!U35 -> 0
A43: GOOGL | B43: ='0. Database'!C52 -> 0 | C43: ='0. Database'!D52 -> 0 | D43: ='0. Database'!E52 -> 1827 | E43: ='0. Database'!F52 -> 3693 | F43: ='0. Database'!G52 -> 4846 | G43: ='0. Database'!H52 -> 9075 | H43: ='0. Database'!I52 -> 18396 | I43: ='0. Database'!J52 -> 31149 | ... T43: ='0. Database'!U52 -> 0
A44: META | B44: ='0. Database'!C71 -> 0 | C44: ='0. Database'!D71 -> 0 | D44: ='0. Database'!E71 -> 0 | E44: ='0. Database'!F71 -> 0 | F44: ='0. Database'!G71 -> 1976 | G44: ='0. Database'!H71 -> 12879 | H44: ='0. Database'!I71 -> 4201 | I44: ='0. Database'!J71 -> 6272 | ... T44: ='0. Database'!U71 -> 1003
A45: ORCL | B45: ='0. Database'!C91 -> 11021 | C45: ='0. Database'!D91 -> 9813 | D45: ='0. Database'!E91 -> 8087 | E45: ='0. Database'!F91 -> 10440 | F45: ='0. Database'!G91 -> 3561 | G45: ='0. Database'!H91 -> 11347 | H45: ='0. Database'!I91 -> 36140 | I45: ='0. Database'!J91 -> 19240 | ... T45: ='0. Database'!U91 -> 0
A48: F. Capex / CFO %
A49: Company | B49: 2013A | C49: 2014A | D49: 2015A | E49: 2016A | F49: 2017A | G49: 2018A | H49: 2019A | I49: 2020A | J49: 2021A | K49: 2022A | L49: 2023A | M49: 2024A | N49: 2025E | O49: 2026E | P49: 2027E | Q49: 2028E | R49: 2029E | S49: 2030E | T49: 2031E
A50: MSFT | B50: =IFERROR('0. Database'!C13/'0. Database'!C16,"") -> 0.14764333 | C50: =IFERROR('0. Database'!D13/'0. Database'!D16,"") -> 0.17017778 | D50: =IFERROR('0. Database'!E13/'0. Database'!E16,"") -> 0.20440165 | E50: =IFERROR('0. Database'!F13/'0. Database'!F16,"") -> 0.26802701 | F50: =IFERROR('0. Database'!G13/'0. Database'!G16,"") -> 0.25818209 | G50: =IFERROR('0. Database'!H13/'0. Database'!H16,"") -> 0.30990794 | H50: =IFERROR('0. Database'!I13/'0. Database'!I16,"") -> 0.32384785 | I50: =IFERROR('0. Database'!J13/'0. Database'!J16,"") -> 0.3131438 | ... T50: =IFERROR('0. Database'!U13/'0. Database'!U16,"")
A51: AMZN | B51: =IFERROR('0. Database'!C32/'0. Database'!C33,"") -> 0.62897333 | C51: =IFERROR('0. Database'!D32/'0. Database'!D33,"") -> 0.71505832 | D51: =IFERROR('0. Database'!E32/'0. Database'!E33,"") -> 0.3848961 | E51: =IFERROR('0. Database'!F32/'0. Database'!F33,"") -> 0.39001795 | F51: =IFERROR('0. Database'!G32/'0. Database'!G33,"") -> 0.54556797 | G51: =IFERROR('0. Database'!H32/'0. Database'!H33,"") -> 0.3685067 | H51: =IFERROR('0. Database'!I32/'0. Database'!I33,"") -> 0.32948202 | I51: =IFERROR('0. Database'!J32/'0. Database'!J33,"") -> 0.53048559 | ... T51: =IFERROR('0. Database'!U32/'0. Database'!U33,"") -> 0.72665727
A52: GOOGL | B52: =IFERROR('0. Database'!C49/'0. Database'!C50,"") -> 0.39593198 | C52: =IFERROR('0. Database'!D49/'0. Database'!D50,"") -> 0.4920528 | D52: =IFERROR('0. Database'!E49/'0. Database'!E50,"") -> 0.38387084 | E52: =IFERROR('0. Database'!F49/'0. Database'!F50,"") -> 0.28257853 | F52: =IFERROR('0. Database'!G49/'0. Database'!G50,"") -> 0.35545011 | G52: =IFERROR('0. Database'!H49/'0. Database'!H50,"") -> 0.52404578 | H52: =IFERROR('0. Database'!I49/'0. Database'!I50,"") -> 0.43191489 | I52: =IFERROR('0. Database'!J49/'0. Database'!J50,"") -> 0.34213193 | ... T52: =IFERROR('0. Database'!U49/'0. Database'!U50,"") -> 0.59266033
A53: META | B53: =IFERROR('0. Database'!C68/'0. Database'!C69,"") -> 0.32259593 | C53: =IFERROR('0. Database'!D68/'0. Database'!D69,"") -> 0.33243763 | D53: =IFERROR('0. Database'!E68/'0. Database'!E69,"") -> 0.2931335 | E53: =IFERROR('0. Database'!F68/'0. Database'!F69,"") -> 0.27962144 | F53: =IFERROR('0. Database'!G68/'0. Database'!G69,"") -> 0.27799802 | G53: =IFERROR('0. Database'!H68/'0. Database'!H69,"") -> 0.47649886 | H53: =IFERROR('0. Database'!I68/'0. Database'!I69,"") -> 0.41588985 | I53: =IFERROR('0. Database'!J68/'0. Database'!J69,"") -> 0.39009472 | ... T53: =IFERROR('0. Database'!U68/'0. Database'!U69,"") -> 0.64853867
A54: ORCL | B54: =IFERROR('0. Database'!C88/'0. Database'!C89,"") -> 0.0456942 | C54: =IFERROR('0. Database'!D88/'0. Database'!D89,"") -> 0.038871389 | D54: =IFERROR('0. Database'!E88/'0. Database'!E89,"") -> 0.09702846 | E54: =IFERROR('0. Database'!F88/'0. Database'!F89,"") -> 0.087684366 | F54: =IFERROR('0. Database'!G88/'0. Database'!G89,"") -> 0.14307965 | G54: =IFERROR('0. Database'!H88/'0. Database'!H89,"") -> 0.11282985 | H54: =IFERROR('0. Database'!I88/'0. Database'!I89,"") -> 0.11408151 | I54: =IFERROR('0. Database'!J88/'0. Database'!J89,"") -> 0.11903493 | ... T54: =IFERROR('0. Database'!U88/'0. Database'!U89,"")

Sheet 5. EPS & Margins
A1: EPS, OpMargin & Profitability (2013-2031E)
A3: A. Operating Income ($mm)
A4: Company | B4: 2013A | C4: 2014A | D4: 2015A | E4: 2016A | F4: 2017A | G4: 2018A | H4: 2019A | I4: 2020A | J4: 2021A | K4: 2022A | L4: 2023A | M4: 2024A | N4: 2025E | O4: 2026E | P4: 2027E | Q4: 2028E | R4: 2029E | S4: 2030E | T4: 2031E
A5: MSFT | B5: ='0. Database'!C7 -> 26764 | C5: ='0. Database'!D7 -> 27759 | D5: ='0. Database'!E7 -> 18161 | E5: ='0. Database'!F7 -> 20182 | F5: ='0. Database'!G7 -> 29025 | G5: ='0. Database'!H7 -> 35058 | H5: ='0. Database'!I7 -> 42959 | I5: ='0. Database'!J7 -> 52959 | ... T5: ='0. Database'!U7 -> 0
A6: AMZN | B6: ='0. Database'!C26 -> 745 | C6: ='0. Database'!D26 -> 178.4 | D6: ='0. Database'!E26 -> 2232.6 | E6: ='0. Database'!F26 -> 4186 | F6: ='0. Database'!G26 -> 4107 | G6: ='0. Database'!H26 -> 12420 | H6: ='0. Database'!I26 -> 14540 | I6: ='0. Database'!J26 -> 22899 | ... T6: ='0. Database'!U26 -> 305413.69
A7: GOOGL | B7: ='0. Database'!C43 -> 15403 | C7: ='0. Database'!D43 -> 16496 | D7: ='0. Database'!E43 -> 19360 | E7: ='0. Database'!F43 -> 23716 | F7: ='0. Database'!G43 -> 26146 | G7: ='0. Database'!H43 -> 26953 | H7: ='0. Database'!I43 -> 34231 | I7: ='0. Database'!J43 -> 41224 | ... T7: ='0. Database'!U43 -> 380286.59
A8: META | B8: ='0. Database'!C62 -> 2804 | C8: ='0. Database'!D62 -> 4994.8 | D8: ='0. Database'!E62 -> 6225 | E8: ='0. Database'!F62 -> 12427 | F8: ='0. Database'!G62 -> 20202 | G8: ='0. Database'!H62 -> 24913 | H8: ='0. Database'!I62 -> 23985.5 | I8: ='0. Database'!J62 -> 32671 | ... T8: ='0. Database'!U62 -> 157939.61
A9: ORCL | B9: ='0. Database'!C80 -> 14684 | C9: ='0. Database'!D80 -> 14758 | D9: ='0. Database'!E80 -> 13870 | E9: ='0. Database'!F80 -> 12604 | F9: ='0. Database'!G80 -> 12710 | G9: ='0. Database'!H80 -> 13264 | H9: ='0. Database'!I80 -> 13535 | I9: ='0. Database'!J80 -> 13897 | ... T9: ='0. Database'!U80 -> 0
A12: B. Operating Margin %
A13: Company | B13: 2013A | C13: 2014A | D13: 2015A | E13: 2016A | F13: 2017A | G13: 2018A | H13: 2019A | I13: 2020A | J13: 2021A | K13: 2022A | L13: 2023A | M13: 2024A | N13: 2025E | O13: 2026E | P13: 2027E | Q13: 2028E | R13: 2029E | S13: 2030E | T13: 2031E
A14: MSFT | B14: =IFERROR('0. Database'!C7/'0. Database'!C6,"") -> 0.34379375 | C14: =IFERROR('0. Database'!D7/'0. Database'!D6,"") -> 0.31968261 | D14: =IFERROR('0. Database'!E7/'0. Database'!E6,"") -> 0.19406925 | E14: =IFERROR('0. Database'!F7/'0. Database'!F6,"") -> 0.23654477 | F14: =IFERROR('0. Database'!G7/'0. Database'!G6,"") -> 0.30055607 | G14: =IFERROR('0. Database'!H7/'0. Database'!H6,"") -> 0.31766945 | H14: =IFERROR('0. Database'!I7/'0. Database'!I6,"") -> 0.3413698 | I14: =IFERROR('0. Database'!J7/'0. Database'!J6,"") -> 0.37030381 | ... T14: =IFERROR('0. Database'!U7/'0. Database'!U6,"")
A15: AMZN | B15: =IFERROR('0. Database'!C26/'0. Database'!C25,"") -> 0.010006313 | C15: =IFERROR('0. Database'!D26/'0. Database'!D25,"") -> 0.0020047557 | D15: =IFERROR('0. Database'!E26/'0. Database'!E25,"") -> 0.020864134 | E15: =IFERROR('0. Database'!F26/'0. Database'!F25,"") -> 0.030782354 | F15: =IFERROR('0. Database'!G26/'0. Database'!G25,"") -> 0.023090416 | G15: =IFERROR('0. Database'!H26/'0. Database'!H25,"") -> 0.053330585 | H15: =IFERROR('0. Database'!I26/'0. Database'!I25,"") -> 0.051831942 | I15: =IFERROR('0. Database'!J26/'0. Database'!J25,"") -> 0.059314 | ... T15: =IFERROR('0. Database'!U26/'0. Database'!U25,"") -> 0.21388822
A16: GOOGL | B16: =IFERROR('0. Database'!C43/'0. Database'!C42,"") -> 0.27743655 | C16: =IFERROR('0. Database'!D43/'0. Database'!D42,"") -> 0.24993561 | D16: =IFERROR('0. Database'!E43/'0. Database'!E42,"") -> 0.2581712 | E16: =IFERROR('0. Database'!F43/'0. Database'!F42,"") -> 0.26271712 | F16: =IFERROR('0. Database'!G43/'0. Database'!G42,"") -> 0.23585765 | G16: =IFERROR('0. Database'!H43/'0. Database'!H42,"") -> 0.19699749 | H16: =IFERROR('0. Database'!I43/'0. Database'!I42,"") -> 0.21148915 | I16: =IFERROR('0. Database'!J43/'0. Database'!J42,"") -> 0.22585152 | ... T16: =IFERROR('0. Database'!U43/'0. Database'!U42,"") -> 0.36948581
A17: META | B17: =IFERROR('0. Database'!C62/'0. Database'!C61,"") -> 0.35619919 | C17: =IFERROR('0. Database'!D62/'0. Database'!D61,"") -> 0.40067383 | D17: =IFERROR('0. Database'!E62/'0. Database'!E61,"") -> 0.34724159 | E17: =IFERROR('0. Database'!F62/'0. Database'!F61,"") -> 0.44963456 | F17: =IFERROR('0. Database'!G62/'0. Database'!G61,"") -> 0.4969375 | G17: =IFERROR('0. Database'!H62/'0. Database'!H61,"") -> 0.44616569 | H17: =IFERROR('0. Database'!I62/'0. Database'!I61,"") -> 0.33927422 | I17: =IFERROR('0. Database'!J62/'0. Database'!J61,"") -> 0.3800456 | ... T17: =IFERROR('0. Database'!U62/'0. Database'!U61,"") -> 0.31356398
A18: ORCL | B18: =IFERROR('0. Database'!C80/'0. Database'!C79,"") -> 0.3941696 | C18: =IFERROR('0. Database'!D80/'0. Database'!D79,"") -> 0.38527607 | D18: =IFERROR('0. Database'!E80/'0. Database'!E79,"") -> 0.36258594 | E18: =IFERROR('0. Database'!F80/'0. Database'!F79,"") -> 0.34012467 | F18: =IFERROR('0. Database'!G80/'0. Database'!G79,"") -> 0.33536505 | G18: =IFERROR('0. Database'!H80/'0. Database'!H79,"") -> 0.33638508 | H18: =IFERROR('0. Database'!I80/'0. Database'!I79,"") -> 0.34244149 | I18: =IFERROR('0. Database'!J80/'0. Database'!J79,"") -> 0.3556676 | ... T18: =IFERROR('0. Database'!U80/'0. Database'!U79,"")
A21: C. Net Income ($mm)
A22: Company | B22: 2013A | C22: 2014A | D22: 2015A | E22: 2016A | F22: 2017A | G22: 2018A | H22: 2019A | I22: 2020A | J22: 2021A | K22: 2022A | L22: 2023A | M22: 2024A | N22: 2025E | O22: 2026E | P22: 2027E | Q22: 2028E | R22: 2029E | S22: 2030E | T22: 2031E
A23: MSFT | B23: ='0. Database'!C8 -> 21863 | C23: ='0. Database'!D8 -> 22074 | D23: ='0. Database'!E8 -> 12193 | E23: ='0. Database'!F8 -> 16798 | F23: ='0. Database'!G8 -> 25489 | G23: ='0. Database'!H8 -> 16571 | H23: ='0. Database'!I8 -> 39240 | I23: ='0. Database'!J8 -> 44281 | ... T23: ='0. Database'!U8 -> 0
A24: AMZN | B24: ='0. Database'!C27 -> 273 | C24: ='0. Database'!D27 -> -240.6 | D24: ='0. Database'!E27 -> 596.1 | E24: ='0. Database'!F27 -> 2371 | F24: ='0. Database'!G27 -> 3033 | G24: ='0. Database'!H27 -> 10073 | H24: ='0. Database'!I27 -> 11588 | I24: ='0. Database'!J27 -> 21331 | ... T24: ='0. Database'!U27 -> 247587.75
A25: GOOGL | B25: ='0. Database'!C44 -> 12720 | C25: ='0. Database'!D44 -> 14136 | D25: ='0. Database'!E44 -> 16348 | E25: ='0. Database'!F44 -> 19478 | F25: ='0. Database'!G44 -> 12662 | G25: ='0. Database'!H44 -> 30736 | H25: ='0. Database'!I44 -> 34343 | I25: ='0. Database'!J44 -> 40269 | ... T25: ='0. Database'!U44 -> 326302.42
A26: META | B26: ='0. Database'!C63 -> 1491 | C26: ='0. Database'!D63 -> 2924.8 | D26: ='0. Database'!E63 -> 3669 | E26: ='0. Database'!F63 -> 10187.2 | F26: ='0. Database'!G63 -> 15919 | G26: ='0. Database'!H63 -> 22112 | H26: ='0. Database'!I63 -> 18484.5 | I26: ='0. Database'!J63 -> 29145 | ... T26: ='0. Database'!U63 -> 143941.83
A27: ORCL | B27: ='0. Database'!C82 -> 10926 | C27: ='0. Database'!D82 -> 10955 | D27: ='0. Database'!E82 -> 9938 | E27: ='0. Database'!F82 -> 8900 | F27: ='0. Database'!G82 -> 9334 | G27: ='0. Database'!H82 -> 3587 | H27: ='0. Database'!I82 -> 11083 | I27: ='0. Database'!J82 -> 10135 | ... T27: ='0. Database'!U82 -> 0
A30: D. EPS ($)
A31: Company | B31: 2013A | C31: 2014A | D31: 2015A | E31: 2016A | F31: 2017A | G31: 2018A | H31: 2019A | I31: 2020A | J31: 2021A | K31: 2022A | L31: 2023A | M31: 2024A | N31: 2025E | O31: 2026E | P31: 2027E | Q31: 2028E | R31: 2029E | S31: 2030E | T31: 2031E
A32: MSFT | B32: ='0. Database'!C9 -> 2.63 | C32: ='0. Database'!D9 -> 2.66 | D32: ='0. Database'!E9 -> 2.59 | E32: ='0. Database'!F9 -> 2.79 | F32: ='0. Database'!G9 -> 3.29 | G32: ='0. Database'!H9 -> 3.88 | H32: ='0. Database'!I9 -> 4.75 | I32: ='0. Database'!J9 -> 5.76 | ... T32: ='0. Database'!U9 -> 0
A33: AMZN | B33: ='0. Database'!C28 -> 0.03 | C33: ='0. Database'!D28 -> -0.03 | D33: ='0. Database'!E28 -> 0.06 | E33: ='0. Database'!F28 -> 0.24 | F33: ='0. Database'!G28 -> 0.31 | G33: ='0. Database'!H28 -> 1.01 | H33: ='0. Database'!I28 -> 1.15 | I33: ='0. Database'!J28 -> 2.08 | ... T33: ='0. Database'!U28 -> 21.97
A34: GOOGL | B34: ='0. Database'!C45 -> 0.94 | C34: ='0. Database'!D45 -> 1.03 | D34: ='0. Database'!E45 -> 1.18 | E34: ='0. Database'!F45 -> 1.39 | F34: ='0. Database'!G45 -> 0.9 | G34: ='0. Database'!H45 -> 2.19 | H34: ='0. Database'!I45 -> 2.46 | I34: ='0. Database'!J45 -> 2.93 | ... T34: ='0. Database'!U45 -> 26.09
A35: META | B35: ='0. Database'!C64 -> 0.59 | C35: ='0. Database'!D64 -> 1.1 | D35: ='0. Database'!E64 -> 1.28 | E35: ='0. Database'!F64 -> 3.48 | F35: ='0. Database'!G64 -> 5.39 | G35: ='0. Database'!H64 -> 7.66 | H35: ='0. Database'!I64 -> 6.44 | I35: ='0. Database'!J64 -> 10.08 | ... T35: ='0. Database'!U64 -> 52.96
A36: ORCL | B36: ='0. Database'!C83 -> 2.26 | C36: ='0. Database'!D83 -> 2.38 | D36: ='0. Database'!E83 -> 2.21 | E36: ='0. Database'!F83 -> 2.07 | F36: ='0. Database'!G83 -> 2.21 | G36: ='0. Database'!H83 -> 0.85 | H36: ='0. Database'!I83 -> 2.97 | I36: ='0. Database'!J83 -> 3.08 | ... T36: ='0. Database'!U83 -> 0
A39: E. EPS YoY %
A40: Company | B40: 2013A | C40: 2014A | D40: 2015A | E40: 2016A | F40: 2017A | G40: 2018A | H40: 2019A | I40: 2020A | J40: 2021A | K40: 2022A | L40: 2023A | M40: 2024A | N40: 2025E | O40: 2026E | P40: 2027E | Q40: 2028E | R40: 2029E | S40: 2030E | T40: 2031E
A41: MSFT | C41: =IFERROR('0. Database'!D9/'0. Database'!C9-1,"") -> 0.011406844 | D41: =IFERROR('0. Database'!E9/'0. Database'!D9-1,"") -> -0.026315789 | E41: =IFERROR('0. Database'!F9/'0. Database'!E9-1,"") -> 0.077220077 | F41: =IFERROR('0. Database'!G9/'0. Database'!F9-1,"") -> 0.17921147 | G41: =IFERROR('0. Database'!H9/'0. Database'!G9-1,"") -> 0.17933131 | H41: =IFERROR('0. Database'!I9/'0. Database'!H9-1,"") -> 0.2242268 | I41: =IFERROR('0. Database'!J9/'0. Database'!I9-1,"") -> 0.21263158 | J41: =IFERROR('0. Database'!K9/'0. Database'!J9-1,"") -> 0.38368056 | ... T41: =IFERROR('0. Database'!U9/'0. Database'!T9-1,"") -> -1
A42: AMZN | C42: =IFERROR('0. Database'!D28/'0. Database'!C28-1,"") -> -2 | D42: =IFERROR('0. Database'!E28/'0. Database'!D28-1,"") -> -3 | E42: =IFERROR('0. Database'!F28/'0. Database'!E28-1,"") -> 3 | F42: =IFERROR('0. Database'!G28/'0. Database'!F28-1,"") -> 0.29166667 | G42: =IFERROR('0. Database'!H28/'0. Database'!G28-1,"") -> 2.2580645 | H42: =IFERROR('0. Database'!I28/'0. Database'!H28-1,"") -> 0.13861386 | I42: =IFERROR('0. Database'!J28/'0. Database'!I28-1,"") -> 0.80869565 | J42: =IFERROR('0. Database'!K28/'0. Database'!J28-1,"") -> 0.5625 | ... T42: =IFERROR('0. Database'!U28/'0. Database'!T28-1,"") -> 0.16120507
A43: GOOGL | C43: =IFERROR('0. Database'!D45/'0. Database'!C45-1,"") -> 0.095744681 | D43: =IFERROR('0. Database'!E45/'0. Database'!D45-1,"") -> 0.14563107 | E43: =IFERROR('0. Database'!F45/'0. Database'!E45-1,"") -> 0.1779661 | F43: =IFERROR('0. Database'!G45/'0. Database'!F45-1,"") -> -0.35251799 | G43: =IFERROR('0. Database'!H45/'0. Database'!G45-1,"") -> 1.4333333 | H43: =IFERROR('0. Database'!I45/'0. Database'!H45-1,"") -> 0.12328767 | I43: =IFERROR('0. Database'!J45/'0. Database'!I45-1,"") -> 0.19105691 | J43: =IFERROR('0. Database'!K45/'0. Database'!J45-1,"") -> 0.91467577 | ... T43: =IFERROR('0. Database'!U45/'0. Database'!T45-1,"") -> 0.13484124
A44: META | C44: =IFERROR('0. Database'!D64/'0. Database'!C64-1,"") -> 0.86440678 | D44: =IFERROR('0. Database'!E64/'0. Database'!D64-1,"") -> 0.16363636 | E44: =IFERROR('0. Database'!F64/'0. Database'!E64-1,"") -> 1.71875 | F44: =IFERROR('0. Database'!G64/'0. Database'!F64-1,"") -> 0.54885057 | G44: =IFERROR('0. Database'!H64/'0. Database'!G64-1,"") -> 0.42115028 | H44: =IFERROR('0. Database'!I64/'0. Database'!H64-1,"") -> -0.15926893 | I44: =IFERROR('0. Database'!J64/'0. Database'!I64-1,"") -> 0.56521739 | J44: =IFERROR('0. Database'!K64/'0. Database'!J64-1,"") -> 0.39583333 | ... T44: =IFERROR('0. Database'!U64/'0. Database'!T64-1,"") -> 0.11447811
A45: ORCL | C45: =IFERROR('0. Database'!D83/'0. Database'!C83-1,"") -> 0.053097345 | D45: =IFERROR('0. Database'!E83/'0. Database'!D83-1,"") -> -0.071428571 | E45: =IFERROR('0. Database'!F83/'0. Database'!E83-1,"") -> -0.063348416 | F45: =IFERROR('0. Database'!G83/'0. Database'!F83-1,"") -> 0.06763285 | G45: =IFERROR('0. Database'!H83/'0. Database'!G83-1,"") -> -0.61538462 | H45: =IFERROR('0. Database'!I83/'0. Database'!H83-1,"") -> 2.4941176 | I45: =IFERROR('0. Database'!J83/'0. Database'!I83-1,"") -> 0.037037037 | J45: =IFERROR('0. Database'!K83/'0. Database'!J83-1,"") -> 0.47727273 | ... T45: =IFERROR('0. Database'!U83/'0. Database'!T83-1,"") -> -1
A48: F. Diluted Shares (mm)
A49: Company | B49: 2013A | C49: 2014A | D49: 2015A | E49: 2016A | F49: 2017A | G49: 2018A | H49: 2019A | I49: 2020A | J49: 2021A | K49: 2022A | L49: 2023A | M49: 2024A | N49: 2025E | O49: 2026E | P49: 2027E | Q49: 2028E | R49: 2029E | S49: 2030E | T49: 2031E
A50: MSFT | B50: ='0. Database'!C10 -> 8452.25 | C50: ='0. Database'!D10 -> 8385.25 | D50: ='0. Database'!E10 -> 8254 | E50: ='0. Database'!F10 -> 8012.25 | F50: ='0. Database'!G10 -> 7831.25 | G50: ='0. Database'!H10 -> 7792.25 | H50: ='0. Database'!I10 -> 7752 | I50: ='0. Database'!J10 -> 7681.5 | ... T50: ='0. Database'!U10 -> 0
A51: AMZN | B51: ='0. Database'!C29 -> 9340 | C51: ='0. Database'!D29 -> 9440 | D51: ='0. Database'!E29 -> 9620 | E51: ='0. Database'!F29 -> 9720 | F51: ='0. Database'!G29 -> 9910 | G51: ='0. Database'!H29 -> 10020 | H51: ='0. Database'!I29 -> 10100 | I51: ='0. Database'!J29 -> 10254 | ... T51: ='0. Database'!U29 -> 11270.24
A52: GOOGL | B52: ='0. Database'!C46 -> 13552.38 | C52: ='0. Database'!D46 -> 13741.41 | D52: ='0. Database'!E46 -> 13858.6 | E52: ='0. Database'!F46 -> 13974.09 | F52: ='0. Database'!G46 -> 14071.67 | G52: ='0. Database'!H46 -> 14065.69 | H52: ='0. Database'!I46 -> 13971.13 | I52: ='0. Database'!J46 -> 13740.56 | ... T52: ='0. Database'!U46 -> 12506.36
A53: META | B53: ='0. Database'!C65 -> 2521.75 | C53: ='0. Database'!D65 -> 2671 | D53: ='0. Database'!E65 -> 2856.75 | E53: ='0. Database'!F65 -> 2923.75 | F53: ='0. Database'!G65 -> 2954 | G53: ='0. Database'!H65 -> 2886 | H53: ='0. Database'!I65 -> 2871 | I53: ='0. Database'!J65 -> 2890 | ... T53: ='0. Database'!U65 -> 2718.12
A54: ORCL | B54: ='0. Database'!C85 -> 4843.75 | C54: ='0. Database'!D85 -> 4604.5 | D54: ='0. Database'!E85 -> 4502.5 | E54: ='0. Database'!F85 -> 4305.5 | F54: ='0. Database'!G85 -> 4217 | G54: ='0. Database'!H85 -> 4238 | H54: ='0. Database'!I85 -> 3732 | I54: ='0. Database'!J85 -> 3293.5 | ... T54: ='0. Database'!U85 -> 0
A57: G. SBC ($mm)
A58: Company | B58: 2013A | C58: 2014A | D58: 2015A | E58: 2016A | F58: 2017A | G58: 2018A | H58: 2019A | I58: 2020A | J58: 2021A | K58: 2022A | L58: 2023A | M58: 2024A | N58: 2025E | O58: 2026E | P58: 2027E | Q58: 2028E | R58: 2029E | S58: 2030E | T58: 2031E
A59: MSFT | B59: ='0. Database'!C11 -> 2406 | C59: ='0. Database'!D11 -> 2446 | D59: ='0. Database'!E11 -> 2574 | E59: ='0. Database'!F11 -> 2668 | F59: ='0. Database'!G11 -> 3266 | G59: ='0. Database'!H11 -> 3940 | H59: ='0. Database'!I11 -> 4652 | I59: ='0. Database'!J11 -> 5289 | ... T59: ='0. Database'!U11 -> 0
A60: AMZN | B60: ='0. Database'!C30 -> -1134 | C60: ='0. Database'!D30 -> -1497 | D60: ='0. Database'!E30 -> -2120 | E60: ='0. Database'!F30 -> -2975 | F60: ='0. Database'!G30 -> -4214 | G60: ='0. Database'!H30 -> -5418 | H60: ='0. Database'!I30 -> -6864 | I60: ='0. Database'!J30 -> -9208 | ... T60: ='0. Database'!U30 -> -21782.06
A61: GOOGL | B61: ='0. Database'!C47 -> -3268 | C61: ='0. Database'!D47 -> -4175 | D61: ='0. Database'!E47 -> -4903 | E61: ='0. Database'!F47 -> -6703 | F61: ='0. Database'!G47 -> -7679 | G61: ='0. Database'!H47 -> -9353 | H61: ='0. Database'!I47 -> -10794 | I61: ='0. Database'!J47 -> -12991 | ... T61: ='0. Database'!U47 -> -37106.95
A62: META | B62: ='0. Database'!C66 -> -906 | C62: ='0. Database'!D66 -> -1837 | D62: ='0. Database'!E66 -> -2969 | E62: ='0. Database'!F66 -> -3202 | F62: ='0. Database'!G66 -> -3723 | G62: ='0. Database'!H66 -> -4152 | H62: ='0. Database'!I66 -> -4835 | I62: ='0. Database'!J66 -> -6536 | ... T62: ='0. Database'!U66 -> -30276.21
A63: ORCL | B63: ='0. Database'!C86 -> 755 | C63: ='0. Database'!D86 -> 805 | D63: ='0. Database'!E86 -> 933 | E63: ='0. Database'!F86 -> 1037 | F63: ='0. Database'!G86 -> 1350 | G63: ='0. Database'!H86 -> 1607 | H63: ='0. Database'!I86 -> 1653 | I63: ='0. Database'!J86 -> 1590 | ... T63: ='0. Database'!U86 -> 0

Sheet 6. Burry Sensitivity
A1: Burry Bear Case — GPU Useful Life Compression (2026E EPS)
A3: THESIS: 5-6yr accounting life vs ~3yr economic life. If compressed, D&A accelerates → EPS declines. Yellow tax cells are editable.
A6: MSFT Tax | C6: AMZN Tax | E6: GOOGL Tax | G6: META Tax | I6: ORCL Tax
A7: 0.18 | C7: 0.2 | E7: 0.16 | G7: 0.13 | I7: 0.2
A9: Company | B9: Base EPS | C9: NI | D9: D&A | E9: Tax | F9: +50% Extra | G9: +50% Hit | H9: +50% Adj EPS | I9: +50% Impact | J9: +100% Extra | K9: +100% Hit | L9: +100% Adj EPS | M9: +100% Impact | N9: Rating
A10: MSFT | B10: ='0. Database'!P9 -> 16.75 | C10: ='0. Database'!P8 -> 129372.86 | D10: ='0. Database'!P12 -> 39638.96 | E10: =$A$7 -> 0.18 | F10: =0.5*'0. Database'!P12 -> 19819.48 | G10: =$F$10*(1-$A$7) -> 16251.974 | H10: =('0. Database'!P8-$G$10)/'0. Database'!P10 -> 15.175925 | I10: =$H$10/'0. Database'!P9-1 -> -0.093974653 | J10: =1*'0. Database'!P12 -> 39638.96 | K10: =$J$10*(1-$A$7) -> 32503.947 | L10: =('0. Database'!P8-$K$10)/'0. Database'!P10 -> 12.995613 | M10: =$L$10/'0. Database'!P9-1 -> -0.22414248 | N10: =IF($M$10<-0.5,"EXTREME",IF($M$10<-0.3,"HIGH",IF($M$10<-0.2,"MEDIUM","LOW"))) -> MEDIUM
A11: AMZN | B11: ='0. Database'!P28 -> 9.02 | C11: ='0. Database'!P27 -> 98333.72 | D11: ='0. Database'!P31 -> 81175.82 | E11: =$C$7 -> 0.2 | F11: =0.5*'0. Database'!P31 -> 40587.91 | G11: =$F$11*(1-$C$7) -> 32470.328 | H11: =('0. Database'!P27-$G$11)/'0. Database'!P29 -> 6.0383305 | I11: =$H$11/'0. Database'!P28-1 -> -0.33056203 | J11: =1*'0. Database'!P31 -> 81175.82 | K11: =$J$11*(1-$C$7) -> 64940.656 | L11: =('0. Database'!P27-$K$11)/'0. Database'!P29 -> 3.0614633 | M11: =$L$11/'0. Database'!P28-1 -> -0.66059165 | N11: =IF($M$11<-0.5,"EXTREME",IF($M$11<-0.3,"HIGH",IF($M$11<-0.2,"MEDIUM","LOW"))) -> EXTREME
A12: GOOGL | B12: ='0. Database'!P45 -> 13.73 | C12: ='0. Database'!P44 -> 168543.28 | D12: ='0. Database'!P48 -> 42874.7 | E12: =$E$7 -> 0.16 | F12: =0.5*'0. Database'!P48 -> 21437.35 | G12: =$F$12*(1-$E$7) -> 18007.374 | H12: =('0. Database'!P44-$G$12)/'0. Database'!P46 -> 12.262659 | I12: =$H$12/'0. Database'!P45-1 -> -0.10687119 | J12: =1*'0. Database'!P48 -> 42874.7 | K12: =$J$12*(1-$E$7) -> 36014.748 | L12: =('0. Database'!P44-$K$12)/'0. Database'!P46 -> 10.795777 | M12: =$L$12/'0. Database'!P45-1 -> -0.21370885 | N12: =IF($M$12<-0.5,"EXTREME",IF($M$12<-0.3,"HIGH",IF($M$12<-0.2,"MEDIUM","LOW"))) -> MEDIUM
A13: META | B13: ='0. Database'!P64 -> 33.28 | C13: ='0. Database'!P63 -> 85782.86 | D13: ='0. Database'!P67 -> 35955.99 | E13: =$G$7 -> 0.13 | F13: =0.5*'0. Database'!P67 -> 17977.995 | G13: =$F$13*(1-$G$7) -> 15640.856 | H13: =('0. Database'!P63-$G$13)/'0. Database'!P65 -> 27.210131 | I13: =$H$13/'0. Database'!P64-1 -> -0.18238788 | J13: =1*'0. Database'!P67 -> 35955.99 | K13: =$J$13*(1-$G$7) -> 31281.711 | L13: =('0. Database'!P63-$K$13)/'0. Database'!P65 -> 21.142587 | M13: =$L$13/'0. Database'!P64-1 -> -0.36470593 | N13: =IF($M$13<-0.5,"EXTREME",IF($M$13<-0.3,"HIGH",IF($M$13<-0.2,"MEDIUM","LOW"))) -> HIGH
A14: ORCL | B14: ='0. Database'!P83 -> 5.43 | C14: ='0. Database'!P82 -> 15820.55 | D14: ='0. Database'!P87 -> 7501.53 | E14: =$I$7 -> 0.2 | F14: =0.5*'0. Database'!P87 -> 3750.765 | G14: =$F$14*(1-$I$7) -> 3000.612 | H14: =('0. Database'!P82-$G$14)/'0. Database'!P85 -> 4.3967741 | I14: =$H$14/'0. Database'!P83-1 -> -0.19028102 | J14: =1*'0. Database'!P87 -> 7501.53 | K14: =$J$14*(1-$I$7) -> 6001.224 | L14: =('0. Database'!P82-$K$14)/'0. Database'!P85 -> 3.3676729 | M14: =$L$14/'0. Database'!P83-1 -> -0.37980241 | N14: =IF($M$14<-0.5,"EXTREME",IF($M$14<-0.3,"HIGH",IF($M$14<-0.2,"MEDIUM","LOW"))) -> HIGH

Sheet 7. Cross-Company
A1: Cross-Company Comparison: 2024A / 2025E / 2026E
B3: MSFT | E3: AMZN | H3: GOOGL | K3: META | N3: ORCL
A4: Metric | B4: 2024A | C4: 2025E | D4: 2026E | E4: 2024A | F4: 2025E | G4: 2026E | H4: 2024A | I4: 2025E | J4: 2026E | K4: 2024A | L4: 2025E | M4: 2026E | N4: 2024A | O4: 2025E | P4: 2026E
A5: Revenue ($mm) | B5: ='0. Database'!N6 -> 245122 | C5: ='0. Database'!O6 -> 281724 | D5: ='0. Database'!P6 -> 329440.24 | E5: ='0. Database'!N25 -> 637959 | F5: ='0. Database'!O25 -> 716924 | G5: ='0. Database'!P25 -> 827599.51 | H5: ='0. Database'!N42 -> 350018 | I5: ='0. Database'!O42 -> 402836 | J5: ='0. Database'!P42 -> 488278.6 | K5: ='0. Database'!N61 -> 164500 | L5: ='0. Database'!O61 -> 200965 | M5: ='0. Database'!P61 -> 255175.56 | N5: ='0. Database'!N79 -> 52961 | O5: ='0. Database'!O79 -> 57399 | P5: ='0. Database'!P79 -> 67286.75
A6: Rev YoY % | B6: =IFERROR('0. Database'!N6/'0. Database'!M6-1,"") -> 0.15669962 | C6: =IFERROR('0. Database'!O6/'0. Database'!N6-1,"") -> 0.14932156 | D6: =IFERROR('0. Database'!P6/'0. Database'!O6-1,"") -> 0.16937229 | E6: =IFERROR('0. Database'!N25/'0. Database'!M25-1,"") -> 0.10990892 | F6: =IFERROR('0. Database'!O25/'0. Database'!N25-1,"") -> 0.12377755 | G6: =IFERROR('0. Database'!P25/'0. Database'!O25-1,"") -> 0.15437551 | H6: =IFERROR('0. Database'!N42/'0. Database'!M42-1,"") -> 0.13866243 | I6: =IFERROR('0. Database'!O42/'0. Database'!N42-1,"") -> 0.15090081 | J6: =IFERROR('0. Database'!P42/'0. Database'!O42-1,"") -> 0.21210269 | K6: =IFERROR('0. Database'!N61/'0. Database'!M61-1,"") -> 0.21941275 | L6: =IFERROR('0. Database'!O61/'0. Database'!N61-1,"") -> 0.22167173 | M6: =IFERROR('0. Database'!P61/'0. Database'!O61-1,"") -> 0.26975125 | N6: =IFERROR('0. Database'!N79/'0. Database'!M79-1,"") -> 0.060174157 | O6: =IFERROR('0. Database'!O79/'0. Database'!N79-1,"") -> 0.083797511 | P6: =IFERROR('0. Database'!P79/'0. Database'!O79-1,"") -> 0.17226345
A7: OpInc ($mm) | B7: ='0. Database'!N7 -> 109433 | C7: ='0. Database'!O7 -> 128528 | D7: ='0. Database'!P7 -> 153454.1 | E7: ='0. Database'!N26 -> 68593 | F7: ='0. Database'!O26 -> 79975 | G7: ='0. Database'!P26 -> 109001.86 | H7: ='0. Database'!N43 -> 112390 | I7: ='0. Database'!O43 -> 129039 | J7: ='0. Database'!P43 -> 167318.21 | K7: ='0. Database'!N62 -> 69380 | L7: ='0. Database'!O62 -> 83276 | M7: ='0. Database'!P62 -> 90489.79 | N7: ='0. Database'!N80 -> 15354 | O7: ='0. Database'!O80 -> 17678 | P7: ='0. Database'!P80 -> 19462.44
A8: OpMargin % | B8: =IFERROR('0. Database'!N7/'0. Database'!N6,"") -> 0.446443 | C8: =IFERROR('0. Database'!O7/'0. Database'!O6,"") -> 0.45621956 | D8: =IFERROR('0. Database'!P7/'0. Database'!P6,"") -> 0.46580254 | E8: =IFERROR('0. Database'!N26/'0. Database'!N25,"") -> 0.10751945 | F8: =IFERROR('0. Database'!O26/'0. Database'!O25,"") -> 0.11155297 | G8: =IFERROR('0. Database'!P26/'0. Database'!P25,"") -> 0.13170846 | H8: =IFERROR('0. Database'!N43/'0. Database'!N42,"") -> 0.32109777 | I8: =IFERROR('0. Database'!O43/'0. Database'!O42,"") -> 0.32032639 | J8: =IFERROR('0. Database'!P43/'0. Database'!P42,"") -> 0.34266955 | K8: =IFERROR('0. Database'!N62/'0. Database'!N61,"") -> 0.42176292 | L8: =IFERROR('0. Database'!O62/'0. Database'!O61,"") -> 0.41438061 | M8: =IFERROR('0. Database'!P62/'0. Database'!P61,"") -> 0.35461778 | N8: =IFERROR('0. Database'!N80/'0. Database'!N79,"") -> 0.28991144 | O8: =IFERROR('0. Database'!O80/'0. Database'!O79,"") -> 0.30798446 | P8: =IFERROR('0. Database'!P80/'0. Database'!P79,"") -> 0.28924625
A9: NI ($mm) | B9: ='0. Database'!N8 -> 88136 | C9: ='0. Database'!O8 -> 101832 | D9: ='0. Database'!P8 -> 129372.86 | E9: ='0. Database'!N27 -> 59248 | F9: ='0. Database'!O27 -> 77670 | G9: ='0. Database'!P27 -> 98333.72 | H9: ='0. Database'!N44 -> 100118 | I9: ='0. Database'!O44 -> 132170 | J9: ='0. Database'!P44 -> 168543.28 | K9: ='0. Database'!N63 -> 62360 | L9: ='0. Database'!O63 -> 60458 | M9: ='0. Database'!P63 -> 85782.86 | N9: ='0. Database'!N82 -> 10467 | O9: ='0. Database'!O82 -> 12443 | P9: ='0. Database'!P82 -> 15820.55
A10: EPS | B10: ='0. Database'!N9 -> 11.8 | C10: ='0. Database'!O9 -> 13.91 | D10: ='0. Database'!P9 -> 16.75 | E10: ='0. Database'!N28 -> 5.53 | F10: ='0. Database'!O28 -> 7.17 | G10: ='0. Database'!P28 -> 9.02 | H10: ='0. Database'!N45 -> 8.04 | I10: ='0. Database'!O45 -> 10.81 | J10: ='0. Database'!P45 -> 13.73 | K10: ='0. Database'!N64 -> 23.99 | L10: ='0. Database'!O64 -> 23.49 | M10: ='0. Database'!P64 -> 33.28 | N10: ='0. Database'!N83 -> 3.71 | O10: ='0. Database'!O83 -> 4.34 | P10: ='0. Database'!P83 -> 5.43
A11: EPS YoY % | B11: =IFERROR('0. Database'!N9/'0. Database'!M9-1,"") -> 0.20285423 | C11: =IFERROR('0. Database'!O9/'0. Database'!N9-1,"") -> 0.17881356 | D11: =IFERROR('0. Database'!P9/'0. Database'!O9-1,"") -> 0.20416966 | E11: =IFERROR('0. Database'!N28/'0. Database'!M28-1,"") -> 0.92013889 | F11: =IFERROR('0. Database'!O28/'0. Database'!N28-1,"") -> 0.2965642 | G11: =IFERROR('0. Database'!P28/'0. Database'!O28-1,"") -> 0.25801953 | H11: =IFERROR('0. Database'!N45/'0. Database'!M45-1,"") -> 0.3862069 | I11: =IFERROR('0. Database'!O45/'0. Database'!N45-1,"") -> 0.34452736 | J11: =IFERROR('0. Database'!P45/'0. Database'!O45-1,"") -> 0.27012026 | K11: =IFERROR('0. Database'!N64/'0. Database'!M64-1,"") -> 0.6133154 | L11: =IFERROR('0. Database'!O64/'0. Database'!N64-1,"") -> -0.020842018 | M11: =IFERROR('0. Database'!P64/'0. Database'!O64-1,"") -> 0.41677309 | N11: =IFERROR('0. Database'!N83/'0. Database'!M83-1,"") -> 0.20846906 | O11: =IFERROR('0. Database'!O83/'0. Database'!N83-1,"") -> 0.16981132 | P11: =IFERROR('0. Database'!P83/'0. Database'!O83-1,"") -> 0.25115207
A12: Capex ($mm) | B12: ='0. Database'!N13 -> 55700 | C12: ='0. Database'!O13 -> 88200 | D12: ='0. Database'!P13 -> 145871.3 | E12: ='0. Database'!N32 -> 77658 | F12: ='0. Database'!O32 -> 128320 | G12: ='0. Database'!P32 -> 200104.98 | H12: ='0. Database'!N49 -> 52535 | I12: ='0. Database'!O49 -> 91447 | J12: ='0. Database'!P49 -> 185234.28 | K12: ='0. Database'!N68 -> 37256 | L12: ='0. Database'!O68 -> 69691 | M12: ='0. Database'!P68 -> 135583.71 | N12: ='0. Database'!N88 -> 6866 | O12: ='0. Database'!O88 -> 21215 | P12: ='0. Database'!P88 -> 51882
A13: Capex/Rev % | B13: =IFERROR('0. Database'!N13/'0. Database'!N6,"") -> 0.22723379 | C13: =IFERROR('0. Database'!O13/'0. Database'!O6,"") -> 0.31307237 | D13: =IFERROR('0. Database'!P13/'0. Database'!P6,"") -> 0.44278531 | E13: =IFERROR('0. Database'!N32/'0. Database'!N25,"") -> 0.12172883 | F13: =IFERROR('0. Database'!O32/'0. Database'!O25,"") -> 0.17898689 | G13: =IFERROR('0. Database'!P32/'0. Database'!P25,"") -> 0.24178963 | H13: =IFERROR('0. Database'!N49/'0. Database'!N42,"") -> 0.15009228 | I13: =IFERROR('0. Database'!O49/'0. Database'!O42,"") -> 0.22700801 | J13: =IFERROR('0. Database'!P49/'0. Database'!P42,"") -> 0.37936186 | K13: =IFERROR('0. Database'!N68/'0. Database'!N61,"") -> 0.22648024 | L13: =IFERROR('0. Database'!O68/'0. Database'!O61,"") -> 0.34678178 | M13: =IFERROR('0. Database'!P68/'0. Database'!P61,"") -> 0.53133501 | N13: =IFERROR('0. Database'!N88/'0. Database'!N79,"") -> 0.12964257 | O13: =IFERROR('0. Database'!O88/'0. Database'!O79,"") -> 0.36960574 | P13: =IFERROR('0. Database'!P88/'0. Database'!P79,"") -> 0.77105819
A14: D&A ($mm) | B14: ='0. Database'!N12 -> 20000 | C14: ='0. Database'!O12 -> 28000 | D14: ='0. Database'!P12 -> 39638.96 | E14: ='0. Database'!N31 -> 52795 | F14: ='0. Database'!O31 -> 65756 | G14: ='0. Database'!P31 -> 81175.82 | H14: ='0. Database'!N48 -> 15311 | I14: ='0. Database'!O48 -> 21136 | J14: ='0. Database'!P48 -> 42874.7 | K14: ='0. Database'!N67 -> 15498 | L14: ='0. Database'!O67 -> 18616 | M14: ='0. Database'!P67 -> 35955.99 | N14: ='0. Database'!N87 -> 3129 | O14: ='0. Database'!O87 -> 3867 | P14: ='0. Database'!P87 -> 7501.53
A15: D&A/Rev % | B15: =IFERROR('0. Database'!N12/'0. Database'!N6,"") -> 0.081592024 | C15: =IFERROR('0. Database'!O12/'0. Database'!O6,"") -> 0.099388054 | D15: =IFERROR('0. Database'!P12/'0. Database'!P6,"") -> 0.12032216 | E15: =IFERROR('0. Database'!N31/'0. Database'!N25,"") -> 0.082756102 | F15: =IFERROR('0. Database'!O31/'0. Database'!O25,"") -> 0.091719624 | G15: =IFERROR('0. Database'!P31/'0. Database'!P25,"") -> 0.098085872 | H15: =IFERROR('0. Database'!N48/'0. Database'!N42,"") -> 0.043743465 | I15: =IFERROR('0. Database'!O48/'0. Database'!O42,"") -> 0.052468002 | J15: =IFERROR('0. Database'!P48/'0. Database'!P42,"") -> 0.087807862 | K15: =IFERROR('0. Database'!N67/'0. Database'!N61,"") -> 0.094212766 | L15: =IFERROR('0. Database'!O67/'0. Database'!O61,"") -> 0.092633046 | M15: =IFERROR('0. Database'!P67/'0. Database'!P61,"") -> 0.14090687 | N15: =IFERROR('0. Database'!N87/'0. Database'!N79,"") -> 0.059081211 | O15: =IFERROR('0. Database'!O87/'0. Database'!O79,"") -> 0.067370512 | P15: =IFERROR('0. Database'!P87/'0. Database'!P79,"") -> 0.11148599
A16: CFO ($mm) | B16: ='0. Database'!N16 -> 118548 | C16: ='0. Database'!O16 -> 136162 | D16: ='0. Database'!P16 -> 174558.18 | E16: ='0. Database'!N33 -> 115877 | F16: ='0. Database'!O33 -> 139514 | G16: ='0. Database'!P33 -> 181004.31 | H16: ='0. Database'!N50 -> 125299 | I16: ='0. Database'!O50 -> 164713 | J16: ='0. Database'!P50 -> 211985.47 | K16: ='0. Database'!N69 -> 91328 | L16: ='0. Database'!O69 -> 115800 | M16: ='0. Database'!P69 -> 180250.64 | N16: ='0. Database'!N89 -> 18673 | O16: ='0. Database'!O89 -> 20821 | P16: ='0. Database'!P89 -> 25457.17
A17: FCF ($mm) | B17: ='0. Database'!N17 -> 62848 | C17: ='0. Database'!O17 -> 47962 | D17: ='0. Database'!P17 -> 28686.88 | E17: ='0. Database'!N34 -> 38219 | F17: ='0. Database'!O34 -> 11194 | G17: ='0. Database'!P34 -> -19100.67 | H17: ='0. Database'!N51 -> 72764 | I17: ='0. Database'!O51 -> 73266 | J17: ='0. Database'!P51 -> 26751.19 | K17: ='0. Database'!N70 -> 54072 | L17: ='0. Database'!O70 -> 46109 | M17: ='0. Database'!P70 -> 44666.93 | N17: ='0. Database'!N90 -> 11807 | O17: ='0. Database'!O90 -> -394 | P17: ='0. Database'!P90 -> -26424.83
A18: FCF Margin % | B18: =IFERROR('0. Database'!N17/'0. Database'!N6,"") -> 0.25639477 | C18: =IFERROR('0. Database'!O17/'0. Database'!O6,"") -> 0.17024464 | D18: =IFERROR('0. Database'!P17/'0. Database'!P6,"") -> 0.087077644 | E18: =IFERROR('0. Database'!N34/'0. Database'!N25,"") -> 0.059908239 | F18: =IFERROR('0. Database'!O34/'0. Database'!O25,"") -> 0.015613928 | G18: =IFERROR('0. Database'!P34/'0. Database'!P25,"") -> -0.023079605 | H18: =IFERROR('0. Database'!N51/'0. Database'!N42,"") -> 0.20788645 | I18: =IFERROR('0. Database'!O51/'0. Database'!O42,"") -> 0.1818755 | J18: =IFERROR('0. Database'!P51/'0. Database'!P42,"") -> 0.054786734 | K18: =IFERROR('0. Database'!N70/'0. Database'!N61,"") -> 0.32870517 | L18: =IFERROR('0. Database'!O70/'0. Database'!O61,"") -> 0.22943796 | M18: =IFERROR('0. Database'!P70/'0. Database'!P61,"") -> 0.17504392 | N18: =IFERROR('0. Database'!N90/'0. Database'!N79,"") -> 0.22293763 | O18: =IFERROR('0. Database'!O90/'0. Database'!O79,"") -> -0.0068642311 | P18: =IFERROR('0. Database'!P90/'0. Database'!P79,"") -> -0.39271967
A19: Buybacks | B19: ='0. Database'!N18 -> 17254 | C19: ='0. Database'!O18 -> 18420 | D19: ='0. Database'!P18 -> 22499.7 | E19: ='0. Database'!N35 -> 0 | F19: ='0. Database'!O35 -> 0 | G19: ='0. Database'!P35 -> 0 | H19: ='0. Database'!N52 -> 62222 | I19: ='0. Database'!O52 -> 45709 | J19: ='0. Database'!P52 -> 0 | K19: ='0. Database'!N71 -> 30125 | L19: ='0. Database'!O71 -> 26248 | M19: ='0. Database'!P71 -> 0 | N19: ='0. Database'!N91 -> 1202 | O19: ='0. Database'!O91 -> 600 | P19: ='0. Database'!P91 -> 95
A20: Shares (mm) | B20: ='0. Database'!N10 -> 7468.5 | C20: ='0. Database'!O10 -> 7467.75 | D20: ='0. Database'!P10 -> 7453.97 | E20: ='0. Database'!N29 -> 10721 | F20: ='0. Database'!O29 -> 10827 | G20: ='0. Database'!P29 -> 10907.55 | H20: ='0. Database'!N46 -> 12447 | I20: ='0. Database'!O46 -> 12230 | J20: ='0. Database'!P46 -> 12275.96 | K20: ='0. Database'!N65 -> 2599 | L20: ='0. Database'!O65 -> 2574 | M20: ='0. Database'!P65 -> 2577.79 | N20: ='0. Database'!N85 -> 2823.25 | O20: ='0. Database'!O85 -> 2866.25 | P20: ='0. Database'!P85 -> 2915.76

Sheet 8. Bubble Analysis
A1: Is the AI Capex a Bubble? When Might it Burst?
A3: A. Self-Funding: CFO - Capex Gap (formula-linked)
A4: Company / Metric | B4: 2020A | C4: 2021A | D4: 2022A | E4: 2023A | F4: 2024A | G4: 2025E | H4: 2026E | I4: 2027E | J4: 2028E
A5: MSFT CFO | B5: ='0. Database'!J16 -> 60675 | C5: ='0. Database'!K16 -> 76740 | D5: ='0. Database'!L16 -> 89035 | E5: ='0. Database'!M16 -> 87582 | F5: ='0. Database'!N16 -> 118548 | G5: ='0. Database'!O16 -> 136162 | H5: ='0. Database'!P16 -> 174558.18 | I5: ='0. Database'!Q16 -> 232097.78 | J5: ='0. Database'!R16 -> 294570.35
A6: MSFT Capex(-) | B6: =-'0. Database'!J13 -> -19000 | C6: =-'0. Database'!K13 -> -24200 | D6: =-'0. Database'!L13 -> -29200 | E6: =-'0. Database'!M13 -> -31900 | F6: =-'0. Database'!N13 -> -55700 | G6: =-'0. Database'!O13 -> -88200 | H6: =-'0. Database'!P13 -> -145871.3 | I6: =-'0. Database'!Q13 -> -245263.45 | J6: =-'0. Database'!R13 -> -286760.35
A7: MSFT GAP | B7: =IFERROR('0. Database'!J16-'0. Database'!J13,"") -> 41675 | C7: =IFERROR('0. Database'!K16-'0. Database'!K13,"") -> 52540 | D7: =IFERROR('0. Database'!L16-'0. Database'!L13,"") -> 59835 | E7: =IFERROR('0. Database'!M16-'0. Database'!M13,"") -> 55682 | F7: =IFERROR('0. Database'!N16-'0. Database'!N13,"") -> 62848 | G7: =IFERROR('0. Database'!O16-'0. Database'!O13,"") -> 47962 | H7: =IFERROR('0. Database'!P16-'0. Database'!P13,"") -> 28686.88 | I7: =IFERROR('0. Database'!Q16-'0. Database'!Q13,"") -> -13165.67 | J7: =IFERROR('0. Database'!R16-'0. Database'!R13,"") -> 7810
A8: MSFT Capex/CFO | B8: =IFERROR('0. Database'!J13/'0. Database'!J16,"") -> 0.3131438 | C8: =IFERROR('0. Database'!K13/'0. Database'!K16,"") -> 0.31535053 | D8: =IFERROR('0. Database'!L13/'0. Database'!L16,"") -> 0.32796091 | E8: =IFERROR('0. Database'!M13/'0. Database'!M16,"") -> 0.36423009 | F8: =IFERROR('0. Database'!N13/'0. Database'!N16,"") -> 0.46985187 | G8: =IFERROR('0. Database'!O13/'0. Database'!O16,"") -> 0.64775782 | H8: =IFERROR('0. Database'!P13/'0. Database'!P16,"") -> 0.83566006 | I8: =IFERROR('0. Database'!Q13/'0. Database'!Q16,"") -> 1.0567247 | J8: =IFERROR('0. Database'!R13/'0. Database'!R16,"") -> 0.97348681
A10: AMZN CFO | B10: ='0. Database'!J33 -> 66064 | C10: ='0. Database'!K33 -> 46327 | D10: ='0. Database'!L33 -> 46752 | E10: ='0. Database'!M33 -> 84946 | F10: ='0. Database'!N33 -> 115877 | G10: ='0. Database'!O33 -> 139514 | H10: ='0. Database'!P33 -> 181004.31 | I10: ='0. Database'!Q33 -> 224443.7 | J10: ='0. Database'!R33 -> 281471.71
A11: AMZN Capex(-) | B11: =-'0. Database'!J32 -> -35046 | C11: =-'0. Database'!K32 -> -55396 | D11: =-'0. Database'!L32 -> -58321 | E11: =-'0. Database'!M32 -> -48133 | F11: =-'0. Database'!N32 -> -77658 | G11: =-'0. Database'!O32 -> -128320 | H11: =-'0. Database'!P32 -> -200104.98 | I11: =-'0. Database'!Q32 -> -270141.72 | J11: =-'0. Database'!R32 -> -283648.81
A12: AMZN GAP | B12: =IFERROR('0. Database'!J33-'0. Database'!J32,"") -> 31018 | C12: =IFERROR('0. Database'!K33-'0. Database'!K32,"") -> -9069 | D12: =IFERROR('0. Database'!L33-'0. Database'!L32,"") -> -11569 | E12: =IFERROR('0. Database'!M33-'0. Database'!M32,"") -> 36813 | F12: =IFERROR('0. Database'!N33-'0. Database'!N32,"") -> 38219 | G12: =IFERROR('0. Database'!O33-'0. Database'!O32,"") -> 11194 | H12: =IFERROR('0. Database'!P33-'0. Database'!P32,"") -> -19100.67 | I12: =IFERROR('0. Database'!Q33-'0. Database'!Q32,"") -> -45698.02 | J12: =IFERROR('0. Database'!R33-'0. Database'!R32,"") -> -2177.1
A13: AMZN Capex/CFO | B13: =IFERROR('0. Database'!J32/'0. Database'!J33,"") -> 0.53048559 | C13: =IFERROR('0. Database'!K32/'0. Database'!K33,"") -> 1.1957606 | D13: =IFERROR('0. Database'!L32/'0. Database'!L33,"") -> 1.2474547 | E13: =IFERROR('0. Database'!M32/'0. Database'!M33,"") -> 0.56663057 | F13: =IFERROR('0. Database'!N32/'0. Database'!N33,"") -> 0.67017614 | G13: =IFERROR('0. Database'!O32/'0. Database'!O33,"") -> 0.91976432 | H13: =IFERROR('0. Database'!P32/'0. Database'!P33,"") -> 1.1055261 | I13: =IFERROR('0. Database'!Q32/'0. Database'!Q33,"") -> 1.2036057 | J13: =IFERROR('0. Database'!R32/'0. Database'!R33,"") -> 1.0077347
A15: GOOGL CFO | B15: ='0. Database'!J50 -> 65124 | C15: ='0. Database'!K50 -> 91652 | D15: ='0. Database'!L50 -> 91495 | E15: ='0. Database'!M50 -> 101746 | F15: ='0. Database'!N50 -> 125299 | G15: ='0. Database'!O50 -> 164713 | H15: ='0. Database'!P50 -> 211985.47 | I15: ='0. Database'!Q50 -> 282346.21 | J15: ='0. Database'!R50 -> 352943.8
A16: GOOGL Capex(-) | B16: =-'0. Database'!J49 -> -22281 | C16: =-'0. Database'!K49 -> -24640 | D16: =-'0. Database'!L49 -> -31485 | E16: =-'0. Database'!M49 -> -32251 | F16: =-'0. Database'!N49 -> -52535 | G16: =-'0. Database'!O49 -> -91447 | H16: =-'0. Database'!P49 -> -185234.28 | I16: =-'0. Database'!Q49 -> -259327.99 | J16: =-'0. Database'!R49 -> -285260.79
A17: GOOGL GAP | B17: =IFERROR('0. Database'!J50-'0. Database'!J49,"") -> 42843 | C17: =IFERROR('0. Database'!K50-'0. Database'!K49,"") -> 67012 | D17: =IFERROR('0. Database'!L50-'0. Database'!L49,"") -> 60010 | E17: =IFERROR('0. Database'!M50-'0. Database'!M49,"") -> 69495 | F17: =IFERROR('0. Database'!N50-'0. Database'!N49,"") -> 72764 | G17: =IFERROR('0. Database'!O50-'0. Database'!O49,"") -> 73266 | H17: =IFERROR('0. Database'!P50-'0. Database'!P49,"") -> 26751.19 | I17: =IFERROR('0. Database'!Q50-'0. Database'!Q49,"") -> 23018.22 | J17: =IFERROR('0. Database'!R50-'0. Database'!R49,"") -> 67683.01
A18: GOOGL Capex/CFO | B18: =IFERROR('0. Database'!J49/'0. Database'!J50,"") -> 0.34213193 | C18: =IFERROR('0. Database'!K49/'0. Database'!K50,"") -> 0.26884301 | D18: =IFERROR('0. Database'!L49/'0. Database'!L50,"") -> 0.34411716 | E18: =IFERROR('0. Database'!M49/'0. Database'!M50,"") -> 0.31697561 | F18: =IFERROR('0. Database'!N49/'0. Database'!N50,"") -> 0.41927709 | G18: =IFERROR('0. Database'!O49/'0. Database'!O50,"") -> 0.55518994 | H18: =IFERROR('0. Database'!P49/'0. Database'!P50,"") -> 0.87380649 | I18: =IFERROR('0. Database'!Q49/'0. Database'!Q50,"") -> 0.91847519 | J18: =IFERROR('0. Database'!R49/'0. Database'!R50,"") -> 0.8082329
A20: META CFO | B20: ='0. Database'!J69 -> 38747 | C20: ='0. Database'!K69 -> 57683 | D20: ='0. Database'!L69 -> 50475 | E20: ='0. Database'!M69 -> 71113 | F20: ='0. Database'!N69 -> 91328 | G20: ='0. Database'!O69 -> 115800 | H20: ='0. Database'!P69 -> 180250.64 | I20: ='0. Database'!Q69 -> 206102.96 | J20: ='0. Database'!R69 -> 243250.01
A21: META Capex(-) | B21: =-'0. Database'!J68 -> -15115 | C21: =-'0. Database'!K68 -> -18567 | D21: =-'0. Database'!L68 -> -31186 | E21: =-'0. Database'!M68 -> -27045 | F21: =-'0. Database'!N68 -> -37256 | G21: =-'0. Database'!O68 -> -69691 | H21: =-'0. Database'!P68 -> -135583.71 | I21: =-'0. Database'!Q68 -> -165714.44 | J21: =-'0. Database'!R68 -> -185600.17
A22: META GAP | B22: =IFERROR('0. Database'!J69-'0. Database'!J68,"") -> 23632 | C22: =IFERROR('0. Database'!K69-'0. Database'!K68,"") -> 39116 | D22: =IFERROR('0. Database'!L69-'0. Database'!L68,"") -> 19289 | E22: =IFERROR('0. Database'!M69-'0. Database'!M68,"") -> 44068 | F22: =IFERROR('0. Database'!N69-'0. Database'!N68,"") -> 54072 | G22: =IFERROR('0. Database'!O69-'0. Database'!O68,"") -> 46109 | H22: =IFERROR('0. Database'!P69-'0. Database'!P68,"") -> 44666.93 | I22: =IFERROR('0. Database'!Q69-'0. Database'!Q68,"") -> 40388.52 | J22: =IFERROR('0. Database'!R69-'0. Database'!R68,"") -> 57649.84
A23: META Capex/CFO | B23: =IFERROR('0. Database'!J68/'0. Database'!J69,"") -> 0.39009472 | C23: =IFERROR('0. Database'!K68/'0. Database'!K69,"") -> 0.32187993 | D23: =IFERROR('0. Database'!L68/'0. Database'!L69,"") -> 0.61785042 | E23: =IFERROR('0. Database'!M68/'0. Database'!M69,"") -> 0.38031021 | F23: =IFERROR('0. Database'!N68/'0. Database'!N69,"") -> 0.40793623 | G23: =IFERROR('0. Database'!O68/'0. Database'!O69,"") -> 0.60182211 | H23: =IFERROR('0. Database'!P68/'0. Database'!P69,"") -> 0.75219544 | I23: =IFERROR('0. Database'!Q68/'0. Database'!Q69,"") -> 0.80403717 | J23: =IFERROR('0. Database'!R68/'0. Database'!R69,"") -> 0.7630017
A25: ORCL CFO | B25: ='0. Database'!J89 -> 13139 | C25: ='0. Database'!K89 -> 15888 | D25: ='0. Database'!L89 -> 9540 | E25: ='0. Database'!M89 -> 17166 | F25: ='0. Database'!N89 -> 18673 | G25: ='0. Database'!O89 -> 20821 | H25: ='0. Database'!P89 -> 25457.17 | I25: ='0. Database'!Q89 -> 33694.38 | J25: ='0. Database'!R89 -> 50132.95
A26: ORCL Capex(-) | B26: =-'0. Database'!J88 -> -1564 | C26: =-'0. Database'!K88 -> -2135 | D26: =-'0. Database'!L88 -> -4511 | E26: =-'0. Database'!M88 -> -8695 | F26: =-'0. Database'!N88 -> -6866 | G26: =-'0. Database'!O88 -> -21215 | H26: =-'0. Database'!P88 -> -51882 | I26: =-'0. Database'!Q88 -> -52141.41 | J26: =-'0. Database'!R88 -> -69869.49
A27: ORCL GAP | B27: =IFERROR('0. Database'!J89-'0. Database'!J88,"") -> 11575 | C27: =IFERROR('0. Database'!K89-'0. Database'!K88,"") -> 13753 | D27: =IFERROR('0. Database'!L89-'0. Database'!L88,"") -> 5029 | E27: =IFERROR('0. Database'!M89-'0. Database'!M88,"") -> 8471 | F27: =IFERROR('0. Database'!N89-'0. Database'!N88,"") -> 11807 | G27: =IFERROR('0. Database'!O89-'0. Database'!O88,"") -> -394 | H27: =IFERROR('0. Database'!P89-'0. Database'!P88,"") -> -26424.83 | I27: =IFERROR('0. Database'!Q89-'0. Database'!Q88,"") -> -18447.03 | J27: =IFERROR('0. Database'!R89-'0. Database'!R88,"") -> -19736.54
A28: ORCL Capex/CFO | B28: =IFERROR('0. Database'!J88/'0. Database'!J89,"") -> 0.11903493 | C28: =IFERROR('0. Database'!K88/'0. Database'!K89,"") -> 0.13437815 | D28: =IFERROR('0. Database'!L88/'0. Database'!L89,"") -> 0.47285115 | E28: =IFERROR('0. Database'!M88/'0. Database'!M89,"") -> 0.50652453 | F28: =IFERROR('0. Database'!N88/'0. Database'!N89,"") -> 0.36769667 | G28: =IFERROR('0. Database'!O88/'0. Database'!O89,"") -> 1.0189232 | H28: =IFERROR('0. Database'!P88/'0. Database'!P89,"") -> 2.0380113 | I28: =IFERROR('0. Database'!Q88/'0. Database'!Q89,"") -> 1.5474809 | J28: =IFERROR('0. Database'!R88/'0. Database'!R89,"") -> 1.393684
A31: B. 2026E Aggregate Capex (formula-summed)
A32: Total 2026E Capex ($mm) | B32: ='0. Database'!P13+'0. Database'!P32+'0. Database'!P49+'0. Database'!P68+'0. Database'!P88 -> 718676.27
A34: C. Trigger Framework + Scenarios
A35: D&A Wave (2027-28) | B35: 85% | C35: HIGH — ORCL FY27E EPS -17% per model; all 5 names face D&A surge; triggers P/E re-rating
A36: Power Constraint (2026-27) | B36: 70% | C36: MIXED — acts as capex brake; delays D&A; but proves plans exceed physics
A37: Macro Shock (6-12mo) | B37: 20-30% | C37: MEDIUM — 10-15% correction; not fatal
A38: Demand Disappointment (12-24mo) | B38: 15-25% | C38: HIGH — breaks thesis; 30-40% multiple compression
A39: Customer Crack (ongoing) | B39: 10-15% | C39: EXTREME — ORCL -50%+; AMZN/GOOGL write-downs $20-50B
A41: Bull 30% (2026H2-28+) | B41: AI apps explode. FCF recovers 2028. Multiples hold. Winners: MSFT/GOOGL/AMZN.
A42: Base 45% (2027H1-28H1) | B42: D&A wave hits EPS. ORCL -17% materializes. Multiples 30x→22-25x. Stocks -15-25%.
A43: Bear 25% (2026Q4-28) | B43: Customer crack + macro. ORCL -50%+. AMZN write-down $20-40B. AI sector -30-40%.
A45: D. Circular Financing Warning (GS Q1'26 insight)
A46: • GOOGL: $36.8B equity gain on Anthropic → Anthropic spends on GOOGL TPUs → revenue + gain on same flow
A47: • AMZN: $16.8B gain on Anthropic → Anthropic uses 5GW Trainium → same circular structure
A48: • MSFT: $5.9B OpenAI-related gains. OpenAI is simultaneously MSFT's largest Azure customer
A49: • 'Other income' = 34% of hyperscaler Q1'26 profit. Strip it → EPS growth 61%→~25% (GS Exhibit 16)
A50: • Mirrors 1999 Cisco vendor financing. When AI labs stumble: lost customer + investment write-down simultaneously
A51: • GS: reward for EPS beats is 20bp — smallest in 25 years. Market already skeptical of EPS quality

Sheet 9. Charts
A1: Visual Summary (2013-2031)
A3: Capex/Rev %
B4: 2013 | C4: 2014 | D4: 2015 | E4: 2016 | F4: 2017 | G4: 2018 | H4: 2019 | I4: 2020 | J4: 2021 | K4: 2022 | L4: 2023 | M4: 2024 | N4: 2025 | O4: 2026 | P4: 2027 | Q4: 2028 | R4: 2029 | S4: 2030 | T4: 2031
A5: MSFT | B5: =IFERROR('0. Database'!C13/'0. Database'!C6,"") -> 0.054682783 | C5: =IFERROR('0. Database'!D13/'0. Database'!D6,"") -> 0.063167229 | D5: =IFERROR('0. Database'!E13/'0. Database'!E6,"") -> 0.063517846 | E5: =IFERROR('0. Database'!F13/'0. Database'!F6,"") -> 0.10468823 | F5: =IFERROR('0. Database'!G13/'0. Database'!G6,"") -> 0.10562177 | G5: =IFERROR('0. Database'!H13/'0. Database'!H6,"") -> 0.12323306 | H5: =IFERROR('0. Database'!I13/'0. Database'!I6,"") -> 0.13429432 | I5: =IFERROR('0. Database'!J13/'0. Database'!J6,"") -> 0.1328532 | ... T5: =IFERROR('0. Database'!U13/'0. Database'!U6,"")
A6: AMZN | B6: =IFERROR('0. Database'!C32/'0. Database'!C25,"") -> 0.046243939 | C6: =IFERROR('0. Database'!D32/'0. Database'!D25,"") -> 0.054973457 | D6: =IFERROR('0. Database'!E32/'0. Database'!E25,"") -> 0.04287586 | E6: =IFERROR('0. Database'!F32/'0. Database'!F25,"") -> 0.049534147 | F6: =IFERROR('0. Database'!G32/'0. Database'!G25,"") -> 0.056542566 | G6: =IFERROR('0. Database'!H32/'0. Database'!H25,"") -> 0.048615852 | H6: =IFERROR('0. Database'!I32/'0. Database'!I25,"") -> 0.045237094 | I6: =IFERROR('0. Database'!J32/'0. Database'!J25,"") -> 0.090777695 | ... T6: =IFERROR('0. Database'!U32/'0. Database'!U25,"") -> 0.22995731
A7: GOOGL | B7: =IFERROR('0. Database'!C49/'0. Database'!C42,"") -> 0.13253121 | C7: =IFERROR('0. Database'!D49/'0. Database'!D42,"") -> 0.16604294 | D7: =IFERROR('0. Database'!E49/'0. Database'!E42,"") -> 0.13221939 | E7: =IFERROR('0. Database'!F49/'0. Database'!F42,"") -> 0.11280353 | F7: =IFERROR('0. Database'!G49/'0. Database'!G42,"") -> 0.11893013 | G7: =IFERROR('0. Database'!H49/'0. Database'!H42,"") -> 0.1837391 | H7: =IFERROR('0. Database'!I49/'0. Database'!I42,"") -> 0.14548645 | I7: =IFERROR('0. Database'!J49/'0. Database'!J42,"") -> 0.12206961 | ... T7: =IFERROR('0. Database'!U49/'0. Database'!U42,"") -> 0.32084608
A8: META | B8: =IFERROR('0. Database'!C68/'0. Database'!C61,"") -> 0.17301829 | C8: =IFERROR('0. Database'!D68/'0. Database'!D61,"") -> 0.14687951 | D8: =IFERROR('0. Database'!E68/'0. Database'!E61,"") -> 0.14073744 | E8: =IFERROR('0. Database'!F68/'0. Database'!F61,"") -> 0.16249367 | F8: =IFERROR('0. Database'!G68/'0. Database'!G61,"") -> 0.16559663 | G8: =IFERROR('0. Database'!H68/'0. Database'!H61,"") -> 0.25036713 | H8: =IFERROR('0. Database'!I68/'0. Database'!I61,"") -> 0.21361736 | I8: =IFERROR('0. Database'!J68/'0. Database'!J61,"") -> 0.17582533 | ... T8: =IFERROR('0. Database'!U68/'0. Database'!U61,"") -> 0.43886513
A9: ORCL | B9: =IFERROR('0. Database'!C88/'0. Database'!C79,"") -> 0.017448259 | C9: =IFERROR('0. Database'!D88/'0. Database'!D79,"") -> 0.015141626 | D9: =IFERROR('0. Database'!E88/'0. Database'!E79,"") -> 0.036363161 | E9: =IFERROR('0. Database'!F88/'0. Database'!F79,"") -> 0.032085706 | F9: =IFERROR('0. Database'!G88/'0. Database'!G79,"") -> 0.053325945 | G9: =IFERROR('0. Database'!H88/'0. Database'!H79,"") -> 0.044026274 | H9: =IFERROR('0. Database'!I88/'0. Database'!I79,"") -> 0.041998735 | I9: =IFERROR('0. Database'!J88/'0. Database'!J79,"") -> 0.040027641 | ... T9: =IFERROR('0. Database'!U88/'0. Database'!U79,"")
A12: FCF Margin %
B13: 2013 | C13: 2014 | D13: 2015 | E13: 2016 | F13: 2017 | G13: 2018 | H13: 2019 | I13: 2020 | J13: 2021 | K13: 2022 | L13: 2023 | M13: 2024 | N13: 2025 | O13: 2026 | P13: 2027 | Q13: 2028 | R13: 2029 | S13: 2030 | T13: 2031
A14: MSFT | B14: =IFERROR('0. Database'!C17/'0. Database'!C6,"") -> 0.31568806 | C14: =IFERROR('0. Database'!D17/'0. Database'!D6,"") -> 0.30801654 | D14: =IFERROR('0. Database'!E17/'0. Database'!E6,"") -> 0.24723231 | E14: =IFERROR('0. Database'!F17/'0. Database'!F6,"") -> 0.28590014 | F14: =IFERROR('0. Database'!G17/'0. Database'!G6,"") -> 0.3034762 | G14: =IFERROR('0. Database'!H17/'0. Database'!H6,"") -> 0.27441102 | H14: =IFERROR('0. Database'!I17/'0. Database'!I6,"") -> 0.28038906 | I14: =IFERROR('0. Database'!J17/'0. Database'!J6,"") -> 0.291403 | ... T14: =IFERROR('0. Database'!U17/'0. Database'!U6,"")
A15: AMZN | B15: =IFERROR('0. Database'!C34/'0. Database'!C25,"") -> 0.027278955 | C15: =IFERROR('0. Database'!D34/'0. Database'!D25,"") -> 0.021906226 | D15: =IFERROR('0. Database'!E34/'0. Database'!E25,"") -> 0.068520073 | E15: =IFERROR('0. Database'!F34/'0. Database'!F25,"") -> 0.077470641 | F15: =IFERROR('0. Database'!G34/'0. Database'!G25,"") -> 0.047097253 | G15: =IFERROR('0. Database'!H34/'0. Database'!H25,"") -> 0.08331079 | H15: =IFERROR('0. Database'!I34/'0. Database'!I25,"") -> 0.092060516 | I15: =IFERROR('0. Database'!J34/'0. Database'!J25,"") -> 0.080344192 | ... T15: =IFERROR('0. Database'!U34/'0. Database'!U25,"") -> 0.086501792
A16: GOOGL | B16: =IFERROR('0. Database'!C51/'0. Database'!C42,"") -> 0.20220105 | C16: =IFERROR('0. Database'!D51/'0. Database'!D42,"") -> 0.17140649 | D16: =IFERROR('0. Database'!E51/'0. Database'!E42,"") -> 0.21221779 | E16: =IFERROR('0. Database'!F51/'0. Database'!F42,"") -> 0.28639002 | F16: =IFERROR('0. Database'!G51/'0. Database'!G42,"") -> 0.2156601 | G16: =IFERROR('0. Database'!H51/'0. Database'!H42,"") -> 0.16687741 | H16: =IFERROR('0. Database'!I51/'0. Database'!I42,"") -> 0.1913541 | I16: =IFERROR('0. Database'!J51/'0. Database'!J42,"") -> 0.23472144 | ... T16: =IFERROR('0. Database'!U51/'0. Database'!U42,"") -> 0.2205198
A17: META | B17: =IFERROR('0. Database'!C70/'0. Database'!C61,"") -> 0.36331301 | C17: =IFERROR('0. Database'!D70/'0. Database'!D61,"") -> 0.29494625 | D17: =IFERROR('0. Database'!E70/'0. Database'!E61,"") -> 0.33937636 | E17: =IFERROR('0. Database'!F70/'0. Database'!F61,"") -> 0.41862653 | F17: =IFERROR('0. Database'!G70/'0. Database'!G61,"") -> 0.43007896 | G17: =IFERROR('0. Database'!H70/'0. Database'!H61,"") -> 0.27506358 | H17: =IFERROR('0. Database'!I70/'0. Database'!I61,"") -> 0.30002192 | I17: =IFERROR('0. Database'!J70/'0. Database'!J61,"") -> 0.27489938 | ... T17: =IFERROR('0. Database'!U70/'0. Database'!U61,"") -> 0.23783335
A18: ORCL | B18: =IFERROR('0. Database'!C90/'0. Database'!C79,"") -> 0.36440018 | C18: =IFERROR('0. Database'!D90/'0. Database'!D79,"") -> 0.37438977 | D18: =IFERROR('0. Database'!E90/'0. Database'!E79,"") -> 0.33840483 | E18: =IFERROR('0. Database'!F90/'0. Database'!F79,"") -> 0.33383706 | F18: =IFERROR('0. Database'!G90/'0. Database'!G79,"") -> 0.31937518 | G18: =IFERROR('0. Database'!H90/'0. Database'!H79,"") -> 0.34617433 | H18: =IFERROR('0. Database'!I90/'0. Database'!I79,"") -> 0.32614801 | I18: =IFERROR('0. Database'!J90/'0. Database'!J79,"") -> 0.29624037 | ... T18: =IFERROR('0. Database'!U90/'0. Database'!U79,"")
A21: Capex ($mm)
B22: 2013 | C22: 2014 | D22: 2015 | E22: 2016 | F22: 2017 | G22: 2018 | H22: 2019 | I22: 2020 | J22: 2021 | K22: 2022 | L22: 2023 | M22: 2024 | N22: 2025 | O22: 2026 | P22: 2027 | Q22: 2028 | R22: 2029 | S22: 2030 | T22: 2031
A23: MSFT | B23: ='0. Database'!C13 -> 4257 | C23: ='0. Database'!D13 -> 5485 | D23: ='0. Database'!E13 -> 5944 | E23: ='0. Database'!F13 -> 8932 | F23: ='0. Database'!G13 -> 10200 | G23: ='0. Database'!H13 -> 13600 | H23: ='0. Database'!I13 -> 16900 | I23: ='0. Database'!J13 -> 19000 | ... T23: ='0. Database'!U13 -> 0
A24: AMZN | B24: ='0. Database'!C32 -> 3443 | C24: ='0. Database'!D32 -> 4892 | D24: ='0. Database'!E32 -> 4588 | E24: ='0. Database'!F32 -> 6736 | F24: ='0. Database'!G32 -> 10057 | G24: ='0. Database'!H32 -> 11322 | H24: ='0. Database'!I32 -> 12690 | I24: ='0. Database'!J32 -> 35046 | ... T24: ='0. Database'!U32 -> 328358.95
A25: GOOGL | B25: ='0. Database'!C49 -> 7358 | C25: ='0. Database'!D49 -> 10959 | D25: ='0. Database'!E49 -> 9915 | E25: ='0. Database'!F49 -> 10183 | F25: ='0. Database'!G49 -> 13184 | G25: ='0. Database'!H49 -> 25139 | H25: ='0. Database'!I49 -> 23548 | I25: ='0. Database'!J49 -> 22281 | ... T25: ='0. Database'!U49 -> 330225.02
A26: META | B26: ='0. Database'!C68 -> 1362 | C26: ='0. Database'!D68 -> 1831 | D26: ='0. Database'!E68 -> 2523 | E26: ='0. Database'!F68 -> 4491 | F26: ='0. Database'!G68 -> 6732 | G26: ='0. Database'!H68 -> 13980 | H26: ='0. Database'!I68 -> 15102 | I26: ='0. Database'!J68 -> 15115 | ... T26: ='0. Database'!U68 -> 221052.77
A27: ORCL | B27: ='0. Database'!C88 -> 650 | C27: ='0. Database'!D88 -> 580 | D27: ='0. Database'!E88 -> 1391 | E27: ='0. Database'!F88 -> 1189 | F27: ='0. Database'!G88 -> 2021 | G27: ='0. Database'!H88 -> 1736 | H27: ='0. Database'!I88 -> 1660 | I27: ='0. Database'!J88 -> 1564 | ... T27: ='0. Database'!U88 -> 0
A30: Rev YoY %
B31: 2013 | C31: 2014 | D31: 2015 | E31: 2016 | F31: 2017 | G31: 2018 | H31: 2019 | I31: 2020 | J31: 2021 | K31: 2022 | L31: 2023 | M31: 2024 | N31: 2025 | O31: 2026 | P31: 2027 | Q31: 2028 | R31: 2029 | S31: 2030 | T31: 2031
A32: MSFT | C32: =IFERROR('0. Database'!D6/'0. Database'!C6-1,"") -> 0.1154029 | D32: =IFERROR('0. Database'!E6/'0. Database'!D6-1,"") -> 0.077700874 | E32: =IFERROR('0. Database'!F6/'0. Database'!E6-1,"") -> -0.088266724 | F32: =IFERROR('0. Database'!G6/'0. Database'!F6-1,"") -> 0.13186826 | G32: =IFERROR('0. Database'!H6/'0. Database'!G6-1,"") -> 0.14278614 | H32: =IFERROR('0. Database'!I6/'0. Database'!H6-1,"") -> 0.1402954 | I32: =IFERROR('0. Database'!J6/'0. Database'!I6-1,"") -> 0.13645574 | J32: =IFERROR('0. Database'!K6/'0. Database'!J6-1,"") -> 0.17531727 | ... T32: =IFERROR('0. Database'!U6/'0. Database'!T6-1,"") -> -1
A33: AMZN | C33: =IFERROR('0. Database'!D25/'0. Database'!C25-1,"") -> 0.19522921 | D33: =IFERROR('0. Database'!E25/'0. Database'!D25-1,"") -> 0.20247808 | E33: =IFERROR('0. Database'!F25/'0. Database'!E25-1,"") -> 0.27082815 | F33: =IFERROR('0. Database'!G25/'0. Database'!F25-1,"") -> 0.30796326 | G33: =IFERROR('0. Database'!H25/'0. Database'!G25-1,"") -> 0.30933962 | H33: =IFERROR('0. Database'!I25/'0. Database'!H25-1,"") -> 0.20454126 | I33: =IFERROR('0. Database'!J25/'0. Database'!I25-1,"") -> 0.37623431 | J33: =IFERROR('0. Database'!K25/'0. Database'!J25-1,"") -> 0.21695367 | ... T33: =IFERROR('0. Database'!U25/'0. Database'!T25-1,"") -> 0.093837665
A34: GOOGL | C34: =IFERROR('0. Database'!D42/'0. Database'!C42-1,"") -> 0.18880023 | D34: =IFERROR('0. Database'!E42/'0. Database'!D42-1,"") -> 0.13617975 | E34: =IFERROR('0. Database'!F42/'0. Database'!E42-1,"") -> 0.20380322 | F34: =IFERROR('0. Database'!G42/'0. Database'!F42-1,"") -> 0.2280109 | G34: =IFERROR('0. Database'!H42/'0. Database'!G42-1,"") -> 0.23421587 | H34: =IFERROR('0. Database'!I42/'0. Database'!H42-1,"") -> 0.1830009 | I34: =IFERROR('0. Database'!J42/'0. Database'!I42-1,"") -> 0.12770532 | J34: =IFERROR('0. Database'!K42/'0. Database'!J42-1,"") -> 0.41150076 | ... T34: =IFERROR('0. Database'!U42/'0. Database'!T42-1,"") -> 0.11645501
A35: META | C35: =IFERROR('0. Database'!D61/'0. Database'!C61-1,"") -> 0.5835874 | D35: =IFERROR('0. Database'!E61/'0. Database'!D61-1,"") -> 0.43807155 | E35: =IFERROR('0. Database'!F61/'0. Database'!E61-1,"") -> 0.54169688 | F35: =IFERROR('0. Database'!G61/'0. Database'!F61-1,"") -> 0.47090962 | G35: =IFERROR('0. Database'!H61/'0. Database'!G61-1,"") -> 0.37352717 | H35: =IFERROR('0. Database'!I61/'0. Database'!H61-1,"") -> 0.26610015 | I35: =IFERROR('0. Database'!J61/'0. Database'!I61-1,"") -> 0.21598665 | J35: =IFERROR('0. Database'!K61/'0. Database'!J61-1,"") -> 0.37180979 | ... T35: =IFERROR('0. Database'!U61/'0. Database'!T61-1,"") -> 0.10412076
A36: ORCL | C36: =IFERROR('0. Database'!D79/'0. Database'!C79-1,"") -> 0.028239336 | D36: =IFERROR('0. Database'!E79/'0. Database'!D79-1,"") -> -0.0013575251 | E36: =IFERROR('0. Database'!F79/'0. Database'!E79-1,"") -> -0.031265522 | F36: =IFERROR('0. Database'!G79/'0. Database'!F79-1,"") -> 0.022721753 | G36: =IFERROR('0. Database'!H79/'0. Database'!G79-1,"") -> 0.04042323 | H36: =IFERROR('0. Database'!I79/'0. Database'!H79-1,"") -> 0.0023839111 | I36: =IFERROR('0. Database'!J79/'0. Database'!I79-1,"") -> -0.0114358 | J36: =IFERROR('0. Database'!K79/'0. Database'!J79-1,"") -> 0.036035114 | ... T36: =IFERROR('0. Database'!U79/'0. Database'!T79-1,"") -> -1
A39: OpMargin %
B40: 2013 | C40: 2014 | D40: 2015 | E40: 2016 | F40: 2017 | G40: 2018 | H40: 2019 | I40: 2020 | J40: 2021 | K40: 2022 | L40: 2023 | M40: 2024 | N40: 2025 | O40: 2026 | P40: 2027 | Q40: 2028 | R40: 2029 | S40: 2030 | T40: 2031
A41: MSFT | B41: =IFERROR('0. Database'!C7/'0. Database'!C6,"") -> 0.34379375 | C41: =IFERROR('0. Database'!D7/'0. Database'!D6,"") -> 0.31968261 | D41: =IFERROR('0. Database'!E7/'0. Database'!E6,"") -> 0.19406925 | E41: =IFERROR('0. Database'!F7/'0. Database'!F6,"") -> 0.23654477 | F41: =IFERROR('0. Database'!G7/'0. Database'!G6,"") -> 0.30055607 | G41: =IFERROR('0. Database'!H7/'0. Database'!H6,"") -> 0.31766945 | H41: =IFERROR('0. Database'!I7/'0. Database'!I6,"") -> 0.3413698 | I41: =IFERROR('0. Database'!J7/'0. Database'!J6,"") -> 0.37030381 | ... T41: =IFERROR('0. Database'!U7/'0. Database'!U6,"")
A42: AMZN | B42: =IFERROR('0. Database'!C26/'0. Database'!C25,"") -> 0.010006313 | C42: =IFERROR('0. Database'!D26/'0. Database'!D25,"") -> 0.0020047557 | D42: =IFERROR('0. Database'!E26/'0. Database'!E25,"") -> 0.020864134 | E42: =IFERROR('0. Database'!F26/'0. Database'!F25,"") -> 0.030782354 | F42: =IFERROR('0. Database'!G26/'0. Database'!G25,"") -> 0.023090416 | G42: =IFERROR('0. Database'!H26/'0. Database'!H25,"") -> 0.053330585 | H42: =IFERROR('0. Database'!I26/'0. Database'!I25,"") -> 0.051831942 | I42: =IFERROR('0. Database'!J26/'0. Database'!J25,"") -> 0.059314 | ... T42: =IFERROR('0. Database'!U26/'0. Database'!U25,"") -> 0.21388822
A43: GOOGL | B43: =IFERROR('0. Database'!C43/'0. Database'!C42,"") -> 0.27743655 | C43: =IFERROR('0. Database'!D43/'0. Database'!D42,"") -> 0.24993561 | D43: =IFERROR('0. Database'!E43/'0. Database'!E42,"") -> 0.2581712 | E43: =IFERROR('0. Database'!F43/'0. Database'!F42,"") -> 0.26271712 | F43: =IFERROR('0. Database'!G43/'0. Database'!G42,"") -> 0.23585765 | G43: =IFERROR('0. Database'!H43/'0. Database'!H42,"") -> 0.19699749 | H43: =IFERROR('0. Database'!I43/'0. Database'!I42,"") -> 0.21148915 | I43: =IFERROR('0. Database'!J43/'0. Database'!J42,"") -> 0.22585152 | ... T43: =IFERROR('0. Database'!U43/'0. Database'!U42,"") -> 0.36948581
A44: META | B44: =IFERROR('0. Database'!C62/'0. Database'!C61,"") -> 0.35619919 | C44: =IFERROR('0. Database'!D62/'0. Database'!D61,"") -> 0.40067383 | D44: =IFERROR('0. Database'!E62/'0. Database'!E61,"") -> 0.34724159 | E44: =IFERROR('0. Database'!F62/'0. Database'!F61,"") -> 0.44963456 | F44: =IFERROR('0. Database'!G62/'0. Database'!G61,"") -> 0.4969375 | G44: =IFERROR('0. Database'!H62/'0. Database'!H61,"") -> 0.44616569 | H44: =IFERROR('0. Database'!I62/'0. Database'!I61,"") -> 0.33927422 | I44: =IFERROR('0. Database'!J62/'0. Database'!J61,"") -> 0.3800456 | ... T44: =IFERROR('0. Database'!U62/'0. Database'!U61,"") -> 0.31356398
A45: ORCL | B45: =IFERROR('0. Database'!C80/'0. Database'!C79,"") -> 0.3941696 | C45: =IFERROR('0. Database'!D80/'0. Database'!D79,"") -> 0.38527607 | D45: =IFERROR('0. Database'!E80/'0. Database'!E79,"") -> 0.36258594 | E45: =IFERROR('0. Database'!F80/'0. Database'!F79,"") -> 0.34012467 | F45: =IFERROR('0. Database'!G80/'0. Database'!G79,"") -> 0.33536505 | G45: =IFERROR('0. Database'!H80/'0. Database'!H79,"") -> 0.33638508 | H45: =IFERROR('0. Database'!I80/'0. Database'!I79,"") -> 0.34244149 | I45: =IFERROR('0. Database'!J80/'0. Database'!J79,"") -> 0.3556676 | ... T45: =IFERROR('0. Database'!U80/'0. Database'!U79,"")
A48: D&A/Rev %
B49: 2013 | C49: 2014 | D49: 2015 | E49: 2016 | F49: 2017 | G49: 2018 | H49: 2019 | I49: 2020 | J49: 2021 | K49: 2022 | L49: 2023 | M49: 2024 | N49: 2025 | O49: 2026 | P49: 2027 | Q49: 2028 | R49: 2029 | S49: 2030 | T49: 2031
A50: MSFT | B50: =IFERROR('0. Database'!C12/'0. Database'!C6,"") -> 0.042890724 | C50: =IFERROR('0. Database'!D12/'0. Database'!D6,"") -> 0.048886944 | D50: =IFERROR('0. Database'!E12/'0. Database'!E6,"") -> 0.057704638 | E50: =IFERROR('0. Database'!F12/'0. Database'!F6,"") -> 0.068893577 | F50: =IFERROR('0. Database'!G12/'0. Database'!G6,"") -> 0.080769589 | G50: =IFERROR('0. Database'!H12/'0. Database'!H6,"") -> 0.089706415 | H50: =IFERROR('0. Database'!I12/'0. Database'!I6,"") -> 0.092178349 | I50: =IFERROR('0. Database'!J12/'0. Database'!J6,"") -> 0.086004965 | ... T50: =IFERROR('0. Database'!U12/'0. Database'!U6,"")
A51: AMZN | B51: =IFERROR('0. Database'!C31/'0. Database'!C25,"") -> 0.043691994 | C51: =IFERROR('0. Database'!D31/'0. Database'!D25,"") -> 0.053321557 | D51: =IFERROR('0. Database'!E31/'0. Database'!E25,"") -> 0.058697314 | E51: =IFERROR('0. Database'!F31/'0. Database'!F25,"") -> 0.059689529 | F51: =IFERROR('0. Database'!G31/'0. Database'!G25,"") -> 0.064531726 | G51: =IFERROR('0. Database'!H31/'0. Database'!H25,"") -> 0.065873149 | H51: =IFERROR('0. Database'!I31/'0. Database'!I25,"") -> 0.077673052 | I51: =IFERROR('0. Database'!J31/'0. Database'!J25,"") -> 0.065406254 | ... T51: =IFERROR('0. Database'!U31/'0. Database'!U25,"") -> 0.13431444
A52: GOOGL | B52: =IFERROR('0. Database'!C48/'0. Database'!C42,"") -> 0.05009096 | C52: =IFERROR('0. Database'!D48/'0. Database'!D42,"") -> 0.053377979 | D52: =IFERROR('0. Database'!E48/'0. Database'!E42,"") -> 0.055101415 | E52: =IFERROR('0. Database'!F48/'0. Database'!F42,"") -> 0.058345888 | F52: =IFERROR('0. Database'!G48/'0. Database'!G42,"") -> 0.055053899 | G52: =IFERROR('0. Database'!H48/'0. Database'!H42,"") -> 0.059670075 | H52: =IFERROR('0. Database'!I48/'0. Database'!I42,"") -> 0.067071551 | I52: =IFERROR('0. Database'!J48/'0. Database'!J42,"") -> 0.070701869 | ... T52: =IFERROR('0. Database'!U48/'0. Database'!U42,"") -> 0.17622984
A53: META | B53: =IFERROR('0. Database'!C67/'0. Database'!C61,"") -> 0.12842988 | C53: =IFERROR('0. Database'!D67/'0. Database'!D61,"") -> 0.099711215 | D53: =IFERROR('0. Database'!E67/'0. Database'!E61,"") -> 0.10849557 | E53: =IFERROR('0. Database'!F67/'0. Database'!F61,"") -> 0.084738404 | F53: =IFERROR('0. Database'!G67/'0. Database'!G61,"") -> 0.074410253 | G53: =IFERROR('0. Database'!H67/'0. Database'!H61,"") -> 0.077277123 | H53: =IFERROR('0. Database'!I67/'0. Database'!I61,"") -> 0.081206283 | I53: =IFERROR('0. Database'!J67/'0. Database'!J61,"") -> 0.079822255 | ... T53: =IFERROR('0. Database'!U67/'0. Database'!U61,"") -> 0.27034813
A54: ORCL | B54: =IFERROR('0. Database'!C87/'0. Database'!C79,"") -> 0.014656538 | C54: =IFERROR('0. Database'!D87/'0. Database'!D79,"") -> 0.015872601 | D54: =IFERROR('0. Database'!E87/'0. Database'!E79,"") -> 0.018612919 | E54: =IFERROR('0. Database'!F87/'0. Database'!F79,"") -> 0.023504331 | F54: =IFERROR('0. Database'!G87/'0. Database'!G79,"") -> 0.02638592 | G54: =IFERROR('0. Database'!H87/'0. Database'!H79,"") -> 0.029545282 | H54: =IFERROR('0. Database'!I87/'0. Database'!I79,"") -> 0.031119545 | I54: =IFERROR('0. Database'!J87/'0. Database'!J79,"") -> 0.035369693 | ... T54: =IFERROR('0. Database'!U87/'0. Database'!U79,"")
