Workbook

Sheet 0. Database
A1: Centralized Database (USD mm except EPS/shares) — Blue = input
A3: Ticker | B3: Metric | C3: 2013A | D3: 2014A | E3: 2015A | F3: 2016A | G3: 2017A | H3: 2018A | I3: 2019A | J3: 2020A | K3: 2021A | L3: 2022A | M3: 2023A | N3: 2024A | O3: 2025E | P3: 2026E | Q3: 2027E | R3: 2028E | S3: 2029E | T3: 2030E
A4: MSFT (FY(Jun))
A5: MSFT | B5: Revenue | C5: 77849 | D5: 86833 | E5: 93580 | F5: 91154 | G5: 96571 | H5: 110360 | I5: 125843 | J5: 143015 | K5: 168088 | L5: 198270 | M5: 211915 | N5: 245122 | O5: 281724 | P5: 319618.35 | Q5: 373106.65 | R5: 445409.63 | S5: 534000.03 | T5: 628544.33
A6: MSFT | B6: Operating Income | C6: 26764 | D6: 27759 | E6: 13359 | F6: 11756 | G6: 11389 | H6: 12924 | I6: 16219 | J6: 18724 | K6: 24351 | L6: 29687 | M6: 50074 | N6: 59661 | O6: 69773 | P6: 79541.62 | Q6: 85628.96 | R6: 69877.51 | S6: 101371.29 | T6: 108509.49
A7: MSFT | B7: Net Income | C7: 21863 | D7: 22074 | E7: 12193 | F7: 16798 | G7: 21204 | H7: 16571 | I7: 39240 | J7: 44281 | K7: 61271 | L7: 72738 | M7: 72361 | N7: 88136 | O7: 101832 | P7: 128773.53 | Q7: 144093.73 | R7: 170374.88 | S7: 198374.44 | T7: 231003.5
A8: MSFT | B8: EPS | C8: 2.58 | D8: 2.63 | E8: 1.48 | F8: 2.1 | G8: 2.71 | H8: 2.13 | I8: 5.06 | J8: 5.76 | K8: 8.05 | L8: 9.65 | M8: 9.68 | N8: 11.8 | O8: 13.64 | P8: 17.280667 | Q8: 19.417143 | R8: 22.809762 | S8: 26.996923 | T8: 31.4925
A9: MSFT | B9: Diluted Shares (mm) | C9: 8470 | D9: 8399 | E9: 8254 | F9: 8013 | G9: 7832 | H9: 7794 | I9: 7753 | J9: 7683 | K9: 7608 | L9: 7540 | M9: 7472 | N9: 7469 | O9: 7465 | P9: 7449.9017 | Q9: 7435.5853 | R9: 7424.3177 | S9: 7387.1205 | T9: 7366.4511
A10: MSFT | B10: SBC | C10: 2197 | D10: 2446 | E10: 2574 | F10: 2668 | G10: 3266 | H10: 3940 | I10: 4652 | J10: 5289 | K10: 6118 | L10: 7502 | M10: 9611 | N10: 10734 | O10: 11974 | P10: 12484.274 | Q10: 13833.136 | R10: 15727.995 | S10: 19055.002 | T10: 21162.66
A11: MSFT | B11: D&A | C11: 3755 | D11: 5212 | E11: 5957 | F11: 6622 | G11: 8778 | H11: 10261 | I11: 11682 | J11: 12796 | K11: 11686 | L11: 14460 | M11: 13861 | N11: 22287 | O11: 34153 | P11: 42005.109 | Q11: 55415.305 | R11: 73946.227 | S11: 97100.106 | T11: 127810.23
A12: MSFT | B12: Capex | C12: 4257 | D12: 5485 | E12: 5944 | F12: 8343 | G12: 8129 | H12: 11632 | I12: 13925 | J12: 15441 | K12: 20622 | L12: 23886 | M12: 28107 | N12: 44477 | O12: 64551 | P12: 117213.77 | Q12: 175938.58 | R12: 195085 | S12: 191785.5 | T12: 196810
A13: MSFT | B13: CFO | C13: 28833 | D13: 32502 | E13: 29668 | F13: 33325 | G13: 39507 | H13: 43884 | I13: 52185 | J13: 60675 | K13: 76740 | L13: 89035 | M13: 87582 | N13: 118548 | O13: 136162 | P13: 173163.84 | Q13: 210868.57 | R13: 255947.12 | S13: 307337.05 | T13: 359926.18
A14: MSFT | B14: FCF | C14: 24576 | D14: 27017 | E14: 23724 | F14: 24982 | G14: 31378 | H14: 32252 | I14: 38260 | J14: 45129 | K14: 56118 | L14: 65149 | M14: 64291 | N14: 74071 | O14: 71611 | P14: 63833.683 | Q14: 40769.753 | R14: 61522.486 | S14: 94794.224 | T14: 137549.86
A15: MSFT | B15: Buybacks | C15: 5360 | D15: 7316 | E15: 14443 | F15: 15969 | G15: 11788 | H15: 10721 | I15: 19543 | J15: 22968 | K15: 27385 | L15: 32696 | M15: 22245 | N15: 17254 | O15: 18420 | P15: 21283.747 | Q15: 20273.417 | R15: 21048.115 | S15: 22626.768 | T15: 24405.726
A16: MSFT | B16: Intell Cloud | C16: 0 | D16: 0 | E16: 0 | F16: 0 | G16: 0 | H16: 0 | I16: 0 | J16: 0 | K16: 0 | L16: 0 | M16: 72314 | N16: 87464 | O16: 106265 | P16: 136688.31 | Q16: 180358.14 | R16: 235873.55 | S16: 304531.45 | T16: 384276.13
... A18: MSFT | B18: Useful Life(yr) | C18: 3.16 | D18: 2.69 | E18: 2.81 | F18: 2.83 | G18: 2.71 | H18: 2.73 | I18: 2.74 | J18: 3.08 | K18: 4.33 | L18: 4.12 | M18: 6.1 | N18: 5.59 | O18: 5.26 | P18: 4.89 | Q18: 4.36 | R18: 4.38 | S18: 4.6 | T18: 4.7
A20: AMZN (CY)
A21: AMZN | B21: Revenue | C21: 41410 | D21: 50834 | E21: 63708 | F21: 79785 | G21: 106110 | H21: 141366 | I21: 170773 | J21: 236282 | K21: 279833 | L21: 315880 | M21: 352828 | N21: 387497 | O21: 426305 | P21: 461081.72 | Q21: 516677.03 | R21: 556072.43 | S21: 599450.61 | T21: 645470.67
A22: AMZN | B22: Operating Income | C22: 673 | D22: 458 | E22: 1507 | F22: 3108 | G22: 4331 | H22: 7296 | I22: 9201 | J22: 13531 | K22: 18532 | L22: 22841 | M22: 24631 | N22: 39834 | O22: 45606 | P22: 58892.45 | Q22: 76144.3 | R22: 98372.18 | S22: 123330.71 | T22: 152115.05
A23: AMZN | B23: Net Income | C23: 274 | D23: -241 | E23: 596 | F23: 2371 | G23: 2244 | H23: 10073 | I23: 11588 | J23: 21331 | K23: 24042 | L23: 7311 | M23: 29793 | N23: 59248 | O23: 77670 | P23: 95381.37 | Q23: 109556.18 | R23: 138562.23 | S23: 162769.35 | T23: 199614.81
A24: AMZN | B24: EPS | C24: 0.0295 | D24: -0.026 | E24: 0.0625 | F24: 0.245 | G24: 0.2275 | H24: 1.007 | I24: 1.1505 | J24: 2.0915 | K24: 2.3341747 | L24: 0.717539 | M24: 2.839592 | N24: 5.53 | O24: 7.17 | P24: 8.7931915 | Q24: 10.028182 | R24: 12.9156 | S24: 14.342727 | T24: 17.133333
A25: AMZN | B25: Diluted Shares (mm) | C25: 9300 | D25: 9240 | E25: 9540 | F25: 9680 | G25: 9860 | H25: 10000 | I25: 10080 | J25: 10200 | K25: 10300 | L25: 10189 | M25: 10492 | N25: 10721 | O25: 10827 | P25: 10899.309 | Q25: 11005.661 | R25: 11088.389 | S25: 11138.956 | T25: 11236.528
A26: AMZN | B26: SBC | C26: 1056 | D26: 1491 | E26: 2119 | F26: 2975 | G26: 4215 | H26: 5418 | I26: 6864 | J26: 9208 | K26: 12757 | L26: 19621 | M26: 24023 | N26: 22011 | O26: 19467 | P26: 19792.578 | Q26: 22146.495 | R26: 24906.477 | S26: 28060.926 | T26: 31047.394
A27: AMZN | B27: D&A | C27: 3253 | D27: 4746 | E27: 6281 | F27: 8116 | G27: 11478 | H27: 15341 | I27: 21789 | J27: 25180 | K27: 34433 | L27: 41921 | M27: 48663 | N27: 52795 | O27: 65756 | P27: 84391.581 | Q27: 107181.82 | R27: 131811.18 | S27: 145951.12 | T27: 164275.19
A28: AMZN | B28: Capex | C28: 3444 | D28: 4893 | E28: 5387 | F28: 7804 | G28: 11955 | H28: 13427 | I28: 16861 | J28: 40140 | K28: 61053 | L28: 63645 | M28: 52729 | N28: 82999 | O28: 131819 | P28: 199073.7 | Q28: 226404.48 | R28: 231478.22 | S28: 222715.44 | T28: 224350.56
A29: AMZN | B29: CFO | C29: 5475 | D29: 6842 | E29: 12039 | F29: 17203 | G29: 18365 | H29: 30723 | I29: 38514 | J29: 66064 | K29: 46327 | L29: 46752 | M29: 84946 | N29: 115877 | O29: 139514 | P29: 183450.99 | Q29: 235811.65 | R29: 295261.25 | S29: 339695.17 | T29: 400510.43
A30: AMZN | B30: FCF | C30: 2031 | D30: 1949 | E30: 6652 | F30: 9399 | G30: 6410 | H30: 17296 | I30: 21653 | J30: 25924 | K30: -14726 | L30: -16893 | M30: 32217 | N30: 32878 | O30: 7695 | P30: -16137.635 | Q30: -1113.9982 | R30: 58782.816 | S30: 115563.17 | T30: 183593.77
A31: AMZN | B31: Buybacks | C31: 0 | D31: 0 | E31: 0 | F31: 0 | G31: 0 | H31: 0 | I31: 0 | J31: 0 | K31: 0 | L31: 6000 | M31: 0 | N31: 0 | O31: 0 | P31: 0 | Q31: 0 | R31: 0 | S31: 0 | T31: 0
A32: AMZN | B32: AWS Rev | C32: 3107.57 | D32: 4644 | E32: 7880 | F32: 12219 | G32: 17458 | H32: 25656 | I32: 35026 | J32: 45370 | K32: 62202 | L32: 80096 | M32: 90757 | N32: 107556 | O32: 128725 | P32: 171284.9 | Q32: 225587.94 | R32: 274421.67 | S32: 323817.58 | T32: 374009.3
A33: AMZN | B33: AWS OI | D33: 458 | E33: 1508 | F33: 3109 | G33: 4331 | H33: 7296 | I33: 9201 | J33: 13531 | K33: 18532 | L33: 22841 | M33: 24631 | N33: 39834 | O33: 45606 | P33: 61254.41 | Q33: 81248.3 | R33: 100888.47 | S33: 121477.03 | T33: 143111.04
A35: GOOGL (CY)
A36: GOOGL | B36: Revenue | C36: 55519 | D36: 66001 | E36: 74989 | F36: 90272 | G36: 110855 | H36: 136819 | I36: 161857 | J36: 182527 | K36: 257637 | L36: 282836 | M36: 307394 | N36: 350018 | O36: 402836 | P36: 486455.79 | Q36: 578508.88 | R36: 684008.77 | S36: 805409.01 | T36: 941245.16
A37: GOOGL | B37: Operating Income | C37: 16260 | D37: 18965 | E37: 23319 | F37: 27055 | G37: 32456 | H37: 43137 | I37: 48999 | J37: 54606 | K37: 91855 | L37: 82699 | M37: 95858 | N37: 121263 | O37: 139404 | P37: 166048.71 | Q37: 188404.24 | R37: 207483.23 | S37: 229196.58 | T37: 258679.36
A38: GOOGL | B38: Net Income | C38: 12214 | D38: 13928 | E38: 15826 | F38: 19478 | G38: 22519 | H38: 30736 | I38: 32508 | J38: 40269 | K38: 76033 | L38: 59972 | M38: 73795 | N38: 100118 | O38: 132170 | P38: 174612.84 | Q38: 180090.27 | R38: 212391.88 | S38: 263167.33 | T38: 322005.86
A39: GOOGL | B39: EPS | C39: 0.90125 | D39: 1.0135 | E39: 1.142 | F39: 1.3925 | G39: 1.6005 | H39: 2.185 | I39: 2.3265 | J39: 2.9305 | K39: 5.61 | L39: 4.56 | M39: 5.8 | N39: 8.04 | O39: 10.81 | P39: 14.186724 | Q39: 14.69 | R39: 17.354848 | S39: 21.248 | T39: 26.035714
A40: GOOGL | B40: Diluted Shares (mm) | C40: 14739.044 | D40: 14839.96 | E40: 14893.5 | F40: 14951.3 | G40: 15014.6 | H40: 15002.98 | I40: 14901.66 | J40: 14664.2 | K40: 14462.08 | L40: 13159 | M40: 12722 | N40: 12447 | O40: 12230 | P40: 12208.564 | Q40: 12183.553 | R40: 12276.514 | S40: 12322.313 | T40: 12302.528
A41: GOOGL | B41: SBC | C41: -3268 | D41: -4175 | E41: -4903 | F41: -6703 | G41: -7679 | H41: -9353 | I41: -10794 | J41: -12991 | K41: -15376 | L41: -19362 | M41: -22460 | N41: -22785 | O41: -24953 | P41: -27937.33 | Q41: -30032.63 | R41: -31979.73 | S41: -33657.1 | T41: -35339.95
A42: GOOGL | B42: D&A | C42: 2781 | D42: 3523 | E42: 4132 | F42: 5267 | G42: 6103 | H42: 8164 | I42: 10856 | J42: 12905 | K42: 11555 | L42: 15287 | M42: 13326 | N42: 15311 | O42: 21136 | P42: 42874.7 | Q42: 69582.72 | R42: 98340.16 | S42: 127674.93 | T42: 156155.17
A43: GOOGL | B43: Capex | C43: 7358 | D43: 10959 | E43: 9950 | F43: 10212 | G43: 13184 | H43: 25139 | I43: 23548 | J43: 22281 | K43: 24640 | L43: 31485 | M43: 32251 | N43: 52535 | O43: 91447 | P43: 186454.02 | Q43: 244373.73 | R43: 260117.7 | S43: 255889.49 | T43: 259990.25
A44: GOOGL | B44: CFO | C44: 18659 | D44: 22376 | E44: 26572 | F44: 36036 | G44: 37091 | H44: 47971 | I44: 54520 | J44: 65124 | K44: 91652 | L44: 91495 | M44: 101746 | N44: 125299 | O44: 164713 | P44: 211732.28 | Q44: 259409.95 | R44: 321961.13 | S44: 388350.35 | T44: 469096.49
A45: GOOGL | B45: FCF | C45: 11301 | D45: 11417 | E45: 20579 | F45: 25853 | G45: 23907 | H45: 22832 | I45: 30972 | J45: 42843 | K45: 67552 | L45: 60010 | M45: 69495 | N45: 72764 | O45: 73266 | P45: 20997.934 | Q45: 15121.625 | R45: 53331.293 | S45: 109926.21 | T45: 168272.55
A46: GOOGL | B46: Buybacks | C46: 0 | D46: 0 | E46: 1780 | F46: 3693 | G46: 4846 | H46: 9075 | I46: 18396 | J46: 31149 | K46: 50274 | L46: 59296 | M46: 61504 | N46: 62222 | O46: 45709 | P46: 27809.976 | Q46: 30646.175 | R46: 24783.911 | S46: 35079.3 | T46: 56980.327
A47: GOOGL | B47: Cloud Rev | G47: 4056 | H47: 5838 | I47: 8918 | J47: 13059 | K47: 19206 | L47: 26280 | M47: 33088 | N47: 43229 | O47: 58705 | P47: 99085.93 | Q47: 157303.91 | R47: 220225.47 | S47: 286293.12 | T47: 343551.74
A48: GOOGL | B48: Search Rev | G48: 69811 | H48: 85296 | I48: 98115 | J48: 104062 | K48: 148951 | L48: 162450 | M48: 175033 | N48: 198084 | O48: 224532 | P48: 258723.55 | Q48: 291360.5 | R48: 324483.39 | S48: 358139.29 | T48: 392613.71
A49: GOOGL | B49: YouTube Rev | G49: 8150 | H49: 11115 | I49: 15149 | J49: 19772 | K49: 28845 | L49: 29243 | M49: 31510 | N49: 36147 | O49: 40367 | P49: 43997.73 | Q49: 49277.45 | R49: 54574.78 | S49: 59759.38 | T49: 64838.93
A50: GOOGL | B50: GCloud OI | H50: -4348 | I50: -4645 | J50: -5607 | K50: -2282 | L50: -1922 | M50: 1716 | N50: 6112 | O50: 13910 | P50: 32420.97 | Q50: 57771.82 | R50: 85285.05 | S50: 113733.5 | T50: 138713.29
A52: META (CY)
A53: META | B53: Revenue | C53: 7872 | D53: 12466 | E53: 17928 | F53: 27638 | G53: 40653 | H53: 55838 | I53: 70196 | J53: 84826 | K53: 115655 | L53: 114450 | M53: 133006 | N53: 162355 | O53: 198759 | P53: 249809.41 | Q53: 297686.36 | R53: 348303.47 | S53: 397616.7 | T53: 448874.02
A54: META | B54: Operating Income | C54: 2804 | D54: 4994 | E54: 6225 | F54: 12427 | G54: 20203 | H54: 24913 | I54: 23986 | J54: 32671 | K54: 46753 | L54: 28944 | M54: 46751 | N54: 69380 | O54: 83276 | P54: 87872.31 | Q54: 102309.2 | R54: 119899.68 | S54: 139513.21 | T54: 162052.13
A55: META | B55: Net Income | C55: 1491 | D55: 2925 | E55: 3669 | F55: 10188 | G55: 18190 | H55: 22112 | I55: 18485 | J55: 29146 | K55: 39370 | L55: 23200 | M55: 39098 | N55: 62360 | O55: 60458 | P55: 83760.967 | Q55: 89664.31 | R55: 105343.36 | S55: 126034.55 | T55: 146055.1
A56: META | B56: EPS | C56: 0.6 | D56: 1.1 | E56: 1.29 | F56: 3.49 | G56: 6.16 | H56: 7.57 | I56: 8.56 | J56: 9.78 | K56: 13.77 | L56: 8.59 | M56: 14.87 | N56: 23.86 | O56: 23.49 | P56: 32.200161 | Q56: 34.904068 | R56: 40.499167 | S56: 48.623529 | T56: 56.996875
A57: META | B57: Diluted Shares (mm) | C57: 2517 | D57: 2664 | E57: 2853 | F57: 2925 | G57: 2956 | H57: 2921 | I57: 2876 | J57: 2888 | K57: 2859 | L57: 2702 | M57: 2629 | N57: 2614 | O57: 2574 | P57: 2561.9327 | Q57: 2567.2625 | R57: 2587.2767 | S57: 2607.039 | T57: 2611.4238
A58: META | B58: SBC | C58: -906 | D58: -1837 | E58: -2969 | F58: -3202 | G58: -3723 | H58: -4152 | I58: -4835 | J58: -6536 | K58: -9163 | L58: -11991 | M58: -14027 | N58: -16690 | O58: -20426 | P58: -23722.2 | Q58: -24908.31 | R58: -26153.73 | S58: -27461.41 | T58: -28834.48
A59: META | B59: D&A | C59: 1011 | D59: 1243 | E59: 1945 | F59: 2342 | G59: 3025 | H59: 4315 | I59: 5741 | J59: 6862 | K59: 7967 | L59: 8686 | M59: 11178 | N59: 15498 | O59: 18616 | P59: 29596.548 | Q59: 43105.476 | R59: 57217.368 | S59: 74363.376 | T59: 87724.365
A60: META | B60: Capex | C60: 1362 | D60: 1831 | E60: 2523 | F60: 4491 | G60: 6733 | H60: 13915 | I60: 15102 | J60: 15163 | K60: 18690 | L60: 31431 | M60: 27266 | N60: 37256 | O60: 69691 | P60: 134391.33 | Q60: 159343.62 | R60: 171564.88 | S60: 174481.58 | T60: 180526.35
A61: META | B61: CFO | C61: 4222 | D61: 5457 | E61: 8599 | F61: 16108 | G61: 24216 | H61: 29274 | I61: 36314 | J61: 38747 | K61: 57683 | L61: 50475 | M61: 71113 | N61: 91328 | O61: 115800 | P61: 139861.26 | Q61: 175575.99 | R61: 206809.14 | S61: 243218.68 | T61: 283498.22
A62: META | B62: FCF | C62: 2849 | D62: 3626 | E62: 6076 | F62: 11617 | G62: 17483 | H62: 15359 | I62: 21212 | J62: 23584 | K62: 38993 | L62: 19044 | M62: 43847 | N62: 54072 | O62: 46109 | P62: 2449.0587 | Q62: 4328.2402 | R62: 28847.775 | S62: 69327.787 | T62: 98032.852
A63: META | B63: Buybacks | C63: 0 | D63: 0 | E63: 0 | F63: 0 | G63: 5222 | H63: 16087 | I63: 6539 | J63: 9836 | K63: 50052 | L63: 31551 | M63: 26786 | N63: 43895 | O63: 44648 | P63: 0 | Q63: 6000 | R63: 6000 | S63: 6000 | T63: 6000
A64: META | B64: Ad Rev(META) | C64: 6986 | D64: 11492 | E64: 17080 | F64: 26885 | G64: 39942 | H64: 55012 | I64: 69654.5 | J64: 84169 | K64: 114934 | L64: 113641 | M64: 131948 | N64: 160632 | O64: 196174 | P64: 248664.66 | Q64: 298597.44 | R64: 348271.65 | S64: 397194.59 | T64: 444912.31
A65: META | B65: FOA Rev | I65: 70196 | J65: 84826 | K65: 115655 | L65: 114450 | M65: 133005 | N65: 162354 | O65: 198758 | P65: 252529.81 | Q65: 303235.62 | R65: 353605.56 | S65: 403061.89 | T65: 451366.33
A66: META | B66: FOA OI | I66: 28489 | J66: 39294 | K66: 56947 | L66: 42662 | M66: 62870 | N66: 87109 | O66: 102469 | P66: 109500.79 | Q66: 122498.06 | R66: 135570.51 | S66: 147823.31 | T66: 158299.25
A67: META | B67: RL Rev | I67: 501 | J67: 1139 | K67: 2274 | L67: 2159 | M67: 1896 | N67: 2146 | O67: 2207 | P67: 2645.75 | Q67: 3174.9 | R67: 3730.51 | S67: 4290.08 | T67: 4826.34
A68: META | B68: RL OI | I68: -4503 | J68: -6623 | K68: -10194 | L68: -13717 | M68: -16119 | N68: -17729 | O68: -19193 | P68: -19011 | Q68: -18060.45 | R68: -17157.43 | S68: -16299.56 | T68: -15484.58
A70: ORCL (FY(May))
A71: ORCL | B71: Revenue | C71: 37180 | D71: 38275 | E71: 38226 | F71: 37047 | G71: 37728 | H71: 39383 | I71: 39506 | J71: 39068 | K71: 40479 | L71: 42440 | M71: 49954 | N71: 52961 | O71: 57399 | P71: 67004.176 | Q71: 87762.517 | R71: 131114.66 | S71: 184457.8 | T71: 223941.18
A72: ORCL | B72: Operating Income | C72: 14684 | D72: 14758 | E72: 13870 | F72: 12604 | G72: 12710 | H72: 13264 | I72: 13535 | J72: 13897 | K72: 15214 | L72: 10927 | M72: 13094 | N72: 15354 | O72: 17678 | P72: 19462.44 | Q72: 21128.19 | R72: 36930.86 | S72: 53057.71 | T72: 57952.82
A73: ORCL | B73: Net Income | C73: 10926 | D73: 10955 | E73: 9938 | F73: 8901 | G73: 9335 | H73: 3825 | I73: 11083 | J73: 10135 | K73: 13746 | L73: 6717 | M73: 8503 | N73: 10467 | O73: 12443 | P73: 17201.059 | Q73: 18923.588 | R73: 26746.345 | S73: 39545.812 | T73: 51960.267
A74: ORCL | B74: EPS | C74: 2.26 | D74: 2.38 | E74: 2.21 | F74: 2.07 | G74: 2.21 | H74: 0.9 | I74: 2.97 | J74: 3.08 | K74: 4.55 | L74: 2.41 | M74: 3.07 | N74: 3.71 | O74: 4.34 | P74: 5.8483871 | Q74: 6.26125 | R74: 8.7907407 | S74: 12.894375 | T74: 16.756
A75: ORCL | B75: Diluted Shares (mm) | C75: 4844 | D75: 4604 | E75: 4503 | F75: 4305 | G75: 4217 | H75: 4238 | I75: 3732 | J75: 3294 | K75: 3022 | L75: 2786 | M75: 2766 | N75: 2823 | O75: 2866 | P75: 2920.2401 | Q75: 2985.9048 | R75: 3029.6512 | S75: 3070.18 | T75: 3102.7389
A76: ORCL | B76: SBC | C76: 755 | D76: 805 | E76: 933 | F76: 1037 | G76: 1350 | H76: 1607 | I76: 1653 | J76: 1590 | K76: 1837 | L76: 2613 | M76: 3547 | N76: 3974 | O76: 4674 | P76: 5069.6 | Q76: 6473.15 | R76: 8609.75 | S76: 10649.61 | T76: 11212.32
A77: ORCL | B77: D&A | C77: 2931 | D77: 2908 | E77: 2861 | F77: 2509 | G77: 2451 | H77: 2785 | I77: 2919 | J77: 2968 | K77: 2916 | L77: 3122 | M77: 6108 | N77: 6139 | O77: 6174 | P77: 9142.317 | Q77: 13499.835 | R77: 21615.571 | S77: 30404.771 | T77: 37972.181
A78: ORCL | B78: Capex | C78: 650 | D78: 580 | E78: 1391 | F78: 1189 | G78: 2021 | H78: 1736 | I78: 1660 | J78: 1564 | K78: 2135 | L78: 4511 | M78: 8695 | N78: 6866 | O78: 21215 | P78: 50345.517 | Q78: 67168.625 | R78: 80914.621 | S78: 87153.471 | T78: 77098.125
A79: ORCL | B79: CFO | C79: 14224 | D79: 14921 | E79: 14580 | F79: 13685 | G79: 14126 | H79: 15386 | I79: 14551 | J79: 13139 | K79: 15887 | L79: 9539 | M79: 17165 | N79: 18673 | O79: 20821 | P79: 26027.191 | Q79: 37558.323 | R79: 55206.912 | S79: 80650.519 | T79: 102585.67
A80: ORCL | B80: FCF | C80: 13574 | D80: 14341 | E80: 13189 | F80: 12496 | G80: 12105 | H80: 13650 | I80: 12891 | J80: 11575 | K80: 13752 | L80: 5028 | M80: 8470 | N80: 11807 | O80: -394 | P80: -23532.429 | Q80: -27416.532 | R80: -26754.536 | S80: -3817.7534 | T80: 27298.067
A81: ORCL | B81: Buybacks | C81: 11021 | D81: 9813 | E81: 8087 | F81: 10440 | G81: 3561 | H81: 11347 | I81: 36140 | J81: 19240 | K81: 20934 | L81: 16248 | M81: 1300 | N81: 1202 | O81: 600 | P81: 95 | Q81: 0 | R81: 0 | S81: 0 | T81: 0
A82: ORCL | B82: CloudTotalRevenue(ORCL) | C82: 37180 | D82: 38275 | E82: 38226 | F82: 37047 | G82: 37728 | H82: 39383 | I82: 39506 | J82: 39068 | K82: 40479 | L82: 42440 | M82: 49954 | N82: 52961 | O82: 57399 | P82: 67004.176 | Q82: 87762.517 | R82: 131114.66 | S82: 184457.8 | T82: 223941.18
A83: ORCL | B83: IaaS Rev | L83: 2760.74 | M83: 4500 | N83: 6800 | O83: 10234 | P83: 18064.4 | Q83: 37935.24 | R83: 72977.07 | S83: 111105.3 | T83: 129847.66
A84: ORCL | B84: SaaS Rev | L84: 7999.33 | M84: 11400 | N84: 12949 | O84: 14272 | P84: 15955.84 | Q84: 17656.52 | R84: 19374.2 | S84: 21109.07 | T84: 22861.28
A85: ORCL | B85: RPO | I85: 36200 | J85: 37000 | K85: 41300 | L85: 46600 | M85: 67900 | N85: 98000 | O85: 138000
A86: ORCL | B86: Operating Income(Adjusted) | C86: 17612 | D86: 18108 | E86: 17396 | F86: 15785 | G86: 16168 | H86: 17155 | I86: 17384 | J86: 17383 | K86: 19000 | L86: 19592 | M86: 20904 | N86: 23054 | O86: 25034 | P86: 28113.04 | Q86: 28489.16 | R86: 46280.73 | S86: 64368.1 | T86: 69758.92
A87: ORCL | B87: EPS(Adjusted) | C87: 2.68 | D87: 2.38 | E87: 2.21 | F87: 2.07 | G87: 2.21 | H87: 0.9 | I87: 2.97 | J87: 3.08 | K87: 4.55 | L87: 2.41 | M87: 3.07 | N87: 3.71 | O87: 4.34 | P87: 5.8483871 | Q87: 6.26125 | R87: 8.7907407 | S87: 12.894375 | T87: 16.756
A89: NVDA (FY Jan)
A90: NVDA | B90: Revenue | D90: 4130.16 | E90: 4681.51 | F90: 5010 | G90: 6910 | H90: 9714 | I90: 11716 | J90: 10918 | K90: 16675 | L90: 26914 | M90: 26974 | N90: 60922 | O90: 130497 | P90: 215938 | Q90: 379513.47 | R90: 519798.97 | S90: 625601.86 | T90: 664318.86
A91: NVDA | B91: Operating Income | J91: 751 | K91: 2548 | L91: 4598 | M91: 5083 | N91: 32016 | O91: 82875 | P91: 130141 | Q91: 245259.44 | R91: 309757.26 | S91: 392712.72 | T91: 481971.82
A92: NVDA | B92: D&A
A93: NVDA | B93: EPS | D93: 0.02 | E93: 0.03 | F93: 0.03 | G93: 0.06 | H93: 0.12 | I93: 0.17 | J93: 0.11 | K93: 0.17 | L93: 0.39 | M93: 0.17 | N93: 1.19 | O93: 2.94 | P93: 4.9 | Q93: 8.97 | R93: 12.06 | S93: 14.09 | T93: 15.84
A94: NVDA | B94: Diluted Shares (mm) | D94: 23520 | E94: 22080 | F94: 21720 | G94: 21640 | H94: 23960 | I94: 24320 | J94: 24390 | K94: 24670 | L94: 24960 | M94: 24870 | N94: 24690 | O94: 24555 | P94: 24359 | Q94: 24298.14 | R94: 24143.46 | S94: 23883.77 | T94: 16685.95
A95: NVDA | B95: Free Cash Flow | D95: 580 | E95: 784 | F95: 1089 | G95: 1496 | H95: 2909 | I95: 3143 | J95: 4272 | K95: 4694 | L95: 8132 | M95: 3808 | N95: 27021 | O95: 60853 | P95: 96676 | Q95: 196546.7 | R95: 268143.94 | S95: 304204.5 | T95: 297544.37
A97: MU (FY Aug)
A98: MU | B98: Revenue | C98: 9073 | D98: 16358 | E98: 16192 | F98: 12399 | G98: 20322 | H98: 30391 | I98: 23406 | J98: 21435 | K98: 27705 | L98: 30758 | M98: 15540 | N98: 25111 | O98: 37378 | P98: 110164.58 | Q98: 178992.05 | R98: 173460.16 | S98: 171120 | T98: 170949
A99: MU | B99: D&A | C99: 1804 | D99: 2103 | E99: 2667 | F99: 2980 | G99: 3861 | H99: 4759 | I99: 5424 | J99: 5650 | K99: 6214 | L99: 7116 | M99: 7756 | N99: 7780 | O99: 8352 | P99: 9862.13 | Q99: 12539.03 | R99: 16162.36 | S99: 21543.79 | T99: 27453.5
A100: MU | B100: EPS | C100: 1.13 | D100: 2.54 | E100: 2.47 | F100: -0.27 | G100: 4.41 | H100: 11.51 | I100: 5.51 | J100: 2.37 | K100: 5.14 | L100: 7.75 | M100: -5.34 | N100: 0.7 | O100: 7.59 | P100: 58.9 | Q100: 102.73 | R100: 96.36 | S100: 89.91 | T100: 62.55
A101: MU | B101: Diluted Shares (mm) | C101: 1022 | D101: 1060 | E101: 1070 | F101: 1036 | G101: 1089 | H101: 1152 | I101: 1114 | J101: 1110 | K101: 1120 | L101: 1112 | M101: 1093 | N101: 1105 | O101: 1116 | P101: 1131.87 | Q101: 1131.16 | R101: 1126.9 | S101: 847.04 | T101: 740.81

Sheet 1. Revenue & Growth
A1: Revenue&AI/CloudSegment Detail (2013-2030E)
A3: A. Total Revenue ($mm)
A4: Company | B4: 2013A | C4: 2014A | D4: 2015A | E4: 2016A | F4: 2017A | G4: 2018A | H4: 2019A | I4: 2020A | J4: 2021A | K4: 2022A | L4: 2023A | M4: 2024A | N4: 2025E | O4: 2026E | P4: 2027E | Q4: 2028E | R4: 2029E | S4: 2030E
A5: MSFT | B5: ='0. Database'!C5 -> 77849 | C5: ='0. Database'!D5 -> 86833 | D5: ='0. Database'!E5 -> 93580 | E5: ='0. Database'!F5 -> 91154 | F5: ='0. Database'!G5 -> 96571 | G5: ='0. Database'!H5 -> 110360 | H5: ='0. Database'!I5 -> 125843 | I5: ='0. Database'!J5 -> 143015 | ... S5: ='0. Database'!T5 -> 628544.33
A6: AMZN | B6: ='0. Database'!C21 -> 41410 | C6: ='0. Database'!D21 -> 50834 | D6: ='0. Database'!E21 -> 63708 | E6: ='0. Database'!F21 -> 79785 | F6: ='0. Database'!G21 -> 106110 | G6: ='0. Database'!H21 -> 141366 | H6: ='0. Database'!I21 -> 170773 | I6: ='0. Database'!J21 -> 236282 | ... S6: ='0. Database'!T21 -> 645470.67
A7: GOOGL | B7: ='0. Database'!C36 -> 55519 | C7: ='0. Database'!D36 -> 66001 | D7: ='0. Database'!E36 -> 74989 | E7: ='0. Database'!F36 -> 90272 | F7: ='0. Database'!G36 -> 110855 | G7: ='0. Database'!H36 -> 136819 | H7: ='0. Database'!I36 -> 161857 | I7: ='0. Database'!J36 -> 182527 | ... S7: ='0. Database'!T36 -> 941245.16
A8: META | B8: ='0. Database'!C53 -> 7872 | C8: ='0. Database'!D53 -> 12466 | D8: ='0. Database'!E53 -> 17928 | E8: ='0. Database'!F53 -> 27638 | F8: ='0. Database'!G53 -> 40653 | G8: ='0. Database'!H53 -> 55838 | H8: ='0. Database'!I53 -> 70196 | I8: ='0. Database'!J53 -> 84826 | ... S8: ='0. Database'!T53 -> 448874.02
A9: ORCL | B9: ='0. Database'!C71 -> 37180 | C9: ='0. Database'!D71 -> 38275 | D9: ='0. Database'!E71 -> 38226 | E9: ='0. Database'!F71 -> 37047 | F9: ='0. Database'!G71 -> 37728 | G9: ='0. Database'!H71 -> 39383 | H9: ='0. Database'!I71 -> 39506 | I9: ='0. Database'!J71 -> 39068 | ... S9: ='0. Database'!T71 -> 223941.18
A11: C. Cloud / AI Proxy Revenue ($mm)
A12: Company | B12: 2013A | C12: 2014A | D12: 2015A | E12: 2016A | F12: 2017A | G12: 2018A | H12: 2019A | I12: 2020A | J12: 2021A | K12: 2022A | L12: 2023A | M12: 2024A | N12: 2025E | O12: 2026E | P12: 2027E | Q12: 2028E | R12: 2029E | S12: 2030E
A13: MSFT — Azure
A14: AMZN — AWS | B14: ='0. Database'!C32 -> 3107.57 | C14: ='0. Database'!D32 -> 4644 | D14: ='0. Database'!E32 -> 7880 | E14: ='0. Database'!F32 -> 12219 | F14: ='0. Database'!G32 -> 17458 | G14: ='0. Database'!H32 -> 25656 | H14: ='0. Database'!I32 -> 35026 | I14: ='0. Database'!J32 -> 45370 | ... S14: ='0. Database'!T32 -> 374009.3
A15: GOOGL — Cloud | B15: ='0. Database'!C47 -> 0 | C15: ='0. Database'!D47 -> 0 | D15: ='0. Database'!E47 -> 0 | E15: ='0. Database'!F47 -> 0 | F15: ='0. Database'!G47 -> 4056 | G15: ='0. Database'!H47 -> 5838 | H15: ='0. Database'!I47 -> 8918 | I15: ='0. Database'!J47 -> 13059 | ... S15: ='0. Database'!T47 -> 343551.74
A16: META — Advertising | B16: ='0. Database'!C64 -> 6986 | C16: ='0. Database'!D64 -> 11492 | D16: ='0. Database'!E64 -> 17080 | E16: ='0. Database'!F64 -> 26885 | F16: ='0. Database'!G64 -> 39942 | G16: ='0. Database'!H64 -> 55012 | H16: ='0. Database'!I64 -> 69654.5 | I16: ='0. Database'!J64 -> 84169 | ... S16: ='0. Database'!T64 -> 444912.31
A17: ORCL — CloudTotalRevenue | B17: ='0. Database'!C82 -> 37180 | C17: ='0. Database'!D82 -> 38275 | D17: ='0. Database'!E82 -> 38226 | E17: ='0. Database'!F82 -> 37047 | F17: ='0. Database'!G82 -> 37728 | G17: ='0. Database'!H82 -> 39383 | H17: ='0. Database'!I82 -> 39506 | I17: ='0. Database'!J82 -> 39068 | ... S17: ='0. Database'!T82 -> 223941.18
A19: B. Revenue YoY %
A20: Company | B20: 2013A | C20: 2014A | D20: 2015A | E20: 2016A | F20: 2017A | G20: 2018A | H20: 2019A | I20: 2020A | J20: 2021A | K20: 2022A | L20: 2023A | M20: 2024A | N20: 2025E | O20: 2026E | P20: 2027E | Q20: 2028E | R20: 2029E | S20: 2030E
A21: MSFT | C21: =IFERROR(C5/B5-1,"") -> 0.1154029 | D21: =IFERROR(D5/C5-1,"") -> 0.077700874 | E21: =IFERROR(E5/D5-1,"") -> -0.025924343 | F21: =IFERROR(F5/E5-1,"") -> 0.059426904 | G21: =IFERROR(G5/F5-1,"") -> 0.14278614 | H21: =IFERROR(H5/G5-1,"") -> 0.1402954 | I21: =IFERROR(I5/H5-1,"") -> 0.13645574 | J21: =IFERROR(J5/I5-1,"") -> 0.17531727 | ... S21: =IFERROR(S5/R5-1,"") -> 0.17704924
A22: AMZN | C22: =IFERROR(C6/B6-1,"") -> 0.22757788 | D22: =IFERROR(D6/C6-1,"") -> 0.2532557 | E22: =IFERROR(E6/D6-1,"") -> 0.25235449 | F22: =IFERROR(F6/E6-1,"") -> 0.32994924 | G22: =IFERROR(G6/F6-1,"") -> 0.33225898 | H22: =IFERROR(H6/G6-1,"") -> 0.20802032 | I22: =IFERROR(I6/H6-1,"") -> 0.38360279 | J22: =IFERROR(J6/I6-1,"") -> 0.18431789 | ... S22: =IFERROR(S6/R6-1,"") -> 0.076770408
A23: GOOGL | C23: =IFERROR(C7/B7-1,"") -> 0.18880023 | D23: =IFERROR(D7/C7-1,"") -> 0.13617975 | E23: =IFERROR(E7/D7-1,"") -> 0.20380322 | F23: =IFERROR(F7/E7-1,"") -> 0.2280109 | G23: =IFERROR(G7/F7-1,"") -> 0.23421587 | H23: =IFERROR(H7/G7-1,"") -> 0.1830009 | I23: =IFERROR(I7/H7-1,"") -> 0.12770532 | J23: =IFERROR(J7/I7-1,"") -> 0.41150076 | ... S23: =IFERROR(S7/R7-1,"") -> 0.16865486
A24: META | C24: =IFERROR(C8/B8-1,"") -> 0.5835874 | D24: =IFERROR(D8/C8-1,"") -> 0.43815177 | E24: =IFERROR(E8/D8-1,"") -> 0.54161089 | F24: =IFERROR(F8/E8-1,"") -> 0.47090962 | G24: =IFERROR(G8/F8-1,"") -> 0.37352717 | H24: =IFERROR(H8/G8-1,"") -> 0.25713672 | I24: =IFERROR(I8/H8-1,"") -> 0.20841643 | J24: =IFERROR(J8/I8-1,"") -> 0.3634381 | ... S24: =IFERROR(S8/R8-1,"") -> 0.12891139
A25: ORCL | C25: =IFERROR(C9/B9-1,"") -> 0.029451318 | D25: =IFERROR(D9/C9-1,"") -> -0.001280209 | E25: =IFERROR(E9/D9-1,"") -> -0.030842882 | F25: =IFERROR(F9/E9-1,"") -> 0.018382055 | G25: =IFERROR(G9/F9-1,"") -> 0.043866624 | H25: =IFERROR(H9/G9-1,"") -> 0.003123175 | I25: =IFERROR(I9/H9-1,"") -> -0.011086924 | J25: =IFERROR(J9/I9-1,"") -> 0.036116515 | ... S25: =IFERROR(S9/R9-1,"") -> 0.21405103

Sheet 2. Capex & D&A
A1: Capex&D&A (2013-2030E)
A3: A. Capex ($mm)
A4: Company | B4: 2013A | C4: 2014A | D4: 2015A | E4: 2016A | F4: 2017A | G4: 2018A | H4: 2019A | I4: 2020A | J4: 2021A | K4: 2022A | L4: 2023A | M4: 2024A | N4: 2025E | O4: 2026E | P4: 2027E | Q4: 2028E | R4: 2029E | S4: 2030E
A5: MSFT | B5: ='0. Database'!C12 -> 4257 | C5: ='0. Database'!D12 -> 5485 | D5: ='0. Database'!E12 -> 5944 | E5: ='0. Database'!F12 -> 8343 | F5: ='0. Database'!G12 -> 8129 | G5: ='0. Database'!H12 -> 11632 | H5: ='0. Database'!I12 -> 13925 | I5: ='0. Database'!J12 -> 15441 | ... S5: ='0. Database'!T12 -> 196810
A6: AMZN | B6: ='0. Database'!C28 -> 3444 | C6: ='0. Database'!D28 -> 4893 | D6: ='0. Database'!E28 -> 5387 | E6: ='0. Database'!F28 -> 7804 | F6: ='0. Database'!G28 -> 11955 | G6: ='0. Database'!H28 -> 13427 | H6: ='0. Database'!I28 -> 16861 | I6: ='0. Database'!J28 -> 40140 | ... S6: ='0. Database'!T28 -> 224350.56
A7: GOOGL | B7: ='0. Database'!C43 -> 7358 | C7: ='0. Database'!D43 -> 10959 | D7: ='0. Database'!E43 -> 9950 | E7: ='0. Database'!F43 -> 10212 | F7: ='0. Database'!G43 -> 13184 | G7: ='0. Database'!H43 -> 25139 | H7: ='0. Database'!I43 -> 23548 | I7: ='0. Database'!J43 -> 22281 | ... S7: ='0. Database'!T43 -> 259990.25
A8: META | B8: ='0. Database'!C60 -> 1362 | C8: ='0. Database'!D60 -> 1831 | D8: ='0. Database'!E60 -> 2523 | E8: ='0. Database'!F60 -> 4491 | F8: ='0. Database'!G60 -> 6733 | G8: ='0. Database'!H60 -> 13915 | H8: ='0. Database'!I60 -> 15102 | I8: ='0. Database'!J60 -> 15163 | ... S8: ='0. Database'!T60 -> 180526.35
A9: ORCL | B9: ='0. Database'!C78 -> 650 | C9: ='0. Database'!D78 -> 580 | D9: ='0. Database'!E78 -> 1391 | E9: ='0. Database'!F78 -> 1189 | F9: ='0. Database'!G78 -> 2021 | G9: ='0. Database'!H78 -> 1736 | H9: ='0. Database'!I78 -> 1660 | I9: ='0. Database'!J78 -> 1564 | ... S9: ='0. Database'!T78 -> 77098.125
A11: D. D&A ($mm)
A12: Company | B12: 2013A | C12: 2014A | D12: 2015A | E12: 2016A | F12: 2017A | G12: 2018A | H12: 2019A | I12: 2020A | J12: 2021A | K12: 2022A | L12: 2023A | M12: 2024A | N12: 2025E | O12: 2026E | P12: 2027E | Q12: 2028E | R12: 2029E | S12: 2030E
A13: MSFT | B13: ='0. Database'!C11 -> 3755 | C13: ='0. Database'!D11 -> 5212 | D13: ='0. Database'!E11 -> 5957 | E13: ='0. Database'!F11 -> 6622 | F13: ='0. Database'!G11 -> 8778 | G13: ='0. Database'!H11 -> 10261 | H13: ='0. Database'!I11 -> 11682 | I13: ='0. Database'!J11 -> 12796 | ... S13: ='0. Database'!T11 -> 127810.23
A14: AMZN | B14: ='0. Database'!C27 -> 3253 | C14: ='0. Database'!D27 -> 4746 | D14: ='0. Database'!E27 -> 6281 | E14: ='0. Database'!F27 -> 8116 | F14: ='0. Database'!G27 -> 11478 | G14: ='0. Database'!H27 -> 15341 | H14: ='0. Database'!I27 -> 21789 | I14: ='0. Database'!J27 -> 25180 | ... S14: ='0. Database'!T27 -> 164275.19
A15: GOOGL | B15: ='0. Database'!C42 -> 2781 | C15: ='0. Database'!D42 -> 3523 | D15: ='0. Database'!E42 -> 4132 | E15: ='0. Database'!F42 -> 5267 | F15: ='0. Database'!G42 -> 6103 | G15: ='0. Database'!H42 -> 8164 | H15: ='0. Database'!I42 -> 10856 | I15: ='0. Database'!J42 -> 12905 | ... S15: ='0. Database'!T42 -> 156155.17
A16: META | B16: ='0. Database'!C59 -> 1011 | C16: ='0. Database'!D59 -> 1243 | D16: ='0. Database'!E59 -> 1945 | E16: ='0. Database'!F59 -> 2342 | F16: ='0. Database'!G59 -> 3025 | G16: ='0. Database'!H59 -> 4315 | H16: ='0. Database'!I59 -> 5741 | I16: ='0. Database'!J59 -> 6862 | ... S16: ='0. Database'!T59 -> 87724.365
A17: ORCL | B17: ='0. Database'!C77 -> 2931 | C17: ='0. Database'!D77 -> 2908 | D17: ='0. Database'!E77 -> 2861 | E17: ='0. Database'!F77 -> 2509 | F17: ='0. Database'!G77 -> 2451 | G17: ='0. Database'!H77 -> 2785 | H17: ='0. Database'!I77 -> 2919 | I17: ='0. Database'!J77 -> 2968 | ... S17: ='0. Database'!T77 -> 37972.181
A19: (Revenue — for ratios)
A20: Company | B20: 2013A | C20: 2014A | D20: 2015A | E20: 2016A | F20: 2017A | G20: 2018A | H20: 2019A | I20: 2020A | J20: 2021A | K20: 2022A | L20: 2023A | M20: 2024A | N20: 2025E | O20: 2026E | P20: 2027E | Q20: 2028E | R20: 2029E | S20: 2030E
A21: MSFT | B21: ='0. Database'!C5 -> 77849 | C21: ='0. Database'!D5 -> 86833 | D21: ='0. Database'!E5 -> 93580 | E21: ='0. Database'!F5 -> 91154 | F21: ='0. Database'!G5 -> 96571 | G21: ='0. Database'!H5 -> 110360 | H21: ='0. Database'!I5 -> 125843 | I21: ='0. Database'!J5 -> 143015 | ... S21: ='0. Database'!T5 -> 628544.33
A22: AMZN | B22: ='0. Database'!C21 -> 41410 | C22: ='0. Database'!D21 -> 50834 | D22: ='0. Database'!E21 -> 63708 | E22: ='0. Database'!F21 -> 79785 | F22: ='0. Database'!G21 -> 106110 | G22: ='0. Database'!H21 -> 141366 | H22: ='0. Database'!I21 -> 170773 | I22: ='0. Database'!J21 -> 236282 | ... S22: ='0. Database'!T21 -> 645470.67
A23: GOOGL | B23: ='0. Database'!C36 -> 55519 | C23: ='0. Database'!D36 -> 66001 | D23: ='0. Database'!E36 -> 74989 | E23: ='0. Database'!F36 -> 90272 | F23: ='0. Database'!G36 -> 110855 | G23: ='0. Database'!H36 -> 136819 | H23: ='0. Database'!I36 -> 161857 | I23: ='0. Database'!J36 -> 182527 | ... S23: ='0. Database'!T36 -> 941245.16
A24: META | B24: ='0. Database'!C53 -> 7872 | C24: ='0. Database'!D53 -> 12466 | D24: ='0. Database'!E53 -> 17928 | E24: ='0. Database'!F53 -> 27638 | F24: ='0. Database'!G53 -> 40653 | G24: ='0. Database'!H53 -> 55838 | H24: ='0. Database'!I53 -> 70196 | I24: ='0. Database'!J53 -> 84826 | ... S24: ='0. Database'!T53 -> 448874.02
A25: ORCL | B25: ='0. Database'!C71 -> 37180 | C25: ='0. Database'!D71 -> 38275 | D25: ='0. Database'!E71 -> 38226 | E25: ='0. Database'!F71 -> 37047 | F25: ='0. Database'!G71 -> 37728 | G25: ='0. Database'!H71 -> 39383 | H25: ='0. Database'!I71 -> 39506 | I25: ='0. Database'!J71 -> 39068 | ... S25: ='0. Database'!T71 -> 223941.18
A27: B. CapexYoY %
A28: Company | B28: 2013A | C28: 2014A | D28: 2015A | E28: 2016A | F28: 2017A | G28: 2018A | H28: 2019A | I28: 2020A | J28: 2021A | K28: 2022A | L28: 2023A | M28: 2024A | N28: 2025E | O28: 2026E | P28: 2027E | Q28: 2028E | R28: 2029E | S28: 2030E
A29: MSFT | C29: =IFERROR(C5/B5-1,"") -> 0.28846606 | D29: =IFERROR(D5/C5-1,"") -> 0.083682771 | E29: =IFERROR(E5/D5-1,"") -> 0.40360027 | F29: =IFERROR(F5/E5-1,"") -> -0.025650246 | G29: =IFERROR(G5/F5-1,"") -> 0.43092631 | H29: =IFERROR(H5/G5-1,"") -> 0.19712861 | I29: =IFERROR(I5/H5-1,"") -> 0.10886894 | J29: =IFERROR(J5/I5-1,"") -> 0.33553526 | ... S29: =IFERROR(S5/R5-1,"") -> 0.02619854
A30: AMZN | C30: =IFERROR(C6/B6-1,"") -> 0.42073171 | D30: =IFERROR(D6/C6-1,"") -> 0.10096056 | E30: =IFERROR(E6/D6-1,"") -> 0.44867273 | F30: =IFERROR(F6/E6-1,"") -> 0.53190671 | G30: =IFERROR(G6/F6-1,"") -> 0.1231284 | H30: =IFERROR(H6/G6-1,"") -> 0.25575333 | I30: =IFERROR(I6/H6-1,"") -> 1.3806417 | J30: =IFERROR(J6/I6-1,"") -> 0.52100149 | ... S30: =IFERROR(S6/R6-1,"") -> 0.0073417051
A31: GOOGL | C31: =IFERROR(C7/B7-1,"") -> 0.48939929 | D31: =IFERROR(D7/C7-1,"") -> -0.092070444 | E31: =IFERROR(E7/D7-1,"") -> 0.026331658 | F31: =IFERROR(F7/E7-1,"") -> 0.29103016 | G31: =IFERROR(G7/F7-1,"") -> 0.90678095 | H31: =IFERROR(H7/G7-1,"") -> -0.063288118 | I31: =IFERROR(I7/H7-1,"") -> -0.053804994 | J31: =IFERROR(J7/I7-1,"") -> 0.10587496 | ... S31: =IFERROR(S7/R7-1,"") -> 0.0160255
A32: META | C32: =IFERROR(C8/B8-1,"") -> 0.34434655 | D32: =IFERROR(D8/C8-1,"") -> 0.37793555 | E32: =IFERROR(E8/D8-1,"") -> 0.78002378 | F32: =IFERROR(F8/E8-1,"") -> 0.49922066 | G32: =IFERROR(G8/F8-1,"") -> 1.0666865 | H32: =IFERROR(H8/G8-1,"") -> 0.085303629 | I32: =IFERROR(I8/H8-1,"") -> 0.0040392001 | J32: =IFERROR(J8/I8-1,"") -> 0.23260568 | ... S32: =IFERROR(S8/R8-1,"") -> 0.034644141
A33: ORCL | C33: =IFERROR(C9/B9-1,"") -> -0.10769231 | D33: =IFERROR(D9/C9-1,"") -> 1.3982759 | E33: =IFERROR(E9/D9-1,"") -> -0.14521927 | F33: =IFERROR(F9/E9-1,"") -> 0.69974769 | G33: =IFERROR(G9/F9-1,"") -> -0.1410193 | H33: =IFERROR(H9/G9-1,"") -> -0.043778802 | I33: =IFERROR(I9/H9-1,"") -> -0.057831325 | J33: =IFERROR(J9/I9-1,"") -> 0.36508951 | ... S33: =IFERROR(S9/R9-1,"") -> -0.11537516
A35: C. Capex / Revenue %
A36: Company | B36: 2013A | C36: 2014A | D36: 2015A | E36: 2016A | F36: 2017A | G36: 2018A | H36: 2019A | I36: 2020A | J36: 2021A | K36: 2022A | L36: 2023A | M36: 2024A | N36: 2025E | O36: 2026E | P36: 2027E | Q36: 2028E | R36: 2029E | S36: 2030E
A37: MSFT | B37: =IFERROR(B5/B21,"") -> 0.054682783 | C37: =IFERROR(C5/C21,"") -> 0.063167229 | D37: =IFERROR(D5/D21,"") -> 0.063517846 | E37: =IFERROR(E5/E21,"") -> 0.091526428 | F37: =IFERROR(F5/F21,"") -> 0.084176409 | G37: =IFERROR(G5/G21,"") -> 0.10540051 | H37: =IFERROR(H5/H21,"") -> 0.11065375 | I37: =IFERROR(I5/I21,"") -> 0.1079677 | ... S37: =IFERROR(S5/S21,"") -> 0.31312032
A38: AMZN | B38: =IFERROR(B6/B22,"") -> 0.083168317 | C38: =IFERROR(C6/C22,"") -> 0.096254475 | D38: =IFERROR(D6/D22,"") -> 0.084557669 | E38: =IFERROR(E6/E22,"") -> 0.097812872 | F38: =IFERROR(F6/F22,"") -> 0.1126661 | G38: =IFERROR(G6/G22,"") -> 0.094980405 | H38: =IFERROR(H6/H22,"") -> 0.098733406 | I38: =IFERROR(I6/I22,"") -> 0.16988175 | ... S38: =IFERROR(S6/S22,"") -> 0.34757668
A39: GOOGL | B39: =IFERROR(B7/B23,"") -> 0.13253121 | C39: =IFERROR(C7/C23,"") -> 0.16604294 | D39: =IFERROR(D7/D23,"") -> 0.13268613 | E39: =IFERROR(E7/E23,"") -> 0.11312478 | F39: =IFERROR(F7/F23,"") -> 0.11893013 | G39: =IFERROR(G7/G23,"") -> 0.1837391 | H39: =IFERROR(H7/H23,"") -> 0.14548645 | I39: =IFERROR(I7/I23,"") -> 0.12206961 | ... S39: =IFERROR(S7/S23,"") -> 0.27621948
A40: META | B40: =IFERROR(B8/B24,"") -> 0.17301829 | C40: =IFERROR(C8/C24,"") -> 0.14687951 | D40: =IFERROR(D8/D24,"") -> 0.14072959 | E40: =IFERROR(E8/E24,"") -> 0.16249367 | F40: =IFERROR(F8/F24,"") -> 0.16562123 | G40: =IFERROR(G8/G24,"") -> 0.24920305 | H40: =IFERROR(H8/H24,"") -> 0.21514046 | I40: =IFERROR(I8/I24,"") -> 0.17875416 | ... S40: =IFERROR(S8/S24,"") -> 0.40217598
A41: ORCL | B41: =IFERROR(B9/B25,"") -> 0.017482517 | C41: =IFERROR(C9/C25,"") -> 0.015153494 | D41: =IFERROR(D9/D25,"") -> 0.036388845 | E41: =IFERROR(E9/E25,"") -> 0.032094367 | F41: =IFERROR(F9/F25,"") -> 0.053567642 | G41: =IFERROR(G9/G25,"") -> 0.044079933 | H41: =IFERROR(H9/H25,"") -> 0.042018934 | I41: =IFERROR(I9/I25,"") -> 0.040032763 | ... S41: =IFERROR(S9/S25,"") -> 0.34427846
A43: E. D&A / Revenue %
A44: Company | B44: 2013A | C44: 2014A | D44: 2015A | E44: 2016A | F44: 2017A | G44: 2018A | H44: 2019A | I44: 2020A | J44: 2021A | K44: 2022A | L44: 2023A | M44: 2024A | N44: 2025E | O44: 2026E | P44: 2027E | Q44: 2028E | R44: 2029E | S44: 2030E
A45: MSFT | B45: =IFERROR(B13/B21,"") -> 0.048234402 | C45: =IFERROR(C13/C21,"") -> 0.060023263 | D45: =IFERROR(D13/D21,"") -> 0.063656764 | E45: =IFERROR(E13/E21,"") -> 0.072646291 | F45: =IFERROR(F13/F21,"") -> 0.090896853 | G45: =IFERROR(G13/G21,"") -> 0.092977528 | H45: =IFERROR(H13/H21,"") -> 0.092829955 | I45: =IFERROR(I13/I21,"") -> 0.089473132 | ... S45: =IFERROR(S13/S21,"") -> 0.20334322
A46: AMZN | B46: =IFERROR(B14/B22,"") -> 0.078555904 | C46: =IFERROR(C14/C22,"") -> 0.09336271 | D46: =IFERROR(D14/D22,"") -> 0.098590444 | E46: =IFERROR(E14/E22,"") -> 0.10172338 | F46: =IFERROR(F14/F22,"") -> 0.10817077 | G46: =IFERROR(G14/G22,"") -> 0.10851973 | H46: =IFERROR(H14/H22,"") -> 0.12759043 | I46: =IFERROR(I14/I22,"") -> 0.10656758 | ... S46: =IFERROR(S14/S22,"") -> 0.25450451
A47: GOOGL | B47: =IFERROR(B15/B23,"") -> 0.05009096 | C47: =IFERROR(C15/C23,"") -> 0.053377979 | D47: =IFERROR(D15/D23,"") -> 0.055101415 | E47: =IFERROR(E15/E23,"") -> 0.058345888 | F47: =IFERROR(F15/F23,"") -> 0.055053899 | G47: =IFERROR(G15/G23,"") -> 0.059670075 | H47: =IFERROR(H15/H23,"") -> 0.067071551 | I47: =IFERROR(I15/I23,"") -> 0.070701869 | ... S47: =IFERROR(S15/S23,"") -> 0.16590276
A48: META | B48: =IFERROR(B16/B24,"") -> 0.12842988 | C48: =IFERROR(C16/C24,"") -> 0.099711215 | D48: =IFERROR(D16/D24,"") -> 0.10848951 | E48: =IFERROR(E16/E24,"") -> 0.084738404 | F48: =IFERROR(F16/F24,"") -> 0.074410253 | G48: =IFERROR(G16/G24,"") -> 0.077277123 | H48: =IFERROR(H16/H24,"") -> 0.081785287 | I48: =IFERROR(I16/I24,"") -> 0.080895009 | ... S48: =IFERROR(S16/S24,"") -> 0.19543204
A49: ORCL | B49: =IFERROR(B17/B25,"") -> 0.078832706 | C49: =IFERROR(C17/C25,"") -> 0.075976486 | D49: =IFERROR(D17/D25,"") -> 0.074844347 | E49: =IFERROR(E17/E25,"") -> 0.067724782 | F49: =IFERROR(F17/F25,"") -> 0.064965013 | G49: =IFERROR(G17/G25,"") -> 0.070715791 | H49: =IFERROR(H17/H25,"") -> 0.073887511 | I49: =IFERROR(I17/I25,"") -> 0.075970103 | ... S49: =IFERROR(S17/S25,"") -> 0.16956319
A51: F. D&AYoY %
A52: Company | B52: 2013A | C52: 2014A | D52: 2015A | E52: 2016A | F52: 2017A | G52: 2018A | H52: 2019A | I52: 2020A | J52: 2021A | K52: 2022A | L52: 2023A | M52: 2024A | N52: 2025E | O52: 2026E | P52: 2027E | Q52: 2028E | R52: 2029E | S52: 2030E
A53: MSFT | C53: =IFERROR(C13/B13-1,"") -> 0.38801598 | D53: =IFERROR(D13/C13-1,"") -> 0.14293937 | E53: =IFERROR(E13/D13-1,"") -> 0.11163337 | F53: =IFERROR(F13/E13-1,"") -> 0.3255814 | G53: =IFERROR(G13/F13-1,"") -> 0.16894509 | H53: =IFERROR(H13/G13-1,"") -> 0.13848553 | I53: =IFERROR(I13/H13-1,"") -> 0.095360383 | J53: =IFERROR(J13/I13-1,"") -> -0.086745858 | ... S53: =IFERROR(S13/R13-1,"") -> 0.31627276
A54: AMZN | C54: =IFERROR(C14/B14-1,"") -> 0.45896096 | D54: =IFERROR(D14/C14-1,"") -> 0.32343026 | E54: =IFERROR(E14/D14-1,"") -> 0.29215093 | F54: =IFERROR(F14/E14-1,"") -> 0.41424347 | G54: =IFERROR(G14/F14-1,"") -> 0.33655689 | H54: =IFERROR(H14/G14-1,"") -> 0.42031158 | I54: =IFERROR(I14/H14-1,"") -> 0.15562899 | J54: =IFERROR(J14/I14-1,"") -> 0.36747419 | ... S54: =IFERROR(S14/R14-1,"") -> 0.12554943
A55: GOOGL | C55: =IFERROR(C15/B15-1,"") -> 0.2668105 | D55: =IFERROR(D15/C15-1,"") -> 0.17286404 | E55: =IFERROR(E15/D15-1,"") -> 0.27468538 | F55: =IFERROR(F15/E15-1,"") -> 0.15872413 | G55: =IFERROR(G15/F15-1,"") -> 0.33770277 | H55: =IFERROR(H15/G15-1,"") -> 0.32974032 | I55: =IFERROR(I15/H15-1,"") -> 0.18874355 | J55: =IFERROR(J15/I15-1,"") -> -0.10461062 | ... S55: =IFERROR(S15/R15-1,"") -> 0.22306838
A56: META | C56: =IFERROR(C16/B16-1,"") -> 0.22947577 | D56: =IFERROR(D16/C16-1,"") -> 0.56476267 | E56: =IFERROR(E16/D16-1,"") -> 0.20411311 | F56: =IFERROR(F16/E16-1,"") -> 0.29163108 | G56: =IFERROR(G16/F16-1,"") -> 0.42644628 | H56: =IFERROR(H16/G16-1,"") -> 0.33047509 | I56: =IFERROR(I16/H16-1,"") -> 0.19526215 | J56: =IFERROR(J16/I16-1,"") -> 0.16103177 | ... S56: =IFERROR(S16/R16-1,"") -> 0.17967163
A57: ORCL | C57: =IFERROR(C17/B17-1,"") -> -0.0078471511 | D57: =IFERROR(D17/C17-1,"") -> -0.016162311 | E57: =IFERROR(E17/D17-1,"") -> -0.1230339 | F57: =IFERROR(F17/E17-1,"") -> -0.02311678 | G57: =IFERROR(G17/F17-1,"") -> 0.13627091 | H57: =IFERROR(H17/G17-1,"") -> 0.048114901 | I57: =IFERROR(I17/H17-1,"") -> 0.016786571 | J57: =IFERROR(J17/I17-1,"") -> -0.017520216 | ... S57: =IFERROR(S17/R17-1,"") -> 0.24888891

Sheet 3. FCF & Cash
A1: Free Cash Flow&Cash Quality (2013-2030E)
A3: A. CFO ($mm)
A4: Company | B4: 2013A | C4: 2014A | D4: 2015A | E4: 2016A | F4: 2017A | G4: 2018A | H4: 2019A | I4: 2020A | J4: 2021A | K4: 2022A | L4: 2023A | M4: 2024A | N4: 2025E | O4: 2026E | P4: 2027E | Q4: 2028E | R4: 2029E | S4: 2030E
A5: MSFT | B5: ='0. Database'!C13 -> 28833 | C5: ='0. Database'!D13 -> 32502 | D5: ='0. Database'!E13 -> 29668 | E5: ='0. Database'!F13 -> 33325 | F5: ='0. Database'!G13 -> 39507 | G5: ='0. Database'!H13 -> 43884 | H5: ='0. Database'!I13 -> 52185 | I5: ='0. Database'!J13 -> 60675 | ... S5: ='0. Database'!T13 -> 359926.18
A6: AMZN | B6: ='0. Database'!C29 -> 5475 | C6: ='0. Database'!D29 -> 6842 | D6: ='0. Database'!E29 -> 12039 | E6: ='0. Database'!F29 -> 17203 | F6: ='0. Database'!G29 -> 18365 | G6: ='0. Database'!H29 -> 30723 | H6: ='0. Database'!I29 -> 38514 | I6: ='0. Database'!J29 -> 66064 | ... S6: ='0. Database'!T29 -> 400510.43
A7: GOOGL | B7: ='0. Database'!C44 -> 18659 | C7: ='0. Database'!D44 -> 22376 | D7: ='0. Database'!E44 -> 26572 | E7: ='0. Database'!F44 -> 36036 | F7: ='0. Database'!G44 -> 37091 | G7: ='0. Database'!H44 -> 47971 | H7: ='0. Database'!I44 -> 54520 | I7: ='0. Database'!J44 -> 65124 | ... S7: ='0. Database'!T44 -> 469096.49
A8: META | B8: ='0. Database'!C61 -> 4222 | C8: ='0. Database'!D61 -> 5457 | D8: ='0. Database'!E61 -> 8599 | E8: ='0. Database'!F61 -> 16108 | F8: ='0. Database'!G61 -> 24216 | G8: ='0. Database'!H61 -> 29274 | H8: ='0. Database'!I61 -> 36314 | I8: ='0. Database'!J61 -> 38747 | ... S8: ='0. Database'!T61 -> 283498.22
A9: ORCL | B9: ='0. Database'!C79 -> 14224 | C9: ='0. Database'!D79 -> 14921 | D9: ='0. Database'!E79 -> 14580 | E9: ='0. Database'!F79 -> 13685 | F9: ='0. Database'!G79 -> 14126 | G9: ='0. Database'!H79 -> 15386 | H9: ='0. Database'!I79 -> 14551 | I9: ='0. Database'!J79 -> 13139 | ... S9: ='0. Database'!T79 -> 102585.67
A11: B. FCF ($mm)
A12: Company | B12: 2013A | C12: 2014A | D12: 2015A | E12: 2016A | F12: 2017A | G12: 2018A | H12: 2019A | I12: 2020A | J12: 2021A | K12: 2022A | L12: 2023A | M12: 2024A | N12: 2025E | O12: 2026E | P12: 2027E | Q12: 2028E | R12: 2029E | S12: 2030E
A13: MSFT | B13: ='0. Database'!C14 -> 24576 | C13: ='0. Database'!D14 -> 27017 | D13: ='0. Database'!E14 -> 23724 | E13: ='0. Database'!F14 -> 24982 | F13: ='0. Database'!G14 -> 31378 | G13: ='0. Database'!H14 -> 32252 | H13: ='0. Database'!I14 -> 38260 | I13: ='0. Database'!J14 -> 45129 | ... S13: ='0. Database'!T14 -> 137549.86
A14: AMZN | B14: ='0. Database'!C30 -> 2031 | C14: ='0. Database'!D30 -> 1949 | D14: ='0. Database'!E30 -> 6652 | E14: ='0. Database'!F30 -> 9399 | F14: ='0. Database'!G30 -> 6410 | G14: ='0. Database'!H30 -> 17296 | H14: ='0. Database'!I30 -> 21653 | I14: ='0. Database'!J30 -> 25924 | ... S14: ='0. Database'!T30 -> 183593.77
A15: GOOGL | B15: ='0. Database'!C45 -> 11301 | C15: ='0. Database'!D45 -> 11417 | D15: ='0. Database'!E45 -> 20579 | E15: ='0. Database'!F45 -> 25853 | F15: ='0. Database'!G45 -> 23907 | G15: ='0. Database'!H45 -> 22832 | H15: ='0. Database'!I45 -> 30972 | I15: ='0. Database'!J45 -> 42843 | ... S15: ='0. Database'!T45 -> 168272.55
A16: META | B16: ='0. Database'!C62 -> 2849 | C16: ='0. Database'!D62 -> 3626 | D16: ='0. Database'!E62 -> 6076 | E16: ='0. Database'!F62 -> 11617 | F16: ='0. Database'!G62 -> 17483 | G16: ='0. Database'!H62 -> 15359 | H16: ='0. Database'!I62 -> 21212 | I16: ='0. Database'!J62 -> 23584 | ... S16: ='0. Database'!T62 -> 98032.852
A17: ORCL | B17: ='0. Database'!C80 -> 13574 | C17: ='0. Database'!D80 -> 14341 | D17: ='0. Database'!E80 -> 13189 | E17: ='0. Database'!F80 -> 12496 | F17: ='0. Database'!G80 -> 12105 | G17: ='0. Database'!H80 -> 13650 | H17: ='0. Database'!I80 -> 12891 | I17: ='0. Database'!J80 -> 11575 | ... S17: ='0. Database'!T80 -> 27298.067
A19: E. Buybacks ($mm)
A20: Company | B20: 2013A | C20: 2014A | D20: 2015A | E20: 2016A | F20: 2017A | G20: 2018A | H20: 2019A | I20: 2020A | J20: 2021A | K20: 2022A | L20: 2023A | M20: 2024A | N20: 2025E | O20: 2026E | P20: 2027E | Q20: 2028E | R20: 2029E | S20: 2030E
A21: MSFT | B21: ='0. Database'!C15 -> 5360 | C21: ='0. Database'!D15 -> 7316 | D21: ='0. Database'!E15 -> 14443 | E21: ='0. Database'!F15 -> 15969 | F21: ='0. Database'!G15 -> 11788 | G21: ='0. Database'!H15 -> 10721 | H21: ='0. Database'!I15 -> 19543 | I21: ='0. Database'!J15 -> 22968 | ... S21: ='0. Database'!T15 -> 24405.726
A22: AMZN | B22: ='0. Database'!C31 -> 0 | C22: ='0. Database'!D31 -> 0 | D22: ='0. Database'!E31 -> 0 | E22: ='0. Database'!F31 -> 0 | F22: ='0. Database'!G31 -> 0 | G22: ='0. Database'!H31 -> 0 | H22: ='0. Database'!I31 -> 0 | I22: ='0. Database'!J31 -> 0 | ... S22: ='0. Database'!T31 -> 0
A23: GOOGL | B23: ='0. Database'!C46 -> 0 | C23: ='0. Database'!D46 -> 0 | D23: ='0. Database'!E46 -> 1780 | E23: ='0. Database'!F46 -> 3693 | F23: ='0. Database'!G46 -> 4846 | G23: ='0. Database'!H46 -> 9075 | H23: ='0. Database'!I46 -> 18396 | I23: ='0. Database'!J46 -> 31149 | ... S23: ='0. Database'!T46 -> 56980.327
A24: META | B24: ='0. Database'!C63 -> 0 | C24: ='0. Database'!D63 -> 0 | D24: ='0. Database'!E63 -> 0 | E24: ='0. Database'!F63 -> 0 | F24: ='0. Database'!G63 -> 5222 | G24: ='0. Database'!H63 -> 16087 | H24: ='0. Database'!I63 -> 6539 | I24: ='0. Database'!J63 -> 9836 | ... S24: ='0. Database'!T63 -> 6000
A25: ORCL | B25: ='0. Database'!C81 -> 11021 | C25: ='0. Database'!D81 -> 9813 | D25: ='0. Database'!E81 -> 8087 | E25: ='0. Database'!F81 -> 10440 | F25: ='0. Database'!G81 -> 3561 | G25: ='0. Database'!H81 -> 11347 | H25: ='0. Database'!I81 -> 36140 | I25: ='0. Database'!J81 -> 19240 | ... S25: ='0. Database'!T81 -> 0
A27: (Revenue)
A28: Company | B28: 2013A | C28: 2014A | D28: 2015A | E28: 2016A | F28: 2017A | G28: 2018A | H28: 2019A | I28: 2020A | J28: 2021A | K28: 2022A | L28: 2023A | M28: 2024A | N28: 2025E | O28: 2026E | P28: 2027E | Q28: 2028E | R28: 2029E | S28: 2030E
A29: MSFT | B29: ='0. Database'!C5 -> 77849 | C29: ='0. Database'!D5 -> 86833 | D29: ='0. Database'!E5 -> 93580 | E29: ='0. Database'!F5 -> 91154 | F29: ='0. Database'!G5 -> 96571 | G29: ='0. Database'!H5 -> 110360 | H29: ='0. Database'!I5 -> 125843 | I29: ='0. Database'!J5 -> 143015 | ... S29: ='0. Database'!T5 -> 628544.33
A30: AMZN | B30: ='0. Database'!C21 -> 41410 | C30: ='0. Database'!D21 -> 50834 | D30: ='0. Database'!E21 -> 63708 | E30: ='0. Database'!F21 -> 79785 | F30: ='0. Database'!G21 -> 106110 | G30: ='0. Database'!H21 -> 141366 | H30: ='0. Database'!I21 -> 170773 | I30: ='0. Database'!J21 -> 236282 | ... S30: ='0. Database'!T21 -> 645470.67
A31: GOOGL | B31: ='0. Database'!C36 -> 55519 | C31: ='0. Database'!D36 -> 66001 | D31: ='0. Database'!E36 -> 74989 | E31: ='0. Database'!F36 -> 90272 | F31: ='0. Database'!G36 -> 110855 | G31: ='0. Database'!H36 -> 136819 | H31: ='0. Database'!I36 -> 161857 | I31: ='0. Database'!J36 -> 182527 | ... S31: ='0. Database'!T36 -> 941245.16
A32: META | B32: ='0. Database'!C53 -> 7872 | C32: ='0. Database'!D53 -> 12466 | D32: ='0. Database'!E53 -> 17928 | E32: ='0. Database'!F53 -> 27638 | F32: ='0. Database'!G53 -> 40653 | G32: ='0. Database'!H53 -> 55838 | H32: ='0. Database'!I53 -> 70196 | I32: ='0. Database'!J53 -> 84826 | ... S32: ='0. Database'!T53 -> 448874.02
A33: ORCL | B33: ='0. Database'!C71 -> 37180 | C33: ='0. Database'!D71 -> 38275 | D33: ='0. Database'!E71 -> 38226 | E33: ='0. Database'!F71 -> 37047 | F33: ='0. Database'!G71 -> 37728 | G33: ='0. Database'!H71 -> 39383 | H33: ='0. Database'!I71 -> 39506 | I33: ='0. Database'!J71 -> 39068 | ... S33: ='0. Database'!T71 -> 223941.18
A35: (NI)
A36: Company | B36: 2013A | C36: 2014A | D36: 2015A | E36: 2016A | F36: 2017A | G36: 2018A | H36: 2019A | I36: 2020A | J36: 2021A | K36: 2022A | L36: 2023A | M36: 2024A | N36: 2025E | O36: 2026E | P36: 2027E | Q36: 2028E | R36: 2029E | S36: 2030E
A37: MSFT | B37: ='0. Database'!C7 -> 21863 | C37: ='0. Database'!D7 -> 22074 | D37: ='0. Database'!E7 -> 12193 | E37: ='0. Database'!F7 -> 16798 | F37: ='0. Database'!G7 -> 21204 | G37: ='0. Database'!H7 -> 16571 | H37: ='0. Database'!I7 -> 39240 | I37: ='0. Database'!J7 -> 44281 | ... S37: ='0. Database'!T7 -> 231003.5
A38: AMZN | B38: ='0. Database'!C23 -> 274 | C38: ='0. Database'!D23 -> -241 | D38: ='0. Database'!E23 -> 596 | E38: ='0. Database'!F23 -> 2371 | F38: ='0. Database'!G23 -> 2244 | G38: ='0. Database'!H23 -> 10073 | H38: ='0. Database'!I23 -> 11588 | I38: ='0. Database'!J23 -> 21331 | ... S38: ='0. Database'!T23 -> 199614.81
A39: GOOGL | B39: ='0. Database'!C38 -> 12214 | C39: ='0. Database'!D38 -> 13928 | D39: ='0. Database'!E38 -> 15826 | E39: ='0. Database'!F38 -> 19478 | F39: ='0. Database'!G38 -> 22519 | G39: ='0. Database'!H38 -> 30736 | H39: ='0. Database'!I38 -> 32508 | I39: ='0. Database'!J38 -> 40269 | ... S39: ='0. Database'!T38 -> 322005.86
A40: META | B40: ='0. Database'!C55 -> 1491 | C40: ='0. Database'!D55 -> 2925 | D40: ='0. Database'!E55 -> 3669 | E40: ='0. Database'!F55 -> 10188 | F40: ='0. Database'!G55 -> 18190 | G40: ='0. Database'!H55 -> 22112 | H40: ='0. Database'!I55 -> 18485 | I40: ='0. Database'!J55 -> 29146 | ... S40: ='0. Database'!T55 -> 146055.1
A41: ORCL | B41: ='0. Database'!C73 -> 10926 | C41: ='0. Database'!D73 -> 10955 | D41: ='0. Database'!E73 -> 9938 | E41: ='0. Database'!F73 -> 8901 | F41: ='0. Database'!G73 -> 9335 | G41: ='0. Database'!H73 -> 3825 | H41: ='0. Database'!I73 -> 11083 | I41: ='0. Database'!J73 -> 10135 | ... S41: ='0. Database'!T73 -> 51960.267
A43: (Capex)
A44: Company | B44: 2013A | C44: 2014A | D44: 2015A | E44: 2016A | F44: 2017A | G44: 2018A | H44: 2019A | I44: 2020A | J44: 2021A | K44: 2022A | L44: 2023A | M44: 2024A | N44: 2025E | O44: 2026E | P44: 2027E | Q44: 2028E | R44: 2029E | S44: 2030E
A45: MSFT | B45: ='0. Database'!C12 -> 4257 | C45: ='0. Database'!D12 -> 5485 | D45: ='0. Database'!E12 -> 5944 | E45: ='0. Database'!F12 -> 8343 | F45: ='0. Database'!G12 -> 8129 | G45: ='0. Database'!H12 -> 11632 | H45: ='0. Database'!I12 -> 13925 | I45: ='0. Database'!J12 -> 15441 | ... S45: ='0. Database'!T12 -> 196810
A46: AMZN | B46: ='0. Database'!C28 -> 3444 | C46: ='0. Database'!D28 -> 4893 | D46: ='0. Database'!E28 -> 5387 | E46: ='0. Database'!F28 -> 7804 | F46: ='0. Database'!G28 -> 11955 | G46: ='0. Database'!H28 -> 13427 | H46: ='0. Database'!I28 -> 16861 | I46: ='0. Database'!J28 -> 40140 | ... S46: ='0. Database'!T28 -> 224350.56
A47: GOOGL | B47: ='0. Database'!C43 -> 7358 | C47: ='0. Database'!D43 -> 10959 | D47: ='0. Database'!E43 -> 9950 | E47: ='0. Database'!F43 -> 10212 | F47: ='0. Database'!G43 -> 13184 | G47: ='0. Database'!H43 -> 25139 | H47: ='0. Database'!I43 -> 23548 | I47: ='0. Database'!J43 -> 22281 | ... S47: ='0. Database'!T43 -> 259990.25
A48: META | B48: ='0. Database'!C60 -> 1362 | C48: ='0. Database'!D60 -> 1831 | D48: ='0. Database'!E60 -> 2523 | E48: ='0. Database'!F60 -> 4491 | F48: ='0. Database'!G60 -> 6733 | G48: ='0. Database'!H60 -> 13915 | H48: ='0. Database'!I60 -> 15102 | I48: ='0. Database'!J60 -> 15163 | ... S48: ='0. Database'!T60 -> 180526.35
A49: ORCL | B49: ='0. Database'!C78 -> 650 | C49: ='0. Database'!D78 -> 580 | D49: ='0. Database'!E78 -> 1391 | E49: ='0. Database'!F78 -> 1189 | F49: ='0. Database'!G78 -> 2021 | G49: ='0. Database'!H78 -> 1736 | H49: ='0. Database'!I78 -> 1660 | I49: ='0. Database'!J78 -> 1564 | ... S49: ='0. Database'!T78 -> 77098.125
A51: C. Free Cash FlowMargin %
A52: Company | B52: 2013A | C52: 2014A | D52: 2015A | E52: 2016A | F52: 2017A | G52: 2018A | H52: 2019A | I52: 2020A | J52: 2021A | K52: 2022A | L52: 2023A | M52: 2024A | N52: 2025E | O52: 2026E | P52: 2027E | Q52: 2028E | R52: 2029E | S52: 2030E
A53: MSFT | B53: =IFERROR(B13/B29,"") -> 0.31568806 | C53: =IFERROR(C13/C29,"") -> 0.31113747 | D53: =IFERROR(D13/D29,"") -> 0.25351571 | E53: =IFERROR(E13/E29,"") -> 0.27406367 | F53: =IFERROR(F13/F29,"") -> 0.32492156 | G53: =IFERROR(G13/G29,"") -> 0.29224357 | H53: =IFERROR(H13/H29,"") -> 0.30402962 | I53: =IFERROR(I13/I29,"") -> 0.31555431 | ... S53: =IFERROR(S13/S29,"") -> 0.21883875
A54: AMZN | B54: =IFERROR(B14/B30,"") -> 0.049046124 | C54: =IFERROR(C14/C30,"") -> 0.038340481 | D54: =IFERROR(D14/D30,"") -> 0.10441389 | E54: =IFERROR(E14/E30,"") -> 0.1178041 | F54: =IFERROR(F14/F30,"") -> 0.06040901 | G54: =IFERROR(G14/G30,"") -> 0.12234908 | H54: =IFERROR(H14/H30,"") -> 0.12679405 | I54: =IFERROR(I14/I30,"") -> 0.10971636 | ... S54: =IFERROR(S14/S30,"") -> 0.28443394
A55: GOOGL | B55: =IFERROR(B15/B31,"") -> 0.20355194 | C55: =IFERROR(C15/C31,"") -> 0.17298223 | D55: =IFERROR(D15/D31,"") -> 0.27442692 | E55: =IFERROR(E15/E31,"") -> 0.28639002 | F55: =IFERROR(F15/F31,"") -> 0.2156601 | G55: =IFERROR(G15/G31,"") -> 0.16687741 | H55: =IFERROR(H15/H31,"") -> 0.1913541 | I55: =IFERROR(I15/I31,"") -> 0.23472144 | ... S55: =IFERROR(S15/S31,"") -> 0.17877654
A56: META | B56: =IFERROR(B16/B32,"") -> 0.36191565 | C56: =IFERROR(C16/C32,"") -> 0.29087117 | D56: =IFERROR(D16/D32,"") -> 0.3389112 | E56: =IFERROR(E16/E32,"") -> 0.42032709 | F56: =IFERROR(F16/F32,"") -> 0.43005436 | G56: =IFERROR(G16/G32,"") -> 0.27506358 | H56: =IFERROR(H16/H32,"") -> 0.30218246 | I56: =IFERROR(I16/I32,"") -> 0.27802796 | ... S56: =IFERROR(S16/S32,"") -> 0.21839725
A57: ORCL | B57: =IFERROR(B17/B33,"") -> 0.36508876 | C57: =IFERROR(C17/C33,"") -> 0.37468321 | D57: =IFERROR(D17/D33,"") -> 0.34502695 | E57: =IFERROR(E17/E33,"") -> 0.33730127 | F57: =IFERROR(F17/F33,"") -> 0.32084924 | G57: =IFERROR(G17/G33,"") -> 0.34659625 | H57: =IFERROR(H17/H33,"") -> 0.32630487 | I57: =IFERROR(I17/I33,"") -> 0.29627828 | ... S57: =IFERROR(S17/S33,"") -> 0.12189838
A59: D. FCF / Net Income %
A60: Company | B60: 2013A | C60: 2014A | D60: 2015A | E60: 2016A | F60: 2017A | G60: 2018A | H60: 2019A | I60: 2020A | J60: 2021A | K60: 2022A | L60: 2023A | M60: 2024A | N60: 2025E | O60: 2026E | P60: 2027E | Q60: 2028E | R60: 2029E | S60: 2030E
A61: MSFT | B61: =IFERROR(B13/B37,"") -> 1.1240909 | C61: =IFERROR(C13/C37,"") -> 1.2239286 | D61: =IFERROR(D13/D37,"") -> 1.9457066 | E61: =IFERROR(E13/E37,"") -> 1.4872009 | F61: =IFERROR(F13/F37,"") -> 1.4798151 | G61: =IFERROR(G13/G37,"") -> 1.9462917 | H61: =IFERROR(H13/H37,"") -> 0.97502548 | I61: =IFERROR(I13/I37,"") -> 1.0191504 | ... S61: =IFERROR(S13/S37,"") -> 0.59544491
A62: AMZN | B62: =IFERROR(B14/B38,"") -> 7.4124088 | C62: =IFERROR(C14/C38,"") -> -8.0871369 | D62: =IFERROR(D14/D38,"") -> 11.161074 | E62: =IFERROR(E14/E38,"") -> 3.9641501 | F62: =IFERROR(F14/F38,"") -> 2.8565062 | G62: =IFERROR(G14/G38,"") -> 1.7170654 | H62: =IFERROR(H14/H38,"") -> 1.8685709 | I62: =IFERROR(I14/I38,"") -> 1.2153204 | ... S62: =IFERROR(S14/S38,"") -> 0.91974021
A63: GOOGL | B63: =IFERROR(B15/B39,"") -> 0.92524971 | C63: =IFERROR(C15/C39,"") -> 0.81971568 | D63: =IFERROR(D15/D39,"") -> 1.3003286 | E63: =IFERROR(E15/E39,"") -> 1.3272923 | F63: =IFERROR(F15/F39,"") -> 1.0616368 | G63: =IFERROR(G15/G39,"") -> 0.74284227 | H63: =IFERROR(H15/H39,"") -> 0.95275009 | I63: =IFERROR(I15/I39,"") -> 1.0639201 | ... S63: =IFERROR(S15/S39,"") -> 0.52257605
A64: META | B64: =IFERROR(B16/B40,"") -> 1.9107981 | C64: =IFERROR(C16/C40,"") -> 1.2396581 | D64: =IFERROR(D16/D40,"") -> 1.6560371 | E64: =IFERROR(E16/E40,"") -> 1.1402631 | F64: =IFERROR(F16/F40,"") -> 0.96113249 | G64: =IFERROR(G16/G40,"") -> 0.69460022 | H64: =IFERROR(H16/H40,"") -> 1.147525 | I64: =IFERROR(I16/I40,"") -> 0.80916764 | ... S64: =IFERROR(S16/S40,"") -> 0.67120458
A65: ORCL | B65: =IFERROR(B17/B41,"") -> 1.2423577 | C65: =IFERROR(C17/C41,"") -> 1.3090826 | D65: =IFERROR(D17/D41,"") -> 1.3271282 | E65: =IFERROR(E17/E41,"") -> 1.4038872 | F65: =IFERROR(F17/F41,"") -> 1.2967327 | G65: =IFERROR(G17/G41,"") -> 3.5686275 | H65: =IFERROR(H17/H41,"") -> 1.1631327 | I65: =IFERROR(I17/I41,"") -> 1.1420819 | ... S65: =IFERROR(S17/S41,"") -> 0.52536426
A67: F. Capex/CFO %
A68: Company | B68: 2013A | C68: 2014A | D68: 2015A | E68: 2016A | F68: 2017A | G68: 2018A | H68: 2019A | I68: 2020A | J68: 2021A | K68: 2022A | L68: 2023A | M68: 2024A | N68: 2025E | O68: 2026E | P68: 2027E | Q68: 2028E | R68: 2029E | S68: 2030E
A69: MSFT | B69: =IFERROR(B45/B5,"") -> 0.14764333 | C69: =IFERROR(C45/C5,"") -> 0.16875885 | D69: =IFERROR(D45/D5,"") -> 0.20035055 | E69: =IFERROR(E45/E5,"") -> 0.25035259 | F69: =IFERROR(F45/F5,"") -> 0.205761 | G69: =IFERROR(G45/G5,"") -> 0.26506244 | H69: =IFERROR(H45/H5,"") -> 0.26683913 | I69: =IFERROR(I45/I5,"") -> 0.25448702 | ... S69: =IFERROR(S45/S5,"") -> 0.54680657
A70: AMZN | B70: =IFERROR(B46/B6,"") -> 0.6290411 | C70: =IFERROR(C46/C6,"") -> 0.71514177 | D70: =IFERROR(D46/D6,"") -> 0.44746241 | E70: =IFERROR(E46/E6,"") -> 0.45364181 | F70: =IFERROR(F46/F6,"") -> 0.65096651 | G70: =IFERROR(G46/G6,"") -> 0.43703414 | H70: =IFERROR(H46/H6,"") -> 0.43778886 | I70: =IFERROR(I46/I6,"") -> 0.60759264 | ... S70: =IFERROR(S46/S6,"") -> 0.56016158
A71: GOOGL | B71: =IFERROR(B47/B7,"") -> 0.39434053 | C71: =IFERROR(C47/C7,"") -> 0.48976582 | D71: =IFERROR(D47/D7,"") -> 0.37445431 | E71: =IFERROR(E47/E7,"") -> 0.28338328 | F71: =IFERROR(F47/F7,"") -> 0.35545011 | G71: =IFERROR(G47/G7,"") -> 0.52404578 | H71: =IFERROR(H47/H7,"") -> 0.43191489 | I71: =IFERROR(I47/I7,"") -> 0.34213193 | ... S71: =IFERROR(S47/S7,"") -> 0.55423619
A72: META | B72: =IFERROR(B48/B8,"") -> 0.32259593 | C72: =IFERROR(C48/C8,"") -> 0.33553234 | D72: =IFERROR(D48/D8,"") -> 0.29340621 | E72: =IFERROR(E48/E8,"") -> 0.27880556 | F72: =IFERROR(F48/F8,"") -> 0.27803931 | G72: =IFERROR(G48/G8,"") -> 0.47533648 | H72: =IFERROR(H48/H8,"") -> 0.41587267 | I72: =IFERROR(I48/I8,"") -> 0.39133352 | ... S72: =IFERROR(S48/S8,"") -> 0.63678123
A73: ORCL | B73: =IFERROR(B49/B9,"") -> 0.045697413 | C73: =IFERROR(C49/C9,"") -> 0.038871389 | D73: =IFERROR(D49/D9,"") -> 0.095404664 | E73: =IFERROR(E49/E9,"") -> 0.086883449 | F73: =IFERROR(F49/F9,"") -> 0.14306952 | G73: =IFERROR(G49/G9,"") -> 0.11282985 | H73: =IFERROR(H49/H9,"") -> 0.11408151 | I73: =IFERROR(I49/I9,"") -> 0.11903493 | ... S73: =IFERROR(S49/S9,"") -> 0.75154867

Sheet 4. EPS & Margins
A1: EPS、Operating IncomeMargin&Profitability (2013-2030E)
A3: A. Operating Income ($mm)
A4: Company | B4: 2013A | C4: 2014A | D4: 2015A | E4: 2016A | F4: 2017A | G4: 2018A | H4: 2019A | I4: 2020A | J4: 2021A | K4: 2022A | L4: 2023A | M4: 2024A | N4: 2025E | O4: 2026E | P4: 2027E | Q4: 2028E | R4: 2029E | S4: 2030E
A5: MSFT | B5: ='0. Database'!C6 -> 26764 | C5: ='0. Database'!D6 -> 27759 | D5: ='0. Database'!E6 -> 13359 | E5: ='0. Database'!F6 -> 11756 | F5: ='0. Database'!G6 -> 11389 | G5: ='0. Database'!H6 -> 12924 | H5: ='0. Database'!I6 -> 16219 | I5: ='0. Database'!J6 -> 18724 | ... S5: ='0. Database'!T6 -> 108509.49
A6: AMZN | B6: ='0. Database'!C22 -> 673 | C6: ='0. Database'!D22 -> 458 | D6: ='0. Database'!E22 -> 1507 | E6: ='0. Database'!F22 -> 3108 | F6: ='0. Database'!G22 -> 4331 | G6: ='0. Database'!H22 -> 7296 | H6: ='0. Database'!I22 -> 9201 | I6: ='0. Database'!J22 -> 13531 | ... S6: ='0. Database'!T22 -> 152115.05
A7: GOOGL | B7: ='0. Database'!C37 -> 16260 | C7: ='0. Database'!D37 -> 18965 | D7: ='0. Database'!E37 -> 23319 | E7: ='0. Database'!F37 -> 27055 | F7: ='0. Database'!G37 -> 32456 | G7: ='0. Database'!H37 -> 43137 | H7: ='0. Database'!I37 -> 48999 | I7: ='0. Database'!J37 -> 54606 | ... S7: ='0. Database'!T37 -> 258679.36
A8: META | B8: ='0. Database'!C54 -> 2804 | C8: ='0. Database'!D54 -> 4994 | D8: ='0. Database'!E54 -> 6225 | E8: ='0. Database'!F54 -> 12427 | F8: ='0. Database'!G54 -> 20203 | G8: ='0. Database'!H54 -> 24913 | H8: ='0. Database'!I54 -> 23986 | I8: ='0. Database'!J54 -> 32671 | ... S8: ='0. Database'!T54 -> 162052.13
A9: ORCL | B9: ='0. Database'!C72 -> 14684 | C9: ='0. Database'!D72 -> 14758 | D9: ='0. Database'!E72 -> 13870 | E9: ='0. Database'!F72 -> 12604 | F9: ='0. Database'!G72 -> 12710 | G9: ='0. Database'!H72 -> 13264 | H9: ='0. Database'!I72 -> 13535 | I9: ='0. Database'!J72 -> 13897 | ... S9: ='0. Database'!T72 -> 57952.82
A11: C. Net Income ($mm)
A12: Company | B12: 2013A | C12: 2014A | D12: 2015A | E12: 2016A | F12: 2017A | G12: 2018A | H12: 2019A | I12: 2020A | J12: 2021A | K12: 2022A | L12: 2023A | M12: 2024A | N12: 2025E | O12: 2026E | P12: 2027E | Q12: 2028E | R12: 2029E | S12: 2030E
A13: MSFT | B13: ='0. Database'!C7 -> 21863 | C13: ='0. Database'!D7 -> 22074 | D13: ='0. Database'!E7 -> 12193 | E13: ='0. Database'!F7 -> 16798 | F13: ='0. Database'!G7 -> 21204 | G13: ='0. Database'!H7 -> 16571 | H13: ='0. Database'!I7 -> 39240 | I13: ='0. Database'!J7 -> 44281 | ... S13: ='0. Database'!T7 -> 231003.5
A14: AMZN | B14: ='0. Database'!C23 -> 274 | C14: ='0. Database'!D23 -> -241 | D14: ='0. Database'!E23 -> 596 | E14: ='0. Database'!F23 -> 2371 | F14: ='0. Database'!G23 -> 2244 | G14: ='0. Database'!H23 -> 10073 | H14: ='0. Database'!I23 -> 11588 | I14: ='0. Database'!J23 -> 21331 | ... S14: ='0. Database'!T23 -> 199614.81
A15: GOOGL | B15: ='0. Database'!C38 -> 12214 | C15: ='0. Database'!D38 -> 13928 | D15: ='0. Database'!E38 -> 15826 | E15: ='0. Database'!F38 -> 19478 | F15: ='0. Database'!G38 -> 22519 | G15: ='0. Database'!H38 -> 30736 | H15: ='0. Database'!I38 -> 32508 | I15: ='0. Database'!J38 -> 40269 | ... S15: ='0. Database'!T38 -> 322005.86
A16: META | B16: ='0. Database'!C55 -> 1491 | C16: ='0. Database'!D55 -> 2925 | D16: ='0. Database'!E55 -> 3669 | E16: ='0. Database'!F55 -> 10188 | F16: ='0. Database'!G55 -> 18190 | G16: ='0. Database'!H55 -> 22112 | H16: ='0. Database'!I55 -> 18485 | I16: ='0. Database'!J55 -> 29146 | ... S16: ='0. Database'!T55 -> 146055.1
A17: ORCL | B17: ='0. Database'!C73 -> 10926 | C17: ='0. Database'!D73 -> 10955 | D17: ='0. Database'!E73 -> 9938 | E17: ='0. Database'!F73 -> 8901 | F17: ='0. Database'!G73 -> 9335 | G17: ='0. Database'!H73 -> 3825 | H17: ='0. Database'!I73 -> 11083 | I17: ='0. Database'!J73 -> 10135 | ... S17: ='0. Database'!T73 -> 51960.267
A19: E. EPS ($)
A20: Company | B20: 2013A | C20: 2014A | D20: 2015A | E20: 2016A | F20: 2017A | G20: 2018A | H20: 2019A | I20: 2020A | J20: 2021A | K20: 2022A | L20: 2023A | M20: 2024A | N20: 2025E | O20: 2026E | P20: 2027E | Q20: 2028E | R20: 2029E | S20: 2030E
A21: MSFT | B21: ='0. Database'!C8 -> 2.58 | C21: ='0. Database'!D8 -> 2.63 | D21: ='0. Database'!E8 -> 1.48 | E21: ='0. Database'!F8 -> 2.1 | F21: ='0. Database'!G8 -> 2.71 | G21: ='0. Database'!H8 -> 2.13 | H21: ='0. Database'!I8 -> 5.06 | I21: ='0. Database'!J8 -> 5.76 | ... S21: ='0. Database'!T8 -> 31.4925
A22: AMZN | B22: ='0. Database'!C24 -> 0.0295 | C22: ='0. Database'!D24 -> -0.026 | D22: ='0. Database'!E24 -> 0.0625 | E22: ='0. Database'!F24 -> 0.245 | F22: ='0. Database'!G24 -> 0.2275 | G22: ='0. Database'!H24 -> 1.007 | H22: ='0. Database'!I24 -> 1.1505 | I22: ='0. Database'!J24 -> 2.0915 | ... S22: ='0. Database'!T24 -> 17.133333
A23: GOOGL | B23: ='0. Database'!C39 -> 0.90125 | C23: ='0. Database'!D39 -> 1.0135 | D23: ='0. Database'!E39 -> 1.142 | E23: ='0. Database'!F39 -> 1.3925 | F23: ='0. Database'!G39 -> 1.6005 | G23: ='0. Database'!H39 -> 2.185 | H23: ='0. Database'!I39 -> 2.3265 | I23: ='0. Database'!J39 -> 2.9305 | ... S23: ='0. Database'!T39 -> 26.035714
A24: META | B24: ='0. Database'!C56 -> 0.6 | C24: ='0. Database'!D56 -> 1.1 | D24: ='0. Database'!E56 -> 1.29 | E24: ='0. Database'!F56 -> 3.49 | F24: ='0. Database'!G56 -> 6.16 | G24: ='0. Database'!H56 -> 7.57 | H24: ='0. Database'!I56 -> 8.56 | I24: ='0. Database'!J56 -> 9.78 | ... S24: ='0. Database'!T56 -> 56.996875
A25: ORCL | B25: ='0. Database'!C74 -> 2.26 | C25: ='0. Database'!D74 -> 2.38 | D25: ='0. Database'!E74 -> 2.21 | E25: ='0. Database'!F74 -> 2.07 | F25: ='0. Database'!G74 -> 2.21 | G25: ='0. Database'!H74 -> 0.9 | H25: ='0. Database'!I74 -> 2.97 | I25: ='0. Database'!J74 -> 3.08 | ... S25: ='0. Database'!T74 -> 16.756
A27: G. Diluted Shares (mm)
A28: Company | B28: 2013A | C28: 2014A | D28: 2015A | E28: 2016A | F28: 2017A | G28: 2018A | H28: 2019A | I28: 2020A | J28: 2021A | K28: 2022A | L28: 2023A | M28: 2024A | N28: 2025E | O28: 2026E | P28: 2027E | Q28: 2028E | R28: 2029E | S28: 2030E
A29: MSFT | B29: ='0. Database'!C9 -> 8470 | C29: ='0. Database'!D9 -> 8399 | D29: ='0. Database'!E9 -> 8254 | E29: ='0. Database'!F9 -> 8013 | F29: ='0. Database'!G9 -> 7832 | G29: ='0. Database'!H9 -> 7794 | H29: ='0. Database'!I9 -> 7753 | I29: ='0. Database'!J9 -> 7683 | ... S29: ='0. Database'!T9 -> 7366.4511
A30: AMZN | B30: ='0. Database'!C25 -> 9300 | C30: ='0. Database'!D25 -> 9240 | D30: ='0. Database'!E25 -> 9540 | E30: ='0. Database'!F25 -> 9680 | F30: ='0. Database'!G25 -> 9860 | G30: ='0. Database'!H25 -> 10000 | H30: ='0. Database'!I25 -> 10080 | I30: ='0. Database'!J25 -> 10200 | ... S30: ='0. Database'!T25 -> 11236.528
A31: GOOGL | B31: ='0. Database'!C40 -> 14739.044 | C31: ='0. Database'!D40 -> 14839.96 | D31: ='0. Database'!E40 -> 14893.5 | E31: ='0. Database'!F40 -> 14951.3 | F31: ='0. Database'!G40 -> 15014.6 | G31: ='0. Database'!H40 -> 15002.98 | H31: ='0. Database'!I40 -> 14901.66 | I31: ='0. Database'!J40 -> 14664.2 | ... S31: ='0. Database'!T40 -> 12302.528
A32: META | B32: ='0. Database'!C57 -> 2517 | C32: ='0. Database'!D57 -> 2664 | D32: ='0. Database'!E57 -> 2853 | E32: ='0. Database'!F57 -> 2925 | F32: ='0. Database'!G57 -> 2956 | G32: ='0. Database'!H57 -> 2921 | H32: ='0. Database'!I57 -> 2876 | I32: ='0. Database'!J57 -> 2888 | ... S32: ='0. Database'!T57 -> 2611.4238
A33: ORCL | B33: ='0. Database'!C75 -> 4844 | C33: ='0. Database'!D75 -> 4604 | D33: ='0. Database'!E75 -> 4503 | E33: ='0. Database'!F75 -> 4305 | F33: ='0. Database'!G75 -> 4217 | G33: ='0. Database'!H75 -> 4238 | H33: ='0. Database'!I75 -> 3732 | I33: ='0. Database'!J75 -> 3294 | ... S33: ='0. Database'!T75 -> 3102.7389
A35: H. SBC ($mm)
A36: Company | B36: 2013A | C36: 2014A | D36: 2015A | E36: 2016A | F36: 2017A | G36: 2018A | H36: 2019A | I36: 2020A | J36: 2021A | K36: 2022A | L36: 2023A | M36: 2024A | N36: 2025E | O36: 2026E | P36: 2027E | Q36: 2028E | R36: 2029E | S36: 2030E
A37: MSFT | B37: ='0. Database'!C10 -> 2197 | C37: ='0. Database'!D10 -> 2446 | D37: ='0. Database'!E10 -> 2574 | E37: ='0. Database'!F10 -> 2668 | F37: ='0. Database'!G10 -> 3266 | G37: ='0. Database'!H10 -> 3940 | H37: ='0. Database'!I10 -> 4652 | I37: ='0. Database'!J10 -> 5289 | ... S37: ='0. Database'!T10 -> 21162.66
A38: AMZN | B38: ='0. Database'!C26 -> 1056 | C38: ='0. Database'!D26 -> 1491 | D38: ='0. Database'!E26 -> 2119 | E38: ='0. Database'!F26 -> 2975 | F38: ='0. Database'!G26 -> 4215 | G38: ='0. Database'!H26 -> 5418 | H38: ='0. Database'!I26 -> 6864 | I38: ='0. Database'!J26 -> 9208 | ... S38: ='0. Database'!T26 -> 31047.394
A39: GOOGL | B39: ='0. Database'!C41 -> -3268 | C39: ='0. Database'!D41 -> -4175 | D39: ='0. Database'!E41 -> -4903 | E39: ='0. Database'!F41 -> -6703 | F39: ='0. Database'!G41 -> -7679 | G39: ='0. Database'!H41 -> -9353 | H39: ='0. Database'!I41 -> -10794 | I39: ='0. Database'!J41 -> -12991 | ... S39: ='0. Database'!T41 -> -35339.95
A40: META | B40: ='0. Database'!C58 -> -906 | C40: ='0. Database'!D58 -> -1837 | D40: ='0. Database'!E58 -> -2969 | E40: ='0. Database'!F58 -> -3202 | F40: ='0. Database'!G58 -> -3723 | G40: ='0. Database'!H58 -> -4152 | H40: ='0. Database'!I58 -> -4835 | I40: ='0. Database'!J58 -> -6536 | ... S40: ='0. Database'!T58 -> -28834.48
A41: ORCL | B41: ='0. Database'!C76 -> 755 | C41: ='0. Database'!D76 -> 805 | D41: ='0. Database'!E76 -> 933 | E41: ='0. Database'!F76 -> 1037 | F41: ='0. Database'!G76 -> 1350 | G41: ='0. Database'!H76 -> 1607 | H41: ='0. Database'!I76 -> 1653 | I41: ='0. Database'!J76 -> 1590 | ... S41: ='0. Database'!T76 -> 11212.32
A43: (Revenue)
A44: Company | B44: 2013A | C44: 2014A | D44: 2015A | E44: 2016A | F44: 2017A | G44: 2018A | H44: 2019A | I44: 2020A | J44: 2021A | K44: 2022A | L44: 2023A | M44: 2024A | N44: 2025E | O44: 2026E | P44: 2027E | Q44: 2028E | R44: 2029E | S44: 2030E
A45: MSFT | B45: ='0. Database'!C5 -> 77849 | C45: ='0. Database'!D5 -> 86833 | D45: ='0. Database'!E5 -> 93580 | E45: ='0. Database'!F5 -> 91154 | F45: ='0. Database'!G5 -> 96571 | G45: ='0. Database'!H5 -> 110360 | H45: ='0. Database'!I5 -> 125843 | I45: ='0. Database'!J5 -> 143015 | ... S45: ='0. Database'!T5 -> 628544.33
A46: AMZN | B46: ='0. Database'!C21 -> 41410 | C46: ='0. Database'!D21 -> 50834 | D46: ='0. Database'!E21 -> 63708 | E46: ='0. Database'!F21 -> 79785 | F46: ='0. Database'!G21 -> 106110 | G46: ='0. Database'!H21 -> 141366 | H46: ='0. Database'!I21 -> 170773 | I46: ='0. Database'!J21 -> 236282 | ... S46: ='0. Database'!T21 -> 645470.67
A47: GOOGL | B47: ='0. Database'!C36 -> 55519 | C47: ='0. Database'!D36 -> 66001 | D47: ='0. Database'!E36 -> 74989 | E47: ='0. Database'!F36 -> 90272 | F47: ='0. Database'!G36 -> 110855 | G47: ='0. Database'!H36 -> 136819 | H47: ='0. Database'!I36 -> 161857 | I47: ='0. Database'!J36 -> 182527 | ... S47: ='0. Database'!T36 -> 941245.16
A48: META | B48: ='0. Database'!C53 -> 7872 | C48: ='0. Database'!D53 -> 12466 | D48: ='0. Database'!E53 -> 17928 | E48: ='0. Database'!F53 -> 27638 | F48: ='0. Database'!G53 -> 40653 | G48: ='0. Database'!H53 -> 55838 | H48: ='0. Database'!I53 -> 70196 | I48: ='0. Database'!J53 -> 84826 | ... S48: ='0. Database'!T53 -> 448874.02
A49: ORCL | B49: ='0. Database'!C71 -> 37180 | C49: ='0. Database'!D71 -> 38275 | D49: ='0. Database'!E71 -> 38226 | E49: ='0. Database'!F71 -> 37047 | F49: ='0. Database'!G71 -> 37728 | G49: ='0. Database'!H71 -> 39383 | H49: ='0. Database'!I71 -> 39506 | I49: ='0. Database'!J71 -> 39068 | ... S49: ='0. Database'!T71 -> 223941.18
A51: B. Operating IncomeMargin %
A52: Company | B52: 2013A | C52: 2014A | D52: 2015A | E52: 2016A | F52: 2017A | G52: 2018A | H52: 2019A | I52: 2020A | J52: 2021A | K52: 2022A | L52: 2023A | M52: 2024A | N52: 2025E | O52: 2026E | P52: 2027E | Q52: 2028E | R52: 2029E | S52: 2030E
A53: MSFT | B53: =IFERROR(B5/B45,"") -> 0.34379375 | C53: =IFERROR(C5/C45,"") -> 0.31968261 | D53: =IFERROR(D5/D45,"") -> 0.14275486 | E53: =IFERROR(E5/E45,"") -> 0.12896856 | F53: =IFERROR(F5/F45,"") -> 0.11793396 | G53: =IFERROR(G5/G45,"") -> 0.11710765 | H53: =IFERROR(H5/H45,"") -> 0.12888281 | I53: =IFERROR(I5/I45,"") -> 0.13092333 | ... S53: =IFERROR(S5/S45,"") -> 0.17263618
A54: AMZN | B54: =IFERROR(B6/B46,"") -> 0.016252113 | C54: =IFERROR(C6/C46,"") -> 0.0090097179 | D54: =IFERROR(D6/D46,"") -> 0.0236548 | E54: =IFERROR(E6/E46,"") -> 0.038954691 | F54: =IFERROR(F6/F46,"") -> 0.040816134 | G54: =IFERROR(G6/G46,"") -> 0.051610713 | H54: =IFERROR(H6/H46,"") -> 0.053878541 | I54: =IFERROR(I6/I46,"") -> 0.057266317 | ... S54: =IFERROR(S6/S46,"") -> 0.23566532
A55: GOOGL | B55: =IFERROR(B7/B47,"") -> 0.29287271 | C55: =IFERROR(C7/C47,"") -> 0.28734413 | D55: =IFERROR(D7/D47,"") -> 0.31096561 | E55: =IFERROR(E7/E47,"") -> 0.29970533 | F55: =IFERROR(F7/F47,"") -> 0.29277886 | G55: =IFERROR(G7/G47,"") -> 0.31528516 | H55: =IFERROR(H7/H47,"") -> 0.30273019 | I55: =IFERROR(I7/I47,"") -> 0.2991667 | ... S55: =IFERROR(S7/S47,"") -> 0.27482676
A56: META | B56: =IFERROR(B8/B48,"") -> 0.35619919 | C56: =IFERROR(C8/C48,"") -> 0.40060966 | D56: =IFERROR(D8/D48,"") -> 0.34722222 | E56: =IFERROR(E8/E48,"") -> 0.44963456 | F56: =IFERROR(F8/F48,"") -> 0.49696209 | G56: =IFERROR(G8/G48,"") -> 0.44616569 | H56: =IFERROR(H8/H48,"") -> 0.34170038 | I56: =IFERROR(I8/I48,"") -> 0.38515314 | ... S56: =IFERROR(S8/S48,"") -> 0.36101918
A57: ORCL | B57: =IFERROR(B9/B49,"") -> 0.39494352 | C57: =IFERROR(C9/C49,"") -> 0.38557805 | D57: =IFERROR(D9/D49,"") -> 0.36284204 | E57: =IFERROR(E9/E49,"") -> 0.34021648 | F57: =IFERROR(F9/F49,"") -> 0.33688507 | G57: =IFERROR(G9/G49,"") -> 0.33679506 | H57: =IFERROR(H9/H49,"") -> 0.34260619 | I57: =IFERROR(I9/I49,"") -> 0.35571312 | ... S57: =IFERROR(S9/S49,"") -> 0.2587859
A59: D. Net Margin %
A60: Company | B60: 2013A | C60: 2014A | D60: 2015A | E60: 2016A | F60: 2017A | G60: 2018A | H60: 2019A | I60: 2020A | J60: 2021A | K60: 2022A | L60: 2023A | M60: 2024A | N60: 2025E | O60: 2026E | P60: 2027E | Q60: 2028E | R60: 2029E | S60: 2030E
A61: MSFT | B61: =IFERROR(B13/B45,"") -> 0.28083855 | C61: =IFERROR(C13/C45,"") -> 0.25421211 | D61: =IFERROR(D13/D45,"") -> 0.13029493 | E61: =IFERROR(E13/E45,"") -> 0.18428155 | F61: =IFERROR(F13/F45,"") -> 0.21956902 | G61: =IFERROR(G13/G45,"") -> 0.15015404 | H61: =IFERROR(H13/H45,"") -> 0.31181711 | I61: =IFERROR(I13/I45,"") -> 0.30962486 | ... S61: =IFERROR(S13/S45,"") -> 0.36752141
A62: AMZN | B62: =IFERROR(B14/B46,"") -> 0.0066167592 | C62: =IFERROR(C14/C46,"") -> -0.0047409214 | D62: =IFERROR(D14/D46,"") -> 0.009355183 | E62: =IFERROR(E14/E46,"") -> 0.029717365 | F62: =IFERROR(F14/F46,"") -> 0.021147865 | G62: =IFERROR(G14/G46,"") -> 0.071254757 | H62: =IFERROR(H14/H46,"") -> 0.06785616 | I62: =IFERROR(I14/I46,"") -> 0.090277719 | ... S62: =IFERROR(S14/S46,"") -> 0.30925466
A63: GOOGL | B63: =IFERROR(B15/B47,"") -> 0.21999676 | C63: =IFERROR(C15/C47,"") -> 0.21102711 | D63: =IFERROR(D15/D47,"") -> 0.21104429 | E63: =IFERROR(E15/E47,"") -> 0.21577012 | F63: =IFERROR(F15/F47,"") -> 0.20313924 | G63: =IFERROR(G15/G47,"") -> 0.22464716 | H63: =IFERROR(H15/H47,"") -> 0.20084395 | I63: =IFERROR(I15/I47,"") -> 0.22061942 | ... S63: =IFERROR(S15/S47,"") -> 0.34210626
A64: META | B64: =IFERROR(B16/B48,"") -> 0.18940549 | C64: =IFERROR(C16/C48,"") -> 0.23463822 | D64: =IFERROR(D16/D48,"") -> 0.20465194 | E64: =IFERROR(E16/E48,"") -> 0.36862291 | F64: =IFERROR(F16/F48,"") -> 0.44744545 | G64: =IFERROR(G16/G48,"") -> 0.39600272 | H64: =IFERROR(H16/H48,"") -> 0.26333409 | I64: =IFERROR(I16/I48,"") -> 0.34359748 | ... S64: =IFERROR(S16/S48,"") -> 0.32538105
A65: ORCL | B65: =IFERROR(B17/B49,"") -> 0.29386767 | C65: =IFERROR(C17/C49,"") -> 0.28621816 | D65: =IFERROR(D17/D49,"") -> 0.25998012 | E65: =IFERROR(E17/E49,"") -> 0.24026237 | F65: =IFERROR(F17/F49,"") -> 0.24742897 | G65: =IFERROR(G17/G49,"") -> 0.097123124 | H65: =IFERROR(H17/H49,"") -> 0.28053966 | I65: =IFERROR(I17/I49,"") -> 0.25941947 | ... S65: =IFERROR(S17/S49,"") -> 0.2320264
A67: F. EPSYoY %
A68: Company | B68: 2013A | C68: 2014A | D68: 2015A | E68: 2016A | F68: 2017A | G68: 2018A | H68: 2019A | I68: 2020A | J68: 2021A | K68: 2022A | L68: 2023A | M68: 2024A | N68: 2025E | O68: 2026E | P68: 2027E | Q68: 2028E | R68: 2029E | S68: 2030E
A69: MSFT | C69: =IFERROR(C21/B21-1,"") -> 0.019379845 | D69: =IFERROR(D21/C21-1,"") -> -0.43726236 | E69: =IFERROR(E21/D21-1,"") -> 0.41891892 | F69: =IFERROR(F21/E21-1,"") -> 0.29047619 | G69: =IFERROR(G21/F21-1,"") -> -0.21402214 | H69: =IFERROR(H21/G21-1,"") -> 1.3755869 | I69: =IFERROR(I21/H21-1,"") -> 0.13833992 | J69: =IFERROR(J21/I21-1,"") -> 0.39756944 | ... S69: =IFERROR(S21/R21-1,"") -> 0.16652183
A70: AMZN | C70: =IFERROR(C22/B22-1,"") -> -1.8813559 | D70: =IFERROR(D22/C22-1,"") -> -3.4038462 | E70: =IFERROR(E22/D22-1,"") -> 2.92 | F70: =IFERROR(F22/E22-1,"") -> -0.071428571 | G70: =IFERROR(G22/F22-1,"") -> 3.4263736 | H70: =IFERROR(H22/G22-1,"") -> 0.14250248 | I70: =IFERROR(I22/H22-1,"") -> 0.81790526 | J70: =IFERROR(J22/I22-1,"") -> 0.11602905 | ... S70: =IFERROR(S22/R22-1,"") -> 0.19456593
A71: GOOGL | C71: =IFERROR(C23/B23-1,"") -> 0.12454924 | D71: =IFERROR(D23/C23-1,"") -> 0.12678836 | E71: =IFERROR(E23/D23-1,"") -> 0.21935201 | F71: =IFERROR(F23/E23-1,"") -> 0.14937163 | G71: =IFERROR(G23/F23-1,"") -> 0.36519838 | H71: =IFERROR(H23/G23-1,"") -> 0.064759725 | I71: =IFERROR(I23/H23-1,"") -> 0.25961745 | J71: =IFERROR(J23/I23-1,"") -> 0.91434909 | ... S71: =IFERROR(S23/R23-1,"") -> 0.22532541
A72: META | C72: =IFERROR(C24/B24-1,"") -> 0.83333333 | D72: =IFERROR(D24/C24-1,"") -> 0.17272727 | E72: =IFERROR(E24/D24-1,"") -> 1.7054264 | F72: =IFERROR(F24/E24-1,"") -> 0.76504298 | G72: =IFERROR(G24/F24-1,"") -> 0.2288961 | H72: =IFERROR(H24/G24-1,"") -> 0.13077939 | I72: =IFERROR(I24/H24-1,"") -> 0.14252336 | J72: =IFERROR(J24/I24-1,"") -> 0.40797546 | ... S72: =IFERROR(S24/R24-1,"") -> 0.17220769
A73: ORCL | C73: =IFERROR(C25/B25-1,"") -> 0.053097345 | D73: =IFERROR(D25/C25-1,"") -> -0.071428571 | E73: =IFERROR(E25/D25-1,"") -> -0.063348416 | F73: =IFERROR(F25/E25-1,"") -> 0.06763285 | G73: =IFERROR(G25/F25-1,"") -> -0.59276018 | H73: =IFERROR(H25/G25-1,"") -> 2.3 | I73: =IFERROR(I25/H25-1,"") -> 0.037037037 | J73: =IFERROR(J25/I25-1,"") -> 0.47727273 | ... S73: =IFERROR(S25/R25-1,"") -> 0.29948136

Sheet 5. Depreciation Sensitivity
A1: Depreciation Sensitivity: IT Useful Life Compression Impact on EPS
A4: A. IT Equipment Share Estimation: MSFT Hard Data + Other Companies from 10-K Filings
A5: Company | B5: IT Equipment % of PP&E | C5: Estimation Basis (Source) | D5: IT Useful Life (yr) | E5: Buildings % of PP&E | F5: Building Life (yr) | G5: Other % of PP&E | H5: Other Life (yr)
A6: MSFT | B6: 0.59 | C6: 10-K/Model: IT equip = 59% of capex (FY2026E). Useful life: 6yr SL. | D6: 6 | E6: 0.34 | F6: 15 | G6: 0.07 | H6: 10
A7: AMZN | B7: 0.37 | C7: 10-K Note 3 (CY2025): Servers & networking $172B / $462B in-service (ex-CIP) = 37%. Heavy equip (logistics) = 14%. Life: 5-6yr. | D7: 5.5 | E7: 0.34 | F7: 30 | G7: 0.29 | H7: 8
A8: GOOGL | B8: 0.46 | C8: 10-K: Tech infra $203.7B / $266.5B in-service = 76%. 60% of tech infra = servers. → 76%×60% = 46% of total PP&E. | D8: 6 | E8: 0.31 | F8: 30 | G8: 0.23 | H8: 10
A9: META | B9: 0.54 | C9: 10-K Note 6 (Q1'26): Servers $106B / $195B in-service (ex-CIP) = 54%. Life: 5-5.5yr. Server D&A = 74% of total. | D9: 5.5 | E9: 0.3 | F9: 27 | G9: 0.16 | H9: 10
A10: ORCL | B10: 0.71 | C10: 10-K Note 5: Computer/network $30.3B/$42.9B ex-CIP = 71%. 10-Q: PP&E net doubled to $83.6B in 9mo. Capex 9mo=$39.2B. | D10: 5 | E10: 0.25 | F10: 25 | G10: 0.01 | H10: 10
A13: B. 2026E Base Data (from Database) + Gross PP&E (from 10-K filings)
A14: Company | B14: 2026E Capex ($mm) | C14: 2026E D&A ($mm) | D14: 2026E NI ($mm) | E14: 2026E EPS ($) | F14: Shares (mm) | G14: Tax Rate (Editable) | H14: 2026E Gross PP&E ($mm, Bloomberg) | I14: Current IT Life (yr) | J14: IT Share of D&A | K14: 2027E NI ($mm) | L14: 2027E EPS ($)
A15: MSFT | B15: ='0. Database'!P12 -> 117213.77 | C15: ='0. Database'!P11 -> 42005.109 | D15: ='0. Database'!P7 -> 128773.53 | E15: ='0. Database'!P8 -> 17.280667 | F15: ='0. Database'!P9 -> 7449.9017 | G15: 0.18 | H15: 439440 | I15: 6 | J15: 0.69 | K15: ='0. Database'!Q7 -> 144093.73 | L15: ='0. Database'!Q8 -> 19.417143
A16: AMZN | B16: ='0. Database'!P28 -> 199073.7 | C16: ='0. Database'!P27 -> 84391.581 | D16: ='0. Database'!P23 -> 95381.37 | E16: ='0. Database'!P24 -> 8.7931915 | F16: ='0. Database'!P25 -> 10899.309 | G16: 0.2 | H16: 732526 | I16: 5.5 | J16: 0.61 | K16: ='0. Database'!Q23 -> 109556.18 | L16: ='0. Database'!Q24 -> 10.028182
A17: GOOGL | B17: ='0. Database'!P43 -> 186454.02 | C17: ='0. Database'!P42 -> 42874.7 | D17: ='0. Database'!P38 -> 174612.84 | E17: ='0. Database'!P39 -> 14.186724 | F17: ='0. Database'!P40 -> 12208.564 | G17: 0.16 | H17: 380000 | I17: 6 | J17: 0.7 | K17: ='0. Database'!Q38 -> 180090.27 | L17: ='0. Database'!Q39 -> 14.69
A18: META | B18: ='0. Database'!P60 -> 134391.33 | C18: ='0. Database'!P59 -> 29596.548 | D18: ='0. Database'!P55 -> 83760.967 | E18: ='0. Database'!P56 -> 32.200161 | F18: ='0. Database'!P57 -> 2561.9327 | G18: 0.13 | H18: 361870 | I18: 5.25 | J18: 0.8 | K18: ='0. Database'!Q55 -> 89664.31 | L18: ='0. Database'!Q56 -> 34.904068
A19: ORCL | B19: ='0. Database'!P78 -> 50345.517 | C19: ='0. Database'!P77 -> 9142.317 | D19: ='0. Database'!P73 -> 17201.059 | E19: ='0. Database'!P87 -> 5.8483871 | F19: ='0. Database'!P75 -> 2920.2401 | G19: 0.2 | H19: 118000 | I19: 5 | J19: 0.92 | K19: ='0. Database'!Q73 -> 18923.588 | L19: ='0. Database'!Q74 -> 6.26125
A22: C. Core Sensitivity: Compress IT Equipment Useful Life (Buildings/Other Unchanged)
A23: New D&A = Gross PP&E × IT% / new_life + Gross PP&E × Bldg% / bldg_life + Gross PP&E × Other% / other_life. Delta vs current D&A flows through to NI and EPS.
A24: IT Equipment Life = 6 Years (Buildings/Other Unchanged)
A25: Company | B25: IT New D&A ($mm) | C25: Building D&A ($mm) | D25: New Total D&A ($mm) | E25: Current D&A ($mm) | F25: Delta D&A ($mm) | G25: Delta After-Tax ($mm) | H25: Adj NI ($mm) | I25: Adj EPS ($) | J25: EPS Change %
A26: MSFT | B26: =$C$15*$J$15*($I$15/6) -> 28983.525 | C26: =$C$15*(1-$J$15) -> 13021.584 | D26: =B26+C26 -> 42005.109 | E26: =$C$15 -> 42005.109 | F26: =D26-E26 -> 0 | G26: =F26*(1-$G$15) -> 0 | H26: =$D$15-G26 -> 128773.53 | I26: =H26/$F$15 -> 17.285266 | J26: =IFERROR(I26/$E$15-1,"") -> 0.00026613226
A27: AMZN | B27: =$C$16*$J$16*($I$16/6) -> 47188.959 | C27: =$C$16*(1-$J$16) -> 32912.716 | D27: =B27+C27 -> 80101.675 | E27: =$C$16 -> 84391.581 | F27: =D27-E27 -> -4289.9053 | G27: =F27*(1-$G$16) -> -3431.9243 | H27: =$D$16-G27 -> 98813.294 | I27: =H27/$F$16 -> 9.0660143 | J27: =IFERROR(I27/$E$16-1,"") -> 0.031026598
A28: GOOGL | B28: =$C$17*$J$17*($I$17/6) -> 30012.29 | C28: =$C$17*(1-$J$17) -> 12862.41 | D28: =B28+C28 -> 42874.7 | E28: =$C$17 -> 42874.7 | F28: =D28-E28 -> 0 | G28: =F28*(1-$G$17) -> 0 | H28: =$D$17-G28 -> 174612.84 | I28: =H28/$F$17 -> 14.302488 | J28: =IFERROR(I28/$E$17-1,"") -> 0.0081600075
A29: META | B29: =$C$18*$J$18*($I$18/6) -> 20717.583 | C29: =$C$18*(1-$J$18) -> 5919.3095 | D29: =B29+C29 -> 26636.893 | E29: =$C$18 -> 29596.548 | F29: =D29-E29 -> -2959.6548 | G29: =F29*(1-$G$18) -> -2574.8996 | H29: =$D$18-G29 -> 86335.867 | I29: =H29/$F$18 -> 33.699506 | J29: =IFERROR(I29/$E$18-1,"") -> 0.04656326
A30: ORCL | B30: =$C$19*$J$19*($I$19/6) -> 7009.1097 | C30: =$C$19*(1-$J$19) -> 731.38536 | D30: =B30+C30 -> 7740.4951 | E30: =$C$19 -> 9142.317 | F30: =D30-E30 -> -1401.8219 | G30: =F30*(1-$G$19) -> -1121.4576 | H30: =$D$19-G30 -> 18322.516 | I30: =H30/$F$19 -> 6.2743184 | J30: =IFERROR(I30/$E$19-1,"") -> 0.072828854
A32: IT Equipment Life = 5 Years (Buildings/Other Unchanged)
A33: Company | B33: IT New D&A ($mm) | C33: Building D&A ($mm) | D33: New Total D&A ($mm) | E33: Current D&A ($mm) | F33: Delta D&A ($mm) | G33: Delta After-Tax ($mm) | H33: Adj NI ($mm) | I33: Adj EPS ($) | J33: EPS Change %
A34: MSFT | B34: =$C$15*$J$15*($I$15/5) -> 34780.23 | C34: =$C$15*(1-$J$15) -> 13021.584 | D34: =B34+C34 -> 47801.814 | E34: =$C$15 -> 42005.109 | F34: =D34-E34 -> 5796.705 | G34: =F34*(1-$G$15) -> 4753.2981 | H34: =$D$15-G34 -> 124020.23 | I34: =H34/$F$15 -> 16.647231 | J34: =IFERROR(I34/$E$15-1,"") -> -0.036655766
A35: AMZN | B35: =$C$16*$J$16*($I$16/5) -> 56626.751 | C35: =$C$16*(1-$J$16) -> 32912.716 | D35: =B35+C35 -> 89539.467 | E35: =$C$16 -> 84391.581 | F35: =D35-E35 -> 5147.8864 | G35: =F35*(1-$G$16) -> 4118.3091 | H35: =$D$16-G35 -> 91263.06 | I35: =H35/$F$16 -> 8.3732884 | J35: =IFERROR(I35/$E$16-1,"") -> -0.047753201
A36: GOOGL | B36: =$C$17*$J$17*($I$17/5) -> 36014.748 | C36: =$C$17*(1-$J$17) -> 12862.41 | D36: =B36+C36 -> 48877.158 | E36: =$C$17 -> 42874.7 | F36: =D36-E36 -> 6002.458 | G36: =F36*(1-$G$17) -> 5042.0647 | H36: =$D$17-G36 -> 169570.78 | I36: =H36/$F$17 -> 13.889494 | J36: =IFERROR(I36/$E$17-1,"") -> -0.020951299
A37: META | B37: =$C$18*$J$18*($I$18/5) -> 24861.1 | C37: =$C$18*(1-$J$18) -> 5919.3095 | D37: =B37+C37 -> 30780.409 | E37: =$C$18 -> 29596.548 | F37: =D37-E37 -> 1183.8619 | G37: =F37*(1-$G$18) -> 1029.9599 | H37: =$D$18-G37 -> 82731.007 | I37: =H37/$F$18 -> 32.29242 | J37: =IFERROR(I37/$E$18-1,"") -> 0.0028651577
A38: ORCL | B38: =$C$19*$J$19*($I$19/5) -> 8410.9317 | C38: =$C$19*(1-$J$19) -> 731.38536 | D38: =B38+C38 -> 9142.317 | E38: =$C$19 -> 9142.317 | F38: =D38-E38 -> 0 | G38: =F38*(1-$G$19) -> 0 | H38: =$D$19-G38 -> 17201.059 | I38: =H38/$F$19 -> 5.8902892 | J38: =IFERROR(I38/$E$19-1,"") -> 0.0071647282
A40: IT Equipment Life = 4 Years (Buildings/Other Unchanged)
A41: Company | B41: IT New D&A ($mm) | C41: Building D&A ($mm) | D41: New Total D&A ($mm) | E41: Current D&A ($mm) | F41: Delta D&A ($mm) | G41: Delta After-Tax ($mm) | H41: Adj NI ($mm) | I41: Adj EPS ($) | J41: EPS Change %
A42: MSFT | B42: =$C$15*$J$15*($I$15/4) -> 43475.288 | C42: =$C$15*(1-$J$15) -> 13021.584 | D42: =B42+C42 -> 56496.872 | E42: =$C$15 -> 42005.109 | F42: =D42-E42 -> 14491.763 | G42: =F42*(1-$G$15) -> 11883.245 | H42: =$D$15-G42 -> 116890.28 | I42: =H42/$F$15 -> 15.690178 | J42: =IFERROR(I42/$E$15-1,"") -> -0.092038613
A43: AMZN | B43: =$C$16*$J$16*($I$16/4) -> 70783.438 | C43: =$C$16*(1-$J$16) -> 32912.716 | D43: =B43+C43 -> 103696.15 | E43: =$C$16 -> 84391.581 | F43: =D43-E43 -> 19304.574 | G43: =F43*(1-$G$16) -> 15443.659 | H43: =$D$16-G43 -> 79937.71 | I43: =H43/$F$16 -> 7.3341997 | J43: =IFERROR(I43/$E$16-1,"") -> -0.1659229
A44: GOOGL | B44: =$C$17*$J$17*($I$17/4) -> 45018.435 | C44: =$C$17*(1-$J$17) -> 12862.41 | D44: =B44+C44 -> 57880.845 | E44: =$C$17 -> 42874.7 | F44: =D44-E44 -> 15006.145 | G44: =F44*(1-$G$17) -> 12605.162 | H44: =$D$17-G44 -> 162007.68 | I44: =H44/$F$17 -> 13.270003 | J44: =IFERROR(I44/$E$17-1,"") -> -0.064618259
A45: META | B45: =$C$18*$J$18*($I$18/4) -> 31076.375 | C45: =$C$18*(1-$J$18) -> 5919.3095 | D45: =B45+C45 -> 36995.684 | E45: =$C$18 -> 29596.548 | F45: =D45-E45 -> 7399.1369 | G45: =F45*(1-$G$18) -> 6437.2491 | H45: =$D$18-G45 -> 77323.718 | I45: =H45/$F$18 -> 30.181791 | J45: =IFERROR(I45/$E$18-1,"") -> -0.062681995
A46: ORCL | B46: =$C$19*$J$19*($I$19/4) -> 10513.665 | C46: =$C$19*(1-$J$19) -> 731.38536 | D46: =B46+C46 -> 11245.05 | E46: =$C$19 -> 9142.317 | F46: =D46-E46 -> 2102.7329 | G46: =F46*(1-$G$19) -> 1682.1863 | H46: =$D$19-G46 -> 15518.872 | I46: =H46/$F$19 -> 5.3142454 | J46: =IFERROR(I46/$E$19-1,"") -> -0.091331461
A48: IT Equipment Life = 3 Years (Buildings/Other Unchanged)
A49: Company | B49: IT New D&A ($mm) | C49: Building D&A ($mm) | D49: New Total D&A ($mm) | E49: Current D&A ($mm) | F49: Delta D&A ($mm) | G49: Delta After-Tax ($mm) | H49: Adj NI ($mm) | I49: Adj EPS ($) | J49: EPS Change %
A50: MSFT | B50: =$C$15*$J$15*($I$15/3) -> 57967.05 | C50: =$C$15*(1-$J$15) -> 13021.584 | D50: =B50+C50 -> 70988.634 | E50: =$C$15 -> 42005.109 | F50: =D50-E50 -> 28983.525 | G50: =F50*(1-$G$15) -> 23766.491 | H50: =$D$15-G50 -> 105007.04 | I50: =H50/$F$15 -> 14.095091 | J50: =IFERROR(I50/$E$15-1,"") -> -0.18434336
A51: AMZN | B51: =$C$16*$J$16*($I$16/3) -> 94377.918 | C51: =$C$16*(1-$J$16) -> 32912.716 | D51: =B51+C51 -> 127290.63 | E51: =$C$16 -> 84391.581 | F51: =D51-E51 -> 42899.053 | G51: =F51*(1-$G$16) -> 34319.243 | H51: =$D$16-G51 -> 61062.127 | I51: =H51/$F$16 -> 5.602385 | J51: =IFERROR(I51/$E$16-1,"") -> -0.3628724
A52: GOOGL | B52: =$C$17*$J$17*($I$17/3) -> 60024.58 | C52: =$C$17*(1-$J$17) -> 12862.41 | D52: =B52+C52 -> 72886.99 | E52: =$C$17 -> 42874.7 | F52: =D52-E52 -> 30012.29 | G52: =F52*(1-$G$17) -> 25210.324 | H52: =$D$17-G52 -> 149402.52 | I52: =H52/$F$17 -> 12.237518 | J52: =IFERROR(I52/$E$17-1,"") -> -0.13739653
A53: META | B53: =$C$18*$J$18*($I$18/3) -> 41435.167 | C53: =$C$18*(1-$J$18) -> 5919.3095 | D53: =B53+C53 -> 47354.476 | E53: =$C$18 -> 29596.548 | F53: =D53-E53 -> 17757.929 | G53: =F53*(1-$G$18) -> 15449.398 | H53: =$D$18-G53 -> 68311.569 | I53: =H53/$F$18 -> 26.664076 | J53: =IFERROR(I53/$E$18-1,"") -> -0.17192725
A54: ORCL | B54: =$C$19*$J$19*($I$19/3) -> 14018.219 | C54: =$C$19*(1-$J$19) -> 731.38536 | D54: =B54+C54 -> 14749.605 | E54: =$C$19 -> 9142.317 | F54: =D54-E54 -> 5607.2878 | G54: =F54*(1-$G$19) -> 4485.8302 | H54: =$D$19-G54 -> 12715.229 | I54: =H54/$F$19 -> 4.3541723 | J54: =IFERROR(I54/$E$19-1,"") -> -0.25549178
A56: IT Equipment Life = 2 Years (Buildings/Other Unchanged)
A57: Company | B57: IT New D&A ($mm) | C57: Building D&A ($mm) | D57: New Total D&A ($mm) | E57: Current D&A ($mm) | F57: Delta D&A ($mm) | G57: Delta After-Tax ($mm) | H57: Adj NI ($mm) | I57: Adj EPS ($) | J57: EPS Change %
A58: MSFT | B58: =$C$15*$J$15*($I$15/2) -> 86950.576 | C58: =$C$15*(1-$J$15) -> 13021.584 | D58: =B58+C58 -> 99972.159 | E58: =$C$15 -> 42005.109 | F58: =D58-E58 -> 57967.05 | G58: =F58*(1-$G$15) -> 47532.981 | H58: =$D$15-G58 -> 81240.548 | I58: =H58/$F$15 -> 10.904915 | J58: =IFERROR(I58/$E$15-1,"") -> -0.36895285
A59: AMZN | B59: =$C$16*$J$16*($I$16/2) -> 141566.88 | C59: =$C$16*(1-$J$16) -> 32912.716 | D59: =B59+C59 -> 174479.59 | E59: =$C$16 -> 84391.581 | F59: =D59-E59 -> 90088.012 | G59: =F59*(1-$G$16) -> 72070.41 | H59: =$D$16-G59 -> 23310.96 | I59: =H59/$F$16 -> 2.1387557 | J59: =IFERROR(I59/$E$16-1,"") -> -0.7567714
A60: GOOGL | B60: =$C$17*$J$17*($I$17/2) -> 90036.87 | C60: =$C$17*(1-$J$17) -> 12862.41 | D60: =B60+C60 -> 102899.28 | E60: =$C$17 -> 42874.7 | F60: =D60-E60 -> 60024.58 | G60: =F60*(1-$G$17) -> 50420.647 | H60: =$D$17-G60 -> 124192.2 | I60: =H60/$F$17 -> 10.172547 | J60: =IFERROR(I60/$E$17-1,"") -> -0.28295306
A61: META | B61: =$C$18*$J$18*($I$18/2) -> 62152.75 | C61: =$C$18*(1-$J$18) -> 5919.3095 | D61: =B61+C61 -> 68072.059 | E61: =$C$18 -> 29596.548 | F61: =D61-E61 -> 38475.512 | G61: =F61*(1-$G$18) -> 33473.695 | H61: =$D$18-G61 -> 50287.272 | I61: =H61/$F$18 -> 19.628646 | J61: =IFERROR(I61/$E$18-1,"") -> -0.39041776
A62: ORCL | B62: =$C$19*$J$19*($I$19/2) -> 21027.329 | C62: =$C$19*(1-$J$19) -> 731.38536 | D62: =B62+C62 -> 21758.715 | E62: =$C$19 -> 9142.317 | F62: =D62-E62 -> 12616.398 | G62: =F62*(1-$G$19) -> 10093.118 | H62: =$D$19-G62 -> 7107.9408 | I62: =H62/$F$19 -> 2.4340261 | J62: =IFERROR(I62/$E$19-1,"") -> -0.58381241

Sheet IT_DA_Share_Derivation
A1: IT D&A Share Derivation
A2: Step-by-step calculation of 'IT Share of D&A' used in Sheet 5 sensitivity analysis
A4: METHODOLOGY:
A5: Step 1: Get Gross PP&E by category from 10-K Note (Property and Equipment)
A6: Step 2: Apply mid-point useful life to each category to get 'implied annual D&A'
A7: Step 3: Sum to get total implied D&A
A8: Step 4: Compare to reported total D&A; compute scale factor (typically 0.7-0.9, accounts for fully-depreciated assets)
A9: Step 5: Apply scale factor uniformly to all categories to match reported D&A
A10: Step 6: IT Share of D&A = (Scaled IT D&A) / (Reported Total D&A)
A13: AMZN — FY2025 (Dec 2025)
A14: Source: 10-K Note 3, Property and Equipment
A16: Category | B16: Gross PP&E ($M) | C16: Useful Life (yr) | D16: Implied D&A ($M) | E16: Step 2 Notes
A17: Land and Buildings (ex-land 15%) | B17: 131852.85 | C17: 35 | D17: =B17/C17 -> 3767.2243 | E17: Buildings 40yr per 10-K; assume 15% is land (non-depreciable)
A18: Servers and Networking [IT] | B18: 172492 | C18: 5.5 | D18: =B18/C18 -> 31362.182 | E18: 5-6 yr per 10-K; mid-point 5.5yr
A19: Heavy Equipment (logistics) | B19: 65545 | C19: 11.5 | D19: =B19/C19 -> 5699.5652 | E19: 10-13 yr per 10-K; mid-point 11.5yr
A20: Other Equipment | B20: 63376 | C20: 6.5 | D20: =B20/C20 -> 9750.1538 | E20: 3-10 yr range; mid-point 6.5yr
A21: Other Assets | B21: 5819 | C21: 7 | D21: =B21/C21 -> 831.28571 | E21: Misc internal-use, ~7yr
A22: Total Implied D&A | D22: =SUM(D17:D21) -> 51410.411
A23: Reported D&A (Bloomberg) | D23: 41900
A24: Scale Factor = Reported / Implied | D24: =D23/D22 -> 0.81501002
A25: Scaled IT D&A = Implied IT × Scale | D25: =D18*D24 -> 25560.492
A26: → IT Share of D&A = Scaled IT / Reported | D26: =D25/D23 -> 0.61003562
A31: GOOGL — FY2024 (Dec 2024)
A32: Source: 10-K — Information Technology Assets disclosure (not as granular as AMZN)
A34: Category | B34: Gross PP&E ($M) | C34: Useful Life (yr) | D34: Implied D&A ($M) | E34: Step 2 Notes
A35: Information Technology Assets | B35: 203700 | E35: Disclosed as single line; includes servers + DC buildings + cabling
A36: ↳ Estimated IT servers/networking [IT] | B36: 122220 | C36: 6 | D36: =B36/C36 -> 20370 | E36: 60% of IT assets are servers (est from earnings commentary); 6yr life
A37: ↳ Estimated DC buildings + other | B37: 81480 | C37: 25 | D37: =B37/C37 -> 3259.2 | E37: 40% is DC buildings + cabling; 25yr life (this is an assumptions)
A38: Land and Buildings (office) | B38: 33000 | C38: 28 | D38: =B38/C38 -> 1178.5714 | E38: 28yr blended for office buildings
A39: Other | B39: 29800 | C39: 7 | D39: =B39/C39 -> 4257.1429 | E39: Office equipment etc
A40: Total Implied D&A | D40: =SUM(D35:D39) -> 29064.914
A41: Reported D&A (Bloomberg) | D41: 17000
A42: Scale Factor = Reported / Implied | D42: =D41/D40 -> 0.58489765
A43: Scaled IT D&A = Implied IT × Scale | D43: =D36*D42 -> 11914.365
A44: → IT Share of D&A = Scaled IT / Reported | D44: =D43/D41 -> 0.70084501
A45: Note: IT share = 55% reflects GOOGL's lower IT concentration (lots of non-IT PP&E)
A48: META — FY2024 (Dec 2024) updated to Q1 2026
A49: Source: 10-K Note 6, Property and Equipment
A51: Category | B51: Gross PP&E ($M) | C51: Useful Life (yr) | D51: Implied D&A ($M) | E51: Step 2 Notes
A52: Servers and Networking [IT] | B52: 106000 | C52: 5.25 | D52: =B52/C52 -> 20190.476 | E52: Per Q1 2026 10-Q; 5-5.5yr (extended from 5yr)
A53: Buildings | B53: 50000 | C53: 30 | D53: =B53/C53 -> 1666.6667 | E53: 30yr per policy
A54: Network equipment | B54: 15000 | C54: 15 | D54: =B54/C54 -> 1000 | E54: Long-haul fiber etc; ~15yr
A55: Office equipment | B55: 5000 | C55: 5 | D55: =B55/C55 -> 1000 | E55: 5yr
A56: Land | B56: 2000 | E56: Non-depreciable
A57: Leasehold improvements | B57: 17000 | C57: 12 | D57: =B57/C57 -> 1416.6667 | E57: 12yr
A58: Total Implied D&A | D58: =SUM(D52:D57) -> 25273.81
A59: Reported D&A (Bloomberg) | D59: 18000
A60: Scale Factor = Reported / Implied | D60: =D59/D58 -> 0.71219972
A61: Scaled IT D&A = Implied IT × Scale | D61: =D52*D60 -> 14379.651
A62: → IT Share of D&A = Scaled IT / Reported | D62: =D61/D59 -> 0.79886952
A63: Note: META disclosed servers depreciation = $13.36B / total $18B = 74% directly in 10-K
A66: ORCL — FY2024 (May 2024)
A67: Source: 10-K Note 5, Property and Equipment
A69: Category | B69: Gross PP&E ($M) | C69: Useful Life (yr) | D69: Implied D&A ($M) | E69: Step 2 Notes
A70: Computer/Network Equipment + Software [IT] | B70: 30300 | C70: 5 | D70: =B70/C70 -> 6060 | E70: 5yr per ORCL policy
A71: Buildings & Improvements | B71: 9600 | C71: 25 | D71: =B71/C71 -> 384 | E71: 25yr per policy (mix of new + old)
A72: Furniture and Equipment | B72: 800 | C72: 5 | D72: =B72/C72 -> 160 | E72: 3-7yr range; use 5yr
A73: Land | B73: 1100 | E73: Non-depreciable
A74: Total Implied D&A | D74: =SUM(D70:D73) -> 6604
A75: Reported D&A (Bloomberg) | D75: 9100
A76: Scale Factor = Reported / Implied | D76: =D75/D74 -> 1.3779528
A77: Scaled IT D&A = Implied IT × Scale | D77: =D70*D76 -> 8350.3937
A78: → IT Share of D&A = Scaled IT / Reported | D78: =D77/D75 -> 0.91762568
A79: Note: IT concentration HIGHEST among 5 — ORCL doesn't own DC, uses partners; PP&E is almost all IT
A81: A. MSFT Actual PP&E/Capex Breakdown
A82: Metric (MSFT FY) | B82: FY2020A | C82: FY2021A | D82: FY2022A | E82: FY2023A | F82: FY2024A | G82: FY2025A | H82: FY2026E
A83: IT Equipment Capex ($mm) | B83: 7438 | C83: 9989 | D83: 9381 | E83: 14330 | F83: 18819 | G83: 41432 | H83: 85947
A84: Buildings Capex ($mm) | B84: 4377 | C84: 6197 | D84: 7805 | E84: 10301 | F84: 13768 | G84: 36747 | H84: 50201
A85: Finance Leases Capex ($mm) | B85: 3330 | C85: 3736 | D85: 3281 | E85: 3150 | F85: 11710 | G85: 21628 | H85: 32878
A86: Capex ($mm) | B86: 396 | C86: 2380 | D86: 2525 | E86: 2053 | F86: 3823 | G86: 10020 | H86: 9745
A87: Total Capex ($mm) | B87: 19000 | C87: 24200 | D87: 29200 | E87: 31900 | F87: 55700 | G87: 88200 | H87: 145871
A88: IT Equipment % of Capex | B88: 0.39 | C88: 0.41 | D88: 0.32 | E88: 0.45 | F88: 0.34 | G88: 0.47 | H88: 0.59
A89: IT Equipment D&A ($mm) | E89: 2231 | F89: 10063 | G89: 14563 | H89: 23911
A90: Buildings D&A ($mm) | E90: 680 | F90: 3304 | G90: 5132 | H90: 8149
A91: Total D&A ($mm) | B91: 10700 | C91: 9300 | D91: 12600 | E91: 11000 | F91: 15200 | G91: 22000 | H91: 34839
A92: IT D&A % of TotalD&A | E92: 0.2 | F92: 0.66 | G92: 0.66 | H92: 0.69
A93: IT EquipmentUseful Life | B93: 6 | C93: 6 | D93: 6 | E93: 6 | F93: 6 | G93: 6 | H93: 6
A94: BuildingsUseful Life | B94: 15 | C94: 15 | D94: 15 | E94: 15 | F94: 15 | G94: 15 | H94: 15
A96: Key: IT equipment share jumped from ~35% pre-AI to 59% in AI era. IT contributes 66-73% of total D&A (because IT 6yr vs buildings 15yr).

Sheet 6. SP500 AI EPS Split
A1: S&P 500: AI vs Non-AI EPSBreakdown + Dual P/E Valuation
A3: S&P 500 EPS — Bloomberg Consensus ($)
A4: EPS: FactSet actual (2018-2024), sell-side/consensus estimates (2025+). Capex/Buybacks: sell-side data (May 7 2026 report). Yellow = editable.
A5: Metric | B5: 2018A | C5: 2019A | D5: 2020A | E5: 2021A | F5: 2022A | G5: 2023A | H5: 2024A | I5: 2025A | J5: 2026E | K5: 2027E | L5: 2028E (ext) | M5: 2029E (ext) | N5: 2030E (ext)
A6: S&P 500 Operating EPS ($) | B6: 160 | C6: 165 | D6: 142 | E6: 200 | F6: 224 | G6: 222 | H6: 239 | I6: 269 | J6: 337 | K6: 386 | L6: 420 | M6: 450 | N6: 478
A7: S&P 500Capex ($B) | B7: 644 | C7: 697 | D7: 591 | E7: 739 | F7: 892 | G7: 958 | H7: 1077 | I7: 1296 | J7: 1724 | K7: 2103 | L7: 2400 | M7: 2600 | N7: 2750
A8: AICapex ($B) | B8: 50 | C8: 55 | D8: 60 | E8: 86 | F8: 158 | G8: 154 | H8: 237 | I8: 412 | J8: 755 | K8: 892 | L8: 950 | M8: 980 | N8: 1000
A9: S&P 500 Buybacks ($B) | B9: 770 | C9: 729 | D9: 520 | E9: 919 | F9: 950 | G9: 823 | H9: 982 | I9: 1066 | J9: 1098 | K9: 1153 | L9: 1200 | M9: 1250 | N9: 1300
A11: B. AI Semi EPS - Bottom-Up (Bloomberg MODL Data)
A12: Adj NI of NVDA/AVGO/MU/AMD/QCOM/AMAT/ANET/MRVL/INTC/SMCI from Bloomberg. Divided by S&P 500 divisor (~8.8B). FY labels as-is.
A13: Metric | B13: 2018A | C13: 2019A | D13: 2020A | E13: 2021A | F13: 2022A | G13: 2023A | H13: 2024A | I13: 2025A | J13: 2026E | K13: 2027E | L13: 2028E | M13: 2029E | N13: 2030E
A14: NVDA Adj NI ($M) | B14: 3085 | C14: 4143 | D14: 4247 | E14: 7381 | F14: 11259 | G14: 8366 | H14: 32312 | I14: 74265 | J14: 116997 | K14: 212170 | L14: 291644 | M14: 328664 | N14: 366752
A15: AVGO Adj NI ($M) | B15: 9391 | C15: 9452 | D15: 9993 | E15: 12578 | F15: 16526 | G15: 18378 | H15: 23733 | I15: 33728 | J15: 55026 | K15: 87678 | L15: 110964 | M15: 140835 | N15: 148395
A16: MU Adj NI ($M) | B16: 14700 | C16: 7314 | D16: 3235 | E16: 6976 | F16: 9475 | G16: -4862 | H16: 1472 | I16: 9470 | J16: 67762 | K16: 118946 | L16: 105153 | M16: 142465 | N16: 116649
A17: AMD Adj NI ($M) | B17: 514 | C17: 756 | D17: 1575 | E17: 3435 | F17: 5504 | G17: 4302 | H17: 5420 | I17: 6831 | J17: 12025 | K17: 21710 | L17: 29961 | M17: 40615 | N17: 52584
A18: QCOM Adj NI ($M) | B18: 5443 | C18: 4323 | D18: 4816 | E18: 9811 | F18: 14254 | G18: 9486 | H18: 11545 | I18: 13298 | J18: 11507.273 | K18: 11056.794 | L18: 12247.941 | M18: 13921.667 | N18: 16849
A19: AMAT Adj NI ($M) | B19: 4569 | C19: 2875 | D19: 3845 | E19: 6287 | F19: 6756 | G19: 6802 | H19: 7210 | I19: 7607 | J19: 9591 | K19: 12654 | L19: 14184 | M19: 13978 | N19: 14450
A20: ANET Adj NI ($M) | B20: 643 | C20: 787 | D20: 827 | E20: 915 | F20: 1448 | G20: 2199 | H20: 2910 | I20: 3806 | J20: 4636 | K20: 5714 | L20: 6899 | M20: 8592 | N20: 9652
A21: MRVL Adj NI ($M) | B21: 616 | C21: 716 | D21: 1827 | E21: 627 | F21: 1279 | G21: 1822 | H21: 1310 | I21: 1377 | J21: 2466 | K21: 3358 | L21: 4806 | M21: 6530 | N21: 7352
A22: INTC Adj NI ($M) | B22: 21525 | C22: 21784 | D22: 22431 | E22: 22356 | F22: 7594 | G22: 4423 | H22: -566 | I22: 1929 | J22: 5578 | K22: 7876 | L22: 11373 | M22: 18425 | N22: 24941
A23: SMCI Adj NI ($M) | B23: 46 | C23: 72 | D23: 150 | E23: 136 | F23: 311 | G23: 673 | H23: 1345 | I23: 1316 | J23: 1825 | K23: 2299 | L23: 1191 | M23: 2839 | N23: 3602
A24: Total AI Semi Adj NI ($M) | B24: =SUM(B14:B23) -> 60532 | C24: =SUM(C14:C23) -> 52222 | D24: =SUM(D14:D23) -> 52946 | E24: =SUM(E14:E23) -> 70502 | F24: =SUM(F14:F23) -> 74406 | G24: =SUM(G14:G23) -> 51589 | H24: =SUM(H14:H23) -> 86691 | I24: =SUM(I14:I23) -> 153627 | ... N24: =SUM(N14:N23) -> 761226
A25: AI EPS ($) = Total NI / 8.8B | B25: =B24/8800 -> 6.8786364 | C25: =C24/8800 -> 5.9343182 | D25: =D24/8800 -> 6.0165909 | E25: =E24/8800 -> 8.0115909 | F25: =F24/8800 -> 8.4552273 | G25: =G24/8800 -> 5.8623864 | H25: =H24/8800 -> 9.85125 | I25: =I24/8800 -> 17.457614 | ... N25: =N24/8800 -> 86.502955
A26: Non-AI EPS ($) = Total S&P EPS - AI EPS | B26: =B6-B25 -> 153.12136 | C26: =C6-C25 -> 159.06568 | D26: =D6-D25 -> 135.98341 | E26: =E6-E25 -> 191.98841 | F26: =F6-F25 -> 215.54477 | G26: =G6-G25 -> 216.13761 | H26: =H6-H25 -> 229.14875 | I26: =I6-I25 -> 251.54239 | ... N26: =N6-N25 -> 391.49705
A27: AI % of Total EPS | B27: =IFERROR(B25/B6,"") -> 0.042991477 | C27: =IFERROR(C25/C6,"") -> 0.035965565 | D27: =IFERROR(D25/D6,"") -> 0.042370359 | E27: =IFERROR(E25/E6,"") -> 0.040057955 | F27: =IFERROR(F25/F6,"") -> 0.03774655 | G27: =IFERROR(G25/G6,"") -> 0.026407146 | H27: =IFERROR(H25/H6,"") -> 0.041218619 | I27: =IFERROR(I25/I6,"") -> 0.064898192 | ... N27: =IFERROR(N25/N6,"") -> 0.18096852
A28: AI EPS YoY % | C28: =IFERROR(C25/B25-1,"") -> -0.13728276 | D28: =IFERROR(D25/C25-1,"") -> 0.013863889 | E28: =IFERROR(E25/D25-1,"") -> 0.33158312 | F28: =IFERROR(F25/E25-1,"") -> 0.055374316 | G28: =IFERROR(G25/F25-1,"") -> -0.30665538 | H28: =IFERROR(H25/G25-1,"") -> 0.68041637 | I28: =IFERROR(I25/H25-1,"") -> 0.77212167 | J28: =IFERROR(J25/I25-1,"") -> 0.8708513 | ... N28: =IFERROR(N25/M25-1,"") -> 0.061882438
A29: C. Dual P/E Valuation - Separate Multiples for AI vs Non-AI EPS
A30: Non-AI P/E (editable) - hist avg ~18x | B30: 21
A31: AI P/E (editable) - NVDA ~30-40x fwd | B31: 40
A33: Valuation Component | B33: 2024A | C33: 2025A | D33: 2026E | E33: 2027E | F33: 2028E | G33: 2029E | H33: 2030E
A34: Non-AI Component = Non-AI EPS x P/E | B34: =H26*$B$30 -> 4812.1237 | C34: =I26*$B$30 -> 5282.3901 | D34: =J26*$B$30 -> 6391.1274 | E34: =K26*$B$30 -> 6952.2844 | F34: =L26*$B$30 -> 7415.8089 | G34: =M26*$B$30 -> 7739.3002 | H34: =N26*$B$30 -> 8221.438
A35: AI Component = AI EPS x P/E | B35: =H25*$B$31 -> 394.05 | C35: =I25*$B$31 -> 698.30455 | D35: =J25*$B$31 -> 1306.424 | E35: =K25*$B$31 -> 2197.5536 | F35: =L25*$B$31 -> 2674.6497 | G35: =M25*$B$31 -> 3258.4758 | H35: =N25*$B$31 -> 3460.1182
A36: Implied S&P 500 Level | B36: =B34+B35 -> 5206.1737 | C36: =C34+C35 -> 5980.6947 | D36: =D34+D35 -> 7697.5514 | E36: =E34+E35 -> 9149.838 | F36: =F34+F35 -> 10090.459 | G36: =G34+G35 -> 10997.776 | H36: =H34+H35 -> 11681.556
A37: Blended P/E (implied) | B37: =IFERROR(B36/H6,"") -> 21.783154 | C37: =IFERROR(C36/I6,"") -> 22.233066 | D37: =IFERROR(D36/J6,"") -> 22.841399 | E37: =IFERROR(E36/K6,"") -> 23.704243 | F37: =IFERROR(F36/L6,"") -> 24.024901 | G37: =IFERROR(G36/M6,"") -> 24.439502 | H37: =IFERROR(H36/N6,"") -> 24.438402
A39: D. Scenario Grid: 2026E Implied S&P 500 at Different P/E Combinations
A40: Each cell = J27*Non-AI-PE + J26*AI-PE. Rows: AI P/E. Columns: Non-AI P/E.
A41: AI P/E vs Non-AI P/E | B41: 22x | C41: 20x | D41: 18x | E41: 16x | F41: 14x
A42: 40x | B42: =J26*22+J25*40 -> 8001.8908 | C42: =J26*20+J25*40 -> 7393.212 | D42: =J26*18+J25*40 -> 6784.5332 | E42: =J26*16+J25*40 -> 6175.8544 | F42: =J26*14+J25*40 -> 5567.1756
A43: 35x | B43: =J26*22+J25*35 -> 7838.5878 | C43: =J26*20+J25*35 -> 7229.909 | D43: =J26*18+J25*35 -> 6621.2302 | E43: =J26*16+J25*35 -> 6012.5514 | F43: =J26*14+J25*35 -> 5403.8726
A44: 30x | B44: =J26*22+J25*30 -> 7675.2848 | C44: =J26*20+J25*30 -> 7066.606 | D44: =J26*18+J25*30 -> 6457.9272 | E44: =J26*16+J25*30 -> 5849.2484 | F44: =J26*14+J25*30 -> 5240.5696
A45: 25x | B45: =J26*22+J25*25 -> 7511.9818 | C45: =J26*20+J25*25 -> 6903.303 | D45: =J26*18+J25*25 -> 6294.6242 | E45: =J26*16+J25*25 -> 5685.9454 | F45: =J26*14+J25*25 -> 5077.2666
A46: 20x | B46: =J26*22+J25*20 -> 7348.6788 | C46: =J26*20+J25*20 -> 6740 | D46: =J26*18+J25*20 -> 6131.3212 | E46: =J26*16+J25*20 -> 5522.6424 | F46: =J26*14+J25*20 -> 4913.9636
A47: 15x | B47: =J26*22+J25*15 -> 7185.3758 | C47: =J26*20+J25*15 -> 6576.697 | D47: =J26*18+J25*15 -> 5968.0182 | E47: =J26*16+J25*15 -> 5359.3394 | F47: =J26*14+J25*15 -> 4750.6606
A48: 10x | B48: =J26*22+J25*10 -> 7022.0728 | C48: =J26*20+J25*10 -> 6413.394 | D48: =J26*18+J25*10 -> 5804.7152 | E48: =J26*16+J25*10 -> 5196.0364 | F48: =J26*14+J25*10 -> 4587.3576
A50: E. Stress Test: 3 Scenarios with Different AI EPS Trajectories
A51: Base Case | AI PE = 40x | Non-AI PE = 21x
A52: Current trajectory. AI capex sustains. NVDA margins hold.
A53: Metric | B53: 2024A | C53: 2025A | D53: 2026E | E53: 2027E | F53: 2028E | G53: 2029E | H53: 2030E | I53: AI PE: | J53: 40 | K53: Non-AI PE: | L53: 21
A54: AI EPS ($) | B54: =H25 -> 9.85125 | C54: =I25 -> 17.457614 | D54: =J25 -> 32.660599 | E54: =K25 -> 54.93884 | F54: =L25 -> 66.866243 | G54: =M25 -> 81.461894 | H54: =N25 -> 86.502955
A55: Non-AI EPS ($) | B55: =H26 -> 229.14875 | C55: =I26 -> 251.54239 | D55: =J26 -> 304.3394 | E55: =K26 -> 331.06116 | F55: =L26 -> 353.13376 | G55: =M26 -> 368.53811 | H55: =N26 -> 391.49705
A56: Implied S&P 500 | B56: =B54*$J$53+B55*$L$53 -> 5206.1737 | C56: =C54*$J$53+C55*$L$53 -> 5980.6947 | D56: =D54*$J$53+D55*$L$53 -> 7697.5514 | E56: =E54*$J$53+E55*$L$53 -> 9149.838 | F56: =F54*$J$53+F55*$L$53 -> 10090.459 | G56: =G54*$J$53+G55*$L$53 -> 10997.776 | H56: =H54*$J$53+H55*$L$53 -> 11681.556
A58: Slowdown | AI PE = 25x | Non-AI PE = 18x
A59: 2027+ capex growth decelerates. Customer crack. AI margins compress.
A60: Metric | B60: 2024A | C60: 2025A | D60: 2026E | E60: 2027E | F60: 2028E | G60: 2029E | H60: 2030E | I60: AI PE: | J60: 25 | K60: Non-AI PE: | L60: 18
A61: AI EPS ($) | B61: =H25 -> 9.85125 | C61: =I25 -> 17.457614 | D61: =J25*0.93 -> 30.374357 | E61: =K25*0.93^2 -> 47.516603 | F61: =L25*0.93^3 -> 53.784331 | G61: =M25*0.93^4 -> 60.937733 | H61: =N25*0.93^5 -> 60.179099
A62: Non-AI EPS ($) | B62: =H26 -> 229.14875 | C62: =I26 -> 251.54239 | D62: =J26 -> 304.3394 | E62: =K26 -> 331.06116 | F62: =L26 -> 353.13376 | G62: =M26 -> 368.53811 | H62: =N26 -> 391.49705
A63: Implied S&P 500 | B63: =B61*$J$60+B62*$L$60 -> 4370.9587 | C63: =C61*$J$60+C62*$L$60 -> 4964.2033 | D63: =D61*$J$60+D62*$L$60 -> 6237.4681 | E63: =E61*$J$60+E62*$L$60 -> 7147.0159 | F63: =F61*$J$60+F62*$L$60 -> 7701.0159 | G63: =G61*$J$60+G62*$L$60 -> 8157.1292 | H63: =H61*$J$60+H62*$L$60 -> 8551.4243
A64: vs Base Delta | B64: =IFERROR(B63/B56-1,"") -> -0.1604278 | C64: =IFERROR(C63/C56-1,"") -> -0.16996209 | D64: =IFERROR(D63/D56-1,"") -> -0.18968152 | E64: =IFERROR(E63/E56-1,"") -> -0.21889153 | F64: =IFERROR(F63/F56-1,"") -> -0.23680219 | G64: =IFERROR(G63/G56-1,"") -> -0.25829284 | H64: =IFERROR(H63/H56-1,"") -> -0.26795504
A66: AI Bust | AI PE = 15x | Non-AI PE = 17x
A67: Capex cut 30% from 2027. AI margins collapse. Re-rating.
A68: Metric | B68: 2024A | C68: 2025A | D68: 2026E | E68: 2027E | F68: 2028E | G68: 2029E | H68: 2030E | I68: AI PE: | J68: 15 | K68: Non-AI PE: | L68: 17
A69: AI EPS ($) | B69: =H25 -> 9.85125 | C69: =I25 -> 17.457614 | D69: =J25*0.7 -> 22.862419 | E69: =K25*0.7^2 -> 26.920032 | F69: =L25*0.7^3 -> 22.935121 | G69: =M25*0.7^4 -> 19.559001 | H69: =N25*0.7^5 -> 14.538552
A70: Non-AI EPS ($) | B70: =H26 -> 229.14875 | C70: =I26 -> 251.54239 | D70: =J26 -> 304.3394 | E70: =K26 -> 331.06116 | F70: =L26 -> 353.13376 | G70: =M26 -> 368.53811 | H70: =N26 -> 391.49705
A71: Implied S&P 500 | B71: =B69*$J$68+B70*$L$68 -> 4043.2975 | C71: =C69*$J$68+C70*$L$68 -> 4538.0848 | D71: =D69*$J$68+D70*$L$68 -> 5516.7061 | E71: =E69*$J$68+E70*$L$68 -> 6031.8402 | F71: =F69*$J$68+F70*$L$68 -> 6347.3007 | G71: =G69*$J$68+G70*$L$68 -> 6558.5328 | H71: =H69*$J$68+H70*$L$68 -> 6873.528
A72: vs Base Delta | B72: =IFERROR(B71/B56-1,"") -> -0.22336486 | C72: =IFERROR(C71/C56-1,"") -> -0.24121109 | D72: =IFERROR(D71/D56-1,"") -> -0.28331675 | E72: =IFERROR(E71/E56-1,"") -> -0.34077082 | F72: =IFERROR(F71/F56-1,"") -> -0.37096014 | G72: =IFERROR(G71/G56-1,"") -> -0.40364917 | H72: =IFERROR(H71/H56-1,"") -> -0.4115914

Sheet 7. SPX Data
A1: S&P 500 Fundamentals — Bloomberg Terminal (FA1.xlsx)
A3: Metric | B3: 2009A | C3: 2010A | D3: 2011A | E3: 2012A | F3: 2013A | G3: 2014A | H3: 2015A | I3: 2016A | J3: 2017A | K3: 2018A | L3: 2019A | M3: 2020A | N3: 2021A | O3: 2022A | P3: 2023A | Q3: 2024A | R3: 2025A | S3: 2026E | T3: 2027E
A4: Sales/Share ($) | B4: 859 | C4: 924 | D4: 1018 | E4: 1054 | F4: 1120 | G4: 1144 | H4: 1129 | I4: 1129 | J4: 1190 | K4: 1307 | L4: 1356 | M4: 1326 | N4: 1510 | O4: 1704 | P4: 1785 | Q4: 1864 | R4: 1947 | S4: 2180 | T4: 2339
A5: Gross Margin (%) | B5: 33.1 | C5: 33.6 | D5: 32.6 | E5: 33.5 | F5: 33.6 | G5: 34.4 | H5: 34.9 | I5: 34.4 | J5: 35.2 | K5: 34.9 | L5: 35 | M5: 34 | N5: 35.5 | O5: 34.7 | P5: 33.6 | Q5: 33.8 | R5: 34.6 | S5: 38.6 | T5: 40.1
A6: EBIT/Share ($) | B6: 75.7 | C6: 116 | D6: 137 | E6: 136 | F6: 142 | G6: 160 | H6: 139 | I6: 139 | J6: 160 | K6: 179 | L6: 182 | M6: 146 | N6: 228 | O6: 251 | P6: 248 | Q6: 270 | R6: 303 | S6: 426 | T6: 495
A7: Op Margin (%) | B7: 8.7 | C7: 12.5 | D7: 13.3 | E7: 12.8 | F7: 12.6 | G7: 13.8 | H7: 12.2 | I7: 12.3 | J7: 13.3 | K7: 13.4 | L7: 13 | M7: 10.7 | N7: 14.9 | O7: 14.6 | P7: 13.5 | Q7: 13.9 | R7: 15 | S7: 19.5 | T7: 21.1
A8: EBITDA/Share ($) | B8: 136 | C8: 166 | D8: 187 | E8: 188 | F8: 198 | G8: 219 | H8: 199 | I8: 200 | J8: 229 | K8: 255 | L8: 270 | M8: 238 | N8: 310 | O8: 341 | P8: 357 | Q8: 393 | R8: 425 | S8: 520 | T8: 601
A9: EPS Aggregate ($) | B9: 57.6 | C9: 83.9 | D9: 99.6 | E9: 104 | F9: 112 | G9: 123 | H9: 120 | I9: 121 | J9: 129 | K9: 160 | L9: 165 | M9: 142 | N9: 200 | O9: 224 | P9: 222 | Q9: 239 | R9: 269 | S9: 337 | T9: 386
A11: EPS YoY % | C11: =IFERROR(C9/B9-1,NA()) -> 0.45659722 | D11: =IFERROR(D9/C9-1,NA()) -> 0.18712753 | E11: =IFERROR(E9/D9-1,NA()) -> 0.044176707 | F11: =IFERROR(F9/E9-1,NA()) -> 0.076923077 | G11: =IFERROR(G9/F9-1,NA()) -> 0.098214286 | H11: =IFERROR(H9/G9-1,NA()) -> -0.024390244 | I11: =IFERROR(I9/H9-1,NA()) -> 0.0083333333 | J11: =IFERROR(J9/I9-1,NA()) -> 0.066115702 | ... T11: =IFERROR(T9/S9-1,NA()) -> 0.14540059
A12: Sales YoY % | C12: =IFERROR(C4/B4-1,NA()) -> 0.075669383 | D12: =IFERROR(D4/C4-1,NA()) -> 0.1017316 | E12: =IFERROR(E4/D4-1,NA()) -> 0.035363458 | F12: =IFERROR(F4/E4-1,NA()) -> 0.062618596 | G12: =IFERROR(G4/F4-1,NA()) -> 0.021428571 | H12: =IFERROR(H4/G4-1,NA()) -> -0.013111888 | I12: =IFERROR(I4/H4-1,NA()) -> 0 | J12: =IFERROR(J4/I4-1,NA()) -> 0.054030115 | ... T12: =IFERROR(T4/S4-1,NA()) -> 0.07293578
A14: Key: 2026E OpMargin jumps from 15.0% to 19.5% = 450bp expansion. Most aggressive in 15 years. If only 200bp (to 17%), EPS~$295 vs $337 = 12% miss. Consensus is a bet on AI margin expansion.
